{
  "type": "Feature",
  "properties": {
    "iso:country":"US",
    "sg:address":"1124 E Front St",
    "sg:city":"Butte",
    "sg:classifiers":[
        {
            "category":"Wholesale",
            "subcategory":"Durable Goods & Equipment",
            "type":"Manufacturing & Wholesale Goods"
        }
    ],
    "sg:phone":"+1 406 782 8502",
    "sg:postcode":"59701",
    "sg:province":"MT",
    "sg:tags":[
        "gaming",
        "supply"
    ],
    "wof:name":"Superior Gaming Svc",
    "wof:placetype":"venue"
},
  "geometry": {"coordinates":[-112.523695,46.002866],"type":"Point"}
}