{
  "type": "Feature",
  "properties": {
    "iso:country":"US",
    "sg:address":"405 Main St",
    "sg:city":"Billings",
    "sg:classifiers":[
        {
            "category":"Wholesale",
            "subcategory":"Electrical",
            "type":"Manufacturing & Wholesale Goods"
        }
    ],
    "sg:phone":"+1 406 259 7444",
    "sg:postcode":"59105",
    "sg:province":"MT",
    "sg:tags":[
        "sound",
        "equipment",
        "system"
    ],
    "wof:name":"Lifetronics",
    "wof:placetype":"venue"
},
  "geometry": {"coordinates":[-108.474783,45.806246],"type":"Point"}
}