{
  "type": "Feature",
  "properties": {
    "addr:full":"3275 N Reserve St Missoula MT 59808",
    "addr:housenumber":"3275",
    "addr:postcode":"59808",
    "addr:street":"N Reserve St",
    "iso:country":"US",
    "sg:address":"3275 N Reserve St",
    "sg:city":"Missoula",
    "sg:classifiers":[
        {
            "category":"Ice Cream",
            "type":"Food & Drink"
        }
    ],
    "sg:menulink":"http://www.allmenus.com/mt/missoula/184069-cold-stone-creamery/menu/",
    "sg:phone":"+1 406 549 5595",
    "sg:postcode":"59808",
    "sg:province":"MT",
    "sg:tags":[
        "smoothy",
        "juice",
        "american"
    ],
    "wof:name":"Cold Stone Creamery",
    "wof:placetype":"venue"
},
  "geometry": {"coordinates":[-114.039615,46.895325],"type":"Point"}
}