{
  "type": "Feature",
  "properties": {
    "iso:country":"US",
    "sg:address":"641 2nd Ave N",
    "sg:city":"Glasgow",
    "sg:classifiers":[
        {
            "category":"Organizations",
            "subcategory":"Religious Organization",
            "type":"Services"
        }
    ],
    "sg:phone":"+1 406 228 4862",
    "sg:postcode":"59230",
    "sg:province":"MT",
    "sg:tags":[
        "church"
    ],
    "wof:name":"First Lutheran Church Inc",
    "wof:placetype":"venue"
},
  "geometry": {"coordinates":[-106.635526,48.197568],"type":"Point"}
}