{
  "type": "Feature",
  "properties": {
    "addr:full":"510 S Main St Three Forks MT 59752",
    "addr:housenumber":"510",
    "addr:postcode":"59752",
    "addr:street":"S Main St",
    "iso:country":"US",
    "sg:address":"510 S Main St",
    "sg:city":"Three Forks",
    "sg:classifiers":[
        {
            "category":"Travel",
            "subcategory":"Hotels & Motels",
            "type":"Entertainment"
        }
    ],
    "sg:phone":"+1 406 285 3474",
    "sg:postcode":"59752",
    "sg:province":"MT",
    "wof:name":"Lewis & Clark Sportsman Lodge",
    "wof:placetype":"venue"
},
  "geometry": {"coordinates":[-111.548042,45.889963],"type":"Point"}
}