{
  "type": "Feature",
  "properties": {
    "addr:full":"205 S 1st Ave Laurel MT 59044",
    "addr:housenumber":"205",
    "addr:postcode":"59044",
    "addr:street":"S 1St Ave",
    "iso:country":"US",
    "sg:address":"205 S 1st Ave",
    "sg:city":"Laurel",
    "sg:classifiers":[
        {
            "category":"Banks & Credit Unions",
            "subcategory":"Bank",
            "type":"Services"
        }
    ],
    "sg:phone":"+1 406 628 1120",
    "sg:postcode":"59044",
    "sg:province":"MT",
    "wof:name":"First Citizens Bank",
    "wof:placetype":"venue"
},
  "geometry": {"coordinates":[-108.771351,45.66658],"type":"Point"}
}