{
  "type": "Feature",
  "properties": {
    "iso:country":"US",
    "sg:address":"812 Columbia Ave",
    "sg:city":"Whitefish",
    "sg:classifiers":[
        {
            "category":"Professional",
            "subcategory":"Art Services",
            "type":"Services"
        }
    ],
    "sg:phone":"+1 406 862 3427",
    "sg:postcode":"59937",
    "sg:province":"MT",
    "sg:tags":[
        "commercial",
        "design"
    ],
    "wof:name":"Sunstorm Murals & Decorative",
    "wof:placetype":"venue"
},
  "geometry": {"coordinates":[-114.332551,48.404086],"type":"Point"}
}