{
  "type": "Feature",
  "properties": {
    "iso:country":"US",
    "sg:address":"1620 6th St NE",
    "sg:city":"Great Falls",
    "sg:classifiers":[
        {
            "category":"Professional",
            "subcategory":"Business Services",
            "type":"Services"
        }
    ],
    "sg:phone":"+1 406 268 0938",
    "sg:postcode":"59404",
    "sg:province":"MT",
    "wof:name":"Water Jet Extreme Tech",
    "wof:placetype":"venue"
},
  "geometry": {"coordinates":[-111.29970899999999,47.522004],"type":"Point"}
}