{
  "type": "Feature",
  "properties": {
    "iso:country":"US",
    "sg:address":"721 Wisconsin Ave",
    "sg:city":"Whitefish",
    "sg:classifiers":[
        {
            "category":"Food & Beverages",
            "subcategory":"Groceries & Convenience Stores",
            "type":"Retail Goods"
        }
    ],
    "sg:phone":"+1 406 862 5025",
    "sg:postcode":"59937",
    "sg:province":"MT",
    "sg:tags":[
        "self",
        "station",
        "gasoline"
    ],
    "wof:name":"Deli & Wine",
    "wof:placetype":"venue"
},
  "geometry": {"coordinates":[-114.34102,48.424267],"type":"Point"}
}