{
  "type": "Feature",
  "properties": {
    "iso:country":"US",
    "sg:address":"2725 Mulberry Ln",
    "sg:city":"Missoula",
    "sg:classifiers":[
        {
            "category":"Professional",
            "subcategory":"Engineering",
            "type":"Services"
        }
    ],
    "sg:phone":"+1 406 728 5801",
    "sg:postcode":"59804",
    "sg:province":"MT",
    "sg:tags":[
        "contract"
    ],
    "wof:name":"Gideon International",
    "wof:placetype":"venue"
},
  "geometry": {"coordinates":[-114.046393,46.852935],"type":"Point"}
}