{
  "type": "Feature",
  "properties": {
    "iso:country":"US",
    "sg:address":"26 Orchard Ln",
    "sg:city":"Billings",
    "sg:classifiers":[
        {
            "category":"Retail",
            "subcategory":"Auto Repair",
            "type":"Services"
        }
    ],
    "sg:phone":"+1 406 248 8465",
    "sg:postcode":"59101",
    "sg:province":"MT",
    "sg:tags":[
        "repairing",
        "automobile"
    ],
    "wof:name":"Magic City Repair",
    "wof:placetype":"venue"
},
  "geometry": {"coordinates":[-108.525487,45.768416],"type":"Point"}
}