{
  "type": "Feature",
  "properties": {
    "iso:country":"US",
    "sg:address":"523 Main St",
    "sg:city":"Stevensville",
    "sg:classifiers":[
        {
            "category":"Manufacturing",
            "subcategory":"Printing",
            "type":"Manufacturing & Wholesale Goods"
        }
    ],
    "sg:phone":"+1 406 777 2729",
    "sg:postcode":"59870",
    "sg:province":"MT",
    "sg:tags":[
        "publisher"
    ],
    "sg:website":"www.stoneydale.com",
    "wof:name":"Stoneydale Press Publishing Co",
    "wof:placetype":"venue"
},
  "geometry": {"coordinates":[-114.09385899999999,46.50659],"type":"Point"}
}