{
  "type": "Feature",
  "properties": {
    "iso:country":"US",
    "sg:address":"141 Interstate Ln",
    "sg:city":"Kalispell",
    "sg:classifiers":[
        {
            "category":"Health Services",
            "subcategory":"Nursing And Care Facility",
            "type":"Services"
        }
    ],
    "sg:phone":"+1 406 755 3240",
    "sg:postcode":"59901",
    "sg:province":"MT",
    "sg:tags":[
        "skilled"
    ],
    "wof:name":"Edgewood Vista",
    "wof:placetype":"venue"
},
  "geometry": {"coordinates":[-114.276628,48.222429],"type":"Point"}
}