{
  "type": "Feature",
  "properties": {
    "iso:country":"US",
    "sg:address":"2611 Gabel Rd",
    "sg:city":"Billings",
    "sg:classifiers":[
        {
            "category":"Professional",
            "subcategory":"Engineering",
            "type":"Services"
        }
    ],
    "sg:phone":"+1 406 245 5499",
    "sg:postcode":"59102",
    "sg:province":"MT",
    "sg:tags":[
        "engineer"
    ],
    "sg:website":"www.kljeng.com",
    "wof:name":"Kadrmas Lee & Jackson",
    "wof:placetype":"venue"
},
  "geometry": {"coordinates":[-108.581114,45.744977],"type":"Point"}
}