{
  "type": "Feature",
  "properties": {
    "iso:country":"US",
    "sg:address":"475 West Rd",
    "sg:city":"Eureka",
    "sg:classifiers":[
        {
            "category":"Farming",
            "subcategory":"Farm",
            "type":"Manufacturing & Wholesale Goods"
        }
    ],
    "sg:phone":"+1 406 889 3229",
    "sg:postcode":"59917",
    "sg:province":"MT",
    "sg:tags":[
        "crop",
        "general"
    ],
    "wof:name":"Leland Mocko",
    "wof:placetype":"venue"
},
  "geometry": {"coordinates":[-115.013775,48.905331],"type":"Point"}
}