{
  "type": "Feature",
  "properties": {
    "iso:country":"US",
    "sg:address":"4439 Old Blue Creek Rd",
    "sg:city":"Billings",
    "sg:classifiers":[
        {
            "category":"Building & Trades",
            "subcategory":"Construction",
            "type":"Services"
        }
    ],
    "sg:phone":"+1 406 896 8803",
    "sg:postcode":"59101",
    "sg:province":"MT",
    "sg:tags":[
        "dry wall",
        "contractor"
    ],
    "wof:name":"Blue Creek Construction",
    "wof:placetype":"venue"
},
  "geometry": {"coordinates":[-108.52500000000001,45.735837],"type":"Point"}
}