{
  "type": "Feature",
  "properties": {
    "iso:country":"US",
    "sg:address":"60 Newlan Creek Rd",
    "sg:city":"White Sulphur Springs",
    "sg:classifiers":[
        {
            "category":"Shopping",
            "subcategory":"Bicycles & Sporting Goods",
            "type":"Retail Goods"
        }
    ],
    "sg:phone":"+1 406 547 3727",
    "sg:postcode":"59645",
    "sg:province":"MT",
    "wof:name":"W M Saddlery",
    "wof:placetype":"venue"
},
  "geometry": {"coordinates":[-110.902407,46.656856],"type":"Point"}
}