{
  "type": "Feature",
  "properties": {
    "iso:country":"US",
    "sg:address":"3547 Briarwood Blvd",
    "sg:city":"Billings",
    "sg:classifiers":[
        {
            "category":"Building & Trades",
            "subcategory":"Construction",
            "type":"Services"
        }
    ],
    "sg:phone":"+1 406 245 6690",
    "sg:postcode":"59101",
    "sg:province":"MT",
    "sg:tags":[
        "general",
        "contractor"
    ],
    "wof:name":"Kuntz Construction",
    "wof:placetype":"venue"
},
  "geometry": {"coordinates":[-108.51019,45.714553],"type":"Point"}
}