{
  "type": "Feature",
  "properties": {
    "addr:full":"511 Reynolds St Billings MT 59101",
    "addr:housenumber":"511",
    "addr:postcode":"59101",
    "addr:street":"Reynolds St",
    "iso:country":"US",
    "sg:address":"511 Reynolds St",
    "sg:city":"Billings",
    "sg:classifiers":[
        {
            "category":"Building & Trades",
            "subcategory":"Construction",
            "type":"Services"
        }
    ],
    "sg:phone":"+1 406 252 1396",
    "sg:postcode":"59101",
    "sg:province":"MT",
    "sg:tags":[
        "painter"
    ],
    "wof:name":"Mooney Painting Inc",
    "wof:placetype":"venue"
},
  "geometry": {"coordinates":[-108.439654,45.806459],"type":"Point"}
}