{
  "type": "Feature",
  "properties": {
    "addr:full":"520 4th St Havre MT 59501",
    "addr:housenumber":"520",
    "addr:postcode":"59501",
    "addr:street":"4Th St",
    "iso:country":"US",
    "sg:address":"520 4th St",
    "sg:city":"Havre",
    "sg:classifiers":[
        {
            "category":"Organizations",
            "subcategory":"Community Association",
            "type":"Services"
        }
    ],
    "sg:phone":"+1 406 265 4444",
    "sg:postcode":"59501",
    "sg:province":"MT",
    "wof:name":"Havre Hill Crimestoppers",
    "wof:placetype":"venue"
},
  "geometry": {"coordinates":[-109.67540200000001,48.550021],"type":"Point"}
}