{
  "type": "Feature",
  "properties": {
    "addr:full":"910 Princeton Ave Billings MT 59102",
    "addr:housenumber":"910",
    "addr:postcode":"59102",
    "addr:street":"Princeton Ave",
    "iso:country":"US",
    "sg:address":"910 Princeton Ave",
    "sg:city":"Billings",
    "sg:classifiers":[
        {
            "category":"Mining & Drilling",
            "type":"Manufacturing & Wholesale Goods"
        }
    ],
    "sg:phone":"+1 406 259 5385",
    "sg:postcode":"59102",
    "sg:province":"MT",
    "sg:tags":[
        "field"
    ],
    "wof:name":"Rae Reta Resources",
    "wof:placetype":"venue"
},
  "geometry": {"coordinates":[-108.540706,45.796869],"type":"Point"}
}