{
  "type": "Feature",
  "properties": {
    "iso:country":"US",
    "sg:address":"212 W Main St",
    "sg:city":"Belgrade",
    "sg:classifiers":[
        {
            "category":"Retail",
            "subcategory":"Laundry & Dry Cleaning",
            "type":"Services"
        }
    ],
    "sg:phone":"+1 406 388 0405",
    "sg:postcode":"59714",
    "sg:province":"MT",
    "sg:tags":[
        "launderer",
        "industrial"
    ],
    "wof:name":"3 DS Inc",
    "wof:placetype":"venue"
},
  "geometry": {"coordinates":[-111.18084,45.777994],"type":"Point"}
}