{
  "type": "Feature",
  "properties": {
    "addr:full":"618 S 25th St Billings MT 59101",
    "addr:housenumber":"618",
    "addr:postcode":"59101",
    "addr:street":"S 25Th St",
    "iso:country":"US",
    "sg:address":"618 S 25th St",
    "sg:city":"Billings",
    "sg:classifiers":[
        {
            "category":"Professional",
            "subcategory":"Engineering",
            "type":"Services"
        }
    ],
    "sg:phone":"+1 406 248 9161",
    "sg:postcode":"59101",
    "sg:province":"MT",
    "sg:tags":[
        "engineer"
    ],
    "wof:name":"Maxim Technologies Inc",
    "wof:placetype":"venue"
},
  "geometry": {"coordinates":[-108.494703,45.776311],"type":"Point"}
}