{
  "type": "Feature",
  "properties": {
    "iso:country":"US",
    "sg:address":"1 King Rd",
    "sg:city":"Cut Bank",
    "sg:classifiers":[
        {
            "category":"Retail",
            "subcategory":"Auto Repair",
            "type":"Services"
        }
    ],
    "sg:phone":"+1 406 873 2520",
    "sg:postcode":"59427",
    "sg:province":"MT",
    "sg:tags":[
        "general"
    ],
    "wof:name":"Dr Daves Foreign Clinic",
    "wof:placetype":"venue"
},
  "geometry": {"coordinates":[-112.319052,48.698646],"type":"Point"}
}