{
  "type": "Feature",
  "properties": {
    "iso:country":"US",
    "sg:address":"650 Lindsey Ct",
    "sg:city":"Kalispell",
    "sg:classifiers":[
        {
            "category":"Building & Trades",
            "subcategory":"Construction",
            "type":"Services"
        }
    ],
    "sg:phone":"+1 406 756 2518",
    "sg:postcode":"59901",
    "sg:province":"MT",
    "sg:tags":[
        "hanging",
        "contractor"
    ],
    "wof:name":"Alpine Interiors LLC",
    "wof:placetype":"venue"
},
  "geometry": {"coordinates":[-114.081299,48.169228],"type":"Point"}
}