{
  "type": "Feature",
  "properties": {
    "iso:country":"US",
    "sg:address":"137 Mesa Ave",
    "sg:city":"Savage",
    "sg:classifiers":[
        {
            "category":"Organizations",
            "subcategory":"Religious Organization",
            "type":"Services"
        }
    ],
    "sg:phone":"+1 406 776 2236",
    "sg:postcode":"59262",
    "sg:province":"MT",
    "sg:tags":[
        "church"
    ],
    "wof:name":"Yellowstone Community Church",
    "wof:placetype":"venue"
},
  "geometry": {"coordinates":[-104.34293,47.453099],"type":"Point"}
}