{
  "type": "Feature",
  "properties": {
    "iso:country":"US",
    "sg:address":"1440 Harrison St",
    "sg:city":"Missoula",
    "sg:classifiers":[
        {
            "category":"Professional",
            "subcategory":"Research",
            "type":"Services"
        }
    ],
    "sg:phone":"+1 406 543 6443",
    "sg:postcode":"59802",
    "sg:province":"MT",
    "sg:tags":[
        "biological"
    ],
    "wof:name":"Fred W Allendorf",
    "wof:placetype":"venue"
},
  "geometry": {"coordinates":[-113.972678,46.875483],"type":"Point"}
}