{
  "type": "Feature",
  "properties": {
    "iso:country":"US",
    "sg:address":"320 N 11th St",
    "sg:city":"Billings",
    "sg:classifiers":[
        {
            "category":"Wholesale",
            "subcategory":"Machinery & Supplies",
            "type":"Manufacturing & Wholesale Goods"
        }
    ],
    "sg:phone":"+1 406 256 3330",
    "sg:postcode":"59101",
    "sg:province":"MT",
    "sg:tags":[
        "equipment",
        "welding"
    ],
    "sg:website":"www.valleywelders.com",
    "wof:name":"Valley Welders Supply Inc",
    "wof:placetype":"venue"
},
  "geometry": {"coordinates":[-108.487286,45.794479],"type":"Point"}
}