{
  "type": "Feature",
  "properties": {
    "addr:full":"306 Washington Blvd Great Falls MT 59404",
    "addr:housenumber":"306",
    "addr:postcode":"59404",
    "addr:street":"Washington Blvd",
    "iso:country":"US",
    "sg:address":"306 Washington Blvd",
    "sg:city":"Great Falls",
    "sg:classifiers":[
        {
            "category":"Freight",
            "type":"Transportation"
        }
    ],
    "sg:phone":"+1 406 965 3815",
    "sg:postcode":"59404",
    "sg:province":"MT",
    "sg:tags":[
        "operator",
        "local",
        "trucking"
    ],
    "wof:name":"Pjs Trucking LLC",
    "wof:placetype":"venue"
},
  "geometry": {"coordinates":[-111.510473,47.547209],"type":"Point"}
}