{
  "type": "Feature",
  "properties": {
    "iso:country":"US",
    "sg:address":"19445 Twin Lakes Rd",
    "sg:city":"Frenchtown",
    "sg:classifiers":[
        {
            "category":"Professional",
            "subcategory":"Management & Consulting",
            "type":"Services"
        }
    ],
    "sg:phone":"+1 406 626 1829",
    "sg:postcode":"59834",
    "sg:province":"MT",
    "sg:tags":[
        "business"
    ],
    "wof:name":"Melissa Holmes",
    "wof:placetype":"venue"
},
  "geometry": {"coordinates":[-114.282183,47.05269],"type":"Point"}
}