{
  "type": "Feature",
  "properties": {
    "iso:country":"US",
    "sg:address":"1028 Stuart St",
    "sg:city":"Helena",
    "sg:classifiers":[
        {
            "category":"Health Services",
            "subcategory":"Chiropractor",
            "type":"Services"
        }
    ],
    "sg:phone":"+1 406 443 8556",
    "sg:postcode":"59601",
    "sg:province":"MT",
    "wof:name":"Aaahh Relief Chiropractic Clin",
    "wof:placetype":"venue"
},
  "geometry": {"coordinates":[-112.05286599999999,46.596815],"type":"Point"}
}