{
  "type": "Feature",
  "properties": {
    "iso:country":"US",
    "sg:address":"615 Oak St",
    "sg:city":"Missoula",
    "sg:classifiers":[
        {
            "category":"Professional",
            "type":"Services"
        }
    ],
    "sg:phone":"+1 406 829 6598",
    "sg:postcode":"59801",
    "sg:province":"MT",
    "wof:name":"Vias Inc",
    "wof:placetype":"venue"
},
  "geometry": {"coordinates":[-114.011195,46.865148],"type":"Point"}
}