{
  "type": "Feature",
  "properties": {
    "addr:full":"1603 Grand Ave Billings MT 59102",
    "addr:housenumber":"1603",
    "addr:postcode":"59102",
    "addr:street":"Grand Ave",
    "iso:country":"US",
    "sg:address":"1603 Grand Ave",
    "sg:city":"Billings",
    "sg:classifiers":[
        {
            "category":"Insurance",
            "subcategory":"Insurance Agent",
            "type":"Services"
        }
    ],
    "sg:phone":"+1 406 252 8360",
    "sg:postcode":"59102",
    "sg:province":"MT",
    "wof:name":"Farmers Insurance Group",
    "wof:placetype":"venue"
},
  "geometry": {"coordinates":[-108.559038,45.784216],"type":"Point"}
}