{
  "type": "Feature",
  "properties": {
    "addr:full":"1237 E Fork Rd Sula MT 59871",
    "addr:housenumber":"1237",
    "addr:postcode":"59871",
    "addr:street":"E Fork Rd",
    "iso:country":"US",
    "sg:address":"1237 E Fork Rd",
    "sg:city":"Sula",
    "sg:classifiers":[
        {
            "category":"Travel",
            "subcategory":"Hotels & Motels",
            "type":"Entertainment"
        }
    ],
    "sg:phone":"+1 406 821 3878",
    "sg:postcode":"59871",
    "sg:province":"MT",
    "sg:tags":[
        "resort"
    ],
    "wof:name":"Broad Axe Lodge & Restaurant",
    "wof:placetype":"venue"
},
  "geometry": {"coordinates":[-113.895313,45.857582],"type":"Point"}
}