{
  "type": "Feature",
  "properties": {
    "iso:country":"US",
    "sg:address":"1101 S Montana St",
    "sg:city":"Butte",
    "sg:classifiers":[
        {
            "category":"Health Services",
            "subcategory":"Doctor",
            "type":"Services"
        }
    ],
    "sg:phone":"+1 406 782 9132",
    "sg:postcode":"59701",
    "sg:province":"MT",
    "sg:tags":[
        "clinic"
    ],
    "sg:website":"www.rockymountainclinic.com",
    "wof:name":"Rocky Mountain Clinic",
    "wof:placetype":"venue"
},
  "geometry": {"coordinates":[-112.539057,45.999535],"type":"Point"}
}