{
  "type": "Feature",
  "properties": {
    "iso:country":"US",
    "sg:address":"610 N Montana St",
    "sg:city":"Dillon",
    "sg:classifiers":[
        {
            "category":"Shopping",
            "subcategory":"Computers & Home Electronics",
            "type":"Retail Goods"
        }
    ],
    "sg:phone":"+1 406 683 9635",
    "sg:postcode":"59725",
    "sg:province":"MT",
    "wof:name":"Computer Discoveries",
    "wof:placetype":"venue"
},
  "geometry": {"coordinates":[-112.630857,45.22329],"type":"Point"}
}