{
  "type": "Feature",
  "properties": {
    "addr:full":"204 Broadwater Ave Billings MT 59101",
    "addr:housenumber":"204",
    "addr:postcode":"59101",
    "addr:street":"Broadwater Ave",
    "iso:country":"US",
    "sg:address":"204 Broadwater Ave",
    "sg:city":"Billings",
    "sg:classifiers":[
        {
            "category":"Bars & Pubs",
            "type":"Food & Drink"
        }
    ],
    "sg:phone":"+1 406 446 3742",
    "sg:postcode":"59101",
    "sg:province":"MT",
    "sg:tags":[
        "drinking"
    ],
    "wof:name":"Blue Ribbon Bar",
    "wof:placetype":"venue"
},
  "geometry": {"coordinates":[-108.522824,45.777046],"type":"Point"}
}