{
  "type": "Feature",
  "properties": {
    "addr:full":"6590 Stagecoach Trail Rd Manhattan MT 59741",
    "addr:housenumber":"6590",
    "addr:postcode":"59741",
    "addr:street":"Stagecoach Trail Rd",
    "iso:country":"US",
    "sg:address":"6590 Stagecoach Trail Rd",
    "sg:city":"Manhattan",
    "sg:phone":"+1 406 282 7940",
    "sg:postcode":"59741",
    "sg:province":"MT",
    "sg:tags":[
        "farm",
        "wheat"
    ],
    "wof:name":"Deboer John",
    "wof:placetype":"venue"
},
  "geometry": {"coordinates":[-111.341352,45.787011],"type":"Point"}
}