{
  "type": "Feature",
  "properties": {
    "addr:full":"4500 US Hwy 93 Whitefish MT 59937",
    "addr:housenumber":"4500",
    "addr:postcode":"59937",
    "addr:street":"Us Hwy 93",
    "iso:country":"US",
    "sg:address":"4500 US Hwy 93",
    "sg:city":"Whitefish",
    "sg:classifiers":[
        {
            "category":"Building & Trades",
            "subcategory":"Construction",
            "type":"Services"
        }
    ],
    "sg:phone":"+1 406 863 9558",
    "sg:postcode":"59937",
    "sg:province":"MT",
    "sg:tags":[
        "excavation",
        "contractor"
    ],
    "wof:name":"Jmk Excavating",
    "wof:placetype":"venue"
},
  "geometry": {"coordinates":[-114.480389,48.437766],"type":"Point"}
}