{
  "type": "Feature",
  "properties": {
    "iso:country":"US",
    "sg:address":"1727 US Hwy 93 S",
    "sg:city":"Hamilton",
    "sg:classifiers":[
        {
            "category":"Manufacturing",
            "subcategory":"Lumber",
            "type":"Manufacturing & Wholesale Goods"
        }
    ],
    "sg:phone":"+1 406 363 1456",
    "sg:postcode":"59840",
    "sg:province":"MT",
    "sg:tags":[
        "pole",
        "piling"
    ],
    "wof:name":"Porterbilt Post & Pole Co",
    "wof:placetype":"venue"
},
  "geometry": {"coordinates":[-114.178534,46.135798],"type":"Point"}
}