{
  "type": "Feature",
  "properties": {
    "addr:full":"2712 S 7th St W Missoula MT 59804",
    "addr:housenumber":"2712",
    "addr:postcode":"59804",
    "addr:street":"S 7Th St W",
    "iso:country":"US",
    "sg:address":"2712 S 7th St W",
    "sg:city":"Missoula",
    "sg:classifiers":[
        {
            "category":"Manufacturing",
            "subcategory":"Lumber",
            "type":"Manufacturing & Wholesale Goods"
        }
    ],
    "sg:phone":"+1 406 543 1494",
    "sg:postcode":"59804",
    "sg:province":"MT",
    "sg:tags":[
        "forester"
    ],
    "wof:name":"International Forestry & Wood",
    "wof:placetype":"venue"
},
  "geometry": {"coordinates":[-114.044501,46.863332],"type":"Point"}
}