{
  "type": "Feature",
  "properties": {
    "addr:full":"119 13th St N Great Falls MT 59401",
    "addr:housenumber":"119",
    "addr:postcode":"59401",
    "addr:street":"13Th St N",
    "iso:country":"US",
    "sg:address":"119 13th St N",
    "sg:city":"Great Falls",
    "sg:classifiers":[
        {
            "category":"Building & Trades",
            "subcategory":"Construction",
            "type":"Services"
        }
    ],
    "sg:phone":"+1 406 727 9208",
    "sg:postcode":"59401",
    "sg:province":"MT",
    "sg:tags":[
        "carpentry"
    ],
    "wof:name":"Sowers Construction",
    "wof:placetype":"venue"
},
  "geometry": {"coordinates":[-111.285032,47.50723],"type":"Point"}
}