{
  "type": "Feature",
  "properties": {
    "iso:country":"US",
    "sg:address":"6656 Falcon Ln",
    "sg:city":"Bozeman",
    "sg:classifiers":[
        {
            "category":"Wholesale",
            "subcategory":"Machinery & Supplies",
            "type":"Manufacturing & Wholesale Goods"
        }
    ],
    "sg:phone":"+1 406 556 9988",
    "sg:postcode":"59718",
    "sg:province":"MT",
    "sg:tags":[
        "industrial"
    ],
    "wof:name":"Western Tool",
    "wof:placetype":"venue"
},
  "geometry": {"coordinates":[-111.15721499999999,45.668863],"type":"Point"}
}