{
  "type": "Feature",
  "properties": {
    "addr:full":"303 US Hwy 93 Polson MT 59860",
    "addr:housenumber":"303",
    "addr:postcode":"59860",
    "addr:street":"Us Hwy 93",
    "iso:country":"US",
    "sg:address":"303 US Hwy 93",
    "sg:city":"Polson",
    "sg:classifiers":[
        {
            "category":"Travel",
            "subcategory":"Hotels & Motels",
            "type":"Entertainment"
        }
    ],
    "sg:phone":"+1 406 883 3636",
    "sg:postcode":"59860",
    "sg:province":"MT",
    "sg:tags":[
        "resort"
    ],
    "wof:name":"Best Western",
    "wof:placetype":"venue"
},
  "geometry": {"coordinates":[-114.15886999999999,47.694398],"type":"Point"}
}