{
  "type": "Feature",
  "properties": {
    "iso:country":"US",
    "sg:address":"507 N Ida Ave",
    "sg:city":"Bozeman",
    "sg:classifiers":[
        {
            "category":"Professional",
            "subcategory":"Business Services",
            "type":"Services"
        }
    ],
    "sg:phone":"+1 406 585 9507",
    "sg:postcode":"59715",
    "sg:province":"MT",
    "sg:tags":[
        "group"
    ],
    "wof:name":"Ultimate Entertainment",
    "wof:placetype":"venue"
},
  "geometry": {"coordinates":[-111.026561,45.685679],"type":"Point"}
}