{
  "type": "Feature",
  "properties": {
    "addr:full":"279 Wilderness View Dr Stevensville MT 59870",
    "addr:housenumber":"279",
    "addr:postcode":"59870",
    "addr:street":"Wilderness View Dr",
    "iso:country":"US",
    "sg:address":"279 Wilderness View Dr",
    "sg:city":"Stevensville",
    "sg:classifiers":[
        {
            "category":"Manufacturing",
            "subcategory":"Lumber",
            "type":"Manufacturing & Wholesale Goods"
        }
    ],
    "sg:phone":"+1 406 777 3103",
    "sg:postcode":"59870",
    "sg:province":"MT",
    "sg:tags":[
        "fuel",
        "reduction",
        "thinning",
        "hazardous",
        "forest"
    ],
    "wof:name":"A Montana Frest Stwrdship Svcs",
    "wof:placetype":"venue"
},
  "geometry": {"coordinates":[-114.07026,46.540184],"type":"Point"}
}