{
  "type": "Feature",
  "properties": {
    "addr:full":"21 Barney Creek Rd Livingston MT 59047",
    "addr:housenumber":"21",
    "addr:postcode":"59047",
    "addr:street":"Barney Creek Rd",
    "iso:country":"US",
    "sg:address":"21 Barney Creek Rd",
    "sg:city":"Livingston",
    "sg:classifiers":[
        {
            "category":"Retail",
            "subcategory":"Animal Services",
            "type":"Services"
        }
    ],
    "sg:phone":"+1 406 222 0278",
    "sg:postcode":"59047",
    "sg:province":"MT",
    "wof:name":"Heston Horse Sports",
    "wof:placetype":"venue"
},
  "geometry": {"coordinates":[-110.538438,45.483429],"type":"Point"}
}