{
  "type": "Feature",
  "properties": {
    "iso:country":"US",
    "sg:address":"3224 Kennedy Ave",
    "sg:city":"Butte",
    "sg:classifiers":[
        {
            "category":"Health Services",
            "subcategory":"Medical Lab",
            "type":"Services"
        }
    ],
    "sg:phone":"+1 406 494 3772",
    "sg:postcode":"59701",
    "sg:province":"MT",
    "sg:tags":[
        "laboratory",
        "dental"
    ],
    "wof:name":"Precision Dental Laboratory",
    "wof:placetype":"venue"
},
  "geometry": {"coordinates":[-112.51408000000001,45.978407],"type":"Point"}
}