{
  "type": "Feature",
  "properties": {
    "iso:country":"US",
    "sg:address":"13229 State Hwy 200",
    "sg:city":"Fort Shaw",
    "sg:classifiers":[
        {
            "category":"Farming",
            "subcategory":"Livestock Farm",
            "type":"Manufacturing & Wholesale Goods"
        }
    ],
    "sg:phone":"+1 406 264 5393",
    "sg:postcode":"59443",
    "sg:province":"MT",
    "sg:tags":[
        "beef",
        "feedlot",
        "cattle"
    ],
    "wof:name":"Fay Lesmeister",
    "wof:placetype":"venue"
},
  "geometry": {"coordinates":[-111.82723,47.495257],"type":"Point"}
}