{
  "type": "Feature",
  "properties": {
    "addr:full":"39 Neill Ave Helena MT 59601",
    "addr:housenumber":"39",
    "addr:postcode":"59601",
    "addr:street":"Neill Ave",
    "iso:country":"US",
    "sg:address":"39 Neill Ave",
    "sg:city":"Helena",
    "sg:classifiers":[
        {
            "category":"Insurance",
            "subcategory":"Insurance Agent",
            "type":"Services"
        }
    ],
    "sg:phone":"+1 406 449 9777",
    "sg:postcode":"59601",
    "sg:province":"MT",
    "wof:name":"Insurance Coordinators of Mont",
    "wof:placetype":"venue"
},
  "geometry": {"coordinates":[-112.037479,46.593177],"type":"Point"}
}