{
  "type": "Feature",
  "properties": {
    "iso:country":"US",
    "sg:address":"995 Demersville Rd",
    "sg:city":"Kalispell",
    "sg:classifiers":[
        {
            "category":"Retail",
            "subcategory":"Animal Services",
            "type":"Services"
        }
    ],
    "sg:phone":"+1 406 752 3140",
    "sg:postcode":"59901",
    "sg:province":"MT",
    "wof:name":"Home Pet Care",
    "wof:placetype":"venue"
},
  "geometry": {"coordinates":[-114.276814,48.141759],"type":"Point"}
}