{
  "type": "Feature",
  "properties": {
    "iso:country":"US",
    "sg:address":"705 E Iron St",
    "sg:city":"Butte",
    "sg:classifiers":[
        {
            "category":"Wholesale",
            "subcategory":"Auto Parts",
            "type":"Manufacturing & Wholesale Goods"
        }
    ],
    "sg:phone":"+1 406 782 6358",
    "sg:postcode":"59701",
    "sg:province":"MT",
    "sg:tags":[
        "automobile",
        "rebuilt"
    ],
    "wof:name":"Summit Valley Auto Sales & Wre",
    "wof:placetype":"venue"
},
  "geometry": {"coordinates":[-112.526325,46.007443],"type":"Point"}
}