{
  "type": "Feature",
  "properties": {
    "iso:country":"US",
    "sg:address":"7645 Woodworth Rd",
    "sg:city":"Greenough",
    "sg:classifiers":[
        {
            "category":"Travel",
            "subcategory":"Hotels & Motels",
            "type":"Entertainment"
        }
    ],
    "sg:phone":"+1 406 677 3436",
    "sg:postcode":"59823",
    "sg:province":"MT",
    "wof:name":"KOSY Kountry",
    "wof:placetype":"venue"
},
  "geometry": {"coordinates":[-113.32364200000001,47.106582],"type":"Point"}
}