{
  "type": "Feature",
  "properties": {
    "iso:country":"US",
    "sg:address":"1550 South Ave W",
    "sg:city":"Missoula",
    "sg:classifiers":[
        {
            "category":"Health Services",
            "subcategory":"Doctor",
            "type":"Services"
        }
    ],
    "sg:phone":"+1 406 721 1550",
    "sg:postcode":"59801",
    "sg:province":"MT",
    "wof:name":"Kevin Miltko DDS",
    "wof:placetype":"venue"
},
  "geometry": {"coordinates":[-114.019504,46.848953],"type":"Point"}
}