{
  "type": "Feature",
  "properties": {
    "addr:full":"130 Eastside Rd Deer Lodge MT 59722",
    "addr:housenumber":"130",
    "addr:postcode":"59722",
    "addr:street":"Eastside Rd",
    "iso:country":"US",
    "sg:address":"130 Eastside Rd",
    "sg:city":"Deer Lodge",
    "sg:classifiers":[
        {
            "category":"Farming",
            "subcategory":"Nursery",
            "type":"Manufacturing & Wholesale Goods"
        }
    ],
    "sg:phone":"+1 406 846 1928",
    "sg:postcode":"59722",
    "sg:province":"MT",
    "sg:tags":[
        "greenhouse"
    ],
    "wof:name":"Eastside Greenhouse",
    "wof:placetype":"venue"
},
  "geometry": {"coordinates":[-112.724175,46.377807],"type":"Point"}
}