{
  "type": "Feature",
  "properties": {
    "iso:country":"US",
    "sg:address":"567 Spokane Ave",
    "sg:city":"Whitefish",
    "sg:classifiers":[
        {
            "category":"Real Estate",
            "subcategory":"Real Estate Agent",
            "type":"Services"
        }
    ],
    "sg:phone":"+1 406 863 8400",
    "sg:postcode":"59937",
    "sg:province":"MT",
    "wof:name":"Chuck Olson Real Estate Inc",
    "wof:placetype":"venue"
},
  "geometry": {"coordinates":[-114.335184,48.406664],"type":"Point"}
}