{
  "type": "Feature",
  "properties": {
    "iso:country":"US",
    "sg:address":"90 Deep Creek Rd",
    "sg:city":"Livingston",
    "sg:classifiers":[
        {
            "category":"Home & Garden",
            "subcategory":"Garden Supply",
            "type":"Retail Goods"
        }
    ],
    "sg:phone":"+1 406 222 7109",
    "sg:postcode":"59047",
    "sg:province":"MT",
    "wof:name":"Deep Creek Green LLC",
    "wof:placetype":"venue"
},
  "geometry": {"coordinates":[-110.535571,45.536944],"type":"Point"}
}