{
  "type": "Feature",
  "properties": {
    "iso:country":"US",
    "sg:address":"465 Moore Ln",
    "sg:city":"Billings",
    "sg:classifiers":[
        {
            "category":"Wholesale",
            "subcategory":"Hardware",
            "type":"Manufacturing & Wholesale Goods"
        }
    ],
    "sg:phone":"+1 406 259 2909",
    "sg:postcode":"59101",
    "sg:province":"MT",
    "sg:tags":[
        "plumbing",
        "equipment",
        "irrigation",
        "fixture",
        "supply"
    ],
    "sg:website":"www.mountainsupply.com",
    "wof:name":"Mountain Supply Co",
    "wof:placetype":"venue"
},
  "geometry": {"coordinates":[-108.540449,45.760134],"type":"Point"}
}