{
  "type": "Feature",
  "properties": {
    "iso:country":"US",
    "sg:address":"2595 Overland Ave",
    "sg:city":"Billings",
    "sg:classifiers":[
        {
            "category":"Professional",
            "subcategory":"Business Services",
            "type":"Services"
        }
    ],
    "sg:phone":"+1 406 656 0099",
    "sg:postcode":"59102",
    "sg:province":"MT",
    "sg:tags":[
        "embroidery"
    ],
    "wof:name":"Montana Garment Co",
    "wof:placetype":"venue"
},
  "geometry": {"coordinates":[-108.581479,45.749833],"type":"Point"}
}