{
  "type": "Feature",
  "properties": {
    "addr:full":"1215 Winne Ave Helena MT 59601",
    "addr:housenumber":"1215",
    "addr:postcode":"59601",
    "addr:street":"Winne Ave",
    "iso:country":"US",
    "sg:address":"1215 Winne Ave",
    "sg:city":"Helena",
    "sg:classifiers":[
        {
            "category":"Farming",
            "subcategory":"Farm",
            "type":"Manufacturing & Wholesale Goods"
        }
    ],
    "sg:phone":"+1 406 443 2755",
    "sg:postcode":"59601",
    "sg:province":"MT",
    "sg:tags":[
        "crop",
        "general"
    ],
    "wof:name":"Dartmans Rentals Farms",
    "wof:placetype":"venue"
},
  "geometry": {"coordinates":[-112.019841,46.581208],"type":"Point"}
}