{
  "type": "Feature",
  "properties": {
    "addr:full":"135 Northern Ave Huntley MT 59037",
    "addr:housenumber":"135",
    "addr:postcode":"59037",
    "addr:street":"Northern Ave",
    "iso:country":"US",
    "sg:address":"135 Northern Ave",
    "sg:city":"Huntley",
    "sg:classifiers":[
        {
            "category":"Food & Beverages",
            "subcategory":"Groceries & Convenience Stores",
            "type":"Retail Goods"
        }
    ],
    "sg:phone":"+1 406 348 9209",
    "sg:postcode":"59037",
    "sg:province":"MT",
    "wof:name":"Express Way",
    "wof:placetype":"venue"
},
  "geometry": {"coordinates":[-108.307823,45.896156],"type":"Point"}
}