{
  "type": "Feature",
  "properties": {
    "iso:country":"US",
    "sg:address":"3012 Vaughn Rd",
    "sg:city":"Great Falls",
    "sg:classifiers":[
        {
            "category":"Wholesale",
            "subcategory":"Farm Supplies",
            "type":"Manufacturing & Wholesale Goods"
        }
    ],
    "sg:phone":"+1 406 452 5158",
    "sg:postcode":"59404",
    "sg:province":"MT",
    "wof:name":"Selstads Lawnranger Spray Svc",
    "wof:placetype":"venue"
},
  "geometry": {"coordinates":[-111.363509,47.518075],"type":"Point"}
}