{
  "type": "Feature",
  "properties": {
    "iso:country":"US",
    "sg:address":"451 Martin Creek Rd",
    "sg:city":"Trout Creek",
    "sg:classifiers":[
        {
            "category":"Travel",
            "subcategory":"Campground",
            "type":"Entertainment"
        }
    ],
    "sg:phone":"+1 406 827 4762",
    "sg:postcode":"59874",
    "sg:province":"MT",
    "sg:tags":[
        "camp"
    ],
    "wof:name":"Blue Spruce Lodge",
    "wof:placetype":"venue"
},
  "geometry": {"coordinates":[-115.703581,47.861601],"type":"Point"}
}