{
  "type": "Feature",
  "properties": {
    "iso:country":"US",
    "sg:address":"2376 Valier Hwy",
    "sg:city":"Cut Bank",
    "sg:classifiers":[
        {
            "category":"Utilities",
            "subcategory":"Telephone",
            "type":"Services"
        }
    ],
    "sg:phone":"+1 406 873 5427",
    "sg:postcode":"59427",
    "sg:province":"MT",
    "sg:tags":[
        "company"
    ],
    "wof:name":"MCI",
    "wof:placetype":"venue"
},
  "geometry": {"coordinates":[-112.36042500000001,48.569655],"type":"Point"}
}