{
  "type": "Feature",
  "properties": {
    "iso:country":"US",
    "sg:address":"3174 US Hwy 93",
    "sg:city":"Stevensville",
    "sg:classifiers":[
        {
            "category":"Building & Trades",
            "subcategory":"Landscaping Services",
            "type":"Services"
        }
    ],
    "sg:phone":"+1 406 642 3415",
    "sg:postcode":"59870",
    "sg:province":"MT",
    "sg:tags":[
        "sprinkler"
    ],
    "sg:website":"www.earthandwood.com",
    "wof:name":"Earth & Wood",
    "wof:placetype":"venue"
},
  "geometry": {"coordinates":[-114.128929,46.471402],"type":"Point"}
}