{
  "type": "Feature",
  "properties": {
    "iso:country":"US",
    "sg:address":"5642 Camp Creek Rd",
    "sg:city":"Big Sandy",
    "sg:phone":"+1 406 378 3295",
    "sg:postcode":"59520",
    "sg:province":"MT",
    "sg:tags":[
        "farm",
        "grain",
        "wheat",
        "cash"
    ],
    "wof:name":"Hettrick Ranch",
    "wof:placetype":"venue"
},
  "geometry": {"coordinates":[-109.93958499999999,48.237306],"type":"Point"}
}