{
  "type": "Feature",
  "properties": {
    "iso:country":"US",
    "sg:address":"1260 Hems Rd",
    "sg:city":"Columbia Falls",
    "sg:classifiers":[
        {
            "category":"Building & Trades",
            "subcategory":"Construction",
            "type":"Services"
        }
    ],
    "sg:phone":"+1 406 892 3690",
    "sg:postcode":"59912",
    "sg:province":"MT",
    "sg:tags":[
        "house",
        "contractor",
        "concrete"
    ],
    "wof:name":"J & B Foundations Inc",
    "wof:placetype":"venue"
},
  "geometry": {"coordinates":[-114.13202099999999,48.358389],"type":"Point"}
}