{
  "type": "Feature",
  "properties": {
    "addr:full":"201 3rd Ave E Polson MT 59860",
    "addr:housenumber":"201",
    "addr:postcode":"59860",
    "addr:street":"3Rd Ave E",
    "iso:country":"US",
    "sg:address":"201 3rd Ave E",
    "sg:city":"Polson",
    "sg:classifiers":[
        {
            "category":"Professional",
            "type":"Services"
        }
    ],
    "sg:phone":"+1 406 883 0987",
    "sg:postcode":"59860",
    "sg:province":"MT",
    "sg:tags":[
        "establishment"
    ],
    "wof:name":"Isabels",
    "wof:placetype":"venue"
},
  "geometry": {"coordinates":[-114.16030000000001,47.693372],"type":"Point"}
}