{
  "type": "Feature",
  "properties": {
    "addr:full":"305 W Mercury St Butte MT 59701",
    "addr:housenumber":"305",
    "addr:postcode":"mt 59701",
    "addr:street":"W Mercury St",
    "iso:country":"US",
    "sg:address":"305 W Mercury St",
    "sg:city":"Butte",
    "sg:classifiers":[
        {
            "category":"Professional",
            "subcategory":"Business Services",
            "type":"Services"
        }
    ],
    "sg:phone":"+1 406 494 2920",
    "sg:postcode":"59701",
    "sg:province":"MT",
    "sg:tags":[
        "electrical",
        "system",
        "power"
    ],
    "wof:name":"P-Tell",
    "wof:placetype":"venue"
},
  "geometry": {"coordinates":[-112.54053399999999,46.011002],"type":"Point"}
}