{
  "type": "Feature",
  "properties": {
    "iso:country":"US",
    "sg:address":"113 W Front St",
    "sg:city":"Missoula",
    "sg:classifiers":[
        {
            "category":"Real Estate",
            "subcategory":"Architect",
            "type":"Services"
        }
    ],
    "sg:phone":"+1 406 880 7823",
    "sg:postcode":"59802",
    "sg:province":"MT",
    "wof:name":"Jeff A Anderson Architecture",
    "wof:placetype":"venue"
},
  "geometry": {"coordinates":[-113.996634,46.870623],"type":"Point"}
}