{
  "type": "Feature",
  "properties": {
    "addr:full":"610 Smelter Ave NE Great Falls MT 59404",
    "addr:housenumber":"610",
    "addr:postcode":"59404",
    "addr:street":"Smelter Ave Ne",
    "iso:country":"US",
    "sg:address":"610 Smelter Ave NE",
    "sg:city":"Great Falls",
    "sg:classifiers":[
        {
            "category":"Retail",
            "subcategory":"Auto Repair",
            "type":"Services"
        }
    ],
    "sg:phone":"+1 406 452 3095",
    "sg:postcode":"59404",
    "sg:province":"MT",
    "sg:tags":[
        "muffler",
        "brake",
        "end"
    ],
    "wof:name":"Meineke Discount Mufflers",
    "wof:placetype":"venue"
},
  "geometry": {"coordinates":[-111.294979,47.524552],"type":"Point"}
}