{
  "type": "Feature",
  "properties": {
    "iso:country":"US",
    "sg:address":"205 S 8th Ave",
    "sg:city":"Laurel",
    "sg:classifiers":[
        {
            "category":"Shopping",
            "subcategory":"Stationery & Office Supplies",
            "type":"Retail Goods"
        }
    ],
    "sg:phone":"+1 406 628 1751",
    "sg:postcode":"59044",
    "sg:province":"MT",
    "wof:name":"Created By ME",
    "wof:placetype":"venue"
},
  "geometry": {"coordinates":[-108.781771,45.665267],"type":"Point"}
}