{
  "type": "Feature",
  "properties": {
    "iso:country":"US",
    "sg:address":"1818 King Ave W",
    "sg:city":"Billings",
    "sg:classifiers":[
        {
            "category":"Travel",
            "subcategory":"Hotels & Motels",
            "type":"Entertainment"
        }
    ],
    "sg:phone":"+1 406 652 9313",
    "sg:postcode":"59102",
    "sg:province":"MT",
    "sg:website":"www.marriott.com/bilsh",
    "wof:name":"Springhill Suites",
    "wof:placetype":"venue"
},
  "geometry": {"coordinates":[-108.563597,45.755146],"type":"Point"}
}