{
  "type": "Feature",
  "properties": {
    "iso:country":"US",
    "sg:address":"1746 E Baseline Rd",
    "sg:city":"Belgrade",
    "sg:classifiers":[
        {
            "category":"Building & Trades",
            "subcategory":"Construction",
            "type":"Services"
        }
    ],
    "sg:phone":"+1 406 388 3463",
    "sg:postcode":"59714",
    "sg:province":"MT",
    "sg:tags":[
        "house",
        "concrete",
        "tr",
        "contractor"
    ],
    "wof:name":"Pro Hand Services",
    "wof:placetype":"venue"
},
  "geometry": {"coordinates":[-111.136084,45.787358],"type":"Point"}
}