{
  "type": "Feature",
  "properties": {
    "iso:country":"US",
    "sg:address":"505 W Park St",
    "sg:city":"Butte",
    "sg:classifiers":[
        {
            "category":"Health Services",
            "subcategory":"Clinic",
            "type":"Services"
        }
    ],
    "sg:phone":"+1 406 723 8238",
    "sg:postcode":"59701",
    "sg:province":"MT",
    "sg:tags":[
        "allied"
    ],
    "wof:name":"Pro-Med Services Inc",
    "wof:placetype":"venue"
},
  "geometry": {"coordinates":[-112.543604,46.012484],"type":"Point"}
}