{
  "type": "Feature",
  "properties": {
    "iso:country":"US",
    "sg:address":"105 Pollywog Ln",
    "sg:city":"Belgrade",
    "sg:classifiers":[
        {
            "category":"Wholesale",
            "subcategory":"Hardware",
            "type":"Manufacturing & Wholesale Goods"
        }
    ],
    "sg:phone":"+1 406 388 8109",
    "sg:postcode":"59714",
    "sg:province":"MT",
    "sg:tags":[
        "sporting"
    ],
    "wof:name":"Doctor Slick Instruments For A",
    "wof:placetype":"venue"
},
  "geometry": {"coordinates":[-111.17803600000001,45.751833],"type":"Point"}
}