{
  "type": "Feature",
  "properties": {
    "iso:country":"US",
    "sg:address":"10720 Gee Norman Rd",
    "sg:city":"Belgrade",
    "sg:classifiers":[
        {
            "category":"Professional",
            "subcategory":"Management & Consulting",
            "type":"Services"
        }
    ],
    "sg:phone":"+1 406 388 4566",
    "sg:postcode":"59714",
    "sg:province":"MT",
    "wof:name":"ETI Corporation",
    "wof:placetype":"venue"
},
  "geometry": {"coordinates":[-111.061019,45.865658],"type":"Point"}
}