{
  "type": "Feature",
  "properties": {
    "addr:full":"2920 S Garfield St Missoula MT 59801",
    "addr:housenumber":"2920",
    "addr:postcode":"59801",
    "addr:street":"S Garfield St",
    "iso:country":"US",
    "sg:address":"2920 S Garfield St",
    "sg:city":"Missoula",
    "sg:classifiers":[
        {
            "category":"Banks & Credit Unions",
            "subcategory":"Bank",
            "type":"Services"
        }
    ],
    "sg:phone":"+1 406 721 2101",
    "sg:postcode":"59801",
    "sg:province":"MT",
    "sg:tags":[
        "mortgage"
    ],
    "wof:name":"Goose Point Mortgage & Investm",
    "wof:placetype":"venue"
},
  "geometry": {"coordinates":[-114.023782,46.842726],"type":"Point"}
}