{
  "type": "Feature",
  "properties": {
    "addr:full":"317 Teton Ave Valier MT 59486",
    "addr:housenumber":"317",
    "addr:postcode":"59486",
    "addr:street":"Teton Ave",
    "iso:country":"US",
    "sg:address":"317 Teton Ave",
    "sg:city":"Valier",
    "sg:classifiers":[
        {
            "category":"Restaurant",
            "type":"Food & Drink"
        }
    ],
    "sg:phone":"+1 406 279 3631",
    "sg:postcode":"59486",
    "sg:province":"MT",
    "wof:name":"Froggies Bar & Grill",
    "wof:placetype":"venue"
},
  "geometry": {"coordinates":[-112.254988,48.308111],"type":"Point"}
}