{
  "type": "Feature",
  "properties": {
    "iso:country":"US",
    "sg:address":"203 Jackrabbit Ln",
    "sg:city":"Belgrade",
    "sg:classifiers":[
        {
            "category":"Organizations",
            "subcategory":"Religious Organization",
            "type":"Services"
        }
    ],
    "sg:phone":"+1 406 388 1358",
    "sg:postcode":"59714",
    "sg:province":"MT",
    "wof:name":"Peace Lutheran Church Elca",
    "wof:placetype":"venue"
},
  "geometry": {"coordinates":[-111.185733,45.675145],"type":"Point"}
}