{
  "type": "Feature",
  "properties": {
    "iso:country":"US",
    "sg:address":"505 Railway St",
    "sg:city":"Whitefish",
    "sg:classifiers":[
        {
            "category":"Professional",
            "subcategory":"Business Services",
            "type":"Services"
        }
    ],
    "sg:phone":"+1 406 862 7463",
    "sg:postcode":"59937",
    "sg:province":"MT",
    "wof:name":"Piney Creek Interiors",
    "wof:placetype":"venue"
},
  "geometry": {"coordinates":[-114.33671200000001,48.412405],"type":"Point"}
}