{
  "type": "Feature",
  "properties": {
    "iso:country":"US",
    "sg:address":"1112 W Broadway St",
    "sg:city":"Missoula",
    "sg:classifiers":[
        {
            "category":"Bars & Pubs",
            "type":"Food & Drink"
        }
    ],
    "sg:phone":"+1 406 728 9077",
    "sg:postcode":"59802",
    "sg:province":"MT",
    "sg:tags":[
        "drinking"
    ],
    "wof:name":"Trails End Bar",
    "wof:placetype":"venue"
},
  "geometry": {"coordinates":[-114.009907,46.876875],"type":"Point"}
}