{
  "type": "Feature",
  "properties": {
    "iso:country":"US",
    "sg:address":"680 Vonderheide Ln",
    "sg:city":"Kalispell",
    "sg:classifiers":[
        {
            "category":"Professional",
            "subcategory":"Business Services",
            "type":"Services"
        }
    ],
    "sg:phone":"+1 406 755 6887",
    "sg:postcode":"59901",
    "sg:province":"MT",
    "wof:name":"Reed Gregerson",
    "wof:placetype":"venue"
},
  "geometry": {"coordinates":[-114.459479,48.155126],"type":"Point"}
}