{
  "type": "Feature",
  "properties": {
    "iso:country":"US",
    "sg:address":"283 Marcus St",
    "sg:city":"Hamilton",
    "sg:classifiers":[
        {
            "category":"Retail",
            "subcategory":"Auto Repair",
            "type":"Services"
        }
    ],
    "sg:phone":"+1 406 363 4009",
    "sg:postcode":"59840",
    "sg:province":"MT",
    "sg:tags":[
        "general"
    ],
    "wof:name":"Jacks Small Engine Service",
    "wof:placetype":"venue"
},
  "geometry": {"coordinates":[-114.147655,46.247666],"type":"Point"}
}