{
  "type": "Feature",
  "properties": {
    "iso:country":"US",
    "sg:address":"1603 Grand Ave",
    "sg:city":"Billings",
    "sg:classifiers":[
        {
            "category":"Personal",
            "subcategory":"Beauty Salon",
            "type":"Services"
        }
    ],
    "sg:phone":"+1 406 248 4611",
    "sg:postcode":"59102",
    "sg:province":"MT",
    "sg:tags":[
        "shop",
        "equipment",
        "establishment"
    ],
    "wof:name":"Little Noggins",
    "wof:placetype":"venue"
},
  "geometry": {"coordinates":[-108.559038,45.784216],"type":"Point"}
}