{
  "type": "Feature",
  "properties": {
    "iso:country":"US",
    "sg:address":"206 W Granite St",
    "sg:city":"Butte",
    "sg:classifiers":[
        {
            "category":"Wholesale",
            "subcategory":"Office Equipment",
            "type":"Manufacturing & Wholesale Goods"
        }
    ],
    "sg:phone":"+1 406 782 4057",
    "sg:postcode":"59701",
    "sg:province":"MT",
    "wof:name":"Empire Office Machines Inc",
    "wof:placetype":"venue"
},
  "geometry": {"coordinates":[-112.539405,46.014178],"type":"Point"}
}