{
  "type": "Feature",
  "properties": {
    "iso:country":"US",
    "sg:address":"1601 2nd Ave N",
    "sg:city":"Great Falls",
    "sg:classifiers":[
        {
            "category":"Professional",
            "subcategory":"Accounting & Tax Preparation",
            "type":"Services"
        }
    ],
    "sg:phone":"+1 406 453 2727",
    "sg:postcode":"59401",
    "sg:province":"MT",
    "sg:tags":[
        "accountant"
    ],
    "wof:name":"Donald L Keith CPA PC",
    "wof:placetype":"venue"
},
  "geometry": {"coordinates":[-111.278146,47.507422],"type":"Point"}
}