{
  "type": "Feature",
  "properties": {
    "iso:country":"US",
    "sg:address":"318 E 6th Ave",
    "sg:city":"Helena",
    "sg:classifiers":[
        {
            "category":"Professional",
            "subcategory":"Lawyer & Legal Services",
            "type":"Services"
        }
    ],
    "sg:phone":"+1 406 443 5790",
    "sg:postcode":"59601",
    "sg:province":"MT",
    "wof:name":"John Hollow",
    "wof:placetype":"venue"
},
  "geometry": {"coordinates":[-112.034684,46.587489],"type":"Point"}
}