{
  "type": "Feature",
  "properties": {
    "iso:country":"US",
    "sg:address":"3311 4th Ave N",
    "sg:city":"Billings",
    "sg:classifiers":[
        {
            "category":"Social Services",
            "type":"Services"
        }
    ],
    "sg:phone":"+1 406 259 2558",
    "sg:postcode":"59101",
    "sg:province":"MT",
    "sg:website":"www.tumbleweedprogram.org",
    "wof:name":"Tumbleweed Runaway Program",
    "wof:placetype":"venue"
},
  "geometry": {"coordinates":[-108.51451,45.781704],"type":"Point"}
}