{
  "type": "Feature",
  "properties": {
    "iso:country":"US",
    "sg:address":"315 Edgewood Dr",
    "sg:city":"Kalispell",
    "sg:classifiers":[
        {
            "category":"Retail",
            "subcategory":"Auto Repair",
            "type":"Services"
        }
    ],
    "sg:phone":"+1 406 257 1547",
    "sg:postcode":"59901",
    "sg:province":"MT",
    "sg:tags":[
        "automotive"
    ],
    "wof:name":"Troys Auto Glass",
    "wof:placetype":"venue"
},
  "geometry": {"coordinates":[-114.26606700000001,48.226538],"type":"Point"}
}