{
  "type": "Feature",
  "properties": {
    "iso:country":"US",
    "sg:address":"819 River St",
    "sg:city":"Hamilton",
    "sg:classifiers":[
        {
            "category":"Real Estate",
            "subcategory":"Real Estate Operator",
            "type":"Services"
        }
    ],
    "sg:phone":"+1 406 363 6854",
    "sg:postcode":"59840",
    "sg:province":"MT",
    "sg:tags":[
        "apartment"
    ],
    "wof:name":"Valley Villas Inc",
    "wof:placetype":"venue"
},
  "geometry": {"coordinates":[-114.166789,46.250566],"type":"Point"}
}