{
  "type": "Feature",
  "properties": {
    "iso:country":"US",
    "sg:address":"6 S Division St",
    "sg:city":"Whitehall",
    "sg:classifiers":[
        {
            "category":"Wholesale",
            "subcategory":"Machinery & Supplies",
            "type":"Manufacturing & Wholesale Goods"
        }
    ],
    "sg:phone":"+1 406 287 5037",
    "sg:postcode":"59759",
    "sg:province":"MT",
    "sg:tags":[
        "operator",
        "trucking"
    ],
    "wof:name":"Francor Inc",
    "wof:placetype":"venue"
},
  "geometry": {"coordinates":[-112.09780600000001,45.869153],"type":"Point"}
}