{
  "type": "Feature",
  "properties": {
    "iso:country":"US",
    "sg:address":"1136 4th Ave W",
    "sg:city":"Kalispell",
    "sg:classifiers":[
        {
            "category":"Retail",
            "subcategory":"Repair Shop",
            "type":"Services"
        }
    ],
    "sg:phone":"+1 406 755 8647",
    "sg:postcode":"59901",
    "sg:province":"MT",
    "wof:name":"Vinyl Technology",
    "wof:placetype":"venue"
},
  "geometry": {"coordinates":[-114.315738,48.186705],"type":"Point"}
}