{
  "type": "Feature",
  "properties": {
    "iso:country":"US",
    "sg:address":"359 Ray Ln",
    "sg:city":"Loma",
    "sg:classifiers":[
        {
            "category":"Farming",
            "subcategory":"Farm",
            "type":"Manufacturing & Wholesale Goods"
        }
    ],
    "sg:phone":"+1 406 378 3277",
    "sg:postcode":"59460",
    "sg:province":"MT",
    "sg:tags":[
        "crop",
        "general"
    ],
    "wof:name":"K E D Farms Inc",
    "wof:placetype":"venue"
},
  "geometry": {"coordinates":[-110.403577,48.096112],"type":"Point"}
}