{
  "type": "Feature",
  "properties": {
    "iso:country":"US",
    "sg:address":"407 Golden Valley Dr",
    "sg:city":"Bozeman",
    "sg:classifiers":[
        {
            "category":"Social Services",
            "subcategory":"Child Care",
            "type":"Services"
        }
    ],
    "sg:phone":"+1 406 522 5494",
    "sg:postcode":"59718",
    "sg:province":"MT",
    "sg:tags":[
        "day"
    ],
    "wof:name":"Bright Futures Inc",
    "wof:placetype":"venue"
},
  "geometry": {"coordinates":[-111.083925,45.676057],"type":"Point"}
}