{
  "type": "Feature",
  "properties": {
    "iso:country":"US",
    "sg:address":"1600 Ave D",
    "sg:city":"Billings",
    "sg:classifiers":[
        {
            "category":"Bars & Pubs",
            "type":"Food & Drink"
        }
    ],
    "sg:phone":"+1 406 252 6220",
    "sg:postcode":"59102",
    "sg:province":"MT",
    "wof:name":"Shooters",
    "wof:placetype":"venue"
},
  "geometry": {"coordinates":[-108.556369,45.787061],"type":"Point"}
}