{
  "type": "Feature",
  "properties": {
    "iso:country":"US",
    "sg:address":"2400 Continental Dr",
    "sg:city":"Butte",
    "sg:classifiers":[
        {
            "category":"Health Services",
            "subcategory":"Nursing And Care Facility",
            "type":"Services"
        }
    ],
    "sg:phone":"+1 406 723 6556",
    "sg:postcode":"59701",
    "sg:province":"MT",
    "sg:tags":[
        "home",
        "skilled",
        "convalescent"
    ],
    "wof:name":"Butte Convalescent Center",
    "wof:placetype":"venue"
},
  "geometry": {"coordinates":[-112.487116,45.990009],"type":"Point"}
}