{
  "type": "Feature",
  "properties": {
    "addr:full":"211 N Main St Boulder MT 59632",
    "addr:housenumber":"211",
    "addr:postcode":"59632",
    "addr:street":"N Main St",
    "iso:country":"US",
    "sg:address":"211 N Main St",
    "sg:city":"Boulder",
    "sg:classifiers":[
        {
            "category":"Food & Beverages",
            "subcategory":"Liquor & Beverages",
            "type":"Retail Goods"
        }
    ],
    "sg:phone":"+1 406 225 3354",
    "sg:postcode":"59632",
    "sg:province":"MT",
    "wof:name":"Liquor Store",
    "wof:placetype":"venue"
},
  "geometry": {"coordinates":[-112.020224,46.402005],"type":"Point"}
}