{
  "type": "Feature",
  "properties": {
    "iso:country":"US",
    "sg:address":"815 3rd St NE",
    "sg:city":"Sidney",
    "sg:classifiers":[
        {
            "category":"Farming",
            "subcategory":"Livestock Farm",
            "type":"Manufacturing & Wholesale Goods"
        }
    ],
    "sg:phone":"+1 406 747 5685",
    "sg:postcode":"59270",
    "sg:province":"MT",
    "sg:tags":[
        "feeding"
    ],
    "wof:name":"Valley View",
    "wof:placetype":"venue"
},
  "geometry": {"coordinates":[-104.145983,47.714102],"type":"Point"}
}