{
  "type": "Feature",
  "properties": {
    "addr:full":"2105 Inverness Pl Missoula MT 59801",
    "addr:housenumber":"2105",
    "addr:postcode":"59801",
    "addr:street":"Inverness Pl",
    "iso:country":"US",
    "sg:address":"2105 Inverness Pl",
    "sg:city":"Missoula",
    "sg:classifiers":[
        {
            "category":"Insurance",
            "subcategory":"Insurance Agent",
            "type":"Services"
        }
    ],
    "sg:phone":"+1 406 829 6600",
    "sg:postcode":"59801",
    "sg:province":"MT",
    "wof:name":"Nationwide Mutual Insurance",
    "wof:placetype":"venue"
},
  "geometry": {"coordinates":[-114.030903,46.873655],"type":"Point"}
}