{
  "type": "Feature",
  "properties": {
    "iso:country":"US",
    "sg:address":"1534 Mansfield Ave",
    "sg:city":"Missoula",
    "sg:classifiers":[
        {
            "category":"Professional",
            "subcategory":"Research",
            "type":"Services"
        }
    ],
    "sg:phone":"+1 406 549 0761",
    "sg:postcode":"59801",
    "sg:province":"MT",
    "sg:tags":[
        "noncommercial"
    ],
    "wof:name":"Kit H Fischer",
    "wof:placetype":"venue"
},
  "geometry": {"coordinates":[-113.985291,46.856462],"type":"Point"}
}