{
  "type": "Feature",
  "properties": {
    "iso:country":"US",
    "sg:address":"218 N Adams St",
    "sg:city":"Boulder",
    "sg:classifiers":[
        {
            "category":"Building & Trades",
            "subcategory":"Construction",
            "type":"Services"
        }
    ],
    "sg:phone":"+1 406 225 3124",
    "sg:postcode":"59632",
    "sg:province":"MT",
    "sg:tags":[
        "excavation",
        "contractor"
    ],
    "wof:name":"Vossler Excavating Inc",
    "wof:placetype":"venue"
},
  "geometry": {"coordinates":[-112.123069,46.239132],"type":"Point"}
}