{
  "type": "Feature",
  "properties": {
    "addr:full":"4979 US Hwy 287 N Ennis MT 59729",
    "addr:housenumber":"4979",
    "addr:postcode":"59729",
    "addr:street":"Us Hwy 287 N",
    "iso:country":"US",
    "sg:address":"4979 US Hwy 287 N",
    "sg:city":"Ennis",
    "sg:classifiers":[
        {
            "category":"Food & Beverages",
            "subcategory":"Groceries & Convenience Stores",
            "type":"Retail Goods"
        }
    ],
    "sg:phone":"+1 406 682 4306",
    "sg:postcode":"59729",
    "sg:province":"MT",
    "sg:tags":[
        "grocer"
    ],
    "wof:name":"Madison Foods Inc",
    "wof:placetype":"venue"
},
  "geometry": {"coordinates":[-111.73076500000001,45.370394],"type":"Point"}
}