{
  "type": "Feature",
  "properties": {
    "iso:country":"US",
    "sg:address":"803 Spokane Ave",
    "sg:city":"Whitefish",
    "sg:classifiers":[
        {
            "category":"Manufacturing",
            "subcategory":"Signs",
            "type":"Manufacturing & Wholesale Goods"
        }
    ],
    "sg:phone":"+1 406 863 9655",
    "sg:postcode":"59937",
    "sg:province":"MT",
    "sg:tags":[
        "specialty",
        "mfg"
    ],
    "wof:name":"Summit Signs",
    "wof:placetype":"venue"
},
  "geometry": {"coordinates":[-114.33518,48.404185],"type":"Point"}
}