{
  "type": "Feature",
  "properties": {
    "iso:country":"US",
    "sg:address":"552 Sudan Pl",
    "sg:city":"Billings",
    "sg:classifiers":[
        {
            "category":"Shopping",
            "subcategory":"Music",
            "type":"Retail Goods"
        }
    ],
    "sg:phone":"+1 406 245 6716",
    "sg:postcode":"59105",
    "sg:province":"MT",
    "sg:tags":[
        "compact",
        "disc"
    ],
    "wof:name":"CD Warehouse Billings Inc",
    "wof:placetype":"venue"
},
  "geometry": {"coordinates":[-108.49705,45.807806],"type":"Point"}
}