{
  "type": "Feature",
  "properties": {
    "iso:country":"US",
    "sg:address":"3800 S Russell St",
    "sg:city":"Missoula",
    "sg:classifiers":[
        {
            "category":"Shopping",
            "type":"Retail Goods"
        }
    ],
    "sg:phone":"+1 406 728 0547",
    "sg:postcode":"59801",
    "sg:province":"MT",
    "sg:tags":[
        "cosmetic",
        "perfume"
    ],
    "wof:name":"Merle Norman Cosmetics",
    "wof:placetype":"venue"
},
  "geometry": {"coordinates":[-114.01817200000001,46.836727],"type":"Point"}
}