{
  "type": "Feature",
  "properties": {
    "iso:country":"US",
    "sg:address":"5505 Foster Ln",
    "sg:city":"Belgrade",
    "sg:classifiers":[
        {
            "category":"Manufacturing",
            "subcategory":"Metals",
            "type":"Manufacturing & Wholesale Goods"
        }
    ],
    "sg:phone":"+1 406 388 7392",
    "sg:postcode":"59714",
    "sg:province":"MT",
    "sg:tags":[
        "blast",
        "furnace",
        "works"
    ],
    "wof:name":"Black Butte Mfg Inc",
    "wof:placetype":"venue"
},
  "geometry": {"coordinates":[-111.057821,45.795563],"type":"Point"}
}