{
  "type": "Feature",
  "properties": {
    "iso:country":"US",
    "sg:address":"13200 Skunk Creek Rd",
    "sg:city":"Bozeman",
    "sg:classifiers":[
        {
            "category":"Building & Trades",
            "subcategory":"Plumbing",
            "type":"Services"
        }
    ],
    "sg:phone":"+1 406 686 4419",
    "sg:postcode":"59715",
    "sg:province":"MT",
    "sg:tags":[
        "contractor"
    ],
    "wof:name":"Superior Plumbing",
    "wof:placetype":"venue"
},
  "geometry": {"coordinates":[-110.814418,45.856217],"type":"Point"}
}