{
  "type": "Feature",
  "properties": {
    "iso:country":"US",
    "sg:address":"525 E Cottonwood Dr",
    "sg:city":"Kalispell",
    "sg:classifiers":[
        {
            "category":"Retail",
            "subcategory":"Auto Repair",
            "type":"Services"
        }
    ],
    "sg:phone":"+1 406 752 4239",
    "sg:postcode":"59901",
    "sg:province":"MT",
    "sg:tags":[
        "body"
    ],
    "wof:name":"Guss Body Shop",
    "wof:placetype":"venue"
},
  "geometry": {"coordinates":[-114.26074,48.218924],"type":"Point"}
}