{
  "type": "Feature",
  "properties": {
    "addr:full":"2708 1st Ave S Billings MT 59101",
    "addr:housenumber":"2708",
    "addr:postcode":"59101",
    "addr:street":"1St Ave S",
    "iso:country":"US",
    "sg:address":"2708 1st Ave S",
    "sg:city":"Billings",
    "sg:classifiers":[
        {
            "category":"Insurance",
            "subcategory":"Life Insurance",
            "type":"Services"
        }
    ],
    "sg:phone":"+1 406 252 4623",
    "sg:postcode":"59101",
    "sg:province":"MT",
    "sg:tags":[
        "carrier"
    ],
    "wof:name":"General American Life Insur Co",
    "wof:placetype":"venue"
},
  "geometry": {"coordinates":[-108.50307599999999,45.779502],"type":"Point"}
}