{
  "type": "Feature",
  "properties": {
    "iso:country":"US",
    "sg:address":"8 4th St S",
    "sg:city":"Fairfield",
    "sg:classifiers":[
        {
            "category":"Real Estate",
            "subcategory":"Real Estate Agent",
            "type":"Services"
        }
    ],
    "sg:phone":"+1 406 467 2188",
    "sg:postcode":"59436",
    "sg:province":"MT",
    "wof:name":"Sun River Land & Sales",
    "wof:placetype":"venue"
},
  "geometry": {"coordinates":[-111.98174899999999,47.614536],"type":"Point"}
}