{
  "type": "Feature",
  "properties": {
    "iso:country":"US",
    "sg:address":"5123 Jellison Rd",
    "sg:city":"Billings",
    "sg:classifiers":[
        {
            "category":"Retail",
            "subcategory":"Car Wash",
            "type":"Services"
        }
    ],
    "sg:phone":"+1 406 245 2099",
    "sg:postcode":"59101",
    "sg:province":"MT",
    "sg:tags":[
        "truck",
        "cleaning"
    ],
    "wof:name":"Mid America Truck Wash",
    "wof:placetype":"venue"
},
  "geometry": {"coordinates":[-108.542657,45.725286],"type":"Point"}
}