{
  "type": "Feature",
  "properties": {
    "addr:full":"231 Main St Kalispell MT 59901",
    "addr:housenumber":"231",
    "addr:postcode":"59901",
    "addr:street":"Main St",
    "iso:country":"US",
    "sg:address":"231 Main St",
    "sg:city":"Kalispell",
    "sg:classifiers":[
        {
            "category":"Shopping",
            "subcategory":"Used Merchandise",
            "type":"Retail Goods"
        }
    ],
    "sg:phone":"+1 406 752 8489",
    "sg:postcode":"59901",
    "sg:province":"MT",
    "wof:name":"Enas",
    "wof:placetype":"venue"
},
  "geometry": {"coordinates":[-114.312922,48.196535],"type":"Point"}
}