{
  "type": "Feature",
  "properties": {
    "iso:country":"US",
    "sg:address":"2511 State Hwy 28",
    "sg:city":"Hot Springs",
    "sg:classifiers":[
        {
            "category":"Wholesale",
            "subcategory":"Construction Materials",
            "type":"Manufacturing & Wholesale Goods"
        }
    ],
    "sg:phone":"+1 406 741 3291",
    "sg:postcode":"59848",
    "sg:province":"MT",
    "sg:tags":[
        "fence"
    ],
    "wof:name":"Jolma Fencing",
    "wof:placetype":"venue"
},
  "geometry": {"coordinates":[-114.626202,47.702985],"type":"Point"}
}