{
  "type": "Feature",
  "properties": {
    "addr:full":"28 N Montana Ave Miles City MT 59301",
    "addr:housenumber":"28",
    "addr:postcode":"59301",
    "addr:street":"N Montana Ave",
    "iso:country":"US",
    "sg:address":"28 N Montana Ave",
    "sg:city":"Miles City",
    "sg:classifiers":[
        {
            "category":"Professional",
            "subcategory":"Management & Consulting",
            "type":"Services"
        }
    ],
    "sg:phone":"+1 406 234 0700",
    "sg:postcode":"59301",
    "sg:province":"MT",
    "wof:name":"American Express",
    "wof:placetype":"venue"
},
  "geometry": {"coordinates":[-105.843362,46.408402],"type":"Point"}
}