{
  "type": "Feature",
  "properties": {
    "addr:full":"2700 Harrison Ave Butte MT 59701",
    "addr:housenumber":"2700",
    "addr:postcode":"mt 59701",
    "addr:street":"Harrison Ave",
    "iso:country":"US",
    "sg:address":"2700 Harrison Ave",
    "sg:city":"Butte",
    "sg:classifiers":[
        {
            "category":"Travel",
            "subcategory":"Hotels & Motels",
            "type":"Entertainment"
        }
    ],
    "sg:phone":"+1 406 494 7000",
    "sg:postcode":"59701",
    "sg:province":"MT",
    "sg:tags":[
        "operation"
    ],
    "wof:name":"Days Inn",
    "wof:placetype":"venue"
},
  "geometry": {"coordinates":[-112.507963,45.985952],"type":"Point"}
}