{
  "type": "Feature",
  "properties": {
    "iso:country":"US",
    "sg:address":"301 W 7th Ave",
    "sg:city":"Big Timber",
    "sg:classifiers":[
        {
            "category":"Health Services",
            "subcategory":"Doctor",
            "type":"Services"
        }
    ],
    "sg:phone":"+1 406 932 4199",
    "sg:postcode":"59011",
    "sg:province":"MT",
    "sg:tags":[
        "medical"
    ],
    "wof:name":"Jacquay Paul Pa-C",
    "wof:placetype":"venue"
},
  "geometry": {"coordinates":[-109.95188,45.82879],"type":"Point"}
}