{
  "type": "Feature",
  "properties": {
    "addr:full":"1420 6th Ave N Billings MT 59101",
    "addr:housenumber":"1420",
    "addr:postcode":"59101",
    "addr:street":"6Th Ave N",
    "iso:country":"US",
    "sg:address":"1420 6th Ave N",
    "sg:city":"Billings",
    "sg:classifiers":[
        {
            "category":"Freight",
            "type":"Transportation"
        }
    ],
    "sg:phone":"+1 406 256 7711",
    "sg:postcode":"59101",
    "sg:province":"MT",
    "sg:tags":[
        "trucking"
    ],
    "sg:website":"www.molerway.com",
    "wof:name":"Molerway Freight Lines Inc",
    "wof:placetype":"venue"
},
  "geometry": {"coordinates":[-108.49375999999999,45.794172],"type":"Point"}
}