{
  "type": "Feature",
  "properties": {
    "iso:country":"US",
    "sg:address":"415 9th St S",
    "sg:city":"Great Falls",
    "sg:classifiers":[
        {
            "category":"Building & Trades",
            "subcategory":"Construction",
            "type":"Services"
        }
    ],
    "sg:phone":"+1 406 452 3007",
    "sg:postcode":"59405",
    "sg:province":"MT",
    "sg:tags":[
        "roofing",
        "painting"
    ],
    "wof:name":"ABC Exteriors Inc",
    "wof:placetype":"venue"
},
  "geometry": {"coordinates":[-111.292038,47.499919],"type":"Point"}
}