{
  "type": "Feature",
  "properties": {
    "iso:country":"US",
    "sg:address":"100 S Canyon St",
    "sg:city":"West Yellowstone",
    "sg:classifiers":[
        {
            "category":"Restaurant",
            "type":"Food & Drink"
        }
    ],
    "sg:phone":"+1 406 646 4592",
    "sg:postcode":"59758",
    "sg:province":"MT",
    "wof:name":"Mc Donald's",
    "wof:placetype":"venue"
},
  "geometry": {"coordinates":[-111.099677,44.658303],"type":"Point"}
}