{
  "type": "Feature",
  "properties": {
    "iso:country":"US",
    "sg:address":"170 S 2nd St",
    "sg:city":"Hamilton",
    "sg:classifiers":[
        {
            "category":"Professional",
            "subcategory":"Lawyer & Legal Services",
            "type":"Services"
        }
    ],
    "sg:phone":"+1 406 375 2266",
    "sg:postcode":"59840",
    "sg:province":"MT",
    "wof:name":"A J H Law Offices",
    "wof:placetype":"venue"
},
  "geometry": {"coordinates":[-114.156975,46.246297],"type":"Point"}
}