{
  "type": "Feature",
  "properties": {
    "iso:country":"US",
    "sg:address":"10056 S Frontage Rd",
    "sg:city":"Billings",
    "sg:classifiers":[
        {
            "category":"Building & Trades",
            "subcategory":"Construction",
            "type":"Services"
        }
    ],
    "sg:phone":"+1 406 656 3613",
    "sg:postcode":"59101",
    "sg:province":"MT",
    "sg:tags":[
        "resurfacing",
        "laying",
        "refinishing",
        "floor"
    ],
    "sg:website":"www.softtouchdesigns.net",
    "wof:name":"Soft Touch Desings Inc",
    "wof:placetype":"venue"
},
  "geometry": {"coordinates":[-108.66186399999999,45.703267],"type":"Point"}
}