{
  "type": "Feature",
  "properties": {
    "iso:country":"US",
    "sg:address":"706 W Broadway St",
    "sg:city":"Butte",
    "sg:classifiers":[
        {
            "category":"Communications",
            "subcategory":"Film & Video Production",
            "type":"Services"
        }
    ],
    "sg:phone":"+1 406 723 4676",
    "sg:postcode":"59701",
    "sg:province":"MT",
    "sg:tags":[
        "taping"
    ],
    "wof:name":"Liondovelamb Productions",
    "wof:placetype":"venue"
},
  "geometry": {"coordinates":[-112.54746,46.013045],"type":"Point"}
}