{
  "type": "Feature",
  "properties": {
    "addr:full":"507 Lincoln Ave Broadus MT 59317",
    "addr:housenumber":"507",
    "addr:postcode":"59317",
    "addr:street":"Lincoln Ave",
    "iso:country":"US",
    "sg:address":"507 Lincoln Ave",
    "sg:city":"Broadus",
    "sg:classifiers":[
        {
            "category":"Government",
            "subcategory":"Office",
            "type":"Public Place"
        }
    ],
    "sg:phone":"+1 406 436 2297",
    "sg:postcode":"59317",
    "sg:province":"MT",
    "sg:tags":[
        "county",
        "program",
        "health"
    ],
    "wof:name":"County Health Nurse",
    "wof:placetype":"venue"
},
  "geometry": {"coordinates":[-105.40692,45.438916],"type":"Point"}
}