{
  "type": "Feature",
  "properties": {
    "addr:full":"5405 Lower River Rd Great Falls MT 59405",
    "addr:housenumber":"5405",
    "addr:postcode":"59405",
    "addr:street":"Lower River Rd",
    "iso:country":"US",
    "sg:address":"5405 Lower River Rd",
    "sg:city":"Great Falls",
    "sg:classifiers":[
        {
            "category":"Shopping",
            "subcategory":"Computers & Home Electronics",
            "type":"Retail Goods"
        }
    ],
    "sg:phone":"+1 406 799 0993",
    "sg:postcode":"59405",
    "sg:province":"MT",
    "wof:name":"Onsite Computer Repair Service",
    "wof:placetype":"venue"
},
  "geometry": {"coordinates":[-111.294105,47.44452],"type":"Point"}
}