{
  "type": "Feature",
  "properties": {
    "addr:full":"201 Avenue E Billings MT 59101",
    "addr:housenumber":"201",
    "addr:postcode":"59101",
    "addr:street":"Avenue",
    "iso:country":"US",
    "sg:address":"201 Avenue E",
    "sg:city":"Billings",
    "sg:classifiers":[
        {
            "category":"Building & Trades",
            "subcategory":"Construction",
            "type":"Services"
        }
    ],
    "sg:phone":"+1 406 248 7252",
    "sg:postcode":"59101",
    "sg:province":"MT",
    "sg:tags":[
        "hanging",
        "contractor"
    ],
    "wof:name":"Mirage Ptng Dec Dplx",
    "wof:placetype":"venue"
},
  "geometry": {"coordinates":[-108.522977,45.788012],"type":"Point"}
}