{
  "type": "Feature",
  "properties": {
    "iso:country":"US",
    "sg:address":"1893 State Hwy 28",
    "sg:city":"Hot Springs",
    "sg:classifiers":[
        {
            "category":"Recreation",
            "subcategory":"Arcade",
            "type":"Entertainment"
        }
    ],
    "sg:phone":"+1 406 741 3212",
    "sg:postcode":"59845",
    "sg:province":"MT",
    "sg:tags":[
        "casino"
    ],
    "wof:name":"Y Casino & Lounge",
    "wof:placetype":"venue"
},
  "geometry": {"coordinates":[-114.62589,47.610687],"type":"Point"}
}