{
  "type": "Feature",
  "properties": {
    "iso:country":"US",
    "sg:address":"1532 W 12th St",
    "sg:city":"Laurel",
    "sg:classifiers":[
        {
            "category":"Building & Trades",
            "subcategory":"Plumbing",
            "type":"Services"
        }
    ],
    "sg:phone":"+1 406 628 6191",
    "sg:postcode":"59044",
    "sg:province":"MT",
    "sg:tags":[
        "plumbing",
        "contractor"
    ],
    "wof:name":"Carlson Plumbing",
    "wof:placetype":"venue"
},
  "geometry": {"coordinates":[-108.790836,45.682479],"type":"Point"}
}