{
  "type": "Feature",
  "properties": {
    "iso:country":"US",
    "sg:address":"1033 S 29th St W",
    "sg:city":"Billings",
    "sg:classifiers":[
        {
            "category":"Building & Trades",
            "subcategory":"Construction",
            "type":"Services"
        }
    ],
    "sg:phone":"+1 406 256 2191",
    "sg:postcode":"59102",
    "sg:province":"MT",
    "sg:tags":[
        "house",
        "siding",
        "contractor"
    ],
    "wof:name":"C's Exterior Designs",
    "wof:placetype":"venue"
},
  "geometry": {"coordinates":[-108.587552,45.749926],"type":"Point"}
}