{
  "type": "Feature",
  "properties": {
    "addr:full":"340 5th Ln NE Fairfield MT 59436",
    "addr:housenumber":"340",
    "addr:postcode":"59436",
    "addr:street":"5Th Ln Ne",
    "iso:country":"US",
    "sg:address":"340 5th Ln NE",
    "sg:city":"Fairfield",
    "sg:phone":"+1 406 467 3151",
    "sg:postcode":"59436",
    "sg:province":"MT",
    "sg:tags":[
        "farm",
        "grain",
        "cash"
    ],
    "wof:name":"Mitch Konen",
    "wof:placetype":"venue"
},
  "geometry": {"coordinates":[-111.881131,47.655988],"type":"Point"}
}