{
  "type": "Feature",
  "properties": {
    "iso:country":"US",
    "sg:address":"820 8th Ave N",
    "sg:city":"Great Falls",
    "sg:classifiers":[
        {
            "category":"Retail",
            "subcategory":"Repair Shop",
            "type":"Services"
        }
    ],
    "sg:phone":"+1 406 453 1814",
    "sg:postcode":"59401",
    "sg:province":"MT",
    "wof:name":"Bk Sports",
    "wof:placetype":"venue"
},
  "geometry": {"coordinates":[-111.29232,47.513966],"type":"Point"}
}