{
  "type": "Feature",
  "properties": {
    "addr:full":"3518 Fairway Dr Great Falls MT 59401",
    "addr:housenumber":"3518",
    "addr:postcode":"59401",
    "addr:street":"Fairway Dr",
    "iso:country":"US",
    "sg:address":"3518 Fairway Dr",
    "sg:city":"Great Falls",
    "sg:classifiers":[
        {
            "category":"Professional",
            "subcategory":"Business Services",
            "type":"Services"
        }
    ],
    "sg:phone":"+1 406 452 8189",
    "sg:postcode":"59401",
    "sg:province":"MT",
    "wof:name":"Jennifer Rimmel",
    "wof:placetype":"venue"
},
  "geometry": {"coordinates":[-111.246528,47.515379],"type":"Point"}
}