{
  "type": "Feature",
  "properties": {
    "addr:full":"717 W Broadway St Butte MT 59701",
    "addr:housenumber":"717",
    "addr:postcode":"mt 59701",
    "addr:street":"W Broadway St",
    "iso:country":"US",
    "sg:address":"717 W Broadway St",
    "sg:city":"Butte",
    "sg:classifiers":[
        {
            "category":"Social Services",
            "subcategory":"Child Care",
            "type":"Services"
        }
    ],
    "sg:phone":"+1 406 782 1612",
    "sg:postcode":"59701",
    "sg:province":"MT",
    "wof:name":"R 'Lil' Rugrats",
    "wof:placetype":"venue"
},
  "geometry": {"coordinates":[-112.54735700000001,46.013196],"type":"Point"}
}