{
  "type": "Feature",
  "properties": {
    "iso:country":"US",
    "sg:address":"517 W Aspen St",
    "sg:city":"Bozeman",
    "sg:classifiers":[
        {
            "category":"Personal",
            "subcategory":"Beauty Salon",
            "type":"Services"
        }
    ],
    "sg:phone":"+1 406 587 7435",
    "sg:postcode":"59715",
    "sg:province":"MT",
    "sg:tags":[
        "shop"
    ],
    "wof:name":"Dorothys Beauty Salon",
    "wof:placetype":"venue"
},
  "geometry": {"coordinates":[-111.044094,45.687602],"type":"Point"}
}