{
  "type": "Feature",
  "properties": {
    "iso:country":"US",
    "sg:address":"2424 1st Ave S",
    "sg:city":"Billings",
    "sg:classifiers":[
        {
            "category":"Autos & Motor Vehicles",
            "subcategory":"Auto Supplies",
            "type":"Retail Goods"
        }
    ],
    "sg:phone":"+1 406 245 8882",
    "sg:postcode":"59101",
    "sg:province":"MT",
    "sg:tags":[
        "equipment",
        "racing",
        "car",
        "automobile"
    ],
    "wof:name":"Frank's Automotive",
    "wof:placetype":"venue"
},
  "geometry": {"coordinates":[-108.499205,45.781373],"type":"Point"}
}