{
  "type": "Feature",
  "properties": {
    "iso:country":"US",
    "sg:address":"908 14th St S",
    "sg:city":"Great Falls",
    "sg:classifiers":[
        {
            "category":"Wholesale",
            "subcategory":"Chemicals & Plastics",
            "type":"Manufacturing & Wholesale Goods"
        }
    ],
    "sg:phone":"+1 406 771 6668",
    "sg:postcode":"59405",
    "sg:province":"MT",
    "sg:tags":[
        "oxygen"
    ],
    "wof:name":"Lincare",
    "wof:placetype":"venue"
},
  "geometry": {"coordinates":[-111.28354299999999,47.494342],"type":"Point"}
}