{
  "type": "Feature",
  "properties": {
    "addr:full":"553 Old Corvallis Rd Hamilton MT 59840",
    "addr:housenumber":"553",
    "addr:postcode":"59840",
    "addr:street":"Old Corvallis Rd",
    "iso:country":"US",
    "sg:address":"553 Old Corvallis Rd",
    "sg:city":"Hamilton",
    "sg:classifiers":[
        {
            "category":"Professional",
            "subcategory":"Research",
            "type":"Services"
        }
    ],
    "sg:phone":"+1 406 363 6214",
    "sg:postcode":"59840",
    "sg:province":"MT",
    "sg:tags":[
        "medical"
    ],
    "sg:website":"www.corixa.com",
    "wof:name":"Corixa Corp",
    "wof:placetype":"venue"
},
  "geometry": {"coordinates":[-114.14584000000001,46.283959],"type":"Point"}
}