{
  "type": "Feature",
  "properties": {
    "iso:country":"US",
    "sg:address":"720 4th Ave N",
    "sg:city":"Billings",
    "sg:classifiers":[
        {
            "category":"Social Services",
            "type":"Services"
        }
    ],
    "sg:phone":"+1 406 628 7571",
    "sg:postcode":"59101",
    "sg:province":"MT",
    "wof:name":"Laurel Senior Citizen Center",
    "wof:placetype":"venue"
},
  "geometry": {"coordinates":[-108.482947,45.79683],"type":"Point"}
}