{
  "type": "Feature",
  "properties": {
    "iso:country":"US",
    "sg:address":"4801 US Hwy 3",
    "sg:city":"Billings",
    "sg:classifiers":[
        {
            "category":"Real Estate",
            "subcategory":"Real Estate Operator",
            "type":"Services"
        }
    ],
    "sg:phone":"+1 406 655 1153",
    "sg:postcode":"59106",
    "sg:province":"MT",
    "sg:tags":[
        "owner",
        "property",
        "commercial"
    ],
    "wof:name":"Eagle Nest Steak House",
    "wof:placetype":"venue"
},
  "geometry": {"coordinates":[-108.63678,45.83069],"type":"Point"}
}