{
  "type": "Feature",
  "properties": {
    "iso:country":"US",
    "sg:address":"125 Meagher Ave",
    "sg:city":"Bozeman",
    "sg:classifiers":[
        {
            "category":"Building & Trades",
            "subcategory":"Plumbing",
            "type":"Services"
        }
    ],
    "sg:phone":"+1 406 586 1277",
    "sg:postcode":"59718",
    "sg:province":"MT",
    "sg:tags":[
        "contractor"
    ],
    "wof:name":"Stay Green Sprinklers Inc",
    "wof:placetype":"venue"
},
  "geometry": {"coordinates":[-111.08651,45.680795],"type":"Point"}
}