{
  "type": "Feature",
  "properties": {
    "iso:country":"US",
    "sg:address":"1532 Sleeping Child Rd",
    "sg:city":"Hamilton",
    "sg:classifiers":[
        {
            "category":"Professional",
            "subcategory":"Management & Consulting",
            "type":"Services"
        }
    ],
    "sg:phone":"+1 406 363 5287",
    "sg:postcode":"59840",
    "sg:province":"MT",
    "sg:tags":[
        "human"
    ],
    "wof:name":"Katherine Q Solberg",
    "wof:placetype":"venue"
},
  "geometry": {"coordinates":[-114.11858100000001,46.148754],"type":"Point"}
}