{
  "type": "Feature",
  "properties": {
    "iso:country":"US",
    "sg:address":"1303 Nutting Rd",
    "sg:city":"Laurel",
    "sg:classifiers":[
        {
            "category":"Professional",
            "subcategory":"Business Services",
            "type":"Services"
        }
    ],
    "sg:phone":"+1 406 426 0022",
    "sg:postcode":"59044",
    "sg:province":"MT",
    "wof:name":"Davis Valuation Svc",
    "wof:placetype":"venue"
},
  "geometry": {"coordinates":[-108.76396,45.657112],"type":"Point"}
}