{
  "type": "Feature",
  "properties": {
    "iso:country":"US",
    "sg:address":"1212 E Park Ave",
    "sg:city":"Anaconda",
    "sg:classifiers":[
        {
            "category":"Restaurant",
            "type":"Food & Drink"
        }
    ],
    "sg:phone":"+1 406 563 7428",
    "sg:postcode":"59711",
    "sg:province":"MT",
    "wof:name":"Peppermint Pattys",
    "wof:placetype":"venue"
},
  "geometry": {"coordinates":[-112.937223,46.126686],"type":"Point"}
}