{
  "type": "Feature",
  "properties": {
    "iso:country":"US",
    "sg:address":"2331 Gilbert Ave",
    "sg:city":"Missoula",
    "sg:classifiers":[
        {
            "category":"Travel",
            "subcategory":"Hotels & Motels",
            "type":"Entertainment"
        }
    ],
    "sg:phone":"+1 406 543 2927",
    "sg:postcode":"59802",
    "sg:province":"MT",
    "sg:tags":[
        "operation"
    ],
    "wof:name":"Foxglove Cttage Bread Brakfast",
    "wof:placetype":"venue"
},
  "geometry": {"coordinates":[-113.967499,46.886723],"type":"Point"}
}