{
  "type": "Feature",
  "properties": {
    "addr:full":"1180 Eastside Hwy Corvallis MT 59828",
    "addr:housenumber":"1180",
    "addr:postcode":"59828",
    "addr:street":"Eastside Hwy",
    "iso:country":"US",
    "sg:address":"1180 Eastside Hwy",
    "sg:city":"Corvallis",
    "sg:classifiers":[
        {
            "category":"Professional",
            "subcategory":"Engineering",
            "type":"Services"
        }
    ],
    "sg:phone":"+1 406 961 5634",
    "sg:postcode":"59828",
    "sg:province":"MT",
    "sg:tags":[
        "engineer"
    ],
    "wof:name":"Bitterroot Engineering-Design",
    "wof:placetype":"venue"
},
  "geometry": {"coordinates":[-114.11357,46.312663],"type":"Point"}
}