{
  "type": "Feature",
  "properties": {
    "addr:full":"1313 Grand Ave Billings MT 59102",
    "addr:housenumber":"1313",
    "addr:postcode":"59102",
    "addr:street":"Grand Ave",
    "iso:country":"US",
    "sg:address":"1313 Grand Ave",
    "sg:city":"Billings",
    "sg:classifiers":[
        {
            "category":"Banks & Credit Unions",
            "subcategory":"Bank",
            "type":"Services"
        }
    ],
    "sg:phone":"+1 406 248 2066",
    "sg:postcode":"59102",
    "sg:province":"MT",
    "sg:tags":[
        "loan"
    ],
    "wof:name":"Check Into Cash",
    "wof:placetype":"venue"
},
  "geometry": {"coordinates":[-108.550951,45.784124],"type":"Point"}
}