{
  "type": "Feature",
  "properties": {
    "addr:full":"300 N Willson Ave Bozeman MT 59715",
    "addr:housenumber":"300",
    "addr:postcode":"59715",
    "addr:street":"N Willson Ave",
    "iso:country":"US",
    "sg:address":"300 N Willson Ave",
    "sg:city":"Bozeman",
    "sg:classifiers":[
        {
            "category":"Real Estate",
            "subcategory":"Real Estate Agent",
            "type":"Services"
        }
    ],
    "sg:phone":"+1 406 582 0478",
    "sg:postcode":"59715",
    "sg:province":"MT",
    "wof:name":"Close Brian F",
    "wof:placetype":"venue"
},
  "geometry": {"coordinates":[-111.038738,45.682978],"type":"Point"}
}