{
  "type": "Feature",
  "properties": {
    "iso:country":"US",
    "sg:address":"4841 US Hwy 89",
    "sg:city":"Choteau",
    "sg:classifiers":[
        {
            "category":"Farming",
            "subcategory":"Livestock Farm",
            "type":"Manufacturing & Wholesale Goods"
        }
    ],
    "sg:phone":"+1 406 466 2971",
    "sg:postcode":"59422",
    "sg:province":"MT",
    "sg:tags":[
        "feed",
        "custom",
        "lot",
        "cattle"
    ],
    "wof:name":"North Montana Feeders Inc",
    "wof:placetype":"venue"
},
  "geometry": {"coordinates":[-112.26532,47.883553],"type":"Point"}
}