{
  "type": "Feature",
  "properties": {
    "iso:country":"US",
    "sg:address":"1270 Trotting Horse Ln",
    "sg:city":"Missoula",
    "sg:classifiers":[
        {
            "category":"Retail",
            "subcategory":"Animal Services",
            "type":"Services"
        }
    ],
    "sg:phone":"+1 406 327 7844",
    "sg:postcode":"59804",
    "sg:province":"MT",
    "wof:name":"Trotting Horse Stables",
    "wof:placetype":"venue"
},
  "geometry": {"coordinates":[-114.138182,46.876047],"type":"Point"}
}