{
  "type": "Feature",
  "properties": {
    "iso:country":"US",
    "sg:address":"1650 Swanson Ln",
    "sg:city":"Billings",
    "sg:classifiers":[
        {
            "category":"Real Estate",
            "subcategory":"Real Estate Agent",
            "type":"Services"
        }
    ],
    "sg:phone":"+1 406 655 9455",
    "sg:postcode":"59102",
    "sg:province":"MT",
    "wof:name":"Yellowstone Group Realtors",
    "wof:placetype":"venue"
},
  "geometry": {"coordinates":[-108.61637899999999,45.788457],"type":"Point"}
}