{
  "type": "Feature",
  "properties": {
    "addr:full":"3309 Eagle Ct Great Falls MT 59404",
    "addr:housenumber":"3309",
    "addr:postcode":"59404",
    "addr:street":"Eagle Ct",
    "iso:country":"US",
    "sg:address":"3309 Eagle Ct",
    "sg:city":"Great Falls",
    "sg:classifiers":[
        {
            "category":"Insurance",
            "subcategory":"Insurance Agent",
            "type":"Services"
        }
    ],
    "sg:phone":"+1 406 727 9984",
    "sg:postcode":"59404",
    "sg:province":"MT",
    "wof:name":"Flegel Insurance",
    "wof:placetype":"venue"
},
  "geometry": {"coordinates":[-111.32661299999999,47.474114],"type":"Point"}
}