{
  "type": "Feature",
  "properties": {
    "iso:country":"US",
    "sg:address":"3080 Airport Rd",
    "sg:city":"Helena",
    "sg:classifiers":[
        {
            "category":"Building & Trades",
            "subcategory":"Equipment Rental",
            "type":"Services"
        }
    ],
    "sg:phone":"+1 406 443 0066",
    "sg:postcode":"59601",
    "sg:province":"MT",
    "sg:tags":[
        "m"
    ],
    "wof:name":"Vetter Aviation",
    "wof:placetype":"venue"
},
  "geometry": {"coordinates":[-111.983193,46.602219],"type":"Point"}
}