{
  "type": "Feature",
  "properties": {
    "iso:country":"US",
    "sg:address":"3303 Duck Club Rd",
    "sg:city":"Billings",
    "sg:classifiers":[
        {
            "category":"Building & Trades",
            "subcategory":"Construction",
            "type":"Services"
        }
    ],
    "sg:phone":"+1 406 373 5335",
    "sg:postcode":"59105",
    "sg:province":"MT",
    "sg:tags":[
        "general",
        "contractor"
    ],
    "wof:name":"R L Enterprises",
    "wof:placetype":"venue"
},
  "geometry": {"coordinates":[-108.388093,45.900237],"type":"Point"}
}