{
  "type": "Feature",
  "properties": {
    "iso:country":"US",
    "sg:address":"222 N 17th St",
    "sg:city":"Billings",
    "sg:classifiers":[
        {
            "category":"Retail",
            "subcategory":"Repair Shop",
            "type":"Services"
        }
    ],
    "sg:phone":"+1 406 256 9663",
    "sg:postcode":"59101",
    "sg:province":"MT",
    "wof:name":"Montana Wildlife Artistry",
    "wof:placetype":"venue"
},
  "geometry": {"coordinates":[-108.493836,45.790092],"type":"Point"}
}