{
  "type": "Feature",
  "properties": {
    "iso:country":"US",
    "sg:address":"60 Duncan District Rd",
    "sg:city":"Sheridan",
    "sg:classifiers":[
        {
            "category":"Building & Trades",
            "subcategory":"Construction",
            "type":"Services"
        }
    ],
    "sg:phone":"+1 406 842 5990",
    "sg:postcode":"59749",
    "sg:province":"MT",
    "sg:tags":[
        "painting",
        "contractor"
    ],
    "wof:name":"Ruby River Paint Co",
    "wof:placetype":"venue"
},
  "geometry": {"coordinates":[-112.215432,45.451792],"type":"Point"}
}