{
  "type": "Feature",
  "properties": {
    "iso:country":"US",
    "sg:address":"6210 Signal Point Dr",
    "sg:city":"Shepherd",
    "sg:classifiers":[
        {
            "category":"Professional",
            "subcategory":"Management & Consulting",
            "type":"Services"
        }
    ],
    "sg:phone":"+1 406 373 9210",
    "sg:postcode":"59079",
    "sg:province":"MT",
    "wof:name":"Regugio J Gutierrez",
    "wof:placetype":"venue"
},
  "geometry": {"coordinates":[-108.326031,45.920174],"type":"Point"}
}