{
  "type": "Feature",
  "properties": {
    "iso:country":"US",
    "sg:address":"310 Red Barn Rd",
    "sg:city":"Hot Springs",
    "sg:classifiers":[
        {
            "category":"Home & Garden",
            "subcategory":"Garden Supply",
            "type":"Retail Goods"
        }
    ],
    "sg:phone":"+1 406 741 5551",
    "sg:postcode":"59845",
    "sg:province":"MT",
    "sg:tags":[
        "nurseryman"
    ],
    "wof:name":"Flower's N Things",
    "wof:placetype":"venue"
},
  "geometry": {"coordinates":[-114.583021,47.659487],"type":"Point"}
}