{
  "type": "Feature",
  "properties": {
    "iso:country":"US",
    "sg:address":"1436 S 1st St",
    "sg:city":"Hamilton",
    "sg:classifiers":[
        {
            "category":"Organizations",
            "subcategory":"Professional Association",
            "type":"Services"
        }
    ],
    "sg:phone":"+1 406 363 3083",
    "sg:postcode":"59840",
    "sg:province":"MT",
    "wof:name":"Rocky Mountain Grange",
    "wof:placetype":"venue"
},
  "geometry": {"coordinates":[-114.155217,46.220631],"type":"Point"}
}