{
  "type": "Feature",
  "properties": {
    "addr:full":"600 Dewey Blvd Butte MT 59701",
    "addr:housenumber":"600",
    "addr:postcode":"mt 59701",
    "addr:street":"Dewey Blvd",
    "iso:country":"US",
    "sg:address":"600 Dewey Blvd",
    "sg:city":"Butte",
    "sg:classifiers":[
        {
            "category":"Insurance",
            "subcategory":"Insurance Agent",
            "type":"Services"
        }
    ],
    "sg:phone":"+1 406 494 3300",
    "sg:postcode":"59701",
    "sg:province":"MT",
    "wof:name":"State Farm Insurance",
    "wof:placetype":"venue"
},
  "geometry": {"coordinates":[-112.52870799999999,45.983343],"type":"Point"}
}