{
  "type": "Feature",
  "properties": {
    "iso:country":"US",
    "sg:address":"2700 Gabel Rd",
    "sg:city":"Billings",
    "sg:classifiers":[
        {
            "category":"Wholesale",
            "subcategory":"Construction Materials",
            "type":"Manufacturing & Wholesale Goods"
        }
    ],
    "sg:phone":"+1 406 656 7710",
    "sg:postcode":"59102",
    "sg:province":"MT",
    "sg:tags":[
        "building"
    ],
    "sg:website":"www.gbpd.com",
    "wof:name":"Guardian Building Products",
    "wof:placetype":"venue"
},
  "geometry": {"coordinates":[-108.584063,45.745212],"type":"Point"}
}