{
  "type": "Feature",
  "properties": {
    "addr:full":"500 Osloski Rd Eureka MT 59917",
    "addr:housenumber":"500",
    "addr:postcode":"59917",
    "addr:street":"Osloski Rd",
    "iso:country":"US",
    "sg:address":"500 Osloski Rd",
    "sg:city":"Eureka",
    "sg:classifiers":[
        {
            "category":"Retail",
            "subcategory":"Repair Shop",
            "type":"Services"
        }
    ],
    "sg:phone":"+1 406 889 3301",
    "sg:postcode":"59917",
    "sg:province":"MT",
    "sg:tags":[
        "repairing",
        "equipment",
        "electric"
    ],
    "sg:website":"www.lincolnelectric.org",
    "wof:name":"Lincoln Electric Co-Op Inc",
    "wof:placetype":"venue"
},
  "geometry": {"coordinates":[-115.060227,48.889922],"type":"Point"}
}