{
  "type": "Feature",
  "properties": {
    "addr:full":"4899 US Hwy 93 Whitefish MT 59937",
    "addr:housenumber":"4899",
    "addr:postcode":"59937",
    "addr:street":"Us Hwy 93",
    "iso:country":"US",
    "sg:address":"4899 US Hwy 93",
    "sg:city":"Whitefish",
    "sg:classifiers":[
        {
            "category":"Food & Beverages",
            "subcategory":"Groceries & Convenience Stores",
            "type":"Retail Goods"
        }
    ],
    "sg:phone":"+1 406 862 6365",
    "sg:postcode":"59937",
    "sg:province":"MT",
    "sg:tags":[
        "rental",
        "video",
        "tape",
        "alcoholic"
    ],
    "wof:name":"Midway Mini Mart",
    "wof:placetype":"venue"
},
  "geometry": {"coordinates":[-114.335825,48.327352],"type":"Point"}
}