{
  "type": "Feature",
  "properties": {
    "iso:country":"US",
    "sg:address":"820 Montana Ave",
    "sg:city":"Deer Lodge",
    "sg:classifiers":[
        {
            "category":"Building & Trades",
            "subcategory":"Plumbing",
            "type":"Services"
        }
    ],
    "sg:phone":"+1 406 846 2007",
    "sg:postcode":"59722",
    "sg:province":"MT",
    "sg:tags":[
        "plumbing",
        "contractor"
    ],
    "wof:name":"Ryan Plumbing & Heating Inc",
    "wof:placetype":"venue"
},
  "geometry": {"coordinates":[-112.724096,46.396142],"type":"Point"}
}