{
  "type": "Feature",
  "properties": {
    "addr:full":"221 W Main St Cut Bank MT 59427",
    "addr:housenumber":"221",
    "addr:postcode":"59427",
    "addr:street":"W Main St",
    "iso:country":"US",
    "sg:address":"221 W Main St",
    "sg:city":"Cut Bank",
    "sg:classifiers":[
        {
            "category":"Government",
            "subcategory":"Office",
            "type":"Public Place"
        }
    ],
    "sg:phone":"+1 406 873 5526",
    "sg:postcode":"59427",
    "sg:province":"MT",
    "sg:tags":[
        "executive"
    ],
    "wof:name":"City of Cut Bank Office",
    "wof:placetype":"venue"
},
  "geometry": {"coordinates":[-112.335173,48.63822],"type":"Point"}
}