{
  "type": "Feature",
  "properties": {
    "iso:country":"US",
    "sg:address":"1287 Burns Way",
    "sg:city":"Kalispell",
    "sg:classifiers":[
        {
            "category":"Health Services",
            "subcategory":"Doctor",
            "type":"Services"
        }
    ],
    "sg:phone":"+1 406 752 8120",
    "sg:postcode":"59901",
    "sg:province":"MT",
    "sg:tags":[
        "medical",
        "practice",
        "general"
    ],
    "wof:name":"Family Health Care PC",
    "wof:placetype":"venue"
},
  "geometry": {"coordinates":[-114.325627,48.212825],"type":"Point"}
}