{
  "type": "Feature",
  "properties": {
    "iso:country":"US",
    "sg:address":"200 1st Ave N",
    "sg:city":"Glasgow",
    "sg:classifiers":[
        {
            "category":"Shopping",
            "subcategory":"Bicycles & Sporting Goods",
            "type":"Retail Goods"
        }
    ],
    "sg:phone":"+1 406 228 4867",
    "sg:postcode":"59230",
    "sg:province":"MT",
    "sg:tags":[
        "gun",
        "gunsmith"
    ],
    "wof:name":"Leroy's Big Valley Gun Works",
    "wof:placetype":"venue"
},
  "geometry": {"coordinates":[-106.631896,48.195654],"type":"Point"}
}