{
  "type": "Feature",
  "properties": {
    "addr:full":"1002 1st Ave N Billings MT 59101",
    "addr:housenumber":"1002",
    "addr:postcode":"59101",
    "addr:street":"1St Ave N",
    "iso:country":"US",
    "sg:address":"1002 1st Ave N",
    "sg:city":"Billings",
    "sg:classifiers":[
        {
            "category":"Autos & Motor Vehicles",
            "subcategory":"Automobile Sales",
            "type":"Retail Goods"
        }
    ],
    "sg:phone":"+1 406 254 1338",
    "sg:postcode":"59101",
    "sg:province":"MT",
    "sg:tags":[
        "car",
        "dealer"
    ],
    "wof:name":"Auto Magic",
    "wof:placetype":"venue"
},
  "geometry": {"coordinates":[-108.484863,45.792155],"type":"Point"}
}