{
  "type": "Feature",
  "properties": {
    "iso:country":"US",
    "sg:address":"2812 Shirley Ln",
    "sg:city":"Billings",
    "sg:classifiers":[
        {
            "category":"Building & Trades",
            "subcategory":"Construction",
            "type":"Services"
        }
    ],
    "sg:phone":"+1 406 860 1167",
    "sg:postcode":"59106",
    "sg:province":"MT",
    "sg:tags":[
        "general",
        "contractor"
    ],
    "wof:name":"Heritage Construction",
    "wof:placetype":"venue"
},
  "geometry": {"coordinates":[-108.648282,45.798213],"type":"Point"}
}