{
  "type": "Feature",
  "properties": {
    "iso:country":"US",
    "sg:address":"209 Blanchard Lake Rd",
    "sg:city":"Whitefish",
    "sg:classifiers":[
        {
            "category":"Shopping",
            "subcategory":"Used Merchandise",
            "type":"Retail Goods"
        }
    ],
    "sg:phone":"+1 406 862 5117",
    "sg:postcode":"59937",
    "sg:province":"MT",
    "wof:name":"Big Mountain Trading & Pawn",
    "wof:placetype":"venue"
},
  "geometry": {"coordinates":[-114.340237,48.370857],"type":"Point"}
}