{
  "type": "Feature",
  "properties": {
    "addr:full":"410 S 26th St Billings MT 59101",
    "addr:housenumber":"410",
    "addr:postcode":"59101",
    "addr:street":"S 26Th St",
    "iso:country":"US",
    "sg:address":"410 S 26th St",
    "sg:city":"Billings",
    "sg:classifiers":[
        {
            "category":"Social Services",
            "type":"Services"
        }
    ],
    "sg:phone":"+1 406 256 6825",
    "sg:postcode":"59101",
    "sg:province":"MT",
    "sg:tags":[
        "executive"
    ],
    "wof:name":"Ted Lechner Youth Service Ctr",
    "wof:placetype":"venue"
},
  "geometry": {"coordinates":[-108.497534,45.777351],"type":"Point"}
}