{
  "type": "Feature",
  "properties": {
    "iso:country":"US",
    "sg:address":"4003 Thomas Dr",
    "sg:city":"Missoula",
    "sg:classifiers":[
        {
            "category":"Building & Trades",
            "subcategory":"Cleaning & Sanitation",
            "type":"Services"
        }
    ],
    "sg:phone":"+1 406 251 3457",
    "sg:postcode":"59803",
    "sg:province":"MT",
    "sg:tags":[
        "house"
    ],
    "wof:name":"Maid Brigade",
    "wof:placetype":"venue"
},
  "geometry": {"coordinates":[-114.033548,46.835019],"type":"Point"}
}