{
  "type": "Feature",
  "properties": {
    "iso:country":"US",
    "sg:address":"611 2nd St",
    "sg:city":"Havre",
    "sg:classifiers":[
        {
            "category":"Organizations",
            "subcategory":"Non-profit Organization",
            "type":"Services"
        }
    ],
    "sg:phone":"+1 406 265 1629",
    "sg:postcode":"59501",
    "sg:province":"MT",
    "sg:tags":[
        "social"
    ],
    "wof:name":"Feed My Sheep Soup Kitchen",
    "wof:placetype":"venue"
},
  "geometry": {"coordinates":[-109.673269,48.552134],"type":"Point"}
}