{
  "type": "Feature",
  "properties": {
    "iso:country":"US",
    "sg:address":"12850 River Rd",
    "sg:city":"Bozeman",
    "sg:classifiers":[
        {
            "category":"Farming",
            "subcategory":"Livestock Farm",
            "type":"Manufacturing & Wholesale Goods"
        }
    ],
    "sg:phone":"+1 406 763 4289",
    "sg:postcode":"59718",
    "sg:province":"MT",
    "sg:tags":[
        "beef",
        "feedlot",
        "cattle"
    ],
    "wof:name":"Joe Axtell",
    "wof:placetype":"venue"
},
  "geometry": {"coordinates":[-111.21675,45.63277],"type":"Point"}
}