{
  "type": "Feature",
  "properties": {
    "iso:country":"US",
    "sg:address":"1650 Ave D",
    "sg:city":"Billings",
    "sg:classifiers":[
        {
            "category":"Freight",
            "type":"Transportation"
        }
    ],
    "sg:phone":"+1 406 259 5050",
    "sg:postcode":"59102",
    "sg:province":"MT",
    "sg:tags":[
        "general"
    ],
    "wof:name":"Lane Wicks Capital LLC",
    "wof:placetype":"venue"
},
  "geometry": {"coordinates":[-108.555091,45.787049],"type":"Point"}
}