{
  "type": "Feature",
  "properties": {
    "iso:country":"US",
    "sg:address":"720 Bear Creek Rd",
    "sg:city":"Libby",
    "sg:classifiers":[
        {
            "category":"Manufacturing",
            "subcategory":"Apparel",
            "type":"Manufacturing & Wholesale Goods"
        }
    ],
    "sg:phone":"+1 406 293 8688",
    "sg:postcode":"59923",
    "sg:province":"MT",
    "sg:tags":[
        "outerwear",
        "mfg"
    ],
    "wof:name":"JP Teez Etc",
    "wof:placetype":"venue"
},
  "geometry": {"coordinates":[-115.520358,48.278566],"type":"Point"}
}