{
  "type": "Feature",
  "properties": {
    "addr:full":"406 N Cheyenne Ave Hardin MT 59034",
    "addr:housenumber":"406",
    "addr:postcode":"59034",
    "addr:street":"N Cheyenne Ave",
    "iso:country":"US",
    "sg:address":"406 N Cheyenne Ave",
    "sg:city":"Hardin",
    "sg:classifiers":[
        {
            "category":"Government",
            "subcategory":"Office",
            "type":"Public Place"
        }
    ],
    "sg:phone":"+1 406 665 9264",
    "sg:postcode":"59034",
    "sg:province":"MT",
    "sg:tags":[
        "city"
    ],
    "wof:name":"City Hall",
    "wof:placetype":"venue"
},
  "geometry": {"coordinates":[-107.60449300000001,45.732451],"type":"Point"}
}