{
  "type": "Feature",
  "properties": {
    "iso:country":"US",
    "sg:address":"102 State Hwy 16",
    "sg:city":"Sidney",
    "sg:classifiers":[
        {
            "category":"Wholesale",
            "subcategory":"Hardware",
            "type":"Manufacturing & Wholesale Goods"
        }
    ],
    "sg:phone":"+1 701 565 2261",
    "sg:postcode":"59270",
    "sg:province":"MT",
    "sg:tags":[
        "pipe"
    ],
    "wof:name":"Tescher Pipe",
    "wof:placetype":"venue"
},
  "geometry": {"coordinates":[-104.156498,47.716219],"type":"Point"}
}