{
  "type": "Feature",
  "properties": {
    "addr:full":"311 Main St Stevensville MT 59870",
    "addr:housenumber":"311",
    "addr:postcode":"59870",
    "addr:street":"Main St",
    "iso:country":"US",
    "sg:address":"311 Main St",
    "sg:city":"Stevensville",
    "sg:classifiers":[
        {
            "category":"Freight",
            "type":"Transportation"
        }
    ],
    "sg:phone":"+1 406 777 2221",
    "sg:postcode":"59870",
    "sg:province":"MT",
    "sg:tags":[
        "broker",
        "trucking"
    ],
    "wof:name":"Crown Truck Brokers",
    "wof:placetype":"venue"
},
  "geometry": {"coordinates":[-114.09356200000001,46.509837],"type":"Point"}
}