{
  "type": "Feature",
  "properties": {
    "addr:full":"196 Lake Hills Dr Bigfork MT 59911",
    "addr:housenumber":"196",
    "addr:postcode":"59911",
    "addr:street":"Lake Hills Dr Bigfork",
    "iso:country":"US",
    "sg:address":"196 Lake Hills Dr",
    "sg:city":"Bigfork",
    "sg:classifiers":[
        {
            "category":"Sports & Exercise",
            "subcategory":"Gym",
            "type":"Entertainment"
        }
    ],
    "sg:phone":"+1 406 837 1462",
    "sg:postcode":"59911",
    "sg:province":"MT",
    "sg:tags":[
        "fitness",
        "physical",
        "facility"
    ],
    "wof:name":"Curves For Women",
    "wof:placetype":"venue"
},
  "geometry": {"coordinates":[-114.08185899999999,48.076507],"type":"Point"}
}