{
  "type": "Feature",
  "properties": {
    "iso:country":"US",
    "sg:address":"425 S Orange St",
    "sg:city":"Missoula",
    "sg:classifiers":[
        {
            "category":"Food & Beverages",
            "subcategory":"Specialty",
            "type":"Retail Goods"
        }
    ],
    "sg:phone":"+1 406 543 3126",
    "sg:postcode":"59801",
    "sg:province":"MT",
    "sg:tags":[
        "tea",
        "coffee"
    ],
    "wof:name":"LA Te Da",
    "wof:placetype":"venue"
},
  "geometry": {"coordinates":[-114.003581,46.867214],"type":"Point"}
}