{
  "type": "Feature",
  "properties": {
    "addr:full":"10020 US Hwy 93 Lolo MT 59847",
    "addr:housenumber":"10020",
    "addr:postcode":"59847",
    "addr:street":"Us Hwy 93",
    "iso:country":"US",
    "sg:address":"10020 US Hwy 93",
    "sg:city":"Lolo",
    "sg:classifiers":[
        {
            "category":"Building & Trades",
            "subcategory":"Landscaping Services",
            "type":"Services"
        }
    ],
    "sg:phone":"+1 406 550 1444",
    "sg:postcode":"59847",
    "sg:province":"MT",
    "sg:tags":[
        "landscape",
        "contractor"
    ],
    "wof:name":"Landscaping & Whatever",
    "wof:placetype":"venue"
},
  "geometry": {"coordinates":[-114.086488,46.775227],"type":"Point"}
}