{
  "type": "Feature",
  "properties": {
    "iso:country":"US",
    "sg:address":"1102 E Front St",
    "sg:city":"Butte",
    "sg:classifiers":[
        {
            "category":"Retail",
            "subcategory":"Auto Repair",
            "type":"Services"
        }
    ],
    "sg:phone":"+1 406 723 3603",
    "sg:postcode":"59701",
    "sg:province":"MT",
    "sg:tags":[
        "general"
    ],
    "wof:name":"Berge Automotive",
    "wof:placetype":"venue"
},
  "geometry": {"coordinates":[-112.524073,46.002758],"type":"Point"}
}