{
  "type": "Feature",
  "properties": {
    "iso:country":"US",
    "sg:address":"2040 Rosebud Dr",
    "sg:city":"Billings",
    "sg:classifiers":[
        {
            "category":"Shopping",
            "subcategory":"Used Merchandise",
            "type":"Retail Goods"
        },
        {
            "category":"Shopping",
            "subcategory":"Books",
            "type":"Retail Goods"
        }
    ],
    "sg:phone":"+1 406 652 1188",
    "sg:postcode":"59102",
    "sg:province":"MT",
    "sg:tags":[
        "rare",
        "dealer"
    ],
    "wof:name":"Buy The Book",
    "wof:placetype":"venue"
},
  "geometry": {"coordinates":[-108.567784,45.758524],"type":"Point"}
}