{
  "type": "Feature",
  "properties": {
    "iso:country":"US",
    "sg:address":"238 Mc Leod Ave",
    "sg:city":"Missoula",
    "sg:classifiers":[
        {
            "category":"Autos & Motor Vehicles",
            "subcategory":"Auto Supplies",
            "type":"Retail Goods"
        }
    ],
    "sg:phone":"+1 406 728 3983",
    "sg:postcode":"59801",
    "sg:province":"MT",
    "wof:name":"Muller Tire Co",
    "wof:placetype":"venue"
},
  "geometry": {"coordinates":[-113.99458,46.859177],"type":"Point"}
}