{
  "type": "Feature",
  "properties": {
    "iso:country":"US",
    "sg:address":"53 Balsam Dr",
    "sg:city":"Miles City",
    "sg:phone":"+1 406 232 0021",
    "sg:postcode":"59301",
    "sg:province":"MT",
    "sg:tags":[
        "farm",
        "corn"
    ],
    "wof:name":"Family Heritage",
    "wof:placetype":"venue"
},
  "geometry": {"coordinates":[-105.833949,46.394361],"type":"Point"}
}