{
  "type": "Feature",
  "properties": {
    "iso:country":"US",
    "sg:address":"1325 Wyoming St",
    "sg:city":"Missoula",
    "sg:classifiers":[
        {
            "category":"Health Services",
            "subcategory":"Clinic",
            "type":"Services"
        }
    ],
    "sg:phone":"+1 406 532 9800",
    "sg:postcode":"59801",
    "sg:province":"MT",
    "sg:tags":[
        "specialty",
        "outpatient"
    ],
    "wof:name":"Turning Point Addiction Svcs",
    "wof:placetype":"venue"
},
  "geometry": {"coordinates":[-114.017086,46.871936],"type":"Point"}
}