{
  "type": "Feature",
  "properties": {
    "iso:country":"US",
    "sg:address":"370 Mountain Meadow Rd",
    "sg:city":"Kalispell",
    "sg:classifiers":[
        {
            "category":"Real Estate",
            "subcategory":"Real Estate Agent",
            "type":"Services"
        }
    ],
    "sg:phone":"+1 406 755 4266",
    "sg:postcode":"59901",
    "sg:province":"MT",
    "wof:name":"Ranch & Home Realty Inc",
    "wof:placetype":"venue"
},
  "geometry": {"coordinates":[-114.47601,48.284764],"type":"Point"}
}