{
  "type": "Feature",
  "properties": {
    "addr:full":"3900 Big Mountain Rd Whitefish MT 59937",
    "addr:housenumber":"3900",
    "addr:postcode":"59937",
    "addr:street":"Big Mountain Rd",
    "iso:country":"US",
    "sg:address":"3900 Big Mountain Rd",
    "sg:city":"Whitefish",
    "sg:classifiers":[
        {
            "category":"Real Estate",
            "subcategory":"Real Estate Operator",
            "type":"Services"
        }
    ],
    "sg:phone":"+1 406 862 6966",
    "sg:postcode":"59937",
    "sg:province":"MT",
    "sg:tags":[
        "operation",
        "dwelling"
    ],
    "wof:name":"Alpinglow Inn Association Inc",
    "wof:placetype":"venue"
},
  "geometry": {"coordinates":[-114.357857,48.482472],"type":"Point"}
}