{
  "type": "Feature",
  "properties": {
    "iso:country":"US",
    "sg:address":"365 Beth Dr",
    "sg:city":"Great Falls",
    "sg:classifiers":[
        {
            "category":"Organizations",
            "subcategory":"Professional Association",
            "type":"Services"
        }
    ],
    "sg:phone":"+1 406 453 2827",
    "sg:postcode":"59405",
    "sg:province":"MT",
    "sg:tags":[
        "business"
    ],
    "wof:name":"Racquet Service",
    "wof:placetype":"venue"
},
  "geometry": {"coordinates":[-111.231833,47.500379],"type":"Point"}
}