{
  "type": "Feature",
  "properties": {
    "addr:full":"365 Beth Dr Great Falls MT 59405",
    "addr:housenumber":"365",
    "addr:postcode":"59405",
    "addr:street":"Beth Dr",
    "iso:country":"US",
    "sg:address":"365 Beth Dr",
    "sg:city":"Great Falls",
    "sg:classifiers":[
        {
            "category":"Organizations",
            "subcategory":"Professional Association",
            "type":"Services"
        }
    ],
    "sg:phone":"+1 406 453 2827",
    "sg:postcode":"59405",
    "sg:province":"MT",
    "sg:tags":[
        "business"
    ],
    "wof:name":"Racquet Service",
    "wof:placetype":"venue"
},
  "geometry": {"coordinates":[-111.23183299999999,47.500379],"type":"Point"}
}