{
  "type": "Feature",
  "properties": {
    "iso:country":"US",
    "sg:address":"3040 Busch Ave",
    "sg:city":"Butte",
    "sg:classifiers":[
        {
            "category":"Restaurant",
            "type":"Food & Drink"
        }
    ],
    "sg:phone":"+1 406 494 5802",
    "sg:postcode":"59701",
    "sg:province":"MT",
    "sg:tags":[
        "eating"
    ],
    "wof:name":"Pizza Hut",
    "wof:placetype":"venue"
},
  "geometry": {"coordinates":[-112.509342,45.980731],"type":"Point"}
}