{
  "type": "Feature",
  "properties": {
    "iso:country":"US",
    "sg:address":"1701 Prospect Ave",
    "sg:city":"Helena",
    "sg:classifiers":[
        {
            "category":"Real Estate",
            "subcategory":"Real Estate Operator",
            "type":"Services"
        }
    ],
    "sg:phone":"+1 406 442 3222",
    "sg:postcode":"59601",
    "sg:province":"MT",
    "sg:tags":[
        "property",
        "commercial"
    ],
    "wof:name":"Vista Square",
    "wof:placetype":"venue"
},
  "geometry": {"coordinates":[-112.011012,46.591145],"type":"Point"}
}