{
  "type": "Feature",
  "properties": {
    "iso:country":"US",
    "sg:address":"425 N 7th Ave",
    "sg:city":"Bozeman",
    "sg:classifiers":[
        {
            "category":"Wholesale",
            "subcategory":"Auto Parts",
            "type":"Manufacturing & Wholesale Goods"
        }
    ],
    "sg:phone":"+1 406 587 4233",
    "sg:postcode":"59715",
    "sg:province":"MT",
    "wof:name":"Carquest Auto Parts Store",
    "wof:placetype":"venue"
},
  "geometry": {"coordinates":[-111.046421,45.683342],"type":"Point"}
}