{
  "type": "Feature",
  "properties": {
    "addr:full":"2225 Broadwater Ave Billings MT 59102",
    "addr:housenumber":"2225",
    "addr:postcode":"59102",
    "addr:street":"Broadwater Ave",
    "iso:country":"US",
    "sg:address":"2225 Broadwater Ave",
    "sg:city":"Billings",
    "sg:classifiers":[
        {
            "category":"Health Services",
            "subcategory":"Doctor",
            "type":"Services"
        }
    ],
    "sg:phone":"+1 406 652 3031",
    "sg:postcode":"59102",
    "sg:province":"MT",
    "sg:tags":[
        "dentist"
    ],
    "wof:name":"Rocky Mountain Dentistry",
    "wof:placetype":"venue"
},
  "geometry": {"coordinates":[-108.57452499999999,45.777005],"type":"Point"}
}