{
  "type": "Feature",
  "properties": {
    "addr:full":"1121 E. Broadway Suite 143A Missoula MT 59802",
    "addr:housenumber":"1121",
    "addr:postcode":"59802",
    "addr:street":"E. Broadway Suite 143A",
    "iso:country":"US",
    "sg:address":"1121 E. Broadway Suite 143A",
    "sg:city":"Missoula",
    "sg:classifiers":[
        {
            "category":"Professional",
            "subcategory":"Computer Services",
            "type":"Services"
        }
    ],
    "sg:phone":"+1 800 947 2393",
    "sg:postcode":"59802",
    "sg:province":"MT",
    "sg:tags":[
        "ticketing",
        "social",
        "box-office",
        "donations",
        "venues",
        "events",
        "seating",
        "saas"
    ],
    "sg:website":"http://www.sameskytickets.com",
    "wof:name":"SameSky Tickets",
    "wof:placetype":"venue"
},
  "geometry": {"coordinates":[-113.98057,46.86812],"type":"Point"}
}