{
  "type": "Feature",
  "properties": {
    "addr:full":"111 N Tracy Ave Bozeman MT 59715",
    "addr:housenumber":"111",
    "addr:postcode":"59715",
    "addr:street":"N Tracy Ave",
    "iso:country":"US",
    "sg:address":"111 N Tracy Ave",
    "sg:city":"Bozeman",
    "sg:classifiers":[
        {
            "category":"Professional",
            "subcategory":"Engineering",
            "type":"Services"
        }
    ],
    "sg:phone":"+1 406 586 0277",
    "sg:postcode":"59715",
    "sg:province":"MT",
    "sg:tags":[
        "consulting",
        "engineer"
    ],
    "wof:name":"Thomas Dean & Hoskins Inc",
    "wof:placetype":"venue"
},
  "geometry": {"coordinates":[-111.03731399999999,45.680703],"type":"Point"}
}