{
  "type": "Feature",
  "properties": {
    "addr:full":"2527 1st Ave S Great Falls MT 59401",
    "addr:housenumber":"2527",
    "addr:postcode":"59401",
    "addr:street":"1St Ave S Great",
    "iso:country":"US",
    "sg:address":"2527 1st Ave S",
    "sg:city":"Great Falls",
    "sg:classifiers":[
        {
            "category":"Professional",
            "subcategory":"Management & Consulting",
            "type":"Services"
        }
    ],
    "sg:phone":"+1 406 761 2413",
    "sg:postcode":"59401",
    "sg:province":"MT",
    "sg:tags":[
        "equipment",
        "construction",
        "trailer"
    ],
    "wof:name":"Christofferson Construction",
    "wof:placetype":"venue"
},
  "geometry": {"coordinates":[-111.262917,47.504065],"type":"Point"}
}