{
  "type": "Feature",
  "properties": {
    "iso:country":"US",
    "sg:address":"1848 Grand Ave",
    "sg:city":"Billings",
    "sg:classifiers":[
        {
            "category":"Shopping",
            "subcategory":"Florist",
            "type":"Retail Goods"
        }
    ],
    "sg:phone":"+1 406 652 6960",
    "sg:postcode":"59102",
    "sg:province":"MT",
    "sg:website":"www.magiccityfloral.com",
    "wof:name":"Magic City Floral Inc",
    "wof:placetype":"venue"
},
  "geometry": {"coordinates":[-108.563177,45.783978],"type":"Point"}
}