{
  "type": "Feature",
  "properties": {
    "iso:country":"US",
    "sg:address":"1226 Eastside Hwy",
    "sg:city":"Corvallis",
    "sg:classifiers":[
        {
            "category":"Wholesale",
            "subcategory":"Farm Supplies",
            "type":"Manufacturing & Wholesale Goods"
        }
    ],
    "sg:phone":"+1 406 961 4917",
    "sg:postcode":"59828",
    "sg:province":"MT",
    "wof:name":"Cowpoke Ranch Supply Inc",
    "wof:placetype":"venue"
},
  "geometry": {"coordinates":[-114.11368400000001,46.319998],"type":"Point"}
}