{
  "type": "Feature",
  "properties": {
    "iso:country":"US",
    "sg:address":"91 W Southview Ave",
    "sg:city":"Belgrade",
    "sg:classifiers":[
        {
            "category":"Professional",
            "subcategory":"Business Services",
            "type":"Services"
        }
    ],
    "sg:phone":"+1 406 388 6701",
    "sg:postcode":"59714",
    "sg:province":"MT",
    "wof:name":"Career Transition",
    "wof:placetype":"venue"
},
  "geometry": {"coordinates":[-111.173856,45.779306],"type":"Point"}
}