{
  "type": "Feature",
  "properties": {
    "iso:country":"US",
    "sg:address":"686 Lost Creek Dr",
    "sg:city":"Kalispell",
    "sg:classifiers":[
        {
            "category":"Building & Trades",
            "subcategory":"Construction",
            "type":"Services"
        }
    ],
    "sg:phone":"+1 406 755 1186",
    "sg:postcode":"59901",
    "sg:province":"MT",
    "sg:tags":[
        "lot",
        "maintenance",
        "parking"
    ],
    "wof:name":"Jem Services Inc",
    "wof:placetype":"venue"
},
  "geometry": {"coordinates":[-114.426284,48.298138],"type":"Point"}
}