{
  "type": "Feature",
  "properties": {
    "addr:full":"613 S Atlantic St Dillon MT 59725",
    "addr:housenumber":"613",
    "addr:postcode":"59725",
    "addr:street":"S Atlantic St",
    "iso:country":"US",
    "sg:address":"613 S Atlantic St",
    "sg:city":"Dillon",
    "sg:classifiers":[
        {
            "category":"Ice Cream",
            "type":"Food & Drink"
        }
    ],
    "sg:menulink":"http://www.allmenus.com/mt/dillon/167591-dairy-queen/menu/",
    "sg:phone":"+1 406 683 2104",
    "sg:postcode":"59725",
    "sg:province":"MT",
    "sg:tags":[
        "burger",
        "american"
    ],
    "wof:name":"Dairy Queen",
    "wof:placetype":"venue"
},
  "geometry": {"coordinates":[-112.638643,45.211297],"type":"Point"}
}