{
  "type": "Feature",
  "properties": {
    "iso:country":"US",
    "sg:address":"120 N Parkmont",
    "sg:city":"Butte",
    "sg:classifiers":[
        {
            "category":"Professional",
            "subcategory":"Management & Consulting",
            "type":"Services"
        }
    ],
    "sg:phone":"+1 406 494 5119",
    "sg:postcode":"59701",
    "sg:province":"MT",
    "sg:tags":[
        "consultant",
        "mining"
    ],
    "wof:name":"Highland Research Ctr",
    "wof:placetype":"venue"
},
  "geometry": {"coordinates":[-112.510451,45.928353],"type":"Point"}
}