{
  "type": "Feature",
  "properties": {
    "addr:full":"320 Front St Wolf Point MT 59201",
    "addr:housenumber":"320",
    "addr:postcode":"59201",
    "addr:street":"Front St Wolf Point",
    "iso:country":"US",
    "sg:address":"320 Front St",
    "sg:city":"Wolf Point",
    "sg:classifiers":[
        {
            "category":"Travel",
            "subcategory":"Travel Agent",
            "type":"Entertainment"
        }
    ],
    "sg:phone":"+1 406 653 2350",
    "sg:postcode":"59201",
    "sg:province":"MT",
    "sg:tags":[
        "railroad",
        "ticket",
        "sales"
    ],
    "wof:name":"Amtrak",
    "wof:placetype":"venue"
},
  "geometry": {"coordinates":[-105.641563,48.091247],"type":"Point"}
}