{
  "type": "Feature",
  "properties": {
    "iso:country":"US",
    "sg:address":"1997 Nye Rd",
    "sg:city":"Fishtail",
    "sg:classifiers":[
        {
            "category":"Food & Beverages",
            "subcategory":"Groceries & Convenience Stores",
            "type":"Retail Goods"
        }
    ],
    "sg:phone":"+1 406 328 6262",
    "sg:postcode":"59028",
    "sg:province":"MT",
    "wof:name":"Nye Trading Post",
    "wof:placetype":"venue"
},
  "geometry": {"coordinates":[-109.803898,45.435441],"type":"Point"}
}