{
  "type": "Feature",
  "properties": {
    "addr:full":"908 Rainbow Ridge Rd Hamilton MT 59840",
    "addr:housenumber":"908",
    "addr:postcode":"59840",
    "addr:street":"Rainbow Ridge Rd",
    "iso:country":"US",
    "sg:address":"908 Rainbow Ridge Rd",
    "sg:city":"Hamilton",
    "sg:classifiers":[
        {
            "category":"Manufacturing",
            "subcategory":"Wood Products",
            "type":"Manufacturing & Wholesale Goods"
        }
    ],
    "sg:phone":"+1 406 363 1511",
    "sg:postcode":"59840",
    "sg:province":"MT",
    "sg:tags":[
        "mfg"
    ],
    "wof:name":"Priest Lake Exotics",
    "wof:placetype":"venue"
},
  "geometry": {"coordinates":[-114.085173,46.18081],"type":"Point"}
}