{
  "type": "Feature",
  "properties": {
    "iso:country":"US",
    "sg:address":"250 Brunner Rd",
    "sg:city":"Columbia Falls",
    "sg:classifiers":[
        {
            "category":"Personal",
            "type":"Services"
        }
    ],
    "sg:phone":"+1 406 892 3249",
    "sg:postcode":"59912",
    "sg:province":"MT",
    "wof:name":"Handyman Stan",
    "wof:placetype":"venue"
},
  "geometry": {"coordinates":[-114.236535,48.341699],"type":"Point"}
}