{
  "type": "Feature",
  "properties": {
    "iso:country":"US",
    "sg:address":"833 Breckenridge St",
    "sg:city":"Helena",
    "sg:classifiers":[
        {
            "category":"Manufacturing",
            "subcategory":"Apparel",
            "type":"Manufacturing & Wholesale Goods"
        }
    ],
    "sg:phone":"+1 406 443 0607",
    "sg:postcode":"59601",
    "sg:province":"MT",
    "sg:tags":[
        "textile",
        "product",
        "fabricated",
        "mfg"
    ],
    "wof:name":"Invisible Ink LLC",
    "wof:placetype":"venue"
},
  "geometry": {"coordinates":[-112.026168,46.58517],"type":"Point"}
}