{
  "type": "Feature",
  "properties": {
    "addr:full":"3303 Seitz Ronan Rd Laurel MT 59044",
    "addr:housenumber":"3303",
    "addr:postcode":"59044",
    "addr:street":"Seitz Ronan Rd",
    "iso:country":"US",
    "sg:address":"3303 Seitz Ronan Rd",
    "sg:city":"Laurel",
    "sg:classifiers":[
        {
            "category":"Manufacturing",
            "subcategory":"Toys & Sporting Goods",
            "type":"Manufacturing & Wholesale Goods"
        }
    ],
    "sg:phone":"+1 406 656 8006",
    "sg:postcode":"59044",
    "sg:province":"MT",
    "sg:tags":[
        "craft"
    ],
    "wof:name":"Crafters Home",
    "wof:placetype":"venue"
},
  "geometry": {"coordinates":[-108.719983,45.70945],"type":"Point"}
}