{
  "type": "Feature",
  "properties": {
    "iso:country":"US",
    "sg:address":"238 1st Ave N",
    "sg:city":"Glasgow",
    "sg:classifiers":[
        {
            "category":"Travel",
            "subcategory":"Hotels & Motels",
            "type":"Entertainment"
        }
    ],
    "sg:phone":"+1 406 228 9311",
    "sg:postcode":"59230",
    "sg:province":"MT",
    "wof:name":"LA Casa Motel",
    "wof:placetype":"venue"
},
  "geometry": {"coordinates":[-106.63136900000001,48.195548],"type":"Point"}
}