{
  "type": "Feature",
  "properties": {
    "iso:country":"US",
    "sg:address":"523 Main St",
    "sg:city":"Stevensville",
    "sg:classifiers":[
        {
            "category":"Home & Garden",
            "subcategory":"Building Materials",
            "type":"Retail Goods"
        }
    ],
    "sg:phone":"+1 406 777 2521",
    "sg:postcode":"59870",
    "sg:province":"MT",
    "sg:tags":[
        "door"
    ],
    "wof:name":"Snowcrest Out Door Products",
    "wof:placetype":"venue"
},
  "geometry": {"coordinates":[-114.09385899999999,46.50659],"type":"Point"}
}