{
  "type": "Feature",
  "properties": {
    "iso:country":"US",
    "sg:address":"730 Main St",
    "sg:city":"Billings",
    "sg:classifiers":[
        {
            "category":"Home & Garden",
            "subcategory":"Building Materials",
            "type":"Retail Goods"
        }
    ],
    "sg:phone":"+1 406 252 1643",
    "sg:postcode":"59105",
    "sg:province":"MT",
    "sg:tags":[
        "paint"
    ],
    "wof:name":"Sherwin-Williams Paints",
    "wof:placetype":"venue"
},
  "geometry": {"coordinates":[-108.471079,45.812808],"type":"Point"}
}