{
  "type": "Feature",
  "properties": {
    "iso:country":"US",
    "sg:address":"504 Grand Ave",
    "sg:city":"Billings",
    "sg:classifiers":[
        {
            "category":"Wholesale",
            "subcategory":"Machinery & Supplies",
            "type":"Manufacturing & Wholesale Goods"
        },
        {
            "category":"Shopping",
            "type":"Retail Goods"
        }
    ],
    "sg:phone":"+1 406 248 1122",
    "sg:postcode":"59101",
    "sg:province":"MT",
    "sg:tags":[
        "repair",
        "printer",
        "laser",
        "photocopy",
        "machine",
        "printing"
    ],
    "wof:name":"Benedict's Imaging Products &",
    "wof:placetype":"venue"
},
  "geometry": {"coordinates":[-108.530468,45.78393],"type":"Point"}
}