{
  "type": "Feature",
  "properties": {
    "addr:full":"638 W Center St Kalispell MT 59901",
    "addr:housenumber":"638",
    "addr:postcode":"59901",
    "addr:street":"W Center St",
    "iso:country":"US",
    "sg:address":"638 W Center St",
    "sg:city":"Kalispell",
    "sg:classifiers":[
        {
            "category":"Autos & Motor Vehicles",
            "subcategory":"Automobile Sales",
            "type":"Retail Goods"
        }
    ],
    "sg:phone":"+1 406 756 1008",
    "sg:postcode":"59901",
    "sg:province":"MT",
    "sg:tags":[
        "car",
        "dealer"
    ],
    "wof:name":"Kris' Auto's",
    "wof:placetype":"venue"
},
  "geometry": {"coordinates":[-114.32301699999999,48.197135],"type":"Point"}
}