{
  "type": "Feature",
  "properties": {
    "iso:country":"US",
    "sg:address":"384 Bear Creek Rd",
    "sg:city":"Victor",
    "sg:classifiers":[
        {
            "category":"Building & Trades",
            "subcategory":"Construction",
            "type":"Services"
        }
    ],
    "sg:phone":"+1 406 642 9533",
    "sg:postcode":"59875",
    "sg:province":"MT",
    "sg:tags":[
        "contractor"
    ],
    "wof:name":"Garber Construction",
    "wof:placetype":"venue"
},
  "geometry": {"coordinates":[-114.15715299999999,46.371004],"type":"Point"}
}