{
  "type": "Feature",
  "properties": {
    "addr:full":"2181 US Hwy 2 E Kalispell MT 59901",
    "addr:housenumber":"2181",
    "addr:postcode":"59901",
    "addr:street":"Us Hwy 2 E",
    "iso:country":"US",
    "sg:address":"2181 US Hwy 2 E",
    "sg:city":"Kalispell",
    "sg:classifiers":[
        {
            "category":"Shopping",
            "subcategory":"Jewelry",
            "type":"Retail Goods"
        }
    ],
    "sg:phone":"+1 406 752 7464",
    "sg:postcode":"59901",
    "sg:province":"MT",
    "wof:name":"Sargents Jewelry",
    "wof:placetype":"venue"
},
  "geometry": {"coordinates":[-114.27696400000001,48.22346],"type":"Point"}
}