{
  "type": "Feature",
  "properties": {
    "iso:country":"US",
    "sg:address":"838 Lewis Ave",
    "sg:city":"Billings",
    "sg:classifiers":[
        {
            "category":"Building & Trades",
            "subcategory":"Cleaning & Sanitation",
            "type":"Services"
        }
    ],
    "sg:phone":"+1 406 252 0465",
    "sg:postcode":"59101",
    "sg:province":"MT",
    "sg:tags":[
        "butler",
        "maid"
    ],
    "wof:name":"Brogan Maid Svc Inc",
    "wof:placetype":"venue"
},
  "geometry": {"coordinates":[-108.537791,45.780598],"type":"Point"}
}