{
  "type": "Feature",
  "properties": {
    "iso:country":"US",
    "sg:address":"6720 Linda Vista Blvd",
    "sg:city":"Missoula",
    "sg:classifiers":[
        {
            "category":"Professional",
            "subcategory":"Management & Consulting",
            "type":"Services"
        }
    ],
    "sg:phone":"+1 406 251 4232",
    "sg:postcode":"59803",
    "sg:province":"MT",
    "sg:tags":[
        "business"
    ],
    "wof:name":"Information Consulting",
    "wof:placetype":"venue"
},
  "geometry": {"coordinates":[-114.05686,46.807853],"type":"Point"}
}