{
  "type": "Feature",
  "properties": {
    "addr:full":"5562 Alloy S Missoula MT 59808",
    "addr:housenumber":"5562",
    "addr:postcode":"59808",
    "addr:street":"Alloy S",
    "iso:country":"US",
    "sg:address":"5562 Alloy S",
    "sg:city":"Missoula",
    "sg:classifiers":[
        {
            "category":"Professional",
            "subcategory":"Research",
            "type":"Services"
        }
    ],
    "sg:phone":"+1 406 728 7755",
    "sg:postcode":"59808",
    "sg:province":"MT",
    "sg:tags":[
        "environmental",
        "ecological"
    ],
    "sg:website":"www.mcs-environmental.com",
    "wof:name":"MCS Environmental Inc",
    "wof:placetype":"venue"
},
  "geometry": {"coordinates":[-114.082352,46.923314],"type":"Point"}
}