{
  "type": "Feature",
  "properties": {
    "iso:country":"US",
    "sg:address":"8522 Nash Rd",
    "sg:city":"Bozeman",
    "sg:classifiers":[
        {
            "category":"Real Estate",
            "subcategory":"Real Estate Operator",
            "type":"Services"
        }
    ],
    "sg:phone":"+1 406 587 2822",
    "sg:postcode":"59715",
    "sg:province":"MT",
    "sg:tags":[
        "building",
        "nonresidential"
    ],
    "wof:name":"Nash Properties LLC",
    "wof:placetype":"venue"
},
  "geometry": {"coordinates":[-111.035428,45.60568],"type":"Point"}
}