{
  "type": "Feature",
  "properties": {
    "iso:country":"US",
    "sg:address":"1313 W Park St",
    "sg:city":"Livingston",
    "sg:classifiers":[
        {
            "category":"Health Services",
            "subcategory":"Clinic",
            "type":"Services"
        }
    ],
    "sg:phone":"+1 406 222 4189",
    "sg:postcode":"59047",
    "sg:province":"MT",
    "sg:tags":[
        "executive",
        "specialty",
        "outpatient"
    ],
    "wof:name":"Well Child Clinic",
    "wof:placetype":"venue"
},
  "geometry": {"coordinates":[-110.571935,45.651142],"type":"Point"}
}