{
  "type": "Feature",
  "properties": {
    "iso:country":"US",
    "sg:address":"941 Center St",
    "sg:city":"Havre",
    "sg:phone":"+1 406 265 8139",
    "sg:postcode":"59501",
    "sg:province":"MT",
    "sg:tags":[
        "farm",
        "wheat"
    ],
    "wof:name":"R Scheuerman",
    "wof:placetype":"venue"
},
  "geometry": {"coordinates":[-109.66866,48.545507],"type":"Point"}
}