{
  "type": "Feature",
  "properties": {
    "addr:full":"109 W River Ln Glendive MT 59330",
    "addr:housenumber":"109",
    "addr:postcode":"59330",
    "addr:street":"W River Ln",
    "iso:country":"US",
    "sg:address":"109 W River Ln",
    "sg:city":"Glendive",
    "sg:classifiers":[
        {
            "category":"Sports & Exercise",
            "subcategory":"Race Track",
            "type":"Entertainment"
        }
    ],
    "sg:phone":"+1 406 377 5952",
    "sg:postcode":"59330",
    "sg:province":"MT",
    "sg:tags":[
        "operation",
        "racing",
        "or"
    ],
    "wof:name":"Davis Haggerty & LLC Kerchal",
    "wof:placetype":"venue"
},
  "geometry": {"coordinates":[-104.758309,47.095283],"type":"Point"}
}