{
  "type": "Feature",
  "properties": {
    "iso:country":"US",
    "sg:address":"1497 Frank Rd",
    "sg:city":"Belgrade",
    "sg:classifiers":[
        {
            "category":"Building & Trades",
            "subcategory":"Construction",
            "type":"Services"
        }
    ],
    "sg:phone":"+1 406 388 1730",
    "sg:postcode":"59714",
    "sg:province":"MT",
    "sg:tags":[
        "excavating",
        "contractor"
    ],
    "wof:name":"Mike Boylan Excavating Inc",
    "wof:placetype":"venue"
},
  "geometry": {"coordinates":[-111.21653499999999,45.758375],"type":"Point"}
}