{
  "type": "Feature",
  "properties": {
    "iso:country":"US",
    "sg:address":"3821 Wooden Shoe Rd",
    "sg:city":"Manhattan",
    "sg:classifiers":[
        {
            "category":"Farming",
            "subcategory":"Farm",
            "type":"Manufacturing & Wholesale Goods"
        }
    ],
    "sg:phone":"+1 406 284 6446",
    "sg:postcode":"59741",
    "sg:province":"MT",
    "sg:tags":[
        "crop",
        "general"
    ],
    "wof:name":"John N Schutter Jr LLC",
    "wof:placetype":"venue"
},
  "geometry": {"coordinates":[-111.34743899999999,45.801472],"type":"Point"}
}