{
  "type": "Feature",
  "properties": {
    "addr:full":"454 Sahara Dr Billings MT 59105",
    "addr:housenumber":"454",
    "addr:postcode":"59105",
    "addr:street":"Sahara Dr",
    "iso:country":"US",
    "sg:address":"454 Sahara Dr",
    "sg:city":"Billings",
    "sg:classifiers":[
        {
            "category":"Real Estate",
            "subcategory":"Real Estate Operator",
            "type":"Services"
        }
    ],
    "sg:phone":"+1 406 259 6554",
    "sg:postcode":"59105",
    "sg:province":"MT",
    "sg:tags":[
        "management",
        "property",
        "oil"
    ],
    "wof:name":"Hamilton Resource Management",
    "wof:placetype":"venue"
},
  "geometry": {"coordinates":[-108.498503,45.812564],"type":"Point"}
}