{
  "type": "Feature",
  "properties": {
    "addr:full":"1224 Ave F Billings MT 59102",
    "addr:housenumber":"1224",
    "addr:postcode":"59102",
    "addr:street":"Ave F",
    "iso:country":"US",
    "sg:address":"1224 Ave F",
    "sg:city":"Billings",
    "sg:classifiers":[
        {
            "category":"Professional",
            "type":"Services"
        }
    ],
    "sg:phone":"+1 406 245 8526",
    "sg:postcode":"59102",
    "sg:province":"MT",
    "sg:tags":[
        "establishment"
    ],
    "wof:name":"Patti Snyder Designs",
    "wof:placetype":"venue"
},
  "geometry": {"coordinates":[-108.547997,45.788853],"type":"Point"}
}