{
  "type": "Feature",
  "properties": {
    "iso:country":"US",
    "sg:address":"848 Main St",
    "sg:city":"Billings",
    "sg:classifiers":[
        {
            "category":"Organizations",
            "subcategory":"Religious Organization",
            "type":"Services"
        }
    ],
    "sg:phone":"+1 406 256 0203",
    "sg:postcode":"59105",
    "sg:province":"MT",
    "wof:name":"Billings Hts Aliance Church",
    "wof:placetype":"venue"
},
  "geometry": {"coordinates":[-108.470828,45.814545],"type":"Point"}
}