{
  "type": "Feature",
  "properties": {
    "iso:country":"US",
    "sg:address":"1023 E Broadway St",
    "sg:city":"Helena",
    "sg:classifiers":[
        {
            "category":"Education",
            "subcategory":"School",
            "type":"Public Place"
        }
    ],
    "sg:phone":"+1 406 324 2060",
    "sg:postcode":"59601",
    "sg:province":"MT",
    "wof:name":"Jefferson Elementary School",
    "wof:placetype":"venue"
},
  "geometry": {"coordinates":[-112.021935,46.584517],"type":"Point"}
}