{
  "type": "Feature",
  "properties": {
    "addr:full":"1001 SW Higgins Ave Missoula MT 59803",
    "addr:housenumber":"1001",
    "addr:postcode":"59803",
    "addr:street":"Sw Higgins Ave",
    "iso:country":"US",
    "sg:address":"1001 SW Higgins Ave",
    "sg:city":"Missoula",
    "sg:classifiers":[
        {
            "category":"Banks & Credit Unions",
            "subcategory":"Investment Brokerage",
            "type":"Services"
        }
    ],
    "sg:phone":"+1 406 542 4777",
    "sg:postcode":"59803",
    "sg:province":"MT",
    "sg:tags":[
        "counselor"
    ],
    "wof:name":"G J Thayer Companies",
    "wof:placetype":"venue"
},
  "geometry": {"coordinates":[-114.01467,46.834699],"type":"Point"}
}