{
  "type": "Feature",
  "properties": {
    "iso:country":"US",
    "sg:address":"1190 Elk Park Rd",
    "sg:city":"Columbia Falls",
    "sg:classifiers":[
        {
            "category":"Wholesale",
            "subcategory":"Construction Materials",
            "type":"Manufacturing & Wholesale Goods"
        }
    ],
    "sg:phone":"+1 406 755 0212",
    "sg:postcode":"59912",
    "sg:province":"MT",
    "wof:name":"Weaver Gravel Inc",
    "wof:placetype":"venue"
},
  "geometry": {"coordinates":[-114.13291599999999,48.30202],"type":"Point"}
}