{
  "type": "Feature",
  "properties": {
    "iso:country":"US",
    "sg:address":"207 Main St SE",
    "sg:city":"Ronan",
    "sg:classifiers":[
        {
            "category":"Government",
            "subcategory":"Office",
            "type":"Public Place"
        }
    ],
    "sg:phone":"+1 406 676 4231",
    "sg:postcode":"59864",
    "sg:province":"MT",
    "sg:tags":[
        "executive"
    ],
    "wof:name":"City Hall",
    "wof:placetype":"venue"
},
  "geometry": {"coordinates":[-114.094346,47.528649],"type":"Point"}
}