{
  "type": "Feature",
  "properties": {
    "addr:full":"121 5th St SW Sidney MT 59270",
    "addr:housenumber":"121",
    "addr:postcode":"59270",
    "addr:street":"5Th St Sw",
    "iso:country":"US",
    "sg:address":"121 5th St SW",
    "sg:city":"Sidney",
    "sg:classifiers":[
        {
            "category":"Organizations",
            "subcategory":"Professional Association",
            "type":"Services"
        }
    ],
    "sg:phone":"+1 406 433 4080",
    "sg:postcode":"59270",
    "sg:province":"MT",
    "wof:name":"Sidney Cmnty Edcatn Foundation",
    "wof:placetype":"venue"
},
  "geometry": {"coordinates":[-104.160758,47.711875],"type":"Point"}
}