{
  "type": "Feature",
  "properties": {
    "iso:country":"US",
    "sg:address":"234 E Babcock St",
    "sg:city":"Bozeman",
    "sg:classifiers":[
        {
            "category":"Health Services",
            "subcategory":"Hospital",
            "type":"Services"
        }
    ],
    "sg:phone":"+1 406 585 0020",
    "sg:postcode":"59715",
    "sg:province":"MT",
    "sg:tags":[
        "mental"
    ],
    "wof:name":"Sandra L Jackson",
    "wof:placetype":"venue"
},
  "geometry": {"coordinates":[-111.033995,45.678193],"type":"Point"}
}