{
  "type": "Feature",
  "properties": {
    "iso:country":"US",
    "sg:address":"1440 S Central Ave",
    "sg:city":"Sidney",
    "sg:classifiers":[
        {
            "category":"Retail",
            "subcategory":"Auto Rental",
            "type":"Services"
        }
    ],
    "sg:phone":"+1 406 482 5811",
    "sg:postcode":"59270",
    "sg:province":"MT",
    "sg:tags":[
        "renting",
        "truck",
        "leasing"
    ],
    "wof:name":"U-Haul Co",
    "wof:placetype":"venue"
},
  "geometry": {"coordinates":[-104.165755,47.702979],"type":"Point"}
}