{
  "type": "Feature",
  "properties": {
    "iso:country":"US",
    "sg:address":"100 Madison St",
    "sg:city":"Missoula",
    "sg:classifiers":[
        {
            "category":"Restaurant",
            "type":"Food & Drink"
        }
    ],
    "sg:menulink":"http://www.allmenus.com/mt/missoula/5085-finn-and-porter/menu/",
    "sg:phone":"+1 406 542 4660",
    "sg:postcode":"59802",
    "sg:province":"MT",
    "sg:tags":[
        "seafood",
        "american"
    ],
    "wof:name":"Finn and Porter",
    "wof:placetype":"venue"
},
  "geometry": {"coordinates":[-113.987252,46.868951],"type":"Point"}
}