{
  "type": "Feature",
  "properties": {
    "iso:country":"US",
    "sg:address":"1037 Main St",
    "sg:city":"Corvallis",
    "sg:classifiers":[
        {
            "category":"Health Services",
            "subcategory":"Doctor",
            "type":"Services"
        }
    ],
    "sg:phone":"+1 406 961 4661",
    "sg:postcode":"59828",
    "sg:province":"MT",
    "sg:tags":[
        "physician",
        "surgeon"
    ],
    "wof:name":"Corvallis Family Medicine",
    "wof:placetype":"venue"
},
  "geometry": {"coordinates":[-114.115527,46.31506],"type":"Point"}
}