{
  "type": "Feature",
  "properties": {
    "iso:country":"US",
    "sg:address":"2101 Harrison Ave",
    "sg:city":"Butte",
    "sg:classifiers":[
        {
            "category":"Restaurant",
            "type":"Food & Drink"
        }
    ],
    "sg:phone":"+1 406 723 4022",
    "sg:postcode":"59701",
    "sg:province":"MT",
    "sg:tags":[
        "eating"
    ],
    "wof:name":"Little Caesars",
    "wof:placetype":"venue"
},
  "geometry": {"coordinates":[-112.51130499999999,45.991842],"type":"Point"}
}