{
  "type": "Feature",
  "properties": {
    "iso:country":"US",
    "sg:address":"305 S Arizona St",
    "sg:city":"Dillon",
    "sg:classifiers":[
        {
            "category":"Real Estate",
            "subcategory":"Real Estate Agent",
            "type":"Services"
        }
    ],
    "sg:phone":"+1 406 683 2536",
    "sg:postcode":"59725",
    "sg:province":"MT",
    "sg:tags":[
        "appraiser"
    ],
    "wof:name":"KNOX Appraisal Svc",
    "wof:placetype":"venue"
},
  "geometry": {"coordinates":[-112.633473,45.211695],"type":"Point"}
}