{
  "type": "Feature",
  "properties": {
    "addr:full":"318 1st Ave W Sunburst MT 59482",
    "addr:housenumber":"318",
    "addr:postcode":"59482",
    "addr:street":"1St Ave W Sunburst",
    "iso:country":"US",
    "sg:address":"318 1st Ave W",
    "sg:city":"Sunburst",
    "sg:classifiers":[
        {
            "category":"Shopping",
            "subcategory":"Gifts & Souvenirs",
            "type":"Retail Goods"
        }
    ],
    "sg:phone":"+1 406 937 2555",
    "sg:postcode":"59482",
    "sg:province":"MT",
    "sg:tags":[
        "shop"
    ],
    "wof:name":"Bag Ladies",
    "wof:placetype":"venue"
},
  "geometry": {"coordinates":[-111.909595,48.880728],"type":"Point"}
}