{
  "type": "Feature",
  "properties": {
    "iso:country":"US",
    "sg:address":"295 Lost Horse Rd",
    "sg:city":"Hamilton",
    "sg:classifiers":[
        {
            "category":"Manufacturing",
            "subcategory":"Buildings",
            "type":"Manufacturing & Wholesale Goods"
        }
    ],
    "sg:phone":"+1 406 363 2834",
    "sg:postcode":"59840",
    "sg:province":"MT",
    "sg:tags":[
        "home",
        "log",
        "cabin"
    ],
    "wof:name":"Mark Behrman Contracting",
    "wof:placetype":"venue"
},
  "geometry": {"coordinates":[-114.198386,46.120535],"type":"Point"}
}