{
  "type": "Feature",
  "properties": {
    "iso:country":"US",
    "sg:address":"300 1st Ave S",
    "sg:city":"Lewistown",
    "sg:classifiers":[
        {
            "category":"Professional",
            "subcategory":"Employment Agencies",
            "type":"Services"
        }
    ],
    "sg:phone":"+1 406 538 8701",
    "sg:postcode":"59457",
    "sg:province":"MT",
    "sg:tags":[
        "job"
    ],
    "wof:name":"Lewistown Job Service Center",
    "wof:placetype":"venue"
},
  "geometry": {"coordinates":[-109.422987,47.06612],"type":"Point"}
}