{
  "type": "Feature",
  "properties": {
    "addr:full":"501 Main St Ashland MT 59072",
    "addr:housenumber":"501",
    "addr:postcode":"59072",
    "addr:street":"Main St",
    "iso:country":"US",
    "sg:address":"501 Main St",
    "sg:city":"Ashland",
    "sg:classifiers":[
        {
            "category":"Health Services",
            "subcategory":"Doctor",
            "type":"Services"
        }
    ],
    "sg:phone":"+1 406 784 2349",
    "sg:postcode":"59072",
    "sg:province":"MT",
    "sg:tags":[
        "clinic"
    ],
    "wof:name":"Ashland Community Health Ctr",
    "wof:placetype":"venue"
},
  "geometry": {"coordinates":[-108.541904,46.445817],"type":"Point"}
}