{
  "type": "Feature",
  "properties": {
    "iso:country":"US",
    "sg:address":"14 2nd Ave W",
    "sg:city":"Culbertson",
    "sg:classifiers":[
        {
            "category":"Building & Trades",
            "subcategory":"Construction",
            "type":"Services"
        }
    ],
    "sg:phone":"+1 406 787 5324",
    "sg:postcode":"59218",
    "sg:province":"MT",
    "sg:tags":[
        "sewer",
        "contractor"
    ],
    "wof:name":"Montana Hiline Sewer & Culvert",
    "wof:placetype":"venue"
},
  "geometry": {"coordinates":[-104.519658,48.143717],"type":"Point"}
}