{
  "type": "Feature",
  "properties": {
    "iso:country":"US",
    "sg:address":"7102 State Hwy 200",
    "sg:city":"Missoula",
    "sg:classifiers":[
        {
            "category":"Freight",
            "type":"Transportation"
        }
    ],
    "sg:phone":"+1 406 273 2713",
    "sg:postcode":"59808",
    "sg:province":"MT",
    "sg:tags":[
        "commercial",
        "storage"
    ],
    "wof:name":"Last Best Space Mini Storage",
    "wof:placetype":"venue"
},
  "geometry": {"coordinates":[-113.902231,46.879914],"type":"Point"}
}