{
  "type": "Feature",
  "properties": {
    "iso:country":"US",
    "sg:address":"439 Fairmont Rd",
    "sg:city":"Kalispell",
    "sg:classifiers":[
        {
            "category":"Farming",
            "subcategory":"Farm",
            "type":"Manufacturing & Wholesale Goods"
        }
    ],
    "sg:phone":"+1 406 756 6340",
    "sg:postcode":"59901",
    "sg:province":"MT",
    "sg:tags":[
        "crop",
        "general"
    ],
    "wof:name":"Brad Gorton",
    "wof:placetype":"venue"
},
  "geometry": {"coordinates":[-114.223084,48.202193],"type":"Point"}
}