{
  "type": "Feature",
  "properties": {
    "addr:full":"842 Steffanich Dr Billings MT 59105",
    "addr:housenumber":"842",
    "addr:postcode":"59105",
    "addr:street":"Steffanich Dr",
    "iso:country":"US",
    "sg:address":"842 Steffanich Dr",
    "sg:city":"Billings",
    "sg:classifiers":[
        {
            "category":"Manufacturing",
            "subcategory":"Glass & Minerals",
            "type":"Manufacturing & Wholesale Goods"
        }
    ],
    "sg:phone":"+1 406 861 4619",
    "sg:postcode":"59105",
    "sg:province":"MT",
    "sg:tags":[
        "concrete",
        "brick",
        "prod",
        "block"
    ],
    "wof:name":"Aspen Curbing & Landscaping",
    "wof:placetype":"venue"
},
  "geometry": {"coordinates":[-108.465317,45.821054],"type":"Point"}
}