{
  "type": "Feature",
  "properties": {
    "iso:country":"US",
    "sg:address":"104 N 2nd St",
    "sg:city":"Livingston",
    "sg:classifiers":[
        {
            "category":"Restaurant",
            "type":"Food & Drink"
        }
    ],
    "sg:phone":"+1 406 222 1200",
    "sg:postcode":"59047",
    "sg:province":"MT",
    "sg:tags":[
        "eating"
    ],
    "wof:name":"Coffee Crossing",
    "wof:placetype":"venue"
},
  "geometry": {"coordinates":[-110.561742,45.661427],"type":"Point"}
}