{
  "type": "Feature",
  "properties": {
    "addr:full":"2025 Webster Ln Dillon MT 59725",
    "addr:housenumber":"2025",
    "addr:postcode":"59725",
    "addr:street":"Webster Ln",
    "iso:country":"US",
    "sg:address":"2025 Webster Ln",
    "sg:city":"Dillon",
    "sg:classifiers":[
        {
            "category":"Building & Trades",
            "subcategory":"Construction",
            "type":"Services"
        }
    ],
    "sg:phone":"+1 406 683 4039",
    "sg:postcode":"59725",
    "sg:province":"MT",
    "sg:tags":[
        "house"
    ],
    "wof:name":"Jim Allen Construction",
    "wof:placetype":"venue"
},
  "geometry": {"coordinates":[-112.616756,45.254783],"type":"Point"}
}