{
  "type": "Feature",
  "properties": {
    "iso:country":"US",
    "sg:address":"415 State St",
    "sg:city":"Hamilton",
    "sg:classifiers":[
        {
            "category":"Personal",
            "type":"Services"
        }
    ],
    "sg:phone":"+1 406 375 0220",
    "sg:postcode":"59840",
    "sg:province":"MT",
    "sg:tags":[
        "therapist",
        "massage"
    ],
    "wof:name":"Rosewood Wellness Ctr",
    "wof:placetype":"venue"
},
  "geometry": {"coordinates":[-114.160116,46.2457],"type":"Point"}
}