{
  "type": "Feature",
  "properties": {
    "addr:full":"86 3rd Ave E Three Forks MT 59752",
    "addr:housenumber":"86",
    "addr:postcode":"59752",
    "addr:street":"3Rd Ave E Three",
    "iso:country":"US",
    "sg:address":"86 3rd Ave E",
    "sg:city":"Three Forks",
    "sg:classifiers":[
        {
            "category":"Professional",
            "subcategory":"Management & Consulting",
            "type":"Services"
        }
    ],
    "sg:phone":"+1 406 388 1977",
    "sg:postcode":"59752",
    "sg:province":"MT",
    "wof:name":"Marys Natural Alternatives",
    "wof:placetype":"venue"
},
  "geometry": {"coordinates":[-111.548044,45.894203],"type":"Point"}
}