{
  "type": "Feature",
  "properties": {
    "iso:country":"US",
    "sg:address":"22 Cedar Lake Dr",
    "sg:city":"Butte",
    "sg:classifiers":[
        {
            "category":"Building & Trades",
            "subcategory":"Construction",
            "type":"Services"
        }
    ],
    "sg:phone":"+1 406 494 4097",
    "sg:postcode":"59701",
    "sg:province":"MT",
    "sg:tags":[
        "general",
        "contractor"
    ],
    "wof:name":"Dwyer Construction",
    "wof:placetype":"venue"
},
  "geometry": {"coordinates":[-112.482091,45.967118],"type":"Point"}
}