{
  "type": "Feature",
  "properties": {
    "iso:country":"US",
    "sg:address":"402 3rd St",
    "sg:city":"Havre",
    "sg:classifiers":[
        {
            "category":"Education",
            "subcategory":"Library",
            "type":"Public Place"
        }
    ],
    "sg:phone":"+1 406 265 2123",
    "sg:postcode":"59501",
    "sg:province":"MT",
    "wof:name":"Havre-Hill County Library",
    "wof:placetype":"venue"
},
  "geometry": {"coordinates":[-109.676941,48.551231],"type":"Point"}
}