{
  "type": "Feature",
  "properties": {
    "iso:country":"US",
    "sg:address":"1016 Mooring Rd",
    "sg:city":"Columbia Falls",
    "sg:classifiers":[
        {
            "category":"Building & Trades",
            "subcategory":"Cleaning & Sanitation",
            "type":"Services"
        }
    ],
    "sg:phone":"+1 406 892 0800",
    "sg:postcode":"59912",
    "sg:province":"MT",
    "sg:tags":[
        "janitorial"
    ],
    "wof:name":"Rita Willcut",
    "wof:placetype":"venue"
},
  "geometry": {"coordinates":[-114.154166,48.286313],"type":"Point"}
}