{
  "type": "Feature",
  "properties": {
    "iso:country":"US",
    "sg:address":"9105 Thorpe Rd",
    "sg:city":"Bozeman",
    "sg:classifiers":[
        {
            "category":"Bars & Pubs",
            "type":"Food & Drink"
        }
    ],
    "sg:phone":"+1 406 388 0148",
    "sg:postcode":"59718",
    "sg:province":"MT",
    "sg:tags":[
        "hotel",
        "bar"
    ],
    "wof:name":"Gallatin River Lodge",
    "wof:placetype":"venue"
},
  "geometry": {"coordinates":[-111.20602,45.723332],"type":"Point"}
}