{
  "type": "Feature",
  "properties": {
    "iso:country":"US",
    "sg:address":"286 Buffalo Hill Dr",
    "sg:city":"Kalispell",
    "sg:classifiers":[
        {
            "category":"Professional",
            "subcategory":"Business Services",
            "type":"Services"
        }
    ],
    "sg:phone":"+1 406 844 3480",
    "sg:postcode":"59901",
    "sg:province":"MT",
    "wof:name":"R Thompson Farms LLC",
    "wof:placetype":"venue"
},
  "geometry": {"coordinates":[-114.321077,48.211578],"type":"Point"}
}