{
  "type": "Feature",
  "properties": {
    "iso:country":"US",
    "sg:address":"127 W Main St",
    "sg:city":"Hamilton",
    "sg:classifiers":[
        {
            "category":"Insurance",
            "subcategory":"Insurance Agent",
            "type":"Services"
        }
    ],
    "sg:phone":"+1 406 363 1116",
    "sg:postcode":"59840",
    "sg:province":"MT",
    "wof:name":"Weeks Insurance",
    "wof:placetype":"venue"
},
  "geometry": {"coordinates":[-114.155885,46.247021],"type":"Point"}
}