{
  "type": "Feature",
  "properties": {
    "iso:country":"US",
    "sg:address":"715 Vaughn South Frontage Rd",
    "sg:city":"Great Falls",
    "sg:classifiers":[
        {
            "category":"Freight",
            "type":"Transportation"
        }
    ],
    "sg:phone":"+1 406 454 3898",
    "sg:postcode":"59404",
    "sg:province":"MT",
    "sg:tags":[
        "operator",
        "local",
        "trucking"
    ],
    "wof:name":"C&L Trucking",
    "wof:placetype":"venue"
},
  "geometry": {"coordinates":[-111.397347,47.526265],"type":"Point"}
}