{
  "type": "Feature",
  "properties": {
    "iso:country":"US",
    "sg:address":"444 S 24th St W",
    "sg:city":"Billings",
    "sg:classifiers":[
        {
            "category":"Recreation",
            "type":"Entertainment"
        }
    ],
    "sg:phone":"+1 406 656 3991",
    "sg:postcode":"59102",
    "sg:province":"MT",
    "sg:tags":[
        "casino"
    ],
    "wof:name":"Riverboat Casino & Dining",
    "wof:placetype":"venue"
},
  "geometry": {"coordinates":[-108.576208,45.76237],"type":"Point"}
}