{
  "type": "Feature",
  "properties": {
    "iso:country":"US",
    "sg:address":"3940 1st Ave S",
    "sg:city":"Billings",
    "sg:classifiers":[
        {
            "category":"Autos & Motor Vehicles",
            "subcategory":"Automobile Sales",
            "type":"Retail Goods"
        }
    ],
    "sg:phone":"+1 406 238 0330",
    "sg:postcode":"59101",
    "sg:province":"MT",
    "sg:tags":[
        "car",
        "dealer"
    ],
    "wof:name":"A 1 Auto Sales",
    "wof:placetype":"venue"
},
  "geometry": {"coordinates":[-108.517438,45.772578],"type":"Point"}
}