{
  "type": "Feature",
  "properties": {
    "addr:full":"134 Regal St Billings MT 59101",
    "addr:housenumber":"134",
    "addr:postcode":"59101",
    "addr:street":"Regal St",
    "iso:country":"US",
    "sg:address":"134 Regal St",
    "sg:city":"Billings",
    "sg:classifiers":[
        {
            "category":"Professional",
            "subcategory":"Management & Consulting",
            "type":"Services"
        }
    ],
    "sg:phone":"+1 406 245 0041",
    "sg:postcode":"59101",
    "sg:province":"MT",
    "sg:tags":[
        "retail",
        "direct",
        "sales"
    ],
    "wof:name":"Culligan",
    "wof:placetype":"venue"
},
  "geometry": {"coordinates":[-108.553481,45.768131],"type":"Point"}
}