{
  "type": "Feature",
  "properties": {
    "addr:full":"830 Reeves Ln Hamilton MT 59840",
    "addr:housenumber":"830",
    "addr:postcode":"59840",
    "addr:street":"Reeves Ln",
    "iso:country":"US",
    "sg:address":"830 Reeves Ln",
    "sg:city":"Hamilton",
    "sg:classifiers":[
        {
            "category":"Retail",
            "subcategory":"Repair Shop",
            "type":"Services"
        },
        {
            "category":"Building & Trades",
            "subcategory":"Construction",
            "type":"Services"
        }
    ],
    "sg:phone":"+1 406 375 0226",
    "sg:postcode":"59840",
    "sg:province":"MT",
    "sg:tags":[
        "ironwork",
        "contractor"
    ],
    "wof:name":"Theodore A Docteur Inc",
    "wof:placetype":"venue"
},
  "geometry": {"coordinates":[-114.09128200000001,46.195132],"type":"Point"}
}