{
  "type": "Feature",
  "properties": {
    "iso:country":"US",
    "sg:address":"120 2nd St E",
    "sg:city":"Kalispell",
    "sg:classifiers":[
        {
            "category":"Professional",
            "subcategory":"Computer Services",
            "type":"Services"
        }
    ],
    "sg:phone":"+1 406 755 0716",
    "sg:postcode":"59901",
    "sg:province":"MT",
    "sg:tags":[
        "design",
        "system",
        "programing",
        "custom"
    ],
    "wof:name":"Digital I O",
    "wof:placetype":"venue"
},
  "geometry": {"coordinates":[-114.31024499999999,48.197185],"type":"Point"}
}