{
  "type": "Feature",
  "properties": {
    "iso:country":"US",
    "sg:address":"38 Tebay Ln",
    "sg:city":"Whitehall",
    "sg:classifiers":[
        {
            "category":"Building & Trades",
            "subcategory":"Construction",
            "type":"Services"
        }
    ],
    "sg:phone":"+1 406 591 2787",
    "sg:postcode":"59759",
    "sg:province":"MT",
    "sg:tags":[
        "excavation",
        "landscaping",
        "contractor"
    ],
    "wof:name":"Tebay Contracting Services",
    "wof:placetype":"venue"
},
  "geometry": {"coordinates":[-112.012781,45.869646],"type":"Point"}
}