{
  "type": "Feature",
  "properties": {
    "iso:country":"US",
    "sg:address":"520 W Main St",
    "sg:city":"Lewistown",
    "sg:classifiers":[
        {
            "category":"Insurance",
            "subcategory":"Insurance Agent",
            "type":"Services"
        }
    ],
    "sg:phone":"+1 406 538 5458",
    "sg:postcode":"59457",
    "sg:province":"MT",
    "wof:name":"Lewistown Insurance",
    "wof:placetype":"venue"
},
  "geometry": {"coordinates":[-109.428917,47.063558],"type":"Point"}
}