{
  "type": "Feature",
  "properties": {
    "iso:country":"US",
    "sg:address":"3003 State Hwy 200",
    "sg:city":"Trout Creek",
    "sg:classifiers":[
        {
            "category":"Retail",
            "subcategory":"Auto Repair",
            "type":"Services"
        }
    ],
    "sg:phone":"+1 406 827 4594",
    "sg:postcode":"59874",
    "sg:province":"MT",
    "sg:tags":[
        "body",
        "automobile",
        "painting"
    ],
    "wof:name":"M Ontana-Pathways",
    "wof:placetype":"venue"
},
  "geometry": {"coordinates":[-115.614198,47.856757],"type":"Point"}
}