{
  "type": "Feature",
  "properties": {
    "iso:country":"US",
    "sg:address":"1107 Gerald Ave",
    "sg:city":"Missoula",
    "sg:classifiers":[
        {
            "category":"Organizations",
            "subcategory":"Community Association",
            "type":"Services"
        }
    ],
    "sg:phone":"+1 406 543 3623",
    "sg:postcode":"59801",
    "sg:province":"MT",
    "wof:name":"Alpha PHI Inc",
    "wof:placetype":"venue"
},
  "geometry": {"coordinates":[-113.99585999999999,46.860139],"type":"Point"}
}