{
  "type": "Feature",
  "properties": {
    "addr:full":"221 5th St S Glasgow MT 59230",
    "addr:housenumber":"221",
    "addr:postcode":"59230",
    "addr:street":"5Th St S",
    "iso:country":"US",
    "sg:address":"221 5th St S",
    "sg:city":"Glasgow",
    "sg:classifiers":[
        {
            "category":"Health Services",
            "subcategory":"Doctor",
            "type":"Services"
        }
    ],
    "sg:phone":"+1 406 228 4391",
    "sg:postcode":"59230",
    "sg:province":"MT",
    "sg:tags":[
        "medical",
        "clinic"
    ],
    "wof:name":"Glasgow Clinic PC",
    "wof:placetype":"venue"
},
  "geometry": {"coordinates":[-106.636909,48.193788],"type":"Point"}
}