{
  "type": "Feature",
  "properties": {
    "iso:country":"US",
    "sg:address":"4515 Rimrock Rd",
    "sg:city":"Billings",
    "sg:classifiers":[
        {
            "category":"Building & Trades",
            "subcategory":"Construction",
            "type":"Services"
        }
    ],
    "sg:phone":"+1 406 651 0011",
    "sg:postcode":"59106",
    "sg:province":"MT",
    "sg:tags":[
        "asbestos",
        "removal"
    ],
    "wof:name":"Safetech Inc",
    "wof:placetype":"venue"
},
  "geometry": {"coordinates":[-108.627983,45.798777],"type":"Point"}
}