{
  "type": "Feature",
  "properties": {
    "iso:country":"US",
    "sg:address":"4221 Wells Pl",
    "sg:city":"Billings",
    "sg:classifiers":[
        {
            "category":"Building & Trades",
            "subcategory":"Plumbing",
            "type":"Services"
        }
    ],
    "sg:phone":"+1 406 655 9240",
    "sg:postcode":"59106",
    "sg:province":"MT",
    "sg:tags":[
        "contractor"
    ],
    "wof:name":"Precision Plumbing & Heating",
    "wof:placetype":"venue"
},
  "geometry": {"coordinates":[-108.62587000000001,45.772199],"type":"Point"}
}