{
  "type": "Feature",
  "properties": {
    "iso:country":"US",
    "sg:address":"312 Prickett Ln",
    "sg:city":"Billings",
    "sg:classifiers":[
        {
            "category":"Manufacturing",
            "subcategory":"Metals",
            "type":"Manufacturing & Wholesale Goods"
        }
    ],
    "sg:phone":"+1 406 248 3797",
    "sg:postcode":"59101",
    "sg:province":"MT",
    "sg:tags":[
        "coating",
        "powder"
    ],
    "wof:name":"MATKINS",
    "wof:placetype":"venue"
},
  "geometry": {"coordinates":[-108.53971300000001,45.769354],"type":"Point"}
}