{
  "type": "Feature",
  "properties": {
    "iso:country":"US",
    "sg:address":"3936 Ave B",
    "sg:city":"Billings",
    "sg:classifiers":[
        {
            "category":"Professional",
            "subcategory":"Lawyer & Legal Services",
            "type":"Services"
        }
    ],
    "sg:phone":"+1 406 252 6656",
    "sg:postcode":"59102",
    "sg:province":"MT",
    "sg:tags":[
        "attorney"
    ],
    "wof:name":"Robert C Smith Law Offices",
    "wof:placetype":"venue"
},
  "geometry": {"coordinates":[-108.61754000000001,45.785614],"type":"Point"}
}