{
  "type": "Feature",
  "properties": {
    "addr:full":"405 22nd Ave W Polson MT 59860",
    "addr:housenumber":"405",
    "addr:postcode":"59860",
    "addr:street":"22Nd Ave W",
    "iso:country":"US",
    "sg:address":"405 22nd Ave W",
    "sg:city":"Polson",
    "sg:classifiers":[
        {
            "category":"Building & Trades",
            "subcategory":"Cleaning & Sanitation",
            "type":"Services"
        }
    ],
    "sg:phone":"+1 406 883 4050",
    "sg:postcode":"59860",
    "sg:province":"MT",
    "sg:tags":[
        "maintenance"
    ],
    "wof:name":"Villegas Jantr Crpt Cleang Svc",
    "wof:placetype":"venue"
},
  "geometry": {"coordinates":[-114.16937,47.67508],"type":"Point"}
}