{
  "type": "Feature",
  "properties": {
    "iso:country":"US",
    "sg:address":"47 W Park St",
    "sg:city":"Butte",
    "sg:classifiers":[
        {
            "category":"Shopping",
            "subcategory":"Gifts & Souvenirs",
            "type":"Retail Goods"
        }
    ],
    "sg:phone":"+1 406 723 8690",
    "sg:postcode":"59701",
    "sg:province":"MT",
    "wof:name":"Wouldnt It Be Great",
    "wof:placetype":"venue"
},
  "geometry": {"coordinates":[-112.536621,46.012815],"type":"Point"}
}