{
  "type": "Feature",
  "properties": {
    "iso:country":"US",
    "sg:address":"119 W Main St",
    "sg:city":"Lewistown",
    "sg:classifiers":[
        {
            "category":"Shopping",
            "type":"Retail Goods"
        }
    ],
    "sg:phone":"+1 406 538 9868",
    "sg:postcode":"59457",
    "sg:province":"MT",
    "sg:tags":[
        "spa",
        "hot",
        "tub"
    ],
    "wof:name":"Big Spring Spas",
    "wof:placetype":"venue"
},
  "geometry": {"coordinates":[-109.424735,47.066195],"type":"Point"}
}