{
  "type": "Feature",
  "properties": {
    "iso:country":"US",
    "sg:address":"200 N Oregon St",
    "sg:city":"Dillon",
    "sg:classifiers":[
        {
            "category":"Health Services",
            "subcategory":"Nursing And Care Facility",
            "type":"Services"
        }
    ],
    "sg:phone":"+1 406 683 5105",
    "sg:postcode":"59725",
    "sg:province":"MT",
    "sg:tags":[
        "hospital",
        "skilled",
        "specialty"
    ],
    "wof:name":"Parkview Acres Care/Rehb CNT",
    "wof:placetype":"venue"
},
  "geometry": {"coordinates":[-112.62392,45.212983],"type":"Point"}
}