{
  "type": "Feature",
  "properties": {
    "iso:country":"US",
    "sg:address":"105 Coclet Ln",
    "sg:city":"Kalispell",
    "sg:classifiers":[
        {
            "category":"Retail",
            "subcategory":"Auto Repair",
            "type":"Services"
        }
    ],
    "sg:phone":"+1 406 257 9640",
    "sg:postcode":"59901",
    "sg:province":"MT",
    "sg:tags":[
        "body"
    ],
    "wof:name":"Mikes Body Shop",
    "wof:placetype":"venue"
},
  "geometry": {"coordinates":[-114.416859,48.251137],"type":"Point"}
}