{
  "type": "Feature",
  "properties": {
    "iso:country":"US",
    "sg:address":"1510 Bulwer St",
    "sg:city":"Missoula",
    "sg:classifiers":[
        {
            "category":"Shopping",
            "type":"Retail Goods"
        }
    ],
    "sg:phone":"+1 406 728 5078",
    "sg:postcode":"59802",
    "sg:province":"MT",
    "sg:tags":[
        "merchandise"
    ],
    "wof:name":"Osteo Northwest",
    "wof:placetype":"venue"
},
  "geometry": {"coordinates":[-114.012343,46.889251],"type":"Point"}
}