{
  "type": "Feature",
  "properties": {
    "iso:country":"US",
    "sg:address":"7507 N Montana Ave",
    "sg:city":"Helena",
    "sg:classifiers":[
        {
            "category":"Food & Beverages",
            "subcategory":"Groceries & Convenience Stores",
            "type":"Retail Goods"
        }
    ],
    "sg:phone":"+1 406 458 5140",
    "sg:postcode":"59602",
    "sg:province":"MT",
    "sg:tags":[
        "station"
    ],
    "wof:name":"Bobs Valley Market",
    "wof:placetype":"venue"
},
  "geometry": {"coordinates":[-112.02086,46.704543],"type":"Point"}
}