{
  "type": "Feature",
  "properties": {
    "iso:country":"US",
    "sg:address":"110 Lupfer Ave",
    "sg:city":"Whitefish",
    "sg:classifiers":[
        {
            "category":"Personal",
            "subcategory":"Beauty Salon",
            "type":"Services"
        }
    ],
    "sg:phone":"+1 406 863 9900",
    "sg:postcode":"59937",
    "sg:province":"MT",
    "wof:name":"Reecias",
    "wof:placetype":"venue"
},
  "geometry": {"coordinates":[-114.339562,48.411535],"type":"Point"}
}