{
  "type": "Feature",
  "properties": {
    "iso:country":"US",
    "sg:address":"3472 US Hwy 2 E",
    "sg:city":"Kalispell",
    "sg:classifiers":[
        {
            "category":"Restaurant",
            "type":"Food & Drink"
        }
    ],
    "sg:phone":"+1 406 752 6778",
    "sg:postcode":"59901",
    "sg:province":"MT",
    "wof:name":"Julie's Restaurant & Saloon",
    "wof:placetype":"venue"
},
  "geometry": {"coordinates":[-114.26113100000001,48.279406],"type":"Point"}
}