{
  "type": "Feature",
  "properties": {
    "iso:country":"US",
    "sg:address":"1320 2nd Ave S",
    "sg:city":"Great Falls",
    "sg:classifiers":[
        {
            "category":"Shopping",
            "subcategory":"Clothing, Apparel, & Fashions",
            "type":"Retail Goods"
        }
    ],
    "sg:phone":"+1 406 727 0943",
    "sg:postcode":"59405",
    "sg:province":"MT",
    "sg:tags":[
        "accessory",
        "plus",
        "size"
    ],
    "wof:name":"Inges Plus Size Fashions",
    "wof:placetype":"venue"
},
  "geometry": {"coordinates":[-111.283754,47.502923],"type":"Point"}
}