{
  "type": "Feature",
  "properties": {
    "iso:country":"US",
    "sg:address":"1401 25th Ave NE",
    "sg:city":"Black Eagle",
    "sg:classifiers":[
        {
            "category":"Wholesale",
            "subcategory":"Farm Supplies",
            "type":"Manufacturing & Wholesale Goods"
        }
    ],
    "sg:phone":"+1 406 761 1451",
    "sg:postcode":"59414",
    "sg:province":"MT",
    "sg:tags":[
        "hardware",
        "ranch"
    ],
    "wof:name":"Fleet Supply Co",
    "wof:placetype":"venue"
},
  "geometry": {"coordinates":[-111.283585,47.528325],"type":"Point"}
}