{
  "type": "Feature",
  "properties": {
    "iso:country":"US",
    "sg:address":"813 9th St S",
    "sg:city":"Great Falls",
    "sg:classifiers":[
        {
            "category":"Home & Garden",
            "subcategory":"Household Appliances",
            "type":"Retail Goods"
        }
    ],
    "sg:phone":"+1 406 727 8412",
    "sg:postcode":"59405",
    "sg:province":"MT",
    "sg:tags":[
        "machine",
        "sewing"
    ],
    "wof:name":"Joe's Sewing Machine Ctr",
    "wof:placetype":"venue"
},
  "geometry": {"coordinates":[-111.292073,47.4955],"type":"Point"}
}