{
  "type": "Feature",
  "properties": {
    "iso:country":"US",
    "sg:address":"305 S Maryland St",
    "sg:city":"Conrad",
    "sg:classifiers":[
        {
            "category":"Mining & Drilling",
            "type":"Manufacturing & Wholesale Goods"
        }
    ],
    "sg:phone":"+1 406 278 5865",
    "sg:postcode":"59425",
    "sg:province":"MT",
    "sg:tags":[
        "field"
    ],
    "wof:name":"Three By Two Enterprises LLC",
    "wof:placetype":"venue"
},
  "geometry": {"coordinates":[-111.949,48.170983],"type":"Point"}
}