{
  "type": "Feature",
  "properties": {
    "iso:country":"US",
    "sg:address":"750 E Cornell St",
    "sg:city":"Dillon",
    "sg:classifiers":[
        {
            "category":"Education",
            "subcategory":"College",
            "type":"Public Place"
        }
    ],
    "sg:phone":"+1 406 683 7565",
    "sg:postcode":"59725",
    "sg:province":"MT",
    "wof:name":"University of Montana",
    "wof:placetype":"venue"
},
  "geometry": {"coordinates":[-112.637317,45.209596],"type":"Point"}
}