{
  "type": "Feature",
  "properties": {
    "addr:full":"3505 Becraft Ln Billings MT 59101",
    "addr:housenumber":"3505",
    "addr:postcode":"59101",
    "addr:street":"Becraft Ln",
    "iso:country":"US",
    "sg:address":"3505 Becraft Ln",
    "sg:city":"Billings",
    "sg:classifiers":[
        {
            "category":"Building & Trades",
            "subcategory":"Construction",
            "type":"Services"
        }
    ],
    "sg:phone":"+1 406 248 5411",
    "sg:postcode":"59101",
    "sg:province":"MT",
    "sg:tags":[
        "contractor"
    ],
    "wof:name":"A Custom Tape & Texture LLC",
    "wof:placetype":"venue"
},
  "geometry": {"coordinates":[-108.387843,45.8122],"type":"Point"}
}