{
  "type": "Feature",
  "properties": {
    "addr:full":"925 Highland Blvd Bozeman MT 59715",
    "addr:housenumber":"925",
    "addr:postcode":"59715",
    "addr:street":"Highland Blvd",
    "iso:country":"US",
    "sg:address":"925 Highland Blvd",
    "sg:city":"Bozeman",
    "sg:classifiers":[
        {
            "category":"Shopping",
            "type":"Retail Goods"
        }
    ],
    "sg:phone":"+1 406 587 5000",
    "sg:postcode":"59715",
    "sg:province":"MT",
    "sg:tags":[
        "merchandise"
    ],
    "wof:name":"Big Sky Ear Nose & Throat",
    "wof:placetype":"venue"
},
  "geometry": {"coordinates":[-111.017578,45.669296],"type":"Point"}
}