{
  "type": "Feature",
  "properties": {
    "iso:country":"US",
    "sg:address":"3010 Parkhill Dr",
    "sg:city":"Billings",
    "sg:classifiers":[
        {
            "category":"Building & Trades",
            "subcategory":"Construction",
            "type":"Services"
        }
    ],
    "sg:phone":"+1 406 252 6912",
    "sg:postcode":"59102",
    "sg:province":"MT",
    "sg:tags":[
        "steam",
        "cleaning"
    ],
    "wof:name":"Big Sky Painting & Power Wash",
    "wof:placetype":"venue"
},
  "geometry": {"coordinates":[-108.59539100000001,45.78994],"type":"Point"}
}