{
  "type": "Feature",
  "properties": {
    "addr:full":"125 Laird Creek Rd Conner MT 59827",
    "addr:housenumber":"125",
    "addr:postcode":"59827",
    "addr:street":"Laird Creek Rd",
    "iso:country":"US",
    "sg:address":"125 Laird Creek Rd",
    "sg:city":"Conner",
    "sg:classifiers":[
        {
            "category":"Building & Trades",
            "subcategory":"Construction",
            "type":"Services"
        }
    ],
    "sg:phone":"+1 406 821 3190",
    "sg:postcode":"59827",
    "sg:province":"MT",
    "sg:tags":[
        "contractor"
    ],
    "wof:name":"Cantarini Concrete Sawing Inc",
    "wof:placetype":"venue"
},
  "geometry": {"coordinates":[-114.054873,45.873225],"type":"Point"}
}