{
  "type": "Feature",
  "properties": {
    "addr:full":"221 N 15th St Billings MT 59101",
    "addr:housenumber":"221",
    "addr:postcode":"59101",
    "addr:street":"N 15Th St",
    "iso:country":"US",
    "sg:address":"221 N 15th St",
    "sg:city":"Billings",
    "sg:classifiers":[
        {
            "category":"Building & Trades",
            "subcategory":"Plumbing",
            "type":"Services"
        }
    ],
    "sg:phone":"+1 406 252 4800",
    "sg:postcode":"59101",
    "sg:province":"MT",
    "sg:tags":[
        "contractor"
    ],
    "wof:name":"Truchot Airtech Inc",
    "wof:placetype":"venue"
},
  "geometry": {"coordinates":[-108.491265,45.79138],"type":"Point"}
}