{
  "type": "Feature",
  "properties": {
    "iso:country":"US",
    "sg:address":"2810 Brooks St",
    "sg:city":"Missoula",
    "sg:classifiers":[
        {
            "category":"Shopping",
            "subcategory":"Optical Goods",
            "type":"Retail Goods"
        }
    ],
    "sg:phone":"+1 406 728 1356",
    "sg:postcode":"59801",
    "sg:province":"MT",
    "wof:name":"Pearle Vision Center",
    "wof:placetype":"venue"
},
  "geometry": {"coordinates":[-114.023573,46.844929],"type":"Point"}
}