{
  "type": "Feature",
  "properties": {
    "iso:country":"US",
    "sg:address":"2135 Charlotte St",
    "sg:city":"Bozeman",
    "sg:classifiers":[
        {
            "category":"Professional",
            "subcategory":"Lawyer & Legal Services",
            "type":"Services"
        }
    ],
    "sg:phone":"+1 406 586 2221",
    "sg:postcode":"59718",
    "sg:province":"MT",
    "sg:tags":[
        "attorney"
    ],
    "wof:name":"Michael J San Souci Law Office",
    "wof:placetype":"venue"
},
  "geometry": {"coordinates":[-111.064263,45.686768],"type":"Point"}
}