{
  "type": "Feature",
  "properties": {
    "iso:country":"US",
    "sg:address":"901 10th Ave S",
    "sg:city":"Great Falls",
    "sg:classifiers":[
        {
            "category":"Cinema",
            "subcategory":"Movie Rental",
            "type":"Entertainment"
        }
    ],
    "sg:phone":"+1 406 454 3289",
    "sg:postcode":"59405",
    "sg:province":"MT",
    "sg:tags":[
        "video",
        "tape"
    ],
    "wof:name":"Blockbuster",
    "wof:placetype":"venue"
},
  "geometry": {"coordinates":[-111.290443,47.494286],"type":"Point"}
}