{
  "type": "Feature",
  "properties": {
    "addr:full":"113 W Park St Livingston MT 59047",
    "addr:housenumber":"113",
    "addr:postcode":"59047",
    "addr:street":"W Park St",
    "iso:country":"US",
    "sg:address":"113 W Park St",
    "sg:city":"Livingston",
    "sg:classifiers":[
        {
            "category":"Professional",
            "type":"Services"
        }
    ],
    "sg:phone":"+1 406 222 3902",
    "sg:postcode":"59047",
    "sg:province":"MT",
    "wof:name":"Hayseed Studio",
    "wof:placetype":"venue"
},
  "geometry": {"coordinates":[-110.561228,45.662241],"type":"Point"}
}