{
  "type": "Feature",
  "properties": {
    "iso:country":"US",
    "sg:address":"9304 Cougar Dr",
    "sg:city":"Bozeman",
    "sg:classifiers":[
        {
            "category":"Professional",
            "subcategory":"Business Services",
            "type":"Services"
        }
    ],
    "sg:phone":"+1 406 586 8086",
    "sg:postcode":"59718",
    "sg:province":"MT",
    "wof:name":"Cougar Enterprises Inc",
    "wof:placetype":"venue"
},
  "geometry": {"coordinates":[-111.09228,45.590879],"type":"Point"}
}