{
  "type": "Feature",
  "properties": {
    "iso:country":"US",
    "sg:address":"112 N Central Ave",
    "sg:city":"Sidney",
    "sg:classifiers":[
        {
            "category":"Bars & Pubs",
            "type":"Food & Drink"
        }
    ],
    "sg:phone":"+1 406 433 1661",
    "sg:postcode":"59270",
    "sg:province":"MT",
    "wof:name":"Club Tavern",
    "wof:placetype":"venue"
},
  "geometry": {"coordinates":[-104.156862,47.715762],"type":"Point"}
}