{
  "type": "Feature",
  "properties": {
    "iso:country":"US",
    "sg:address":"3 Holiday Way",
    "sg:city":"Butte",
    "sg:classifiers":[
        {
            "category":"Bars & Pubs",
            "type":"Food & Drink"
        }
    ],
    "sg:phone":"+1 406 494 1484",
    "sg:postcode":"59701",
    "sg:province":"MT",
    "sg:tags":[
        "drinking"
    ],
    "wof:name":"O Connell Pub",
    "wof:placetype":"venue"
},
  "geometry": {"coordinates":[-112.50506,45.985277],"type":"Point"}
}