{
  "type": "Feature",
  "properties": {
    "addr:full":"213 W Main St Hamilton MT 59840",
    "addr:housenumber":"213",
    "addr:postcode":"59840",
    "addr:street":"W Main St",
    "iso:country":"US",
    "sg:address":"213 W Main St",
    "sg:city":"Hamilton",
    "sg:classifiers":[
        {
            "category":"Shopping",
            "subcategory":"Discount & Variety Stores",
            "type":"Retail Goods"
        }
    ],
    "sg:phone":"+1 406 363 0236",
    "sg:postcode":"59840",
    "sg:province":"MT",
    "wof:name":"Tamikos",
    "wof:placetype":"venue"
},
  "geometry": {"coordinates":[-114.157241,46.246947],"type":"Point"}
}