{
  "type": "Feature",
  "properties": {
    "iso:country":"US",
    "sg:address":"312 1st Ave E",
    "sg:city":"Kalispell",
    "sg:classifiers":[
        {
            "category":"Recreation",
            "type":"Entertainment"
        }
    ],
    "sg:phone":"+1 406 758 7718",
    "sg:postcode":"59901",
    "sg:province":"MT",
    "sg:tags":[
        "parks"
    ],
    "wof:name":"Kalispell Parks & Recreation",
    "wof:placetype":"venue"
},
  "geometry": {"coordinates":[-114.311271,48.195975],"type":"Point"}
}