{
  "type": "Feature",
  "properties": {
    "iso:country":"US",
    "sg:address":"801 3rd St SW",
    "sg:city":"Sidney",
    "sg:classifiers":[
        {
            "category":"Professional",
            "subcategory":"Business Services",
            "type":"Services"
        }
    ],
    "sg:phone":"+1 406 433 2006",
    "sg:postcode":"59270",
    "sg:province":"MT",
    "wof:name":"Global Opportunity Enterprises",
    "wof:placetype":"venue"
},
  "geometry": {"coordinates":[-104.167941,47.714953],"type":"Point"}
}