{
  "type": "Feature",
  "properties": {
    "addr:full":"5305 3rd Ave S Great Falls MT 59405",
    "addr:housenumber":"5305",
    "addr:postcode":"59405",
    "addr:street":"3Rd Ave S Great",
    "iso:country":"US",
    "sg:address":"5305 3rd Ave S",
    "sg:city":"Great Falls",
    "sg:classifiers":[
        {
            "category":"Education",
            "subcategory":"School",
            "type":"Public Place"
        }
    ],
    "sg:phone":"+1 406 268 6675",
    "sg:postcode":"59405",
    "sg:province":"MT",
    "wof:name":"Chief Joseph Elementary School",
    "wof:placetype":"venue"
},
  "geometry": {"coordinates":[-111.21815100000001,47.501601],"type":"Point"}
}