{
  "type": "Feature",
  "properties": {
    "iso:country":"US",
    "sg:address":"1910 Broadwater Ave",
    "sg:city":"Billings",
    "sg:classifiers":[
        {
            "category":"Shopping",
            "subcategory":"Bicycles & Sporting Goods",
            "type":"Retail Goods"
        }
    ],
    "sg:phone":"+1 406 656 8342",
    "sg:postcode":"59102",
    "sg:province":"MT",
    "sg:website":"www.spokeshop.com",
    "wof:name":"Spoke Shop",
    "wof:placetype":"venue"
},
  "geometry": {"coordinates":[-108.5647,45.776857],"type":"Point"}
}