{
  "type": "Feature",
  "properties": {
    "addr:full":"2424 Enterprise Ave Billings MT 59102",
    "addr:housenumber":"2424",
    "addr:postcode":"59102",
    "addr:street":"Enterprise Ave",
    "iso:country":"US",
    "sg:address":"2424 Enterprise Ave",
    "sg:city":"Billings",
    "sg:classifiers":[
        {
            "category":"Home & Garden",
            "subcategory":"Carpets & Floor Coverings",
            "type":"Retail Goods"
        }
    ],
    "sg:phone":"+1 406 652 5568",
    "sg:postcode":"59102",
    "sg:province":"MT",
    "sg:tags":[
        "dealer",
        "rug"
    ],
    "sg:website":"www.carpetgarage.com",
    "wof:name":"Carpet Garage Mill Outlet",
    "wof:placetype":"venue"
},
  "geometry": {"coordinates":[-108.576786,45.75059],"type":"Point"}
}