{
  "type": "Feature",
  "properties": {
    "iso:country":"US",
    "sg:address":"1402 Airport Rd",
    "sg:city":"Kalispell",
    "sg:classifiers":[
        {
            "category":"Retail",
            "subcategory":"Auto Repair",
            "type":"Services"
        }
    ],
    "sg:phone":"+1 406 257 2341",
    "sg:postcode":"59901",
    "sg:province":"MT",
    "sg:tags":[
        "automotive"
    ],
    "wof:name":"Southside Speedy Lube Inc",
    "wof:placetype":"venue"
},
  "geometry": {"coordinates":[-114.309419,48.184202],"type":"Point"}
}