{
  "type": "Feature",
  "properties": {
    "iso:country":"US",
    "sg:address":"201 N Main St",
    "sg:city":"Darby",
    "sg:classifiers":[
        {
            "category":"Food & Beverages",
            "subcategory":"Liquor & Beverages",
            "type":"Retail Goods"
        }
    ],
    "sg:phone":"+1 406 821 4117",
    "sg:postcode":"59829",
    "sg:province":"MT",
    "wof:name":"Darby Liquor Store",
    "wof:placetype":"venue"
},
  "geometry": {"coordinates":[-114.17821499999999,46.022493],"type":"Point"}
}