{
  "type": "Feature",
  "properties": {
    "addr:full":"1029 Kristin Dr Billings MT 59101",
    "addr:housenumber":"1029",
    "addr:postcode":"59101",
    "addr:street":"Kristin Dr",
    "iso:country":"US",
    "sg:address":"1029 Kristin Dr",
    "sg:city":"Billings",
    "sg:classifiers":[
        {
            "category":"Wholesale",
            "subcategory":"Electrical",
            "type":"Manufacturing & Wholesale Goods"
        }
    ],
    "sg:phone":"+1 406 252 4473",
    "sg:postcode":"59101",
    "sg:province":"MT",
    "sg:tags":[
        "control",
        "security",
        "system"
    ],
    "wof:name":"Excalibur Security Svc",
    "wof:placetype":"venue"
},
  "geometry": {"coordinates":[-108.396908,45.816565],"type":"Point"}
}