{
  "type": "Feature",
  "properties": {
    "iso:country":"US",
    "sg:address":"4020 Rimrock Rd",
    "sg:city":"Billings",
    "sg:classifiers":[
        {
            "category":"Manufacturing",
            "subcategory":"Musical Instruments",
            "type":"Manufacturing & Wholesale Goods"
        }
    ],
    "sg:phone":"+1 406 656 8862",
    "sg:postcode":"59106",
    "sg:province":"MT",
    "sg:tags":[
        "mfg"
    ],
    "wof:name":"Kirk Violins Inc",
    "wof:placetype":"venue"
},
  "geometry": {"coordinates":[-108.61759499999999,45.798452],"type":"Point"}
}