{
  "type": "Feature",
  "properties": {
    "iso:country":"US",
    "sg:address":"5241 Koch Ln",
    "sg:city":"Florence",
    "sg:classifiers":[
        {
            "category":"Autos & Motor Vehicles",
            "subcategory":"Motorcycle Sales",
            "type":"Retail Goods"
        }
    ],
    "sg:phone":"+1 406 777 2344",
    "sg:postcode":"59833",
    "sg:province":"MT",
    "wof:name":"Wolf Cycle",
    "wof:placetype":"venue"
},
  "geometry": {"coordinates":[-114.087851,46.615277],"type":"Point"}
}