{
  "type": "Feature",
  "properties": {
    "iso:country":"US",
    "sg:address":"1213 Elkhorn Dr",
    "sg:city":"Laurel",
    "sg:classifiers":[
        {
            "category":"Professional",
            "subcategory":"Testing Lab",
            "type":"Services"
        }
    ],
    "sg:phone":"+1 406 628 8496",
    "sg:postcode":"59044",
    "sg:province":"MT",
    "sg:tags":[
        "laboratory"
    ],
    "wof:name":"Boesh Engineering & Testing",
    "wof:placetype":"venue"
},
  "geometry": {"coordinates":[-108.72855,45.683415],"type":"Point"}
}