{
  "type": "Feature",
  "properties": {
    "iso:country":"US",
    "sg:address":"324 S Grand Ave",
    "sg:city":"Bozeman",
    "sg:classifiers":[
        {
            "category":"Real Estate",
            "subcategory":"Surveying",
            "type":"Services"
        }
    ],
    "sg:phone":"+1 406 586 2623",
    "sg:postcode":"59715",
    "sg:province":"MT",
    "wof:name":"Swart Charles R Co",
    "wof:placetype":"venue"
},
  "geometry": {"coordinates":[-111.040077,45.676038],"type":"Point"}
}