{
  "type": "Feature",
  "properties": {
    "iso:country":"US",
    "sg:address":"410 S Yellowstone St",
    "sg:city":"Livingston",
    "sg:classifiers":[
        {
            "category":"Building & Trades",
            "subcategory":"Construction",
            "type":"Services"
        }
    ],
    "sg:phone":"+1 406 222 6657",
    "sg:postcode":"59047",
    "sg:province":"MT",
    "sg:tags":[
        "house"
    ],
    "wof:name":"Johns Home Repair LLC",
    "wof:placetype":"venue"
},
  "geometry": {"coordinates":[-110.560038,45.656356],"type":"Point"}
}