{
  "type": "Feature",
  "properties": {
    "addr:full":"2086 Bryan Rd Bozeman MT 59718",
    "addr:housenumber":"2086",
    "addr:postcode":"59718",
    "addr:street":"Bryan Rd",
    "iso:country":"US",
    "sg:address":"2086 Bryan Rd",
    "sg:city":"Bozeman",
    "sg:classifiers":[
        {
            "category":"Wholesale",
            "subcategory":"Farm Supplies",
            "type":"Manufacturing & Wholesale Goods"
        }
    ],
    "sg:phone":"+1 406 586 0571",
    "sg:postcode":"59718",
    "sg:province":"MT",
    "sg:tags":[
        "bean"
    ],
    "wof:name":"Bryan Ranch",
    "wof:placetype":"venue"
},
  "geometry": {"coordinates":[-111.232069,45.699776],"type":"Point"}
}