{
  "type": "Feature",
  "properties": {
    "iso:country":"US",
    "sg:address":"32 Jet Dr",
    "sg:city":"Glasgow",
    "sg:phone":"+1 406 228 4578",
    "sg:postcode":"59230",
    "sg:province":"MT",
    "sg:tags":[
        "farm",
        "wheat"
    ],
    "wof:name":"Allen Evenson",
    "wof:placetype":"venue"
},
  "geometry": {"coordinates":[-106.63677300000001,48.207978],"type":"Point"}
}