{
  "type": "Feature",
  "properties": {
    "iso:country":"US",
    "sg:address":"1770 Ashley Lake Rd",
    "sg:city":"Kalispell",
    "sg:classifiers":[
        {
            "category":"Freight",
            "type":"Transportation"
        }
    ],
    "sg:phone":"+1 406 752 7360",
    "sg:postcode":"59901",
    "sg:province":"MT",
    "sg:tags":[
        "local",
        "trucking"
    ],
    "wof:name":"Jim Cameron",
    "wof:placetype":"venue"
},
  "geometry": {"coordinates":[-114.50161300000001,48.187425],"type":"Point"}
}