{
  "type": "Feature",
  "properties": {
    "iso:country":"US",
    "sg:address":"9033 Walker Rd",
    "sg:city":"Belgrade",
    "sg:classifiers":[
        {
            "category":"Farming",
            "subcategory":"Farm & Veterinary Services",
            "type":"Manufacturing & Wholesale Goods"
        }
    ],
    "sg:phone":"+1 406 585 3586",
    "sg:postcode":"59714",
    "sg:province":"MT",
    "sg:tags":[
        "livestock"
    ],
    "wof:name":"Trans Ova Genetcis",
    "wof:placetype":"venue"
},
  "geometry": {"coordinates":[-111.045433,45.827576],"type":"Point"}
}