{
  "type": "Feature",
  "properties": {
    "iso:country":"US",
    "sg:address":"191 Sun Loop Ln",
    "sg:city":"Great Falls",
    "sg:classifiers":[
        {
            "category":"Professional",
            "subcategory":"Detective & Security Services",
            "type":"Services"
        }
    ],
    "sg:phone":"+1 406 590 3901",
    "sg:postcode":"59404",
    "sg:province":"MT",
    "sg:tags":[
        "guard",
        "contract"
    ],
    "wof:name":"Dave Hickman",
    "wof:placetype":"venue"
},
  "geometry": {"coordinates":[-111.51073700000001,47.530283],"type":"Point"}
}