{
  "type": "Feature",
  "properties": {
    "addr:full":"301 College St Stevensville MT 59870",
    "addr:housenumber":"301",
    "addr:postcode":"59870",
    "addr:street":"College St",
    "iso:country":"US",
    "sg:address":"301 College St",
    "sg:city":"Stevensville",
    "sg:classifiers":[
        {
            "category":"Shopping",
            "type":"Retail Goods"
        }
    ],
    "sg:phone":"+1 406 363 4318",
    "sg:postcode":"59870",
    "sg:province":"MT",
    "sg:tags":[
        "wedding",
        "supply"
    ],
    "wof:name":"Bitterroot Valley Floral Co",
    "wof:placetype":"venue"
},
  "geometry": {"coordinates":[-114.090768,46.509634],"type":"Point"}
}