{
  "type": "Feature",
  "properties": {
    "iso:country":"US",
    "sg:address":"456 Red Fox Ln",
    "sg:city":"Stevensville",
    "sg:classifiers":[
        {
            "category":"Wholesale",
            "subcategory":"Machinery & Supplies",
            "type":"Manufacturing & Wholesale Goods"
        }
    ],
    "sg:phone":"+1 406 777 6946",
    "sg:postcode":"59870",
    "sg:province":"MT",
    "sg:tags":[
        "pump"
    ],
    "wof:name":"Accelerated Pump Svc",
    "wof:placetype":"venue"
},
  "geometry": {"coordinates":[-114.054965,46.537025],"type":"Point"}
}