{
  "type": "Feature",
  "properties": {
    "iso:country":"US",
    "sg:address":"1609 11th Ave",
    "sg:city":"Helena",
    "sg:classifiers":[
        {
            "category":"Food & Beverages",
            "subcategory":"Liquor & Beverages",
            "type":"Retail Goods"
        }
    ],
    "sg:phone":"+1 406 442 8540",
    "sg:postcode":"59601",
    "sg:province":"MT",
    "wof:name":"M-T Glass Liquor Store",
    "wof:placetype":"venue"
},
  "geometry": {"coordinates":[-112.01257099999999,46.589707],"type":"Point"}
}