{
  "type": "Feature",
  "properties": {
    "iso:country":"US",
    "sg:address":"17 4th Ave SE",
    "sg:city":"Ronan",
    "sg:classifiers":[
        {
            "category":"Professional",
            "subcategory":"Testing Lab",
            "type":"Services"
        }
    ],
    "sg:phone":"+1 406 676 4261",
    "sg:postcode":"59864",
    "sg:province":"MT",
    "sg:tags":[
        "laboratory"
    ],
    "wof:name":"Robert J Bullard",
    "wof:placetype":"venue"
},
  "geometry": {"coordinates":[-114.09183,47.529604],"type":"Point"}
}