{
  "type": "Feature",
  "properties": {
    "iso:country":"US",
    "sg:address":"260 Morning View Dr",
    "sg:city":"Kalispell",
    "sg:classifiers":[
        {
            "category":"Manufacturing",
            "subcategory":"Lumber",
            "type":"Manufacturing & Wholesale Goods"
        }
    ],
    "sg:phone":"+1 406 837 0047",
    "sg:postcode":"59901",
    "sg:province":"MT",
    "sg:tags":[
        "forestry"
    ],
    "wof:name":"Bruch Bros Line Logging",
    "wof:placetype":"venue"
},
  "geometry": {"coordinates":[-114.404689,48.189416],"type":"Point"}
}