{
  "type": "Feature",
  "properties": {
    "iso:country":"US",
    "sg:address":"1014 W Park St",
    "sg:city":"Livingston",
    "sg:classifiers":[
        {
            "category":"Manufacturing",
            "subcategory":"Apparel",
            "type":"Manufacturing & Wholesale Goods"
        }
    ],
    "sg:phone":"+1 406 222 7977",
    "sg:postcode":"59047",
    "sg:province":"MT",
    "wof:name":"Big Sky Embroidery of Montana",
    "wof:placetype":"venue"
},
  "geometry": {"coordinates":[-110.570336,45.655366],"type":"Point"}
}