{
  "type": "Feature",
  "properties": {
    "iso:country":"US",
    "sg:address":"852 Willoughby Ln",
    "sg:city":"Stevensville",
    "sg:classifiers":[
        {
            "category":"Travel",
            "subcategory":"Hotels & Motels",
            "type":"Entertainment"
        }
    ],
    "sg:phone":"+1 406 777 3145",
    "sg:postcode":"59870",
    "sg:province":"MT",
    "sg:tags":[
        "breakfast",
        "accommodation",
        "bed"
    ],
    "wof:name":"Country Caboose",
    "wof:placetype":"venue"
},
  "geometry": {"coordinates":[-114.027605,46.443473],"type":"Point"}
}