{
  "type": "Feature",
  "properties": {
    "addr:full":"1985 Oriole Dr Missoula MT 59808",
    "addr:housenumber":"1985",
    "addr:postcode":"59808",
    "addr:street":"Oriole Dr",
    "iso:country":"US",
    "sg:address":"1985 Oriole Dr",
    "sg:city":"Missoula",
    "sg:classifiers":[
        {
            "category":"Retail",
            "subcategory":"Auto Repair",
            "type":"Services"
        }
    ],
    "sg:phone":"+1 406 549 6956",
    "sg:postcode":"59808",
    "sg:province":"MT",
    "sg:tags":[
        "general"
    ],
    "wof:name":"D JS Automotive Repair",
    "wof:placetype":"venue"
},
  "geometry": {"coordinates":[-114.11848000000001,46.889038],"type":"Point"}
}