{
  "type": "Feature",
  "properties": {
    "addr:full":"1212 W Custer Ave Helena MT 59602",
    "addr:housenumber":"1212",
    "addr:postcode":"59602",
    "addr:street":"W Custer Ave",
    "iso:country":"US",
    "sg:address":"1212 W Custer Ave",
    "sg:city":"Helena",
    "sg:classifiers":[
        {
            "category":"Restaurant",
            "type":"Food & Drink"
        }
    ],
    "sg:menulink":"http://www.allmenus.com/mt/helena/85220-applebees/menu/",
    "sg:phone":"+1 406 449 7300",
    "sg:postcode":"59602",
    "sg:province":"MT",
    "sg:tags":[
        "burger",
        "american",
        "sandwich",
        "soup"
    ],
    "wof:name":"Applebee's",
    "wof:placetype":"venue"
},
  "geometry": {"coordinates":[-112.021801,46.616676],"type":"Point"}
}