{
  "type": "Feature",
  "properties": {
    "iso:country":"US",
    "sg:address":"676 S Ferguson Ave",
    "sg:city":"Bozeman",
    "sg:classifiers":[
        {
            "category":"Organizations",
            "subcategory":"Professional Association",
            "type":"Services"
        }
    ],
    "sg:phone":"+1 406 585 7443",
    "sg:postcode":"59718",
    "sg:province":"MT",
    "sg:tags":[
        "merchant",
        "credit",
        "processor",
        "card"
    ],
    "wof:name":"Frontline Processing Corp",
    "wof:placetype":"venue"
},
  "geometry": {"coordinates":[-111.093797,45.672286],"type":"Point"}
}