{
  "type": "Feature",
  "properties": {
    "addr:full":"1500 3rd St NW Great Falls MT 59404",
    "addr:housenumber":"1500",
    "addr:postcode":"59404",
    "addr:street":"3Rd St Nw",
    "iso:country":"US",
    "sg:address":"1500 3rd St NW",
    "sg:city":"Great Falls",
    "sg:classifiers":[
        {
            "category":"Retail",
            "subcategory":"Auto Repair",
            "type":"Services"
        }
    ],
    "sg:phone":"+1 406 452 8336",
    "sg:postcode":"59404",
    "sg:province":"MT",
    "sg:tags":[
        "lubrication"
    ],
    "wof:name":"Pro Lube",
    "wof:placetype":"venue"
},
  "geometry": {"coordinates":[-111.309606,47.519324],"type":"Point"}
}