{
  "type": "Feature",
  "properties": {
    "iso:country":"US",
    "sg:address":"101 Milwaukee Ave",
    "sg:city":"Deer Lodge",
    "sg:classifiers":[
        {
            "category":"Shopping",
            "subcategory":"Bicycles & Sporting Goods",
            "type":"Retail Goods"
        }
    ],
    "sg:phone":"+1 406 846 2926",
    "sg:postcode":"59722",
    "sg:province":"MT",
    "wof:name":"Rivers Edge Sporting Goods",
    "wof:placetype":"venue"
},
  "geometry": {"coordinates":[-112.73822,46.397978],"type":"Point"}
}