{
  "type": "Feature",
  "properties": {
    "iso:country":"US",
    "sg:address":"30 Pine Creek Rd",
    "sg:city":"Livingston",
    "sg:classifiers":[
        {
            "category":"Farming",
            "subcategory":"Livestock Farm",
            "type":"Manufacturing & Wholesale Goods"
        }
    ],
    "sg:phone":"+1 406 222 8209",
    "sg:postcode":"59047",
    "sg:province":"MT",
    "sg:tags":[
        "beef",
        "feedlot",
        "cattle"
    ],
    "wof:name":"Donald E Lange",
    "wof:placetype":"venue"
},
  "geometry": {"coordinates":[-110.60508799999999,45.51134],"type":"Point"}
}