{
  "type": "Feature",
  "properties": {
    "iso:country":"US",
    "sg:address":"102 N Central Ave",
    "sg:city":"Sidney",
    "sg:classifiers":[
        {
            "category":"Shopping",
            "subcategory":"Department Store",
            "type":"Retail Goods"
        }
    ],
    "sg:phone":"+1 406 488 1201",
    "sg:postcode":"59270",
    "sg:province":"MT",
    "sg:website":"www.yellowstonemerc.com",
    "wof:name":"Yellowstone Mercantile",
    "wof:placetype":"venue"
},
  "geometry": {"coordinates":[-104.156498,47.716219],"type":"Point"}
}