{
  "type": "Feature",
  "properties": {
    "iso:country":"US",
    "sg:address":"20 N Stacy Ave",
    "sg:city":"Miles City",
    "sg:classifiers":[
        {
            "category":"Organizations",
            "subcategory":"Religious Organization",
            "type":"Services"
        }
    ],
    "sg:phone":"+1 406 232 2110",
    "sg:postcode":"59301",
    "sg:province":"MT",
    "wof:name":"Fellowship Baptist Church Inc",
    "wof:placetype":"venue"
},
  "geometry": {"coordinates":[-105.831718,46.409143],"type":"Point"}
}