{
  "type": "Feature",
  "properties": {
    "iso:country":"US",
    "sg:address":"4151 1st Ave S",
    "sg:city":"Billings",
    "sg:classifiers":[
        {
            "category":"Manufacturing",
            "subcategory":"Food",
            "type":"Manufacturing & Wholesale Goods"
        }
    ],
    "sg:phone":"+1 406 245 6211",
    "sg:postcode":"59101",
    "sg:province":"MT",
    "sg:tags":[
        "bottler"
    ],
    "wof:name":"Coca-Cola Bottling Co",
    "wof:placetype":"venue"
},
  "geometry": {"coordinates":[-108.521985,45.77065],"type":"Point"}
}