{
  "type": "Feature",
  "properties": {
    "iso:country":"US",
    "sg:address":"27 N 27th St",
    "sg:city":"Billings",
    "sg:classifiers":[
        {
            "category":"Professional",
            "subcategory":"Lawyer & Legal Services",
            "type":"Services"
        }
    ],
    "sg:phone":"+1 406 248 7731",
    "sg:postcode":"59101",
    "sg:province":"MT",
    "sg:tags":[
        "attorney"
    ],
    "sg:website":"www.moultonlawfirm.com",
    "wof:name":"Moulton Bellingham Longo",
    "wof:placetype":"venue"
},
  "geometry": {"coordinates":[-108.50418500000001,45.78252],"type":"Point"}
}