{
  "type": "Feature",
  "properties": {
    "addr:full":"2020 W Babcock St Bozeman MT 59718",
    "addr:housenumber":"2020",
    "addr:postcode":"59718",
    "addr:street":"W Babcock St",
    "iso:country":"US",
    "sg:address":"2020 W Babcock St",
    "sg:city":"Bozeman",
    "sg:classifiers":[
        {
            "category":"Restaurant",
            "type":"Food & Drink"
        }
    ],
    "sg:phone":"+1 406 586 5431",
    "sg:postcode":"59718",
    "sg:province":"MT",
    "sg:tags":[
        "eating"
    ],
    "wof:name":"Dominos Pizza",
    "wof:placetype":"venue"
},
  "geometry": {"coordinates":[-111.064536,45.678354],"type":"Point"}
}