{
  "type": "Feature",
  "properties": {
    "addr:full":"1901 Terminal Cir Billings MT 59105",
    "addr:housenumber":"1901",
    "addr:postcode":"59105",
    "addr:street":"Terminal Cir",
    "iso:country":"US",
    "sg:address":"1901 Terminal Cir",
    "sg:city":"Billings",
    "sg:classifiers":[
        {
            "category":"Government",
            "subcategory":"Police Station",
            "type":"Public Place"
        }
    ],
    "sg:phone":"+1 406 657 8498",
    "sg:postcode":"59105",
    "sg:province":"MT",
    "sg:tags":[
        "department"
    ],
    "wof:name":"Airport Police",
    "wof:placetype":"venue"
},
  "geometry": {"coordinates":[-108.536883,45.802516],"type":"Point"}
}