{
  "type": "Feature",
  "properties": {
    "iso:country":"US",
    "sg:address":"1925 Grand Ave",
    "sg:city":"Billings",
    "sg:classifiers":[
        {
            "category":"Home & Garden",
            "subcategory":"Mobile Homes",
            "type":"Retail Goods"
        }
    ],
    "sg:phone":"+1 406 248 3641",
    "sg:postcode":"59102",
    "sg:province":"MT",
    "wof:name":"Oakland & Company",
    "wof:placetype":"venue"
},
  "geometry": {"coordinates":[-108.56619499999999,45.78413],"type":"Point"}
}