{
  "type": "Feature",
  "properties": {
    "addr:full":"3100 Horseshoe Bend Rd Helena MT 59602",
    "addr:housenumber":"3100",
    "addr:postcode":"59602",
    "addr:street":"Horseshoe Bend Rd",
    "iso:country":"US",
    "sg:address":"3100 Horseshoe Bend Rd",
    "sg:city":"Helena",
    "sg:classifiers":[
        {
            "category":"Organizations",
            "subcategory":"Professional Association",
            "type":"Services"
        }
    ],
    "sg:phone":"+1 406 442 9964",
    "sg:postcode":"59602",
    "sg:province":"MT",
    "wof:name":"LABORERS Agc Training Program",
    "wof:placetype":"venue"
},
  "geometry": {"coordinates":[-112.062763,46.620991],"type":"Point"}
}