{
  "type": "Feature",
  "properties": {
    "iso:country":"US",
    "sg:address":"311 Railroad St W",
    "sg:city":"Missoula",
    "sg:classifiers":[
        {
            "category":"Manufacturing",
            "subcategory":"Motor Vehicles & Parts",
            "type":"Manufacturing & Wholesale Goods"
        }
    ],
    "sg:phone":"+1 406 549 4545",
    "sg:postcode":"59802",
    "sg:province":"MT",
    "sg:tags":[
        "mfg",
        "trimming"
    ],
    "wof:name":"Team Shirts",
    "wof:placetype":"venue"
},
  "geometry": {"coordinates":[-113.99569700000001,46.877039],"type":"Point"}
}