{
  "type": "Feature",
  "properties": {
    "iso:country":"US",
    "sg:address":"1350 Airport Rd",
    "sg:city":"Deer Lodge",
    "sg:classifiers":[
        {
            "category":"Airport",
            "type":"Transportation"
        }
    ],
    "sg:phone":"+1 406 846 1388",
    "sg:postcode":"59725",
    "sg:province":"MT",
    "sg:tags":[
        "aircraft",
        "support",
        "ground"
    ],
    "wof:name":"Heli-Works Flight Svc",
    "wof:placetype":"venue"
},
  "geometry": {"coordinates":[-112.56634,45.25144],"type":"Point"}
}