{
  "type": "Feature",
  "properties": {
    "iso:country":"US",
    "sg:address":"795 Sunset Blvd",
    "sg:city":"Kalispell",
    "sg:classifiers":[
        {
            "category":"Health Services",
            "subcategory":"Health Practitioner",
            "type":"Services"
        }
    ],
    "sg:phone":"+1 406 257 4327",
    "sg:postcode":"59901",
    "sg:province":"MT",
    "sg:tags":[
        "aids",
        "audiologist",
        "hearing"
    ],
    "wof:name":"Family Hearing Professionals",
    "wof:placetype":"venue"
},
  "geometry": {"coordinates":[-114.320508,48.207098],"type":"Point"}
}