{
  "type": "Feature",
  "properties": {
    "iso:country":"US",
    "sg:address":"2900 N Montana Ave",
    "sg:city":"Helena",
    "sg:classifiers":[
        {
            "category":"Food & Beverages",
            "subcategory":"Groceries & Convenience Stores",
            "type":"Retail Goods"
        }
    ],
    "sg:phone":"+1 406 449 3207",
    "sg:postcode":"59601",
    "sg:province":"MT",
    "wof:name":"Town Pump Inc & Affiliates",
    "wof:placetype":"venue"
},
  "geometry": {"coordinates":[-112.02083399999999,46.614802],"type":"Point"}
}