{
  "type": "Feature",
  "properties": {
    "iso:country":"US",
    "sg:address":"619 N Last Chance Gulch St",
    "sg:city":"Helena",
    "sg:classifiers":[
        {
            "category":"Utilities",
            "subcategory":"Mobile Phone",
            "type":"Services"
        }
    ],
    "sg:phone":"+1 406 443 4002",
    "sg:postcode":"59601",
    "sg:province":"MT",
    "sg:tags":[
        "sales",
        "cellular"
    ],
    "wof:name":"Mountin Top Wireless",
    "wof:placetype":"venue"
},
  "geometry": {"coordinates":[-112.036405,46.59266],"type":"Point"}
}