{
  "type": "Feature",
  "properties": {
    "addr:full":"1003 Michael Ln Billings MT 59105",
    "addr:housenumber":"1003",
    "addr:postcode":"59105",
    "addr:street":"Michael Ln",
    "iso:country":"US",
    "sg:address":"1003 Michael Ln",
    "sg:city":"Billings",
    "sg:classifiers":[
        {
            "category":"Professional",
            "subcategory":"Business Services",
            "type":"Services"
        }
    ],
    "sg:phone":"+1 406 245 6138",
    "sg:postcode":"59105",
    "sg:province":"MT",
    "sg:tags":[
        "convention",
        "meeting",
        "facility"
    ],
    "wof:name":"Country Reception Hall",
    "wof:placetype":"venue"
},
  "geometry": {"coordinates":[-108.461251,45.905489],"type":"Point"}
}