{
  "type": "Feature",
  "properties": {
    "iso:country":"US",
    "sg:address":"2472 Birch Glen Rd",
    "sg:city":"Whitefish",
    "sg:classifiers":[
        {
            "category":"Manufacturing",
            "subcategory":"Printing",
            "type":"Manufacturing & Wholesale Goods"
        }
    ],
    "sg:phone":"+1 406 862 7777",
    "sg:postcode":"59937",
    "sg:province":"MT",
    "sg:tags":[
        "advisory",
        "investment",
        "letter",
        "publishing"
    ],
    "wof:name":"Investech Mutl Funds Advisors",
    "wof:placetype":"venue"
},
  "geometry": {"coordinates":[-114.362212,48.451203],"type":"Point"}
}