{
  "type": "Feature",
  "properties": {
    "addr:full":"1103 Helena Ave Helena MT 59601",
    "addr:housenumber":"1103",
    "addr:postcode":"59601",
    "addr:street":"Helena Ave",
    "iso:country":"US",
    "sg:address":"1103 Helena Ave",
    "sg:city":"Helena",
    "sg:classifiers":[
        {
            "category":"Home & Garden",
            "subcategory":"Household Appliances",
            "type":"Retail Goods"
        }
    ],
    "sg:phone":"+1 406 443 5724",
    "sg:postcode":"59601",
    "sg:province":"MT",
    "wof:name":"Sues Sewing Palace Bernina",
    "wof:placetype":"venue"
},
  "geometry": {"coordinates":[-112.020871,46.59787],"type":"Point"}
}