{
  "type": "Feature",
  "properties": {
    "iso:country":"US",
    "sg:address":"631 Utah Ave",
    "sg:city":"Butte",
    "sg:classifiers":[
        {
            "category":"Building & Trades",
            "subcategory":"Electrical",
            "type":"Services"
        }
    ],
    "sg:phone":"+1 406 723 3465",
    "sg:postcode":"59701",
    "sg:province":"MT",
    "sg:tags":[
        "general",
        "electrical",
        "contractor"
    ],
    "wof:name":"R & R Electric",
    "wof:placetype":"venue"
},
  "geometry": {"coordinates":[-112.53066099999999,46.007684],"type":"Point"}
}