{
  "type": "Feature",
  "properties": {
    "addr:full":"3310 Laredo Pl Billings MT 59102",
    "addr:housenumber":"3310",
    "addr:postcode":"59102",
    "addr:street":"Laredo Pl",
    "iso:country":"US",
    "sg:address":"3310 Laredo Pl",
    "sg:city":"Billings",
    "sg:classifiers":[
        {
            "category":"Building & Trades",
            "subcategory":"Construction",
            "type":"Services"
        }
    ],
    "sg:phone":"+1 406 655 4646",
    "sg:postcode":"59102",
    "sg:province":"MT",
    "sg:tags":[
        "general",
        "contractor"
    ],
    "wof:name":"Billings Builders Inc",
    "wof:placetype":"venue"
},
  "geometry": {"coordinates":[-108.61499999999999,45.802441],"type":"Point"}
}