{
  "type": "Feature",
  "properties": {
    "iso:country":"US",
    "sg:address":"340 W Center St",
    "sg:city":"Kalispell",
    "sg:classifiers":[
        {
            "category":"Health Services",
            "subcategory":"Doctor",
            "type":"Services"
        }
    ],
    "sg:phone":"+1 406 755 7123",
    "sg:postcode":"59901",
    "sg:province":"MT",
    "sg:tags":[
        "dentist"
    ],
    "wof:name":"Jones Dentistry",
    "wof:placetype":"venue"
},
  "geometry": {"coordinates":[-114.318687,48.197862],"type":"Point"}
}