{
  "type": "Feature",
  "properties": {
    "addr:full":"1233 Ave F Billings MT 59102",
    "addr:housenumber":"1233",
    "addr:postcode":"59102",
    "addr:street":"Ave F",
    "iso:country":"US",
    "sg:address":"1233 Ave F",
    "sg:city":"Billings",
    "sg:classifiers":[
        {
            "category":"Building & Trades",
            "subcategory":"Construction",
            "type":"Services"
        }
    ],
    "sg:phone":"+1 406 860 3002",
    "sg:postcode":"59102",
    "sg:province":"MT",
    "sg:tags":[
        "maintenance",
        "contractor"
    ],
    "wof:name":"Montana Maintenance & Svc",
    "wof:placetype":"venue"
},
  "geometry": {"coordinates":[-108.547849,45.789003],"type":"Point"}
}