{
  "type": "Feature",
  "properties": {
    "addr:full":"1305 W Diamond St Butte MT 59701",
    "addr:housenumber":"1305",
    "addr:postcode":"mt 59701",
    "addr:street":"W Diamond St",
    "iso:country":"US",
    "sg:address":"1305 W Diamond St",
    "sg:city":"Butte",
    "sg:classifiers":[
        {
            "category":"Wholesale",
            "subcategory":"Machinery & Supplies",
            "type":"Manufacturing & Wholesale Goods"
        }
    ],
    "sg:phone":"+1 406 782 7074",
    "sg:postcode":"59701",
    "sg:province":"MT",
    "sg:tags":[
        "equipment",
        "industrial"
    ],
    "wof:name":"Km Industrial Sales Inc",
    "wof:placetype":"venue"
},
  "geometry": {"coordinates":[-112.55838799999999,46.009312],"type":"Point"}
}