{
  "type": "Feature",
  "properties": {
    "addr:full":"1015 7th Ave SW Sidney MT 59270",
    "addr:housenumber":"1015",
    "addr:postcode":"59270",
    "addr:street":"7Th Ave Sw",
    "iso:country":"US",
    "sg:address":"1015 7th Ave SW",
    "sg:city":"Sidney",
    "sg:classifiers":[
        {
            "category":"Health Services",
            "subcategory":"Nursing And Care Facility",
            "type":"Services"
        },
        {
            "category":"Social Services",
            "subcategory":"Adult Care",
            "type":"Services"
        },
        {
            "category":"Travel",
            "subcategory":"Hotels & Motels",
            "type":"Entertainment"
        }
    ],
    "sg:phone":"+1 406 488 4682",
    "sg:postcode":"59270",
    "sg:province":"MT",
    "sg:tags":[
        "home",
        "residential",
        "intermediate",
        "resort"
    ],
    "wof:name":"Lodge The At Lone Tree Creek",
    "wof:placetype":"venue"
},
  "geometry": {"coordinates":[-104.16500000000001,47.707919],"type":"Point"}
}