{
  "type": "Feature",
  "properties": {
    "addr:full":"3713 Creekwood Rd Missoula MT 59802",
    "addr:housenumber":"3713",
    "addr:postcode":"59802",
    "addr:street":"Creekwood Rd",
    "iso:country":"US",
    "sg:address":"3713 Creekwood Rd",
    "sg:city":"Missoula",
    "sg:classifiers":[
        {
            "category":"Professional",
            "subcategory":"Engineering",
            "type":"Services"
        }
    ],
    "sg:phone":"+1 406 721 9908",
    "sg:postcode":"59802",
    "sg:province":"MT",
    "wof:name":"Horton Associates",
    "wof:placetype":"venue"
},
  "geometry": {"coordinates":[-113.97069399999999,46.899033],"type":"Point"}
}