{
  "type": "Feature",
  "properties": {
    "iso:country":"US",
    "sg:address":"3713 Creekwood Rd",
    "sg:city":"Missoula",
    "sg:classifiers":[
        {
            "category":"Professional",
            "subcategory":"Engineering",
            "type":"Services"
        }
    ],
    "sg:phone":"+1 406 721 9908",
    "sg:postcode":"59802",
    "sg:province":"MT",
    "wof:name":"Horton Associates",
    "wof:placetype":"venue"
},
  "geometry": {"coordinates":[-113.970694,46.899033],"type":"Point"}
}