{
  "type": "Feature",
  "properties": {
    "iso:country":"US",
    "sg:address":"7 7th Ave W",
    "sg:city":"Polson",
    "sg:classifiers":[
        {
            "category":"Social Services",
            "type":"Services"
        }
    ],
    "sg:phone":"+1 406 883 0002",
    "sg:postcode":"59860",
    "sg:province":"MT",
    "sg:tags":[
        "worker"
    ],
    "wof:name":"Margaret Kearney Lcsw",
    "wof:placetype":"venue"
},
  "geometry": {"coordinates":[-114.16486399999999,47.689159],"type":"Point"}
}