{
  "type": "Feature",
  "properties": {
    "iso:country":"US",
    "sg:address":"110 S Grand Ave",
    "sg:city":"Bozeman",
    "sg:classifiers":[
        {
            "category":"Organizations",
            "subcategory":"Religious Organization",
            "type":"Services"
        }
    ],
    "sg:phone":"+1 406 586 6944",
    "sg:postcode":"59715",
    "sg:province":"MT",
    "wof:name":"Grand Avenue Christian Church",
    "wof:placetype":"venue"
},
  "geometry": {"coordinates":[-111.040047,45.678144],"type":"Point"}
}