{
  "type": "Feature",
  "properties": {
    "addr:full":"1000 Grizzly Trl Butte MT 59701",
    "addr:housenumber":"1000",
    "addr:postcode":"mt 59701",
    "addr:street":"Grizzly Trl",
    "iso:country":"US",
    "sg:address":"1000 Grizzly Trl",
    "sg:city":"Butte",
    "sg:classifiers":[
        {
            "category":"Restaurant",
            "type":"Food & Drink"
        }
    ],
    "sg:menulink":"http://www.allmenus.com/mt/butte/211856-mcdonalds/menu/",
    "sg:phone":"+1 406 782 2565",
    "sg:postcode":"59701",
    "sg:province":"MT",
    "sg:tags":[
        "burger",
        "american"
    ],
    "wof:name":"McDonald's",
    "wof:placetype":"venue"
},
  "geometry": {"coordinates":[-112.60632200000001,46.003204],"type":"Point"}
}