{
  "type": "Feature",
  "properties": {
    "iso:country":"US",
    "sg:address":"815 19th St N",
    "sg:city":"Great Falls",
    "sg:classifiers":[
        {
            "category":"Retail",
            "subcategory":"Auto Repair",
            "type":"Services"
        }
    ],
    "sg:phone":"+1 406 452 9608",
    "sg:postcode":"59401",
    "sg:province":"MT",
    "sg:tags":[
        "glass",
        "replacement"
    ],
    "wof:name":"Cascade Autoglass Incorporated",
    "wof:placetype":"venue"
},
  "geometry": {"coordinates":[-111.27452099999999,47.514776],"type":"Point"}
}