{
  "type": "Feature",
  "properties": {
    "iso:country":"US",
    "sg:address":"12 Garden Ave",
    "sg:city":"Billings",
    "sg:classifiers":[
        {
            "category":"Social Services",
            "type":"Services"
        }
    ],
    "sg:phone":"+1 406 252 0488",
    "sg:postcode":"59101",
    "sg:province":"MT",
    "sg:tags":[
        "youth",
        "organization",
        "center"
    ],
    "sg:website":"www.montanagirlscouts.org",
    "wof:name":"Girl Scouts Treasure Trails",
    "wof:placetype":"venue"
},
  "geometry": {"coordinates":[-108.48399499999999,45.768029],"type":"Point"}
}