{
  "type": "Feature",
  "properties": {
    "iso:country":"US",
    "sg:address":"234 Moore Ln",
    "sg:city":"Billings",
    "sg:classifiers":[
        {
            "category":"Professional",
            "subcategory":"Management & Consulting",
            "type":"Services"
        }
    ],
    "sg:phone":"+1 406 655 1116",
    "sg:postcode":"59101",
    "sg:province":"MT",
    "sg:tags":[
        "construction"
    ],
    "wof:name":"Hulteng Ccm Inc",
    "wof:placetype":"venue"
},
  "geometry": {"coordinates":[-108.54228,45.763922],"type":"Point"}
}