{
  "type": "Feature",
  "properties": {
    "iso:country":"US",
    "sg:address":"575 Blue Slide Rd",
    "sg:city":"Thompson Falls",
    "sg:classifiers":[
        {
            "category":"Professional",
            "type":"Services"
        }
    ],
    "sg:phone":"+1 406 827 4535",
    "sg:postcode":"59873",
    "sg:province":"MT",
    "sg:tags":[
        "establishment"
    ],
    "wof:name":"Leufkens Co",
    "wof:placetype":"venue"
},
  "geometry": {"coordinates":[-115.394785,47.665833],"type":"Point"}
}