{
  "type": "Feature",
  "properties": {
    "addr:full":"440 2nd Ave N Glasgow MT 59230",
    "addr:housenumber":"440",
    "addr:postcode":"59230",
    "addr:street":"2Nd Ave N",
    "iso:country":"US",
    "sg:address":"440 2nd Ave N",
    "sg:city":"Glasgow",
    "sg:classifiers":[
        {
            "category":"Autos & Motor Vehicles",
            "subcategory":"Automobile Sales",
            "type":"Retail Goods"
        }
    ],
    "sg:phone":"+1 406 228 4381",
    "sg:postcode":"59230",
    "sg:province":"MT",
    "sg:tags":[
        "used"
    ],
    "wof:name":"Newton Motors Inc",
    "wof:placetype":"venue"
},
  "geometry": {"coordinates":[-106.632541,48.196881],"type":"Point"}
}