{
  "type": "Feature",
  "properties": {
    "addr:full":"3900 Olympic Blvd Billings MT 59102",
    "addr:housenumber":"3900",
    "addr:postcode":"59102",
    "addr:street":"Olympic Blvd",
    "iso:country":"US",
    "sg:address":"3900 Olympic Blvd",
    "sg:city":"Billings",
    "sg:classifiers":[
        {
            "category":"Building & Trades",
            "subcategory":"Construction",
            "type":"Services"
        }
    ],
    "sg:phone":"+1 406 861 2277",
    "sg:postcode":"59102",
    "sg:province":"MT",
    "sg:tags":[
        "dry wall",
        "contractor"
    ],
    "wof:name":"Rok Wall Systems",
    "wof:placetype":"venue"
},
  "geometry": {"coordinates":[-108.616095,45.757672],"type":"Point"}
}