{
  "type": "Feature",
  "properties": {
    "addr:full":"53 W Broadway St Butte MT 59701",
    "addr:housenumber":"53",
    "addr:postcode":"mt 59701",
    "addr:street":"W Broadway St",
    "iso:country":"US",
    "sg:address":"53 W Broadway St",
    "sg:city":"Butte",
    "sg:classifiers":[
        {
            "category":"Retail",
            "subcategory":"Repair Shop",
            "type":"Services"
        }
    ],
    "sg:phone":"+1 406 723 3321",
    "sg:postcode":"59701",
    "sg:province":"MT",
    "wof:name":"Buffalo Gallery",
    "wof:placetype":"venue"
},
  "geometry": {"coordinates":[-112.53724699999999,46.013668],"type":"Point"}
}