{
  "type": "Feature",
  "properties": {
    "addr:full":"1038 Main St Billings MT 59105",
    "addr:housenumber":"1038",
    "addr:postcode":"59105",
    "addr:street":"Main St",
    "iso:country":"US",
    "sg:address":"1038 Main St",
    "sg:city":"Billings",
    "sg:classifiers":[
        {
            "category":"Social Services",
            "subcategory":"Child Care",
            "type":"Services"
        }
    ],
    "sg:phone":"+1 406 248 4249",
    "sg:postcode":"59105",
    "sg:province":"MT",
    "wof:name":"Grannys Hugs",
    "wof:placetype":"venue"
},
  "geometry": {"coordinates":[-108.470803,45.818349],"type":"Point"}
}