{
  "type": "Feature",
  "properties": {
    "iso:country":"US",
    "sg:address":"2003 Bridger Dr",
    "sg:city":"Bozeman",
    "sg:classifiers":[
        {
            "category":"Wholesale",
            "subcategory":"Electrical",
            "type":"Manufacturing & Wholesale Goods"
        }
    ],
    "sg:phone":"+1 406 587 3535",
    "sg:postcode":"59715",
    "sg:province":"MT",
    "sg:tags":[
        "electronic"
    ],
    "wof:name":"At & Lee",
    "wof:placetype":"venue"
},
  "geometry": {"coordinates":[-111.01820499999999,45.702804],"type":"Point"}
}