{
  "type": "Feature",
  "properties": {
    "iso:country":"US",
    "sg:address":"6 Mountain View Rd",
    "sg:city":"Big Timber",
    "sg:classifiers":[
        {
            "category":"Professional",
            "type":"Services"
        }
    ],
    "sg:phone":"+1 406 932 4161",
    "sg:postcode":"59067",
    "sg:province":"MT",
    "sg:tags":[
        "establishment"
    ],
    "wof:name":"Barbara Van Cleve Studio",
    "wof:placetype":"venue"
},
  "geometry": {"coordinates":[-109.21454900000001,45.831584],"type":"Point"}
}