{
  "type": "Feature",
  "properties": {
    "iso:country":"US",
    "sg:address":"109 W Towne St",
    "sg:city":"Glendive",
    "sg:classifiers":[
        {
            "category":"Personal",
            "subcategory":"Beauty Salon",
            "type":"Services"
        }
    ],
    "sg:phone":"+1 406 377 2588",
    "sg:postcode":"59330",
    "sg:province":"MT",
    "sg:tags":[
        "shop"
    ],
    "wof:name":"Your Beauty Shop & Boutique",
    "wof:placetype":"venue"
},
  "geometry": {"coordinates":[-104.71322,47.105429],"type":"Point"}
}