{
  "type": "Feature",
  "properties": {
    "iso:country":"US",
    "sg:address":"25 Annette Park Dr",
    "sg:city":"Bozeman",
    "sg:classifiers":[
        {
            "category":"Professional",
            "subcategory":"Engineering",
            "type":"Services"
        }
    ],
    "sg:phone":"+1 406 586 0701",
    "sg:postcode":"59715",
    "sg:province":"MT",
    "wof:name":"Van Mullem Engineering Pllc",
    "wof:placetype":"venue"
},
  "geometry": {"coordinates":[-111.024165,45.635835],"type":"Point"}
}