{
  "type": "Feature",
  "properties": {
    "iso:country":"US",
    "sg:address":"516 E Tamarack St",
    "sg:city":"Bozeman",
    "sg:classifiers":[
        {
            "category":"Manufacturing",
            "subcategory":"Tools & Machinery",
            "type":"Manufacturing & Wholesale Goods"
        }
    ],
    "sg:phone":"+1 406 556 5740",
    "sg:postcode":"59715",
    "sg:province":"MT",
    "sg:tags":[
        "instrument",
        "optical",
        "lense"
    ],
    "sg:website":"www.latticematerials.com",
    "wof:name":"Lattice Materials",
    "wof:placetype":"venue"
},
  "geometry": {"coordinates":[-111.029984,45.688532],"type":"Point"}
}