{
  "type": "Feature",
  "properties": {
    "addr:full":"107 Fulton St Thompson Falls MT 59873",
    "addr:housenumber":"107",
    "addr:postcode":"59873",
    "addr:street":"Fulton St",
    "iso:country":"US",
    "sg:address":"107 Fulton St",
    "sg:city":"Thompson Falls",
    "sg:classifiers":[
        {
            "category":"Banks & Credit Unions",
            "subcategory":"Bank",
            "type":"Services"
        }
    ],
    "sg:phone":"+1 406 827 7000",
    "sg:postcode":"59873",
    "sg:province":"MT",
    "wof:name":"First State Bank",
    "wof:placetype":"venue"
},
  "geometry": {"coordinates":[-115.348341,47.594272],"type":"Point"}
}