{
  "type": "Feature",
  "properties": {
    "iso:country":"US",
    "sg:address":"690 N Meridian Rd",
    "sg:city":"Kalispell",
    "sg:classifiers":[
        {
            "category":"Insurance",
            "subcategory":"Insurance Agent",
            "type":"Services"
        }
    ],
    "sg:phone":"+1 406 257 1252",
    "sg:postcode":"59901",
    "sg:province":"MT",
    "wof:name":"Farmers Insurance",
    "wof:placetype":"venue"
},
  "geometry": {"coordinates":[-114.330371,48.204795],"type":"Point"}
}