{
  "type": "Feature",
  "properties": {
    "iso:country":"US",
    "sg:address":"130 Riverside Rd",
    "sg:city":"Billings",
    "sg:classifiers":[
        {
            "category":"Retail",
            "subcategory":"Repair Shop",
            "type":"Services"
        }
    ],
    "sg:phone":"+1 406 252 5559",
    "sg:postcode":"59101",
    "sg:province":"MT",
    "sg:tags":[
        "pipe",
        "cleaning"
    ],
    "wof:name":"Pace Construction Inc",
    "wof:placetype":"venue"
},
  "geometry": {"coordinates":[-108.504597,45.765127],"type":"Point"}
}