{
  "type": "Feature",
  "properties": {
    "iso:country":"US",
    "sg:address":"3318 3rd Ave N",
    "sg:city":"Billings",
    "sg:classifiers":[
        {
            "category":"Professional",
            "subcategory":"Accounting & Tax Preparation",
            "type":"Services"
        }
    ],
    "sg:phone":"+1 406 252 0585",
    "sg:postcode":"59101",
    "sg:province":"MT",
    "sg:tags":[
        "accountant",
        "return"
    ],
    "wof:name":"Filby Accounting & Tax Svcs",
    "wof:placetype":"venue"
},
  "geometry": {"coordinates":[-108.514622,45.780315],"type":"Point"}
}