{
  "type": "Feature",
  "properties": {
    "iso:country":"US",
    "sg:address":"6787 Trade Center Ave",
    "sg:city":"Billings",
    "sg:classifiers":[
        {
            "category":"Wholesale",
            "subcategory":"Hardware",
            "type":"Manufacturing & Wholesale Goods"
        }
    ],
    "sg:phone":"+1 406 259 0950",
    "sg:postcode":"59101",
    "sg:province":"MT",
    "sg:tags":[
        "nut",
        "bolt"
    ],
    "sg:website":"www.bighornbolt.com",
    "wof:name":"Big Horn Bolt & Anchor",
    "wof:placetype":"venue"
},
  "geometry": {"coordinates":[-108.590157,45.73381],"type":"Point"}
}