{
  "type": "Feature",
  "properties": {
    "iso:country":"US",
    "sg:address":"7007 Bristol Ln",
    "sg:city":"Bozeman",
    "sg:classifiers":[
        {
            "category":"Building & Trades",
            "subcategory":"Construction",
            "type":"Services"
        }
    ],
    "sg:phone":"+1 406 585 3711",
    "sg:postcode":"59715",
    "sg:province":"MT",
    "sg:tags":[
        "residential",
        "custom"
    ],
    "wof:name":"Mavor Design & Construction",
    "wof:placetype":"venue"
},
  "geometry": {"coordinates":[-111.049274,45.590212],"type":"Point"}
}