{
  "type": "Feature",
  "properties": {
    "addr:full":"2709 Humble Rd Missoula MT 59804",
    "addr:postcode":"2709;59804",
    "addr:street":"Humble Rd",
    "iso:country":"US",
    "sg:address":"2709 Humble Rd",
    "sg:city":"Missoula",
    "sg:classifiers":[
        {
            "category":"Health Services",
            "subcategory":"Hospital",
            "type":"Services"
        }
    ],
    "sg:phone":"+1 406 549 5200",
    "sg:postcode":"59804",
    "sg:province":"MT",
    "sg:tags":[
        "mental"
    ],
    "wof:name":"Lorri Williams",
    "wof:placetype":"venue"
},
  "geometry": {"coordinates":[-114.092069,46.847875],"type":"Point"}
}