{
  "type": "Feature",
  "properties": {
    "iso:country":"US",
    "sg:address":"5917 Bridger Canyon Rd",
    "sg:city":"Bozeman",
    "sg:classifiers":[
        {
            "category":"Social Services",
            "subcategory":"Child Care",
            "type":"Services"
        }
    ],
    "sg:phone":"+1 406 582 0720",
    "sg:postcode":"59715",
    "sg:province":"MT",
    "sg:tags":[
        "day"
    ],
    "wof:name":"Creekside Nursery & Landscape",
    "wof:placetype":"venue"
},
  "geometry": {"coordinates":[-110.949201,45.706097],"type":"Point"}
}