{
  "type": "Feature",
  "properties": {
    "iso:country":"US",
    "sg:address":"100 N Johnson St",
    "sg:city":"Missoula",
    "sg:classifiers":[
        {
            "category":"Retail",
            "subcategory":"Auto Repair",
            "type":"Services"
        }
    ],
    "sg:phone":"+1 406 549 2569",
    "sg:postcode":"59801",
    "sg:province":"MT",
    "sg:tags":[
        "automotive"
    ],
    "wof:name":"Missoula Spring Bender",
    "wof:placetype":"venue"
},
  "geometry": {"coordinates":[-114.02812299999999,46.872907],"type":"Point"}
}