{
  "type": "Feature",
  "properties": {
    "iso:country":"US",
    "sg:address":"28888 US Hwy 2",
    "sg:city":"Shelby",
    "sg:classifiers":[
        {
            "category":"Farming",
            "subcategory":"Farm",
            "type":"Manufacturing & Wholesale Goods"
        }
    ],
    "sg:phone":"+1 406 432 2292",
    "sg:postcode":"59474",
    "sg:province":"MT",
    "sg:tags":[
        "crop",
        "general"
    ],
    "wof:name":"James McKenchie",
    "wof:placetype":"venue"
},
  "geometry": {"coordinates":[-111.666422,48.479003],"type":"Point"}
}