{
  "type": "Feature",
  "properties": {
    "addr:full":"8007 W Fork Rd Darby MT 59829",
    "addr:housenumber":"8007",
    "addr:postcode":"59829",
    "addr:street":"W Fork Rd",
    "iso:country":"US",
    "sg:address":"8007 W Fork Rd",
    "sg:city":"Darby",
    "sg:classifiers":[
        {
            "category":"Manufacturing",
            "subcategory":"Printing",
            "type":"Manufacturing & Wholesale Goods"
        }
    ],
    "sg:phone":"+1 406 349 2038",
    "sg:postcode":"59829",
    "sg:province":"MT",
    "sg:tags":[
        "book"
    ],
    "wof:name":"Blue Pine Publishing",
    "wof:placetype":"venue"
},
  "geometry": {"coordinates":[-114.27859599999999,45.722075],"type":"Point"}
}