{
  "type": "Feature",
  "properties": {
    "addr:full":"121 4th St N Great Falls MT 59401",
    "addr:housenumber":"121",
    "addr:postcode":"59401",
    "addr:street":"4Th St N",
    "iso:country":"US",
    "sg:address":"121 4th St N",
    "sg:city":"Great Falls",
    "sg:classifiers":[
        {
            "category":"Professional",
            "subcategory":"Lawyer & Legal Services",
            "type":"Services"
        }
    ],
    "sg:phone":"+1 406 727 5510",
    "sg:postcode":"59401",
    "sg:province":"MT",
    "sg:tags":[
        "attorney"
    ],
    "wof:name":"Steven M Hudspeth",
    "wof:placetype":"venue"
},
  "geometry": {"coordinates":[-111.300702,47.507292],"type":"Point"}
}