{
  "type": "Feature",
  "properties": {
    "addr:full":"1220 E Curtiss St Bozeman MT 59715",
    "addr:housenumber":"1220",
    "addr:postcode":"59715",
    "addr:street":"E Curtiss St",
    "iso:country":"US",
    "sg:address":"1220 E Curtiss St",
    "sg:city":"Bozeman",
    "sg:classifiers":[
        {
            "category":"Wholesale",
            "subcategory":"Vending Machines",
            "type":"Manufacturing & Wholesale Goods"
        }
    ],
    "sg:phone":"+1 406 585 0076",
    "sg:postcode":"59715",
    "sg:province":"MT",
    "sg:tags":[
        "operator"
    ],
    "wof:name":"Forkn Fondue LLC",
    "wof:placetype":"venue"
},
  "geometry": {"coordinates":[-111.01911,45.676739],"type":"Point"}
}