{
  "type": "Feature",
  "properties": {
    "iso:country":"US",
    "sg:address":"208 N 29th St",
    "sg:city":"Billings",
    "sg:classifiers":[
        {
            "category":"Insurance",
            "subcategory":"Insurance Agent",
            "type":"Services"
        }
    ],
    "sg:phone":"+1 406 255 8682",
    "sg:postcode":"59101",
    "sg:province":"MT",
    "wof:name":"Robert Field Financial Svc",
    "wof:placetype":"venue"
},
  "geometry": {"coordinates":[-108.508711,45.783109],"type":"Point"}
}