{
  "type": "Feature",
  "properties": {
    "addr:full":"1107 Brentwood Ave Bozeman MT 59718",
    "addr:housenumber":"1107",
    "addr:postcode":"59718",
    "addr:street":"Brentwood Ave",
    "iso:country":"US",
    "sg:address":"1107 Brentwood Ave",
    "sg:city":"Bozeman",
    "sg:classifiers":[
        {
            "category":"Real Estate",
            "subcategory":"Developer",
            "type":"Services"
        }
    ],
    "sg:phone":"+1 406 581 6060",
    "sg:postcode":"59718",
    "sg:province":"MT",
    "wof:name":"KLW Inc",
    "wof:placetype":"venue"
},
  "geometry": {"coordinates":[-111.06602100000001,45.690054],"type":"Point"}
}