{
  "type": "Feature",
  "properties": {
    "addr:full":"2727 Airport Rd Helena MT 59601",
    "addr:housenumber":"2727",
    "addr:postcode":"59601",
    "addr:street":"Airport Rd",
    "iso:country":"US",
    "sg:address":"2727 Airport Rd",
    "sg:city":"Helena",
    "sg:classifiers":[
        {
            "category":"Wholesale",
            "subcategory":"Beer",
            "type":"Manufacturing & Wholesale Goods"
        }
    ],
    "sg:phone":"+1 406 442 1570",
    "sg:postcode":"59601",
    "sg:province":"MT",
    "wof:name":"Sandy Macs Distributing",
    "wof:placetype":"venue"
},
  "geometry": {"coordinates":[-111.99279900000001,46.602029],"type":"Point"}
}