{
  "type": "Feature",
  "properties": {
    "addr:full":"2540 Hwy 78 Absarokee MT 59001",
    "addr:housenumber":"2540",
    "addr:postcode":"59001",
    "addr:street":"Hwy 78",
    "iso:country":"US",
    "sg:address":"2540 Hwy 78",
    "sg:city":"Absarokee",
    "sg:classifiers":[
        {
            "category":"Farming",
            "subcategory":"Livestock Farm",
            "type":"Manufacturing & Wholesale Goods"
        }
    ],
    "sg:phone":"+1 406 328 4174",
    "sg:postcode":"59001",
    "sg:province":"MT",
    "sg:tags":[
        "beef",
        "feedlot",
        "cattle"
    ],
    "wof:name":"Ferster Ranch",
    "wof:placetype":"venue"
},
  "geometry": {"coordinates":[-109.472069,45.420803],"type":"Point"}
}