{
  "type": "Feature",
  "properties": {
    "iso:country":"US",
    "sg:address":"6746 Linda Vista Blvd",
    "sg:city":"Missoula",
    "sg:classifiers":[
        {
            "category":"Professional",
            "subcategory":"Management & Consulting",
            "type":"Services"
        }
    ],
    "sg:phone":"+1 406 251 2887",
    "sg:postcode":"59803",
    "sg:province":"MT",
    "wof:name":"Eyi Integrated Marketing",
    "wof:placetype":"venue"
},
  "geometry": {"coordinates":[-114.05802,46.807858],"type":"Point"}
}