{
  "type": "Feature",
  "properties": {
    "addr:full":"3513 Norman Dr Missoula MT 59804",
    "addr:housenumber":"3513",
    "addr:postcode":"59804",
    "addr:street":"Norman Dr",
    "iso:country":"US",
    "sg:address":"3513 Norman Dr",
    "sg:city":"Missoula",
    "sg:phone":"+1 406 721 4377",
    "sg:postcode":"59804",
    "sg:province":"MT",
    "sg:tags":[
        "equipment",
        "commercial"
    ],
    "wof:name":"Atm of Montana Inc",
    "wof:placetype":"venue"
},
  "geometry": {"coordinates":[-114.067943,46.8601],"type":"Point"}
}