{
  "type": "Feature",
  "properties": {
    "iso:country":"US",
    "sg:address":"103 S Main St",
    "sg:city":"Livingston",
    "sg:classifiers":[
        {
            "category":"Professional",
            "subcategory":"Art Services",
            "type":"Services"
        }
    ],
    "sg:phone":"+1 406 222 8193",
    "sg:postcode":"59047",
    "sg:province":"MT",
    "sg:tags":[
        "photography",
        "commercial"
    ],
    "wof:name":"Tony Demin Photography",
    "wof:placetype":"venue"
},
  "geometry": {"coordinates":[-110.559967,45.661437],"type":"Point"}
}