{
  "type": "Feature",
  "properties": {
    "iso:country":"US",
    "sg:address":"1619 Grand Ave",
    "sg:city":"Butte",
    "sg:classifiers":[
        {
            "category":"Utilities",
            "subcategory":"Mobile Phone",
            "type":"Services"
        }
    ],
    "sg:phone":"+1 406 723 1133",
    "sg:postcode":"59701",
    "sg:province":"MT",
    "sg:tags":[
        "telephone",
        "cellular"
    ],
    "wof:name":"Copper City Wireless",
    "wof:placetype":"venue"
},
  "geometry": {"coordinates":[-112.51572400000001,45.999921],"type":"Point"}
}