{
  "type": "Feature",
  "properties": {
    "addr:full":"541 N Daly Ave Hamilton MT 59840",
    "addr:housenumber":"541",
    "addr:postcode":"59840",
    "addr:street":"N Daly Ave",
    "iso:country":"US",
    "sg:address":"541 N Daly Ave",
    "sg:city":"Hamilton",
    "sg:classifiers":[
        {
            "category":"Manufacturing",
            "subcategory":"Retail Goods",
            "type":"Manufacturing & Wholesale Goods"
        }
    ],
    "sg:phone":"+1 406 363 0022",
    "sg:postcode":"59840",
    "sg:province":"MT",
    "sg:tags":[
        "manufacturer"
    ],
    "wof:name":"CSE-Cine Support Equip",
    "wof:placetype":"venue"
},
  "geometry": {"coordinates":[-114.15037599999999,46.254084],"type":"Point"}
}