{
  "type": "Feature",
  "properties": {
    "addr:full":"25 S Ewing St Helena MT 59601",
    "addr:housenumber":"25",
    "addr:postcode":"59601",
    "addr:street":"S Ewing",
    "iso:country":"US",
    "sg:address":"25 S Ewing St",
    "sg:city":"Helena",
    "sg:classifiers":[
        {
            "category":"Social Services",
            "type":"Services"
        }
    ],
    "sg:phone":"+1 406 495 1936",
    "sg:postcode":"59601",
    "sg:province":"MT",
    "sg:tags":[
        "counselor",
        "marriage",
        "family"
    ],
    "wof:name":"Life Opportunities Consulting",
    "wof:placetype":"venue"
},
  "geometry": {"coordinates":[-112.03759599999999,46.584316],"type":"Point"}
}