{
  "type": "Feature",
  "properties": {
    "iso:country":"US",
    "sg:address":"9 E Main St",
    "sg:city":"Bozeman",
    "sg:classifiers":[
        {
            "category":"Restaurant",
            "type":"Food & Drink"
        }
    ],
    "sg:phone":"+1 406 587 3205",
    "sg:postcode":"59715",
    "sg:province":"MT",
    "sg:tags":[
        "eating"
    ],
    "wof:name":"Main Street Overeasy",
    "wof:placetype":"venue"
},
  "geometry": {"coordinates":[-111.037163,45.67934],"type":"Point"}
}