{
  "type": "Feature",
  "properties": {
    "iso:country":"US",
    "sg:address":"300 S 24th St W",
    "sg:city":"Billings",
    "sg:classifiers":[
        {
            "category":"Shopping",
            "subcategory":"Clothing, Apparel, & Fashions",
            "type":"Retail Goods"
        }
    ],
    "sg:phone":"+1 406 652 9568",
    "sg:postcode":"59102",
    "sg:province":"MT",
    "sg:tags":[
        "sportswear"
    ],
    "wof:name":"Champs Sports",
    "wof:placetype":"venue"
},
  "geometry": {"coordinates":[-108.576139,45.763449],"type":"Point"}
}