{
  "type": "Feature",
  "properties": {
    "iso:country":"US",
    "sg:address":"112 Central Ave",
    "sg:city":"Great Falls",
    "sg:classifiers":[
        {
            "category":"Food & Beverages",
            "subcategory":"Bakery",
            "type":"Retail Goods"
        }
    ],
    "sg:phone":"+1 406 727 5910",
    "sg:postcode":"59401",
    "sg:province":"MT",
    "sg:tags":[
        "pub"
    ],
    "wof:name":"Big Stack Bakery",
    "wof:placetype":"venue"
},
  "geometry": {"coordinates":[-111.30443699999999,47.505216],"type":"Point"}
}