{
  "type": "Feature",
  "properties": {
    "iso:country":"US",
    "sg:address":"514 7th St S",
    "sg:city":"Great Falls",
    "sg:classifiers":[
        {
            "category":"Building & Trades",
            "subcategory":"Construction",
            "type":"Services"
        }
    ],
    "sg:phone":"+1 406 452 0978",
    "sg:postcode":"59405",
    "sg:province":"MT",
    "sg:tags":[
        "residential"
    ],
    "wof:name":"Super Enterprises",
    "wof:placetype":"venue"
},
  "geometry": {"coordinates":[-111.29569499999999,47.499529],"type":"Point"}
}