{
  "type": "Feature",
  "properties": {
    "iso:country":"US",
    "sg:address":"11 17th Ave E",
    "sg:city":"Polson",
    "sg:classifiers":[
        {
            "category":"Health Services",
            "subcategory":"Nursing And Care Facility",
            "type":"Services"
        }
    ],
    "sg:phone":"+1 406 883 1011",
    "sg:postcode":"59860",
    "sg:province":"MT",
    "sg:tags":[
        "building",
        "intermediate",
        "apartment",
        "operator"
    ],
    "wof:name":"Saint Joseph Retirement Cmnty",
    "wof:placetype":"venue"
},
  "geometry": {"coordinates":[-114.164472,47.680169],"type":"Point"}
}