{
  "type": "Feature",
  "properties": {
    "addr:full":"203 W Madison Ave Belgrade MT 59714",
    "addr:housenumber":"203",
    "addr:postcode":"59714",
    "addr:street":"W Madison Ave",
    "iso:country":"US",
    "sg:address":"203 W Madison Ave",
    "sg:city":"Belgrade",
    "sg:classifiers":[
        {
            "category":"Manufacturing",
            "subcategory":"Printing",
            "type":"Manufacturing & Wholesale Goods"
        }
    ],
    "sg:phone":"+1 406 388 7516",
    "sg:postcode":"59714",
    "sg:province":"MT",
    "sg:tags":[
        "printer",
        "commercial"
    ],
    "wof:name":"Insty-Prints",
    "wof:placetype":"venue"
},
  "geometry": {"coordinates":[-111.183205,45.77301],"type":"Point"}
}