{
  "type": "Feature",
  "properties": {
    "iso:country":"US",
    "sg:address":"103 Shelby Dr",
    "sg:city":"Missoula",
    "sg:classifiers":[
        {
            "category":"Education",
            "subcategory":"Special Training",
            "type":"Public Place"
        }
    ],
    "sg:phone":"+1 406 251 5762",
    "sg:postcode":"59803",
    "sg:province":"MT",
    "sg:tags":[
        "instruction",
        "music"
    ],
    "wof:name":"Kindermusik",
    "wof:placetype":"venue"
},
  "geometry": {"coordinates":[-114.04679,46.822332],"type":"Point"}
}