{
  "type": "Feature",
  "properties": {
    "addr:full":"119 N Russell St Missoula MT 59801",
    "addr:housenumber":"119",
    "addr:postcode":"59801",
    "addr:street":"N Russell St",
    "iso:country":"US",
    "sg:address":"119 N Russell St",
    "sg:city":"Missoula",
    "sg:classifiers":[
        {
            "category":"Home & Garden",
            "subcategory":"Building Materials",
            "type":"Retail Goods"
        }
    ],
    "sg:phone":"+1 406 728 4750",
    "sg:postcode":"59801",
    "sg:province":"MT",
    "wof:name":"B M C West Corporation",
    "wof:placetype":"venue"
},
  "geometry": {"coordinates":[-114.018545,46.871713],"type":"Point"}
}