{
  "type": "Feature",
  "properties": {
    "iso:country":"US",
    "sg:address":"16 Story Rd",
    "sg:city":"Hysham",
    "sg:phone":"+1 406 342 5339",
    "sg:postcode":"59027",
    "sg:province":"MT",
    "sg:tags":[
        "irrigation",
        "company"
    ],
    "wof:name":"Hysham Irrigation District",
    "wof:placetype":"venue"
},
  "geometry": {"coordinates":[-110.744125,45.361861],"type":"Point"}
}