{
  "type": "Feature",
  "properties": {
    "addr:full":"126 6th Ave SW Ronan MT 59864",
    "addr:housenumber":"126",
    "addr:postcode":"59864",
    "addr:street":"6Th Ave Sw",
    "iso:country":"US",
    "sg:address":"126 6th Ave SW",
    "sg:city":"Ronan",
    "sg:classifiers":[
        {
            "category":"Health Services",
            "subcategory":"Doctor",
            "type":"Services"
        }
    ],
    "sg:phone":"+1 406 676 3600",
    "sg:postcode":"59864",
    "sg:province":"MT",
    "sg:tags":[
        "medical"
    ],
    "wof:name":"Ed T Vizcarra MD",
    "wof:placetype":"venue"
},
  "geometry": {"coordinates":[-114.10618100000001,47.528451],"type":"Point"}
}