{
  "type": "Feature",
  "properties": {
    "iso:country":"US",
    "sg:address":"2203 Montana Ave",
    "sg:city":"Billings",
    "sg:classifiers":[
        {
            "category":"Home & Garden",
            "subcategory":"Building Materials",
            "type":"Retail Goods"
        }
    ],
    "sg:phone":"+1 406 248 1171",
    "sg:postcode":"59101",
    "sg:province":"MT",
    "sg:tags":[
        "glass",
        "window",
        "plate"
    ],
    "wof:name":"United Glass",
    "wof:placetype":"venue"
},
  "geometry": {"coordinates":[-108.498816,45.78427],"type":"Point"}
}