{
  "type": "Feature",
  "properties": {
    "iso:country":"US",
    "sg:address":"3943 Brooks St",
    "sg:city":"Missoula",
    "sg:classifiers":[
        {
            "category":"Restaurant",
            "type":"Food & Drink"
        }
    ],
    "sg:phone":"+1 406 251 2525",
    "sg:postcode":"59804",
    "sg:province":"MT",
    "sg:tags":[
        "eating"
    ],
    "wof:name":"Petit De Tout LLC",
    "wof:placetype":"venue"
},
  "geometry": {"coordinates":[-114.03946,46.836616],"type":"Point"}
}