{
  "type": "Feature",
  "properties": {
    "iso:country":"US",
    "sg:address":"420 Nora St",
    "sg:city":"Missoula",
    "sg:classifiers":[
        {
            "category":"Wholesale",
            "subcategory":"Dairy",
            "type":"Manufacturing & Wholesale Goods"
        }
    ],
    "sg:phone":"+1 406 543 3173",
    "sg:postcode":"59802",
    "sg:province":"MT",
    "sg:tags":[
        "product"
    ],
    "wof:name":"Meadow Gold Dairies",
    "wof:placetype":"venue"
},
  "geometry": {"coordinates":[-114.00480899999999,46.877438],"type":"Point"}
}