{
  "type": "Feature",
  "properties": {
    "addr:full":"1029 Main St Billings MT 59105",
    "addr:housenumber":"1029",
    "addr:postcode":"59105",
    "addr:street":"Main St",
    "iso:country":"US",
    "sg:address":"1029 Main St",
    "sg:city":"Billings",
    "sg:classifiers":[
        {
            "category":"Restaurant",
            "type":"Food & Drink"
        }
    ],
    "sg:phone":"+1 406 248 4201",
    "sg:postcode":"59105",
    "sg:province":"MT",
    "sg:website":"www.circleinn.com",
    "wof:name":"Circle Inn",
    "wof:placetype":"venue"
},
  "geometry": {"coordinates":[-108.470634,45.817019],"type":"Point"}
}