{
  "type": "Feature",
  "properties": {
    "iso:country":"US",
    "sg:address":"1035 Mount Ave",
    "sg:city":"Missoula",
    "sg:classifiers":[
        {
            "category":"Wholesale",
            "subcategory":"Machinery & Supplies",
            "type":"Manufacturing & Wholesale Goods"
        }
    ],
    "sg:phone":"+1 406 728 2790",
    "sg:postcode":"59801",
    "sg:province":"MT",
    "sg:tags":[
        "industrial"
    ],
    "wof:name":"Frontier Fastening Systems",
    "wof:placetype":"venue"
},
  "geometry": {"coordinates":[-114.01325,46.855963],"type":"Point"}
}