{
  "type": "Feature",
  "properties": {
    "iso:country":"US",
    "sg:address":"5380 Violet Rd",
    "sg:city":"Bozeman",
    "sg:classifiers":[
        {
            "category":"Professional",
            "subcategory":"Business Services",
            "type":"Services"
        }
    ],
    "sg:phone":"+1 406 522 7785",
    "sg:postcode":"59718",
    "sg:province":"MT",
    "wof:name":"Foust Enterprises Inc",
    "wof:placetype":"venue"
},
  "geometry": {"coordinates":[-111.188661,45.652879],"type":"Point"}
}