{
  "type": "Feature",
  "properties": {
    "addr:full":"1839 Alderson Ave Billings MT 59102",
    "addr:housenumber":"1839",
    "addr:postcode":"59102",
    "addr:street":"Alderson Ave",
    "iso:country":"US",
    "sg:address":"1839 Alderson Ave",
    "sg:city":"Billings",
    "sg:classifiers":[
        {
            "category":"Building & Trades",
            "subcategory":"Construction",
            "type":"Services"
        }
    ],
    "sg:phone":"+1 406 252 8824",
    "sg:postcode":"59102",
    "sg:province":"MT",
    "sg:tags":[
        "house"
    ],
    "wof:name":"K D G Skirting & Carpentry",
    "wof:placetype":"venue"
},
  "geometry": {"coordinates":[-108.563351,45.783186],"type":"Point"}
}