{
  "type": "Feature",
  "properties": {
    "iso:country":"US",
    "sg:address":"750 Electric Ave",
    "sg:city":"Bigfork",
    "sg:classifiers":[
        {
            "category":"Organizations",
            "subcategory":"Religious Organization",
            "type":"Services"
        }
    ],
    "sg:phone":"+1 406 837 4547",
    "sg:postcode":"59911",
    "sg:province":"MT",
    "sg:tags":[
        "methodist",
        "church"
    ],
    "wof:name":"Community Untd Methdst Church",
    "wof:placetype":"venue"
},
  "geometry": {"coordinates":[-114.073336,48.064278],"type":"Point"}
}