{
  "type": "Feature",
  "properties": {
    "iso:country":"US",
    "sg:address":"3 2nd Ave E",
    "sg:city":"Polson",
    "sg:classifiers":[
        {
            "category":"Manufacturing",
            "subcategory":"Printing",
            "type":"Manufacturing & Wholesale Goods"
        }
    ],
    "sg:phone":"+1 406 883 4343",
    "sg:postcode":"59860",
    "sg:province":"MT",
    "sg:tags":[
        "newspaper"
    ],
    "sg:website":"www.leaderadvertiser.com",
    "wof:name":"Lake County Leader/Advertiser",
    "wof:placetype":"venue"
},
  "geometry": {"coordinates":[-114.16335100000001,47.694491],"type":"Point"}
}