{
  "type": "Feature",
  "properties": {
    "iso:country":"US",
    "sg:address":"1120 S Edick",
    "sg:city":"Red Lodge",
    "sg:classifiers":[
        {
            "category":"Real Estate",
            "subcategory":"Real Estate Operator",
            "type":"Services"
        }
    ],
    "sg:phone":"+1 406 446 3108",
    "sg:postcode":"59068",
    "sg:province":"MT",
    "sg:tags":[
        "building",
        "apartment"
    ],
    "wof:name":"Red Lodge Apts",
    "wof:placetype":"venue"
},
  "geometry": {"coordinates":[-109.25550800000001,45.174869],"type":"Point"}
}