{
  "type": "Feature",
  "properties": {
    "iso:country":"US",
    "sg:address":"1223 Grand Ave",
    "sg:city":"Billings",
    "sg:classifiers":[
        {
            "category":"Bars & Pubs",
            "type":"Food & Drink"
        }
    ],
    "sg:phone":"+1 406 248 6678",
    "sg:postcode":"59102",
    "sg:province":"MT",
    "wof:name":"Magoo's",
    "wof:placetype":"venue"
},
  "geometry": {"coordinates":[-108.54808199999999,45.784113],"type":"Point"}
}