{
  "type": "Feature",
  "properties": {
    "addr:full":"2033 11th Ave Helena MT 59601",
    "addr:housenumber":"2033",
    "addr:postcode":"59601",
    "addr:street":"11Th Ave",
    "iso:country":"US",
    "sg:address":"2033 11th Ave",
    "sg:city":"Helena",
    "sg:classifiers":[
        {
            "category":"Professional",
            "subcategory":"Business Services",
            "type":"Services"
        }
    ],
    "sg:phone":"+1 406 443 5430",
    "sg:postcode":"59601",
    "sg:province":"MT",
    "wof:name":"Denali Ventures Inc",
    "wof:placetype":"venue"
},
  "geometry": {"coordinates":[-112.004862,46.589761],"type":"Point"}
}