{
  "type": "Feature",
  "properties": {
    "iso:country":"US",
    "sg:address":"1831 11th Ave",
    "sg:city":"Helena",
    "sg:classifiers":[
        {
            "category":"Food & Beverages",
            "subcategory":"Groceries & Convenience Stores",
            "type":"Retail Goods"
        }
    ],
    "sg:phone":"+1 406 442 4865",
    "sg:postcode":"59601",
    "sg:province":"MT",
    "sg:tags":[
        "be",
        "station",
        "gasoline",
        "alcoholic"
    ],
    "wof:name":"Friendlys East",
    "wof:placetype":"venue"
},
  "geometry": {"coordinates":[-112.007642,46.589756],"type":"Point"}
}