{
  "type": "Feature",
  "properties": {
    "iso:country":"US",
    "sg:address":"678 Manning Rd",
    "sg:city":"Kalispell",
    "sg:classifiers":[
        {
            "category":"Building & Trades",
            "subcategory":"Construction",
            "type":"Services"
        }
    ],
    "sg:phone":"+1 406 257 1583",
    "sg:postcode":"59901",
    "sg:province":"MT",
    "sg:tags":[
        "excavation",
        "contractor"
    ],
    "wof:name":"Randy Gembala Excavation Co",
    "wof:placetype":"venue"
},
  "geometry": {"coordinates":[-114.16588900000001,48.12435],"type":"Point"}
}