{
  "type": "Feature",
  "properties": {
    "iso:country":"US",
    "sg:address":"159 S Manchester Rd",
    "sg:city":"Great Falls",
    "sg:classifiers":[
        {
            "category":"Real Estate",
            "subcategory":"Real Estate Agent",
            "type":"Services"
        }
    ],
    "sg:phone":"+1 406 453 8282",
    "sg:postcode":"59404",
    "sg:province":"MT",
    "sg:tags":[
        "investment",
        "closed"
    ],
    "wof:name":"Thurber Family Ltd Partne",
    "wof:placetype":"venue"
},
  "geometry": {"coordinates":[-111.446247,47.524653],"type":"Point"}
}