{
  "type": "Feature",
  "properties": {
    "iso:country":"US",
    "sg:address":"516 Poppy Pl",
    "sg:city":"Billings",
    "sg:classifiers":[
        {
            "category":"Professional",
            "subcategory":"Business Services",
            "type":"Services"
        }
    ],
    "sg:phone":"+1 406 896 0176",
    "sg:postcode":"59105",
    "sg:province":"MT",
    "wof:name":"Stocker Paralegal Services",
    "wof:placetype":"venue"
},
  "geometry": {"coordinates":[-108.50004300000001,45.811718],"type":"Point"}
}