{
  "type": "Feature",
  "properties": {
    "iso:country":"US",
    "sg:address":"233 Lewis Ave",
    "sg:city":"Billings",
    "sg:classifiers":[
        {
            "category":"Professional",
            "subcategory":"Management & Consulting",
            "type":"Services"
        }
    ],
    "sg:phone":"+1 406 256 3035",
    "sg:postcode":"59101",
    "sg:province":"MT",
    "sg:tags":[
        "business"
    ],
    "wof:name":"On Site Services LLC",
    "wof:placetype":"venue"
},
  "geometry": {"coordinates":[-108.522203,45.781176],"type":"Point"}
}