{
  "type": "Feature",
  "properties": {
    "iso:country":"US",
    "sg:address":"812 1st St S",
    "sg:city":"Hardin",
    "sg:classifiers":[
        {
            "category":"Farming",
            "subcategory":"Livestock Farm",
            "type":"Manufacturing & Wholesale Goods"
        }
    ],
    "sg:phone":"+1 406 665 3037",
    "sg:postcode":"59034",
    "sg:province":"MT",
    "sg:tags":[
        "beef",
        "feedlot",
        "cattle"
    ],
    "wof:name":"Randy Uffelman",
    "wof:placetype":"venue"
},
  "geometry": {"coordinates":[-107.619612,45.727295],"type":"Point"}
}