{
  "type": "Feature",
  "properties": {
    "iso:country":"US",
    "sg:address":"717 E Gallatin Ave",
    "sg:city":"Belgrade",
    "sg:classifiers":[
        {
            "category":"Building & Trades",
            "subcategory":"Construction",
            "type":"Services"
        }
    ],
    "sg:phone":"+1 406 388 0139",
    "sg:postcode":"59714",
    "sg:province":"MT",
    "sg:tags":[
        "house"
    ],
    "wof:name":"Bristol Const",
    "wof:placetype":"venue"
},
  "geometry": {"coordinates":[-111.172009,45.770855],"type":"Point"}
}