{
  "type": "Feature",
  "properties": {
    "iso:country":"US",
    "sg:address":"11 N Broadway Ave",
    "sg:city":"Red Lodge",
    "sg:classifiers":[
        {
            "category":"Shopping",
            "subcategory":"Florist",
            "type":"Retail Goods"
        }
    ],
    "sg:phone":"+1 406 446 1100",
    "sg:postcode":"59068",
    "sg:province":"MT",
    "wof:name":"Mignon's Gifts & Flowers",
    "wof:placetype":"venue"
},
  "geometry": {"coordinates":[-109.24706999999999,45.186801],"type":"Point"}
}