{
  "type": "Feature",
  "properties": {
    "iso:country":"US",
    "sg:address":"513 Dawson St",
    "sg:city":"Wolf Point",
    "sg:classifiers":[
        {
            "category":"Organizations",
            "subcategory":"Religious Organization",
            "type":"Services"
        }
    ],
    "sg:phone":"+1 406 653 2610",
    "sg:postcode":"59201",
    "sg:province":"MT",
    "sg:tags":[
        "church"
    ],
    "wof:name":"Immaculate Conception Catholic",
    "wof:placetype":"venue"
},
  "geometry": {"coordinates":[-105.642754,48.08717],"type":"Point"}
}