{
  "type": "Feature",
  "properties": {
    "iso:country":"US",
    "sg:address":"1720 10th Ave S",
    "sg:city":"Great Falls",
    "sg:classifiers":[
        {
            "category":"Home & Garden",
            "subcategory":"Household Appliances",
            "type":"Retail Goods"
        }
    ],
    "sg:phone":"+1 406 727 6692",
    "sg:postcode":"59405",
    "sg:province":"MT",
    "sg:tags":[
        "repair",
        "electrical"
    ],
    "wof:name":"All Vacuum Inc",
    "wof:placetype":"venue"
},
  "geometry": {"coordinates":[-111.276892,47.49415],"type":"Point"}
}