{
  "type": "Feature",
  "properties": {
    "addr:full":"1019 1st Ave N Billings MT 59101",
    "addr:housenumber":"1019",
    "addr:postcode":"59101",
    "addr:street":"1St Ave N",
    "iso:country":"US",
    "sg:address":"1019 1st Ave N",
    "sg:city":"Billings",
    "sg:classifiers":[
        {
            "category":"Autos & Motor Vehicles",
            "subcategory":"Automobile Sales",
            "type":"Retail Goods"
        }
    ],
    "sg:phone":"+1 406 245 0747",
    "sg:postcode":"59101",
    "sg:province":"MT",
    "sg:tags":[
        "car",
        "dealer"
    ],
    "wof:name":"Bear Tooth Auto Sales",
    "wof:placetype":"venue"
},
  "geometry": {"coordinates":[-108.48480600000001,45.792379],"type":"Point"}
}