{
  "type": "Feature",
  "properties": {
    "iso:country":"US",
    "sg:address":"2640 N Bridger Dr",
    "sg:city":"Billings",
    "sg:classifiers":[
        {
            "category":"Professional",
            "subcategory":"Advertising",
            "type":"Services"
        }
    ],
    "sg:phone":"+1 406 252 2680",
    "sg:postcode":"59102",
    "sg:province":"MT",
    "wof:name":"Inside Signs",
    "wof:placetype":"venue"
},
  "geometry": {"coordinates":[-108.583288,45.797606],"type":"Point"}
}