{
  "type": "Feature",
  "properties": {
    "iso:country":"US",
    "sg:address":"2425 US Hwy 2 E",
    "sg:city":"Kalispell",
    "sg:classifiers":[
        {
            "category":"Professional",
            "subcategory":"Advertising",
            "type":"Services"
        }
    ],
    "sg:phone":"+1 406 752 7751",
    "sg:postcode":"59901",
    "sg:province":"MT",
    "sg:tags":[
        "outdoor",
        "spec",
        "mfg"
    ],
    "wof:name":"Signs Northwest",
    "wof:placetype":"venue"
},
  "geometry": {"coordinates":[-114.276046,48.234525],"type":"Point"}
}