{
  "type": "Feature",
  "properties": {
    "iso:country":"US",
    "sg:address":"391 Airport Bench Rd",
    "sg:city":"Great Falls",
    "sg:phone":"+1 406 727 4960",
    "sg:postcode":"59404",
    "sg:province":"MT",
    "sg:tags":[
        "grain",
        "cash"
    ],
    "wof:name":"S & S Farms",
    "wof:placetype":"venue"
},
  "geometry": {"coordinates":[-111.47028,47.480562],"type":"Point"}
}