{
  "type": "Feature",
  "properties": {
    "iso:country":"US",
    "sg:address":"215 E Main St",
    "sg:city":"Sidney",
    "sg:classifiers":[
        {
            "category":"Retail",
            "subcategory":"Car Wash",
            "type":"Services"
        }
    ],
    "sg:phone":"+1 406 433 5277",
    "sg:postcode":"59270",
    "sg:province":"MT",
    "sg:tags":[
        "automobile",
        "detail",
        "clean"
    ],
    "wof:name":"Kleen Auto Detailing",
    "wof:placetype":"venue"
},
  "geometry": {"coordinates":[-104.155698,47.714732],"type":"Point"}
}