{
  "type": "Feature",
  "properties": {
    "iso:country":"US",
    "sg:address":"2320 Watts Ln",
    "sg:city":"Bozeman",
    "sg:classifiers":[
        {
            "category":"Professional",
            "subcategory":"Business Services",
            "type":"Services"
        }
    ],
    "sg:phone":"+1 406 582 9329",
    "sg:postcode":"59718",
    "sg:province":"MT",
    "wof:name":"RB Enterprises LLC",
    "wof:placetype":"venue"
},
  "geometry": {"coordinates":[-111.10090700000001,45.718007],"type":"Point"}
}