{
  "type": "Feature",
  "properties": {
    "iso:country":"US",
    "sg:address":"1303 Kaw Ave",
    "sg:city":"Butte",
    "sg:classifiers":[
        {
            "category":"Professional",
            "subcategory":"Business Services",
            "type":"Services"
        }
    ],
    "sg:phone":"+1 406 782 4100",
    "sg:postcode":"59701",
    "sg:province":"MT",
    "wof:name":"rountown Review",
    "wof:placetype":"venue"
},
  "geometry": {"coordinates":[-112.533337,45.997691],"type":"Point"}
}