{
  "type": "Feature",
  "properties": {
    "addr:full":"2106 Northridge Cir Billings MT 59102",
    "addr:housenumber":"2106",
    "addr:postcode":"59102",
    "addr:street":"Northridge Cir",
    "iso:country":"US",
    "sg:address":"2106 Northridge Cir",
    "sg:city":"Billings",
    "sg:classifiers":[
        {
            "category":"Building & Trades",
            "subcategory":"Construction",
            "type":"Services"
        }
    ],
    "sg:phone":"+1 406 245 5171",
    "sg:postcode":"59102",
    "sg:province":"MT",
    "sg:tags":[
        "carpentry",
        "contractor"
    ],
    "wof:name":"Oles Carpentry",
    "wof:placetype":"venue"
},
  "geometry": {"coordinates":[-108.584485,45.789922],"type":"Point"}
}