{
  "type": "Feature",
  "properties": {
    "iso:country":"US",
    "sg:address":"813 6th St SW",
    "sg:city":"Great Falls",
    "sg:classifiers":[
        {
            "category":"Personal",
            "subcategory":"Beauty Salon",
            "type":"Services"
        }
    ],
    "sg:phone":"+1 406 453 6321",
    "sg:postcode":"59404",
    "sg:province":"MT",
    "sg:tags":[
        "shop"
    ],
    "wof:name":"Clip Joint",
    "wof:placetype":"venue"
},
  "geometry": {"coordinates":[-111.325969,47.495658],"type":"Point"}
}