{
  "type": "Feature",
  "properties": {
    "addr:full":"300 Indian Creek Rd Huntley MT 59037",
    "addr:housenumber":"300",
    "addr:postcode":"59037",
    "addr:street":"Indian Creek Rd",
    "iso:country":"US",
    "sg:address":"300 Indian Creek Rd",
    "sg:city":"Huntley",
    "sg:classifiers":[
        {
            "category":"Manufacturing",
            "subcategory":"Chemicals & Compounds",
            "type":"Manufacturing & Wholesale Goods"
        }
    ],
    "sg:phone":"+1 406 348 2184",
    "sg:postcode":"59037",
    "sg:province":"MT",
    "sg:tags":[
        "explosive",
        "mfg"
    ],
    "wof:name":"Buckley Powder Co",
    "wof:placetype":"venue"
},
  "geometry": {"coordinates":[-108.033739,45.797838],"type":"Point"}
}