{
  "type": "Feature",
  "properties": {
    "iso:country":"US",
    "sg:address":"612 1st Ave S",
    "sg:city":"Lewistown",
    "sg:classifiers":[
        {
            "category":"Wholesale",
            "subcategory":"Meat",
            "type":"Manufacturing & Wholesale Goods"
        }
    ],
    "sg:phone":"+1 406 538 5932",
    "sg:postcode":"59457",
    "sg:province":"MT",
    "wof:name":"Snowy Mountain Meats",
    "wof:placetype":"venue"
},
  "geometry": {"coordinates":[-109.418903,47.06339],"type":"Point"}
}