{
  "type": "Feature",
  "properties": {
    "iso:country":"US",
    "sg:address":"7160 Fox Ln",
    "sg:city":"Darby",
    "sg:classifiers":[
        {
            "category":"Building & Trades",
            "subcategory":"Construction",
            "type":"Services"
        }
    ],
    "sg:phone":"+1 406 349 2764",
    "sg:postcode":"59829",
    "sg:province":"MT",
    "sg:tags":[
        "residential"
    ],
    "wof:name":"Toliver Construction",
    "wof:placetype":"venue"
},
  "geometry": {"coordinates":[-114.284705,45.805336],"type":"Point"}
}