{
  "type": "Feature",
  "properties": {
    "addr:full":"63 Kindsfather Dr Livingston MT 59047",
    "addr:housenumber":"63",
    "addr:postcode":"59047",
    "addr:street":"Kindsfather Dr",
    "iso:country":"US",
    "sg:address":"63 Kindsfather Dr",
    "sg:city":"Livingston",
    "sg:classifiers":[
        {
            "category":"Professional",
            "subcategory":"Management & Consulting",
            "type":"Services"
        }
    ],
    "sg:phone":"+1 406 222 1199",
    "sg:postcode":"59047",
    "sg:province":"MT",
    "wof:name":"Doeg Paul G & Associates LLC",
    "wof:placetype":"venue"
},
  "geometry": {"coordinates":[-110.546736,45.694925],"type":"Point"}
}