{
  "type": "Feature",
  "properties": {
    "iso:country":"US",
    "sg:address":"335 W Spruce St",
    "sg:city":"Missoula",
    "sg:classifiers":[
        {
            "category":"Professional",
            "subcategory":"Lawyer & Legal Services",
            "type":"Services"
        }
    ],
    "sg:phone":"+1 406 829 1766",
    "sg:postcode":"59802",
    "sg:province":"MT",
    "wof:name":"Meismer & Associate Pllc",
    "wof:placetype":"venue"
},
  "geometry": {"coordinates":[-113.996831,46.875142],"type":"Point"}
}