{
  "type": "Feature",
  "properties": {
    "iso:country":"US",
    "sg:address":"2917 Lohof Dr",
    "sg:city":"Billings",
    "sg:classifiers":[
        {
            "category":"Organizations",
            "subcategory":"Membership Organization",
            "type":"Services"
        }
    ],
    "sg:phone":"+1 406 252 5418",
    "sg:postcode":"59102",
    "sg:province":"MT",
    "wof:name":"Carol D Dimich Memorial Fund",
    "wof:placetype":"venue"
},
  "geometry": {"coordinates":[-108.544685,45.799952],"type":"Point"}
}