{
  "type": "Feature",
  "properties": {
    "iso:country":"US",
    "sg:address":"1204 S Rouse Ave",
    "sg:city":"Bozeman",
    "sg:classifiers":[
        {
            "category":"Building & Trades",
            "subcategory":"Construction",
            "type":"Services"
        }
    ],
    "sg:phone":"+1 406 586 9066",
    "sg:postcode":"59715",
    "sg:province":"MT",
    "sg:tags":[
        "work"
    ],
    "wof:name":"Bozeman Sheet Metal & Heating",
    "wof:placetype":"venue"
},
  "geometry": {"coordinates":[-111.03249,45.66433],"type":"Point"}
}