{
  "type": "Feature",
  "properties": {
    "iso:country":"US",
    "sg:address":"114 13th St W",
    "sg:city":"Billings",
    "sg:classifiers":[
        {
            "category":"Restaurant",
            "type":"Food & Drink"
        }
    ],
    "sg:phone":"+1 406 245 4976",
    "sg:postcode":"59102",
    "sg:province":"MT",
    "sg:tags":[
        "device",
        "operator",
        "eating",
        "amusement"
    ],
    "wof:name":"Luckys Grand Casino",
    "wof:placetype":"venue"
},
  "geometry": {"coordinates":[-108.548768,45.771928],"type":"Point"}
}