{
  "type": "Feature",
  "properties": {
    "iso:country":"US",
    "sg:address":"413 Dawson St",
    "sg:city":"Wolf Point",
    "sg:classifiers":[
        {
            "category":"Personal",
            "subcategory":"Beauty Salon",
            "type":"Services"
        }
    ],
    "sg:phone":"+1 406 653 3152",
    "sg:postcode":"59201",
    "sg:province":"MT",
    "sg:tags":[
        "shop"
    ],
    "wof:name":"Shear Creations Beauty Salon",
    "wof:placetype":"venue"
},
  "geometry": {"coordinates":[-105.644535,48.087088],"type":"Point"}
}