{
  "type": "Feature",
  "properties": {
    "iso:country":"US",
    "sg:address":"621 Charles St",
    "sg:city":"Billings",
    "sg:classifiers":[
        {
            "category":"Manufacturing",
            "subcategory":"Tools & Machinery",
            "type":"Manufacturing & Wholesale Goods"
        }
    ],
    "sg:phone":"+1 406 259 8444",
    "sg:postcode":"59101",
    "sg:province":"MT",
    "sg:tags":[
        "machine",
        "shop"
    ],
    "wof:name":"Northwest Plating Co",
    "wof:placetype":"venue"
},
  "geometry": {"coordinates":[-108.552429,45.758962],"type":"Point"}
}