{
  "type": "Feature",
  "properties": {
    "addr:full":"6040 Bethal Dr Manhattan MT 59741",
    "addr:postcode":"6040;59741",
    "addr:street":"Bethal Dr",
    "iso:country":"US",
    "sg:address":"6040 Bethal Dr",
    "sg:city":"Manhattan",
    "sg:classifiers":[
        {
            "category":"Organizations",
            "subcategory":"Religious Organization",
            "type":"Services"
        }
    ],
    "sg:phone":"+1 406 282 7445",
    "sg:postcode":"59741",
    "sg:province":"MT",
    "wof:name":"Bethel Christn Reformed Church",
    "wof:placetype":"venue"
},
  "geometry": {"coordinates":[-111.309258,45.750101],"type":"Point"}
}