{
  "type": "Feature",
  "properties": {
    "addr:full":"2019 Broadwater Ave Billings MT 59102",
    "addr:housenumber":"2019",
    "addr:postcode":"59102",
    "addr:street":"Broadwater Ave",
    "iso:country":"US",
    "sg:address":"2019 Broadwater Ave",
    "sg:city":"Billings",
    "sg:classifiers":[
        {
            "category":"Health Services",
            "subcategory":"Doctor",
            "type":"Services"
        }
    ],
    "sg:phone":"+1 406 237 8550",
    "sg:postcode":"59102",
    "sg:province":"MT",
    "wof:name":"Wagner Sarah Pa-C",
    "wof:placetype":"venue"
},
  "geometry": {"coordinates":[-108.567975,45.777012],"type":"Point"}
}