{
  "type": "Feature",
  "properties": {
    "iso:country":"US",
    "sg:address":"1495 Monad Rd",
    "sg:city":"Billings",
    "sg:classifiers":[
        {
            "category":"Wholesale",
            "subcategory":"Stationery",
            "type":"Manufacturing & Wholesale Goods"
        }
    ],
    "sg:phone":"+1 406 252 2103",
    "sg:postcode":"59102",
    "sg:province":"MT",
    "sg:tags":[
        "product",
        "paper"
    ],
    "wof:name":"Xpedx",
    "wof:placetype":"venue"
},
  "geometry": {"coordinates":[-108.553624,45.762508],"type":"Point"}
}