{
  "type": "Feature",
  "properties": {
    "iso:country":"US",
    "sg:address":"606 6th Ave S",
    "sg:city":"Glasgow",
    "sg:classifiers":[
        {
            "category":"Building & Trades",
            "subcategory":"Construction",
            "type":"Services"
        }
    ],
    "sg:phone":"+1 406 228 8071",
    "sg:postcode":"59230",
    "sg:province":"MT",
    "sg:tags":[
        "residential",
        "contractor"
    ],
    "wof:name":"Thoeny Construction Inc",
    "wof:placetype":"venue"
},
  "geometry": {"coordinates":[-106.64233,48.191536],"type":"Point"}
}