{
  "type": "Feature",
  "properties": {
    "iso:country":"US",
    "sg:address":"120 Lexington Dr",
    "sg:city":"Billings",
    "sg:classifiers":[
        {
            "category":"Education",
            "subcategory":"School",
            "type":"Public Place"
        }
    ],
    "sg:phone":"+1 406 655 3121",
    "sg:postcode":"59102",
    "sg:province":"MT",
    "wof:name":"Central Heights Elementary",
    "wof:placetype":"venue"
},
  "geometry": {"coordinates":[-108.572676,45.767832],"type":"Point"}
}