{
  "type": "Feature",
  "properties": {
    "iso:country":"US",
    "sg:address":"30 Riverside Dr",
    "sg:city":"Kalispell",
    "sg:classifiers":[
        {
            "category":"Autos & Motor Vehicles",
            "subcategory":"Auto Supplies",
            "type":"Retail Goods"
        }
    ],
    "sg:phone":"+1 406 257 2555",
    "sg:postcode":"59901",
    "sg:province":"MT",
    "wof:name":"Essential Speed Products",
    "wof:placetype":"venue"
},
  "geometry": {"coordinates":[-114.30407599999999,48.213501],"type":"Point"}
}