{
  "type": "Feature",
  "properties": {
    "addr:full":"15 1st St W Havre MT 59501",
    "addr:housenumber":"15",
    "addr:postcode":"59501",
    "addr:street":"1St St W",
    "iso:country":"US",
    "sg:address":"15 1st St W",
    "sg:city":"Havre",
    "sg:classifiers":[
        {
            "category":"Food & Beverages",
            "subcategory":"Groceries & Convenience Stores",
            "type":"Retail Goods"
        }
    ],
    "sg:phone":"+1 406 265 1404",
    "sg:postcode":"59501",
    "sg:province":"MT",
    "wof:name":"Gary & Leos IGA",
    "wof:placetype":"venue"
},
  "geometry": {"coordinates":[-109.684569,48.554205],"type":"Point"}
}