{
  "type": "Feature",
  "properties": {
    "iso:country":"US",
    "sg:address":"709 Continental Way",
    "sg:city":"Missoula",
    "sg:classifiers":[
        {
            "category":"Freight",
            "type":"Transportation"
        }
    ],
    "sg:phone":"+1 406 721 0589",
    "sg:postcode":"59803",
    "sg:province":"MT",
    "sg:tags":[
        "trucking"
    ],
    "wof:name":"W-W Transport",
    "wof:placetype":"venue"
},
  "geometry": {"coordinates":[-114.007983,46.832189],"type":"Point"}
}