{
  "type": "Feature",
  "properties": {
    "addr:full":"201 Main St Victor MT 59875",
    "addr:housenumber":"201",
    "addr:postcode":"59875",
    "addr:street":"Main St",
    "iso:country":"US",
    "sg:address":"201 Main St",
    "sg:city":"Victor",
    "sg:classifiers":[
        {
            "category":"Government",
            "subcategory":"Post Office",
            "type":"Public Place"
        }
    ],
    "sg:phone":"+1 406 642 3361",
    "sg:postcode":"59875",
    "sg:province":"MT",
    "wof:name":"US Post Office",
    "wof:placetype":"venue"
},
  "geometry": {"coordinates":[-114.147373,46.418088],"type":"Point"}
}