{
  "type": "Feature",
  "properties": {
    "addr:full":"403 Main St Fort Benton MT 59442",
    "addr:housenumber":"403",
    "addr:postcode":"59442",
    "addr:street":"Main St",
    "iso:country":"US",
    "sg:address":"403 Main St",
    "sg:city":"Fort Benton",
    "sg:classifiers":[
        {
            "category":"Building & Trades",
            "subcategory":"Plumbing",
            "type":"Services"
        }
    ],
    "sg:phone":"+1 406 622 5565",
    "sg:postcode":"59442",
    "sg:province":"MT",
    "sg:tags":[
        "plumbing",
        "air",
        "conditioning",
        "heating"
    ],
    "wof:name":"Longhorn Plumbling & Heating",
    "wof:placetype":"venue"
},
  "geometry": {"coordinates":[-110.677999,47.809158],"type":"Point"}
}