{
  "type": "Feature",
  "properties": {
    "iso:country":"US",
    "sg:address":"902 Wyoming Ave",
    "sg:city":"Billings",
    "sg:classifiers":[
        {
            "category":"Health Services",
            "subcategory":"Doctor",
            "type":"Services"
        }
    ],
    "sg:phone":"+1 406 252 6082",
    "sg:postcode":"59101",
    "sg:province":"MT",
    "sg:tags":[
        "physician",
        "surgeon",
        "medical"
    ],
    "wof:name":"Burford Psychiatric Service",
    "wof:placetype":"venue"
},
  "geometry": {"coordinates":[-108.53936,45.77797],"type":"Point"}
}