{
  "type": "Feature",
  "properties": {
    "iso:country":"US",
    "sg:address":"1805 Maurice Ave",
    "sg:city":"Missoula",
    "sg:classifiers":[
        {
            "category":"Building & Trades",
            "subcategory":"Construction",
            "type":"Services"
        }
    ],
    "sg:phone":"+1 406 728 7567",
    "sg:postcode":"59801",
    "sg:province":"MT",
    "sg:tags":[
        "roofing",
        "contractor"
    ],
    "wof:name":"Max-Tite Metal Roof Systems",
    "wof:placetype":"venue"
},
  "geometry": {"coordinates":[-113.986911,46.853218],"type":"Point"}
}