{
  "type": "Feature",
  "properties": {
    "iso:country":"US",
    "sg:address":"189 River Pl",
    "sg:city":"Kalispell",
    "sg:classifiers":[
        {
            "category":"Professional",
            "type":"Services"
        }
    ],
    "sg:phone":"+1 406 755 1956",
    "sg:postcode":"59901",
    "sg:province":"MT",
    "sg:tags":[
        "establishment"
    ],
    "wof:name":"Lair & Lair",
    "wof:placetype":"venue"
},
  "geometry": {"coordinates":[-114.28234999999999,48.219292],"type":"Point"}
}