{
  "type": "Feature",
  "properties": {
    "addr:full":"1313 W Park St Livingston MT 59047",
    "addr:housenumber":"1313",
    "addr:postcode":"59047",
    "addr:street":"W Park St",
    "iso:country":"US",
    "sg:address":"1313 W Park St",
    "sg:city":"Livingston",
    "sg:classifiers":[
        {
            "category":"Professional",
            "subcategory":"Art Services",
            "type":"Services"
        }
    ],
    "sg:phone":"+1 406 222 7051",
    "sg:postcode":"59047",
    "sg:province":"MT",
    "sg:tags":[
        "photographer"
    ],
    "wof:name":"Matt Long Photography",
    "wof:placetype":"venue"
},
  "geometry": {"coordinates":[-110.571935,45.651142],"type":"Point"}
}