{
  "type": "Feature",
  "properties": {
    "addr:full":"12472 Bull Lake Rd Troy MT 59935",
    "addr:housenumber":"12472",
    "addr:postcode":"59935",
    "addr:street":"Bull Lake Rd",
    "iso:country":"US",
    "sg:address":"12472 Bull Lake Rd",
    "sg:city":"Troy",
    "sg:classifiers":[
        {
            "category":"Professional",
            "type":"Services"
        }
    ],
    "sg:phone":"+1 406 295 4277",
    "sg:postcode":"59935",
    "sg:province":"MT",
    "wof:name":"Cochran George R Ailene A",
    "wof:placetype":"venue"
},
  "geometry": {"coordinates":[-115.841773,48.283534],"type":"Point"}
}