{
  "type": "Feature",
  "properties": {
    "iso:country":"US",
    "sg:address":"109 Golden Valley Loop",
    "sg:city":"Great Falls",
    "sg:classifiers":[
        {
            "category":"Retail",
            "subcategory":"Auto Repair",
            "type":"Services"
        }
    ],
    "sg:phone":"+1 406 453 1446",
    "sg:postcode":"59404",
    "sg:province":"MT",
    "sg:tags":[
        "body"
    ],
    "wof:name":"Chucks Custom Auto",
    "wof:placetype":"venue"
},
  "geometry": {"coordinates":[-111.351253,47.560019],"type":"Point"}
}