{
  "type": "Feature",
  "properties": {
    "addr:full":"238 2nd Ave S Glasgow MT 59230",
    "addr:housenumber":"238",
    "addr:postcode":"59230",
    "addr:street":"2Nd Ave S",
    "iso:country":"US",
    "sg:address":"238 2nd Ave S",
    "sg:city":"Glasgow",
    "sg:classifiers":[
        {
            "category":"Professional",
            "subcategory":"Employment Agencies",
            "type":"Services"
        }
    ],
    "sg:phone":"+1 406 228 9523",
    "sg:postcode":"59230",
    "sg:province":"MT",
    "sg:tags":[
        "opportunity"
    ],
    "wof:name":"Montana Job Svc",
    "wof:placetype":"venue"
},
  "geometry": {"coordinates":[-106.633504,48.19288],"type":"Point"}
}