{
  "type": "Feature",
  "properties": {
    "addr:full":"509 E 1st Ave Plentywood MT 59254",
    "addr:housenumber":"509",
    "addr:postcode":"59254",
    "addr:street":"E 1St Ave",
    "iso:country":"US",
    "sg:address":"509 E 1st Ave",
    "sg:city":"Plentywood",
    "sg:classifiers":[
        {
            "category":"Professional",
            "subcategory":"Business Services",
            "type":"Services"
        }
    ],
    "sg:phone":"+1 406 765 2254",
    "sg:postcode":"59254",
    "sg:province":"MT",
    "wof:name":"Hark Salvage Auctioneer",
    "wof:placetype":"venue"
},
  "geometry": {"coordinates":[-104.55126,48.77303],"type":"Point"}
}