{
  "type": "Feature",
  "properties": {
    "addr:full":"316 Clay St Glendive MT 59330",
    "addr:housenumber":"316",
    "addr:postcode":"59330",
    "addr:street":"Clay St",
    "iso:country":"US",
    "sg:address":"316 Clay St",
    "sg:city":"Glendive",
    "sg:classifiers":[
        {
            "category":"Shopping",
            "type":"Retail Goods"
        }
    ],
    "sg:phone":"+1 406 377 6948",
    "sg:postcode":"59330",
    "sg:province":"MT",
    "sg:tags":[
        "art",
        "boot",
        "repair"
    ],
    "wof:name":"Circle C Boot & Boot Repair",
    "wof:placetype":"venue"
},
  "geometry": {"coordinates":[-104.704472,47.119903],"type":"Point"}
}