{
  "type": "Feature",
  "properties": {
    "iso:country":"US",
    "sg:address":"427 Lordwith Dr",
    "sg:city":"Billings",
    "sg:classifiers":[
        {
            "category":"Communications",
            "type":"Services"
        }
    ],
    "sg:phone":"+1 406 254 0903",
    "sg:postcode":"59102",
    "sg:province":"MT",
    "wof:name":"Italics Business Communication",
    "wof:placetype":"venue"
},
  "geometry": {"coordinates":[-108.526532,45.786552],"type":"Point"}
}