{
  "type": "Feature",
  "properties": {
    "iso:country":"US",
    "sg:address":"330 Eastside Hwy",
    "sg:city":"Hamilton",
    "sg:classifiers":[
        {
            "category":"Farming",
            "subcategory":"Livestock Farm",
            "type":"Manufacturing & Wholesale Goods"
        }
    ],
    "sg:phone":"+1 406 375 0568",
    "sg:postcode":"59840",
    "sg:province":"MT",
    "sg:tags":[
        "producer"
    ],
    "wof:name":"Stock Farm LLC",
    "wof:placetype":"venue"
},
  "geometry": {"coordinates":[-114.140227,46.247646],"type":"Point"}
}