{
  "type": "Feature",
  "properties": {
    "iso:country":"US",
    "sg:address":"718 7th Ave SW",
    "sg:city":"Ronan",
    "sg:classifiers":[
        {
            "category":"Building & Trades",
            "subcategory":"Construction",
            "type":"Services"
        }
    ],
    "sg:phone":"+1 406 676 0291",
    "sg:postcode":"59864",
    "sg:province":"MT",
    "sg:tags":[
        "concrete",
        "contractor"
    ],
    "wof:name":"Rhineos Excavating",
    "wof:placetype":"venue"
},
  "geometry": {"coordinates":[-114.106983,47.522634],"type":"Point"}
}