{
  "type": "Feature",
  "properties": {
    "addr:full":"1201 W Porphyry St Butte MT 59701",
    "addr:housenumber":"1201",
    "addr:postcode":"mt 59701",
    "addr:street":"W Porphyry St",
    "iso:country":"US",
    "sg:address":"1201 W Porphyry St",
    "sg:city":"Butte",
    "sg:classifiers":[
        {
            "category":"Professional",
            "subcategory":"Engineering",
            "type":"Services"
        }
    ],
    "sg:phone":"+1 406 723 5092",
    "sg:postcode":"59701",
    "sg:province":"MT",
    "sg:tags":[
        "course",
        "mining",
        "instruction"
    ],
    "wof:name":"Susan Patton",
    "wof:placetype":"venue"
},
  "geometry": {"coordinates":[-112.554914,46.00848],"type":"Point"}
}