{
  "type": "Feature",
  "properties": {
    "iso:country":"US",
    "sg:address":"926 Smelter Ave NW",
    "sg:city":"Great Falls",
    "sg:classifiers":[
        {
            "category":"Organizations",
            "subcategory":"Religious Organization",
            "type":"Services"
        }
    ],
    "sg:phone":"+1 406 727 8781",
    "sg:postcode":"59404",
    "sg:province":"MT",
    "sg:tags":[
        "church"
    ],
    "wof:name":"Kingdom Hall Jehovah's Witness",
    "wof:placetype":"venue"
},
  "geometry": {"coordinates":[-111.327716,47.524349],"type":"Point"}
}