{
  "type": "Feature",
  "properties": {
    "addr:full":"528 Main St SW Ronan MT 59864",
    "addr:housenumber":"528",
    "addr:postcode":"59864",
    "addr:street":"Main St Sw",
    "iso:country":"US",
    "sg:address":"528 Main St SW",
    "sg:city":"Ronan",
    "sg:classifiers":[
        {
            "category":"Social Services",
            "type":"Services"
        }
    ],
    "sg:phone":"+1 406 676 2371",
    "sg:postcode":"59864",
    "sg:province":"MT",
    "wof:name":"Senior Citizens",
    "wof:placetype":"venue"
},
  "geometry": {"coordinates":[-114.10528499999999,47.528803],"type":"Point"}
}