{
  "type": "Feature",
  "properties": {
    "addr:full":"3746 Riada Dr Laurel MT 59044",
    "addr:housenumber":"3746",
    "addr:postcode":"59044",
    "addr:street":"Riada Dr",
    "iso:country":"US",
    "sg:address":"3746 Riada Dr",
    "sg:city":"Laurel",
    "sg:classifiers":[
        {
            "category":"Freight",
            "type":"Transportation"
        }
    ],
    "sg:phone":"+1 406 628 8990",
    "sg:postcode":"59044",
    "sg:province":"MT",
    "sg:tags":[
        "operator",
        "trucking"
    ],
    "wof:name":"Eddie Breum Trucking",
    "wof:placetype":"venue"
},
  "geometry": {"coordinates":[-108.799561,45.611601],"type":"Point"}
}