{
  "type": "Feature",
  "properties": {
    "iso:country":"US",
    "sg:address":"901 S Washington St",
    "sg:city":"Butte",
    "sg:classifiers":[
        {
            "category":"Real Estate",
            "subcategory":"Real Estate Operator",
            "type":"Services"
        }
    ],
    "sg:phone":"+1 406 723 4100",
    "sg:postcode":"59701",
    "sg:province":"MT",
    "sg:tags":[
        "mobile",
        "home",
        "site"
    ],
    "wof:name":"Tecumseh Lode Estates",
    "wof:placetype":"venue"
},
  "geometry": {"coordinates":[-112.541734,46.002756],"type":"Point"}
}