{
  "type": "Feature",
  "properties": {
    "iso:country":"US",
    "sg:address":"807 13th Ave S",
    "sg:city":"Great Falls",
    "sg:classifiers":[
        {
            "category":"Real Estate",
            "subcategory":"Real Estate Agent",
            "type":"Services"
        }
    ],
    "sg:phone":"+1 406 727 3000",
    "sg:postcode":"59405",
    "sg:province":"MT",
    "wof:name":"For Sale By Home Owner",
    "wof:placetype":"venue"
},
  "geometry": {"coordinates":[-111.29368599999999,47.491155],"type":"Point"}
}