{
  "type": "Feature",
  "properties": {
    "iso:country":"US",
    "sg:address":"3570 Farm To Market Rd",
    "sg:city":"Kalispell",
    "sg:classifiers":[
        {
            "category":"Manufacturing",
            "subcategory":"Metals",
            "type":"Manufacturing & Wholesale Goods"
        }
    ],
    "sg:phone":"+1 406 257 5450",
    "sg:postcode":"59901",
    "sg:province":"MT",
    "sg:tags":[
        "copper",
        "foundry"
    ],
    "wof:name":"Laloba Bronze & Co Inc",
    "wof:placetype":"venue"
},
  "geometry": {"coordinates":[-114.41733000000001,48.289372],"type":"Point"}
}