{
  "type": "Feature",
  "properties": {
    "iso:country":"US",
    "sg:address":"917 Bridger Dr",
    "sg:city":"Bozeman",
    "sg:classifiers":[
        {
            "category":"Retail",
            "subcategory":"Auto Repair",
            "type":"Services"
        }
    ],
    "sg:phone":"+1 406 585 5420",
    "sg:postcode":"59715",
    "sg:province":"MT",
    "sg:tags":[
        "body"
    ],
    "wof:name":"Autobody Experience Inc",
    "wof:placetype":"venue"
},
  "geometry": {"coordinates":[-111.024261,45.702774],"type":"Point"}
}