{
  "type": "Feature",
  "properties": {
    "addr:full":"5078 US Hwy 287 N Ennis MT 59729",
    "addr:housenumber":"5078",
    "addr:postcode":"59729",
    "addr:street":"Us Hwy 287 N",
    "iso:country":"US",
    "sg:address":"5078 US Hwy 287 N",
    "sg:city":"Ennis",
    "sg:classifiers":[
        {
            "category":"Building & Trades",
            "subcategory":"Plumbing",
            "type":"Services"
        }
    ],
    "sg:phone":"+1 406 682 7913",
    "sg:postcode":"59729",
    "sg:province":"MT",
    "sg:tags":[
        "contractor"
    ],
    "wof:name":"Madison Valley Plumbing",
    "wof:placetype":"venue"
},
  "geometry": {"coordinates":[-111.73069700000001,45.382812],"type":"Point"}
}