{
  "type": "Feature",
  "properties": {
    "addr:full":"299 Fairgrounds Rd Hamilton MT 59840",
    "addr:housenumber":"299",
    "addr:postcode":"59840",
    "addr:street":"Fairgrounds Rd",
    "iso:country":"US",
    "sg:address":"299 Fairgrounds Rd",
    "sg:city":"Hamilton",
    "sg:classifiers":[
        {
            "category":"Health Services",
            "subcategory":"Podiatrist",
            "type":"Services"
        }
    ],
    "sg:phone":"+1 406 363 4214",
    "sg:postcode":"59840",
    "sg:province":"MT",
    "wof:name":"Bitterroot Foot & Ankle",
    "wof:placetype":"venue"
},
  "geometry": {"coordinates":[-114.150476,46.25496],"type":"Point"}
}