{
  "type": "Feature",
  "properties": {
    "iso:country":"US",
    "sg:address":"1501 W Central Ave",
    "sg:city":"Missoula",
    "sg:classifiers":[
        {
            "category":"Professional",
            "subcategory":"Management & Consulting",
            "type":"Services"
        }
    ],
    "sg:phone":"+1 406 721 1977",
    "sg:postcode":"59801",
    "sg:province":"MT",
    "sg:tags":[
        "aquatic",
        "ecology",
        "analysis"
    ],
    "wof:name":"Rhithron Associates Inc",
    "wof:placetype":"venue"
},
  "geometry": {"coordinates":[-114.02014699999999,46.850653],"type":"Point"}
}