{
  "type": "Feature",
  "properties": {
    "iso:country":"US",
    "sg:address":"2155 Whitefish Stage",
    "sg:city":"Kalispell",
    "sg:classifiers":[
        {
            "category":"Professional",
            "subcategory":"Business Services",
            "type":"Services"
        }
    ],
    "sg:phone":"+1 406 755 7866",
    "sg:postcode":"59901",
    "sg:province":"MT",
    "wof:name":"Second Chance Enterprises Inc",
    "wof:placetype":"venue"
},
  "geometry": {"coordinates":[-114.308663,48.25568],"type":"Point"}
}