{
  "type": "Feature",
  "properties": {
    "iso:country":"US",
    "sg:address":"28030 US Hwy 10",
    "sg:city":"Huson",
    "sg:classifiers":[
        {
            "category":"Restaurant",
            "type":"Food & Drink"
        }
    ],
    "sg:phone":"+1 406 626 5668",
    "sg:postcode":"59846",
    "sg:province":"MT",
    "sg:tags":[
        "drinking",
        "eating"
    ],
    "wof:name":"Nine Mile House Inc",
    "wof:placetype":"venue"
},
  "geometry": {"coordinates":[-114.382462,47.021679],"type":"Point"}
}