{
  "type": "Feature",
  "properties": {
    "iso:country":"US",
    "sg:address":"122 J B Stetson St",
    "sg:city":"Billings",
    "sg:classifiers":[
        {
            "category":"Banks & Credit Unions",
            "subcategory":"Financial Services",
            "type":"Services"
        }
    ],
    "sg:phone":"+1 406 656 4325",
    "sg:postcode":"59106",
    "sg:province":"MT",
    "sg:tags":[
        "trust",
        "nonprofit",
        "management"
    ],
    "wof:name":"Routson Family Foundation",
    "wof:placetype":"venue"
},
  "geometry": {"coordinates":[-108.62111299999999,45.769753],"type":"Point"}
}