{
  "type": "Feature",
  "properties": {
    "iso:country":"US",
    "sg:address":"531 E Poindexter St",
    "sg:city":"Dillon",
    "sg:classifiers":[
        {
            "category":"Restaurant",
            "type":"Food & Drink"
        }
    ],
    "sg:phone":"+1 406 683 9004",
    "sg:postcode":"59725",
    "sg:province":"MT",
    "sg:tags":[
        "eating"
    ],
    "wof:name":"Stageline Pizza",
    "wof:placetype":"venue"
},
  "geometry": {"coordinates":[-112.640193,45.207723],"type":"Point"}
}