{
  "type": "Feature",
  "properties": {
    "addr:full":"334 E Broadway St Missoula MT 59802",
    "addr:housenumber":"334",
    "addr:postcode":"59802",
    "addr:street":"E Broadway St",
    "iso:country":"US",
    "sg:address":"334 E Broadway St",
    "sg:city":"Missoula",
    "sg:classifiers":[
        {
            "category":"Banks & Credit Unions",
            "subcategory":"Bank",
            "type":"Services"
        }
    ],
    "sg:phone":"+1 406 327 8777",
    "sg:postcode":"59802",
    "sg:province":"MT",
    "sg:tags":[
        "broker",
        "mortgage"
    ],
    "wof:name":"L & L Mortgage LLC",
    "wof:placetype":"venue"
},
  "geometry": {"coordinates":[-113.99003500000001,46.87102],"type":"Point"}
}