{
  "type": "Feature",
  "properties": {
    "iso:country":"US",
    "sg:address":"939 Getchell St",
    "sg:city":"Helena",
    "sg:classifiers":[
        {
            "category":"Manufacturing",
            "subcategory":"Food",
            "type":"Manufacturing & Wholesale Goods"
        }
    ],
    "sg:phone":"+1 406 442 5960",
    "sg:postcode":"59601",
    "sg:province":"MT",
    "sg:tags":[
        "malt",
        "beverage",
        "mfg"
    ],
    "wof:name":"Sleeping Giant Brewing",
    "wof:placetype":"venue"
},
  "geometry": {"coordinates":[-112.037779,46.59739],"type":"Point"}
}