{
  "type": "Feature",
  "properties": {
    "iso:country":"US",
    "sg:address":"700 N 7th St",
    "sg:city":"Miles City",
    "sg:classifiers":[
        {
            "category":"Retail",
            "subcategory":"Auto Repair",
            "type":"Services"
        }
    ],
    "sg:phone":"+1 406 232 1661",
    "sg:postcode":"59301",
    "sg:province":"MT",
    "sg:tags":[
        "body",
        "automobile",
        "painting"
    ],
    "wof:name":"Jack's Body Shop",
    "wof:placetype":"venue"
},
  "geometry": {"coordinates":[-105.853768,46.413401],"type":"Point"}
}