{
  "type": "Feature",
  "properties": {
    "addr:full":"124 Tailgate Ln Hamilton MT 59840",
    "addr:housenumber":"124",
    "addr:postcode":"59840",
    "addr:street":"Tailgate Ln",
    "iso:country":"US",
    "sg:address":"124 Tailgate Ln",
    "sg:city":"Hamilton",
    "sg:classifiers":[
        {
            "category":"Wholesale",
            "subcategory":"Electrical",
            "type":"Manufacturing & Wholesale Goods"
        }
    ],
    "sg:phone":"+1 406 363 0700",
    "sg:postcode":"59840",
    "sg:province":"MT",
    "sg:tags":[
        "electronic"
    ],
    "wof:name":"Big Sky Communications",
    "wof:placetype":"venue"
},
  "geometry": {"coordinates":[-114.17569899999999,46.256189],"type":"Point"}
}