{
  "type": "Feature",
  "properties": {
    "iso:country":"US",
    "sg:address":"640 19th St W",
    "sg:city":"Billings",
    "sg:classifiers":[
        {
            "category":"Social Services",
            "type":"Services"
        }
    ],
    "sg:phone":"+1 406 259 7219",
    "sg:postcode":"59102",
    "sg:province":"MT",
    "wof:name":"Amend Park",
    "wof:placetype":"venue"
},
  "geometry": {"coordinates":[-108.564232,45.776543],"type":"Point"}
}