{
  "type": "Feature",
  "properties": {
    "iso:country":"US",
    "sg:address":"361 Mill Creek Rd",
    "sg:city":"Livingston",
    "sg:classifiers":[
        {
            "category":"Farming",
            "subcategory":"Livestock Farm",
            "type":"Manufacturing & Wholesale Goods"
        }
    ],
    "sg:phone":"+1 406 333 4624",
    "sg:postcode":"59047",
    "sg:province":"MT",
    "sg:tags":[
        "animal",
        "general"
    ],
    "wof:name":"Rising Son Ranch Inc",
    "wof:placetype":"venue"
},
  "geometry": {"coordinates":[-110.63757200000001,45.385947],"type":"Point"}
}