{
  "type": "Feature",
  "properties": {
    "iso:country":"US",
    "sg:address":"818 Stuart St",
    "sg:city":"Helena",
    "sg:classifiers":[
        {
            "category":"Professional",
            "subcategory":"Business Services",
            "type":"Services"
        }
    ],
    "sg:phone":"+1 406 443 9293",
    "sg:postcode":"59601",
    "sg:province":"MT",
    "wof:name":"Max Pigman",
    "wof:placetype":"venue"
},
  "geometry": {"coordinates":[-112.049708,46.595818],"type":"Point"}
}