{
  "type": "Feature",
  "properties": {
    "iso:country":"US",
    "sg:address":"1610 10th Ave S",
    "sg:city":"Great Falls",
    "sg:classifiers":[
        {
            "category":"Utilities",
            "subcategory":"Mobile Phone",
            "type":"Services"
        }
    ],
    "sg:phone":"+1 406 727 1000",
    "sg:postcode":"59405",
    "sg:province":"MT",
    "sg:tags":[
        "wireless",
        "communications"
    ],
    "wof:name":"Cellular One",
    "wof:placetype":"venue"
},
  "geometry": {"coordinates":[-111.278397,47.494155],"type":"Point"}
}