{
  "type": "Feature",
  "properties": {
    "iso:country":"US",
    "sg:address":"105 N Ct",
    "sg:city":"Hamilton",
    "sg:classifiers":[
        {
            "category":"Building & Trades",
            "subcategory":"Cleaning & Sanitation",
            "type":"Services"
        }
    ],
    "sg:phone":"+1 406 363 1188",
    "sg:postcode":"59840",
    "sg:province":"MT",
    "sg:tags":[
        "window"
    ],
    "wof:name":"Nu-View Window Cleaning",
    "wof:placetype":"venue"
},
  "geometry": {"coordinates":[-114.153329,46.232902],"type":"Point"}
}