{
  "type": "Feature",
  "properties": {
    "iso:country":"US",
    "sg:address":"900 N Orange St",
    "sg:city":"Missoula",
    "sg:classifiers":[
        {
            "category":"Health Services",
            "subcategory":"Doctor",
            "type":"Services"
        }
    ],
    "sg:phone":"+1 406 728 1563",
    "sg:postcode":"59802",
    "sg:province":"MT",
    "sg:tags":[
        "medical"
    ],
    "wof:name":"Douglas L Woolley",
    "wof:placetype":"venue"
},
  "geometry": {"coordinates":[-113.993455,46.879439],"type":"Point"}
}