{
  "type": "Feature",
  "properties": {
    "addr:full":"2675 Central Ave Billings MT 59102",
    "addr:housenumber":"2675",
    "addr:postcode":"59102",
    "addr:street":"Central Ave",
    "iso:country":"US",
    "sg:address":"2675 Central Ave",
    "sg:city":"Billings",
    "sg:classifiers":[
        {
            "category":"Health Services",
            "subcategory":"Doctor",
            "type":"Services"
        }
    ],
    "sg:phone":"+1 406 238 2050",
    "sg:postcode":"59102",
    "sg:province":"MT",
    "sg:tags":[
        "medical"
    ],
    "wof:name":"Donald A Grewell",
    "wof:placetype":"venue"
},
  "geometry": {"coordinates":[-108.58421199999999,45.769812],"type":"Point"}
}