{
  "type": "Feature",
  "properties": {
    "addr:full":"731 Cooper St Missoula MT 59802",
    "addr:housenumber":"731",
    "addr:postcode":"59802",
    "addr:street":"Cooper St",
    "iso:country":"US",
    "sg:address":"731 Cooper St",
    "sg:city":"Missoula",
    "sg:classifiers":[
        {
            "category":"Professional",
            "subcategory":"Research",
            "type":"Services"
        }
    ],
    "sg:phone":"+1 406 549 8972",
    "sg:postcode":"59802",
    "sg:province":"MT",
    "sg:tags":[
        "consultant"
    ],
    "wof:name":"Historical Discoveries",
    "wof:placetype":"venue"
},
  "geometry": {"coordinates":[-114.00135899999999,46.878942],"type":"Point"}
}