{
  "type": "Feature",
  "properties": {
    "iso:country":"US",
    "sg:address":"909 Shirley Pl",
    "sg:city":"Belgrade",
    "sg:classifiers":[
        {
            "category":"Building & Trades",
            "subcategory":"Construction",
            "type":"Services"
        }
    ],
    "sg:phone":"+1 406 388 1511",
    "sg:postcode":"59714",
    "sg:province":"MT",
    "sg:tags":[
        "excavation",
        "contractor"
    ],
    "wof:name":"Mountain Movers",
    "wof:placetype":"venue"
},
  "geometry": {"coordinates":[-111.17740999999999,45.767803],"type":"Point"}
}