{
  "type": "Feature",
  "properties": {
    "addr:full":"322 Vaughn South Frontage Rd Great Falls MT 59404",
    "addr:housenumber":"322",
    "addr:postcode":"59404",
    "addr:street":"Vaughn South Frontage Rd",
    "iso:country":"US",
    "sg:address":"322 Vaughn South Frontage Rd",
    "sg:city":"Great Falls",
    "sg:classifiers":[
        {
            "category":"Insurance",
            "subcategory":"Insurance Agent",
            "type":"Services"
        }
    ],
    "sg:phone":"+1 406 727 7065",
    "sg:postcode":"59404",
    "sg:province":"MT",
    "wof:name":"Joe Barkshre",
    "wof:placetype":"venue"
},
  "geometry": {"coordinates":[-111.47872099999999,47.545558],"type":"Point"}
}