{
  "type": "Feature",
  "properties": {
    "iso:country":"US",
    "sg:address":"245 Blanchard Lake Rd",
    "sg:city":"Whitefish",
    "sg:classifiers":[
        {
            "category":"Retail",
            "subcategory":"Auto Repair",
            "type":"Services"
        }
    ],
    "sg:phone":"+1 406 862 5633",
    "sg:postcode":"59937",
    "sg:province":"MT",
    "sg:tags":[
        "repairing",
        "automobile"
    ],
    "wof:name":"Jack's Auto & Truck Repair",
    "wof:placetype":"venue"
},
  "geometry": {"coordinates":[-114.342876,48.370777],"type":"Point"}
}