{
  "type": "Feature",
  "properties": {
    "addr:full":"800 Minnesota Ave Billings MT 59101",
    "addr:housenumber":"800",
    "addr:postcode":"59101",
    "addr:street":"Minnesota Ave",
    "iso:country":"US",
    "sg:address":"800 Minnesota Ave",
    "sg:city":"Billings",
    "sg:classifiers":[
        {
            "category":"Manufacturing",
            "subcategory":"Food",
            "type":"Manufacturing & Wholesale Goods"
        }
    ],
    "sg:phone":"+1 406 254 2917",
    "sg:postcode":"59101",
    "sg:province":"MT",
    "sg:tags":[
        "rendering",
        "company"
    ],
    "wof:name":"Baker Commodities Inc",
    "wof:placetype":"venue"
},
  "geometry": {"coordinates":[-108.479614,45.792601],"type":"Point"}
}