{
  "type": "Feature",
  "properties": {
    "iso:country":"US",
    "sg:address":"801 Central Ave",
    "sg:city":"Great Falls",
    "sg:classifiers":[
        {
            "category":"Banks & Credit Unions",
            "subcategory":"Bank",
            "type":"Services"
        }
    ],
    "sg:phone":"+1 406 452 5050",
    "sg:postcode":"59401",
    "sg:province":"MT",
    "sg:tags":[
        "institution",
        "business"
    ],
    "wof:name":"B & R Check Holders Inc",
    "wof:placetype":"venue"
},
  "geometry": {"coordinates":[-111.292041,47.505224],"type":"Point"}
}