{
  "type": "Feature",
  "properties": {
    "addr:full":"538 Stillwater River Rd Absarokee MT 59001",
    "addr:housenumber":"538",
    "addr:postcode":"59001",
    "addr:street":"Stillwater River Rd",
    "iso:country":"US",
    "sg:address":"538 Stillwater River Rd",
    "sg:city":"Absarokee",
    "sg:classifiers":[
        {
            "category":"Food & Beverages",
            "subcategory":"Liquor & Beverages",
            "type":"Retail Goods"
        }
    ],
    "sg:phone":"+1 406 328 4447",
    "sg:postcode":"59001",
    "sg:province":"MT",
    "wof:name":"Absarokee Liquor Store",
    "wof:placetype":"venue"
},
  "geometry": {"coordinates":[-109.545883,45.526857],"type":"Point"}
}