{
  "type": "Feature",
  "properties": {
    "iso:country":"US",
    "sg:address":"1850 Rd 261",
    "sg:city":"Glendive",
    "sg:classifiers":[
        {
            "category":"Farming",
            "subcategory":"Livestock Farm",
            "type":"Manufacturing & Wholesale Goods"
        }
    ],
    "sg:phone":"+1 406 486 5414",
    "sg:postcode":"59330",
    "sg:province":"MT",
    "sg:tags":[
        "beef",
        "feedlot",
        "cattle"
    ],
    "wof:name":"K S Farms",
    "wof:placetype":"venue"
},
  "geometry": {"coordinates":[-104.96178399999999,46.910212],"type":"Point"}
}