{
  "type": "Feature",
  "properties": {
    "iso:country":"US",
    "sg:address":"167 Ritzman Ln",
    "sg:city":"Kalispell",
    "sg:classifiers":[
        {
            "category":"Professional",
            "subcategory":"Management & Consulting",
            "type":"Services"
        }
    ],
    "sg:phone":"+1 406 755 8123",
    "sg:postcode":"59901",
    "sg:province":"MT",
    "wof:name":"Denham & Assoc Inc",
    "wof:placetype":"venue"
},
  "geometry": {"coordinates":[-114.298852,48.23092],"type":"Point"}
}