{
  "type": "Feature",
  "properties": {
    "iso:country":"US",
    "sg:address":"2992 Olsen Rd",
    "sg:city":"Charlo",
    "sg:classifiers":[
        {
            "category":"Farming",
            "subcategory":"Livestock Farm",
            "type":"Manufacturing & Wholesale Goods"
        }
    ],
    "sg:phone":"+1 406 644 2708",
    "sg:postcode":"59824",
    "sg:province":"MT",
    "sg:tags":[
        "general"
    ],
    "wof:name":"Nelson Dairy",
    "wof:placetype":"venue"
},
  "geometry": {"coordinates":[-114.15119300000001,47.428241],"type":"Point"}
}