{
  "type": "Feature",
  "properties": {
    "iso:country":"US",
    "sg:address":"310 S Jackson St",
    "sg:city":"Plentywood",
    "sg:classifiers":[
        {
            "category":"Social Services",
            "subcategory":"Job Training",
            "type":"Services"
        }
    ],
    "sg:phone":"+1 406 765 1085",
    "sg:postcode":"59254",
    "sg:province":"MT",
    "sg:tags":[
        "rehabilitation"
    ],
    "wof:name":"Glenwood Inc Personal Care Hm",
    "wof:placetype":"venue"
},
  "geometry": {"coordinates":[-104.559421,48.771297],"type":"Point"}
}