{
  "type": "Feature",
  "properties": {
    "iso:country":"US",
    "sg:address":"5121 US Hwy 93",
    "sg:city":"Whitefish",
    "sg:classifiers":[
        {
            "category":"Restaurant",
            "type":"Food & Drink"
        }
    ],
    "sg:phone":"+1 406 652 5149",
    "sg:postcode":"59937",
    "sg:province":"MT",
    "sg:tags":[
        "eating"
    ],
    "wof:name":"Buffalo Bobs Pizza",
    "wof:placetype":"venue"
},
  "geometry": {"coordinates":[-114.48921199999999,48.457371],"type":"Point"}
}