{
  "type": "Feature",
  "properties": {
    "iso:country":"US",
    "sg:address":"14 4th St S",
    "sg:city":"Fairfield",
    "sg:classifiers":[
        {
            "category":"Education",
            "subcategory":"Library",
            "type":"Public Place"
        }
    ],
    "sg:phone":"+1 406 467 2477",
    "sg:postcode":"59436",
    "sg:province":"MT",
    "wof:name":"Fairfield Public Library",
    "wof:placetype":"venue"
},
  "geometry": {"coordinates":[-111.981748,47.614471],"type":"Point"}
}