{
  "type": "Feature",
  "properties": {
    "iso:country":"US",
    "sg:address":"521 Round Butte Rd W",
    "sg:city":"Ronan",
    "sg:classifiers":[
        {
            "category":"Professional",
            "subcategory":"Business Services",
            "type":"Services"
        }
    ],
    "sg:phone":"+1 406 676 2490",
    "sg:postcode":"59864",
    "sg:province":"MT",
    "wof:name":"Redman Auctions & Trading Post",
    "wof:placetype":"venue"
},
  "geometry": {"coordinates":[-114.104928,47.529695],"type":"Point"}
}