{
  "type": "Feature",
  "properties": {
    "iso:country":"US",
    "sg:address":"2255 Dry Creek Rd",
    "sg:city":"Belgrade",
    "sg:classifiers":[
        {
            "category":"Building & Trades",
            "subcategory":"Construction",
            "type":"Services"
        }
    ],
    "sg:phone":"+1 406 388 0736",
    "sg:postcode":"59714",
    "sg:province":"MT",
    "sg:tags":[
        "contractor"
    ],
    "wof:name":"On Site Management Log Yard",
    "wof:placetype":"venue"
},
  "geometry": {"coordinates":[-111.170372,45.801873],"type":"Point"}
}