{
  "type": "Feature",
  "properties": {
    "iso:country":"US",
    "sg:address":"2207 Grand Ave",
    "sg:city":"Billings",
    "sg:classifiers":[
        {
            "category":"Personal",
            "subcategory":"Beauty Salon",
            "type":"Services"
        }
    ],
    "sg:phone":"+1 406 656 4810",
    "sg:postcode":"59102",
    "sg:province":"MT",
    "sg:tags":[
        "shop"
    ],
    "wof:name":"Shortcuts Salon",
    "wof:placetype":"venue"
},
  "geometry": {"coordinates":[-108.576274,45.784176],"type":"Point"}
}