{
  "type": "Feature",
  "properties": {
    "iso:country":"US",
    "sg:address":"730 Main St",
    "sg:city":"Billings",
    "sg:classifiers":[
        {
            "category":"Professional",
            "subcategory":"Engineering",
            "type":"Services"
        }
    ],
    "sg:phone":"+1 406 248 3233",
    "sg:postcode":"59105",
    "sg:province":"MT",
    "sg:tags":[
        "engineer"
    ],
    "wof:name":"Mission Engineering Inc",
    "wof:placetype":"venue"
},
  "geometry": {"coordinates":[-108.471079,45.812808],"type":"Point"}
}