{
  "type": "Feature",
  "properties": {
    "iso:country":"US",
    "sg:address":"1205 Central Ave",
    "sg:city":"Great Falls",
    "sg:classifiers":[
        {
            "category":"Shopping",
            "type":"Retail Goods"
        }
    ],
    "sg:phone":"+1 406 452 8430",
    "sg:postcode":"59401",
    "sg:province":"MT",
    "sg:tags":[
        "burning",
        "gas",
        "related",
        "item",
        "wood",
        "spa",
        "pellet"
    ],
    "wof:name":"All Seasons Spas & Stoves Inc",
    "wof:placetype":"venue"
},
  "geometry": {"coordinates":[-111.285174,47.505266],"type":"Point"}
}