{
  "type": "Feature",
  "properties": {
    "iso:country":"US",
    "sg:address":"523 S Orange St",
    "sg:city":"Missoula",
    "sg:classifiers":[
        {
            "category":"Professional",
            "subcategory":"Lawyer & Legal Services",
            "type":"Services"
        }
    ],
    "sg:phone":"+1 406 543 0909",
    "sg:postcode":"59801",
    "sg:province":"MT",
    "sg:tags":[
        "attorney"
    ],
    "sg:website":"www.blakley.net",
    "wof:name":"John R Velk Law Offices",
    "wof:placetype":"venue"
},
  "geometry": {"coordinates":[-114.003596,46.866207],"type":"Point"}
}