{
  "type": "Feature",
  "properties": {
    "iso:country":"US",
    "sg:address":"4863 State Hwy 91 N",
    "sg:city":"Dillon",
    "sg:classifiers":[
        {
            "category":"Building & Trades",
            "subcategory":"Construction",
            "type":"Services"
        }
    ],
    "sg:phone":"+1 406 683 6354",
    "sg:postcode":"59725",
    "sg:province":"MT",
    "sg:tags":[
        "excavation",
        "contractor"
    ],
    "wof:name":"Huffakers Cnstr & Excvtg",
    "wof:placetype":"venue"
},
  "geometry": {"coordinates":[-112.64188300000001,45.259963],"type":"Point"}
}