{
  "type": "Feature",
  "properties": {
    "iso:country":"US",
    "sg:address":"1900 W Broadway St",
    "sg:city":"Missoula",
    "sg:classifiers":[
        {
            "category":"Manufacturing",
            "subcategory":"Printing",
            "type":"Manufacturing & Wholesale Goods"
        }
    ],
    "sg:phone":"+1 406 543 6222",
    "sg:postcode":"59808",
    "sg:province":"MT",
    "sg:tags":[
        "mfg"
    ],
    "wof:name":"Scrapbook Hide",
    "wof:placetype":"venue"
},
  "geometry": {"coordinates":[-114.02302,46.882343],"type":"Point"}
}