{
  "type": "Feature",
  "properties": {
    "iso:country":"US",
    "sg:address":"520 Holmes Ave",
    "sg:city":"Butte",
    "sg:classifiers":[
        {
            "category":"Retail",
            "subcategory":"Auto Repair",
            "type":"Services"
        }
    ],
    "sg:phone":"+1 406 494 3606",
    "sg:postcode":"59701",
    "sg:province":"MT",
    "sg:tags":[
        "wrecker"
    ],
    "wof:name":"Red Wrecker Svc",
    "wof:placetype":"venue"
},
  "geometry": {"coordinates":[-112.526813,45.974839],"type":"Point"}
}