{
  "type": "Feature",
  "properties": {
    "iso:country":"US",
    "sg:address":"775 N Valley Creek Rd",
    "sg:city":"Arlee",
    "sg:classifiers":[
        {
            "category":"Farming",
            "subcategory":"Livestock Farm",
            "type":"Manufacturing & Wholesale Goods"
        }
    ],
    "sg:phone":"+1 406 726 3649",
    "sg:postcode":"59821",
    "sg:province":"MT",
    "sg:tags":[
        "beef",
        "feedlot",
        "cattle"
    ],
    "wof:name":"Broken Circle Ranch Company",
    "wof:placetype":"venue"
},
  "geometry": {"coordinates":[-114.187157,47.229397],"type":"Point"}
}