{
  "type": "Feature",
  "properties": {
    "iso:country":"US",
    "sg:address":"423 Wells Ln",
    "sg:city":"Victor",
    "sg:classifiers":[
        {
            "category":"Farming",
            "subcategory":"Livestock Farm",
            "type":"Manufacturing & Wholesale Goods"
        }
    ],
    "sg:phone":"+1 406 642 3225",
    "sg:postcode":"59875",
    "sg:province":"MT",
    "sg:tags":[
        "beef",
        "feedlot",
        "cattle"
    ],
    "wof:name":"R & W Ranch",
    "wof:placetype":"venue"
},
  "geometry": {"coordinates":[-114.182693,46.38884],"type":"Point"}
}