{
  "type": "Feature",
  "properties": {
    "addr:full":"3200 Broadwater Ave Billings MT 59102",
    "addr:housenumber":"3200",
    "addr:postcode":"59102",
    "addr:street":"Broadwater Ave",
    "iso:country":"US",
    "sg:address":"3200 Broadwater Ave",
    "sg:city":"Billings",
    "sg:classifiers":[
        {
            "category":"Social Services",
            "subcategory":"Child Care",
            "type":"Services"
        }
    ],
    "sg:phone":"+1 406 652 1399",
    "sg:postcode":"59102",
    "sg:province":"MT",
    "sg:tags":[
        "day"
    ],
    "wof:name":"Little Treasures Daycare",
    "wof:placetype":"venue"
},
  "geometry": {"coordinates":[-108.599515,45.776789],"type":"Point"}
}