{
  "type": "Feature",
  "properties": {
    "addr:full":"819 W Park Ave Anaconda MT 59711",
    "addr:housenumber":"819",
    "addr:postcode":"59711",
    "addr:street":"W Park Ave",
    "iso:country":"US",
    "sg:address":"819 W Park Ave",
    "sg:city":"Anaconda",
    "sg:classifiers":[
        {
            "category":"Autos & Motor Vehicles",
            "subcategory":"Fuel & Gas Station",
            "type":"Retail Goods"
        }
    ],
    "sg:phone":"+1 406 563 6707",
    "sg:postcode":"59711",
    "sg:province":"MT",
    "sg:tags":[
        "station",
        "gasoline"
    ],
    "wof:name":"Town Pump Inc & Affiliates",
    "wof:placetype":"venue"
},
  "geometry": {"coordinates":[-112.963399,46.130946],"type":"Point"}
}