{
  "type": "Feature",
  "properties": {
    "iso:country":"US",
    "sg:address":"4261 Sourdough Rd",
    "sg:city":"Bozeman",
    "sg:classifiers":[
        {
            "category":"Manufacturing",
            "subcategory":"Tools & Machinery",
            "type":"Manufacturing & Wholesale Goods"
        }
    ],
    "sg:phone":"+1 406 522 8321",
    "sg:postcode":"59715",
    "sg:province":"MT",
    "sg:tags":[
        "industrial",
        "mfg"
    ],
    "wof:name":"Grind LLC",
    "wof:placetype":"venue"
},
  "geometry": {"coordinates":[-111.021723,45.635747],"type":"Point"}
}