{
  "type": "Feature",
  "properties": {
    "addr:full":"144 Mountain Goat Rd Hamilton MT 59840",
    "addr:housenumber":"144",
    "addr:postcode":"59840",
    "addr:street":"Mountain Goat Rd",
    "iso:country":"US",
    "sg:address":"144 Mountain Goat Rd",
    "sg:city":"Hamilton",
    "sg:classifiers":[
        {
            "category":"Real Estate",
            "subcategory":"Real Estate Agent",
            "type":"Services"
        }
    ],
    "sg:phone":"+1 406 363 4788",
    "sg:postcode":"59840",
    "sg:province":"MT",
    "wof:name":"Cathy Erickson",
    "wof:placetype":"venue"
},
  "geometry": {"coordinates":[-114.177234,46.212968],"type":"Point"}
}