{
  "type": "Feature",
  "properties": {
    "iso:country":"US",
    "sg:address":"742 Kensington Ave",
    "sg:city":"Missoula",
    "sg:classifiers":[
        {
            "category":"Real Estate",
            "subcategory":"Real Estate Agent",
            "type":"Services"
        }
    ],
    "sg:phone":"+1 406 542 0400",
    "sg:postcode":"59801",
    "sg:province":"MT",
    "wof:name":"By Owner Realty Network",
    "wof:placetype":"venue"
},
  "geometry": {"coordinates":[-114.00904300000001,46.853415],"type":"Point"}
}