{
  "type": "Feature",
  "properties": {
    "iso:country":"US",
    "sg:address":"1600 S 19th Ave",
    "sg:city":"Bozeman",
    "sg:classifiers":[
        {
            "category":"Restaurant",
            "type":"Food & Drink"
        }
    ],
    "sg:menulink":"http://www.allmenus.com/mt/bozeman/6286-taco-del-mar/menu/",
    "sg:phone":"+1 406 522 9599",
    "sg:postcode":"59718",
    "sg:province":"MT",
    "sg:tags":[
        "mexican"
    ],
    "wof:name":"Taco Del Mar",
    "wof:placetype":"venue"
},
  "geometry": {"coordinates":[-111.06281300000001,45.664398],"type":"Point"}
}