{
  "type": "Feature",
  "properties": {
    "iso:country":"US",
    "sg:address":"405 Helmville Rd",
    "sg:city":"Ovando",
    "sg:classifiers":[
        {
            "category":"Recreation",
            "type":"Entertainment"
        }
    ],
    "sg:phone":"+1 406 793 5046",
    "sg:postcode":"59832",
    "sg:province":"MT",
    "sg:tags":[
        "guide"
    ],
    "wof:name":"North Fork Crossing",
    "wof:placetype":"venue"
},
  "geometry": {"coordinates":[-113.08752800000001,46.720028],"type":"Point"}
}