{
  "type": "Feature",
  "properties": {
    "iso:country":"US",
    "sg:address":"1139 N 27th St",
    "sg:city":"Billings",
    "sg:classifiers":[
        {
            "category":"Personal",
            "subcategory":"Beauty Salon",
            "type":"Services"
        }
    ],
    "sg:phone":"+1 406 256 9772",
    "sg:postcode":"59101",
    "sg:province":"MT",
    "wof:name":"Willow Creek Esthetics",
    "wof:placetype":"venue"
},
  "geometry": {"coordinates":[-108.51521,45.793643],"type":"Point"}
}