{
  "type": "Feature",
  "properties": {
    "iso:country":"US",
    "sg:address":"6302 Hillview Way",
    "sg:city":"Missoula",
    "sg:classifiers":[
        {
            "category":"Professional",
            "subcategory":"Management & Consulting",
            "type":"Services"
        }
    ],
    "sg:phone":"+1 406 251 0601",
    "sg:postcode":"59803",
    "sg:province":"MT",
    "wof:name":"Diamond Eagle Inc",
    "wof:placetype":"venue"
},
  "geometry": {"coordinates":[-114.026726,46.811272],"type":"Point"}
}