{
  "type": "Feature",
  "properties": {
    "iso:country":"US",
    "sg:address":"1270 Lockwood Rd",
    "sg:city":"Billings",
    "sg:classifiers":[
        {
            "category":"Building & Trades",
            "subcategory":"Construction",
            "type":"Services"
        }
    ],
    "sg:phone":"+1 406 245 3636",
    "sg:postcode":"59101",
    "sg:province":"MT",
    "sg:tags":[
        "insulation",
        "heat",
        "contractor"
    ],
    "wof:name":"C C Insulation & Urethane Inc",
    "wof:placetype":"venue"
},
  "geometry": {"coordinates":[-108.453109,45.801035],"type":"Point"}
}