{
  "type": "Feature",
  "properties": {
    "iso:country":"US",
    "sg:address":"214 W Curtiss St",
    "sg:city":"Bozeman",
    "sg:classifiers":[
        {
            "category":"Building & Trades",
            "subcategory":"Construction",
            "type":"Services"
        }
    ],
    "sg:phone":"+1 406 587 2623",
    "sg:postcode":"59715",
    "sg:province":"MT",
    "sg:tags":[
        "hanging",
        "contractor"
    ],
    "wof:name":"F & B Painting",
    "wof:placetype":"venue"
},
  "geometry": {"coordinates":[-111.04028700000001,45.676208],"type":"Point"}
}