{
  "type": "Feature",
  "properties": {
    "iso:country":"US",
    "sg:address":"2017 S 10th St W",
    "sg:city":"Missoula",
    "sg:classifiers":[
        {
            "category":"Professional",
            "type":"Services"
        }
    ],
    "sg:phone":"+1 406 542 0279",
    "sg:postcode":"59801",
    "sg:province":"MT",
    "wof:name":"Tait Jorgenson",
    "wof:placetype":"venue"
},
  "geometry": {"coordinates":[-114.029874,46.860441],"type":"Point"}
}