{
  "type": "Feature",
  "properties": {
    "addr:full":"1314 4th St Havre MT 59501",
    "addr:housenumber":"1314",
    "addr:postcode":"59501",
    "addr:street":"4Th St",
    "iso:country":"US",
    "sg:address":"1314 4th St",
    "sg:city":"Havre",
    "sg:classifiers":[
        {
            "category":"Wholesale",
            "subcategory":"Home Furnishings",
            "type":"Manufacturing & Wholesale Goods"
        }
    ],
    "sg:phone":"+1 406 265 1289",
    "sg:postcode":"59501",
    "sg:province":"MT",
    "wof:name":"Bear Paw Boulder & Veneer",
    "wof:placetype":"venue"
},
  "geometry": {"coordinates":[-109.66404,48.54856],"type":"Point"}
}