{
  "type": "Feature",
  "properties": {
    "iso:country":"US",
    "sg:address":"900 1st Ave N",
    "sg:city":"Great Falls",
    "sg:classifiers":[
        {
            "category":"Food & Beverages",
            "subcategory":"Groceries & Convenience Stores",
            "type":"Retail Goods"
        }
    ],
    "sg:phone":"+1 406 761 8723",
    "sg:postcode":"59401",
    "sg:province":"MT",
    "sg:tags":[
        "station",
        "gasoline"
    ],
    "wof:name":"Mini Mart 766",
    "wof:placetype":"venue"
},
  "geometry": {"coordinates":[-111.290341,47.506327],"type":"Point"}
}