{
  "type": "Feature",
  "properties": {
    "iso:country":"US",
    "sg:address":"5539 Helfrick Rd",
    "sg:city":"Billings",
    "sg:classifiers":[
        {
            "category":"Building & Trades",
            "subcategory":"Landscaping Services",
            "type":"Services"
        }
    ],
    "sg:phone":"+1 406 245 7243",
    "sg:postcode":"59101",
    "sg:province":"MT",
    "sg:tags":[
        "landscape",
        "contractor"
    ],
    "wof:name":"M & H Landscaping",
    "wof:placetype":"venue"
},
  "geometry": {"coordinates":[-108.472138,45.670251],"type":"Point"}
}