{
  "type": "Feature",
  "properties": {
    "iso:country":"US",
    "sg:address":"210 N 4th Ave",
    "sg:city":"Forsyth",
    "sg:classifiers":[
        {
            "category":"Professional",
            "type":"Services"
        }
    ],
    "sg:phone":"+1 406 346 7612",
    "sg:postcode":"59327",
    "sg:province":"MT",
    "sg:tags":[
        "establishment"
    ],
    "wof:name":"Kehler & Kehler",
    "wof:placetype":"venue"
},
  "geometry": {"coordinates":[-106.686812,46.264452],"type":"Point"}
}