{
  "type": "Feature",
  "properties": {
    "iso:country":"US",
    "sg:address":"125 W Granite St",
    "sg:city":"Butte",
    "sg:classifiers":[
        {
            "category":"Professional",
            "subcategory":"Lawyer & Legal Services",
            "type":"Services"
        }
    ],
    "sg:phone":"+1 406 723 5300",
    "sg:postcode":"59701",
    "sg:province":"MT",
    "sg:tags":[
        "attorney"
    ],
    "wof:name":"Shea Law Office Pllc",
    "wof:placetype":"venue"
},
  "geometry": {"coordinates":[-112.538183,46.01442],"type":"Point"}
}