{
  "type": "Feature",
  "properties": {
    "iso:country":"US",
    "sg:address":"512 E Broadway St",
    "sg:city":"Missoula",
    "sg:classifiers":[
        {
            "category":"Travel",
            "subcategory":"Hotels & Motels",
            "type":"Entertainment"
        }
    ],
    "sg:phone":"+1 406 543 7371",
    "sg:postcode":"59802",
    "sg:province":"MT",
    "sg:tags":[
        "operation",
        "eating"
    ],
    "wof:name":"Family Inns",
    "wof:placetype":"venue"
},
  "geometry": {"coordinates":[-113.987053,46.870074],"type":"Point"}
}