{
  "type": "Feature",
  "properties": {
    "iso:country":"US",
    "sg:address":"161 Front St",
    "sg:city":"Bynum",
    "sg:classifiers":[
        {
            "category":"Manufacturing",
            "subcategory":"Jewelry",
            "type":"Manufacturing & Wholesale Goods"
        }
    ],
    "sg:phone":"+1 406 469 2314",
    "sg:postcode":"59419",
    "sg:province":"MT",
    "wof:name":"Trex Agate Shop",
    "wof:placetype":"venue"
},
  "geometry": {"coordinates":[-112.311942,47.977762],"type":"Point"}
}