{
  "type": "Feature",
  "properties": {
    "iso:country":"US",
    "sg:address":"51 Willow Glen Dr",
    "sg:city":"Kalispell",
    "sg:classifiers":[
        {
            "category":"Personal",
            "type":"Services"
        }
    ],
    "sg:phone":"+1 406 755 5011",
    "sg:postcode":"59901",
    "sg:province":"MT",
    "sg:tags":[
        "therapist",
        "massage"
    ],
    "wof:name":"ICMO",
    "wof:placetype":"venue"
},
  "geometry": {"coordinates":[-114.28789,48.201418],"type":"Point"}
}