{
  "type": "Feature",
  "properties": {
    "addr:full":"125 W Main St Missoula MT 59802",
    "addr:housenumber":"125",
    "addr:postcode":"59802",
    "addr:street":"W Main St",
    "iso:country":"US",
    "sg:address":"125 W Main St",
    "sg:city":"Missoula",
    "sg:classifiers":[
        {
            "category":"Personal",
            "subcategory":"Barber",
            "type":"Services"
        }
    ],
    "sg:phone":"+1 406 549 7731",
    "sg:postcode":"59802",
    "sg:province":"MT",
    "wof:name":"Life Styles Hairstyling",
    "wof:placetype":"venue"
},
  "geometry": {"coordinates":[-113.995969,46.871437],"type":"Point"}
}