{
  "type": "Feature",
  "properties": {
    "addr:full":"818 S Arizona St Butte MT 59701",
    "addr:housenumber":"818",
    "addr:postcode":"mt 59701",
    "addr:street":"S Arizona St",
    "iso:country":"US",
    "sg:address":"818 S Arizona St",
    "sg:city":"Butte",
    "sg:classifiers":[
        {
            "category":"Wholesale",
            "subcategory":"Drugs",
            "type":"Manufacturing & Wholesale Goods"
        }
    ],
    "sg:phone":"+1 406 723 6009",
    "sg:postcode":"59701",
    "sg:province":"MT",
    "sg:tags":[
        "biological",
        "product",
        "allied"
    ],
    "wof:name":"Emerald Bioagriculture Corp",
    "wof:placetype":"venue"
},
  "geometry": {"coordinates":[-112.52842800000001,46.005998],"type":"Point"}
}