{
  "type": "Feature",
  "properties": {
    "addr:full":"38 1st Ave SW Choteau MT 59422",
    "addr:housenumber":"38",
    "addr:postcode":"59422",
    "addr:street":"1St Ave Sw",
    "iso:country":"US",
    "sg:address":"38 1st Ave SW",
    "sg:city":"Choteau",
    "sg:classifiers":[
        {
            "category":"Social Services",
            "subcategory":"Child Care",
            "type":"Services"
        }
    ],
    "sg:phone":"+1 406 466 5770",
    "sg:postcode":"59422",
    "sg:province":"MT",
    "sg:tags":[
        "kindergarten",
        "academic",
        "school"
    ],
    "wof:name":"Head Start Program",
    "wof:placetype":"venue"
},
  "geometry": {"coordinates":[-112.18385499999999,47.81029],"type":"Point"}
}