{
  "type": "Feature",
  "properties": {
    "addr:full":"7464 US Hwy 212 Red Lodge MT 59068",
    "addr:housenumber":"7464",
    "addr:postcode":"59068",
    "addr:street":"Us Hwy 212",
    "iso:country":"US",
    "sg:address":"7464 US Hwy 212",
    "sg:city":"Red Lodge",
    "sg:classifiers":[
        {
            "category":"Travel",
            "subcategory":"Campground",
            "type":"Entertainment"
        }
    ],
    "sg:phone":"+1 406 446 2364",
    "sg:postcode":"59068",
    "sg:province":"MT",
    "wof:name":"KOA Kampgrounds",
    "wof:placetype":"venue"
},
  "geometry": {"coordinates":[-109.224929,45.264416],"type":"Point"}
}