{
  "type": "Feature",
  "properties": {
    "iso:country":"US",
    "sg:address":"204 E Main St",
    "sg:city":"Laurel",
    "sg:classifiers":[
        {
            "category":"Home & Garden",
            "subcategory":"Building Materials",
            "type":"Retail Goods"
        }
    ],
    "sg:phone":"+1 406 628 7852",
    "sg:postcode":"59044",
    "sg:province":"MT",
    "sg:tags":[
        "shower",
        "door",
        "enclosure"
    ],
    "wof:name":"Northern Rockies Glass & Dtlng",
    "wof:placetype":"venue"
},
  "geometry": {"coordinates":[-108.768567,45.669753],"type":"Point"}
}