{
  "type": "Feature",
  "properties": {
    "addr:full":"540 N Main St Melrose MT 59722",
    "addr:housenumber":"540",
    "addr:postcode":"59722",
    "addr:street":"N Main St",
    "iso:country":"US",
    "sg:address":"540 N Main St",
    "sg:city":"Melrose",
    "sg:classifiers":[
        {
            "category":"Travel",
            "subcategory":"Hotels & Motels",
            "type":"Entertainment"
        }
    ],
    "sg:phone":"+1 406 835 2141",
    "sg:postcode":"59722",
    "sg:province":"MT",
    "wof:name":"Sportsman Motel",
    "wof:placetype":"venue"
},
  "geometry": {"coordinates":[-112.734758,46.40698],"type":"Point"}
}