{
  "type": "Feature",
  "properties": {
    "addr:full":"157 Conner Cutoff Rd Conner MT 59829",
    "addr:housenumber":"157",
    "addr:postcode":"59829",
    "addr:street":"Conner Cutoff Rd",
    "iso:country":"US",
    "sg:address":"157 Conner Cutoff Rd",
    "sg:city":"Conner",
    "sg:classifiers":[
        {
            "category":"Government",
            "subcategory":"Post Office",
            "type":"Public Place"
        }
    ],
    "sg:phone":"+1 406 821 4776",
    "sg:postcode":"59829",
    "sg:province":"MT",
    "wof:name":"US Post Office",
    "wof:placetype":"venue"
},
  "geometry": {"coordinates":[-114.12465400000001,45.930614],"type":"Point"}
}