{
  "type": "Feature",
  "properties": {
    "addr:full":"7720 Shedhorn Dr Bozeman MT 59718",
    "addr:housenumber":"7720",
    "addr:postcode":"59718",
    "addr:street":"Shedhorn Dr",
    "iso:country":"US",
    "sg:address":"7720 Shedhorn Dr",
    "sg:city":"Bozeman",
    "sg:classifiers":[
        {
            "category":"Recreation",
            "type":"Entertainment"
        }
    ],
    "sg:phone":"+1 406 586 6492",
    "sg:postcode":"59718",
    "sg:province":"MT",
    "sg:tags":[
        "water",
        "spa",
        "park",
        "pool"
    ],
    "wof:name":"Bozeman Hot Springs Inc",
    "wof:placetype":"venue"
},
  "geometry": {"coordinates":[-111.182913,45.672593],"type":"Point"}
}