{
  "type": "Feature",
  "properties": {
    "iso:country":"US",
    "sg:address":"805 S 1st St",
    "sg:city":"Hamilton",
    "sg:classifiers":[
        {
            "category":"Shopping",
            "subcategory":"Clothing, Apparel, & Fashions",
            "type":"Retail Goods"
        }
    ],
    "sg:phone":"+1 406 363 3496",
    "sg:postcode":"59840",
    "sg:province":"MT",
    "sg:tags":[
        "repair",
        "boot",
        "western",
        "shoes"
    ],
    "wof:name":"The Cobbler",
    "wof:placetype":"venue"
},
  "geometry": {"coordinates":[-114.15470999999999,46.239537],"type":"Point"}
}