{
  "type": "Feature",
  "properties": {
    "iso:country":"US",
    "sg:address":"523 Bus Hub Dr",
    "sg:city":"Belgrade",
    "sg:classifiers":[
        {
            "category":"Manufacturing",
            "subcategory":"Retail Goods",
            "type":"Manufacturing & Wholesale Goods"
        }
    ],
    "sg:phone":"+1 406 388 5788",
    "sg:postcode":"59714",
    "sg:province":"MT",
    "sg:tags":[
        "tub",
        "mfg",
        "hot",
        "for",
        "system"
    ],
    "wof:name":"Centech",
    "wof:placetype":"venue"
},
  "geometry": {"coordinates":[-111.20484,45.776575],"type":"Point"}
}