{
  "type": "Feature",
  "properties": {
    "iso:country":"US",
    "sg:address":"924 Millegan Rd",
    "sg:city":"Great Falls",
    "sg:classifiers":[
        {
            "category":"Farming",
            "subcategory":"Livestock Farm",
            "type":"Manufacturing & Wholesale Goods"
        }
    ],
    "sg:phone":"+1 406 866 3250",
    "sg:postcode":"59405",
    "sg:province":"MT",
    "sg:tags":[
        "animal",
        "general"
    ],
    "wof:name":"Roehm Ranch",
    "wof:placetype":"venue"
},
  "geometry": {"coordinates":[-111.426026,47.338042],"type":"Point"}
}