{
  "type": "Feature",
  "properties": {
    "addr:full":"240 3rd St N Glasgow MT 59230",
    "addr:housenumber":"240",
    "addr:postcode":"59230",
    "addr:street":"3Rd St N",
    "iso:country":"US",
    "sg:address":"240 3rd St N",
    "sg:city":"Glasgow",
    "sg:classifiers":[
        {
            "category":"Building & Trades",
            "subcategory":"Construction",
            "type":"Services"
        }
    ],
    "sg:phone":"+1 406 228 4837",
    "sg:postcode":"59230",
    "sg:province":"MT",
    "sg:tags":[
        "general",
        "contractor"
    ],
    "wof:name":"Tihista Construction LLC",
    "wof:placetype":"venue"
},
  "geometry": {"coordinates":[-106.631163,48.196605],"type":"Point"}
}