{
  "type": "Feature",
  "properties": {
    "addr:full":"210 N Higgins Ave Missoula MT 59802",
    "addr:housenumber":"210",
    "addr:postcode":"59802",
    "addr:street":"N Higgins Ave",
    "iso:country":"US",
    "sg:address":"210 N Higgins Ave",
    "sg:city":"Missoula",
    "sg:classifiers":[
        {
            "category":"Professional",
            "subcategory":"Lawyer & Legal Services",
            "type":"Services"
        }
    ],
    "sg:phone":"+1 406 721 4210",
    "sg:postcode":"59802",
    "sg:province":"MT",
    "sg:tags":[
        "attorney"
    ],
    "wof:name":"Maclay Law Firm",
    "wof:placetype":"venue"
},
  "geometry": {"coordinates":[-113.994005,46.871993],"type":"Point"}
}