{
  "type": "Feature",
  "properties": {
    "iso:country":"US",
    "sg:address":"18 6th St N",
    "sg:city":"Great Falls",
    "sg:classifiers":[
        {
            "category":"Professional",
            "subcategory":"Lawyer & Legal Services",
            "type":"Services"
        }
    ],
    "sg:phone":"+1 406 452 8566",
    "sg:postcode":"59401",
    "sg:province":"MT",
    "wof:name":"Stubbs Todd",
    "wof:placetype":"venue"
},
  "geometry": {"coordinates":[-111.297325,47.506185],"type":"Point"}
}