{
  "type": "Feature",
  "properties": {
    "iso:country":"US",
    "sg:address":"1721 Wire Mill Rd",
    "sg:city":"Black Eagle",
    "sg:classifiers":[
        {
            "category":"Wholesale",
            "subcategory":"Groceries",
            "type":"Manufacturing & Wholesale Goods"
        }
    ],
    "sg:phone":"+1 406 727 1740",
    "sg:postcode":"59414",
    "sg:province":"MT",
    "sg:tags":[
        "food",
        "snack"
    ],
    "wof:name":"Frito-Lay",
    "wof:placetype":"venue"
},
  "geometry": {"coordinates":[-111.279433,47.528142],"type":"Point"}
}