{
  "type": "Feature",
  "properties": {
    "addr:full":"343 Hi Frances Rd Arlee MT 59821",
    "addr:housenumber":"343",
    "addr:postcode":"59821",
    "addr:street":"Hi Frances Rd",
    "iso:country":"US",
    "sg:address":"343 Hi Frances Rd",
    "sg:city":"Arlee",
    "sg:classifiers":[
        {
            "category":"Organizations",
            "subcategory":"Religious Organization",
            "type":"Services"
        }
    ],
    "sg:phone":"+1 406 726 3540",
    "sg:postcode":"59821",
    "sg:province":"MT",
    "wof:name":"Sacred Heart Catholic Church",
    "wof:placetype":"venue"
},
  "geometry": {"coordinates":[-114.014544,47.138265],"type":"Point"}
}