{
  "type": "Feature",
  "properties": {
    "addr:full":"1533 Avenue E Billings MT 59102",
    "addr:housenumber":"1533",
    "addr:postcode":"59102",
    "addr:street":"Avenue",
    "iso:country":"US",
    "sg:address":"1533 Avenue E",
    "sg:city":"Billings",
    "sg:classifiers":[
        {
            "category":"Professional",
            "type":"Services"
        }
    ],
    "sg:phone":"+1 406 245 3966",
    "sg:postcode":"59102",
    "sg:province":"MT",
    "wof:name":"Anderson G&C Family LLC",
    "wof:placetype":"venue"
},
  "geometry": {"coordinates":[-108.55559,45.788118],"type":"Point"}
}