{
  "type": "Feature",
  "properties": {
    "iso:country":"US",
    "sg:address":"2801 S Russell St",
    "sg:city":"Missoula",
    "sg:classifiers":[
        {
            "category":"Wholesale",
            "subcategory":"Stationery",
            "type":"Manufacturing & Wholesale Goods"
        }
    ],
    "sg:phone":"+1 406 728 8102",
    "sg:postcode":"59801",
    "sg:province":"MT",
    "sg:tags":[
        "business",
        "broker",
        "form"
    ],
    "wof:name":"Rocky Mountain Forms & Graphic",
    "wof:placetype":"venue"
},
  "geometry": {"coordinates":[-114.018284,46.841591],"type":"Point"}
}