{
  "type": "Feature",
  "properties": {
    "iso:country":"US",
    "sg:address":"3470 Wharton St",
    "sg:city":"Butte",
    "sg:classifiers":[
        {
            "category":"Building & Trades",
            "subcategory":"Equipment Rental",
            "type":"Services"
        }
    ],
    "sg:phone":"+1 406 494 2081",
    "sg:postcode":"59701",
    "sg:province":"MT",
    "wof:name":"Scalabrin Rental",
    "wof:placetype":"venue"
},
  "geometry": {"coordinates":[-112.48324,45.978795],"type":"Point"}
}