{
  "type": "Feature",
  "properties": {
    "iso:country":"US",
    "sg:address":"901 14th St N",
    "sg:city":"Great Falls",
    "sg:classifiers":[
        {
            "category":"Building & Trades",
            "subcategory":"Construction",
            "type":"Services"
        }
    ],
    "sg:phone":"+1 406 452 3877",
    "sg:postcode":"59401",
    "sg:province":"MT",
    "sg:tags":[
        "overhead",
        "door",
        "contractor"
    ],
    "wof:name":"Big Sky Overhead Door Inc",
    "wof:placetype":"venue"
},
  "geometry": {"coordinates":[-111.28328500000001,47.515333],"type":"Point"}
}