{
  "type": "Feature",
  "properties": {
    "addr:full":"90 Poly Dr Billings MT 59102",
    "addr:housenumber":"90",
    "addr:postcode":"59102",
    "addr:street":"Poly Dr",
    "iso:country":"US",
    "sg:address":"90 Poly Dr",
    "sg:city":"Billings",
    "sg:classifiers":[
        {
            "category":"Health Services",
            "subcategory":"Doctor",
            "type":"Services"
        }
    ],
    "sg:phone":"+1 406 245 4100",
    "sg:postcode":"59102",
    "sg:province":"MT",
    "sg:tags":[
        "physician",
        "surgeon",
        "medical"
    ],
    "wof:name":"Janet L Dietrich MD",
    "wof:placetype":"venue"
},
  "geometry": {"coordinates":[-108.519896,45.794943],"type":"Point"}
}