{
  "type": "Feature",
  "properties": {
    "iso:country":"US",
    "sg:address":"7104 Bristol Ln",
    "sg:city":"Bozeman",
    "sg:classifiers":[
        {
            "category":"Professional",
            "subcategory":"Business Services",
            "type":"Services"
        }
    ],
    "sg:phone":"+1 406 586 5773",
    "sg:postcode":"59715",
    "sg:province":"MT",
    "wof:name":"Druckenmiller Enterprises LLC",
    "wof:placetype":"venue"
},
  "geometry": {"coordinates":[-111.048367,45.5907],"type":"Point"}
}