{
  "type": "Feature",
  "properties": {
    "iso:country":"US",
    "sg:address":"141 Springville Ln",
    "sg:city":"Townsend",
    "sg:classifiers":[
        {
            "category":"Farming",
            "subcategory":"Farm & Veterinary Services",
            "type":"Manufacturing & Wholesale Goods"
        }
    ],
    "sg:phone":"+1 406 266 4994",
    "sg:postcode":"59644",
    "sg:province":"MT",
    "sg:tags":[
        "preparation",
        "soil"
    ],
    "wof:name":"Judd Services",
    "wof:placetype":"venue"
},
  "geometry": {"coordinates":[-111.556755,46.342503],"type":"Point"}
}