{
  "type": "Feature",
  "properties": {
    "iso:country":"US",
    "sg:address":"5101 N Star Blvd",
    "sg:city":"Great Falls",
    "sg:classifiers":[
        {
            "category":"Retail",
            "subcategory":"Veterinary Services",
            "type":"Services"
        }
    ],
    "sg:phone":"+1 406 761 8387",
    "sg:postcode":"59405",
    "sg:province":"MT",
    "wof:name":"Big Sky Animal Medical Center",
    "wof:placetype":"venue"
},
  "geometry": {"coordinates":[-111.222915,47.519792],"type":"Point"}
}