{
  "type": "Feature",
  "properties": {
    "addr:full":"5723 Stearns Cir Billings MT 59101",
    "addr:housenumber":"5723",
    "addr:postcode":"59101",
    "addr:street":"Stearns Cir",
    "iso:country":"US",
    "sg:address":"5723 Stearns Cir",
    "sg:city":"Billings",
    "sg:classifiers":[
        {
            "category":"Building & Trades",
            "subcategory":"Construction",
            "type":"Services"
        }
    ],
    "sg:phone":"+1 406 259 7591",
    "sg:postcode":"59101",
    "sg:province":"MT",
    "sg:tags":[
        "carpenter"
    ],
    "wof:name":"Billings Carpentry Industry",
    "wof:placetype":"venue"
},
  "geometry": {"coordinates":[-108.558142,45.736937],"type":"Point"}
}