{
  "type": "Feature",
  "properties": {
    "addr:full":"109 Riverview Pl Great Falls MT 59404",
    "addr:housenumber":"109",
    "addr:postcode":"59404",
    "addr:street":"Riverview Pl",
    "iso:country":"US",
    "sg:address":"109 Riverview Pl",
    "sg:city":"Great Falls",
    "sg:classifiers":[
        {
            "category":"Building & Trades",
            "subcategory":"Construction",
            "type":"Services"
        }
    ],
    "sg:phone":"+1 406 452 8789",
    "sg:postcode":"59404",
    "sg:province":"MT",
    "sg:tags":[
        "house"
    ],
    "wof:name":"Celestial Spas",
    "wof:placetype":"venue"
},
  "geometry": {"coordinates":[-111.30680599999999,47.530329],"type":"Point"}
}