{
  "type": "Feature",
  "properties": {
    "iso:country":"US",
    "sg:address":"3517 1st Ave S",
    "sg:city":"Great Falls",
    "sg:classifiers":[
        {
            "category":"Manufacturing",
            "subcategory":"Metals",
            "type":"Manufacturing & Wholesale Goods"
        }
    ],
    "sg:phone":"+1 406 453 0197",
    "sg:postcode":"59401",
    "sg:province":"MT",
    "sg:tags":[
        "mfg"
    ],
    "wof:name":"Quality Service Overdoor Co",
    "wof:placetype":"venue"
},
  "geometry": {"coordinates":[-111.245243,47.503996],"type":"Point"}
}