{
  "type": "Feature",
  "properties": {
    "addr:full":"1025 Webster Ln Dillon MT 59725",
    "addr:housenumber":"1025",
    "addr:postcode":"59725",
    "addr:street":"Webster Ln",
    "iso:country":"US",
    "sg:address":"1025 Webster Ln",
    "sg:city":"Dillon",
    "sg:classifiers":[
        {
            "category":"Home & Garden",
            "subcategory":"Building Materials",
            "type":"Retail Goods"
        }
    ],
    "sg:phone":"+1 406 683 5690",
    "sg:postcode":"59725",
    "sg:province":"MT",
    "sg:tags":[
        "truss"
    ],
    "wof:name":"Maclin Trusses",
    "wof:placetype":"venue"
},
  "geometry": {"coordinates":[-112.619488,45.254902],"type":"Point"}
}