{
  "type": "Feature",
  "properties": {
    "iso:country":"US",
    "sg:address":"47995 Gallatin Rd",
    "sg:city":"Gallatin Gateway",
    "sg:classifiers":[
        {
            "category":"Restaurant",
            "type":"Food & Drink"
        }
    ],
    "sg:phone":"+1 406 995 3350",
    "sg:postcode":"59730",
    "sg:province":"MT",
    "wof:name":"Jo-Mama's",
    "wof:placetype":"venue"
},
  "geometry": {"coordinates":[-111.252959,45.265888],"type":"Point"}
}