{
  "type": "Feature",
  "properties": {
    "iso:country":"US",
    "sg:address":"131 Burlington Ave",
    "sg:city":"Billings",
    "sg:classifiers":[
        {
            "category":"Wholesale",
            "subcategory":"Vending Machines",
            "type":"Manufacturing & Wholesale Goods"
        }
    ],
    "sg:phone":"+1 406 248 3315",
    "sg:postcode":"59101",
    "sg:province":"MT",
    "sg:tags":[
        "operator",
        "repair"
    ],
    "wof:name":"Classic Vendors Inc",
    "wof:placetype":"venue"
},
  "geometry": {"coordinates":[-108.519725,45.78216],"type":"Point"}
}