{
  "type": "Feature",
  "properties": {
    "addr:full":"71 Park Dr N Conrad MT 59401",
    "addr:housenumber":"71",
    "addr:postcode":"59401",
    "addr:street":"Park Dr N Conrad",
    "iso:country":"US",
    "sg:address":"71 Park Dr N",
    "sg:city":"Conrad",
    "sg:classifiers":[
        {
            "category":"Mining & Drilling",
            "type":"Manufacturing & Wholesale Goods"
        }
    ],
    "sg:phone":"+1 406 278 3632",
    "sg:postcode":"59401",
    "sg:province":"MT",
    "sg:tags":[
        "field"
    ],
    "wof:name":"Prewett Ron Construction",
    "wof:placetype":"venue"
},
  "geometry": {"coordinates":[-111.305982,47.505591],"type":"Point"}
}