{
  "type": "Feature",
  "properties": {
    "iso:country":"US",
    "sg:address":"73800 Gallatin Rd",
    "sg:city":"Gallatin Gateway",
    "sg:classifiers":[
        {
            "category":"Shopping",
            "subcategory":"Used Merchandise",
            "type":"Retail Goods"
        }
    ],
    "sg:phone":"+1 406 763 9100",
    "sg:postcode":"59730",
    "sg:province":"MT",
    "wof:name":"Buffalo Gals",
    "wof:placetype":"venue"
},
  "geometry": {"coordinates":[-111.201527,45.557417],"type":"Point"}
}