{
  "type": "Feature",
  "properties": {
    "iso:country":"US",
    "sg:address":"1715 Vaughn Rd",
    "sg:city":"Great Falls",
    "sg:classifiers":[
        {
            "category":"Restaurant",
            "type":"Food & Drink"
        }
    ],
    "sg:phone":"+1 406 453 7992",
    "sg:postcode":"59404",
    "sg:province":"MT",
    "sg:tags":[
        "eating"
    ],
    "wof:name":"Crossroads Cafe",
    "wof:placetype":"venue"
},
  "geometry": {"coordinates":[-111.347117,47.514248],"type":"Point"}
}