{
  "type": "Feature",
  "properties": {
    "addr:full":"21 N Broadway Ave Red Lodge MT 59068",
    "addr:housenumber":"21",
    "addr:postcode":"59068",
    "addr:street":"N Broadway Ave",
    "iso:country":"US",
    "sg:address":"21 N Broadway Ave",
    "sg:city":"Red Lodge",
    "sg:classifiers":[
        {
            "category":"Building & Trades",
            "subcategory":"Construction",
            "type":"Services"
        }
    ],
    "sg:phone":"+1 406 446 0282",
    "sg:postcode":"59068",
    "sg:province":"MT",
    "sg:tags":[
        "contractor"
    ],
    "wof:name":"Mc Campbell Building",
    "wof:placetype":"venue"
},
  "geometry": {"coordinates":[-109.24706500000001,45.186709],"type":"Point"}
}