{
  "type": "Feature",
  "properties": {
    "iso:country":"US",
    "sg:address":"3620 US Hwy 2 E",
    "sg:city":"Kalispell",
    "sg:classifiers":[
        {
            "category":"Retail",
            "subcategory":"Veterinary Services",
            "type":"Services"
        }
    ],
    "sg:phone":"+1 406 257 9399",
    "sg:postcode":"59901",
    "sg:province":"MT",
    "wof:name":"La Salle Veterinary Clinic",
    "wof:placetype":"venue"
},
  "geometry": {"coordinates":[-114.257745,48.285466],"type":"Point"}
}