{
  "type": "Feature",
  "properties": {
    "iso:country":"US",
    "sg:address":"780 22nd Rd NE",
    "sg:city":"Dutton",
    "sg:classifiers":[
        {
            "category":"Farming",
            "subcategory":"Livestock Farm",
            "type":"Manufacturing & Wholesale Goods"
        }
    ],
    "sg:phone":"+1 406 753 2313",
    "sg:postcode":"59433",
    "sg:province":"MT",
    "sg:tags":[
        "beef",
        "ca",
        "crop",
        "field",
        "cattle",
        "feedlot"
    ],
    "wof:name":"Frank Horak",
    "wof:placetype":"venue"
},
  "geometry": {"coordinates":[-111.853516,47.9261],"type":"Point"}
}