{
  "type": "Feature",
  "properties": {
    "iso:country":"US",
    "sg:address":"2134 Industrial Dr",
    "sg:city":"Bozeman",
    "sg:classifiers":[
        {
            "category":"Social Services",
            "subcategory":"Adult Care",
            "type":"Services"
        }
    ],
    "sg:phone":"+1 406 587 1271",
    "sg:postcode":"59715",
    "sg:province":"MT",
    "sg:tags":[
        "disabled",
        "residential",
        "vocational",
        "for"
    ],
    "wof:name":"Reach Inc",
    "wof:placetype":"venue"
},
  "geometry": {"coordinates":[-111.033478,45.702044],"type":"Point"}
}