{
  "type": "Feature",
  "properties": {
    "iso:country":"US",
    "sg:address":"1195 State Hwy 83",
    "sg:city":"Bigfork",
    "sg:classifiers":[
        {
            "category":"Restaurant",
            "type":"Food & Drink"
        }
    ],
    "sg:phone":"+1 406 837 4252",
    "sg:postcode":"59911",
    "sg:province":"MT",
    "sg:tags":[
        "eating"
    ],
    "wof:name":"Echo Lake Cafe LLP",
    "wof:placetype":"venue"
},
  "geometry": {"coordinates":[-114.029338,48.095549],"type":"Point"}
}