{
  "type": "Feature",
  "properties": {
    "iso:country":"US",
    "sg:address":"2110 Overland Ave",
    "sg:city":"Billings",
    "sg:classifiers":[
        {
            "category":"Social Services",
            "type":"Services"
        }
    ],
    "sg:phone":"+1 406 652 5443",
    "sg:postcode":"59102",
    "sg:province":"MT",
    "sg:tags":[
        "organization",
        "welfare"
    ],
    "wof:name":"Resource Support & Dev",
    "wof:placetype":"venue"
},
  "geometry": {"coordinates":[-108.568333,45.751861],"type":"Point"}
}