{
  "type": "Feature",
  "properties": {
    "addr:full":"313 Cirque Dr Bozeman MT 59718",
    "addr:housenumber":"313",
    "addr:postcode":"59718",
    "addr:street":"Cirque Dr",
    "iso:country":"US",
    "sg:address":"313 Cirque Dr",
    "sg:city":"Bozeman",
    "sg:classifiers":[
        {
            "category":"Building & Trades",
            "subcategory":"Landscaping Services",
            "type":"Services"
        }
    ],
    "sg:phone":"+1 406 587 5002",
    "sg:postcode":"59718",
    "sg:province":"MT",
    "sg:tags":[
        "landscape",
        "contractor"
    ],
    "wof:name":"L & L Bobcat Landscape",
    "wof:placetype":"venue"
},
  "geometry": {"coordinates":[-111.108175,45.742336],"type":"Point"}
}