{
  "type": "Feature",
  "properties": {
    "addr:full":"3490 Quincy St Butte MT 59701",
    "addr:housenumber":"3490",
    "addr:postcode":"mt 59701",
    "addr:street":"Quincy St",
    "iso:country":"US",
    "sg:address":"3490 Quincy St",
    "sg:city":"Butte",
    "sg:classifiers":[
        {
            "category":"Manufacturing",
            "subcategory":"Apparel",
            "type":"Manufacturing & Wholesale Goods"
        }
    ],
    "sg:phone":"+1 406 494 6614",
    "sg:postcode":"59701",
    "sg:province":"MT",
    "wof:name":"Stitch N Tyme",
    "wof:placetype":"venue"
},
  "geometry": {"coordinates":[-112.47837,45.976247],"type":"Point"}
}