{
  "type": "Feature",
  "properties": {
    "iso:country":"US",
    "sg:address":"715 W Central Ave",
    "sg:city":"Missoula",
    "sg:classifiers":[
        {
            "category":"Health Services",
            "subcategory":"Doctor",
            "type":"Services"
        }
    ],
    "sg:phone":"+1 406 728 2840",
    "sg:postcode":"59801",
    "sg:province":"MT",
    "wof:name":"Ruben ONeal DDS PC",
    "wof:placetype":"venue"
},
  "geometry": {"coordinates":[-114.009396,46.850594],"type":"Point"}
}