{
  "type": "Feature",
  "properties": {
    "addr:full":"501 US Hwy 10 W Park City MT 59063",
    "addr:housenumber":"501",
    "addr:postcode":"59063",
    "addr:street":"Us Hwy 10 W Park",
    "iso:country":"US",
    "sg:address":"501 US Hwy 10 W",
    "sg:city":"Park City",
    "sg:classifiers":[
        {
            "category":"Retail",
            "subcategory":"Repair Shop",
            "type":"Services"
        }
    ],
    "sg:phone":"+1 406 633 2387",
    "sg:postcode":"59063",
    "sg:province":"MT",
    "sg:tags":[
        "welding"
    ],
    "wof:name":"Park City Welding Shop",
    "wof:placetype":"venue"
},
  "geometry": {"coordinates":[-108.94562000000001,45.626654],"type":"Point"}
}