{
  "type": "Feature",
  "properties": {
    "addr:full":"945 Broadwater Ave Billings MT 59101",
    "addr:housenumber":"945",
    "addr:postcode":"59101",
    "addr:street":"Broadwater Ave",
    "iso:country":"US",
    "sg:address":"945 Broadwater Ave",
    "sg:city":"Billings",
    "sg:classifiers":[
        {
            "category":"Health Services",
            "subcategory":"Doctor",
            "type":"Services"
        }
    ],
    "sg:phone":"+1 406 248 7136",
    "sg:postcode":"59101",
    "sg:province":"MT",
    "sg:tags":[
        "physician",
        "surgeon",
        "medical"
    ],
    "wof:name":"T J Miller MD PC",
    "wof:placetype":"venue"
},
  "geometry": {"coordinates":[-108.53997200000001,45.777124],"type":"Point"}
}