{
  "type": "Feature",
  "properties": {
    "iso:country":"US",
    "sg:address":"500 Mission View Dr",
    "sg:city":"Polson",
    "sg:classifiers":[
        {
            "category":"Building & Trades",
            "subcategory":"Construction",
            "type":"Services"
        }
    ],
    "sg:phone":"+1 406 883 9337",
    "sg:postcode":"59860",
    "sg:province":"MT",
    "sg:tags":[
        "house"
    ],
    "wof:name":"Nunlist Construction Inc",
    "wof:placetype":"venue"
},
  "geometry": {"coordinates":[-114.148397,47.675984],"type":"Point"}
}