{
  "type": "Feature",
  "properties": {
    "addr:full":"62 S Last Chance Gulch St Helena MT 59601",
    "addr:housenumber":"62",
    "addr:postcode":"59601",
    "addr:street":"S Last Chance Gulch",
    "iso:country":"US",
    "sg:address":"62 S Last Chance Gulch St",
    "sg:city":"Helena",
    "sg:classifiers":[
        {
            "category":"Social Services",
            "subcategory":"Child Care",
            "type":"Services"
        }
    ],
    "sg:phone":"+1 406 442 7233",
    "sg:postcode":"59601",
    "sg:province":"MT",
    "sg:tags":[
        "day"
    ],
    "wof:name":"Early Movement Preschool",
    "wof:placetype":"venue"
},
  "geometry": {"coordinates":[-112.04027499999999,46.586],"type":"Point"}
}