{
  "type": "Feature",
  "properties": {
    "iso:country":"US",
    "sg:address":"2630 Gabel Rd",
    "sg:city":"Billings",
    "sg:classifiers":[
        {
            "category":"Freight",
            "type":"Transportation"
        }
    ],
    "sg:phone":"+1 406 256 2238",
    "sg:postcode":"59102",
    "sg:province":"MT",
    "sg:tags":[
        "trucking"
    ],
    "sg:website":"www.abf.com",
    "wof:name":"ABF Freight System Inc",
    "wof:placetype":"venue"
},
  "geometry": {"coordinates":[-108.582014,45.744481],"type":"Point"}
}