{
  "type": "Feature",
  "properties": {
    "iso:country":"US",
    "sg:address":"3611 Mallard Dr",
    "sg:city":"Billings",
    "sg:classifiers":[
        {
            "category":"Building & Trades",
            "subcategory":"Construction",
            "type":"Services"
        }
    ],
    "sg:phone":"+1 406 652 6851",
    "sg:postcode":"59101",
    "sg:province":"MT",
    "sg:tags":[
        "carpentry",
        "contractor"
    ],
    "wof:name":"True Design",
    "wof:placetype":"venue"
},
  "geometry": {"coordinates":[-108.646968,45.704202],"type":"Point"}
}