{
  "type": "Feature",
  "properties": {
    "addr:full":"422 Madison St Missoula MT 59802",
    "addr:housenumber":"422",
    "addr:postcode":"59802",
    "addr:street":"Madison St",
    "iso:country":"US",
    "sg:address":"422 Madison St",
    "sg:city":"Missoula",
    "sg:classifiers":[
        {
            "category":"Professional",
            "subcategory":"Management & Consulting",
            "type":"Services"
        }
    ],
    "sg:phone":"+1 406 549 3504",
    "sg:postcode":"59802",
    "sg:province":"MT",
    "sg:tags":[
        "business"
    ],
    "wof:name":"Norman Taylor",
    "wof:placetype":"venue"
},
  "geometry": {"coordinates":[-113.985731,46.871668],"type":"Point"}
}