{
  "type": "Feature",
  "properties": {
    "addr:full":"110 E. Broadway Suite 400 Missoula MT 59802",
    "addr:housenumber":"110",
    "addr:postcode":"59802",
    "addr:street":"E. Broadway Suite 400",
    "iso:country":"US",
    "sg:address":"110 E. Broadway Suite 400",
    "sg:city":"Missoula",
    "sg:classifiers":[
        {
            "category":"Professional",
            "subcategory":"Research",
            "type":"Services"
        }
    ],
    "sg:phone":"+1 603 883 5200",
    "sg:postcode":"59802",
    "sg:province":"MT",
    "sg:tags":[
        "solar"
    ],
    "sg:website":"http://www.gtsolar.com/",
    "wof:name":"GT Solar",
    "wof:placetype":"venue"
},
  "geometry": {"coordinates":[-113.98974200000001,46.870804],"type":"Point"}
}