{
  "type": "Feature",
  "properties": {
    "iso:country":"US",
    "sg:address":"1805 14th St SW",
    "sg:city":"Sidney",
    "sg:phone":"+1 406 482 8113",
    "sg:postcode":"59270",
    "sg:province":"MT",
    "sg:tags":[
        "farm",
        "beet"
    ],
    "wof:name":"T&J Farms",
    "wof:placetype":"venue"
},
  "geometry": {"coordinates":[-104.18219000000001,47.703603],"type":"Point"}
}