{
  "type": "Feature",
  "properties": {
    "iso:country":"US",
    "sg:address":"426 13th Ave",
    "sg:city":"Havre",
    "sg:classifiers":[
        {
            "category":"Shopping",
            "subcategory":"Gifts & Souvenirs",
            "type":"Retail Goods"
        }
    ],
    "sg:phone":"+1 406 265 1662",
    "sg:postcode":"59501",
    "sg:province":"MT",
    "wof:name":"Treasured Memories HM Parties",
    "wof:placetype":"venue"
},
  "geometry": {"coordinates":[-109.66425,48.548364],"type":"Point"}
}