{
  "type": "Feature",
  "properties": {
    "iso:country":"US",
    "sg:address":"3003 Forsythia Blvd",
    "sg:city":"Billings",
    "sg:classifiers":[
        {
            "category":"Insurance",
            "subcategory":"Insurance Agent",
            "type":"Services"
        }
    ],
    "sg:phone":"+1 406 655 9694",
    "sg:postcode":"59102",
    "sg:province":"MT",
    "wof:name":"May & Accoc",
    "wof:placetype":"venue"
},
  "geometry": {"coordinates":[-108.592603,45.798711],"type":"Point"}
}