{
  "type": "Feature",
  "properties": {
    "iso:country":"US",
    "sg:address":"319 N Higgins Ave",
    "sg:city":"Missoula",
    "sg:classifiers":[
        {
            "category":"Shopping",
            "subcategory":"Optical Goods",
            "type":"Retail Goods"
        }
    ],
    "sg:phone":"+1 406 549 5700",
    "sg:postcode":"59802",
    "sg:province":"MT",
    "wof:name":"Specticca Optical Boutique",
    "wof:placetype":"venue"
},
  "geometry": {"coordinates":[-113.993549,46.872937],"type":"Point"}
}