{
  "type": "Feature",
  "properties": {
    "iso:country":"US",
    "sg:address":"205 Sunnyview Ln",
    "sg:city":"Kalispell",
    "sg:classifiers":[
        {
            "category":"Organizations",
            "subcategory":"Non-profit Organization",
            "type":"Services"
        }
    ],
    "sg:phone":"+1 406 751 4189",
    "sg:postcode":"59901",
    "sg:province":"MT",
    "sg:tags":[
        "social"
    ],
    "wof:name":"Northwest Healthcare Corp",
    "wof:placetype":"venue"
},
  "geometry": {"coordinates":[-114.328515,48.215298],"type":"Point"}
}