{
  "type": "Feature",
  "properties": {
    "iso:country":"US",
    "sg:address":"1103 Union Rd",
    "sg:city":"Circle",
    "sg:classifiers":[
        {
            "category":"Farming",
            "subcategory":"Livestock Farm",
            "type":"Manufacturing & Wholesale Goods"
        }
    ],
    "sg:phone":"+1 406 485 3534",
    "sg:postcode":"59215",
    "sg:province":"MT",
    "sg:tags":[
        "beef",
        "feedlot",
        "cattle"
    ],
    "wof:name":"Dekker Inc",
    "wof:placetype":"venue"
},
  "geometry": {"coordinates":[-105.555166,47.259384],"type":"Point"}
}