{
  "type": "Feature",
  "properties": {
    "iso:country":"US",
    "sg:address":"32 Corrigeux Rd",
    "sg:city":"Cut Bank",
    "sg:classifiers":[
        {
            "category":"Freight",
            "type":"Transportation"
        }
    ],
    "sg:phone":"+1 406 873 5042",
    "sg:postcode":"59427",
    "sg:province":"MT",
    "sg:tags":[
        "trucking"
    ],
    "wof:name":"Hughson Trucking Inc",
    "wof:placetype":"venue"
},
  "geometry": {"coordinates":[-112.345754,48.643445],"type":"Point"}
}