{
  "type": "Feature",
  "properties": {
    "iso:country":"US",
    "sg:address":"202 S Montana St",
    "sg:city":"Butte",
    "sg:classifiers":[
        {
            "category":"Health Services",
            "subcategory":"Doctor",
            "type":"Services"
        }
    ],
    "sg:phone":"+1 406 723 6526",
    "sg:postcode":"59701",
    "sg:province":"MT",
    "sg:tags":[
        "medical"
    ],
    "wof:name":"Divide Creek",
    "wof:placetype":"venue"
},
  "geometry": {"coordinates":[-112.539289,46.010983],"type":"Point"}
}