{
  "type": "Feature",
  "properties": {
    "iso:country":"US",
    "sg:address":"2405 W Main St",
    "sg:city":"Bozeman",
    "sg:classifiers":[
        {
            "category":"Wholesale",
            "subcategory":"Machinery & Supplies",
            "type":"Manufacturing & Wholesale Goods"
        },
        {
            "category":"Shopping",
            "subcategory":"Beauty & Cosmetics",
            "type":"Retail Goods"
        }
    ],
    "sg:phone":"+1 406 586 2224",
    "sg:postcode":"59718",
    "sg:province":"MT",
    "sg:tags":[
        "salon"
    ],
    "wof:name":"J A Beauty Supply Inc",
    "wof:placetype":"venue"
},
  "geometry": {"coordinates":[-111.069213,45.676496],"type":"Point"}
}