{
  "type": "Feature",
  "properties": {
    "iso:country":"US",
    "sg:address":"114 Lincoln Ave",
    "sg:city":"Broadus",
    "sg:classifiers":[
        {
            "category":"Government",
            "subcategory":"Office",
            "type":"Public Place"
        }
    ],
    "sg:phone":"+1 406 436 2417",
    "sg:postcode":"59317",
    "sg:province":"MT",
    "sg:tags":[
        "federal"
    ],
    "wof:name":"Natural Resources Conservation",
    "wof:placetype":"venue"
},
  "geometry": {"coordinates":[-105.40671,45.443412],"type":"Point"}
}