{
  "type": "Feature",
  "properties": {
    "addr:full":"202 2nd Ave W Kalispell MT 59901",
    "addr:housenumber":"202",
    "addr:postcode":"59901",
    "addr:street":"2Nd Ave W",
    "iso:country":"US",
    "sg:address":"202 2nd Ave W",
    "sg:city":"Kalispell",
    "sg:classifiers":[
        {
            "category":"Shopping",
            "subcategory":"Pharmacy",
            "type":"Retail Goods"
        }
    ],
    "sg:phone":"+1 406 257 4806",
    "sg:postcode":"59901",
    "sg:province":"MT",
    "wof:name":"Sykes Pharmacy Inc",
    "wof:placetype":"venue"
},
  "geometry": {"coordinates":[-114.316159,48.196273],"type":"Point"}
}