{
  "type": "Feature",
  "properties": {
    "addr:full":"16 E Granite St Butte MT 59701",
    "addr:housenumber":"16",
    "addr:postcode":"mt 59701",
    "addr:street":"E Granite St",
    "iso:country":"US",
    "sg:address":"16 E Granite St",
    "sg:city":"Butte",
    "sg:classifiers":[
        {
            "category":"Building & Trades",
            "subcategory":"Plumbing",
            "type":"Services"
        }
    ],
    "sg:phone":"+1 406 723 5421",
    "sg:postcode":"59701",
    "sg:province":"MT",
    "sg:tags":[
        "product",
        "management",
        "energy",
        "system"
    ],
    "wof:name":"North Western Energy",
    "wof:placetype":"venue"
},
  "geometry": {"coordinates":[-112.533857,46.014629],"type":"Point"}
}