{
  "type": "Feature",
  "properties": {
    "addr:full":"712 Wibaux St S Wibaux MT 59353",
    "addr:housenumber":"712",
    "addr:postcode":"59353",
    "addr:street":"Wibaux St S Wibaux",
    "iso:country":"US",
    "sg:address":"712 Wibaux St S",
    "sg:city":"Wibaux",
    "sg:classifiers":[
        {
            "category":"Health Services",
            "subcategory":"Nursing And Care Facility",
            "type":"Services"
        }
    ],
    "sg:phone":"+1 406 796 2429",
    "sg:postcode":"59353",
    "sg:province":"MT",
    "sg:tags":[
        "home",
        "convalescent"
    ],
    "wof:name":"Wibaux County Nursing Home",
    "wof:placetype":"venue"
},
  "geometry": {"coordinates":[-104.188524,46.980645],"type":"Point"}
}