{
  "type": "Feature",
  "properties": {
    "iso:country":"US",
    "sg:address":"604 4th Ave W",
    "sg:city":"Poplar",
    "sg:classifiers":[
        {
            "category":"Social Services",
            "subcategory":"Child Care",
            "type":"Services"
        }
    ],
    "sg:phone":"+1 406 768 5525",
    "sg:postcode":"59255",
    "sg:province":"MT",
    "wof:name":"Jungle Gym Daycare",
    "wof:placetype":"venue"
},
  "geometry": {"coordinates":[-105.201738,48.113035],"type":"Point"}
}