{
  "type": "Feature",
  "properties": {
    "iso:country":"US",
    "sg:address":"4589 Carbine Rd",
    "sg:city":"Ronan",
    "sg:classifiers":[
        {
            "category":"Building & Trades",
            "subcategory":"Construction",
            "type":"Services"
        }
    ],
    "sg:phone":"+1 406 675 3558",
    "sg:postcode":"59864",
    "sg:province":"MT",
    "sg:tags":[
        "tile",
        "dealer"
    ],
    "wof:name":"Knapp Ceramic Tile",
    "wof:placetype":"venue"
},
  "geometry": {"coordinates":[-114.218425,47.5877],"type":"Point"}
}