{
  "type": "Feature",
  "properties": {
    "iso:country":"US",
    "sg:address":"111 Wyoming Ave",
    "sg:city":"Billings",
    "sg:classifiers":[
        {
            "category":"Professional",
            "subcategory":"Management & Consulting",
            "type":"Services"
        }
    ],
    "sg:phone":"+1 406 252 6120",
    "sg:postcode":"59101",
    "sg:province":"MT",
    "sg:tags":[
        "business"
    ],
    "wof:name":"Clancy Consultants",
    "wof:placetype":"venue"
},
  "geometry": {"coordinates":[-108.520196,45.77821],"type":"Point"}
}