{
  "type": "Feature",
  "properties": {
    "iso:country":"US",
    "sg:address":"404 Ironwood St",
    "sg:city":"Great Falls",
    "sg:classifiers":[
        {
            "category":"Professional",
            "subcategory":"Business Services",
            "type":"Services"
        }
    ],
    "sg:phone":"+1 406 761 2706",
    "sg:postcode":"59405",
    "sg:province":"MT",
    "wof:name":"Jason Broussard",
    "wof:placetype":"venue"
},
  "geometry": {"coordinates":[-111.21013499999999,47.512454],"type":"Point"}
}