{
  "type": "Feature",
  "properties": {
    "iso:country":"US",
    "sg:address":"501 9th Ave NE",
    "sg:city":"Sidney",
    "sg:classifiers":[
        {
            "category":"Wholesale",
            "subcategory":"Groceries",
            "type":"Manufacturing & Wholesale Goods"
        }
    ],
    "sg:phone":"+1 406 433 3403",
    "sg:postcode":"59270",
    "sg:province":"MT",
    "sg:tags":[
        "beverage"
    ],
    "wof:name":"Pepsi-Cola Bottling Co",
    "wof:placetype":"venue"
},
  "geometry": {"coordinates":[-104.14260299999999,47.717985],"type":"Point"}
}