{
  "type": "Feature",
  "properties": {
    "iso:country":"US",
    "sg:address":"1008 N 7th Ave",
    "sg:city":"Bozeman",
    "sg:classifiers":[
        {
            "category":"Shopping",
            "subcategory":"Computers & Home Electronics",
            "type":"Retail Goods"
        }
    ],
    "sg:phone":"+1 406 586 4916",
    "sg:postcode":"59715",
    "sg:province":"MT",
    "sg:tags":[
        "satellite",
        "alarm",
        "stereo",
        "system"
    ],
    "wof:name":"Avitel",
    "wof:placetype":"venue"
},
  "geometry": {"coordinates":[-111.046103,45.690423],"type":"Point"}
}