{
  "type": "Feature",
  "properties": {
    "iso:country":"US",
    "sg:address":"405 Parmenter Ave",
    "sg:city":"Libby",
    "sg:classifiers":[
        {
            "category":"Professional",
            "subcategory":"Business Services",
            "type":"Services"
        }
    ],
    "sg:phone":"+1 406 293 6350",
    "sg:postcode":"59923",
    "sg:province":"MT",
    "wof:name":"R & B Construction of Montana",
    "wof:placetype":"venue"
},
  "geometry": {"coordinates":[-115.58287900000001,48.395314],"type":"Point"}
}