{
  "type": "Feature",
  "properties": {
    "iso:country":"US",
    "sg:address":"43 Stubble Ln",
    "sg:city":"Belgrade",
    "sg:classifiers":[
        {
            "category":"Social Services",
            "type":"Services"
        }
    ],
    "sg:phone":"+1 406 585 7243",
    "sg:postcode":"59714",
    "sg:province":"MT",
    "sg:tags":[
        "organization",
        "self",
        "provides"
    ],
    "wof:name":"Intentional Partnership",
    "wof:placetype":"venue"
},
  "geometry": {"coordinates":[-111.21872999999999,45.790684],"type":"Point"}
}