{
  "type": "Feature",
  "properties": {
    "iso:country":"US",
    "sg:address":"200 N 34th St",
    "sg:city":"Billings",
    "sg:classifiers":[
        {
            "category":"Professional",
            "subcategory":"Credit Reporting & Collection",
            "type":"Services"
        }
    ],
    "sg:phone":"+1 406 245 2040",
    "sg:postcode":"59101",
    "sg:province":"MT",
    "sg:tags":[
        "agency"
    ],
    "wof:name":"CBB Collections Inc",
    "wof:placetype":"venue"
},
  "geometry": {"coordinates":[-108.514824,45.780266],"type":"Point"}
}