{
  "type": "Feature",
  "properties": {
    "iso:country":"US",
    "sg:address":"132 Park Knoll Ln",
    "sg:city":"Whitefish",
    "sg:classifiers":[
        {
            "category":"Real Estate",
            "subcategory":"Real Estate Agent",
            "type":"Services"
        }
    ],
    "sg:phone":"+1 406 862 3362",
    "sg:postcode":"59937",
    "sg:province":"MT",
    "wof:name":"Jeff Fisher Realty",
    "wof:placetype":"venue"
},
  "geometry": {"coordinates":[-114.338172,48.389145],"type":"Point"}
}