{
  "type": "Feature",
  "properties": {
    "iso:country":"US",
    "sg:address":"2702 Enterprise Ave",
    "sg:city":"Billings",
    "sg:classifiers":[
        {
            "category":"Building & Trades",
            "subcategory":"Electrical",
            "type":"Services"
        }
    ],
    "sg:phone":"+1 406 245 7528",
    "sg:postcode":"59102",
    "sg:province":"MT",
    "sg:tags":[
        "electric",
        "contractor"
    ],
    "wof:name":"Circuit Electric",
    "wof:placetype":"venue"
},
  "geometry": {"coordinates":[-108.583537,45.750294],"type":"Point"}
}