{
  "type": "Feature",
  "properties": {
    "iso:country":"US",
    "sg:address":"145 Loomont Ln",
    "sg:city":"Whitehall",
    "sg:phone":"+1 406 287 5628",
    "sg:postcode":"59759",
    "sg:province":"MT",
    "sg:tags":[
        "farm",
        "field",
        "crop"
    ],
    "wof:name":"Willow Springs Ranch",
    "wof:placetype":"venue"
},
  "geometry": {"coordinates":[-112.16275,45.74358],"type":"Point"}
}