{
  "type": "Feature",
  "properties": {
    "iso:country":"US",
    "sg:address":"205 Bedford St",
    "sg:city":"Hamilton",
    "sg:classifiers":[
        {
            "category":"Government",
            "subcategory":"Jail",
            "type":"Public Place"
        }
    ],
    "sg:phone":"+1 406 375 6281",
    "sg:postcode":"59840",
    "sg:province":"MT",
    "sg:tags":[
        "county",
        "govt",
        "institution"
    ],
    "wof:name":"Ravalli County Jail",
    "wof:placetype":"venue"
},
  "geometry": {"coordinates":[-114.156888,46.244867],"type":"Point"}
}