{
  "type": "Feature",
  "properties": {
    "iso:country":"US",
    "sg:address":"612 W Beall St",
    "sg:city":"Bozeman",
    "sg:classifiers":[
        {
            "category":"Professional",
            "subcategory":"Accounting & Tax Preparation",
            "type":"Services"
        }
    ],
    "sg:phone":"+1 406 586 4346",
    "sg:postcode":"59715",
    "sg:province":"MT",
    "wof:name":"Bailey & Brinkman",
    "wof:placetype":"venue"
},
  "geometry": {"coordinates":[-111.045267,45.681928],"type":"Point"}
}