{
  "type": "Feature",
  "properties": {
    "addr:full":"290 Bergiers Lake Rd Dagmar MT 59219",
    "addr:housenumber":"290",
    "addr:postcode":"59219",
    "addr:street":"Bergiers Lake Rd",
    "iso:country":"US",
    "sg:address":"290 Bergiers Lake Rd",
    "sg:city":"Dagmar",
    "sg:classifiers":[
        {
            "category":"Mining & Drilling",
            "type":"Manufacturing & Wholesale Goods"
        }
    ],
    "sg:phone":"+1 406 483 5255",
    "sg:postcode":"59219",
    "sg:province":"MT",
    "sg:tags":[
        "field",
        "oil"
    ],
    "wof:name":"Justice Oil Field Svc",
    "wof:placetype":"venue"
},
  "geometry": {"coordinates":[-104.11029499999999,48.54854],"type":"Point"}
}