{
  "type": "Feature",
  "properties": {
    "iso:country":"US",
    "sg:address":"28 6th St W",
    "sg:city":"Roundup",
    "sg:classifiers":[
        {
            "category":"Restaurant",
            "type":"Food & Drink"
        }
    ],
    "sg:phone":"+1 406 323 3300",
    "sg:postcode":"59072",
    "sg:province":"MT",
    "sg:tags":[
        "eating"
    ],
    "wof:name":"Blue Star Espresso Inc",
    "wof:placetype":"venue"
},
  "geometry": {"coordinates":[-108.550225,46.441219],"type":"Point"}
}