{
  "type": "Feature",
  "properties": {
    "addr:full":"212 S Montana St Butte MT 59701",
    "addr:housenumber":"212",
    "addr:postcode":"mt 59701",
    "addr:street":"S Montana St",
    "iso:country":"US",
    "sg:address":"212 S Montana St",
    "sg:city":"Butte",
    "sg:classifiers":[
        {
            "category":"Manufacturing",
            "subcategory":"Printing",
            "type":"Manufacturing & Wholesale Goods"
        }
    ],
    "sg:phone":"+1 406 723 4736",
    "sg:postcode":"59701",
    "sg:province":"MT",
    "sg:tags":[
        "printer"
    ],
    "wof:name":"Greenfield Printers Inc",
    "wof:placetype":"venue"
},
  "geometry": {"coordinates":[-112.539287,46.010876],"type":"Point"}
}