{
  "type": "Feature",
  "properties": {
    "iso:country":"US",
    "sg:address":"2224 US Hwy 87 E",
    "sg:city":"Billings",
    "sg:classifiers":[
        {
            "category":"Professional",
            "subcategory":"Management & Consulting",
            "type":"Services"
        }
    ],
    "sg:phone":"+1 406 256 1652",
    "sg:postcode":"59101",
    "sg:province":"MT",
    "sg:tags":[
        "resource",
        "human"
    ],
    "wof:name":"Jashaun L Eagleman",
    "wof:placetype":"venue"
},
  "geometry": {"coordinates":[-108.428019,45.796351],"type":"Point"}
}