{
  "type": "Feature",
  "properties": {
    "iso:country":"US",
    "sg:address":"4321 Loma Vista Dr",
    "sg:city":"Billings",
    "sg:classifiers":[
        {
            "category":"Banks & Credit Unions",
            "subcategory":"Investment Brokerage",
            "type":"Services"
        }
    ],
    "sg:phone":"+1 406 248 6508",
    "sg:postcode":"59106",
    "sg:province":"MT",
    "sg:tags":[
        "natural",
        "gas"
    ],
    "wof:name":"Nielson Energy Inc",
    "wof:placetype":"venue"
},
  "geometry": {"coordinates":[-108.625454,45.797922],"type":"Point"}
}