{
  "type": "Feature",
  "properties": {
    "iso:country":"US",
    "sg:address":"302 Central Ave",
    "sg:city":"Fairfield",
    "sg:classifiers":[
        {
            "category":"Autos & Motor Vehicles",
            "subcategory":"Automobile Sales",
            "type":"Retail Goods"
        }
    ],
    "sg:phone":"+1 406 467 2511",
    "sg:postcode":"59436",
    "sg:province":"MT",
    "sg:tags":[
        "car",
        "dealer"
    ],
    "sg:website":"www.millsmotor.net",
    "wof:name":"Mills Motor Co",
    "wof:placetype":"venue"
},
  "geometry": {"coordinates":[-111.981696,47.614527],"type":"Point"}
}