{
  "type": "Feature",
  "properties": {
    "addr:full":"2810 Pine St Butte MT 59701",
    "addr:housenumber":"2810",
    "addr:postcode":"mt 59701",
    "addr:street":"Pine St",
    "iso:country":"US",
    "sg:address":"2810 Pine St",
    "sg:city":"Butte",
    "sg:classifiers":[
        {
            "category":"Restaurant",
            "type":"Food & Drink"
        }
    ],
    "sg:phone":"+1 406 782 7410",
    "sg:postcode":"59701",
    "sg:province":"MT",
    "sg:tags":[
        "caterer"
    ],
    "wof:name":"Nancy Mc Laughlin's Pasty Shop",
    "wof:placetype":"venue"
},
  "geometry": {"coordinates":[-112.493567,46.004148],"type":"Point"}
}