{
  "type": "Feature",
  "properties": {
    "addr:full":"1820 W Lincoln St Bozeman MT 59715",
    "addr:housenumber":"1820",
    "addr:postcode":"59715",
    "addr:street":"W Lincoln St",
    "iso:country":"US",
    "sg:address":"1820 W Lincoln St",
    "sg:city":"Bozeman",
    "sg:classifiers":[
        {
            "category":"Insurance",
            "subcategory":"Hazard Insurance",
            "type":"Services"
        }
    ],
    "sg:phone":"+1 406 582 0919",
    "sg:postcode":"59715",
    "sg:province":"MT",
    "sg:tags":[
        "carrier"
    ],
    "wof:name":"Liberty Northwest Companies",
    "wof:placetype":"venue"
},
  "geometry": {"coordinates":[-111.061747,45.663849],"type":"Point"}
}