{
  "type": "Feature",
  "properties": {
    "iso:country":"US",
    "sg:address":"241 Red Coulee Rd",
    "sg:city":"Belt",
    "sg:classifiers":[
        {
            "category":"Professional",
            "subcategory":"Accounting & Tax Preparation",
            "type":"Services"
        }
    ],
    "sg:phone":"+1 406 277 3056",
    "sg:postcode":"59412",
    "sg:province":"MT",
    "sg:tags":[
        "return"
    ],
    "wof:name":"Health Center Financial Svcs",
    "wof:placetype":"venue"
},
  "geometry": {"coordinates":[-110.959827,47.456813],"type":"Point"}
}