{
  "type": "Feature",
  "properties": {
    "iso:country":"US",
    "sg:address":"103 Lyndale Ave",
    "sg:city":"Hamilton",
    "sg:classifiers":[
        {
            "category":"Professional",
            "type":"Services"
        }
    ],
    "sg:phone":"+1 406 363 4220",
    "sg:postcode":"59840",
    "sg:province":"MT",
    "sg:tags":[
        "establishment"
    ],
    "wof:name":"Cuddle Bugs",
    "wof:placetype":"venue"
},
  "geometry": {"coordinates":[-114.158929,46.256751],"type":"Point"}
}