{
  "type": "Feature",
  "properties": {
    "iso:country":"US",
    "sg:address":"501 Brooks St",
    "sg:city":"Missoula",
    "sg:classifiers":[
        {
            "category":"Building & Trades",
            "subcategory":"Construction",
            "type":"Services"
        }
    ],
    "sg:phone":"+1 406 721 3212",
    "sg:postcode":"59801",
    "sg:province":"MT",
    "sg:tags":[
        "house",
        "nonresidential",
        "general",
        "contractor"
    ],
    "wof:name":"Jon B Cusker Construction",
    "wof:placetype":"venue"
},
  "geometry": {"coordinates":[-114.003476,46.858686],"type":"Point"}
}