{
  "type": "Feature",
  "properties": {
    "iso:country":"US",
    "sg:address":"348 Flower Creek Rd",
    "sg:city":"Libby",
    "sg:classifiers":[
        {
            "category":"Retail",
            "subcategory":"Auto Repair",
            "type":"Services"
        }
    ],
    "sg:phone":"+1 406 293 8535",
    "sg:postcode":"59923",
    "sg:province":"MT",
    "sg:tags":[
        "general"
    ],
    "wof:name":"Raycin Automotive",
    "wof:placetype":"venue"
},
  "geometry": {"coordinates":[-115.56304900000001,48.38162],"type":"Point"}
}