{
  "type": "Feature",
  "properties": {
    "iso:country":"US",
    "sg:address":"300 1st Ave W",
    "sg:city":"Poplar",
    "sg:classifiers":[
        {
            "category":"Food & Beverages",
            "subcategory":"Groceries & Convenience Stores",
            "type":"Retail Goods"
        }
    ],
    "sg:phone":"+1 406 768 3461",
    "sg:postcode":"59255",
    "sg:province":"MT",
    "sg:tags":[
        "grocer"
    ],
    "wof:name":"Tande Grocery",
    "wof:placetype":"venue"
},
  "geometry": {"coordinates":[-105.195477,48.110839],"type":"Point"}
}