{
  "type": "Feature",
  "properties": {
    "iso:country":"US",
    "sg:address":"5320 Holiday Ave",
    "sg:city":"Billings",
    "sg:classifiers":[
        {
            "category":"Wholesale",
            "subcategory":"Electrical",
            "type":"Manufacturing & Wholesale Goods"
        }
    ],
    "sg:phone":"+1 406 248 4204",
    "sg:postcode":"59101",
    "sg:province":"MT",
    "sg:tags":[
        "telecommunication"
    ],
    "sg:website":"www.abtelcom.net",
    "wof:name":"A B Telcom",
    "wof:placetype":"venue"
},
  "geometry": {"coordinates":[-108.54675400000001,45.744969],"type":"Point"}
}