{
  "type": "Feature",
  "properties": {
    "iso:country":"US",
    "sg:address":"35 Hossfeld Ln",
    "sg:city":"Toston",
    "sg:classifiers":[
        {
            "category":"Farming",
            "subcategory":"Livestock Farm",
            "type":"Manufacturing & Wholesale Goods"
        }
    ],
    "sg:phone":"+1 406 266 4445",
    "sg:postcode":"59643",
    "sg:province":"MT",
    "sg:tags":[
        "beef",
        "feedlot",
        "cattle"
    ],
    "wof:name":"Robert Hossfeld",
    "wof:placetype":"venue"
},
  "geometry": {"coordinates":[-111.51551000000001,46.135969],"type":"Point"}
}