{
  "type": "Feature",
  "properties": {
    "iso:country":"US",
    "sg:address":"2 Eaton Ave",
    "sg:city":"Great Falls",
    "sg:classifiers":[
        {
            "category":"Real Estate",
            "subcategory":"Real Estate Agent",
            "type":"Services"
        }
    ],
    "sg:phone":"+1 406 453 3391",
    "sg:postcode":"59405",
    "sg:province":"MT",
    "wof:name":"Stone Management Services",
    "wof:placetype":"venue"
},
  "geometry": {"coordinates":[-111.246349,47.471081],"type":"Point"}
}