{
  "type": "Feature",
  "properties": {
    "iso:country":"US",
    "sg:address":"702 S Main St",
    "sg:city":"Conrad",
    "sg:classifiers":[
        {
            "category":"Organizations",
            "subcategory":"Non-profit Organization",
            "type":"Services"
        }
    ],
    "sg:phone":"+1 406 271 7237",
    "sg:postcode":"59425",
    "sg:province":"MT",
    "wof:name":"PCP Pondera Coalition",
    "wof:placetype":"venue"
},
  "geometry": {"coordinates":[-111.949262,48.165192],"type":"Point"}
}