{
  "type": "Feature",
  "properties": {
    "iso:country":"US",
    "sg:address":"602 2nd Ave",
    "sg:city":"Homestead",
    "sg:classifiers":[
        {
            "category":"Professional",
            "type":"Services"
        }
    ],
    "sg:phone":"+1 406 963 2307",
    "sg:postcode":"59219",
    "sg:province":"MT",
    "sg:tags":[
        "biological",
        "research"
    ],
    "wof:name":"Ross D Flagen",
    "wof:placetype":"venue"
},
  "geometry": {"coordinates":[-104.536106,48.419844],"type":"Point"}
}