{
  "type": "Feature",
  "properties": {
    "addr:full":"28 W Main St Bozeman MT 59715",
    "addr:housenumber":"28",
    "addr:postcode":"59715",
    "addr:street":"W Main St",
    "iso:country":"US",
    "sg:address":"28 W Main St",
    "sg:city":"Bozeman",
    "sg:classifiers":[
        {
            "category":"Shopping",
            "subcategory":"Books",
            "type":"Retail Goods"
        }
    ],
    "sg:phone":"+1 406 587 0166",
    "sg:postcode":"59715",
    "sg:province":"MT",
    "wof:name":"Country Bookshelf",
    "wof:placetype":"venue"
},
  "geometry": {"coordinates":[-111.038477,45.679189],"type":"Point"}
}