{
  "type": "Feature",
  "properties": {
    "iso:country":"US",
    "sg:address":"1313 Renwood Dr",
    "sg:city":"Libby",
    "sg:classifiers":[
        {
            "category":"Home & Garden",
            "subcategory":"Building Materials",
            "type":"Retail Goods"
        }
    ],
    "sg:phone":"+1 406 293 3985",
    "sg:postcode":"59923",
    "sg:province":"MT",
    "sg:tags":[
        "insulation"
    ],
    "wof:name":"Kootenai Insulation",
    "wof:placetype":"venue"
},
  "geometry": {"coordinates":[-115.564563,48.384431],"type":"Point"}
}