{
  "type": "Feature",
  "properties": {
    "addr:full":"615 Pattee Canyon Dr Missoula MT 59803",
    "addr:housenumber":"615",
    "addr:postcode":"59803",
    "addr:street":"Pattee Canyon Dr",
    "iso:country":"US",
    "sg:address":"615 Pattee Canyon Dr",
    "sg:city":"Missoula",
    "sg:classifiers":[
        {
            "category":"Retail",
            "subcategory":"Repair Shop",
            "type":"Services"
        }
    ],
    "sg:phone":"+1 406 549 2206",
    "sg:postcode":"59803",
    "sg:province":"MT",
    "sg:tags":[
        "electrical"
    ],
    "wof:name":"Montana Guitar Works",
    "wof:placetype":"venue"
},
  "geometry": {"coordinates":[-113.989327,46.834793],"type":"Point"}
}