{
  "type": "Feature",
  "properties": {
    "iso:country":"US",
    "sg:address":"226 Edgewood Dr",
    "sg:city":"Kalispell",
    "sg:classifiers":[
        {
            "category":"Wholesale",
            "subcategory":"Meat",
            "type":"Manufacturing & Wholesale Goods"
        }
    ],
    "sg:phone":"+1 406 752 3093",
    "sg:postcode":"59901",
    "sg:province":"MT",
    "sg:tags":[
        "plant",
        "packing"
    ],
    "wof:name":"Dons Country Smokehouse",
    "wof:placetype":"venue"
},
  "geometry": {"coordinates":[-114.266319,48.230503],"type":"Point"}
}