{
  "type": "Feature",
  "properties": {
    "iso:country":"US",
    "sg:address":"1143 US Hwy 93 S",
    "sg:city":"Hamilton",
    "sg:classifiers":[
        {
            "category":"Building & Trades",
            "subcategory":"Construction",
            "type":"Services"
        }
    ],
    "sg:phone":"+1 406 360 5032",
    "sg:postcode":"59840",
    "sg:province":"MT",
    "sg:tags":[
        "paving",
        "contractor"
    ],
    "wof:name":"Crocket Paving",
    "wof:placetype":"venue"
},
  "geometry": {"coordinates":[-114.181994,46.177201],"type":"Point"}
}