{
  "type": "Feature",
  "properties": {
    "addr:full":"4148 1st Ave S Billings MT 59101",
    "addr:housenumber":"4148",
    "addr:postcode":"59101",
    "addr:street":"1St Ave S",
    "iso:country":"US",
    "sg:address":"4148 1st Ave S",
    "sg:city":"Billings",
    "sg:classifiers":[
        {
            "category":"Wholesale",
            "subcategory":"Stationery",
            "type":"Manufacturing & Wholesale Goods"
        }
    ],
    "sg:phone":"+1 406 259 5432",
    "sg:postcode":"59101",
    "sg:province":"MT",
    "sg:tags":[
        "business",
        "form",
        "system"
    ],
    "sg:website":"www.eagleforms.net",
    "wof:name":"Eagle Business Forms",
    "wof:placetype":"venue"
},
  "geometry": {"coordinates":[-108.521912,45.770518],"type":"Point"}
}