{
  "type": "Feature",
  "properties": {
    "iso:country":"US",
    "sg:address":"3328 Pipestone Dr",
    "sg:city":"Billings",
    "sg:classifiers":[
        {
            "category":"Food & Beverages",
            "subcategory":"Bakery",
            "type":"Retail Goods"
        }
    ],
    "sg:phone":"+1 406 651 8662",
    "sg:postcode":"59102",
    "sg:province":"MT",
    "wof:name":"Cakes & Bake",
    "wof:placetype":"venue"
},
  "geometry": {"coordinates":[-108.598759,45.763643],"type":"Point"}
}