{
  "type": "Feature",
  "properties": {
    "iso:country":"US",
    "sg:address":"1803 N Rouse Ave",
    "sg:city":"Bozeman",
    "sg:classifiers":[
        {
            "category":"Retail",
            "subcategory":"Auto Repair",
            "type":"Services"
        }
    ],
    "sg:phone":"+1 406 587 8261",
    "sg:postcode":"59715",
    "sg:province":"MT",
    "sg:tags":[
        "general"
    ],
    "wof:name":"Truck & Equipment Company",
    "wof:placetype":"venue"
},
  "geometry": {"coordinates":[-111.031487,45.697653],"type":"Point"}
}