{
  "type": "Feature",
  "properties": {
    "iso:country":"US",
    "sg:address":"1240 Burlington Ave",
    "sg:city":"Billings",
    "sg:classifiers":[
        {
            "category":"Manufacturing",
            "subcategory":"Printing",
            "type":"Manufacturing & Wholesale Goods"
        }
    ],
    "sg:phone":"+1 406 248 3465",
    "sg:postcode":"59102",
    "sg:province":"MT",
    "sg:tags":[
        "consulting",
        "book",
        "business"
    ],
    "wof:name":"Council For Indian Education",
    "wof:placetype":"venue"
},
  "geometry": {"coordinates":[-108.547771,45.781539],"type":"Point"}
}