{
  "type": "Feature",
  "properties": {
    "iso:country":"US",
    "sg:address":"1232 E 6th Ave",
    "sg:city":"Helena",
    "sg:classifiers":[
        {
            "category":"Organizations",
            "subcategory":"Labor Organization",
            "type":"Services"
        }
    ],
    "sg:phone":"+1 406 442 2123",
    "sg:postcode":"59601",
    "sg:province":"MT",
    "wof:name":"MEA Mft Southwest Field Ofc",
    "wof:placetype":"venue"
},
  "geometry": {"coordinates":[-112.018863,46.586848],"type":"Point"}
}