{
  "type": "Feature",
  "properties": {
    "addr:full":"520 N F St Livingston MT 59047",
    "addr:housenumber":"520",
    "addr:postcode":"59047",
    "addr:street":"N F St",
    "iso:country":"US",
    "sg:address":"520 N F St",
    "sg:city":"Livingston",
    "sg:classifiers":[
        {
            "category":"Building & Trades",
            "subcategory":"Construction",
            "type":"Services"
        }
    ],
    "sg:phone":"+1 406 222 4995",
    "sg:postcode":"59047",
    "sg:province":"MT",
    "sg:tags":[
        "remodeling"
    ],
    "wof:name":"Sam Gordon",
    "wof:placetype":"venue"
},
  "geometry": {"coordinates":[-110.55883300000001,45.668704],"type":"Point"}
}