{
  "type": "Feature",
  "properties": {
    "iso:country":"US",
    "sg:address":"100 W Laurel Ave",
    "sg:city":"Plentywood",
    "sg:classifiers":[
        {
            "category":"Government",
            "subcategory":"Office",
            "type":"Public Place"
        }
    ],
    "sg:phone":"+1 406 765 3414",
    "sg:postcode":"59254",
    "sg:province":"MT",
    "sg:tags":[
        "county",
        "taxation"
    ],
    "wof:name":"Sheridan County Treasurer",
    "wof:placetype":"venue"
},
  "geometry": {"coordinates":[-104.558142,48.778403],"type":"Point"}
}