{
  "type": "Feature",
  "properties": {
    "iso:country":"US",
    "sg:address":"PO Box 8255",
    "sg:city":"Missoula",
    "sg:classifiers":[
        {
            "category":"Professional",
            "subcategory":"Computer Services",
            "type":"Services"
        }
    ],
    "sg:postcode":"59802",
    "sg:province":"MT",
    "sg:tags":[
        "submissions",
        "curation",
        "cloud-based-document-management"
    ],
    "sg:website":"http://www.submishmash.com",
    "wof:name":"Submishmash",
    "wof:placetype":"venue"
},
  "geometry": {"coordinates":[-113.91914800000001,46.903865],"type":"Point"}
}