{
  "type": "Feature",
  "properties": {
    "iso:country":"US",
    "sg:address":"3800 10th Ave S",
    "sg:city":"Great Falls",
    "sg:classifiers":[
        {
            "category":"Restaurant",
            "type":"Food & Drink"
        }
    ],
    "sg:phone":"+1 406 761 4550",
    "sg:postcode":"59405",
    "sg:province":"MT",
    "sg:tags":[
        "eating"
    ],
    "wof:name":"Black Angus Steak House",
    "wof:placetype":"venue"
},
  "geometry": {"coordinates":[-111.240031,47.49404],"type":"Point"}
}