{
  "type": "Feature",
  "properties": {
    "iso:country":"US",
    "sg:address":"438 W Spruce St",
    "sg:city":"Missoula",
    "sg:classifiers":[
        {
            "category":"Government",
            "subcategory":"Office",
            "type":"Public Place"
        }
    ],
    "sg:phone":"+1 406 523 4861",
    "sg:postcode":"59802",
    "sg:province":"MT",
    "sg:tags":[
        "educational",
        "program",
        "administrative"
    ],
    "wof:name":"Missoula Area Education Co Op",
    "wof:placetype":"venue"
},
  "geometry": {"coordinates":[-113.99823000000001,46.875718],"type":"Point"}
}