{
  "type": "Feature",
  "properties": {
    "iso:country":"US",
    "sg:address":"1027 N 27th St",
    "sg:city":"Billings",
    "sg:classifiers":[
        {
            "category":"Shopping",
            "type":"Retail Goods"
        }
    ],
    "sg:phone":"+1 406 248 9002",
    "sg:postcode":"59101",
    "sg:province":"MT",
    "sg:tags":[
        "orthopedic",
        "appliance"
    ],
    "wof:name":"Great Plains Health Co",
    "wof:placetype":"venue"
},
  "geometry": {"coordinates":[-108.513826,45.792296],"type":"Point"}
}