{
  "type": "Feature",
  "properties": {
    "iso:country":"US",
    "sg:address":"1525 Central Ave",
    "sg:city":"Billings",
    "sg:classifiers":[
        {
            "category":"Professional",
            "subcategory":"Computer Services",
            "type":"Services"
        }
    ],
    "sg:phone":"+1 406 655 1788",
    "sg:postcode":"59102",
    "sg:province":"MT",
    "sg:tags":[
        "internet"
    ],
    "wof:name":"Freedom Satellite",
    "wof:placetype":"venue"
},
  "geometry": {"coordinates":[-108.555729,45.769839],"type":"Point"}
}