{
  "type": "Feature",
  "properties": {
    "iso:country":"US",
    "sg:address":"5610 Alabama Dr",
    "sg:city":"Helena",
    "sg:classifiers":[
        {
            "category":"Building & Trades",
            "subcategory":"Landscaping Services",
            "type":"Services"
        }
    ],
    "sg:phone":"+1 406 458 9568",
    "sg:postcode":"59602",
    "sg:province":"MT",
    "sg:tags":[
        "landscape",
        "contractor"
    ],
    "wof:name":"B & Z Landscaping",
    "wof:placetype":"venue"
},
  "geometry": {"coordinates":[-112.022835,46.655905],"type":"Point"}
}