{
  "type": "Feature",
  "properties": {
    "iso:country":"US",
    "sg:address":"125 C St",
    "sg:city":"Lewistown",
    "sg:classifiers":[
        {
            "category":"Organizations",
            "subcategory":"Religious Organization",
            "type":"Services"
        }
    ],
    "sg:phone":"+1 406 538 8563",
    "sg:postcode":"59457",
    "sg:province":"MT",
    "wof:name":"Saint Pauls Lutheran Church",
    "wof:placetype":"venue"
},
  "geometry": {"coordinates":[-109.439757,47.059529],"type":"Point"}
}