{
  "type": "Feature",
  "properties": {
    "iso:country":"US",
    "sg:address":"100 W Foss Ct",
    "sg:city":"Missoula",
    "sg:classifiers":[
        {
            "category":"Organizations",
            "subcategory":"Religious Organization",
            "type":"Services"
        }
    ],
    "sg:phone":"+1 406 251 3983",
    "sg:postcode":"59803",
    "sg:province":"MT",
    "wof:name":"Missoula Alliance Pre School",
    "wof:placetype":"venue"
},
  "geometry": {"coordinates":[-114.029743,46.818438],"type":"Point"}
}