{
  "type": "Feature",
  "properties": {
    "iso:country":"US",
    "sg:address":"102 Main St SW",
    "sg:city":"Ronan",
    "sg:classifiers":[
        {
            "category":"Manufacturing",
            "subcategory":"Printing",
            "type":"Manufacturing & Wholesale Goods"
        }
    ],
    "sg:phone":"+1 406 676 2804",
    "sg:postcode":"59864",
    "sg:province":"MT",
    "sg:tags":[
        "magazine",
        "publishing"
    ],
    "wof:name":"Milestone Publications Inc",
    "wof:placetype":"venue"
},
  "geometry": {"coordinates":[-114.10011299999999,47.52881],"type":"Point"}
}