{
  "type": "Feature",
  "properties": {
    "addr:full":"1942 Birch St Missoula MT 59808",
    "addr:housenumber":"1942",
    "addr:postcode":"59808",
    "addr:street":"Birch St",
    "iso:country":"US",
    "sg:address":"1942 Birch St",
    "sg:city":"Missoula",
    "sg:classifiers":[
        {
            "category":"Utilities",
            "subcategory":"Cable",
            "type":"Services"
        }
    ],
    "sg:phone":"+1 406 542 3444",
    "sg:postcode":"59808",
    "sg:province":"MT",
    "sg:tags":[
        "television",
        "trade",
        "contractor"
    ],
    "wof:name":"Montana Wireless Television",
    "wof:placetype":"venue"
},
  "geometry": {"coordinates":[-114.020758,46.88069],"type":"Point"}
}