{
  "type": "Feature",
  "properties": {
    "addr:full":"1 Tina Ave Missoula MT 59808",
    "addr:housenumber":"1",
    "addr:postcode":"59808",
    "addr:street":"Tina Ave",
    "iso:country":"US",
    "sg:address":"1 Tina Ave",
    "sg:city":"Missoula",
    "sg:classifiers":[
        {
            "category":"Manufacturing",
            "subcategory":"Lumber",
            "type":"Manufacturing & Wholesale Goods"
        }
    ],
    "sg:phone":"+1 406 542 1807",
    "sg:postcode":"59808",
    "sg:province":"MT",
    "sg:tags":[
        "fire",
        "forest"
    ],
    "wof:name":"Steven R Combs",
    "wof:placetype":"venue"
},
  "geometry": {"coordinates":[-114.04146799999999,46.892489],"type":"Point"}
}