{
  "type": "Feature",
  "properties": {
    "iso:country":"US",
    "sg:address":"718 Logan St",
    "sg:city":"Helena",
    "sg:classifiers":[
        {
            "category":"Education",
            "subcategory":"Dance Studio",
            "type":"Public Place"
        }
    ],
    "sg:phone":"+1 406 442 6519",
    "sg:postcode":"59601",
    "sg:province":"MT",
    "wof:name":"Creative Arts Center Helena",
    "wof:placetype":"venue"
},
  "geometry": {"coordinates":[-112.032732,46.593851],"type":"Point"}
}