{
  "type": "Feature",
  "properties": {
    "iso:country":"US",
    "sg:address":"6400 Yellowstone Trl",
    "sg:city":"Huntley",
    "sg:classifiers":[
        {
            "category":"Freight",
            "type":"Transportation"
        }
    ],
    "sg:phone":"+1 406 248 1164",
    "sg:postcode":"59037",
    "sg:province":"MT",
    "sg:tags":[
        "hauling",
        "trucking"
    ],
    "wof:name":"Gary Zumbrun Trucking",
    "wof:placetype":"venue"
},
  "geometry": {"coordinates":[-108.321072,45.865802],"type":"Point"}
}