{
  "type": "Feature",
  "properties": {
    "iso:country":"US",
    "sg:address":"503 N Black Ave",
    "sg:city":"Bozeman",
    "sg:classifiers":[
        {
            "category":"Professional",
            "subcategory":"Research",
            "type":"Services"
        }
    ],
    "sg:phone":"+1 406 586 1148",
    "sg:postcode":"59715",
    "sg:province":"MT",
    "sg:tags":[
        "commercial",
        "physical"
    ],
    "wof:name":"Western Biologics Inc",
    "wof:placetype":"venue"
},
  "geometry": {"coordinates":[-111.036001,45.685499],"type":"Point"}
}