{
  "type": "Feature",
  "properties": {
    "iso:country":"US",
    "sg:address":"1040 Maki Ln",
    "sg:city":"Corvallis",
    "sg:classifiers":[
        {
            "category":"Professional",
            "subcategory":"Business Services",
            "type":"Services"
        }
    ],
    "sg:phone":"+1 406 961 5555",
    "sg:postcode":"59828",
    "sg:province":"MT",
    "sg:tags":[
        "recording",
        "studio"
    ],
    "wof:name":"True Proportions Studio",
    "wof:placetype":"venue"
},
  "geometry": {"coordinates":[-114.053139,46.284167],"type":"Point"}
}