{
  "type": "Feature",
  "properties": {
    "iso:country":"US",
    "sg:address":"423 Erie Dr",
    "sg:city":"Billings",
    "sg:classifiers":[
        {
            "category":"Manufacturing",
            "subcategory":"Signs",
            "type":"Manufacturing & Wholesale Goods"
        }
    ],
    "sg:phone":"+1 406 245 8919",
    "sg:postcode":"59101",
    "sg:province":"MT",
    "sg:tags":[
        "electric",
        "mfg"
    ],
    "sg:website":"www.rimrocksigns.com",
    "wof:name":"Rimrock Signs Inc",
    "wof:placetype":"venue"
},
  "geometry": {"coordinates":[-108.49109300000001,45.770538],"type":"Point"}
}