{
  "type": "Feature",
  "properties": {
    "iso:country":"US",
    "sg:address":"139 State Hwy 24W",
    "sg:city":"Glasgow",
    "sg:classifiers":[
        {
            "category":"Utilities",
            "subcategory":"Natural Gas",
            "type":"Services"
        }
    ],
    "sg:phone":"+1 406 228 4395",
    "sg:postcode":"59230",
    "sg:province":"MT",
    "sg:tags":[
        "transportation"
    ],
    "wof:name":"Northern Plains Natural Gas Co",
    "wof:placetype":"venue"
},
  "geometry": {"coordinates":[-106.631512,48.193117],"type":"Point"}
}