{
  "type": "Feature",
  "properties": {
    "iso:country":"US",
    "sg:address":"3211 Hesper Rd",
    "sg:city":"Billings",
    "sg:classifiers":[
        {
            "category":"Wholesale",
            "subcategory":"Electrical",
            "type":"Manufacturing & Wholesale Goods"
        }
    ],
    "sg:phone":"+1 406 656 5030",
    "sg:postcode":"59102",
    "sg:province":"MT",
    "sg:tags":[
        "alarm",
        "burglar",
        "system"
    ],
    "wof:name":"Big Sky Security",
    "wof:placetype":"venue"
},
  "geometry": {"coordinates":[-108.598713,45.740792],"type":"Point"}
}