{
  "type": "Feature",
  "properties": {
    "iso:country":"US",
    "sg:address":"1065 Boylan Rd",
    "sg:city":"Bozeman",
    "sg:classifiers":[
        {
            "category":"Professional",
            "subcategory":"Business Services",
            "type":"Services"
        }
    ],
    "sg:phone":"+1 406 586 9199",
    "sg:postcode":"59715",
    "sg:province":"MT",
    "wof:name":"Montana Education Assoc",
    "wof:placetype":"venue"
},
  "geometry": {"coordinates":[-111.02466800000001,45.705411],"type":"Point"}
}