{
  "type": "Feature",
  "properties": {
    "iso:country":"US",
    "sg:address":"13 Valleyview Dr",
    "sg:city":"Helena",
    "sg:classifiers":[
        {
            "category":"Professional",
            "subcategory":"Management & Consulting",
            "type":"Services"
        }
    ],
    "sg:phone":"+1 406 442 5636",
    "sg:postcode":"59601",
    "sg:province":"MT",
    "sg:tags":[
        "translation",
        "education",
        "interpreting"
    ],
    "wof:name":"Tanya A Lukenbil",
    "wof:placetype":"venue"
},
  "geometry": {"coordinates":[-112.000353,46.577969],"type":"Point"}
}