{
  "type": "Feature",
  "properties": {
    "addr:full":"2428 North Ave W Missoula MT 59801",
    "addr:housenumber":"2428",
    "addr:postcode":"59801",
    "addr:street":"North Ave W",
    "iso:country":"US",
    "sg:address":"2428 North Ave W",
    "sg:city":"Missoula",
    "sg:classifiers":[
        {
            "category":"Organizations",
            "subcategory":"Community Association",
            "type":"Services"
        }
    ],
    "sg:phone":"+1 406 549 4678",
    "sg:postcode":"59801",
    "sg:province":"MT",
    "wof:name":"Milida Chapter Order Demolay",
    "wof:placetype":"venue"
},
  "geometry": {"coordinates":[-114.039421,46.852478],"type":"Point"}
}