{
  "type": "Feature",
  "properties": {
    "iso:country":"US",
    "sg:address":"414 9th St S",
    "sg:city":"Great Falls",
    "sg:classifiers":[
        {
            "category":"Shopping",
            "type":"Retail Goods"
        }
    ],
    "sg:phone":"+1 406 454 2522",
    "sg:postcode":"59405",
    "sg:province":"MT",
    "sg:tags":[
        "communication",
        "radiotelephone",
        "merchandise"
    ],
    "wof:name":"Airtel Wireless",
    "wof:placetype":"venue"
},
  "geometry": {"coordinates":[-111.292188,47.499918],"type":"Point"}
}