{
  "type": "Feature",
  "properties": {
    "iso:country":"US",
    "sg:address":"2014 Gilkerson St",
    "sg:city":"Bozeman",
    "sg:classifiers":[
        {
            "category":"Professional",
            "subcategory":"Engineering",
            "type":"Services"
        }
    ],
    "sg:phone":"+1 406 585 5415",
    "sg:postcode":"59715",
    "sg:province":"MT",
    "wof:name":"Joe Stanislao Pe",
    "wof:placetype":"venue"
},
  "geometry": {"coordinates":[-111.04278499999999,45.698138],"type":"Point"}
}