{
  "type": "Feature",
  "properties": {
    "addr:full":"599 Somers Rd Somers MT 59932",
    "addr:housenumber":"599",
    "addr:postcode":"59932",
    "addr:street":"Somers Rd",
    "iso:country":"US",
    "sg:address":"599 Somers Rd",
    "sg:city":"Somers",
    "sg:classifiers":[
        {
            "category":"Building & Trades",
            "subcategory":"Cleaning & Sanitation",
            "type":"Services"
        }
    ],
    "sg:phone":"+1 406 857 3155",
    "sg:postcode":"59932",
    "sg:province":"MT",
    "sg:tags":[
        "maintenance"
    ],
    "wof:name":"A Days Work",
    "wof:placetype":"venue"
},
  "geometry": {"coordinates":[-114.218271,48.081787],"type":"Point"}
}