{
  "type": "Feature",
  "properties": {
    "addr:full":"4227 Pine Cove Rd Billings MT 59106",
    "addr:housenumber":"4227",
    "addr:street":"Pine Cove Rd",
    "iso:country":"US",
    "sg:address":"4227 Pine Cove Rd",
    "sg:city":"Billings",
    "sg:classifiers":[
        {
            "category":"Building & Trades",
            "subcategory":"Construction",
            "type":"Services"
        }
    ],
    "sg:phone":"+1 406 656 4884",
    "sg:postcode":"59106",
    "sg:province":"MT",
    "sg:tags":[
        "general",
        "contractor"
    ],
    "wof:name":"Artisan Builders Dennis Olson",
    "wof:placetype":"venue"
},
  "geometry": {"coordinates":[-108.62320800000001,45.801157],"type":"Point"}
}