{
  "type": "Feature",
  "properties": {
    "addr:full":"19900 Molly Ln Florence MT 59833",
    "addr:housenumber":"19900",
    "addr:postcode":"59833",
    "addr:street":"Molly Ln",
    "iso:country":"US",
    "sg:address":"19900 Molly Ln",
    "sg:city":"Florence",
    "sg:classifiers":[
        {
            "category":"Professional",
            "subcategory":"Business Services",
            "type":"Services"
        }
    ],
    "sg:phone":"+1 406 273 2912",
    "sg:postcode":"59833",
    "sg:province":"MT",
    "wof:name":"Vivid Design LLC",
    "wof:placetype":"venue"
},
  "geometry": {"coordinates":[-114.085841,46.681312],"type":"Point"}
}