{
  "type": "Feature",
  "properties": {
    "addr:full":"706 S Central Ave Sidney MT 59270",
    "addr:housenumber":"706",
    "addr:postcode":"59270",
    "addr:street":"S Central Ave",
    "iso:country":"US",
    "sg:address":"706 S Central Ave",
    "sg:city":"Sidney",
    "sg:classifiers":[
        {
            "category":"Food & Beverages",
            "subcategory":"Groceries & Convenience Stores",
            "type":"Retail Goods"
        }
    ],
    "sg:phone":"+1 406 482 5647",
    "sg:postcode":"59270",
    "sg:province":"MT",
    "sg:tags":[
        "station",
        "gasoline"
    ],
    "wof:name":"Mini Mart Inc",
    "wof:placetype":"venue"
},
  "geometry": {"coordinates":[-104.16079000000001,47.709421],"type":"Point"}
}