{
  "type": "Feature",
  "properties": {
    "addr:full":"2001 Old Hardin Rd Billings MT 59101",
    "addr:housenumber":"2001",
    "addr:postcode":"59101",
    "addr:street":"Old Hardin Rd",
    "iso:country":"US",
    "sg:address":"2001 Old Hardin Rd",
    "sg:city":"Billings",
    "sg:classifiers":[
        {
            "category":"Wholesale",
            "subcategory":"Machinery & Supplies",
            "type":"Manufacturing & Wholesale Goods"
        }
    ],
    "sg:phone":"+1 406 252 7667",
    "sg:postcode":"59101",
    "sg:province":"MT",
    "sg:tags":[
        "contractor"
    ],
    "wof:name":"Ditch Witch Of Montana",
    "wof:placetype":"venue"
},
  "geometry": {"coordinates":[-108.43076600000001,45.805621],"type":"Point"}
}