{
  "type": "Feature",
  "properties": {
    "iso:country":"US",
    "sg:address":"518 Central Ave",
    "sg:city":"Great Falls",
    "sg:classifiers":[
        {
            "category":"Restaurant",
            "type":"Food & Drink"
        }
    ],
    "sg:phone":"+1 406 453 1760",
    "sg:postcode":"59401",
    "sg:province":"MT",
    "sg:tags":[
        "eating"
    ],
    "wof:name":"Lobby Cafe",
    "wof:placetype":"venue"
},
  "geometry": {"coordinates":[-111.29759199999999,47.505186],"type":"Point"}
}