{
  "type": "Feature",
  "properties": {
    "iso:country":"US",
    "sg:address":"4524 Central Ave",
    "sg:city":"Billings",
    "sg:phone":"+1 406 656 3686",
    "sg:postcode":"59106",
    "sg:province":"MT",
    "sg:tags":[
        "beef",
        "farm",
        "corn",
        "crop",
        "field",
        "cattle",
        "feedlot"
    ],
    "wof:name":"Hardt Bros Farm",
    "wof:placetype":"venue"
},
  "geometry": {"coordinates":[-108.631016,45.769589],"type":"Point"}
}