{
  "type": "Feature",
  "properties": {
    "addr:full":"210 W Main St Lewistown MT 59457",
    "addr:housenumber":"210",
    "addr:postcode":"59457",
    "addr:street":"W Main St",
    "iso:country":"US",
    "sg:address":"210 W Main St",
    "sg:city":"Lewistown",
    "sg:classifiers":[
        {
            "category":"Shopping",
            "subcategory":"Pharmacy",
            "type":"Retail Goods"
        }
    ],
    "sg:phone":"+1 406 538 8128",
    "sg:postcode":"59457",
    "sg:province":"MT",
    "wof:name":"Lewistown Pharmacy",
    "wof:placetype":"venue"
},
  "geometry": {"coordinates":[-109.425825,47.065442],"type":"Point"}
}