{
  "type": "Feature",
  "properties": {
    "iso:country":"US",
    "sg:address":"1220 Central Ave",
    "sg:city":"Great Falls",
    "sg:classifiers":[
        {
            "category":"Health Services",
            "subcategory":"Health Practitioner",
            "type":"Services"
        }
    ],
    "sg:phone":"+1 406 761 0471",
    "sg:postcode":"59401",
    "sg:province":"MT",
    "wof:name":"HealthSouth",
    "wof:placetype":"venue"
},
  "geometry": {"coordinates":[-111.285481,47.505118],"type":"Point"}
}