{
  "type": "Feature",
  "properties": {
    "addr:full":"869 E 2nd St Stevensville MT 59870",
    "addr:housenumber":"869",
    "addr:postcode":"59870",
    "addr:street":"E 2Nd St",
    "iso:country":"US",
    "sg:address":"869 E 2nd St",
    "sg:city":"Stevensville",
    "sg:classifiers":[
        {
            "category":"Wholesale",
            "subcategory":"Machinery & Supplies",
            "type":"Manufacturing & Wholesale Goods"
        }
    ],
    "sg:phone":"+1 406 777 3173",
    "sg:postcode":"59870",
    "sg:province":"MT",
    "wof:name":"Industrial Farm Sales",
    "wof:placetype":"venue"
},
  "geometry": {"coordinates":[-114.080518,46.50996],"type":"Point"}
}