{
  "type": "Feature",
  "properties": {
    "addr:full":"4422 N Montana Ave Helena MT 59602",
    "addr:housenumber":"4422",
    "addr:postcode":"59602",
    "addr:street":"N Montana Ave",
    "iso:country":"US",
    "sg:address":"4422 N Montana Ave",
    "sg:city":"Helena",
    "sg:classifiers":[
        {
            "category":"Professional",
            "subcategory":"Management & Consulting",
            "type":"Services"
        }
    ],
    "sg:phone":"+1 406 458 6277",
    "sg:postcode":"59602",
    "sg:province":"MT",
    "wof:name":"Quality Assurance Inc",
    "wof:placetype":"venue"
},
  "geometry": {"coordinates":[-112.021371,46.637815],"type":"Point"}
}