{
  "type": "Feature",
  "properties": {
    "iso:country":"US",
    "sg:address":"420 3rd St W",
    "sg:city":"Whitefish",
    "sg:classifiers":[
        {
            "category":"Professional",
            "subcategory":"Management & Consulting",
            "type":"Services"
        }
    ],
    "sg:phone":"+1 406 862 6130",
    "sg:postcode":"59937",
    "sg:province":"MT",
    "sg:tags":[
        "business"
    ],
    "wof:name":"Jeff Arcel Consulting",
    "wof:placetype":"venue"
},
  "geometry": {"coordinates":[-114.350469,48.409751],"type":"Point"}
}