{
  "type": "Feature",
  "properties": {
    "addr:full":"410 N 1st St Hamilton MT 59840",
    "addr:housenumber":"410",
    "addr:postcode":"59840",
    "addr:street":"N 1St St",
    "iso:country":"US",
    "sg:address":"410 N 1st St",
    "sg:city":"Hamilton",
    "sg:classifiers":[
        {
            "category":"Personal",
            "subcategory":"Beauty Salon",
            "type":"Services"
        }
    ],
    "sg:phone":"+1 406 363 3314",
    "sg:postcode":"59840",
    "sg:province":"MT",
    "sg:tags":[
        "shop"
    ],
    "wof:name":"Added Touch",
    "wof:placetype":"venue"
},
  "geometry": {"coordinates":[-114.156086,46.251233],"type":"Point"}
}