{
  "type": "Feature",
  "properties": {
    "addr:full":"450 Klock Rd Cascade MT 59421",
    "addr:housenumber":"450",
    "addr:postcode":"59421",
    "addr:street":"Klock Rd Cascade",
    "iso:country":"US",
    "sg:address":"450 Klock Rd",
    "sg:city":"Cascade",
    "sg:phone":"+1 406 468 2375",
    "sg:postcode":"59421",
    "sg:province":"MT",
    "sg:tags":[
        "wheat",
        "beef",
        "farm",
        "cash",
        "grain",
        "cattle",
        "feedlot"
    ],
    "wof:name":"Olson Brothers",
    "wof:placetype":"venue"
},
  "geometry": {"coordinates":[-111.48688300000001,47.30577],"type":"Point"}
}