{
  "type": "Feature",
  "properties": {
    "iso:country":"US",
    "sg:address":"4410 Rainbow Dr",
    "sg:city":"Missoula",
    "sg:classifiers":[
        {
            "category":"Social Services",
            "subcategory":"Child Care",
            "type":"Services"
        }
    ],
    "sg:phone":"+1 406 251 6945",
    "sg:postcode":"59803",
    "sg:province":"MT",
    "sg:tags":[
        "day"
    ],
    "wof:name":"Little Treasures Child Care",
    "wof:placetype":"venue"
},
  "geometry": {"coordinates":[-114.04158099999999,46.833437],"type":"Point"}
}