{
  "type": "Feature",
  "properties": {
    "addr:full":"2920 Outfitter Trl Laurel MT 59044",
    "addr:postcode":"2920;59044",
    "addr:street":"Outfitter Trl",
    "iso:country":"US",
    "sg:address":"2920 Outfitter Trl",
    "sg:city":"Laurel",
    "sg:classifiers":[
        {
            "category":"Organizations",
            "subcategory":"Religious Organization",
            "type":"Services"
        }
    ],
    "sg:phone":"+1 406 628 8528",
    "sg:postcode":"59044",
    "sg:province":"MT",
    "sg:tags":[
        "church"
    ],
    "wof:name":"Laurel Baptist Church Inc",
    "wof:placetype":"venue"
},
  "geometry": {"coordinates":[-108.71854,45.683996],"type":"Point"}
}