{
  "type": "Feature",
  "properties": {
    "addr:full":"608 Main St Thompson Falls MT 59873",
    "addr:housenumber":"608",
    "addr:postcode":"59873",
    "addr:street":"Main St",
    "iso:country":"US",
    "sg:address":"608 Main St",
    "sg:city":"Thompson Falls",
    "sg:classifiers":[
        {
            "category":"Professional",
            "subcategory":"Employment Agencies",
            "type":"Services"
        }
    ],
    "sg:phone":"+1 406 827 3472",
    "sg:postcode":"59873",
    "sg:province":"MT",
    "sg:tags":[
        "opportunity"
    ],
    "wof:name":"Job Service",
    "wof:placetype":"venue"
},
  "geometry": {"coordinates":[-115.349773,47.595097],"type":"Point"}
}