{
  "type": "Feature",
  "properties": {
    "iso:country":"US",
    "sg:address":"11865 US Hwy 93",
    "sg:city":"Lolo",
    "sg:classifiers":[
        {
            "category":"Bars & Pubs",
            "type":"Food & Drink"
        }
    ],
    "sg:phone":"+1 406 273 9995",
    "sg:postcode":"59847",
    "sg:province":"MT",
    "wof:name":"Lolo Tavern",
    "wof:placetype":"venue"
},
  "geometry": {"coordinates":[-114.082133,46.757763],"type":"Point"}
}