{
  "type": "Feature",
  "properties": {
    "iso:country":"US",
    "sg:address":"1628 Grand Ave",
    "sg:city":"Billings",
    "sg:classifiers":[
        {
            "category":"Retail",
            "subcategory":"Auto Repair",
            "type":"Services"
        }
    ],
    "sg:phone":"+1 406 248 6226",
    "sg:postcode":"59102",
    "sg:province":"MT",
    "sg:tags":[
        "automotive"
    ],
    "sg:website":"www.masterlube.com",
    "wof:name":"Master Lube",
    "wof:placetype":"venue"
},
  "geometry": {"coordinates":[-108.558373,45.783969],"type":"Point"}
}