{
  "type": "Feature",
  "properties": {
    "iso:country":"US",
    "sg:address":"8263 State Hwy 35",
    "sg:city":"Bigfork",
    "sg:classifiers":[
        {
            "category":"Food & Beverages",
            "subcategory":"Groceries & Convenience Stores",
            "type":"Retail Goods"
        }
    ],
    "sg:phone":"+1 406 837 1551",
    "sg:postcode":"59911",
    "sg:province":"MT",
    "sg:tags":[
        "business",
        "association"
    ],
    "wof:name":"Bigfork State Stop",
    "wof:placetype":"venue"
},
  "geometry": {"coordinates":[-114.080761,48.068015],"type":"Point"}
}