{
  "type": "Feature",
  "properties": {
    "iso:country":"US",
    "sg:address":"1659 N 1st St",
    "sg:city":"Hamilton",
    "sg:classifiers":[
        {
            "category":"Manufacturing",
            "subcategory":"Printing",
            "type":"Manufacturing & Wholesale Goods"
        }
    ],
    "sg:phone":"+1 406 375 1700",
    "sg:postcode":"59840",
    "sg:province":"MT",
    "sg:tags":[
        "printer"
    ],
    "wof:name":"Print Works",
    "wof:placetype":"venue"
},
  "geometry": {"coordinates":[-114.157118,46.263328],"type":"Point"}
}