{
  "type": "Feature",
  "properties": {
    "iso:country":"US",
    "sg:address":"328 W Center St",
    "sg:city":"Kalispell",
    "sg:phone":"+1 406 756 2326",
    "sg:postcode":"59901",
    "sg:province":"MT",
    "sg:website":"http://www.coffeetraders.com",
    "wof:name":"Montana Coffee Traders",
    "wof:placetype":"venue"
},
  "geometry": {"coordinates":[-114.318667,48.197933],"type":"Point"}
}