{
  "type": "Feature",
  "properties": {
    "addr:full":"206 20th Ave W Polson MT 59860",
    "addr:housenumber":"206",
    "addr:postcode":"59860",
    "addr:street":"20Th Ave W",
    "iso:country":"US",
    "sg:address":"206 20th Ave W",
    "sg:city":"Polson",
    "sg:classifiers":[
        {
            "category":"Freight",
            "type":"Transportation"
        }
    ],
    "sg:phone":"+1 406 883 5191",
    "sg:postcode":"59860",
    "sg:province":"MT",
    "sg:tags":[
        "operator",
        "local",
        "trucking"
    ],
    "wof:name":"Harvey Kenitzer Trucking",
    "wof:placetype":"venue"
},
  "geometry": {"coordinates":[-114.166129,47.676811],"type":"Point"}
}