{
  "type": "Feature",
  "properties": {
    "addr:full":"1210 11th St Havre MT 59501",
    "addr:housenumber":"1210",
    "addr:postcode":"59501",
    "addr:street":"11Th St",
    "iso:country":"US",
    "sg:address":"1210 11th St",
    "sg:city":"Havre",
    "sg:classifiers":[
        {
            "category":"Farming",
            "subcategory":"Farm",
            "type":"Manufacturing & Wholesale Goods"
        }
    ],
    "sg:phone":"+1 406 265 5474",
    "sg:postcode":"59501",
    "sg:province":"MT",
    "sg:tags":[
        "crop",
        "general"
    ],
    "wof:name":"G&M Farms Inc",
    "wof:placetype":"venue"
},
  "geometry": {"coordinates":[-109.66449799999999,48.541912],"type":"Point"}
}