{
  "type": "Feature",
  "properties": {
    "iso:country":"US",
    "sg:address":"213 Main St",
    "sg:city":"Jackson",
    "sg:classifiers":[
        {
            "category":"Government",
            "subcategory":"Fire Station",
            "type":"Public Place"
        }
    ],
    "sg:phone":"+1 406 689 3638",
    "sg:postcode":"59711",
    "sg:province":"MT",
    "sg:tags":[
        "protection"
    ],
    "wof:name":"Kirkpatrick Buzz",
    "wof:placetype":"venue"
},
  "geometry": {"coordinates":[-112.952955,46.129149],"type":"Point"}
}