{
  "type": "Feature",
  "properties": {
    "addr:full":"1102 9th Ave Laurel MT 59044",
    "addr:housenumber":"1102",
    "addr:postcode":"59044",
    "addr:street":"9Th Ave",
    "iso:country":"US",
    "sg:address":"1102 9th Ave",
    "sg:city":"Laurel",
    "sg:classifiers":[
        {
            "category":"Building & Trades",
            "subcategory":"Construction",
            "type":"Services"
        }
    ],
    "sg:phone":"+1 406 628 7513",
    "sg:postcode":"59044",
    "sg:province":"MT",
    "sg:tags":[
        "contractor"
    ],
    "wof:name":"Duane Wagner Drywall",
    "wof:placetype":"venue"
},
  "geometry": {"coordinates":[-108.78310399999999,45.681848],"type":"Point"}
}