{
  "type": "Feature",
  "properties": {
    "iso:country":"US",
    "sg:address":"1027 Spotted Jack Loop E",
    "sg:city":"Billings",
    "sg:classifiers":[
        {
            "category":"Building & Trades",
            "subcategory":"Landscaping Services",
            "type":"Services"
        }
    ],
    "sg:phone":"+1 406 698 9046",
    "sg:postcode":"59101",
    "sg:province":"MT",
    "sg:tags":[
        "designer",
        "landscape"
    ],
    "wof:name":"Spotted Jack Landscape & Dsgn",
    "wof:placetype":"venue"
},
  "geometry": {"coordinates":[-108.388955,45.818145],"type":"Point"}
}