{
  "type": "Feature",
  "properties": {
    "iso:country":"US",
    "sg:address":"3100 Paxson St",
    "sg:city":"Missoula",
    "sg:classifiers":[
        {
            "category":"Utilities",
            "subcategory":"Mobile Phone",
            "type":"Services"
        }
    ],
    "sg:phone":"+1 406 543 2355",
    "sg:postcode":"59801",
    "sg:province":"MT",
    "sg:tags":[
        "telephone",
        "cellular"
    ],
    "wof:name":"Cellular One",
    "wof:placetype":"venue"
},
  "geometry": {"coordinates":[-114.028998,46.841515],"type":"Point"}
}