{
  "type": "Feature",
  "properties": {
    "iso:country":"US",
    "sg:address":"4501 10th Ave S",
    "sg:city":"Great Falls",
    "sg:classifiers":[
        {
            "category":"Professional",
            "subcategory":"Business Services",
            "type":"Services"
        }
    ],
    "sg:phone":"+1 406 453 2451",
    "sg:postcode":"59405",
    "sg:province":"MT",
    "wof:name":"Tirerana Big Sky",
    "wof:placetype":"venue"
},
  "geometry": {"coordinates":[-111.23062,47.494063],"type":"Point"}
}