{
  "type": "Feature",
  "properties": {
    "addr:full":"830 Caledonia St Butte MT 59701",
    "addr:housenumber":"830",
    "addr:postcode":"mt 59701",
    "addr:street":"Caledonia St",
    "iso:country":"US",
    "sg:address":"830 Caledonia St",
    "sg:city":"Butte",
    "sg:classifiers":[
        {
            "category":"Recreation",
            "type":"Entertainment"
        }
    ],
    "sg:phone":"+1 406 782 0567",
    "sg:postcode":"59701",
    "sg:province":"MT",
    "wof:name":"Bob Folkedahl Big Hole River",
    "wof:placetype":"venue"
},
  "geometry": {"coordinates":[-112.548879,46.01606],"type":"Point"}
}