{
  "type": "Feature",
  "properties": {
    "iso:country":"US",
    "sg:address":"1217 Utah Ave",
    "sg:city":"Libby",
    "sg:classifiers":[
        {
            "category":"Retail",
            "subcategory":"Repair Shop",
            "type":"Services"
        }
    ],
    "sg:phone":"+1 406 293 6491",
    "sg:postcode":"59923",
    "sg:province":"MT",
    "sg:tags":[
        "welding"
    ],
    "wof:name":"Jungst Welding & Machine Shop",
    "wof:placetype":"venue"
},
  "geometry": {"coordinates":[-115.551046,48.383891],"type":"Point"}
}