{
  "type": "Feature",
  "properties": {
    "iso:country":"US",
    "sg:address":"440 10th Ave SE",
    "sg:city":"Sidney",
    "sg:classifiers":[
        {
            "category":"Building & Trades",
            "subcategory":"Plumbing",
            "type":"Services"
        }
    ],
    "sg:phone":"+1 406 433 2717",
    "sg:postcode":"59270",
    "sg:province":"MT",
    "sg:tags":[
        "product",
        "management",
        "energy",
        "system"
    ],
    "wof:name":"Bear Paw Energy Inc",
    "wof:placetype":"venue"
},
  "geometry": {"coordinates":[-104.145385,47.708681],"type":"Point"}
}