{
  "type": "Feature",
  "properties": {
    "addr:full":"135 Pleasant Valley Rd Marion MT 59925",
    "addr:housenumber":"135",
    "addr:postcode":"59925",
    "addr:street":"Pleasant Valley Rd",
    "iso:country":"US",
    "sg:address":"135 Pleasant Valley Rd",
    "sg:city":"Marion",
    "sg:classifiers":[
        {
            "category":"Manufacturing",
            "subcategory":"Lumber",
            "type":"Manufacturing & Wholesale Goods"
        }
    ],
    "sg:phone":"+1 406 854 9331",
    "sg:postcode":"59925",
    "sg:province":"MT",
    "sg:tags":[
        "logging"
    ],
    "wof:name":"Montana Stone Supply Inc",
    "wof:placetype":"venue"
},
  "geometry": {"coordinates":[-114.651437,48.101284],"type":"Point"}
}