{
  "type": "Feature",
  "properties": {
    "addr:full":"15350 Thayer Rd Lolo MT 59847",
    "addr:housenumber":"15350",
    "addr:postcode":"59847",
    "addr:street":"Thayer Rd",
    "iso:country":"US",
    "sg:address":"15350 Thayer Rd",
    "sg:city":"Lolo",
    "sg:classifiers":[
        {
            "category":"Building & Trades",
            "subcategory":"Construction",
            "type":"Services"
        }
    ],
    "sg:phone":"+1 406 273 0416",
    "sg:postcode":"59847",
    "sg:province":"MT",
    "sg:tags":[
        "residential"
    ],
    "wof:name":"Lidberg Construction",
    "wof:placetype":"venue"
},
  "geometry": {"coordinates":[-114.213132,46.750537],"type":"Point"}
}