{
  "type": "Feature",
  "properties": {
    "iso:country":"US",
    "sg:address":"301 S Park Ave",
    "sg:city":"Helena",
    "sg:classifiers":[
        {
            "category":"Professional",
            "subcategory":"Computer Services",
            "type":"Services"
        }
    ],
    "sg:phone":"+1 406 441 4200",
    "sg:postcode":"59601",
    "sg:province":"MT",
    "sg:tags":[
        "prepackaged",
        "software"
    ],
    "wof:name":"Fast Enterprises LLC",
    "wof:placetype":"venue"
},
  "geometry": {"coordinates":[-112.04284,46.584735],"type":"Point"}
}