{
  "type": "Feature",
  "properties": {
    "addr:full":"32 S Ewing St Helena MT 59601",
    "addr:housenumber":"32",
    "addr:postcode":"59601",
    "addr:street":"S Ewing",
    "iso:country":"US",
    "sg:address":"32 S Ewing St",
    "sg:city":"Helena",
    "sg:classifiers":[
        {
            "category":"Professional",
            "type":"Services"
        }
    ],
    "sg:phone":"+1 406 442 5399",
    "sg:postcode":"59601",
    "sg:province":"MT",
    "sg:tags":[
        "establishment"
    ],
    "wof:name":"KNK Aquatic Ecology",
    "wof:placetype":"venue"
},
  "geometry": {"coordinates":[-112.037569,46.584486],"type":"Point"}
}