{
  "type": "Feature",
  "properties": {
    "iso:country":"US",
    "sg:address":"20 W Evergreen Dr",
    "sg:city":"Kalispell",
    "sg:classifiers":[
        {
            "category":"Education",
            "subcategory":"School",
            "type":"Public Place"
        }
    ],
    "sg:phone":"+1 406 751 1131",
    "sg:postcode":"59901",
    "sg:province":"MT",
    "wof:name":"Evergreen Junior High School",
    "wof:placetype":"venue"
},
  "geometry": {"coordinates":[-114.27792599999999,48.225834],"type":"Point"}
}