{
  "type": "Feature",
  "properties": {
    "iso:country":"US",
    "sg:address":"412 W 5th Ave",
    "sg:city":"Big Timber",
    "sg:classifiers":[
        {
            "category":"Education",
            "subcategory":"Special Training",
            "type":"Public Place"
        }
    ],
    "sg:phone":"+1 406 932 6877",
    "sg:postcode":"59011",
    "sg:province":"MT",
    "sg:tags":[
        "aircraft",
        "school"
    ],
    "wof:name":"Angel Air",
    "wof:placetype":"venue"
},
  "geometry": {"coordinates":[-109.95551,45.829521],"type":"Point"}
}