{
  "type": "Feature",
  "properties": {
    "addr:full":"3125 5th Ave S Great Falls MT 59405",
    "addr:housenumber":"3125",
    "addr:postcode":"59405",
    "addr:street":"5Th Ave S Great",
    "iso:country":"US",
    "sg:address":"3125 5th Ave S",
    "sg:city":"Great Falls",
    "sg:classifiers":[
        {
            "category":"Organizations",
            "subcategory":"Religious Organization",
            "type":"Services"
        }
    ],
    "sg:phone":"+1 406 454 1309",
    "sg:postcode":"59405",
    "sg:province":"MT",
    "wof:name":"Faith Lutheran Church E L C A",
    "wof:placetype":"venue"
},
  "geometry": {"coordinates":[-111.25247899999999,47.499627],"type":"Point"}
}