{
  "type": "Feature",
  "properties": {
    "iso:country":"US",
    "sg:address":"3125 5th Ave S",
    "sg:city":"Great Falls",
    "sg:classifiers":[
        {
            "category":"Organizations",
            "subcategory":"Religious Organization",
            "type":"Services"
        }
    ],
    "sg:phone":"+1 406 454 1309",
    "sg:postcode":"59405",
    "sg:province":"MT",
    "wof:name":"Faith Lutheran Church E L C A",
    "wof:placetype":"venue"
},
  "geometry": {"coordinates":[-111.252479,47.499627],"type":"Point"}
}