{
  "type": "Feature",
  "properties": {
    "addr:full":"1302 24th St W Billings MT 59102",
    "addr:housenumber":"1302",
    "addr:postcode":"59102",
    "addr:street":"24Th St W",
    "iso:country":"US",
    "sg:address":"1302 24th St W",
    "sg:city":"Billings",
    "sg:classifiers":[
        {
            "category":"Building & Trades",
            "subcategory":"Electrical",
            "type":"Services"
        }
    ],
    "sg:phone":"+1 406 591 0695",
    "sg:postcode":"59102",
    "sg:province":"MT",
    "sg:tags":[
        "electrical",
        "contractor"
    ],
    "wof:name":"Ice Electric",
    "wof:placetype":"venue"
},
  "geometry": {"coordinates":[-108.576455,45.784105],"type":"Point"}
}