{
  "type": "Feature",
  "properties": {
    "iso:country":"US",
    "sg:address":"301 Durland Ave",
    "sg:city":"Laurel",
    "sg:classifiers":[
        {
            "category":"Social Services",
            "subcategory":"Child Care",
            "type":"Services"
        }
    ],
    "sg:phone":"+1 406 628 6004",
    "sg:postcode":"59044",
    "sg:province":"MT",
    "wof:name":"Heaven Sent Child Care",
    "wof:placetype":"venue"
},
  "geometry": {"coordinates":[-108.777973,45.664573],"type":"Point"}
}