{
  "type": "Feature",
  "properties": {
    "iso:country":"US",
    "sg:address":"743 1st Ave W",
    "sg:city":"Kalispell",
    "sg:classifiers":[
        {
            "category":"Building & Trades",
            "subcategory":"Construction",
            "type":"Services"
        }
    ],
    "sg:phone":"+1 406 257 8856",
    "sg:postcode":"59901",
    "sg:province":"MT",
    "sg:tags":[
        "house"
    ],
    "wof:name":"Luikens Construction",
    "wof:placetype":"venue"
},
  "geometry": {"coordinates":[-114.312669,48.191295],"type":"Point"}
}