{
  "type": "Feature",
  "properties": {
    "iso:country":"US",
    "sg:address":"100 N 27th St",
    "sg:city":"Billings",
    "sg:classifiers":[
        {
            "category":"Professional",
            "subcategory":"Business Services",
            "type":"Services"
        }
    ],
    "sg:phone":"+1 406 245 9424",
    "sg:postcode":"59101",
    "sg:province":"MT",
    "wof:name":"Spence Accounts Incorporated",
    "wof:placetype":"venue"
},
  "geometry": {"coordinates":[-108.505336,45.783584],"type":"Point"}
}