{
  "type": "Feature",
  "properties": {
    "iso:country":"US",
    "sg:address":"3316 2nd Ave N",
    "sg:city":"Billings",
    "sg:classifiers":[
        {
            "category":"Professional",
            "subcategory":"Employment Agencies",
            "type":"Services"
        }
    ],
    "sg:phone":"+1 406 252 8794",
    "sg:postcode":"59101",
    "sg:province":"MT",
    "sg:tags":[
        "help",
        "supply"
    ],
    "wof:name":"Professnal Nrsing Prsnnel Pool",
    "wof:placetype":"venue"
},
  "geometry": {"coordinates":[-108.513785,45.779437],"type":"Point"}
}