{
  "type": "Feature",
  "properties": {
    "iso:country":"US",
    "sg:address":"1485 Continental Dr",
    "sg:city":"Butte",
    "sg:classifiers":[
        {
            "category":"Professional",
            "subcategory":"Management & Consulting",
            "type":"Services"
        }
    ],
    "sg:phone":"+1 406 782 9423",
    "sg:postcode":"59701",
    "sg:province":"MT",
    "sg:tags":[
        "business"
    ],
    "wof:name":"Water & Environmental Tech",
    "wof:placetype":"venue"
},
  "geometry": {"coordinates":[-112.48825100000001,45.998127],"type":"Point"}
}