{
  "type": "Feature",
  "properties": {
    "addr:full":"2100 Fairway Dr Bozeman MT 59715",
    "addr:housenumber":"2100",
    "addr:postcode":"59715",
    "addr:street":"Fairway Dr",
    "iso:country":"US",
    "sg:address":"2100 Fairway Dr",
    "sg:city":"Bozeman",
    "sg:classifiers":[
        {
            "category":"Professional",
            "subcategory":"Management & Consulting",
            "type":"Services"
        }
    ],
    "sg:phone":"+1 406 582 0050",
    "sg:postcode":"59715",
    "sg:province":"MT",
    "sg:tags":[
        "business"
    ],
    "wof:name":"Beland R Dale AIA Aicp",
    "wof:placetype":"venue"
},
  "geometry": {"coordinates":[-111.03612800000001,45.654244],"type":"Point"}
}