{
  "type": "Feature",
  "properties": {
    "iso:country":"US",
    "sg:address":"1845 Bancroft St",
    "sg:city":"Missoula",
    "sg:classifiers":[
        {
            "category":"Health Services",
            "subcategory":"Doctor",
            "type":"Services"
        }
    ],
    "sg:phone":"+1 406 721 4007",
    "sg:postcode":"59801",
    "sg:province":"MT",
    "sg:tags":[
        "medical"
    ],
    "wof:name":"Ogilvie Steven L Podiatrist",
    "wof:placetype":"venue"
},
  "geometry": {"coordinates":[-114.007913,46.853735],"type":"Point"}
}