{
  "type": "Feature",
  "properties": {
    "iso:country":"US",
    "sg:address":"3117 5th Ave S",
    "sg:city":"Great Falls",
    "sg:classifiers":[
        {
            "category":"Building & Trades",
            "subcategory":"Cleaning & Sanitation",
            "type":"Services"
        }
    ],
    "sg:phone":"+1 406 268 6745",
    "sg:postcode":"59405",
    "sg:province":"MT",
    "sg:tags":[
        "maintenance"
    ],
    "wof:name":"Buildings & Grounds",
    "wof:placetype":"venue"
},
  "geometry": {"coordinates":[-111.252265,47.499626],"type":"Point"}
}