{
  "type": "Feature",
  "properties": {
    "iso:country":"US",
    "sg:address":"1894 Orville Way",
    "sg:city":"Bozeman",
    "sg:classifiers":[
        {
            "category":"Manufacturing",
            "subcategory":"Musical Instruments",
            "type":"Manufacturing & Wholesale Goods"
        }
    ],
    "sg:phone":"+1 406 587 4117",
    "sg:postcode":"59718",
    "sg:province":"MT",
    "sg:tags":[
        "guitar",
        "mfg",
        "accessory"
    ],
    "wof:name":"Gibson Guitar Corp",
    "wof:placetype":"venue"
},
  "geometry": {"coordinates":[-111.064031,45.706165],"type":"Point"}
}