{
  "type": "Feature",
  "properties": {
    "iso:country":"US",
    "sg:address":"202 State St",
    "sg:city":"Hamilton",
    "sg:classifiers":[
        {
            "category":"Personal",
            "subcategory":"Beauty Salon",
            "type":"Services"
        }
    ],
    "sg:phone":"+1 406 363 2731",
    "sg:postcode":"59840",
    "sg:province":"MT",
    "sg:tags":[
        "shop"
    ],
    "wof:name":"S K Kuts",
    "wof:placetype":"venue"
},
  "geometry": {"coordinates":[-114.157005,46.246066],"type":"Point"}
}