{
  "type": "Feature",
  "properties": {
    "iso:country":"US",
    "sg:address":"5284 US Hwy 2 S",
    "sg:city":"Libby",
    "sg:classifiers":[
        {
            "category":"Freight",
            "type":"Transportation"
        }
    ],
    "sg:phone":"+1 406 293 9607",
    "sg:postcode":"59923",
    "sg:province":"MT",
    "sg:tags":[
        "log",
        "hauling"
    ],
    "wof:name":"M & M Trucking",
    "wof:placetype":"venue"
},
  "geometry": {"coordinates":[-115.520614,48.323813],"type":"Point"}
}