{
  "type": "Feature",
  "properties": {
    "addr:full":"213 1st St W Polson MT 59860",
    "addr:housenumber":"213",
    "addr:postcode":"59860",
    "addr:street":"1St St W",
    "iso:country":"US",
    "sg:address":"213 1st St W",
    "sg:city":"Polson",
    "sg:classifiers":[
        {
            "category":"Banks & Credit Unions",
            "subcategory":"Investment Brokerage",
            "type":"Services"
        }
    ],
    "sg:phone":"+1 406 883 4099",
    "sg:postcode":"59860",
    "sg:province":"MT",
    "sg:tags":[
        "security"
    ],
    "wof:name":"Investment Center",
    "wof:placetype":"venue"
},
  "geometry": {"coordinates":[-114.164405,47.69427],"type":"Point"}
}