{
  "type": "Feature",
  "properties": {
    "iso:country":"US",
    "sg:address":"3214 Rosemont Way",
    "sg:city":"Billings",
    "sg:classifiers":[
        {
            "category":"Professional",
            "subcategory":"Management & Consulting",
            "type":"Services"
        }
    ],
    "sg:phone":"+1 406 252 1107",
    "sg:postcode":"59101",
    "sg:province":"MT",
    "sg:tags":[
        "business"
    ],
    "wof:name":"Newell Business Consulting",
    "wof:placetype":"venue"
},
  "geometry": {"coordinates":[-108.497,45.718649],"type":"Point"}
}