{
  "type": "Feature",
  "properties": {
    "iso:country":"US",
    "sg:address":"194 S Kootenai Creek Rd",
    "sg:city":"Stevensville",
    "sg:classifiers":[
        {
            "category":"Wholesale",
            "subcategory":"Home Furnishings",
            "type":"Manufacturing & Wholesale Goods"
        }
    ],
    "sg:phone":"+1 406 777 7188",
    "sg:postcode":"59870",
    "sg:province":"MT",
    "wof:name":"Acorn Floors Inc",
    "wof:placetype":"venue"
},
  "geometry": {"coordinates":[-114.12351700000001,46.51576],"type":"Point"}
}