{
  "type": "Feature",
  "properties": {
    "addr:full":"30 Central Ave S Harlowton MT 59036",
    "addr:housenumber":"30",
    "addr:postcode":"59036",
    "addr:street":"Central Ave S Harlowton",
    "iso:country":"US",
    "sg:address":"30 Central Ave S",
    "sg:city":"Harlowton",
    "sg:classifiers":[
        {
            "category":"Health Services",
            "subcategory":"Optometrist",
            "type":"Services"
        }
    ],
    "sg:phone":"+1 406 632 4234",
    "sg:postcode":"59036",
    "sg:province":"MT",
    "wof:name":"Eyecare Associates",
    "wof:placetype":"venue"
},
  "geometry": {"coordinates":[-109.831256,46.434729],"type":"Point"}
}