{
  "type": "Feature",
  "properties": {
    "addr:full":"1880 Brooks St Missoula MT 59801",
    "addr:housenumber":"1880",
    "addr:postcode":"59801",
    "addr:street":"Brooks St",
    "iso:country":"US",
    "sg:address":"1880 Brooks St",
    "sg:city":"Missoula",
    "sg:classifiers":[
        {
            "category":"Ice Cream",
            "type":"Food & Drink"
        }
    ],
    "sg:menulink":"http://www.allmenus.com/mt/missoula/243339-baskin-robbins/menu/",
    "sg:phone":"+1 406 542 2731",
    "sg:postcode":"59801",
    "sg:province":"MT",
    "sg:tags":[
        "american"
    ],
    "wof:name":"Baskin-Robbins",
    "wof:placetype":"venue"
},
  "geometry": {"coordinates":[-114.010628,46.853458],"type":"Point"}
}