{
  "type": "Feature",
  "properties": {
    "addr:full":"625 4th Ave Havre MT 59501",
    "addr:housenumber":"625",
    "addr:postcode":"59501",
    "addr:street":"4Th Ave",
    "iso:country":"US",
    "sg:address":"625 4th Ave",
    "sg:city":"Havre",
    "sg:classifiers":[
        {
            "category":"Organizations",
            "subcategory":"Religious Organization",
            "type":"Services"
        }
    ],
    "sg:phone":"+1 406 265 4862",
    "sg:postcode":"59501",
    "sg:province":"MT",
    "wof:name":"First Baptist Church",
    "wof:placetype":"venue"
},
  "geometry": {"coordinates":[-109.67775399999999,48.547701],"type":"Point"}
}