{
  "type": "Feature",
  "properties": {
    "iso:country":"US",
    "sg:address":"556 3rd Avenue E N",
    "sg:city":"Kalispell",
    "sg:classifiers":[
        {
            "category":"Building & Trades",
            "subcategory":"Construction",
            "type":"Services"
        }
    ],
    "sg:phone":"+1 406 752 8468",
    "sg:postcode":"59901",
    "sg:province":"MT",
    "sg:tags":[
        "house"
    ],
    "wof:name":"Kent Meyer Construction Inc",
    "wof:placetype":"venue"
},
  "geometry": {"coordinates":[-114.311801,48.205801],"type":"Point"}
}