{
  "type": "Feature",
  "properties": {
    "iso:country":"US",
    "sg:address":"6800 Mount Hwy 273",
    "sg:city":"Dillon",
    "sg:classifiers":[
        {
            "category":"Building & Trades",
            "subcategory":"Construction",
            "type":"Services"
        }
    ],
    "sg:phone":"+1 406 683 5788",
    "sg:postcode":"59711",
    "sg:province":"MT",
    "sg:tags":[
        "house"
    ],
    "wof:name":"All Season Remodeling",
    "wof:placetype":"venue"
},
  "geometry": {"coordinates":[-112.847801,46.222988],"type":"Point"}
}