{
  "type": "Feature",
  "properties": {
    "iso:country":"US",
    "sg:address":"301 Livingston Ave",
    "sg:city":"Missoula",
    "sg:classifiers":[
        {
            "category":"Professional",
            "type":"Services"
        }
    ],
    "sg:phone":"+1 406 543 4856",
    "sg:postcode":"59801",
    "sg:province":"MT",
    "sg:tags":[
        "establishment"
    ],
    "wof:name":"International Assoc",
    "wof:placetype":"venue"
},
  "geometry": {"coordinates":[-114.00261,46.847888],"type":"Point"}
}