{
  "type": "Feature",
  "properties": {
    "addr:full":"2425 Mary Ave Missoula MT 59801",
    "addr:housenumber":"2425",
    "addr:postcode":"59801",
    "addr:street":"Mary Ave",
    "iso:country":"US",
    "sg:address":"2425 Mary Ave",
    "sg:city":"Missoula",
    "sg:classifiers":[
        {
            "category":"Manufacturing",
            "subcategory":"Tools & Machinery",
            "type":"Manufacturing & Wholesale Goods"
        }
    ],
    "sg:phone":"+1 406 728 3950",
    "sg:postcode":"59801",
    "sg:province":"MT",
    "sg:tags":[
        "construction"
    ],
    "sg:website":"www.lifttech.com",
    "wof:name":"Lifting Technologies",
    "wof:placetype":"venue"
},
  "geometry": {"coordinates":[-114.03685299999999,46.844221],"type":"Point"}
}