{
  "type": "Feature",
  "properties": {
    "iso:country":"US",
    "sg:address":"106 E Main St",
    "sg:city":"White Slphr Spgs",
    "sg:classifiers":[
        {
            "category":"Food & Beverages",
            "subcategory":"Groceries & Convenience Stores",
            "type":"Retail Goods"
        }
    ],
    "sg:phone":"+1 406 547 3512",
    "sg:postcode":"59645",
    "sg:province":"MT",
    "sg:tags":[
        "grocer"
    ],
    "wof:name":"Mathis Food Farm",
    "wof:placetype":"venue"
},
  "geometry": {"coordinates":[-110.901914,46.548088],"type":"Point"}
}