{
  "type": "Feature",
  "properties": {
    "addr:full":"1100 11th Ave Havre MT 59501",
    "addr:housenumber":"1100",
    "addr:postcode":"59501",
    "addr:street":"11Th Ave",
    "iso:country":"US",
    "sg:address":"1100 11th Ave",
    "sg:city":"Havre",
    "sg:classifiers":[
        {
            "category":"Organizations",
            "subcategory":"Religious Organization",
            "type":"Services"
        }
    ],
    "sg:phone":"+1 406 265 7637",
    "sg:postcode":"59501",
    "sg:province":"MT",
    "wof:name":"Saint Pauls Lutheran Church",
    "wof:placetype":"venue"
},
  "geometry": {"coordinates":[-109.667181,48.541602],"type":"Point"}
}