{
  "type": "Feature",
  "properties": {
    "iso:country":"US",
    "sg:address":"305 W Mercury St",
    "sg:city":"Butte",
    "sg:classifiers":[
        {
            "category":"Building & Trades",
            "subcategory":"Construction",
            "type":"Services"
        }
    ],
    "sg:phone":"+1 406 723 8831",
    "sg:postcode":"59701",
    "sg:province":"MT",
    "sg:tags":[
        "home",
        "builder"
    ],
    "wof:name":"Montana Building Ind Assoc",
    "wof:placetype":"venue"
},
  "geometry": {"coordinates":[-112.54053399999999,46.011002],"type":"Point"}
}