{
  "type": "Feature",
  "properties": {
    "iso:country":"US",
    "sg:address":"2820 Lyndale Ln",
    "sg:city":"Billings",
    "sg:classifiers":[
        {
            "category":"Professional",
            "subcategory":"Business Services",
            "type":"Services"
        }
    ],
    "sg:phone":"+1 406 652 1989",
    "sg:postcode":"59102",
    "sg:province":"MT",
    "sg:tags":[
        "appraiser"
    ],
    "wof:name":"Wicks & Assoc LLC",
    "wof:placetype":"venue"
},
  "geometry": {"coordinates":[-108.58592,45.795144],"type":"Point"}
}