{
  "type": "Feature",
  "properties": {
    "iso:country":"US",
    "sg:address":"1140 Enterprise Dr",
    "sg:city":"Helena",
    "sg:classifiers":[
        {
            "category":"Home & Garden",
            "subcategory":"Carpets & Floor Coverings",
            "type":"Retail Goods"
        }
    ],
    "sg:phone":"+1 406 442 2334",
    "sg:postcode":"59601",
    "sg:province":"MT",
    "wof:name":"Remnant Room",
    "wof:placetype":"venue"
},
  "geometry": {"coordinates":[-112.022869,46.61364],"type":"Point"}
}