{
  "type": "Feature",
  "properties": {
    "addr:full":"718 5th Ave Havre MT 59501",
    "addr:housenumber":"718",
    "addr:postcode":"59501",
    "addr:street":"5Th Ave",
    "iso:country":"US",
    "sg:address":"718 5th Ave",
    "sg:city":"Havre",
    "sg:classifiers":[
        {
            "category":"Social Services",
            "subcategory":"Child Care",
            "type":"Services"
        }
    ],
    "sg:phone":"+1 406 265 8346",
    "sg:postcode":"59501",
    "sg:province":"MT",
    "sg:tags":[
        "day"
    ],
    "wof:name":"Toybox Daycare",
    "wof:placetype":"venue"
},
  "geometry": {"coordinates":[-109.67652,48.546624],"type":"Point"}
}