{
  "type": "Feature",
  "properties": {
    "addr:full":"880 Adobe Dr Billings MT 59105",
    "addr:housenumber":"880",
    "addr:postcode":"59105",
    "addr:street":"Adobe Dr",
    "iso:country":"US",
    "sg:address":"880 Adobe Dr",
    "sg:city":"Billings",
    "sg:classifiers":[
        {
            "category":"Building & Trades",
            "subcategory":"Plumbing",
            "type":"Services"
        }
    ],
    "sg:phone":"+1 406 256 3033",
    "sg:postcode":"59105",
    "sg:province":"MT",
    "sg:tags":[
        "contractor"
    ],
    "wof:name":"Quality Heating & AC",
    "wof:placetype":"venue"
},
  "geometry": {"coordinates":[-108.509845,45.831809],"type":"Point"}
}