{
  "type": "Feature",
  "properties": {
    "iso:country":"US",
    "sg:address":"329 3rd St",
    "sg:city":"Havre",
    "sg:classifiers":[
        {
            "category":"Health Services",
            "subcategory":"Doctor",
            "type":"Services"
        }
    ],
    "sg:phone":"+1 406 265 1790",
    "sg:postcode":"59501",
    "sg:province":"MT",
    "sg:tags":[
        "dentist"
    ],
    "wof:name":"Lee D Laeupple DDS",
    "wof:placetype":"venue"
},
  "geometry": {"coordinates":[-109.678225,48.551502],"type":"Point"}
}