{
  "type": "Feature",
  "properties": {
    "iso:country":"US",
    "sg:address":"71 Fisherman Ln",
    "sg:city":"Hamilton",
    "sg:classifiers":[
        {
            "category":"Home & Garden",
            "subcategory":"Building Materials",
            "type":"Retail Goods"
        },
        {
            "category":"Manufacturing",
            "subcategory":"Metals",
            "type":"Manufacturing & Wholesale Goods"
        }
    ],
    "sg:phone":"+1 406 363 5143",
    "sg:postcode":"59840",
    "sg:province":"MT",
    "sg:tags":[
        "hardware",
        "door",
        "mfg"
    ],
    "wof:name":"Big Sky Garage Doors & Rain",
    "wof:placetype":"venue"
},
  "geometry": {"coordinates":[-114.176091,46.132198],"type":"Point"}
}