{
  "type": "Feature",
  "properties": {
    "addr:full":"129 W Broadway St Butte MT 59701",
    "addr:housenumber":"129",
    "addr:postcode":"mt 59701",
    "addr:street":"W Broadway St",
    "iso:country":"US",
    "sg:address":"129 W Broadway St",
    "sg:city":"Butte",
    "sg:classifiers":[
        {
            "category":"Shopping",
            "subcategory":"Used Merchandise",
            "type":"Retail Goods"
        }
    ],
    "sg:phone":"+1 406 782 2231",
    "sg:postcode":"59701",
    "sg:province":"MT",
    "sg:tags":[
        "shop",
        "thrift"
    ],
    "wof:name":"Silverhouse Thrift Store",
    "wof:placetype":"venue"
},
  "geometry": {"coordinates":[-112.538364,46.013568],"type":"Point"}
}