{
  "type": "Feature",
  "properties": {
    "addr:full":"3896 Old Yellowstone Trl N Livingston MT 59047",
    "addr:housenumber":"3896",
    "addr:postcode":"59047",
    "addr:street":"Old Yellowstone Trl N",
    "iso:country":"US",
    "sg:address":"3896 Old Yellowstone Trl N",
    "sg:city":"Livingston",
    "sg:classifiers":[
        {
            "category":"Farming",
            "subcategory":"Livestock Farm",
            "type":"Manufacturing & Wholesale Goods"
        }
    ],
    "sg:phone":"+1 406 222 2734",
    "sg:postcode":"59047",
    "sg:province":"MT",
    "sg:tags":[
        "ranch"
    ],
    "wof:name":"Inverness Counsel Inc",
    "wof:placetype":"venue"
},
  "geometry": {"coordinates":[-110.691536,45.460515],"type":"Point"}
}