{
  "type": "Feature",
  "properties": {
    "iso:country":"US",
    "sg:address":"1528 S Higgins Ave",
    "sg:city":"Missoula",
    "sg:classifiers":[
        {
            "category":"Organizations",
            "subcategory":"Religious Organization",
            "type":"Services"
        }
    ],
    "sg:phone":"+1 406 549 1744",
    "sg:postcode":"59801",
    "sg:province":"MT",
    "wof:name":"Church of Christ Inc",
    "wof:placetype":"venue"
},
  "geometry": {"coordinates":[-113.997332,46.856547],"type":"Point"}
}