{
  "type": "Feature",
  "properties": {
    "iso:country":"US",
    "sg:address":"120 Greenwood Dr",
    "sg:city":"Helena",
    "sg:classifiers":[
        {
            "category":"Manufacturing",
            "subcategory":"Printing",
            "type":"Manufacturing & Wholesale Goods"
        }
    ],
    "sg:phone":"+1 406 495 1020",
    "sg:postcode":"59601",
    "sg:province":"MT",
    "sg:tags":[
        "publishing"
    ],
    "wof:name":"Cottonwood Publishing Inc",
    "wof:placetype":"venue"
},
  "geometry": {"coordinates":[-112.045843,46.610214],"type":"Point"}
}