{
  "type": "Feature",
  "properties": {
    "iso:country":"US",
    "sg:address":"400 2nd Ave S",
    "sg:city":"Wolf Point",
    "sg:classifiers":[
        {
            "category":"Government",
            "subcategory":"Court House",
            "type":"Public Place"
        }
    ],
    "sg:phone":"+1 406 653 6264",
    "sg:postcode":"59201",
    "sg:province":"MT",
    "sg:tags":[
        "county"
    ],
    "wof:name":"Roosevelt County Dist Judge",
    "wof:placetype":"venue"
},
  "geometry": {"coordinates":[-105.638823,48.088235],"type":"Point"}
}