{
  "type": "Feature",
  "properties": {
    "iso:country":"US",
    "sg:address":"204 7th Ave W",
    "sg:city":"Kalispell",
    "sg:classifiers":[
        {
            "category":"Organizations",
            "subcategory":"Religious Organization",
            "type":"Services"
        }
    ],
    "sg:phone":"+1 406 755 5205",
    "sg:postcode":"59901",
    "sg:province":"MT",
    "wof:name":"United Church Homes",
    "wof:placetype":"venue"
},
  "geometry": {"coordinates":[-114.32343299999999,48.195043],"type":"Point"}
}