{
  "type": "Feature",
  "properties": {
    "iso:country":"US",
    "sg:address":"2655 Nettie St",
    "sg:city":"Butte",
    "sg:classifiers":[
        {
            "category":"Manufacturing",
            "subcategory":"Food",
            "type":"Manufacturing & Wholesale Goods"
        }
    ],
    "sg:phone":"+1 406 782 8572",
    "sg:postcode":"59701",
    "sg:province":"MT",
    "sg:tags":[
        "rendering",
        "company"
    ],
    "wof:name":"Baker Commodities Inc",
    "wof:placetype":"venue"
},
  "geometry": {"coordinates":[-112.49862400000001,45.990418],"type":"Point"}
}