{
  "type": "Feature",
  "properties": {
    "addr:full":"1525 1st Ave N Billings MT 59101",
    "addr:housenumber":"1525",
    "addr:postcode":"59101",
    "addr:street":"1St Ave N",
    "iso:country":"US",
    "sg:address":"1525 1st Ave N",
    "sg:city":"Billings",
    "sg:classifiers":[
        {
            "category":"Autos & Motor Vehicles",
            "subcategory":"Automobile Sales",
            "type":"Retail Goods"
        }
    ],
    "sg:phone":"+1 406 252 7000",
    "sg:postcode":"59101",
    "sg:province":"MT",
    "sg:tags":[
        "car",
        "dealer"
    ],
    "wof:name":"Phillip Hurling Motors",
    "wof:placetype":"venue"
},
  "geometry": {"coordinates":[-108.49081700000001,45.789441],"type":"Point"}
}