{
  "type": "Feature",
  "properties": {
    "addr:full":"7105 Devonshire Ln Missoula MT 59804",
    "addr:housenumber":"7105",
    "addr:postcode":"59804",
    "addr:street":"Devonshire Ln",
    "iso:country":"US",
    "sg:address":"7105 Devonshire Ln",
    "sg:city":"Missoula",
    "sg:classifiers":[
        {
            "category":"Wholesale",
            "subcategory":"Non-durable Goods",
            "type":"Manufacturing & Wholesale Goods"
        }
    ],
    "sg:phone":"+1 406 251 3888",
    "sg:postcode":"59804",
    "sg:province":"MT",
    "wof:name":"Red Bow Boutique",
    "wof:placetype":"venue"
},
  "geometry": {"coordinates":[-114.09529499999999,46.81873],"type":"Point"}
}