{
  "type": "Feature",
  "properties": {
    "iso:country":"US",
    "sg:address":"197 Wyant Ln",
    "sg:city":"Hamilton",
    "sg:classifiers":[
        {
            "category":"Manufacturing",
            "subcategory":"Toys & Sporting Goods",
            "type":"Manufacturing & Wholesale Goods"
        }
    ],
    "sg:phone":"+1 406 363 6650",
    "sg:postcode":"59840",
    "sg:province":"MT",
    "sg:tags":[
        "athletic"
    ],
    "wof:name":"Tote Manufacturing",
    "wof:placetype":"venue"
},
  "geometry": {"coordinates":[-114.199184,46.243738],"type":"Point"}
}