{
  "type": "Feature",
  "properties": {
    "iso:country":"US",
    "sg:address":"2 4th Ave SE",
    "sg:city":"Conrad",
    "sg:classifiers":[
        {
            "category":"Insurance",
            "subcategory":"Insurance Agent",
            "type":"Services"
        }
    ],
    "sg:phone":"+1 406 278 3222",
    "sg:postcode":"59425",
    "sg:province":"MT",
    "wof:name":"State Farm Insurance",
    "wof:placetype":"venue"
},
  "geometry": {"coordinates":[-111.946907,48.168984],"type":"Point"}
}