{
  "type": "Feature",
  "properties": {
    "addr:full":"611 Ogden Ave Thompson Falls MT 59873",
    "addr:housenumber":"611",
    "addr:postcode":"59873",
    "addr:street":"Ogden Ave",
    "iso:country":"US",
    "sg:address":"611 Ogden Ave",
    "sg:city":"Thompson Falls",
    "sg:classifiers":[
        {
            "category":"Organizations",
            "subcategory":"Religious Organization",
            "type":"Services"
        }
    ],
    "sg:phone":"+1 406 827 3926",
    "sg:postcode":"59873",
    "sg:province":"MT",
    "sg:tags":[
        "church"
    ],
    "wof:name":"Our Saviour's Lutheran Church",
    "wof:placetype":"venue"
},
  "geometry": {"coordinates":[-115.348175,47.596591],"type":"Point"}
}