{
  "type": "Feature",
  "properties": {
    "iso:country":"US",
    "sg:address":"90 W Madison Ave",
    "sg:city":"Belgrade",
    "sg:classifiers":[
        {
            "category":"Banks & Credit Unions",
            "subcategory":"Bank",
            "type":"Services"
        }
    ],
    "sg:phone":"+1 406 388 5626",
    "sg:postcode":"59714",
    "sg:province":"MT",
    "sg:tags":[
        "loan",
        "broker"
    ],
    "wof:name":"Americas 1 Financial",
    "wof:placetype":"venue"
},
  "geometry": {"coordinates":[-111.180918,45.772818],"type":"Point"}
}