{
  "type": "Feature",
  "properties": {
    "iso:country":"US",
    "sg:address":"11735 Mallard Ct",
    "sg:city":"Missoula",
    "sg:classifiers":[
        {
            "category":"Building & Trades",
            "subcategory":"Construction",
            "type":"Services"
        }
    ],
    "sg:phone":"+1 406 543 1262",
    "sg:postcode":"59808",
    "sg:province":"MT",
    "sg:tags":[
        "floor",
        "laying",
        "contractor"
    ],
    "wof:name":"Brackens Flooring",
    "wof:placetype":"venue"
},
  "geometry": {"coordinates":[-114.159241,46.91554],"type":"Point"}
}