{
  "type": "Feature",
  "properties": {
    "iso:country":"US",
    "sg:address":"1106 W Park St",
    "sg:city":"Livingston",
    "sg:classifiers":[
        {
            "category":"Shopping",
            "subcategory":"Bicycles & Sporting Goods",
            "type":"Retail Goods"
        }
    ],
    "sg:phone":"+1 406 222 5414",
    "sg:postcode":"59047",
    "sg:province":"MT",
    "sg:tags":[
        "apparel",
        "sport"
    ],
    "wof:name":"Yellowstone Gateway Sports",
    "wof:placetype":"venue"
},
  "geometry": {"coordinates":[-110.571054,45.65428],"type":"Point"}
}