{
  "type": "Feature",
  "properties": {
    "iso:country":"US",
    "sg:address":"4004 North Ave W",
    "sg:city":"Missoula",
    "sg:classifiers":[
        {
            "category":"Retail",
            "subcategory":"Repair Shop",
            "type":"Services"
        }
    ],
    "sg:phone":"+1 406 543 8134",
    "sg:postcode":"59804",
    "sg:province":"MT",
    "sg:tags":[
        "electrical"
    ],
    "wof:name":"Montana Central Vac",
    "wof:placetype":"venue"
},
  "geometry": {"coordinates":[-114.080911,46.852431],"type":"Point"}
}