{
  "type": "Feature",
  "properties": {
    "iso:country":"US",
    "sg:address":"233 Roaring Lion Rd",
    "sg:city":"Hamilton",
    "sg:classifiers":[
        {
            "category":"Wholesale",
            "subcategory":"Machinery & Supplies",
            "type":"Manufacturing & Wholesale Goods"
        }
    ],
    "sg:phone":"+1 406 363 2202",
    "sg:postcode":"59840",
    "sg:province":"MT",
    "sg:tags":[
        "forestry",
        "log",
        "business"
    ],
    "wof:name":"Small Diamitor Log Inc",
    "wof:placetype":"venue"
},
  "geometry": {"coordinates":[-114.191779,46.193054],"type":"Point"}
}