{
  "type": "Feature",
  "properties": {
    "iso:country":"US",
    "sg:address":"1920 20th Ave S",
    "sg:city":"Great Falls",
    "sg:classifiers":[
        {
            "category":"Building & Trades",
            "subcategory":"Construction",
            "type":"Services"
        }
    ],
    "sg:phone":"+1 406 452 6610",
    "sg:postcode":"59405",
    "sg:province":"MT",
    "sg:tags":[
        "house"
    ],
    "wof:name":"Lucke Construction",
    "wof:placetype":"venue"
},
  "geometry": {"coordinates":[-111.273455,47.48362],"type":"Point"}
}