{
  "type": "Feature",
  "properties": {
    "iso:country":"US",
    "sg:address":"6 Yellowstone St",
    "sg:city":"Kalispell",
    "sg:classifiers":[
        {
            "category":"Professional",
            "type":"Services"
        }
    ],
    "sg:phone":"+1 406 755 5034",
    "sg:postcode":"59901",
    "sg:province":"MT",
    "wof:name":"Randy Christensen",
    "wof:placetype":"venue"
},
  "geometry": {"coordinates":[-114.33496,48.205515],"type":"Point"}
}