{
  "type": "Feature",
  "properties": {
    "iso:country":"US",
    "sg:address":"226 1st St S",
    "sg:city":"Shelby",
    "sg:classifiers":[
        {
            "category":"Government",
            "subcategory":"Office",
            "type":"Public Place"
        }
    ],
    "sg:phone":"+1 406 424 8370",
    "sg:postcode":"59474",
    "sg:province":"MT",
    "wof:name":"Toole County Assessment",
    "wof:placetype":"venue"
},
  "geometry": {"coordinates":[-111.858435,48.504957],"type":"Point"}
}