{
  "type": "Feature",
  "properties": {
    "iso:country":"US",
    "sg:address":"5325 Tri Hill Frontage Rd",
    "sg:city":"Great Falls",
    "sg:classifiers":[
        {
            "category":"Professional",
            "type":"Services"
        }
    ],
    "sg:phone":"+1 406 453 4060",
    "sg:postcode":"59404",
    "sg:province":"MT",
    "sg:tags":[
        "establishment"
    ],
    "wof:name":"MCI",
    "wof:placetype":"venue"
},
  "geometry": {"coordinates":[-111.38506700000001,47.462116],"type":"Point"}
}