{
  "type": "Feature",
  "properties": {
    "iso:country":"US",
    "sg:address":"811 E Wren Ln",
    "sg:city":"Glendive",
    "sg:classifiers":[
        {
            "category":"Retail",
            "subcategory":"Car Wash",
            "type":"Services"
        }
    ],
    "sg:phone":"+1 406 377 4333",
    "sg:postcode":"59330",
    "sg:province":"MT",
    "sg:tags":[
        "auto"
    ],
    "wof:name":"Creative Auto Trim",
    "wof:placetype":"venue"
},
  "geometry": {"coordinates":[-104.746592,47.114374],"type":"Point"}
}