{
  "type": "Feature",
  "properties": {
    "addr:full":"1 S Main St Conrad MT 59425",
    "addr:housenumber":"1",
    "addr:postcode":"59425",
    "addr:street":"S Main St",
    "iso:country":"US",
    "sg:address":"1 S Main St",
    "sg:city":"Conrad",
    "sg:classifiers":[
        {
            "category":"Utilities",
            "subcategory":"Refuse",
            "type":"Services"
        }
    ],
    "sg:phone":"+1 406 278 3095",
    "sg:postcode":"59425",
    "sg:province":"MT",
    "sg:tags":[
        "land",
        "fill"
    ],
    "wof:name":"Northern Mt Joint Ref Disposal",
    "wof:placetype":"venue"
},
  "geometry": {"coordinates":[-111.94383000000001,48.174071],"type":"Point"}
}