{
  "type": "Feature",
  "properties": {
    "iso:country":"US",
    "sg:address":"4420 Airport Rd",
    "sg:city":"Belgrade",
    "sg:classifiers":[
        {
            "category":"Retail",
            "subcategory":"Animal Services",
            "type":"Services"
        }
    ],
    "sg:phone":"+1 406 388 7547",
    "sg:postcode":"59714",
    "sg:province":"MT",
    "wof:name":"Corner Gait Ranch",
    "wof:placetype":"venue"
},
  "geometry": {"coordinates":[-111.082564,45.77655],"type":"Point"}
}