{
  "type": "Feature",
  "properties": {
    "iso:country":"US",
    "sg:address":"3954 Hwy 312",
    "sg:city":"Billings",
    "sg:classifiers":[
        {
            "category":"Retail",
            "subcategory":"Auto Rental",
            "type":"Services"
        }
    ],
    "sg:phone":"+1 406 373 0152",
    "sg:postcode":"59105",
    "sg:province":"MT",
    "sg:tags":[
        "renting",
        "truck",
        "leasing"
    ],
    "wof:name":"U-Haul Co",
    "wof:placetype":"venue"
},
  "geometry": {"coordinates":[-108.426222,45.87063],"type":"Point"}
}