{
  "type": "Feature",
  "properties": {
    "iso:country":"US",
    "sg:address":"2500 State Hwy 91 N",
    "sg:city":"Dillon",
    "sg:classifiers":[
        {
            "category":"Manufacturing",
            "subcategory":"Glass & Minerals",
            "type":"Manufacturing & Wholesale Goods"
        }
    ],
    "sg:phone":"+1 406 683 2101",
    "sg:postcode":"59725",
    "sg:province":"MT",
    "sg:tags":[
        "ready"
    ],
    "wof:name":"L S Ready-Mix Concrete Inc",
    "wof:placetype":"venue"
},
  "geometry": {"coordinates":[-112.632879,45.239953],"type":"Point"}
}