{
  "type": "Feature",
  "properties": {
    "addr:full":"600 Central Ave Great Falls MT 59401",
    "addr:housenumber":"600",
    "addr:postcode":"59401",
    "addr:street":"Central Ave",
    "iso:country":"US",
    "sg:address":"600 Central Ave",
    "sg:city":"Great Falls",
    "sg:classifiers":[
        {
            "category":"Professional",
            "subcategory":"Business Services",
            "type":"Services"
        }
    ],
    "sg:phone":"+1 406 727 4121",
    "sg:postcode":"59401",
    "sg:province":"MT",
    "wof:name":"Collection Bureau Service",
    "wof:placetype":"venue"
},
  "geometry": {"coordinates":[-111.295708,47.505357],"type":"Point"}
}