{
  "type": "Feature",
  "properties": {
    "iso:country":"US",
    "sg:address":"2123 2nd Ave N",
    "sg:city":"Billings",
    "sg:classifiers":[
        {
            "category":"Home & Garden",
            "subcategory":"Building Materials",
            "type":"Retail Goods"
        }
    ],
    "sg:phone":"+1 406 259 0160",
    "sg:postcode":"59101",
    "sg:province":"MT",
    "sg:tags":[
        "glass",
        "window",
        "plate"
    ],
    "wof:name":"ZNG Glass",
    "wof:placetype":"venue"
},
  "geometry": {"coordinates":[-108.499177,45.786664],"type":"Point"}
}