{
  "type": "Feature",
  "properties": {
    "addr:full":"81 23rd Rd NW Dutton MT 59433",
    "addr:housenumber":"81",
    "addr:postcode":"59433",
    "addr:street":"23Rd Rd Nw",
    "iso:country":"US",
    "sg:address":"81 23rd Rd NW",
    "sg:city":"Dutton",
    "sg:classifiers":[
        {
            "category":"Farming",
            "subcategory":"Farm",
            "type":"Manufacturing & Wholesale Goods"
        }
    ],
    "sg:phone":"+1 406 466 2801",
    "sg:postcode":"59433",
    "sg:province":"MT",
    "sg:tags":[
        "crop",
        "general"
    ],
    "wof:name":"Caskey Farms",
    "wof:placetype":"venue"
},
  "geometry": {"coordinates":[-111.98847600000001,47.941357],"type":"Point"}
}