{
  "type": "Feature",
  "properties": {
    "iso:country":"US",
    "sg:address":"1101 10th Ave N",
    "sg:city":"Great Falls",
    "sg:classifiers":[
        {
            "category":"Wholesale",
            "subcategory":"Groceries",
            "type":"Manufacturing & Wholesale Goods"
        }
    ],
    "sg:phone":"+1 406 453 1722",
    "sg:postcode":"59401",
    "sg:province":"MT",
    "sg:tags":[
        "coffee"
    ],
    "wof:name":"Boyd Coffee Company",
    "wof:placetype":"venue"
},
  "geometry": {"coordinates":[-111.286768,47.51622],"type":"Point"}
}