{
  "type": "Feature",
  "properties": {
    "addr:full":"103 Hickory St Missoula MT 59801",
    "addr:housenumber":"103",
    "addr:postcode":"59801",
    "addr:street":"Hickory St",
    "iso:country":"US",
    "sg:address":"103 Hickory St",
    "sg:city":"Missoula",
    "sg:classifiers":[
        {
            "category":"Professional",
            "subcategory":"Management & Consulting",
            "type":"Services"
        }
    ],
    "sg:phone":"+1 406 728 2720",
    "sg:postcode":"59801",
    "sg:province":"MT",
    "sg:tags":[
        "business"
    ],
    "wof:name":"Montana Conservation Corps",
    "wof:placetype":"venue"
},
  "geometry": {"coordinates":[-114.006615,46.870433],"type":"Point"}
}