{
  "type": "Feature",
  "properties": {
    "iso:country":"US",
    "sg:address":"2605 Minnesota Ave",
    "sg:city":"Billings",
    "sg:classifiers":[
        {
            "category":"Manufacturing",
            "subcategory":"Food",
            "type":"Manufacturing & Wholesale Goods"
        }
    ],
    "sg:phone":"+1 406 248 5715",
    "sg:postcode":"59101",
    "sg:province":"MT",
    "sg:tags":[
        "processor"
    ],
    "wof:name":"Potato Factory Inc",
    "wof:placetype":"venue"
},
  "geometry": {"coordinates":[-108.502821,45.781125],"type":"Point"}
}