{
  "type": "Feature",
  "properties": {
    "addr:full":"2140 N 9th Rd Worden MT 59088",
    "addr:housenumber":"2140",
    "addr:postcode":"59088",
    "addr:street":"N 9Th Rd",
    "iso:country":"US",
    "sg:address":"2140 N 9th Rd",
    "sg:city":"Worden",
    "sg:classifiers":[
        {
            "category":"Home & Garden",
            "subcategory":"Building Materials",
            "type":"Retail Goods"
        }
    ],
    "sg:phone":"+1 406 967 2022",
    "sg:postcode":"59088",
    "sg:province":"MT",
    "wof:name":"Sawmill",
    "wof:placetype":"venue"
},
  "geometry": {"coordinates":[-108.22757799999999,45.932727],"type":"Point"}
}