{
  "type": "Feature",
  "properties": {
    "addr:full":"1903 Central Ave Billings MT 59102",
    "addr:housenumber":"1903",
    "addr:postcode":"59102",
    "addr:street":"Central Ave",
    "iso:country":"US",
    "sg:address":"1903 Central Ave",
    "sg:city":"Billings",
    "sg:classifiers":[
        {
            "category":"Shopping",
            "type":"Retail Goods"
        }
    ],
    "sg:phone":"+1 406 655 9655",
    "sg:postcode":"59102",
    "sg:province":"MT",
    "sg:tags":[
        "orthopedic",
        "appliance"
    ],
    "wof:name":"Curt Uhler Prosthetics",
    "wof:placetype":"venue"
},
  "geometry": {"coordinates":[-108.563213,45.769839],"type":"Point"}
}