{
  "type": "Feature",
  "properties": {
    "addr:full":"1572 Beartooth Dr Laurel MT 59044",
    "addr:housenumber":"1572",
    "addr:postcode":"59044",
    "addr:street":"Beartooth Dr",
    "iso:country":"US",
    "sg:address":"1572 Beartooth Dr",
    "sg:city":"Laurel",
    "sg:classifiers":[
        {
            "category":"Retail",
            "subcategory":"Portrait Studio",
            "type":"Services"
        }
    ],
    "sg:phone":"+1 406 628 2111",
    "sg:postcode":"59044",
    "sg:province":"MT",
    "sg:tags":[
        "photographer"
    ],
    "wof:name":"Beartooth Photography",
    "wof:placetype":"venue"
},
  "geometry": {"coordinates":[-108.77894499999999,45.69462],"type":"Point"}
}