{
  "type": "Feature",
  "properties": {
    "iso:country":"US",
    "sg:address":"3100 Airport Rd",
    "sg:city":"Helena",
    "sg:classifiers":[
        {
            "category":"Government",
            "subcategory":"Office",
            "type":"Public Place"
        }
    ],
    "sg:phone":"+1 406 449 5756",
    "sg:postcode":"59601",
    "sg:province":"MT",
    "sg:tags":[
        "transportation"
    ],
    "wof:name":"Airport Traffic Control Tower",
    "wof:placetype":"venue"
},
  "geometry": {"coordinates":[-111.982632,46.602224],"type":"Point"}
}