{
  "type": "Feature",
  "properties": {
    "iso:country":"US",
    "sg:address":"201 Sugar Ave",
    "sg:city":"Billings",
    "sg:classifiers":[
        {
            "category":"Manufacturing",
            "subcategory":"Pet Food",
            "type":"Manufacturing & Wholesale Goods"
        }
    ],
    "sg:phone":"+1 406 248 3631",
    "sg:postcode":"59101",
    "sg:province":"MT",
    "sg:tags":[
        "feed"
    ],
    "sg:website":"www.nutralix.com",
    "wof:name":"Nutra-Lix Inc",
    "wof:placetype":"venue"
},
  "geometry": {"coordinates":[-108.494291,45.765786],"type":"Point"}
}