{
  "type": "Feature",
  "properties": {
    "iso:country":"US",
    "sg:address":"805 Van Sant Rd",
    "sg:city":"Kalispell",
    "sg:classifiers":[
        {
            "category":"Shopping",
            "subcategory":"Luggage & Leather Goods",
            "type":"Retail Goods"
        }
    ],
    "sg:phone":"+1 406 755 0359",
    "sg:postcode":"59901",
    "sg:province":"MT",
    "sg:tags":[
        "mfg"
    ],
    "wof:name":"Dragonfly Stitches",
    "wof:placetype":"venue"
},
  "geometry": {"coordinates":[-114.13755,48.25103],"type":"Point"}
}