{
  "type": "Feature",
  "properties": {
    "addr:full":"3105 Prospect Ave Helena MT 59601",
    "addr:housenumber":"3105",
    "addr:postcode":"59601",
    "addr:street":"Prospect Ave",
    "iso:country":"US",
    "sg:address":"3105 Prospect Ave",
    "sg:city":"Helena",
    "sg:classifiers":[
        {
            "category":"Building & Trades",
            "subcategory":"Construction",
            "type":"Services"
        }
    ],
    "sg:phone":"+1 406 442 9170",
    "sg:postcode":"59601",
    "sg:province":"MT",
    "sg:tags":[
        "general",
        "contractor"
    ],
    "wof:name":"Yak & Abe Construction",
    "wof:placetype":"venue"
},
  "geometry": {"coordinates":[-111.986639,46.591122],"type":"Point"}
}