{
  "type": "Feature",
  "properties": {
    "addr:full":"120 2nd Ave SE Sidney MT 59270",
    "addr:housenumber":"120",
    "addr:postcode":"59270",
    "addr:street":"2Nd Ave Se",
    "iso:country":"US",
    "sg:address":"120 2nd Ave SE",
    "sg:city":"Sidney",
    "sg:classifiers":[
        {
            "category":"Personal",
            "subcategory":"Beauty Salon",
            "type":"Services"
        }
    ],
    "sg:phone":"+1 406 433 4583",
    "sg:postcode":"59270",
    "sg:province":"MT",
    "wof:name":"Mark Anthony & Co",
    "wof:placetype":"venue"
},
  "geometry": {"coordinates":[-104.155855,47.714637],"type":"Point"}
}