{
  "type": "Feature",
  "properties": {
    "addr:full":"621 S 6th Ave Bozeman MT 59715",
    "addr:housenumber":"621",
    "addr:postcode":"59715",
    "addr:street":"S 6Th Ave",
    "iso:country":"US",
    "sg:address":"621 S 6th Ave",
    "sg:city":"Bozeman",
    "sg:phone":"+1 406 587 9125",
    "sg:postcode":"59715",
    "sg:province":"MT",
    "sg:tags":[
        "farm",
        "wheat"
    ],
    "wof:name":"Kenneth Nyquist",
    "wof:placetype":"venue"
},
  "geometry": {"coordinates":[-111.04544199999999,45.673118],"type":"Point"}
}