{
  "type": "Feature",
  "properties": {
    "iso:country":"US",
    "sg:address":"2309 Wilder Ave",
    "sg:city":"Helena",
    "sg:classifiers":[
        {
            "category":"Building & Trades",
            "subcategory":"Construction",
            "type":"Services"
        }
    ],
    "sg:phone":"+1 406 594 2008",
    "sg:postcode":"59601",
    "sg:province":"MT",
    "sg:tags":[
        "home",
        "contractor",
        "family",
        "new",
        "roofing"
    ],
    "wof:name":"Rocky Mountain Roofing & Cnstr",
    "wof:placetype":"venue"
},
  "geometry": {"coordinates":[-112.069783,46.608374],"type":"Point"}
}