{
  "type": "Feature",
  "properties": {
    "iso:country":"US",
    "sg:address":"151 Bunkhouse Rd",
    "sg:city":"Darby",
    "sg:classifiers":[
        {
            "category":"Building & Trades",
            "subcategory":"Construction",
            "type":"Services"
        }
    ],
    "sg:phone":"+1 406 821 2015",
    "sg:postcode":"59829",
    "sg:province":"MT",
    "sg:tags":[
        "home",
        "builder"
    ],
    "wof:name":"Bachman Enterprises",
    "wof:placetype":"venue"
},
  "geometry": {"coordinates":[-114.185956,46.033324],"type":"Point"}
}