{
  "type": "Feature",
  "properties": {
    "iso:country":"US",
    "sg:address":"355 Lorenz Spur Dr",
    "sg:city":"Hamilton",
    "sg:classifiers":[
        {
            "category":"Professional",
            "subcategory":"Computer Services",
            "type":"Services"
        }
    ],
    "sg:phone":"+1 406 961 4481",
    "sg:postcode":"59840",
    "sg:province":"MT",
    "sg:tags":[
        "design",
        "system"
    ],
    "wof:name":"Lorenz Spur",
    "wof:placetype":"venue"
},
  "geometry": {"coordinates":[-114.173891,46.336145],"type":"Point"}
}