{
  "type": "Feature",
  "properties": {
    "iso:country":"US",
    "sg:address":"1425 8th Ave N",
    "sg:city":"Great Falls",
    "sg:classifiers":[
        {
            "category":"Travel",
            "subcategory":"Hotels & Motels",
            "type":"Entertainment"
        }
    ],
    "sg:phone":"+1 406 453 5403",
    "sg:postcode":"59401",
    "sg:province":"MT",
    "sg:tags":[
        "operation"
    ],
    "wof:name":"Nickel Nats",
    "wof:placetype":"venue"
},
  "geometry": {"coordinates":[-111.281947,47.514069],"type":"Point"}
}