{
  "type": "Feature",
  "properties": {
    "addr:full":"901 N Last Chance Gulch St Helena MT 59601",
    "addr:housenumber":"901",
    "addr:postcode":"59601",
    "addr:street":"N Last Chance Gulch",
    "iso:country":"US",
    "sg:address":"901 N Last Chance Gulch St",
    "sg:city":"Helena",
    "sg:classifiers":[
        {
            "category":"Wholesale",
            "subcategory":"Home Furnishings",
            "type":"Manufacturing & Wholesale Goods"
        }
    ],
    "sg:phone":"+1 406 457 0428",
    "sg:postcode":"59601",
    "sg:province":"MT",
    "wof:name":"Budget Framer",
    "wof:placetype":"venue"
},
  "geometry": {"coordinates":[-112.03259300000001,46.597331],"type":"Point"}
}