{
  "type": "Feature",
  "properties": {
    "addr:full":"501 2nd Ave Laurel MT 59044",
    "addr:housenumber":"501",
    "addr:postcode":"59044",
    "addr:street":"2Nd Ave",
    "iso:country":"US",
    "sg:address":"501 2nd Ave",
    "sg:city":"Laurel",
    "sg:classifiers":[
        {
            "category":"Building & Trades",
            "subcategory":"Construction",
            "type":"Services"
        }
    ],
    "sg:phone":"+1 406 698 4731",
    "sg:postcode":"59044",
    "sg:province":"MT",
    "sg:tags":[
        "contractor"
    ],
    "wof:name":"Kueffler Roofing LLC",
    "wof:placetype":"venue"
},
  "geometry": {"coordinates":[-108.773066,45.674509],"type":"Point"}
}