{
  "type": "Feature",
  "properties": {
    "iso:country":"US",
    "sg:address":"6130 US Hwy 93",
    "sg:city":"Whitefish",
    "sg:classifiers":[
        {
            "category":"Home & Garden",
            "subcategory":"Building Materials",
            "type":"Retail Goods"
        }
    ],
    "sg:phone":"+1 406 862 2545",
    "sg:postcode":"59937",
    "sg:province":"MT",
    "sg:tags":[
        "lumber"
    ],
    "wof:name":"Western Ace Home Center Str 3",
    "wof:placetype":"venue"
},
  "geometry": {"coordinates":[-114.33579,48.383026],"type":"Point"}
}