{
  "type": "Feature",
  "properties": {
    "iso:country":"US",
    "sg:address":"208 State St",
    "sg:city":"Hamilton",
    "sg:classifiers":[
        {
            "category":"Banks & Credit Unions",
            "subcategory":"Investment Brokerage",
            "type":"Services"
        }
    ],
    "sg:phone":"+1 406 363 1271",
    "sg:postcode":"59840",
    "sg:province":"MT",
    "sg:tags":[
        "consultant",
        "planning",
        "financial"
    ],
    "wof:name":"Rocky Mountain Financial Advs",
    "wof:placetype":"venue"
},
  "geometry": {"coordinates":[-114.157068,46.24606],"type":"Point"}
}