{
  "type": "Feature",
  "properties": {
    "iso:country":"US",
    "sg:address":"2203 Grand Ave",
    "sg:city":"Billings",
    "sg:classifiers":[
        {
            "category":"Real Estate",
            "subcategory":"Real Estate Agent",
            "type":"Services"
        }
    ],
    "sg:phone":"+1 406 651 0005",
    "sg:postcode":"59102",
    "sg:province":"MT",
    "wof:name":"West Wing Real Estate Company",
    "wof:placetype":"venue"
},
  "geometry": {"coordinates":[-108.57633199999999,45.784205],"type":"Point"}
}