{
  "type": "Feature",
  "properties": {
    "iso:country":"US",
    "sg:address":"1645 Ave D",
    "sg:city":"Billings",
    "sg:classifiers":[
        {
            "category":"Health Services",
            "subcategory":"Health Practitioner",
            "type":"Services"
        }
    ],
    "sg:phone":"+1 406 252 6620",
    "sg:postcode":"59102",
    "sg:province":"MT",
    "wof:name":"Tranel Ned N",
    "wof:placetype":"venue"
},
  "geometry": {"coordinates":[-108.555198,45.787201],"type":"Point"}
}