{
  "type": "Feature",
  "properties": {
    "iso:country":"US",
    "sg:address":"4135 4th Ave S",
    "sg:city":"Great Falls",
    "sg:classifiers":[
        {
            "category":"Manufacturing",
            "subcategory":"Printing",
            "type":"Manufacturing & Wholesale Goods"
        }
    ],
    "sg:phone":"+1 406 771 1178",
    "sg:postcode":"59405",
    "sg:province":"MT",
    "sg:tags":[
        "offset"
    ],
    "wof:name":"Quality Quick Print",
    "wof:placetype":"venue"
},
  "geometry": {"coordinates":[-111.234242,47.500634],"type":"Point"}
}