{
  "type": "Feature",
  "properties": {
    "iso:country":"US",
    "sg:address":"1342 Blue Slide Rd",
    "sg:city":"Thompson Falls",
    "sg:classifiers":[
        {
            "category":"Government",
            "subcategory":"Office",
            "type":"Public Place"
        },
        {
            "category":"Education",
            "subcategory":"School",
            "type":"Public Place"
        }
    ],
    "sg:phone":"+1 406 827 4344",
    "sg:postcode":"59873",
    "sg:province":"MT",
    "sg:website":"www.blueslide.com",
    "wof:name":"Spring Creek Lodge LLC",
    "wof:placetype":"venue"
},
  "geometry": {"coordinates":[-115.466313,47.763372],"type":"Point"}
}