{
  "type": "Feature",
  "properties": {
    "addr:full":"1875 Anderson Ln Dillon MT 59725",
    "addr:housenumber":"1875",
    "addr:postcode":"59725",
    "addr:street":"Anderson Ln",
    "iso:country":"US",
    "sg:address":"1875 Anderson Ln",
    "sg:city":"Dillon",
    "sg:classifiers":[
        {
            "category":"Building & Trades",
            "subcategory":"Construction",
            "type":"Services"
        }
    ],
    "sg:phone":"+1 406 683 4620",
    "sg:postcode":"59725",
    "sg:province":"MT",
    "sg:tags":[
        "contractor"
    ],
    "wof:name":"Anderson Fencing LLC",
    "wof:placetype":"venue"
},
  "geometry": {"coordinates":[-112.626559,45.30562],"type":"Point"}
}