{
  "type": "Feature",
  "properties": {
    "addr:full":"2800 Gregory Dr S Billings MT 59102",
    "addr:housenumber":"2800",
    "addr:postcode":"59102",
    "addr:street":"Gregory Dr S",
    "iso:country":"US",
    "sg:address":"2800 Gregory Dr S",
    "sg:city":"Billings",
    "sg:classifiers":[
        {
            "category":"Professional",
            "type":"Services"
        }
    ],
    "sg:phone":"+1 406 656 6820",
    "sg:postcode":"59102",
    "sg:province":"MT",
    "sg:tags":[
        "engineering"
    ],
    "wof:name":"Lee Techni-Coal",
    "wof:placetype":"venue"
},
  "geometry": {"coordinates":[-108.58304800000001,45.799205],"type":"Point"}
}