{
  "type": "Feature",
  "properties": {
    "addr:full":"2617 16th Ave S Great Falls MT 59405",
    "addr:housenumber":"2617",
    "addr:postcode":"59405",
    "addr:street":"16Th Ave S Great",
    "iso:country":"US",
    "sg:address":"2617 16th Ave S",
    "sg:city":"Great Falls",
    "sg:classifiers":[
        {
            "category":"Health Services",
            "subcategory":"Doctor",
            "type":"Services"
        }
    ],
    "sg:phone":"+1 406 452 8180",
    "sg:postcode":"59405",
    "sg:province":"MT",
    "wof:name":"Brett Bruggeman DDS",
    "wof:placetype":"venue"
},
  "geometry": {"coordinates":[-111.262013,47.488219],"type":"Point"}
}