{
  "type": "Feature",
  "properties": {
    "addr:full":"1011 River Dr Livingston MT 59047",
    "addr:housenumber":"1011",
    "addr:postcode":"59047",
    "addr:street":"River Dr",
    "iso:country":"US",
    "sg:address":"1011 River Dr",
    "sg:city":"Livingston",
    "sg:classifiers":[
        {
            "category":"Professional",
            "type":"Services"
        }
    ],
    "sg:phone":"+1 406 222 1586",
    "sg:postcode":"59047",
    "sg:province":"MT",
    "wof:name":"Focuscripts Inc",
    "wof:placetype":"venue"
},
  "geometry": {"coordinates":[-110.564727,45.649069],"type":"Point"}
}