{
  "type": "Feature",
  "properties": {
    "iso:country":"US",
    "sg:address":"876 N Shoshone Loop",
    "sg:city":"Hamilton",
    "sg:classifiers":[
        {
            "category":"Recreation",
            "type":"Entertainment"
        }
    ],
    "sg:phone":"+1 406 363 4200",
    "sg:postcode":"59840",
    "sg:province":"MT",
    "sg:tags":[
        "stable"
    ],
    "wof:name":"Bitterroot Arena",
    "wof:placetype":"venue"
},
  "geometry": {"coordinates":[-114.104721,46.197078],"type":"Point"}
}