{
  "type": "Feature",
  "properties": {
    "iso:country":"US",
    "sg:address":"745 Oilfield Ave",
    "sg:city":"Shelby",
    "sg:classifiers":[
        {
            "category":"Food & Beverages",
            "subcategory":"Groceries & Convenience Stores",
            "type":"Retail Goods"
        }
    ],
    "sg:phone":"+1 406 434 5472",
    "sg:postcode":"59474",
    "sg:province":"MT",
    "wof:name":"Blazers Fresh Foods IGA Inc",
    "wof:placetype":"venue"
},
  "geometry": {"coordinates":[-111.85571,48.512085],"type":"Point"}
}