{
  "type": "Feature",
  "properties": {
    "addr:full":"221 N 29th St Billings MT 59101",
    "addr:housenumber":"221",
    "addr:postcode":"59101",
    "addr:street":"N 29Th St",
    "iso:country":"US",
    "sg:address":"221 N 29th St",
    "sg:city":"Billings",
    "sg:classifiers":[
        {
            "category":"Shopping",
            "subcategory":"Used Merchandise",
            "type":"Retail Goods"
        }
    ],
    "sg:phone":"+1 406 259 5011",
    "sg:postcode":"59101",
    "sg:province":"MT",
    "sg:tags":[
        "antique",
        "store"
    ],
    "wof:name":"Silver Hill",
    "wof:placetype":"venue"
},
  "geometry": {"coordinates":[-108.508464,45.783088],"type":"Point"}
}