{
  "type": "Feature",
  "properties": {
    "iso:country":"US",
    "sg:address":"3655 Stucky Rd",
    "sg:city":"Bozeman",
    "sg:classifiers":[
        {
            "category":"Building & Trades",
            "subcategory":"Construction",
            "type":"Services"
        }
    ],
    "sg:phone":"+1 406 586 6626",
    "sg:postcode":"59718",
    "sg:province":"MT",
    "sg:tags":[
        "residential",
        "commercial",
        "gen",
        "contractor"
    ],
    "wof:name":"Bill Slingsby Construction",
    "wof:placetype":"venue"
},
  "geometry": {"coordinates":[-111.113227,45.656613],"type":"Point"}
}