{
  "type": "Feature",
  "properties": {
    "iso:country":"US",
    "sg:address":"1610 Poly Dr",
    "sg:city":"Billings",
    "sg:classifiers":[
        {
            "category":"Banks & Credit Unions",
            "subcategory":"Bank",
            "type":"Services"
        }
    ],
    "sg:phone":"+1 406 259 5261",
    "sg:postcode":"59102",
    "sg:province":"MT",
    "wof:name":"Rocky Mountain Bank",
    "wof:placetype":"venue"
},
  "geometry": {"coordinates":[-108.558179,45.794892],"type":"Point"}
}