{
  "type": "Feature",
  "properties": {
    "iso:country":"US",
    "sg:address":"114 N 29th St",
    "sg:city":"Billings",
    "sg:classifiers":[
        {
            "category":"Shopping",
            "subcategory":"Used Merchandise",
            "type":"Retail Goods"
        }
    ],
    "sg:phone":"+1 406 294 8578",
    "sg:postcode":"59101",
    "sg:province":"MT",
    "sg:tags":[
        "antique"
    ],
    "wof:name":"Meadowlark Antiques",
    "wof:placetype":"venue"
},
  "geometry": {"coordinates":[-108.506322,45.780677],"type":"Point"}
}