{
  "type": "Feature",
  "properties": {
    "addr:full":"10 Central Ave Whitefish MT 59937",
    "addr:housenumber":"10",
    "addr:postcode":"59937",
    "addr:street":"Central Ave",
    "iso:country":"US",
    "sg:address":"10 Central Ave",
    "sg:city":"Whitefish",
    "sg:classifiers":[
        {
            "category":"Restaurant",
            "type":"Food & Drink"
        }
    ],
    "sg:phone":"+1 406 862 5600",
    "sg:postcode":"59937",
    "sg:province":"MT",
    "sg:tags":[
        "eating"
    ],
    "wof:name":"Serranos Mexican Restaurant",
    "wof:placetype":"venue"
},
  "geometry": {"coordinates":[-114.33683499999999,48.412412],"type":"Point"}
}