{
  "type": "Feature",
  "properties": {
    "iso:country":"US",
    "sg:address":"2 Driftwood Dr",
    "sg:city":"Livingston",
    "sg:classifiers":[
        {
            "category":"Retail",
            "subcategory":"Repair Shop",
            "type":"Services"
        }
    ],
    "sg:phone":"+1 406 222 5890",
    "sg:postcode":"59047",
    "sg:province":"MT",
    "sg:tags":[
        "taxidermist"
    ],
    "wof:name":"Sasquatch Taxidermy",
    "wof:placetype":"venue"
},
  "geometry": {"coordinates":[-110.535899,45.685545],"type":"Point"}
}