{
  "type": "Feature",
  "properties": {
    "iso:country":"US",
    "sg:address":"108 Sourdough Ridge Rd",
    "sg:city":"Bozeman",
    "sg:classifiers":[
        {
            "category":"Professional",
            "subcategory":"Management & Consulting",
            "type":"Services"
        }
    ],
    "sg:phone":"+1 406 582 9638",
    "sg:postcode":"59715",
    "sg:province":"MT",
    "wof:name":"Clint Sly Inc",
    "wof:placetype":"venue"
},
  "geometry": {"coordinates":[-111.023328,45.648245],"type":"Point"}
}