{
  "type": "Feature",
  "properties": {
    "addr:full":"1124 Wilson Rd Power MT 59468",
    "addr:housenumber":"1124",
    "addr:postcode":"59468",
    "addr:street":"Wilson Rd",
    "iso:country":"US",
    "sg:address":"1124 Wilson Rd",
    "sg:city":"Power",
    "sg:classifiers":[
        {
            "category":"Building & Trades",
            "subcategory":"Plumbing",
            "type":"Services"
        }
    ],
    "sg:phone":"+1 406 463 2513",
    "sg:postcode":"59468",
    "sg:province":"MT",
    "sg:tags":[
        "mechanic"
    ],
    "wof:name":"James E Neumann",
    "wof:placetype":"venue"
},
  "geometry": {"coordinates":[-111.474699,47.639939],"type":"Point"}
}