{
  "type": "Feature",
  "properties": {
    "iso:country":"US",
    "sg:address":"2330 1st St",
    "sg:city":"Havre",
    "sg:classifiers":[
        {
            "category":"Freight",
            "type":"Transportation"
        }
    ],
    "sg:phone":"+1 406 265 8263",
    "sg:postcode":"59501",
    "sg:province":"MT",
    "sg:tags":[
        "local",
        "without",
        "storage",
        "trucking"
    ],
    "wof:name":"Bobs Pickup & Delivery",
    "wof:placetype":"venue"
},
  "geometry": {"coordinates":[-109.651994,48.551549],"type":"Point"}
}