{
  "type": "Feature",
  "properties": {
    "iso:country":"US",
    "sg:address":"781 Lower Sweet Grass Rd",
    "sg:city":"Big Timber",
    "sg:classifiers":[
        {
            "category":"Farming",
            "subcategory":"Livestock Farm",
            "type":"Manufacturing & Wholesale Goods"
        }
    ],
    "sg:phone":"+1 406 932 6503",
    "sg:postcode":"59011",
    "sg:province":"MT",
    "sg:tags":[
        "beef",
        "feedlot",
        "cattle"
    ],
    "wof:name":"Thomas Agnew",
    "wof:placetype":"venue"
},
  "geometry": {"coordinates":[-109.75268800000001,45.862839],"type":"Point"}
}