{
  "type": "Feature",
  "properties": {
    "iso:country":"US",
    "sg:address":"21 S Manchester Rd",
    "sg:city":"Great Falls",
    "sg:classifiers":[
        {
            "category":"Retail",
            "subcategory":"Auto Repair",
            "type":"Services"
        }
    ],
    "sg:phone":"+1 406 771 1130",
    "sg:postcode":"59404",
    "sg:province":"MT",
    "sg:tags":[
        "body"
    ],
    "wof:name":"Tc Collision Center",
    "wof:placetype":"venue"
},
  "geometry": {"coordinates":[-111.461921,47.543546],"type":"Point"}
}