{
  "type": "Feature",
  "properties": {
    "iso:country":"US",
    "sg:address":"111 S 24th St W",
    "sg:city":"Billings",
    "sg:classifiers":[
        {
            "category":"Personal",
            "subcategory":"Tattoo Parlor",
            "type":"Services"
        }
    ],
    "sg:phone":"+1 406 655 0011",
    "sg:postcode":"59102",
    "sg:province":"MT",
    "sg:tags":[
        "tattooing"
    ],
    "wof:name":"Eternal Ink",
    "wof:placetype":"venue"
},
  "geometry": {"coordinates":[-108.576075,45.76481],"type":"Point"}
}