{
  "type": "Feature",
  "properties": {
    "iso:country":"US",
    "sg:address":"2108 Broadwater Ave",
    "sg:city":"Billings",
    "sg:classifiers":[
        {
            "category":"Banks & Credit Unions",
            "subcategory":"Investment Brokerage",
            "type":"Services"
        }
    ],
    "sg:phone":"+1 406 325 9738",
    "sg:postcode":"59102",
    "sg:province":"MT",
    "sg:tags":[
        "stock",
        "bond"
    ],
    "wof:name":"American Capital",
    "wof:placetype":"venue"
},
  "geometry": {"coordinates":[-108.565721,45.776856],"type":"Point"}
}