{
  "type": "Feature",
  "properties": {
    "iso:country":"US",
    "sg:address":"56 E Mercury St",
    "sg:city":"Butte",
    "sg:classifiers":[
        {
            "category":"Building & Trades",
            "subcategory":"Construction",
            "type":"Services"
        }
    ],
    "sg:phone":"+1 406 782 9354",
    "sg:postcode":"59701",
    "sg:province":"MT",
    "sg:tags":[
        "project"
    ],
    "wof:name":"Blue Range Engineering",
    "wof:placetype":"venue"
},
  "geometry": {"coordinates":[-112.534153,46.01127],"type":"Point"}
}