{
  "type": "Feature",
  "properties": {
    "addr:full":"617 S Main St Conrad MT 59425",
    "addr:housenumber":"617",
    "addr:postcode":"59425",
    "addr:street":"S Main St",
    "iso:country":"US",
    "sg:address":"617 S Main St",
    "sg:city":"Conrad",
    "sg:classifiers":[
        {
            "category":"Organizations",
            "subcategory":"Community Association",
            "type":"Services"
        }
    ],
    "sg:phone":"+1 406 278 3631",
    "sg:postcode":"59425",
    "sg:province":"MT",
    "sg:tags":[
        "fraternal"
    ],
    "wof:name":"Loyal Order Of Moose",
    "wof:placetype":"venue"
},
  "geometry": {"coordinates":[-111.94844399999999,48.1662],"type":"Point"}
}