{
  "type": "Feature",
  "properties": {
    "iso:country":"US",
    "sg:address":"1325 N 7th Ave",
    "sg:city":"Bozeman",
    "sg:classifiers":[
        {
            "category":"Travel",
            "subcategory":"Hotels & Motels",
            "type":"Entertainment"
        }
    ],
    "sg:phone":"+1 406 587 5261",
    "sg:postcode":"59715",
    "sg:province":"MT",
    "sg:tags":[
        "lounge",
        "poker",
        "coin",
        "ma",
        "keno"
    ],
    "wof:name":"Best Western",
    "wof:placetype":"venue"
},
  "geometry": {"coordinates":[-111.046408,45.693078],"type":"Point"}
}