{
  "type": "Feature",
  "properties": {
    "iso:country":"US",
    "sg:address":"1520 Ashley Lake Rd",
    "sg:city":"Kalispell",
    "sg:classifiers":[
        {
            "category":"Wholesale",
            "subcategory":"Auto Parts",
            "type":"Manufacturing & Wholesale Goods"
        }
    ],
    "sg:phone":"+1 406 752 4635",
    "sg:postcode":"59901",
    "sg:province":"MT",
    "sg:tags":[
        "supply"
    ],
    "wof:name":"Knutson Excavating",
    "wof:placetype":"venue"
},
  "geometry": {"coordinates":[-114.497108,48.182678],"type":"Point"}
}