{
  "type": "Feature",
  "properties": {
    "iso:country":"US",
    "sg:address":"1407 Lincoln St",
    "sg:city":"Miles City",
    "sg:classifiers":[
        {
            "category":"Professional",
            "type":"Services"
        }
    ],
    "sg:phone":"+1 406 234 2803",
    "sg:postcode":"59301",
    "sg:province":"MT",
    "sg:tags":[
        "establishment"
    ],
    "wof:name":"M Braunbeck",
    "wof:placetype":"venue"
},
  "geometry": {"coordinates":[-105.842309,46.418177],"type":"Point"}
}