{
  "type": "Feature",
  "properties": {
    "iso:country":"US",
    "sg:address":"612 Lavender St",
    "sg:city":"Billings",
    "sg:classifiers":[
        {
            "category":"Building & Trades",
            "subcategory":"Construction",
            "type":"Services"
        }
    ],
    "sg:phone":"+1 406 656 0051",
    "sg:postcode":"59106",
    "sg:province":"MT",
    "sg:tags":[
        "house"
    ],
    "wof:name":"Kat Construction LLC",
    "wof:placetype":"venue"
},
  "geometry": {"coordinates":[-108.645933,45.776584],"type":"Point"}
}