{
  "type": "Feature",
  "properties": {
    "iso:country":"US",
    "sg:address":"2010 South Ave W",
    "sg:city":"Missoula",
    "sg:classifiers":[
        {
            "category":"Restaurant",
            "type":"Food & Drink"
        }
    ],
    "sg:phone":"+1 406 721 2011",
    "sg:postcode":"59801",
    "sg:province":"MT",
    "sg:tags":[
        "eating"
    ],
    "wof:name":"Howards Pizza Villa Inc",
    "wof:placetype":"venue"
},
  "geometry": {"coordinates":[-114.029984,46.848881],"type":"Point"}
}