{
  "type": "Feature",
  "properties": {
    "iso:country":"US",
    "sg:address":"5035 Hamm Rd",
    "sg:city":"Belgrade",
    "sg:classifiers":[
        {
            "category":"Building & Trades",
            "subcategory":"Construction",
            "type":"Services"
        }
    ],
    "sg:phone":"+1 406 585 9464",
    "sg:postcode":"59714",
    "sg:province":"MT",
    "sg:tags":[
        "contractor"
    ],
    "wof:name":"Meridian Roofing Services Inc",
    "wof:placetype":"venue"
},
  "geometry": {"coordinates":[-111.071242,45.795697],"type":"Point"}
}