{
  "type": "Feature",
  "properties": {
    "iso:country":"US",
    "sg:address":"414 3rd St S",
    "sg:city":"Sunburst",
    "sg:classifiers":[
        {
            "category":"Education",
            "subcategory":"School",
            "type":"Public Place"
        }
    ],
    "sg:phone":"+1 406 937 7366",
    "sg:postcode":"59482",
    "sg:province":"MT",
    "wof:name":"North Toole County Supt Office",
    "wof:placetype":"venue"
},
  "geometry": {"coordinates":[-111.915353,48.880751],"type":"Point"}
}