{
  "type": "Feature",
  "properties": {
    "iso:country":"US",
    "sg:address":"3119 Cooney Dr",
    "sg:city":"Helena",
    "sg:classifiers":[
        {
            "category":"Retail",
            "subcategory":"Auto Repair",
            "type":"Services"
        }
    ],
    "sg:phone":"+1 406 442 3001",
    "sg:postcode":"59602",
    "sg:province":"MT",
    "sg:tags":[
        "automotive"
    ],
    "wof:name":"Ace Carburetor & Electric Svc",
    "wof:placetype":"venue"
},
  "geometry": {"coordinates":[-112.037061,46.621703],"type":"Point"}
}