{
  "type": "Feature",
  "properties": {
    "iso:country":"US",
    "sg:address":"117 South Ave W",
    "sg:city":"Missoula",
    "sg:classifiers":[
        {
            "category":"Restaurant",
            "type":"Food & Drink"
        }
    ],
    "sg:phone":"+1 406 721 5041",
    "sg:postcode":"59801",
    "sg:province":"MT",
    "sg:tags":[
        "greek"
    ],
    "wof:name":"Acropolis Gyros & Greek Spc",
    "wof:placetype":"venue"
},
  "geometry": {"coordinates":[-113.998952,46.848744],"type":"Point"}
}