{
  "type": "Feature",
  "properties": {
    "iso:country":"US",
    "sg:address":"138 N 30th St",
    "sg:city":"Billings",
    "sg:classifiers":[
        {
            "category":"Professional",
            "subcategory":"Art Services",
            "type":"Services"
        }
    ],
    "sg:phone":"+1 406 252 1422",
    "sg:postcode":"59101",
    "sg:province":"MT",
    "sg:tags":[
        "photography",
        "commercial"
    ],
    "wof:name":"Photographic Solutions",
    "wof:placetype":"venue"
},
  "geometry": {"coordinates":[-108.50881,45.781402],"type":"Point"}
}