{
  "type": "Feature",
  "properties": {
    "iso:country":"US",
    "sg:address":"419 N 7th St",
    "sg:city":"Miles City",
    "sg:classifiers":[
        {
            "category":"Museum",
            "type":"Entertainment"
        }
    ],
    "sg:phone":"+1 406 232 0769",
    "sg:postcode":"59301",
    "sg:province":"MT",
    "sg:tags":[
        "gallery",
        "merchandise"
    ],
    "wof:name":"Wool House Gallery",
    "wof:placetype":"venue"
},
  "geometry": {"coordinates":[-105.85255100000001,46.411227],"type":"Point"}
}