{
  "type": "Feature",
  "properties": {
    "iso:country":"US",
    "sg:address":"9 1st Ave",
    "sg:city":"Laurel",
    "sg:classifiers":[
        {
            "category":"Utilities",
            "subcategory":"Mobile Phone",
            "type":"Services"
        }
    ],
    "sg:phone":"+1 406 628 8868",
    "sg:postcode":"59044",
    "sg:province":"MT",
    "sg:tags":[
        "telephone",
        "cellular"
    ],
    "wof:name":"Cowboy Connections Cellular",
    "wof:placetype":"venue"
},
  "geometry": {"coordinates":[-108.905563,45.390691],"type":"Point"}
}