{
  "type": "Feature",
  "properties": {
    "iso:country":"US",
    "sg:address":"1701 Harrison Ave",
    "sg:city":"Butte",
    "sg:classifiers":[
        {
            "category":"Autos & Motor Vehicles",
            "subcategory":"Automobile Sales",
            "type":"Retail Goods"
        }
    ],
    "sg:phone":"+1 406 782 9102",
    "sg:postcode":"59701",
    "sg:province":"MT",
    "sg:tags":[
        "body",
        "used"
    ],
    "wof:name":"Harrison Avenue Motor Co",
    "wof:placetype":"venue"
},
  "geometry": {"coordinates":[-112.515432,45.997992],"type":"Point"}
}