{
  "type": "Feature",
  "properties": {
    "addr:full":"6730 Tawney Brown Ln Bozeman MT 59718",
    "addr:housenumber":"6730",
    "addr:postcode":"59718",
    "addr:street":"Tawney Brown Ln",
    "iso:country":"US",
    "sg:address":"6730 Tawney Brown Ln",
    "sg:city":"Bozeman",
    "sg:classifiers":[
        {
            "category":"Home & Garden",
            "subcategory":"Building Materials",
            "type":"Retail Goods"
        }
    ],
    "sg:phone":"+1 406 522 9644",
    "sg:postcode":"59718",
    "sg:province":"MT",
    "sg:tags":[
        "specializing",
        "work",
        "cabinet",
        "r",
        "custom",
        "furniture"
    ],
    "wof:name":"New Creation Cabinetry",
    "wof:placetype":"venue"
},
  "geometry": {"coordinates":[-111.154161,45.670263],"type":"Point"}
}