{
  "type": "Feature",
  "properties": {
    "iso:country":"US",
    "sg:address":"209 W Missoula Ave",
    "sg:city":"Darby",
    "sg:classifiers":[
        {
            "category":"Manufacturing",
            "subcategory":"Lumber",
            "type":"Manufacturing & Wholesale Goods"
        }
    ],
    "sg:phone":"+1 406 821 3158",
    "sg:postcode":"59829",
    "sg:province":"MT",
    "sg:tags":[
        "company",
        "logging"
    ],
    "wof:name":"Mc Kinney Trucking",
    "wof:placetype":"venue"
},
  "geometry": {"coordinates":[-114.18212,46.022486],"type":"Point"}
}