{
  "type": "Feature",
  "properties": {
    "addr:full":"1113 Yale Ave Billings MT 59102",
    "addr:housenumber":"1113",
    "addr:postcode":"59102",
    "addr:street":"Yale Ave",
    "iso:country":"US",
    "sg:address":"1113 Yale Ave",
    "sg:city":"Billings",
    "sg:classifiers":[
        {
            "category":"Building & Trades",
            "subcategory":"Construction",
            "type":"Services"
        }
    ],
    "sg:phone":"+1 406 245 3021",
    "sg:postcode":"59102",
    "sg:province":"MT",
    "sg:tags":[
        "general",
        "contractor"
    ],
    "wof:name":"W P Construction",
    "wof:placetype":"venue"
},
  "geometry": {"coordinates":[-108.545839,45.797994],"type":"Point"}
}