{
  "type": "Feature",
  "properties": {
    "addr:full":"740 Topaz Ave Billings MT 59105",
    "addr:housenumber":"740",
    "addr:postcode":"59105",
    "addr:street":"Topaz Ave",
    "iso:country":"US",
    "sg:address":"740 Topaz Ave",
    "sg:city":"Billings",
    "sg:classifiers":[
        {
            "category":"Insurance",
            "subcategory":"Insurance Agent",
            "type":"Services"
        }
    ],
    "sg:phone":"+1 406 248 3593",
    "sg:postcode":"59105",
    "sg:province":"MT",
    "wof:name":"Ron Dague Insurance",
    "wof:placetype":"venue"
},
  "geometry": {"coordinates":[-108.48682599999999,45.811055],"type":"Point"}
}