{
  "type": "Feature",
  "properties": {
    "iso:country":"US",
    "sg:address":"1921 Eastridge Dr",
    "sg:city":"Billings",
    "sg:classifiers":[
        {
            "category":"Real Estate",
            "subcategory":"Developer",
            "type":"Services"
        }
    ],
    "sg:phone":"+1 406 651 0010",
    "sg:postcode":"59102",
    "sg:province":"MT",
    "wof:name":"Double Arrow Investments Inc",
    "wof:placetype":"venue"
},
  "geometry": {"coordinates":[-108.577327,45.788761],"type":"Point"}
}