{
  "type": "Feature",
  "properties": {
    "iso:country":"US",
    "sg:address":"15 E Woolman St",
    "sg:city":"Butte",
    "sg:classifiers":[
        {
            "category":"Professional",
            "subcategory":"Computer Services",
            "type":"Services"
        }
    ],
    "sg:phone":"+1 406 494 7234",
    "sg:postcode":"59701",
    "sg:province":"MT",
    "sg:tags":[
        "related"
    ],
    "wof:name":"Wrap Pack",
    "wof:placetype":"venue"
},
  "geometry": {"coordinates":[-112.53619500000001,46.017772],"type":"Point"}
}