{
  "type": "Feature",
  "properties": {
    "addr:full":"711 E 13th St Whitefish MT 59937",
    "addr:housenumber":"711",
    "addr:postcode":"59937",
    "addr:street":"E 13Th St",
    "iso:country":"US",
    "sg:address":"711 E 13th St",
    "sg:city":"Whitefish",
    "sg:classifiers":[
        {
            "category":"Wholesale",
            "subcategory":"Durable Goods & Equipment",
            "type":"Manufacturing & Wholesale Goods"
        }
    ],
    "sg:phone":"+1 406 862 5576",
    "sg:postcode":"59937",
    "sg:province":"MT",
    "sg:tags":[
        "laser"
    ],
    "wof:name":"Laser Solutions",
    "wof:placetype":"venue"
},
  "geometry": {"coordinates":[-114.33266999999999,48.399871],"type":"Point"}
}