{
  "type": "Feature",
  "properties": {
    "iso:country":"US",
    "sg:address":"9225 King Ave W",
    "sg:city":"Billings",
    "sg:classifiers":[
        {
            "category":"Building & Trades",
            "subcategory":"Landscaping Services",
            "type":"Services"
        }
    ],
    "sg:phone":"+1 406 652 6758",
    "sg:postcode":"59106",
    "sg:province":"MT",
    "wof:name":"Lefevre Bobcat Svc & Ldscpg",
    "wof:placetype":"venue"
},
  "geometry": {"coordinates":[-108.75117400000001,45.755206],"type":"Point"}
}