{
  "type": "Feature",
  "properties": {
    "iso:country":"US",
    "sg:address":"1900 N Last Chance Gulch St",
    "sg:city":"Helena",
    "sg:classifiers":[
        {
            "category":"Retail",
            "subcategory":"Portrait Studio",
            "type":"Services"
        }
    ],
    "sg:phone":"+1 406 443 1966",
    "sg:postcode":"59601",
    "sg:province":"MT",
    "sg:tags":[
        "photography",
        "commercial"
    ],
    "wof:name":"Helena Photography",
    "wof:placetype":"venue"
},
  "geometry": {"coordinates":[-112.02592,46.604316],"type":"Point"}
}