{
  "type": "Feature",
  "properties": {
    "iso:country":"US",
    "sg:address":"1123 Euclid Ave",
    "sg:city":"Helena",
    "sg:classifiers":[
        {
            "category":"Personal",
            "subcategory":"Beauty Salon",
            "type":"Services"
        }
    ],
    "sg:phone":"+1 406 449 3016",
    "sg:postcode":"59601",
    "sg:province":"MT",
    "sg:tags":[
        "shop"
    ],
    "wof:name":"Shears To You",
    "wof:placetype":"venue"
},
  "geometry": {"coordinates":[-112.05185299999999,46.601363],"type":"Point"}
}