{
  "type": "Feature",
  "properties": {
    "addr:full":"16 N 7th St Miles City MT 59301",
    "addr:housenumber":"16",
    "addr:postcode":"59301",
    "addr:street":"N 7Th St",
    "iso:country":"US",
    "sg:address":"16 N 7th St",
    "sg:city":"Miles City",
    "sg:classifiers":[
        {
            "category":"Food & Beverages",
            "subcategory":"Groceries & Convenience Stores",
            "type":"Retail Goods"
        }
    ],
    "sg:phone":"+1 406 232 6661",
    "sg:postcode":"59301",
    "sg:province":"MT",
    "sg:tags":[
        "station",
        "gasoline"
    ],
    "wof:name":"Short Stop",
    "wof:placetype":"venue"
},
  "geometry": {"coordinates":[-105.84975300000001,46.407381],"type":"Point"}
}