{
  "type": "Feature",
  "properties": {
    "iso:country":"US",
    "sg:address":"4804 Danford Dr",
    "sg:city":"Billings",
    "sg:classifiers":[
        {
            "category":"Wholesale",
            "subcategory":"Farm Supplies",
            "type":"Manufacturing & Wholesale Goods"
        }
    ],
    "sg:phone":"+1 406 656 2804",
    "sg:postcode":"59106",
    "sg:province":"MT",
    "sg:tags":[
        "chemical",
        "agricultural"
    ],
    "wof:name":"Simplot Grower Solutions",
    "wof:placetype":"venue"
},
  "geometry": {"coordinates":[-108.637996,45.717836],"type":"Point"}
}