{
  "type": "Feature",
  "properties": {
    "iso:country":"US",
    "sg:address":"602 W Hemlock St",
    "sg:city":"Bozeman",
    "sg:classifiers":[
        {
            "category":"Retail",
            "subcategory":"Repair Shop",
            "type":"Services"
        }
    ],
    "sg:phone":"+1 406 587 1420",
    "sg:postcode":"59715",
    "sg:province":"MT",
    "sg:tags":[
        "e"
    ],
    "wof:name":"C B Gallatin & Audio",
    "wof:placetype":"venue"
},
  "geometry": {"coordinates":[-111.04472199999999,45.690429],"type":"Point"}
}