{
  "type": "Feature",
  "properties": {
    "iso:country":"US",
    "sg:address":"4700 Gooch Hill Rd",
    "sg:city":"Bozeman",
    "sg:classifiers":[
        {
            "category":"Wholesale",
            "subcategory":"Meat",
            "type":"Manufacturing & Wholesale Goods"
        }
    ],
    "sg:phone":"+1 406 587 8972",
    "sg:postcode":"59718",
    "sg:province":"MT",
    "sg:tags":[
        "poultry",
        "plant",
        "mfg",
        "processing",
        "prepared",
        "packing"
    ],
    "wof:name":"Happels Meat Processing",
    "wof:placetype":"venue"
},
  "geometry": {"coordinates":[-111.124815,45.678464],"type":"Point"}
}