{
  "type": "Feature",
  "properties": {
    "iso:country":"US",
    "sg:address":"1104 20th St S",
    "sg:city":"Great Falls",
    "sg:classifiers":[
        {
            "category":"Banks & Credit Unions",
            "subcategory":"Bank",
            "type":"Services"
        }
    ],
    "sg:phone":"+1 406 727 6662",
    "sg:postcode":"59405",
    "sg:province":"MT",
    "sg:tags":[
        "depository",
        "banking"
    ],
    "wof:name":"Bonded Escrow Services",
    "wof:placetype":"venue"
},
  "geometry": {"coordinates":[-111.273133,47.492028],"type":"Point"}
}