{
  "type": "Feature",
  "properties": {
    "addr:full":"100 Bushbuck Rd Townsend MT 59644",
    "addr:housenumber":"100",
    "addr:postcode":"59644",
    "addr:street":"Bushbuck Rd",
    "iso:country":"US",
    "sg:address":"100 Bushbuck Rd",
    "sg:city":"Townsend",
    "sg:classifiers":[
        {
            "category":"Professional",
            "subcategory":"Computer Services",
            "type":"Services"
        }
    ],
    "sg:phone":"+1 406 266 4624",
    "sg:postcode":"59644",
    "sg:province":"MT",
    "sg:tags":[
        "programming",
        "custom"
    ],
    "wof:name":"Geartech",
    "wof:placetype":"venue"
},
  "geometry": {"coordinates":[-111.61222600000001,46.41277],"type":"Point"}
}