{
  "type": "Feature",
  "properties": {
    "addr:full":"7663 Lodgepole Rd Bozeman MT 59718",
    "addr:housenumber":"7663",
    "addr:postcode":"59718",
    "addr:street":"Lodgepole Rd",
    "iso:country":"US",
    "sg:address":"7663 Lodgepole Rd",
    "sg:city":"Bozeman",
    "sg:classifiers":[
        {
            "category":"Wholesale",
            "subcategory":"Medical Equipment & Supplies",
            "type":"Manufacturing & Wholesale Goods"
        }
    ],
    "sg:phone":"+1 406 582 1391",
    "sg:postcode":"59718",
    "sg:province":"MT",
    "sg:tags":[
        "home",
        "product",
        "health",
        "care"
    ],
    "wof:name":"First Choice Medical Spc",
    "wof:placetype":"venue"
},
  "geometry": {"coordinates":[-111.19279899999999,45.675513],"type":"Point"}
}