{
  "type": "Feature",
  "properties": {
    "addr:full":"3767 Eastside Hwy Stevensville MT 59870",
    "addr:housenumber":"3767",
    "addr:postcode":"59870",
    "addr:street":"Eastside Hwy",
    "iso:country":"US",
    "sg:address":"3767 Eastside Hwy",
    "sg:city":"Stevensville",
    "sg:classifiers":[
        {
            "category":"Shopping",
            "subcategory":"Crafts & Fabrics",
            "type":"Retail Goods"
        }
    ],
    "sg:phone":"+1 406 777 3727",
    "sg:postcode":"59870",
    "sg:province":"MT",
    "sg:tags":[
        "shop"
    ],
    "wof:name":"About Fabric",
    "wof:placetype":"venue"
},
  "geometry": {"coordinates":[-114.09325800000001,46.496107],"type":"Point"}
}