{
  "type": "Feature",
  "properties": {
    "iso:country":"US",
    "sg:address":"415 N Last Chance Gulch St",
    "sg:city":"Helena",
    "sg:classifiers":[
        {
            "category":"Real Estate",
            "subcategory":"Real Estate Agent",
            "type":"Services"
        }
    ],
    "sg:phone":"+1 406 443 6110",
    "sg:postcode":"59601",
    "sg:province":"MT",
    "sg:tags":[
        "management"
    ],
    "wof:name":"Melenium Property Management",
    "wof:placetype":"venue"
},
  "geometry": {"coordinates":[-112.037008,46.59148],"type":"Point"}
}