{
  "type": "Feature",
  "properties": {
    "iso:country":"US",
    "sg:address":"3231 Granger Ave E",
    "sg:city":"Billings",
    "sg:classifiers":[
        {
            "category":"Education",
            "subcategory":"School",
            "type":"Public Place"
        }
    ],
    "sg:phone":"+1 406 655 3115",
    "sg:postcode":"59102",
    "sg:province":"MT",
    "sg:website":"www.billings.k12.mt.us/bigsky",
    "wof:name":"Big Sky Elementary School",
    "wof:placetype":"venue"
},
  "geometry": {"coordinates":[-108.597613,45.758868],"type":"Point"}
}