{
  "type": "Feature",
  "properties": {
    "iso:country":"US",
    "sg:address":"2988 Wylie Dr",
    "sg:city":"East Helena",
    "sg:classifiers":[
        {
            "category":"Building & Trades",
            "subcategory":"Cleaning & Sanitation",
            "type":"Services"
        }
    ],
    "sg:phone":"+1 406 227 7043",
    "sg:postcode":"59602",
    "sg:province":"MT",
    "sg:tags":[
        "maintenance"
    ],
    "wof:name":"Trueax Janitorial",
    "wof:placetype":"venue"
},
  "geometry": {"coordinates":[-111.935928,46.615282],"type":"Point"}
}