{
  "type": "Feature",
  "properties": {
    "addr:full":"2421 8th Ave S Great Falls MT 59405",
    "addr:housenumber":"2421",
    "addr:postcode":"59405",
    "addr:street":"8Th Ave S Great",
    "iso:country":"US",
    "sg:address":"2421 8th Ave S",
    "sg:city":"Great Falls",
    "sg:classifiers":[
        {
            "category":"Professional",
            "subcategory":"Business Services",
            "type":"Services"
        }
    ],
    "sg:phone":"+1 406 453 6245",
    "sg:postcode":"59405",
    "sg:province":"MT",
    "wof:name":"Carol J Brannon",
    "wof:placetype":"venue"
},
  "geometry": {"coordinates":[-111.265978,47.49641],"type":"Point"}
}