{
  "type": "Feature",
  "properties": {
    "iso:country":"US",
    "sg:address":"416 Electric Ave",
    "sg:city":"Bigfork",
    "sg:classifiers":[
        {
            "category":"Real Estate",
            "subcategory":"Real Estate Agent",
            "type":"Services"
        }
    ],
    "sg:phone":"+1 406 837 6100",
    "sg:postcode":"59911",
    "sg:province":"MT",
    "wof:name":"Paulson Real Estate",
    "wof:placetype":"venue"
},
  "geometry": {"coordinates":[-114.073379,48.061148],"type":"Point"}
}