{
  "type": "Feature",
  "properties": {
    "iso:country":"US",
    "sg:address":"1119 Stock Farm Rd",
    "sg:city":"Hamilton",
    "sg:classifiers":[
        {
            "category":"Recreation",
            "type":"Entertainment"
        }
    ],
    "sg:phone":"+1 406 375 0491",
    "sg:postcode":"59840",
    "sg:province":"MT",
    "sg:tags":[
        "course",
        "golf"
    ],
    "sg:website":"www.stockfarm.com",
    "wof:name":"Stock Farm Golf Club",
    "wof:placetype":"venue"
},
  "geometry": {"coordinates":[-114.064619,46.249319],"type":"Point"}
}