{
  "type": "Feature",
  "properties": {
    "addr:full":"7987 State Hwy 35 Bigfork MT 59911",
    "addr:housenumber":"7987",
    "addr:postcode":"59911",
    "addr:street":"State Hwy 35",
    "iso:country":"US",
    "sg:address":"7987 State Hwy 35",
    "sg:city":"Bigfork",
    "sg:classifiers":[
        {
            "category":"Real Estate",
            "subcategory":"Architect",
            "type":"Services"
        }
    ],
    "sg:phone":"+1 406 837 7362",
    "sg:postcode":"59911",
    "sg:province":"MT",
    "sg:tags":[
        "architectural"
    ],
    "wof:name":"Peters & Associates Architects",
    "wof:placetype":"venue"
},
  "geometry": {"coordinates":[-114.07884900000001,48.079183],"type":"Point"}
}