{
  "type": "Feature",
  "properties": {
    "iso:country":"US",
    "sg:address":"217 Main St",
    "sg:city":"Wolf Point",
    "sg:classifiers":[
        {
            "category":"Restaurant",
            "type":"Food & Drink"
        }
    ],
    "sg:phone":"+1 406 653 9910",
    "sg:postcode":"59201",
    "sg:province":"MT",
    "sg:tags":[
        "eating"
    ],
    "wof:name":"Wolf Point Cafe",
    "wof:placetype":"venue"
},
  "geometry": {"coordinates":[-105.63897900000001,48.090523],"type":"Point"}
}