{
  "type": "Feature",
  "properties": {
    "iso:country":"US",
    "sg:address":"425 Grouse Ct",
    "sg:city":"Bozeman",
    "sg:classifiers":[
        {
            "category":"Retail",
            "subcategory":"Laundry & Dry Cleaning",
            "type":"Services"
        }
    ],
    "sg:phone":"+1 406 579 1188",
    "sg:postcode":"59718",
    "sg:province":"MT",
    "sg:tags":[
        "cleaners",
        "rug",
        "carpet"
    ],
    "wof:name":"Master Cleaning",
    "wof:placetype":"venue"
},
  "geometry": {"coordinates":[-111.074785,45.684454],"type":"Point"}
}