{
  "type": "Feature",
  "properties": {
    "iso:country":"US",
    "sg:address":"18425 Morgan Ln",
    "sg:city":"Frenchtown",
    "sg:classifiers":[
        {
            "category":"Professional",
            "subcategory":"Business Services",
            "type":"Services"
        }
    ],
    "sg:phone":"+1 406 626 5571",
    "sg:postcode":"59834",
    "sg:province":"MT",
    "wof:name":"Jak Enterprises Inc",
    "wof:placetype":"venue"
},
  "geometry": {"coordinates":[-114.257455,47.044387],"type":"Point"}
}