{
  "type": "Feature",
  "properties": {
    "addr:full":"1605 Ash St Ballantine MT 59006",
    "addr:housenumber":"1605",
    "addr:postcode":"59006",
    "addr:street":"Ash St",
    "iso:country":"US",
    "sg:address":"1605 Ash St",
    "sg:city":"Ballantine",
    "sg:classifiers":[
        {
            "category":"Government",
            "subcategory":"Post Office",
            "type":"Public Place"
        }
    ],
    "sg:phone":"+1 406 967 6913",
    "sg:postcode":"59006",
    "sg:province":"MT",
    "wof:name":"US Post Office",
    "wof:placetype":"venue"
},
  "geometry": {"coordinates":[-108.14960000000001,45.947008],"type":"Point"}
}