{
  "type": "Feature",
  "properties": {
    "addr:full":"811 Mantle Dr Belgrade MT 59714",
    "addr:housenumber":"811",
    "addr:postcode":"59714",
    "addr:street":"Mantle Dr",
    "iso:country":"US",
    "sg:address":"811 Mantle Dr",
    "sg:city":"Belgrade",
    "sg:classifiers":[
        {
            "category":"Building & Trades",
            "subcategory":"Construction",
            "type":"Services"
        }
    ],
    "sg:phone":"+1 406 580 9800",
    "sg:postcode":"59714",
    "sg:province":"MT",
    "sg:tags":[
        "roofing",
        "contractor"
    ],
    "wof:name":"Langley Roofing",
    "wof:placetype":"venue"
},
  "geometry": {"coordinates":[-111.184123,45.793613],"type":"Point"}
}