{
  "type": "Feature",
  "properties": {
    "iso:country":"US",
    "sg:address":"140 Cherry St",
    "sg:city":"Hamilton",
    "sg:classifiers":[
        {
            "category":"Local Transit",
            "type":"Transportation"
        }
    ],
    "sg:phone":"+1 406 363 2105",
    "sg:postcode":"59840",
    "sg:province":"MT",
    "sg:tags":[
        "for",
        "anything",
        "driver",
        "hauling",
        "to",
        "transport"
    ],
    "wof:name":"Charles Haroutunian",
    "wof:placetype":"venue"
},
  "geometry": {"coordinates":[-114.156324,46.249276],"type":"Point"}
}