{
  "type": "Feature",
  "properties": {
    "iso:country":"US",
    "sg:address":"71 25th St W",
    "sg:city":"Billings",
    "sg:classifiers":[
        {
            "category":"Health Services",
            "subcategory":"Chiropractor",
            "type":"Services"
        }
    ],
    "sg:phone":"+1 406 652 4333",
    "sg:postcode":"59102",
    "sg:province":"MT",
    "sg:tags":[
        "medical"
    ],
    "wof:name":"Dwayne G Vogel D C P C",
    "wof:placetype":"venue"
},
  "geometry": {"coordinates":[-108.57972700000001,45.770285],"type":"Point"}
}