{
  "type": "Feature",
  "properties": {
    "addr:full":"319 29th St W Billings MT 59102",
    "addr:housenumber":"319",
    "addr:postcode":"59102",
    "addr:street":"29Th St W",
    "iso:country":"US",
    "sg:address":"319 29th St W",
    "sg:city":"Billings",
    "sg:classifiers":[
        {
            "category":"Professional",
            "subcategory":"Detective & Security Services",
            "type":"Services"
        }
    ],
    "sg:phone":"+1 406 256 2929",
    "sg:postcode":"59102",
    "sg:province":"MT",
    "sg:tags":[
        "guard"
    ],
    "wof:name":"Valerie V Juhl",
    "wof:placetype":"venue"
},
  "geometry": {"coordinates":[-108.587547,45.774417],"type":"Point"}
}