{
  "type": "Feature",
  "properties": {
    "iso:country":"US",
    "sg:address":"1177 Nordheim Ln",
    "sg:city":"Corvallis",
    "sg:classifiers":[
        {
            "category":"Retail",
            "subcategory":"Laundry & Dry Cleaning",
            "type":"Services"
        }
    ],
    "sg:phone":"+1 406 961 3122",
    "sg:postcode":"59828",
    "sg:province":"MT",
    "sg:tags":[
        "cleaners",
        "rug",
        "carpet"
    ],
    "wof:name":"Tim's Cleaner Carpets",
    "wof:placetype":"venue"
},
  "geometry": {"coordinates":[-114.071676,46.325332],"type":"Point"}
}