{
  "type": "Feature",
  "properties": {
    "addr:full":"109 Applehouse Ln Missoula MT 59802",
    "addr:housenumber":"109",
    "addr:postcode":"59802",
    "addr:street":"Applehouse Ln",
    "iso:country":"US",
    "sg:address":"109 Applehouse Ln",
    "sg:city":"Missoula",
    "sg:classifiers":[
        {
            "category":"Manufacturing",
            "subcategory":"Printing",
            "type":"Manufacturing & Wholesale Goods"
        }
    ],
    "sg:phone":"+1 406 549 4448",
    "sg:postcode":"59802",
    "sg:province":"MT",
    "sg:tags":[
        "magazine",
        "publishing"
    ],
    "wof:name":"Wrestling USA Magazine",
    "wof:placetype":"venue"
},
  "geometry": {"coordinates":[-113.959756,46.898255],"type":"Point"}
}