{
  "type": "Feature",
  "properties": {
    "iso:country":"US",
    "sg:address":"1807 W Dickerson St",
    "sg:city":"Bozeman",
    "sg:classifiers":[
        {
            "category":"Real Estate",
            "subcategory":"Architect",
            "type":"Services"
        }
    ],
    "sg:phone":"+1 406 586 3624",
    "sg:postcode":"59715",
    "sg:province":"MT",
    "sg:tags":[
        "architectural"
    ],
    "wof:name":"Cikan Architects PC Inc",
    "wof:placetype":"venue"
},
  "geometry": {"coordinates":[-111.061064,45.673377],"type":"Point"}
}