{
  "type": "Feature",
  "properties": {
    "iso:country":"US",
    "sg:address":"405 N Main St",
    "sg:city":"Darby",
    "sg:phone":"+1 406 821 1988",
    "sg:postcode":"59829",
    "sg:province":"MT",
    "sg:tags":[
        "tanner"
    ],
    "wof:name":"Bitterroot Fur Dressing",
    "wof:placetype":"venue"
},
  "geometry": {"coordinates":[-114.17788,46.024461],"type":"Point"}
}