{
  "type": "Feature",
  "properties": {
    "addr:full":"2060 Overland Ave Billings MT 59102",
    "addr:housenumber":"2060",
    "addr:postcode":"59102",
    "addr:street":"Overland Ave",
    "iso:country":"US",
    "sg:address":"2060 Overland Ave",
    "sg:city":"Billings",
    "sg:classifiers":[
        {
            "category":"Wholesale",
            "subcategory":"Machinery & Supplies",
            "type":"Manufacturing & Wholesale Goods"
        }
    ],
    "sg:phone":"+1 406 652 8944",
    "sg:postcode":"59102",
    "sg:province":"MT",
    "sg:tags":[
        "equipment",
        "establishment"
    ],
    "wof:name":"Beaches Distributing",
    "wof:placetype":"venue"
},
  "geometry": {"coordinates":[-108.567385,45.75258],"type":"Point"}
}