{
  "type": "Feature",
  "properties": {
    "iso:country":"US",
    "sg:address":"3204 Broadwater Ave",
    "sg:city":"Billings",
    "sg:classifiers":[
        {
            "category":"Organizations",
            "subcategory":"Religious Organization",
            "type":"Services"
        }
    ],
    "sg:phone":"+1 406 652 1799",
    "sg:postcode":"59102",
    "sg:province":"MT",
    "sg:tags":[
        "school",
        "church"
    ],
    "wof:name":"Central Acres U S A",
    "wof:placetype":"venue"
},
  "geometry": {"coordinates":[-108.599453,45.776712],"type":"Point"}
}