{
  "type": "Feature",
  "properties": {
    "addr:full":"8695 Applegate Dr Helena MT 59602",
    "addr:housenumber":"8695",
    "addr:postcode":"59602",
    "addr:street":"Applegate Dr",
    "iso:country":"US",
    "sg:address":"8695 Applegate Dr",
    "sg:city":"Helena",
    "sg:classifiers":[
        {
            "category":"Professional",
            "subcategory":"Management & Consulting",
            "type":"Services"
        }
    ],
    "sg:phone":"+1 406 458 9717",
    "sg:postcode":"59602",
    "sg:province":"MT",
    "sg:tags":[
        "business"
    ],
    "wof:name":"Montana Systems Development",
    "wof:placetype":"venue"
},
  "geometry": {"coordinates":[-112.04086700000001,46.749593],"type":"Point"}
}