{
  "type": "Feature",
  "properties": {
    "addr:full":"511 2nd Ave SE Sidney MT 59270",
    "addr:housenumber":"511",
    "addr:postcode":"59270",
    "addr:street":"2Nd Ave Se",
    "iso:country":"US",
    "sg:address":"511 2nd Ave SE",
    "sg:city":"Sidney",
    "sg:phone":"+1 406 482 3750",
    "sg:postcode":"59270",
    "sg:province":"MT",
    "sg:tags":[
        "farm",
        "wheat"
    ],
    "wof:name":"Rhines Farming Corp",
    "wof:placetype":"venue"
},
  "geometry": {"coordinates":[-104.15835,47.710984],"type":"Point"}
}