{
  "type": "Feature",
  "properties": {
    "iso:country":"US",
    "sg:address":"29 Merrill Ln",
    "sg:city":"Livingston",
    "sg:classifiers":[
        {
            "category":"Organizations",
            "subcategory":"Religious Organization",
            "type":"Services"
        }
    ],
    "sg:phone":"+1 406 222 3193",
    "sg:postcode":"59047",
    "sg:province":"MT",
    "wof:name":"Church of Nazarene",
    "wof:placetype":"venue"
},
  "geometry": {"coordinates":[-110.582681,45.636451],"type":"Point"}
}