{
  "type": "Feature",
  "properties": {
    "iso:country":"US",
    "sg:address":"2509 7th Ave S",
    "sg:city":"Great Falls",
    "sg:classifiers":[
        {
            "category":"Health Services",
            "subcategory":"Optometrist",
            "type":"Services"
        }
    ],
    "sg:phone":"+1 406 761 2211",
    "sg:postcode":"59405",
    "sg:province":"MT",
    "wof:name":"Lincoln Medical Court",
    "wof:placetype":"venue"
},
  "geometry": {"coordinates":[-111.262646,47.497491],"type":"Point"}
}