{
  "type": "Feature",
  "properties": {
    "iso:country":"US",
    "sg:address":"501 State Hwy 16",
    "sg:city":"Glasgow",
    "sg:classifiers":[
        {
            "category":"Government",
            "subcategory":"Office",
            "type":"Public Place"
        }
    ],
    "sg:phone":"+1 406 228 8747",
    "sg:postcode":"59254",
    "sg:province":"MT",
    "sg:tags":[
        "county",
        "govt",
        "program"
    ],
    "wof:name":"Valley County Transit",
    "wof:placetype":"venue"
},
  "geometry": {"coordinates":[-104.567894,48.77688],"type":"Point"}
}