{
  "type": "Feature",
  "properties": {
    "iso:country":"US",
    "sg:address":"58176 US Hwy 93",
    "sg:city":"Polson",
    "sg:classifiers":[
        {
            "category":"Manufacturing",
            "subcategory":"Tools & Machinery",
            "type":"Manufacturing & Wholesale Goods"
        }
    ],
    "sg:phone":"+1 406 883 6264",
    "sg:postcode":"59860",
    "sg:province":"MT",
    "sg:tags":[
        "industrial",
        "mfg"
    ],
    "wof:name":"Mangels Machine Works",
    "wof:placetype":"venue"
},
  "geometry": {"coordinates":[-114.12056699999999,47.681585],"type":"Point"}
}