{
  "type": "Feature",
  "properties": {
    "iso:country":"US",
    "sg:address":"3321 Arbor Way",
    "sg:city":"Great Falls",
    "sg:classifiers":[
        {
            "category":"Farming",
            "subcategory":"Livestock Farm",
            "type":"Manufacturing & Wholesale Goods"
        }
    ],
    "sg:phone":"+1 406 453 7173",
    "sg:postcode":"59405",
    "sg:province":"MT",
    "sg:tags":[
        "animal",
        "general"
    ],
    "wof:name":"Goon Coulee Ranch",
    "wof:placetype":"venue"
},
  "geometry": {"coordinates":[-111.249057,47.50332],"type":"Point"}
}