{
  "type": "Feature",
  "properties": {
    "iso:country":"US",
    "sg:address":"1035 S Pacific St",
    "sg:city":"Dillon",
    "sg:classifiers":[
        {
            "category":"Utilities",
            "subcategory":"Mobile Phone",
            "type":"Services"
        }
    ],
    "sg:phone":"+1 406 683 4736",
    "sg:postcode":"59725",
    "sg:province":"MT",
    "sg:tags":[
        "cellular"
    ],
    "wof:name":"Beaverhead Communications",
    "wof:placetype":"venue"
},
  "geometry": {"coordinates":[-112.642972,45.20912],"type":"Point"}
}