{
  "type": "Feature",
  "properties": {
    "addr:full":"701 N Meridian Rd Kalispell MT 59901",
    "addr:housenumber":"701",
    "addr:postcode":"59901",
    "addr:street":"N Meridian Rd",
    "iso:country":"US",
    "sg:address":"701 N Meridian Rd",
    "sg:city":"Kalispell",
    "sg:classifiers":[
        {
            "category":"Restaurant",
            "type":"Food & Drink"
        }
    ],
    "sg:phone":"+1 406 755 0447",
    "sg:postcode":"59901",
    "sg:province":"MT",
    "sg:tags":[
        "shop",
        "coffee"
    ],
    "wof:name":"Juice N Java Junction",
    "wof:placetype":"venue"
},
  "geometry": {"coordinates":[-114.33022099999999,48.204722],"type":"Point"}
}