{
  "type": "Feature",
  "properties": {
    "iso:country":"US",
    "sg:address":"401 Central Ave",
    "sg:city":"Great Falls",
    "sg:classifiers":[
        {
            "category":"Shopping",
            "subcategory":"Jewelry",
            "type":"Retail Goods"
        }
    ],
    "sg:phone":"+1 406 452 4367",
    "sg:postcode":"59401",
    "sg:province":"MT",
    "sg:tags":[
        "material",
        "mfg"
    ],
    "wof:name":"Fox Fine Jewelers",
    "wof:placetype":"venue"
},
  "geometry": {"coordinates":[-111.29909,47.505264],"type":"Point"}
}