{
  "type": "Feature",
  "properties": {
    "iso:country":"US",
    "sg:address":"214 E 1st Ave",
    "sg:city":"Plentywood",
    "sg:classifiers":[
        {
            "category":"Insurance",
            "subcategory":"Insurance Agent",
            "type":"Services"
        }
    ],
    "sg:phone":"+1 406 765 1190",
    "sg:postcode":"59254",
    "sg:province":"MT",
    "wof:name":"Thompson Collins & Assoc",
    "wof:placetype":"venue"
},
  "geometry": {"coordinates":[-104.557474,48.773874],"type":"Point"}
}