{
  "type": "Feature",
  "properties": {
    "addr:full":"1300 N Montana Ave Helena MT 59601",
    "addr:housenumber":"1300",
    "addr:postcode":"59601",
    "addr:street":"N Montana Ave",
    "iso:country":"US",
    "sg:address":"1300 N Montana Ave",
    "sg:city":"Helena",
    "sg:classifiers":[
        {
            "category":"Personal",
            "subcategory":"Beauty Salon",
            "type":"Services"
        }
    ],
    "sg:phone":"+1 406 443 7445",
    "sg:postcode":"59601",
    "sg:province":"MT",
    "sg:tags":[
        "shop"
    ],
    "wof:name":"Avalon Salon",
    "wof:placetype":"venue"
},
  "geometry": {"coordinates":[-112.020875,46.597952],"type":"Point"}
}