{
  "type": "Feature",
  "properties": {
    "iso:country":"US",
    "sg:address":"3900 Olympic Blvd",
    "sg:city":"Billings",
    "sg:classifiers":[
        {
            "category":"Real Estate",
            "subcategory":"Real Estate Operator",
            "type":"Services"
        }
    ],
    "sg:phone":"+1 406 656 4413",
    "sg:postcode":"59102",
    "sg:province":"MT",
    "sg:tags":[
        "building",
        "apartment"
    ],
    "wof:name":"Shiloh Glen Apartments",
    "wof:placetype":"venue"
},
  "geometry": {"coordinates":[-108.616095,45.757672],"type":"Point"}
}