{
  "type": "Feature",
  "properties": {
    "addr:full":"320 S Idaho St Butte MT 59701",
    "addr:housenumber":"320",
    "addr:postcode":"mt 59701",
    "addr:street":"S Idaho St",
    "iso:country":"US",
    "sg:address":"320 S Idaho St",
    "sg:city":"Butte",
    "sg:classifiers":[
        {
            "category":"Health Services",
            "subcategory":"Clinic",
            "type":"Services"
        }
    ],
    "sg:phone":"+1 406 782 2927",
    "sg:postcode":"59701",
    "sg:province":"MT",
    "sg:tags":[
        "specialty",
        "outpatient"
    ],
    "wof:name":"New Hope Pregnancy Support Ctr",
    "wof:placetype":"venue"
},
  "geometry": {"coordinates":[-112.54037099999999,46.009667],"type":"Point"}
}