{
  "type": "Feature",
  "properties": {
    "iso:country":"US",
    "sg:address":"932 S 1st St",
    "sg:city":"Hamilton",
    "sg:classifiers":[
        {
            "category":"Food & Beverages",
            "subcategory":"Groceries & Convenience Stores",
            "type":"Retail Goods"
        }
    ],
    "sg:phone":"+1 406 363 4454",
    "sg:postcode":"59840",
    "sg:province":"MT",
    "wof:name":"Town Pump Inc & Affiliates",
    "wof:placetype":"venue"
},
  "geometry": {"coordinates":[-114.154358,46.23789],"type":"Point"}
}