{
  "type": "Feature",
  "properties": {
    "iso:country":"US",
    "sg:address":"1750 State Hwy 35",
    "sg:city":"Kalispell",
    "sg:classifiers":[
        {
            "category":"Retail",
            "subcategory":"Repair Shop",
            "type":"Services"
        }
    ],
    "sg:phone":"+1 406 752 8121",
    "sg:postcode":"59901",
    "sg:province":"MT",
    "sg:tags":[
        "equipment",
        "refrigeration"
    ],
    "wof:name":"Advanced Restaurant Supply",
    "wof:placetype":"venue"
},
  "geometry": {"coordinates":[-114.257086,48.223296],"type":"Point"}
}