{
  "type": "Feature",
  "properties": {
    "iso:country":"US",
    "sg:address":"4024 5th Ave N",
    "sg:city":"Great Falls",
    "sg:classifiers":[
        {
            "category":"Arts & Performance",
            "subcategory":"Theater",
            "type":"Entertainment"
        }
    ],
    "sg:phone":"+1 406 452 9320",
    "sg:postcode":"59405",
    "sg:province":"MT",
    "sg:tags":[
        "group"
    ],
    "wof:name":"Flash Back Band",
    "wof:placetype":"venue"
},
  "geometry": {"coordinates":[-111.234817,47.510401],"type":"Point"}
}