{
  "type": "Feature",
  "properties": {
    "iso:country":"US",
    "sg:address":"1659 Heath St",
    "sg:city":"Huntley",
    "sg:classifiers":[
        {
            "category":"Retail",
            "subcategory":"Auto Repair",
            "type":"Services"
        }
    ],
    "sg:phone":"+1 406 348 3168",
    "sg:postcode":"59037",
    "sg:province":"MT",
    "sg:tags":[
        "transmission",
        "tractor"
    ],
    "wof:name":"K Enterprises Truck",
    "wof:placetype":"venue"
},
  "geometry": {"coordinates":[-108.301301,45.903243],"type":"Point"}
}