{
  "type": "Feature",
  "properties": {
    "addr:full":"115 Honeysuckle St Billings MT 59106",
    "addr:housenumber":"115",
    "addr:street":"Honeysuckle St",
    "iso:country":"US",
    "sg:address":"115 Honeysuckle St",
    "sg:city":"Billings",
    "sg:classifiers":[
        {
            "category":"Building & Trades",
            "subcategory":"Construction",
            "type":"Services"
        }
    ],
    "sg:phone":"+1 406 860 5025",
    "sg:postcode":"59106",
    "sg:province":"MT",
    "sg:tags":[
        "home",
        "improvement"
    ],
    "wof:name":"Brew's Home Maintenance",
    "wof:placetype":"venue"
},
  "geometry": {"coordinates":[-108.64089,45.771684],"type":"Point"}
}