{
  "type": "Feature",
  "properties": {
    "iso:country":"US",
    "sg:address":"44 Rd 241",
    "sg:city":"Glendive",
    "sg:phone":"+1 406 486 5639",
    "sg:postcode":"59330",
    "sg:province":"MT",
    "sg:tags":[
        "farm",
        "beet"
    ],
    "wof:name":"Allen Ollerman Farms",
    "wof:placetype":"venue"
},
  "geometry": {"coordinates":[-104.96377099999999,46.89246],"type":"Point"}
}