{
  "type": "Feature",
  "properties": {
    "iso:country":"US",
    "sg:address":"121 Red Tail Hawk Dr",
    "sg:city":"Belgrade",
    "sg:classifiers":[
        {
            "category":"Building & Trades",
            "subcategory":"Construction",
            "type":"Services"
        }
    ],
    "sg:phone":"+1 406 388 9110",
    "sg:postcode":"59714",
    "sg:province":"MT",
    "sg:tags":[
        "carpentry",
        "floor",
        "laying",
        "contractor"
    ],
    "wof:name":"Diverse Enterprises",
    "wof:placetype":"venue"
},
  "geometry": {"coordinates":[-111.20580200000001,45.780964],"type":"Point"}
}