{
  "type": "Feature",
  "properties": {
    "iso:country":"US",
    "sg:address":"117 16th Ave NW",
    "sg:city":"Great Falls",
    "sg:classifiers":[
        {
            "category":"Organizations",
            "subcategory":"Religious Organization",
            "type":"Services"
        }
    ],
    "sg:phone":"+1 406 771 0629",
    "sg:postcode":"59404",
    "sg:province":"MT",
    "wof:name":"New Apostolic Church",
    "wof:placetype":"venue"
},
  "geometry": {"coordinates":[-111.315691,47.521354],"type":"Point"}
}