{
  "type": "Feature",
  "properties": {
    "iso:country":"US",
    "sg:address":"616 4th Ave N",
    "sg:city":"Wolf Point",
    "sg:classifiers":[
        {
            "category":"Organizations",
            "subcategory":"Religious Organization",
            "type":"Services"
        }
    ],
    "sg:phone":"+1 406 653 1732",
    "sg:postcode":"59201",
    "sg:province":"MT",
    "sg:tags":[
        "church"
    ],
    "wof:name":"Assembly Of God Church",
    "wof:placetype":"venue"
},
  "geometry": {"coordinates":[-105.642686,48.095709],"type":"Point"}
}