{
  "type": "Feature",
  "properties": {
    "iso:country":"US",
    "sg:address":"1331 Central Ave",
    "sg:city":"Billings",
    "sg:classifiers":[
        {
            "category":"Personal",
            "subcategory":"Barber",
            "type":"Services"
        }
    ],
    "sg:phone":"+1 406 252 4950",
    "sg:postcode":"59102",
    "sg:province":"MT",
    "sg:tags":[
        "shop"
    ],
    "wof:name":"Rusty Razor",
    "wof:placetype":"venue"
},
  "geometry": {"coordinates":[-108.55059300000001,45.769858],"type":"Point"}
}