{
  "type": "Feature",
  "properties": {
    "addr:full":"311 E Division St Harlowton MT 59036",
    "addr:housenumber":"311",
    "addr:postcode":"59036",
    "addr:street":"E Division St",
    "iso:country":"US",
    "sg:address":"311 E Division St",
    "sg:city":"Harlowton",
    "sg:classifiers":[
        {
            "category":"Organizations",
            "subcategory":"Religious Organization",
            "type":"Services"
        }
    ],
    "sg:phone":"+1 406 632 5876",
    "sg:postcode":"59036",
    "sg:province":"MT",
    "sg:tags":[
        "church"
    ],
    "wof:name":"American Lutheran Church",
    "wof:placetype":"venue"
},
  "geometry": {"coordinates":[-109.827257,46.436256],"type":"Point"}
}