{
  "type": "Feature",
  "properties": {
    "iso:country":"US",
    "sg:address":"1010 14th St W",
    "sg:city":"Billings",
    "sg:classifiers":[
        {
            "category":"Freight",
            "type":"Transportation"
        }
    ],
    "sg:phone":"+1 406 259 7476",
    "sg:postcode":"59102",
    "sg:province":"MT",
    "sg:tags":[
        "operator",
        "logging",
        "trucking"
    ],
    "wof:name":"Yellowstone Trucking",
    "wof:placetype":"venue"
},
  "geometry": {"coordinates":[-108.55125,45.779417],"type":"Point"}
}