{
  "type": "Feature",
  "properties": {
    "iso:country":"US",
    "sg:address":"1300 28th St S",
    "sg:city":"Great Falls",
    "sg:classifiers":[
        {
            "category":"Health Services",
            "subcategory":"Doctor",
            "type":"Services"
        }
    ],
    "sg:phone":"+1 406 761 1800",
    "sg:postcode":"59405",
    "sg:province":"MT",
    "sg:tags":[
        "medical"
    ],
    "wof:name":"Great Falls Gastroenterologist",
    "wof:placetype":"venue"
},
  "geometry": {"coordinates":[-111.259247,47.491206],"type":"Point"}
}