{
  "type": "Feature",
  "properties": {
    "iso:country":"US",
    "sg:address":"517 E 3rd St",
    "sg:city":"Anaconda",
    "sg:classifiers":[
        {
            "category":"Bars & Pubs",
            "type":"Food & Drink"
        }
    ],
    "sg:phone":"+1 406 563 6722",
    "sg:postcode":"59711",
    "sg:province":"MT",
    "sg:tags":[
        "drinking"
    ],
    "wof:name":"Mill Bar",
    "wof:placetype":"venue"
},
  "geometry": {"coordinates":[-112.94748199999999,46.127224],"type":"Point"}
}