{
  "type": "Feature",
  "properties": {
    "iso:country":"US",
    "sg:address":"203 Tam Oshanter Rd",
    "sg:city":"Billings",
    "sg:classifiers":[
        {
            "category":"Professional",
            "subcategory":"Management & Consulting",
            "type":"Services"
        }
    ],
    "sg:phone":"+1 406 670 9902",
    "sg:postcode":"59105",
    "sg:province":"MT",
    "sg:tags":[
        "business"
    ],
    "wof:name":"Otb Consulting Inc",
    "wof:placetype":"venue"
},
  "geometry": {"coordinates":[-108.493427,45.828004],"type":"Point"}
}