{
  "type": "Feature",
  "properties": {
    "iso:country":"US",
    "sg:address":"115 N 19th St",
    "sg:city":"Billings",
    "sg:classifiers":[
        {
            "category":"Freight",
            "type":"Transportation"
        }
    ],
    "sg:phone":"+1 406 256 2076",
    "sg:postcode":"59101",
    "sg:province":"MT",
    "wof:name":"Treasure State Transportation",
    "wof:placetype":"venue"
},
  "geometry": {"coordinates":[-108.495426,45.788216],"type":"Point"}
}