{
  "type": "Feature",
  "properties": {
    "addr:full":"2969 Airport Rd Helena MT 59601",
    "addr:housenumber":"2969",
    "addr:postcode":"59601",
    "addr:street":"Airport Rd",
    "iso:country":"US",
    "sg:address":"2969 Airport Rd",
    "sg:city":"Helena",
    "sg:classifiers":[
        {
            "category":"Professional",
            "subcategory":"Art Services",
            "type":"Services"
        }
    ],
    "sg:phone":"+1 406 442 8108",
    "sg:postcode":"59601",
    "sg:province":"MT",
    "sg:tags":[
        "photography",
        "aerial"
    ],
    "wof:name":"Piedmont Air Services",
    "wof:placetype":"venue"
},
  "geometry": {"coordinates":[-111.987279,46.602047],"type":"Point"}
}