{
  "type": "Feature",
  "properties": {
    "iso:country":"US",
    "sg:address":"156 Reeds Ln",
    "sg:city":"Columbia Falls",
    "sg:classifiers":[
        {
            "category":"Arts & Performance",
            "subcategory":"Theater",
            "type":"Entertainment"
        }
    ],
    "sg:phone":"+1 406 892 7529",
    "sg:postcode":"59912",
    "sg:province":"MT",
    "sg:tags":[
        "group"
    ],
    "wof:name":"Special K Multiple Choice Mus",
    "wof:placetype":"venue"
},
  "geometry": {"coordinates":[-114.271879,48.366724],"type":"Point"}
}