{
  "type": "Feature",
  "properties": {
    "iso:country":"US",
    "sg:address":"743 Wall St",
    "sg:city":"Hamilton",
    "sg:classifiers":[
        {
            "category":"Professional",
            "subcategory":"Management & Consulting",
            "type":"Services"
        }
    ],
    "sg:phone":"+1 406 363 7506",
    "sg:postcode":"59840",
    "sg:province":"MT",
    "sg:tags":[
        "roofing",
        "consultant"
    ],
    "wof:name":"Eagle Roofing",
    "wof:placetype":"venue"
},
  "geometry": {"coordinates":[-114.143325,46.203435],"type":"Point"}
}