{
  "type": "Feature",
  "properties": {
    "iso:country":"US",
    "sg:address":"4944 James Trl",
    "sg:city":"Stevensville",
    "sg:classifiers":[
        {
            "category":"Retail",
            "subcategory":"Auto Repair",
            "type":"Services"
        }
    ],
    "sg:phone":"+1 406 777 3015",
    "sg:postcode":"59870",
    "sg:province":"MT",
    "sg:tags":[
        "automobile",
        "top",
        "upholstery"
    ],
    "wof:name":"Bitterroot Upholstery",
    "wof:placetype":"venue"
},
  "geometry": {"coordinates":[-114.013958,46.593892],"type":"Point"}
}