{
  "type": "Feature",
  "properties": {
    "iso:country":"US",
    "sg:address":"913 SW Higgins Ave",
    "sg:city":"Missoula",
    "sg:classifiers":[
        {
            "category":"Health Services",
            "subcategory":"Doctor",
            "type":"Services"
        }
    ],
    "sg:phone":"+1 406 721 2686",
    "sg:postcode":"59803",
    "sg:province":"MT",
    "wof:name":"Max F Porter DDS",
    "wof:placetype":"venue"
},
  "geometry": {"coordinates":[-114.009677,46.837273],"type":"Point"}
}