{
  "type": "Feature",
  "properties": {
    "iso:country":"US",
    "sg:address":"5119 Cherokee Trl",
    "sg:city":"Billings",
    "sg:classifiers":[
        {
            "category":"Professional",
            "subcategory":"Business Services",
            "type":"Services"
        }
    ],
    "sg:phone":"+1 406 670 5830",
    "sg:postcode":"59106",
    "sg:province":"MT",
    "sg:tags":[
        "training",
        "computer",
        "mapping"
    ],
    "wof:name":"Geoscience Associates Inc",
    "wof:placetype":"venue"
},
  "geometry": {"coordinates":[-108.644558,45.810669],"type":"Point"}
}