{
  "type": "Feature",
  "properties": {
    "addr:full":"2478 Home Acres Rd Stevensville MT 59870",
    "addr:housenumber":"2478",
    "addr:postcode":"59870",
    "addr:street":"Home Acres Rd",
    "iso:country":"US",
    "sg:address":"2478 Home Acres Rd",
    "sg:city":"Stevensville",
    "sg:classifiers":[
        {
            "category":"Retail",
            "subcategory":"Repair Shop",
            "type":"Services"
        }
    ],
    "sg:phone":"+1 406 777 2847",
    "sg:postcode":"59870",
    "sg:province":"MT",
    "wof:name":"Mary P Ewer",
    "wof:placetype":"venue"
},
  "geometry": {"coordinates":[-114.06885699999999,46.421404],"type":"Point"}
}