{
  "type": "Feature",
  "properties": {
    "iso:country":"US",
    "sg:address":"7 W 6th Ave",
    "sg:city":"Helena",
    "sg:classifiers":[
        {
            "category":"Shopping",
            "subcategory":"Stationery & Office Supplies",
            "type":"Retail Goods"
        }
    ],
    "sg:phone":"+1 406 442 6578",
    "sg:postcode":"59601",
    "sg:province":"MT",
    "sg:tags":[
        "business",
        "form"
    ],
    "wof:name":"Standard Register Company",
    "wof:placetype":"venue"
},
  "geometry": {"coordinates":[-112.039131,46.589096],"type":"Point"}
}