{
  "type": "Feature",
  "properties": {
    "iso:country":"US",
    "sg:address":"233 Cascade St",
    "sg:city":"Wolf Point",
    "sg:classifiers":[
        {
            "category":"Professional",
            "type":"Services"
        }
    ],
    "sg:phone":"+1 406 653 1538",
    "sg:postcode":"59201",
    "sg:province":"MT",
    "sg:tags":[
        "establishment"
    ],
    "wof:name":"Fbi Task Force",
    "wof:placetype":"venue"
},
  "geometry": {"coordinates":[-105.639251,48.094057],"type":"Point"}
}