{
  "type": "Feature",
  "properties": {
    "addr:full":"432 N Last Chance Gulch St Helena MT 59601",
    "addr:housenumber":"432",
    "addr:postcode":"59601",
    "addr:street":"N Last Chance Gulch",
    "iso:country":"US",
    "sg:address":"432 N Last Chance Gulch St",
    "sg:city":"Helena",
    "sg:classifiers":[
        {
            "category":"Professional",
            "subcategory":"Management & Consulting",
            "type":"Services"
        }
    ],
    "sg:phone":"+1 406 495 1560",
    "sg:postcode":"59601",
    "sg:province":"MT",
    "sg:tags":[
        "business"
    ],
    "wof:name":"National Prks Cnservation Assn",
    "wof:placetype":"venue"
},
  "geometry": {"coordinates":[-112.03722,46.591299],"type":"Point"}
}