{
  "type": "Feature",
  "properties": {
    "iso:country":"US",
    "sg:address":"2424 Central Ave",
    "sg:city":"Billings",
    "sg:classifiers":[
        {
            "category":"Shopping",
            "subcategory":"Pharmacy",
            "type":"Retail Goods"
        }
    ],
    "sg:phone":"+1 406 656 0913",
    "sg:postcode":"59102",
    "sg:province":"MT",
    "sg:website":"www.bluelight.com",
    "wof:name":"Kmart",
    "wof:placetype":"venue"
},
  "geometry": {"coordinates":[-108.578962,45.769672],"type":"Point"}
}