{
  "type": "Feature",
  "properties": {
    "addr:full":"310 Meany St Plains MT 59859",
    "addr:housenumber":"310",
    "addr:postcode":"59859",
    "addr:street":"Meany St",
    "iso:country":"US",
    "sg:address":"310 Meany St",
    "sg:city":"Plains",
    "sg:classifiers":[
        {
            "category":"Government",
            "subcategory":"Post Office",
            "type":"Public Place"
        }
    ],
    "sg:phone":"+1 406 826 3541",
    "sg:postcode":"59859",
    "sg:province":"MT",
    "wof:name":"US Post Office",
    "wof:placetype":"venue"
},
  "geometry": {"coordinates":[-114.886875,47.460872],"type":"Point"}
}