{
  "type": "Feature",
  "properties": {
    "addr:full":"515 Mc Leod Ave Missoula MT 59801",
    "addr:housenumber":"515",
    "addr:postcode":"59801",
    "addr:street":"Mc Leod Ave",
    "iso:country":"US",
    "sg:address":"515 Mc Leod Ave",
    "sg:city":"Missoula",
    "sg:classifiers":[
        {
            "category":"Education",
            "subcategory":"Special Training",
            "type":"Public Place"
        }
    ],
    "sg:phone":"+1 406 549 6343",
    "sg:postcode":"59801",
    "sg:province":"MT",
    "wof:name":"LDS Institute",
    "wof:placetype":"venue"
},
  "geometry": {"coordinates":[-113.98938800000001,46.859027],"type":"Point"}
}