{
  "type": "Feature",
  "properties": {
    "addr:full":"431 4th Ave N Wolf Point MT 59201",
    "addr:housenumber":"431",
    "addr:postcode":"59201",
    "addr:street":"4Th Ave N Wolf Point",
    "iso:country":"US",
    "sg:address":"431 4th Ave N",
    "sg:city":"Wolf Point",
    "sg:classifiers":[
        {
            "category":"Shopping",
            "subcategory":"Florist",
            "type":"Retail Goods"
        }
    ],
    "sg:phone":"+1 406 653 1381",
    "sg:postcode":"59201",
    "sg:province":"MT",
    "wof:name":"Friesen's Floral & Greenhouse",
    "wof:placetype":"venue"
},
  "geometry": {"coordinates":[-105.642826,48.09379],"type":"Point"}
}