{
  "type": "Feature",
  "properties": {
    "iso:country":"US",
    "sg:address":"1085 Helena Ave",
    "sg:city":"Helena",
    "sg:classifiers":[
        {
            "category":"Professional",
            "subcategory":"Lawyer & Legal Services",
            "type":"Services"
        }
    ],
    "sg:phone":"+1 406 442 3625",
    "sg:postcode":"59601",
    "sg:province":"MT",
    "wof:name":"Charles Petaja",
    "wof:placetype":"venue"
},
  "geometry": {"coordinates":[-112.022993,46.59718],"type":"Point"}
}