{
  "type": "Feature",
  "properties": {
    "iso:country":"US",
    "sg:address":"2600 Wilson St",
    "sg:city":"Miles City",
    "sg:classifiers":[
        {
            "category":"Health Services",
            "subcategory":"Hospital",
            "type":"Services"
        }
    ],
    "sg:phone":"+1 406 232 2540",
    "sg:postcode":"59301",
    "sg:province":"MT",
    "sg:tags":[
        "nursing",
        "facility",
        "medical",
        "skilled",
        "general",
        "care"
    ],
    "wof:name":"Holy Rosary Extended Care",
    "wof:placetype":"venue"
},
  "geometry": {"coordinates":[-105.827838,46.397349],"type":"Point"}
}