{
  "type": "Feature",
  "properties": {
    "iso:country":"US",
    "sg:address":"115 6th Ave N",
    "sg:city":"Judith Gap",
    "sg:classifiers":[
        {
            "category":"Government",
            "subcategory":"Post Office",
            "type":"Public Place"
        }
    ],
    "sg:phone":"+1 406 473 2256",
    "sg:postcode":"59474",
    "sg:province":"MT",
    "wof:name":"US Post Office",
    "wof:placetype":"venue"
},
  "geometry": {"coordinates":[-111.862749,48.507308],"type":"Point"}
}