{
  "type": "Feature",
  "properties": {
    "iso:country":"US",
    "sg:address":"503 N Front St",
    "sg:city":"Townsend",
    "sg:classifiers":[
        {
            "category":"Utilities",
            "subcategory":"Fuel Oil & Lpg",
            "type":"Services"
        }
    ],
    "sg:phone":"+1 406 266 3815",
    "sg:postcode":"59644",
    "sg:province":"MT",
    "sg:tags":[
        "liquefied",
        "gas",
        "petroleum"
    ],
    "wof:name":"AmeriGas",
    "wof:placetype":"venue"
},
  "geometry": {"coordinates":[-111.524629,46.323854],"type":"Point"}
}