{
  "type": "Feature",
  "properties": {
    "iso:country":"US",
    "sg:address":"55 Rd 433",
    "sg:city":"Richey",
    "sg:phone":"+1 406 773 5623",
    "sg:postcode":"59315",
    "sg:province":"MT",
    "sg:tags":[
        "beef",
        "farm",
        "cash",
        "grain",
        "cattle",
        "feedlot"
    ],
    "wof:name":"Pastor Creek",
    "wof:placetype":"venue"
},
  "geometry": {"coordinates":[-105.064363,47.530255],"type":"Point"}
}