{
  "type": "Feature",
  "properties": {
    "addr:full":"179 Cerise Rd Billings MT 59101",
    "addr:housenumber":"179",
    "addr:postcode":"59101",
    "addr:street":"Cerise Rd",
    "iso:country":"US",
    "sg:address":"179 Cerise Rd",
    "sg:city":"Billings",
    "sg:classifiers":[
        {
            "category":"Freight",
            "type":"Transportation"
        }
    ],
    "sg:phone":"+1 406 252 5483",
    "sg:postcode":"59101",
    "sg:province":"MT",
    "sg:tags":[
        "dry",
        "bulk",
        "trucking"
    ],
    "wof:name":"Lomco Inc",
    "wof:placetype":"venue"
},
  "geometry": {"coordinates":[-108.466144,45.800162],"type":"Point"}
}