{
  "type": "Feature",
  "properties": {
    "addr:full":"220 3rd Ave Havre MT 59501",
    "addr:housenumber":"220",
    "addr:postcode":"59501",
    "addr:street":"3Rd Ave",
    "iso:country":"US",
    "sg:address":"220 3rd Ave",
    "sg:city":"Havre",
    "sg:classifiers":[
        {
            "category":"Shopping",
            "subcategory":"Gifts & Souvenirs",
            "type":"Retail Goods"
        }
    ],
    "sg:phone":"+1 406 265 8655",
    "sg:postcode":"59501",
    "sg:province":"MT",
    "wof:name":"Carousel Decor & Crafts",
    "wof:placetype":"venue"
},
  "geometry": {"coordinates":[-109.67853599999999,48.552298],"type":"Point"}
}