{
  "type": "Feature",
  "properties": {
    "iso:country":"US",
    "sg:address":"91 John G Mine Rd",
    "sg:city":"Helena",
    "sg:classifiers":[
        {
            "category":"Banks & Credit Unions",
            "subcategory":"Financial Services",
            "type":"Services"
        }
    ],
    "sg:phone":"+1 406 458 4914",
    "sg:postcode":"59602",
    "sg:province":"MT",
    "sg:tags":[
        "company",
        "holding"
    ],
    "wof:name":"Western Skys Ltd Co",
    "wof:placetype":"venue"
},
  "geometry": {"coordinates":[-112.059302,46.688882],"type":"Point"}
}