{
  "type": "Feature",
  "properties": {
    "addr:full":"1920 Central Ave Billings MT 59102",
    "addr:housenumber":"1920",
    "addr:postcode":"59102",
    "addr:street":"Central Ave",
    "iso:country":"US",
    "sg:address":"1920 Central Ave",
    "sg:city":"Billings",
    "sg:classifiers":[
        {
            "category":"Recreation",
            "type":"Entertainment"
        }
    ],
    "sg:phone":"+1 406 245 8808",
    "sg:postcode":"59102",
    "sg:province":"MT",
    "sg:tags":[
        "martial",
        "arts",
        "instruction"
    ],
    "wof:name":"Park's Martial Arts Academy",
    "wof:placetype":"venue"
},
  "geometry": {"coordinates":[-108.562405,45.769689],"type":"Point"}
}