{
  "type": "Feature",
  "properties": {
    "iso:country":"US",
    "sg:address":"109 E Commercial Ave",
    "sg:city":"Anaconda",
    "sg:classifiers":[
        {
            "category":"Building & Trades",
            "subcategory":"Plumbing",
            "type":"Services"
        }
    ],
    "sg:phone":"+1 406 563 7642",
    "sg:postcode":"59711",
    "sg:province":"MT",
    "sg:tags":[
        "mechanical",
        "contractor"
    ],
    "wof:name":"Copper City Shtmtl Htg & A Co",
    "wof:placetype":"venue"
},
  "geometry": {"coordinates":[-112.952586,46.130181],"type":"Point"}
}