{
  "type": "Feature",
  "properties": {
    "addr:full":"1344 US Hwy 93 Victor MT 59875",
    "addr:housenumber":"1344",
    "addr:postcode":"59875",
    "addr:street":"Us Hwy 93 Victor",
    "iso:country":"US",
    "sg:address":"1344 US Hwy 93",
    "sg:city":"Victor",
    "sg:classifiers":[
        {
            "category":"Manufacturing",
            "subcategory":"Buildings",
            "type":"Manufacturing & Wholesale Goods"
        }
    ],
    "sg:phone":"+1 406 961 3273",
    "sg:postcode":"59875",
    "sg:province":"MT",
    "sg:tags":[
        "mfg",
        "log",
        "structure",
        "handcrafted"
    ],
    "sg:website":"www.rmlh.com",
    "wof:name":"Pioneer Log Homes",
    "wof:placetype":"venue"
},
  "geometry": {"coordinates":[-114.150088,46.338963],"type":"Point"}
}