{
  "type": "Feature",
  "properties": {
    "iso:country":"US",
    "sg:address":"1210 E Main St",
    "sg:city":"Cut Bank",
    "sg:classifiers":[
        {
            "category":"Health Services",
            "subcategory":"Hospital",
            "type":"Services"
        }
    ],
    "sg:phone":"+1 406 873 5538",
    "sg:postcode":"59427",
    "sg:province":"MT",
    "sg:tags":[
        "executive",
        "psychiatric"
    ],
    "wof:name":"Golden Trangle Mental Hlth Ctr",
    "wof:placetype":"venue"
},
  "geometry": {"coordinates":[-112.316954,48.629401],"type":"Point"}
}