{
  "type": "Feature",
  "properties": {
    "addr:full":"2901 Brooks St Missoula MT 59801",
    "addr:housenumber":"2901",
    "addr:postcode":"59801",
    "addr:street":"Brooks St",
    "iso:country":"US",
    "sg:address":"2901 Brooks St",
    "sg:city":"Missoula",
    "sg:classifiers":[
        {
            "category":"Shopping",
            "subcategory":"Clothing, Apparel, & Fashions",
            "type":"Retail Goods"
        }
    ],
    "sg:phone":"+1 406 728 1727",
    "sg:postcode":"59801",
    "sg:province":"MT",
    "wof:name":"Gap",
    "wof:placetype":"venue"
},
  "geometry": {"coordinates":[-114.024674,46.844438],"type":"Point"}
}