{
  "type": "Feature",
  "properties": {
    "iso:country":"US",
    "sg:address":"813 16th St W",
    "sg:city":"Billings",
    "sg:classifiers":[
        {
            "category":"Shopping",
            "subcategory":"Clothing, Apparel, & Fashions",
            "type":"Retail Goods"
        }
    ],
    "sg:phone":"+1 406 254 6797",
    "sg:postcode":"59102",
    "sg:province":"MT",
    "sg:tags":[
        "shop",
        "bridal"
    ],
    "wof:name":"Je T'Aime Bridals & Formal",
    "wof:placetype":"venue"
},
  "geometry": {"coordinates":[-108.5563,45.778785],"type":"Point"}
}