{
  "type": "Feature",
  "properties": {
    "iso:country":"US",
    "sg:address":"1140 11th Ave",
    "sg:city":"Helena",
    "sg:classifiers":[
        {
            "category":"Retail",
            "subcategory":"Auto Repair",
            "type":"Services"
        }
    ],
    "sg:phone":"+1 406 442 2724",
    "sg:postcode":"59601",
    "sg:province":"MT",
    "sg:tags":[
        "automotive"
    ],
    "wof:name":"Prestige Service Center",
    "wof:placetype":"venue"
},
  "geometry": {"coordinates":[-112.0216,46.589794],"type":"Point"}
}