{
  "type": "Feature",
  "properties": {
    "iso:country":"US",
    "sg:address":"2817 2nd Ave N",
    "sg:city":"Billings",
    "sg:classifiers":[
        {
            "category":"Professional",
            "subcategory":"Lawyer & Legal Services",
            "type":"Services"
        }
    ],
    "sg:phone":"+1 406 252 8500",
    "sg:postcode":"59101",
    "sg:province":"MT",
    "sg:tags":[
        "attorney"
    ],
    "wof:name":"Patten Peterman & Bekkedahl",
    "wof:placetype":"venue"
},
  "geometry": {"coordinates":[-108.507756,45.782524],"type":"Point"}
}