{
  "type": "Feature",
  "properties": {
    "iso:country":"US",
    "sg:address":"23 N 8th St",
    "sg:city":"Miles City",
    "sg:classifiers":[
        {
            "category":"Professional",
            "subcategory":"Lawyer & Legal Services",
            "type":"Services"
        }
    ],
    "sg:phone":"+1 406 232 5257",
    "sg:postcode":"59301",
    "sg:province":"MT",
    "sg:tags":[
        "attorney"
    ],
    "wof:name":"J Dennis Corbin Law Office",
    "wof:placetype":"venue"
},
  "geometry": {"coordinates":[-105.848703,46.407602],"type":"Point"}
}