{
  "type": "Feature",
  "properties": {
    "iso:country":"US",
    "sg:address":"4021 Chamberlain Dr",
    "sg:city":"Billings",
    "sg:classifiers":[
        {
            "category":"Building & Trades",
            "subcategory":"Construction",
            "type":"Services"
        }
    ],
    "sg:phone":"+1 406 254 0655",
    "sg:postcode":"59101",
    "sg:province":"MT",
    "sg:tags":[
        "residential"
    ],
    "wof:name":"Lueck Construction Inc",
    "wof:placetype":"venue"
},
  "geometry": {"coordinates":[-108.514484,45.754123],"type":"Point"}
}