{
  "type": "Feature",
  "properties": {
    "iso:country":"US",
    "sg:address":"503 Ave D",
    "sg:city":"Billings",
    "sg:classifiers":[
        {
            "category":"Health Services",
            "subcategory":"Chiropractor",
            "type":"Services"
        }
    ],
    "sg:phone":"+1 406 252 2581",
    "sg:postcode":"59102",
    "sg:province":"MT",
    "wof:name":"Robinson H R",
    "wof:placetype":"venue"
},
  "geometry": {"coordinates":[-108.530536,45.787049],"type":"Point"}
}