{
  "type": "Feature",
  "properties": {
    "iso:country":"US",
    "sg:address":"1863 Harrison Ave",
    "sg:city":"Butte",
    "sg:classifiers":[
        {
            "category":"Personal",
            "subcategory":"Beauty Salon",
            "type":"Services"
        }
    ],
    "sg:phone":"+1 406 782 7283",
    "sg:postcode":"59701",
    "sg:province":"MT",
    "sg:tags":[
        "shop"
    ],
    "wof:name":"Angie's Beauty Salon",
    "wof:placetype":"venue"
},
  "geometry": {"coordinates":[-112.513932,45.995635],"type":"Point"}
}