{
  "type": "Feature",
  "properties": {
    "addr:full":"1007 Berthot Dr Bozeman MT 59715",
    "addr:housenumber":"1007",
    "addr:postcode":"59715",
    "addr:street":"Berthot Dr",
    "iso:country":"US",
    "sg:address":"1007 Berthot Dr",
    "sg:city":"Bozeman",
    "sg:classifiers":[
        {
            "category":"Real Estate",
            "subcategory":"Real Estate Operator",
            "type":"Services"
        }
    ],
    "sg:phone":"+1 406 522 5686",
    "sg:postcode":"59715",
    "sg:province":"MT",
    "sg:tags":[
        "building",
        "nonresidential"
    ],
    "wof:name":"T & W Cowdrey Property Inc",
    "wof:placetype":"venue"
},
  "geometry": {"coordinates":[-111.022508,45.660051],"type":"Point"}
}