{
  "type": "Feature",
  "properties": {
    "iso:country":"US",
    "sg:address":"1322 5th Ave",
    "sg:city":"Laurel",
    "sg:classifiers":[
        {
            "category":"Building & Trades",
            "subcategory":"Construction",
            "type":"Services"
        }
    ],
    "sg:phone":"+1 406 628 6857",
    "sg:postcode":"59044",
    "sg:province":"MT",
    "sg:tags":[
        "floor",
        "laying",
        "contractor"
    ],
    "wof:name":"Flooring Service Inc",
    "wof:placetype":"venue"
},
  "geometry": {"coordinates":[-108.777572,45.686025],"type":"Point"}
}