{
  "type": "Feature",
  "properties": {
    "addr:full":"2812 1st Ave N Billings MT 59101",
    "addr:housenumber":"2812",
    "addr:postcode":"59101",
    "addr:street":"1St Ave N",
    "iso:country":"US",
    "sg:address":"2812 1st Ave N",
    "sg:city":"Billings",
    "sg:classifiers":[
        {
            "category":"Mining & Drilling",
            "type":"Manufacturing & Wholesale Goods"
        }
    ],
    "sg:phone":"+1 406 259 3981",
    "sg:postcode":"59101",
    "sg:province":"MT",
    "sg:tags":[
        "company",
        "oil"
    ],
    "wof:name":"R B Oil Co",
    "wof:placetype":"venue"
},
  "geometry": {"coordinates":[-108.506878,45.781531],"type":"Point"}
}