{
  "type": "Feature",
  "properties": {
    "iso:country":"US",
    "sg:address":"3199 Harrison Ave",
    "sg:city":"Butte",
    "sg:classifiers":[
        {
            "category":"Restaurant",
            "type":"Food & Drink"
        }
    ],
    "sg:phone":"+1 406 494 8094",
    "sg:postcode":"59701",
    "sg:province":"MT",
    "sg:tags":[
        "eating"
    ],
    "wof:name":"TCBY",
    "wof:placetype":"venue"
},
  "geometry": {"coordinates":[-112.508016,45.97877],"type":"Point"}
}