{
  "type": "Feature",
  "properties": {
    "iso:country":"US",
    "sg:address":"3306 Becraft Ln",
    "sg:city":"Billings",
    "sg:classifiers":[
        {
            "category":"Recreation",
            "type":"Entertainment"
        }
    ],
    "sg:phone":"+1 406 259 2011",
    "sg:postcode":"59101",
    "sg:province":"MT",
    "sg:tags":[
        "stable"
    ],
    "sg:website":"www.equinemotel.net",
    "wof:name":"Rickochet Ranch",
    "wof:placetype":"venue"
},
  "geometry": {"coordinates":[-108.398297,45.812142],"type":"Point"}
}