{
  "type": "Feature",
  "properties": {
    "iso:country":"US",
    "sg:address":"1694 Sylvan Dr",
    "sg:city":"Bigfork",
    "sg:classifiers":[
        {
            "category":"Shopping",
            "subcategory":"Computers & Home Electronics",
            "type":"Retail Goods"
        }
    ],
    "sg:phone":"+1 406 837 0265",
    "sg:postcode":"59911",
    "sg:province":"MT",
    "wof:name":"Phoenix Satellite Inc",
    "wof:placetype":"venue"
},
  "geometry": {"coordinates":[-114.057002,48.0056],"type":"Point"}
}