{
  "type": "Feature",
  "properties": {
    "addr:full":"524 E Main St Sidney MT 59270",
    "addr:housenumber":"524",
    "addr:postcode":"59270",
    "addr:street":"E Main St",
    "iso:country":"US",
    "sg:address":"524 E Main St",
    "sg:city":"Sidney",
    "sg:classifiers":[
        {
            "category":"Manufacturing",
            "subcategory":"Retail Goods",
            "type":"Manufacturing & Wholesale Goods"
        }
    ],
    "sg:phone":"+1 406 433 2965",
    "sg:postcode":"59270",
    "sg:province":"MT",
    "sg:tags":[
        "manufacturer"
    ],
    "wof:name":"Richland Yellowstone Mfg",
    "wof:placetype":"venue"
},
  "geometry": {"coordinates":[-104.15116,47.713562],"type":"Point"}
}