{
  "type": "Feature",
  "properties": {
    "iso:country":"US",
    "sg:address":"3120 Sequoia Ln",
    "sg:city":"Billings",
    "sg:classifiers":[
        {
            "category":"Retail",
            "subcategory":"Animal Services",
            "type":"Services"
        }
    ],
    "sg:phone":"+1 406 860 6366",
    "sg:postcode":"59102",
    "sg:province":"MT",
    "sg:tags":[
        "pet",
        "grooming"
    ],
    "wof:name":"Pooch Caboose LLC",
    "wof:placetype":"venue"
},
  "geometry": {"coordinates":[-108.584582,45.800532],"type":"Point"}
}