{
  "type": "Feature",
  "properties": {
    "addr:full":"800 Kensington Ave Missoula MT 59801",
    "addr:housenumber":"800",
    "addr:postcode":"59801",
    "addr:street":"Kensington Ave",
    "iso:country":"US",
    "sg:address":"800 Kensington Ave",
    "sg:city":"Missoula",
    "sg:classifiers":[
        {
            "category":"Manufacturing",
            "subcategory":"Printing",
            "type":"Manufacturing & Wholesale Goods"
        }
    ],
    "sg:phone":"+1 406 549 9846",
    "sg:postcode":"59801",
    "sg:province":"MT",
    "sg:tags":[
        "lithographic",
        "commercial"
    ],
    "wof:name":"Budget Print",
    "wof:placetype":"venue"
},
  "geometry": {"coordinates":[-114.011273,46.853321],"type":"Point"}
}