{
  "type": "Feature",
  "properties": {
    "iso:country":"US",
    "sg:address":"110 N 24th St",
    "sg:city":"Billings",
    "sg:classifiers":[
        {
            "category":"Real Estate",
            "subcategory":"Real Estate Agent",
            "type":"Services"
        }
    ],
    "sg:phone":"+1 406 252 6385",
    "sg:postcode":"59101",
    "sg:province":"MT",
    "wof:name":"O E Lee & Co",
    "wof:placetype":"venue"
},
  "geometry": {"coordinates":[-108.50169699999999,45.785215],"type":"Point"}
}