{
  "type": "Feature",
  "properties": {
    "iso:country":"US",
    "sg:address":"302 1st St W",
    "sg:city":"Polson",
    "sg:classifiers":[
        {
            "category":"Insurance",
            "subcategory":"Insurance Agent",
            "type":"Services"
        }
    ],
    "sg:phone":"+1 406 883 5372",
    "sg:postcode":"59860",
    "sg:province":"MT",
    "wof:name":"Bishop Insurance Service",
    "wof:placetype":"venue"
},
  "geometry": {"coordinates":[-114.164975,47.693394],"type":"Point"}
}