{
  "type": "Feature",
  "properties": {
    "iso:country":"US",
    "sg:address":"609 Central Ave",
    "sg:city":"Great Falls",
    "sg:classifiers":[
        {
            "category":"Real Estate",
            "subcategory":"Real Estate Operator",
            "type":"Services"
        }
    ],
    "sg:phone":"+1 406 727 2478",
    "sg:postcode":"59401",
    "sg:province":"MT",
    "sg:tags":[
        "building",
        "apartment"
    ],
    "wof:name":"Hastings Apts",
    "wof:placetype":"venue"
},
  "geometry": {"coordinates":[-111.295801,47.505424],"type":"Point"}
}