{
  "type": "Feature",
  "properties": {
    "iso:country":"US",
    "sg:address":"117 Boardwalk Dr",
    "sg:city":"Stevensville",
    "sg:classifiers":[
        {
            "category":"Freight",
            "type":"Transportation"
        }
    ],
    "sg:phone":"+1 406 777 3315",
    "sg:postcode":"59870",
    "sg:province":"MT",
    "sg:tags":[
        "operator",
        "local",
        "trucking"
    ],
    "wof:name":"Rex Olson Trucking Inc",
    "wof:placetype":"venue"
},
  "geometry": {"coordinates":[-114.090709,46.496256],"type":"Point"}
}