{
  "type": "Feature",
  "properties": {
    "iso:country":"US",
    "sg:address":"44 Aberdeen St",
    "sg:city":"Glasgow",
    "sg:classifiers":[
        {
            "category":"Building & Trades",
            "subcategory":"Landscaping Services",
            "type":"Services"
        }
    ],
    "sg:phone":"+1 406 228 9263",
    "sg:postcode":"59230",
    "sg:province":"MT",
    "sg:tags":[
        "lawn",
        "maintenance",
        "grounds"
    ],
    "wof:name":"Shipp Contracting",
    "wof:placetype":"venue"
},
  "geometry": {"coordinates":[-106.616741,48.201355],"type":"Point"}
}