{
  "type": "Feature",
  "properties": {
    "iso:country":"US",
    "sg:address":"30 E Washington St",
    "sg:city":"Kalispell",
    "sg:classifiers":[
        {
            "category":"Banks & Credit Unions",
            "subcategory":"Bank",
            "type":"Services"
        }
    ],
    "sg:phone":"+1 406 755 5848",
    "sg:postcode":"59901",
    "sg:province":"MT",
    "sg:tags":[
        "loan",
        "real estate"
    ],
    "wof:name":"Integrity Mortgage",
    "wof:placetype":"venue"
},
  "geometry": {"coordinates":[-114.31425299999999,48.203205],"type":"Point"}
}