{
  "type": "Feature",
  "properties": {
    "iso:country":"US",
    "sg:address":"5908 Eastside Hwy",
    "sg:city":"Florence",
    "sg:classifiers":[
        {
            "category":"Shopping",
            "subcategory":"Hobbies, Toys, & Games",
            "type":"Retail Goods"
        },
        {
            "category":"Shopping",
            "subcategory":"Gifts & Souvenirs",
            "type":"Retail Goods"
        }
    ],
    "sg:phone":"+1 406 273 6332",
    "sg:postcode":"59833",
    "sg:province":"MT",
    "sg:tags":[
        "doll"
    ],
    "sg:website":"www.montanadollhouse.com",
    "wof:name":"Theresa's Dolls & Gifts",
    "wof:placetype":"venue"
},
  "geometry": {"coordinates":[-114.048552,46.632818],"type":"Point"}
}