{
  "type": "Feature",
  "properties": {
    "iso:country":"US",
    "sg:address":"502 S 19th Ave",
    "sg:city":"Bozeman",
    "sg:classifiers":[
        {
            "category":"Building & Trades",
            "subcategory":"Construction",
            "type":"Services"
        }
    ],
    "sg:phone":"+1 406 585 4648",
    "sg:postcode":"59718",
    "sg:province":"MT",
    "sg:tags":[
        "house"
    ],
    "wof:name":"Elephant Builders Inc",
    "wof:placetype":"venue"
},
  "geometry": {"coordinates":[-111.062614,45.674269],"type":"Point"}
}