{
  "type": "Feature",
  "properties": {
    "addr:full":"739 Hollibaugh Rd Stevensville MT 59870",
    "addr:housenumber":"739",
    "addr:postcode":"59870",
    "addr:street":"Hollibaugh Rd",
    "iso:country":"US",
    "sg:address":"739 Hollibaugh Rd",
    "sg:city":"Stevensville",
    "sg:classifiers":[
        {
            "category":"Farming",
            "subcategory":"Livestock Farm",
            "type":"Manufacturing & Wholesale Goods"
        }
    ],
    "sg:phone":"+1 406 777 7107",
    "sg:postcode":"59870",
    "sg:province":"MT",
    "sg:tags":[
        "animal",
        "general"
    ],
    "wof:name":"Pronk Ave LLC",
    "wof:placetype":"venue"
},
  "geometry": {"coordinates":[-114.032347,46.519075],"type":"Point"}
}