{
  "type": "Feature",
  "properties": {
    "iso:country":"US",
    "sg:address":"217 N 3rd St",
    "sg:city":"Hamilton",
    "sg:classifiers":[
        {
            "category":"Social Services",
            "type":"Services"
        }
    ],
    "sg:phone":"+1 406 363 3882",
    "sg:postcode":"59840",
    "sg:province":"MT",
    "sg:tags":[
        "family",
        "specialty",
        "outpatient",
        "clinic",
        "marriage",
        "counselor"
    ],
    "wof:name":"Bitterroot Valley Counseling",
    "wof:placetype":"venue"
},
  "geometry": {"coordinates":[-114.158939,46.248861],"type":"Point"}
}