{
  "type": "Feature",
  "properties": {
    "iso:country":"US",
    "sg:address":"1314 Front St",
    "sg:city":"Fort Benton",
    "sg:classifiers":[
        {
            "category":"Sports & Exercise",
            "subcategory":"Bowling",
            "type":"Entertainment"
        }
    ],
    "sg:phone":"+1 406 622 5040",
    "sg:postcode":"59442",
    "sg:province":"MT",
    "sg:tags":[
        "center"
    ],
    "wof:name":"Jack's Bar & Lanes LLC",
    "wof:placetype":"venue"
},
  "geometry": {"coordinates":[-110.668451,47.816503],"type":"Point"}
}