{
  "type": "Feature",
  "properties": {
    "iso:country":"US",
    "sg:address":"24 S Willson Ave",
    "sg:city":"Bozeman",
    "sg:classifiers":[
        {
            "category":"Organizations",
            "subcategory":"Professional Association",
            "type":"Services"
        }
    ],
    "sg:phone":"+1 406 585 7513",
    "sg:postcode":"59715",
    "sg:province":"MT",
    "sg:tags":[
        "health"
    ],
    "wof:name":"Tamara Nelson",
    "wof:placetype":"venue"
},
  "geometry": {"coordinates":[-111.038692,45.679019],"type":"Point"}
}