{
  "type": "Feature",
  "properties": {
    "addr:full":"2625 S Hills Dr Missoula MT 59803",
    "addr:housenumber":"2625",
    "addr:postcode":"59803",
    "addr:street":"S Hills Dr",
    "iso:country":"US",
    "sg:address":"2625 S Hills Dr",
    "sg:city":"Missoula",
    "sg:classifiers":[
        {
            "category":"Education",
            "subcategory":"Special Training",
            "type":"Public Place"
        }
    ],
    "sg:phone":"+1 406 251 3473",
    "sg:postcode":"59803",
    "sg:province":"MT",
    "sg:tags":[
        "consulting",
        "business"
    ],
    "wof:name":"Montana Sorbonne Abacus Inst",
    "wof:placetype":"venue"
},
  "geometry": {"coordinates":[-114.044603,46.825543],"type":"Point"}
}