{
  "type": "Feature",
  "properties": {
    "addr:full":"3801 Brooks St Missoula MT 59804",
    "addr:housenumber":"3801",
    "addr:postcode":"59804",
    "addr:street":"Brooks St",
    "iso:country":"US",
    "sg:address":"3801 Brooks St",
    "sg:city":"Missoula",
    "sg:classifiers":[
        {
            "category":"Restaurant",
            "type":"Food & Drink"
        }
    ],
    "sg:phone":"+1 406 251 5882",
    "sg:postcode":"59804",
    "sg:province":"MT",
    "sg:tags":[
        "eating"
    ],
    "wof:name":"4 B S Family Restaurant",
    "wof:placetype":"venue"
},
  "geometry": {"coordinates":[-114.04468199999999,46.834714],"type":"Point"}
}