{
  "type": "Feature",
  "properties": {
    "iso:country":"US",
    "sg:address":"602 1st Ave SW",
    "sg:city":"Wibaux",
    "sg:classifiers":[
        {
            "category":"Professional",
            "type":"Services"
        }
    ],
    "sg:phone":"+1 406 796 2530",
    "sg:postcode":"59353",
    "sg:province":"MT",
    "sg:tags":[
        "establishment"
    ],
    "wof:name":"Nunberg & Nunberg",
    "wof:placetype":"venue"
},
  "geometry": {"coordinates":[-104.196482,46.987277],"type":"Point"}
}