{
  "type": "Feature",
  "properties": {
    "addr:full":"532 Fairview Ln Laurel MT 59044",
    "addr:housenumber":"532",
    "addr:postcode":"59044",
    "addr:street":"Fairview Ln",
    "iso:country":"US",
    "sg:address":"532 Fairview Ln",
    "sg:city":"Laurel",
    "sg:classifiers":[
        {
            "category":"Wholesale",
            "subcategory":"Durable Goods & Equipment",
            "type":"Manufacturing & Wholesale Goods"
        }
    ],
    "sg:phone":"+1 406 628 1382",
    "sg:postcode":"59044",
    "sg:province":"MT",
    "wof:name":"Tdl Industries Inc",
    "wof:placetype":"venue"
},
  "geometry": {"coordinates":[-108.77913100000001,45.683242],"type":"Point"}
}