{
  "type": "Feature",
  "properties": {
    "addr:full":"545 Somers Stage Rd Kalispell MT 59901",
    "addr:housenumber":"545",
    "addr:postcode":"59901",
    "addr:street":"Somers Stage Rd",
    "iso:country":"US",
    "sg:address":"545 Somers Stage Rd",
    "sg:city":"Kalispell",
    "sg:phone":"+1 406 752 3591",
    "sg:postcode":"59901",
    "sg:province":"MT",
    "sg:tags":[
        "farm",
        "grain",
        "cash"
    ],
    "wof:name":"Ray Sanders Farm",
    "wof:placetype":"venue"
},
  "geometry": {"coordinates":[-114.24484699999999,48.134813],"type":"Point"}
}