{
  "type": "Feature",
  "properties": {
    "iso:country":"US",
    "sg:address":"2088 S US Hwy 2",
    "sg:city":"Libby",
    "sg:classifiers":[
        {
            "category":"Shopping",
            "subcategory":"Used Merchandise",
            "type":"Retail Goods"
        }
    ],
    "sg:phone":"+1 406 293 3492",
    "sg:postcode":"59923",
    "sg:province":"MT",
    "wof:name":"Twice But Nice",
    "wof:placetype":"venue"
},
  "geometry": {"coordinates":[-115.536974,48.362661],"type":"Point"}
}