{
  "type": "Feature",
  "properties": {
    "iso:country":"US",
    "sg:address":"1034 Princeton Ave",
    "sg:city":"Billings",
    "sg:classifiers":[
        {
            "category":"Real Estate",
            "subcategory":"Real Estate Operator",
            "type":"Services"
        }
    ],
    "sg:phone":"+1 406 248 3307",
    "sg:postcode":"59102",
    "sg:province":"MT",
    "sg:tags":[
        "building",
        "apartment"
    ],
    "wof:name":"Mueller Rentals",
    "wof:placetype":"venue"
},
  "geometry": {"coordinates":[-108.542683,45.796867],"type":"Point"}
}