{
  "type": "Feature",
  "properties": {
    "addr:full":"135 Rye Dr Butte MT 59701",
    "addr:housenumber":"135",
    "addr:postcode":"mt 59701",
    "addr:street":"Rye Dr",
    "iso:country":"US",
    "sg:address":"135 Rye Dr",
    "sg:city":"Butte",
    "sg:classifiers":[
        {
            "category":"Building & Trades",
            "subcategory":"Construction",
            "type":"Services"
        }
    ],
    "sg:phone":"+1 406 494 3836",
    "sg:postcode":"59701",
    "sg:province":"MT",
    "sg:tags":[
        "nonresidential"
    ],
    "wof:name":"Project Green of Montana",
    "wof:placetype":"venue"
},
  "geometry": {"coordinates":[-112.468898,45.915694],"type":"Point"}
}