{
  "type": "Feature",
  "properties": {
    "iso:country":"US",
    "sg:address":"1020 S 3rd Ave",
    "sg:city":"Bozeman",
    "sg:classifiers":[
        {
            "category":"Manufacturing",
            "subcategory":"Buildings",
            "type":"Manufacturing & Wholesale Goods"
        }
    ],
    "sg:phone":"+1 406 587 4948",
    "sg:postcode":"59715",
    "sg:province":"MT",
    "sg:tags":[
        "prefabricated",
        "wood",
        "mfg"
    ],
    "wof:name":"Gone Beaver Handcraft Logs",
    "wof:placetype":"venue"
},
  "geometry": {"coordinates":[-111.041636,45.668961],"type":"Point"}
}