{
  "type": "Feature",
  "properties": {
    "iso:country":"US",
    "sg:address":"2040 Fox Rd",
    "sg:city":"Laurel",
    "sg:classifiers":[
        {
            "category":"Manufacturing",
            "subcategory":"Tools & Machinery",
            "type":"Manufacturing & Wholesale Goods"
        }
    ],
    "sg:phone":"+1 406 628 4147",
    "sg:postcode":"59044",
    "sg:province":"MT",
    "sg:tags":[
        "machine",
        "shop"
    ],
    "wof:name":"Weber & Sons Inc",
    "wof:placetype":"venue"
},
  "geometry": {"coordinates":[-108.756648,45.702897],"type":"Point"}
}