{
  "type": "Feature",
  "properties": {
    "addr:full":"102 N Alabama St Butte MT 59701",
    "addr:housenumber":"102",
    "addr:postcode":"mt 59701",
    "addr:street":"N Alabama St",
    "iso:country":"US",
    "sg:address":"102 N Alabama St",
    "sg:city":"Butte",
    "sg:classifiers":[
        {
            "category":"Professional",
            "subcategory":"Engineering",
            "type":"Services"
        }
    ],
    "sg:phone":"+1 406 782 3441",
    "sg:postcode":"59701",
    "sg:province":"MT",
    "sg:tags":[
        "engineer"
    ],
    "wof:name":"Kuipers & Associates",
    "wof:placetype":"venue"
},
  "geometry": {"coordinates":[-112.54745699999999,46.01386],"type":"Point"}
}