{
  "type": "Feature",
  "properties": {
    "addr:full":"420 W Koch St Bozeman MT 59715",
    "addr:housenumber":"420",
    "addr:postcode":"59715",
    "addr:street":"W Koch St",
    "iso:country":"US",
    "sg:address":"420 W Koch St",
    "sg:city":"Bozeman",
    "sg:classifiers":[
        {
            "category":"Travel",
            "subcategory":"Travel Agent",
            "type":"Entertainment"
        }
    ],
    "sg:phone":"+1 406 585 5356",
    "sg:postcode":"59715",
    "sg:province":"MT",
    "sg:tags":[
        "operator",
        "tour",
        "agency"
    ],
    "wof:name":"Crossing Latitudes Inc",
    "wof:placetype":"venue"
},
  "geometry": {"coordinates":[-111.0437,45.67522],"type":"Point"}
}