{
  "type": "Feature",
  "properties": {
    "addr:full":"414 1st St E Polson MT 59860",
    "addr:housenumber":"414",
    "addr:postcode":"59860",
    "addr:street":"1St St E",
    "iso:country":"US",
    "sg:address":"414 1st St E",
    "sg:city":"Polson",
    "sg:classifiers":[
        {
            "category":"Social Services",
            "type":"Services"
        }
    ],
    "sg:phone":"+1 406 883 0777",
    "sg:postcode":"59860",
    "sg:province":"MT",
    "wof:name":"Janice Lundeen Lcsw",
    "wof:placetype":"venue"
},
  "geometry": {"coordinates":[-114.161912,47.692168],"type":"Point"}
}