{
  "type": "Feature",
  "properties": {
    "iso:country":"US",
    "sg:address":"1547 US Hwy 212 S",
    "sg:city":"Laurel",
    "sg:classifiers":[
        {
            "category":"Retail",
            "subcategory":"Auto Repair",
            "type":"Services"
        }
    ],
    "sg:phone":"+1 406 628 6901",
    "sg:postcode":"59044",
    "sg:province":"MT",
    "sg:tags":[
        "automotive"
    ],
    "wof:name":"Big Sky Radiator & Wrecker",
    "wof:placetype":"venue"
},
  "geometry": {"coordinates":[-108.756799,45.650501],"type":"Point"}
}