{
  "type": "Feature",
  "properties": {
    "addr:full":"2820 Spurgin Rd Missoula MT 59804",
    "addr:housenumber":"2820",
    "addr:postcode":"59804",
    "addr:street":"Spurgin Rd",
    "iso:country":"US",
    "sg:address":"2820 Spurgin Rd",
    "sg:city":"Missoula",
    "sg:classifiers":[
        {
            "category":"Manufacturing",
            "subcategory":"Tools & Machinery",
            "type":"Manufacturing & Wholesale Goods"
        }
    ],
    "sg:phone":"+1 406 721 6214",
    "sg:postcode":"59804",
    "sg:province":"MT",
    "sg:tags":[
        "instrument",
        "mfg"
    ],
    "wof:name":"Body In Balance LLC",
    "wof:placetype":"venue"
},
  "geometry": {"coordinates":[-114.04885,46.859708],"type":"Point"}
}