{
  "type": "Feature",
  "properties": {
    "addr:full":"316 E Reserve Dr Kalispell MT 59901",
    "addr:housenumber":"316",
    "addr:postcode":"59901",
    "addr:street":"E Reserve Dr",
    "iso:country":"US",
    "sg:address":"316 E Reserve Dr",
    "sg:city":"Kalispell",
    "sg:classifiers":[
        {
            "category":"Manufacturing",
            "subcategory":"Retail Goods",
            "type":"Manufacturing & Wholesale Goods"
        }
    ],
    "sg:phone":"+1 406 752 5275",
    "sg:postcode":"59901",
    "sg:province":"MT",
    "sg:tags":[
        "commercial",
        "lead",
        "mfg"
    ],
    "wof:name":"Toby Mercer",
    "wof:placetype":"venue"
},
  "geometry": {"coordinates":[-114.265739,48.24036],"type":"Point"}
}