{
  "type": "Feature",
  "properties": {
    "iso:country":"US",
    "sg:address":"8846 US Hwy 287",
    "sg:city":"Toston",
    "sg:classifiers":[
        {
            "category":"Bars & Pubs",
            "type":"Food & Drink"
        }
    ],
    "sg:phone":"+1 406 266 5302",
    "sg:postcode":"59643",
    "sg:province":"MT",
    "sg:tags":[
        "drinking"
    ],
    "wof:name":"Bunk House Bar",
    "wof:placetype":"venue"
},
  "geometry": {"coordinates":[-111.449191,46.169197],"type":"Point"}
}