{
  "type": "Feature",
  "properties": {
    "iso:country":"US",
    "sg:address":"922 Grand Ave",
    "sg:city":"Billings",
    "sg:classifiers":[
        {
            "category":"Shopping",
            "subcategory":"Musical Instruments",
            "type":"Retail Goods"
        }
    ],
    "sg:phone":"+1 406 252 2604",
    "sg:postcode":"59102",
    "sg:province":"MT",
    "wof:name":"Eckroth Music Co",
    "wof:placetype":"venue"
},
  "geometry": {"coordinates":[-108.540432,45.783987],"type":"Point"}
}