{
  "type": "Feature",
  "properties": {
    "iso:country":"US",
    "sg:address":"100 Critter Way",
    "sg:city":"Victor",
    "sg:classifiers":[
        {
            "category":"Freight",
            "type":"Transportation"
        }
    ],
    "sg:phone":"+1 406 642 3471",
    "sg:postcode":"59875",
    "sg:province":"MT",
    "sg:tags":[
        "special"
    ],
    "wof:name":"Mini Storage Corral",
    "wof:placetype":"venue"
},
  "geometry": {"coordinates":[-114.14609,46.423089],"type":"Point"}
}