{
  "type": "Feature",
  "properties": {
    "iso:country":"US",
    "sg:address":"5 Gallatin Field Rd",
    "sg:city":"Belgrade",
    "sg:classifiers":[
        {
            "category":"Retail",
            "subcategory":"Auto Rental",
            "type":"Services"
        }
    ],
    "sg:phone":"+1 406 388 6694",
    "sg:postcode":"59714",
    "sg:province":"MT",
    "sg:tags":[
        "passenger",
        "car"
    ],
    "wof:name":"National Car Rental",
    "wof:placetype":"venue"
},
  "geometry": {"coordinates":[-111.15660200000001,45.772232],"type":"Point"}
}