{
  "type": "Feature",
  "properties": {
    "addr:full":"224 Mc Leod St Big Timber MT 59011",
    "addr:housenumber":"224",
    "addr:postcode":"59011",
    "addr:street":"Mc Leod St",
    "iso:country":"US",
    "sg:address":"224 Mc Leod St",
    "sg:city":"Big Timber",
    "sg:classifiers":[
        {
            "category":"Real Estate",
            "subcategory":"Real Estate Agent",
            "type":"Services"
        }
    ],
    "sg:phone":"+1 406 932 5805",
    "sg:postcode":"59011",
    "sg:province":"MT",
    "sg:website":"www.mlproperties.com",
    "wof:name":"M L Properties",
    "wof:placetype":"venue"
},
  "geometry": {"coordinates":[-109.954319,45.833881],"type":"Point"}
}