{
  "type": "Feature",
  "properties": {
    "addr:full":"414 E Babcock St Bozeman MT 59715",
    "addr:housenumber":"414",
    "addr:postcode":"59715",
    "addr:street":"E Babcock St",
    "iso:country":"US",
    "sg:address":"414 E Babcock St",
    "sg:city":"Bozeman",
    "sg:classifiers":[
        {
            "category":"Sports & Exercise",
            "subcategory":"Bowling",
            "type":"Entertainment"
        }
    ],
    "sg:phone":"+1 406 586 5018",
    "sg:postcode":"59715",
    "sg:province":"MT",
    "sg:tags":[
        "lounge",
        "alley"
    ],
    "wof:name":"Bozeman Bowl The",
    "wof:placetype":"venue"
},
  "geometry": {"coordinates":[-111.031885,45.678244],"type":"Point"}
}