{
  "type": "Feature",
  "properties": {
    "addr:full":"2900 S Reserve St Missoula MT 59801",
    "addr:housenumber":"2900",
    "addr:postcode":"59801",
    "addr:street":"S Reserve St",
    "iso:country":"US",
    "sg:address":"2900 S Reserve St",
    "sg:city":"Missoula",
    "sg:classifiers":[
        {
            "category":"Retail",
            "subcategory":"Animal Services",
            "type":"Services"
        }
    ],
    "sg:phone":"+1 406 728 8500",
    "sg:postcode":"59801",
    "sg:province":"MT",
    "wof:name":"Jorgenson Arlene Pet Grooming",
    "wof:placetype":"venue"
},
  "geometry": {"coordinates":[-114.039565,46.843347],"type":"Point"}
}