{
  "type": "Feature",
  "properties": {
    "iso:country":"US",
    "sg:address":"1847 Bender St",
    "sg:city":"Billings",
    "sg:classifiers":[
        {
            "category":"Social Services",
            "subcategory":"Child Care",
            "type":"Services"
        }
    ],
    "sg:phone":"+1 406 252 7878",
    "sg:postcode":"59105",
    "sg:province":"MT",
    "sg:tags":[
        "day"
    ],
    "wof:name":"Bonnie's House Inc",
    "wof:placetype":"venue"
},
  "geometry": {"coordinates":[-108.467069,45.832151],"type":"Point"}
}