{
  "type": "Feature",
  "properties": {
    "iso:country":"US",
    "sg:address":"2418 S 7th St W",
    "sg:city":"Missoula",
    "sg:phone":"+1 406 543 5061",
    "sg:postcode":"59801",
    "sg:province":"MT",
    "sg:tags":[
        "farm"
    ],
    "wof:name":"Benson Farm",
    "wof:placetype":"venue"
},
  "geometry": {"coordinates":[-114.035295,46.863295],"type":"Point"}
}