{
  "type": "Feature",
  "properties": {
    "iso:country":"US",
    "sg:address":"1651 Oklahoma Star Trl",
    "sg:city":"Billings",
    "sg:classifiers":[
        {
            "category":"Building & Trades",
            "subcategory":"Construction",
            "type":"Services"
        }
    ],
    "sg:phone":"+1 406 256 8844",
    "sg:postcode":"59105",
    "sg:province":"MT",
    "sg:tags":[
        "house"
    ],
    "wof:name":"Specialized Construction Inc",
    "wof:placetype":"venue"
},
  "geometry": {"coordinates":[-108.44031,45.854538],"type":"Point"}
}