{
  "type": "Feature",
  "properties": {
    "iso:country":"US",
    "sg:address":"500 E Spruce St",
    "sg:city":"Missoula",
    "sg:classifiers":[
        {
            "category":"Home & Garden",
            "subcategory":"Furniture",
            "type":"Retail Goods"
        }
    ],
    "sg:phone":"+1 406 728 7525",
    "sg:postcode":"59802",
    "sg:province":"MT",
    "wof:name":"Volkmann Desgr Craftsman In WD",
    "wof:placetype":"venue"
},
  "geometry": {"coordinates":[-113.987011,46.872304],"type":"Point"}
}