{
  "type": "Feature",
  "properties": {
    "iso:country":"US",
    "sg:address":"18 E Quartz St",
    "sg:city":"Butte",
    "sg:classifiers":[
        {
            "category":"Building & Trades",
            "subcategory":"Construction",
            "type":"Services"
        }
    ],
    "sg:phone":"+1 406 490 7789",
    "sg:postcode":"59701",
    "sg:province":"MT",
    "sg:tags":[
        "roofing",
        "contractor"
    ],
    "wof:name":"Lifetime Roofs",
    "wof:placetype":"venue"
},
  "geometry": {"coordinates":[-112.53401599999999,46.015352],"type":"Point"}
}