{
  "type": "Feature",
  "properties": {
    "addr:full":"3307 Grand Ave Billings MT 59102",
    "addr:housenumber":"3307",
    "addr:postcode":"59102",
    "addr:street":"Grand Ave",
    "iso:country":"US",
    "sg:address":"3307 Grand Ave",
    "sg:city":"Billings",
    "sg:classifiers":[
        {
            "category":"Building & Trades",
            "subcategory":"Construction",
            "type":"Services"
        }
    ],
    "sg:phone":"+1 406 256 8200",
    "sg:postcode":"59102",
    "sg:province":"MT",
    "sg:tags":[
        "general",
        "contractor"
    ],
    "wof:name":"Treasure State Electric",
    "wof:placetype":"venue"
},
  "geometry": {"coordinates":[-108.59793999999999,45.784171],"type":"Point"}
}