{
  "type": "Feature",
  "properties": {
    "iso:country":"US",
    "sg:address":"2304 N 7th Ave",
    "sg:city":"Bozeman",
    "sg:classifiers":[
        {
            "category":"Personal",
            "subcategory":"Beauty Salon",
            "type":"Services"
        },
        {
            "category":"Sports & Exercise",
            "subcategory":"Gym",
            "type":"Entertainment"
        }
    ],
    "sg:phone":"+1 406 522 9009",
    "sg:postcode":"59715",
    "sg:province":"MT",
    "sg:tags":[
        "fitness",
        "establishment",
        "physical",
        "facility"
    ],
    "sg:website":"www.jevosalon.com",
    "wof:name":"Je Vo Salon & Day Spa",
    "wof:placetype":"venue"
},
  "geometry": {"coordinates":[-111.046087,45.701472],"type":"Point"}
}