{
  "type": "Feature",
  "properties": {
    "addr:full":"116 1st Ave N Antelope MT 59211",
    "addr:housenumber":"116",
    "addr:postcode":"59211",
    "addr:street":"1St Ave N",
    "iso:country":"US",
    "sg:address":"116 1st Ave N",
    "sg:city":"Antelope",
    "sg:classifiers":[
        {
            "category":"Insurance",
            "subcategory":"Insurance Agent",
            "type":"Services"
        }
    ],
    "sg:phone":"+1 406 286 5214",
    "sg:postcode":"59211",
    "sg:province":"MT",
    "wof:name":"Reliastar",
    "wof:placetype":"venue"
},
  "geometry": {"coordinates":[-104.456277,48.690341],"type":"Point"}
}