{
  "type": "Feature",
  "properties": {
    "iso:country":"US",
    "sg:address":"16873 Beckwith St",
    "sg:city":"Frenchtown",
    "sg:classifiers":[
        {
            "category":"Travel",
            "subcategory":"Hotels & Motels",
            "type":"Entertainment"
        }
    ],
    "sg:phone":"+1 406 626 4006",
    "sg:postcode":"59834",
    "sg:province":"MT",
    "sg:tags":[
        "operation"
    ],
    "wof:name":"French Cnnection Casino Lounge",
    "wof:placetype":"venue"
},
  "geometry": {"coordinates":[-114.229422,47.014884],"type":"Point"}
}