{
  "type": "Feature",
  "properties": {
    "iso:country":"US",
    "sg:address":"1196 Canyon Mill Rd",
    "sg:city":"Ronan",
    "sg:classifiers":[
        {
            "category":"Professional",
            "subcategory":"Business Services",
            "type":"Services"
        }
    ],
    "sg:phone":"+1 406 676 5515",
    "sg:postcode":"59864",
    "sg:province":"MT",
    "wof:name":"Trosper Appraisals Inc",
    "wof:placetype":"venue"
},
  "geometry": {"coordinates":[-114.07050599999999,47.558738],"type":"Point"}
}