{
  "type": "Feature",
  "properties": {
    "iso:country":"US",
    "sg:address":"301 S Main St",
    "sg:city":"Conrad",
    "sg:classifiers":[
        {
            "category":"Autos & Motor Vehicles",
            "subcategory":"Fuel & Gas Station",
            "type":"Retail Goods"
        }
    ],
    "sg:phone":"+1 406 278 5213",
    "sg:postcode":"59425",
    "sg:province":"MT",
    "sg:tags":[
        "oil"
    ],
    "wof:name":"Tom's Exxon",
    "wof:placetype":"venue"
},
  "geometry": {"coordinates":[-111.946135,48.170269],"type":"Point"}
}