{
  "type": "Feature",
  "properties": {
    "iso:country":"US",
    "sg:address":"2100 Fairway Dr",
    "sg:city":"Bozeman",
    "sg:classifiers":[
        {
            "category":"Professional",
            "subcategory":"Computer Services",
            "type":"Services"
        }
    ],
    "sg:phone":"+1 406 586 2674",
    "sg:postcode":"59715",
    "sg:province":"MT",
    "sg:tags":[
        "programing",
        "custom"
    ],
    "wof:name":"Design Services",
    "wof:placetype":"venue"
},
  "geometry": {"coordinates":[-111.03612800000001,45.654244],"type":"Point"}
}