{
  "type": "Feature",
  "properties": {
    "iso:country":"US",
    "sg:address":"1550 Mountain Meadow Rd",
    "sg:city":"Kalispell",
    "sg:classifiers":[
        {
            "category":"Organizations",
            "subcategory":"Religious Organization",
            "type":"Services"
        }
    ],
    "sg:phone":"+1 406 756 8844",
    "sg:postcode":"59901",
    "sg:province":"MT",
    "wof:name":"Restoration International",
    "wof:placetype":"venue"
},
  "geometry": {"coordinates":[-114.502926,48.320644],"type":"Point"}
}