{
  "type": "Feature",
  "properties": {
    "iso:country":"US",
    "sg:address":"310 E Railroad Ave",
    "sg:city":"Plains",
    "sg:classifiers":[
        {
            "category":"Food & Beverages",
            "subcategory":"Specialty",
            "type":"Retail Goods"
        }
    ],
    "sg:phone":"+1 406 826 3400",
    "sg:postcode":"59859",
    "sg:province":"MT",
    "sg:tags":[
        "health",
        "diet"
    ],
    "wof:name":"Honeysuckle Natural Foods",
    "wof:placetype":"venue"
},
  "geometry": {"coordinates":[-114.878618,47.45627],"type":"Point"}
}