{
  "type": "Feature",
  "properties": {
    "iso:country":"US",
    "sg:address":"94 Willow Dr",
    "sg:city":"Livingston",
    "sg:classifiers":[
        {
            "category":"Professional",
            "type":"Services"
        }
    ],
    "sg:phone":"+1 406 222 3421",
    "sg:postcode":"59047",
    "sg:province":"MT",
    "wof:name":"Boyer Bronze",
    "wof:placetype":"venue"
},
  "geometry": {"coordinates":[-110.57766100000001,45.640627],"type":"Point"}
}