{
  "type": "Feature",
  "properties": {
    "iso:country":"US",
    "sg:address":"220 6th St S",
    "sg:city":"Great Falls",
    "sg:classifiers":[
        {
            "category":"Real Estate",
            "subcategory":"Real Estate Agent",
            "type":"Services"
        }
    ],
    "sg:phone":"+1 406 761 8865",
    "sg:postcode":"59405",
    "sg:province":"MT",
    "wof:name":"James Co Realty Inc",
    "wof:placetype":"venue"
},
  "geometry": {"coordinates":[-111.297369,47.502188],"type":"Point"}
}