{
  "type": "Feature",
  "properties": {
    "addr:full":"219 S Idaho St Dillon MT 59725",
    "addr:housenumber":"219",
    "addr:postcode":"59725",
    "addr:street":"S Idaho St",
    "iso:country":"US",
    "sg:address":"219 S Idaho St",
    "sg:city":"Dillon",
    "sg:classifiers":[
        {
            "category":"Personal",
            "subcategory":"Beauty Salon",
            "type":"Services"
        }
    ],
    "sg:phone":"+1 406 683 9636",
    "sg:postcode":"59725",
    "sg:province":"MT",
    "sg:tags":[
        "shop"
    ],
    "wof:name":"Hair Depot",
    "wof:placetype":"venue"
},
  "geometry": {"coordinates":[-112.638384,45.21563],"type":"Point"}
}