{
  "type": "Feature",
  "properties": {
    "iso:country":"US",
    "sg:address":"206 Meany St",
    "sg:city":"Plains",
    "sg:classifiers":[
        {
            "category":"Organizations",
            "subcategory":"Religious Organization",
            "type":"Services"
        }
    ],
    "sg:phone":"+1 406 826 3526",
    "sg:postcode":"59859",
    "sg:province":"MT",
    "sg:tags":[
        "church"
    ],
    "wof:name":"United Methodist Church-Plains",
    "wof:placetype":"venue"
},
  "geometry": {"coordinates":[-114.88295100000001,47.456995],"type":"Point"}
}