{
  "type": "Feature",
  "properties": {
    "iso:country":"US",
    "sg:address":"2 W Main St",
    "sg:city":"Bozeman",
    "sg:classifiers":[
        {
            "category":"Shopping",
            "subcategory":"Clothing, Apparel, & Fashions",
            "type":"Retail Goods"
        }
    ],
    "sg:phone":"+1 406 587 5521",
    "sg:postcode":"59715",
    "sg:province":"MT",
    "sg:tags":[
        "cards",
        "book",
        "jew",
        "gift",
        "greeting"
    ],
    "wof:name":"Odyssey",
    "wof:placetype":"venue"
},
  "geometry": {"coordinates":[-111.038764,45.679263],"type":"Point"}
}