{
  "type": "Feature",
  "properties": {
    "iso:country":"US",
    "sg:address":"273 Flynn Ln",
    "sg:city":"Townsend",
    "sg:phone":"+1 406 266 3578",
    "sg:postcode":"59644",
    "sg:province":"MT",
    "sg:tags":[
        "farm",
        "field",
        "grain",
        "cash",
        "crop"
    ],
    "wof:name":"Flynn Hay & Grain",
    "wof:placetype":"venue"
},
  "geometry": {"coordinates":[-111.451476,46.259121],"type":"Point"}
}