{
  "type": "Feature",
  "properties": {
    "iso:country":"US",
    "sg:address":"280 1st Ln NE",
    "sg:city":"Fairfield",
    "sg:classifiers":[
        {
            "category":"Wholesale",
            "subcategory":"Machinery & Supplies",
            "type":"Manufacturing & Wholesale Goods"
        }
    ],
    "sg:phone":"+1 406 467 2619",
    "sg:postcode":"59436",
    "sg:province":"MT",
    "sg:tags":[
        "equipment",
        "irrigation",
        "system"
    ],
    "wof:name":"Teton Irrigation Svc",
    "wof:placetype":"venue"
},
  "geometry": {"coordinates":[-111.966093,47.652332],"type":"Point"}
}