{
  "type": "Feature",
  "properties": {
    "iso:country":"US",
    "sg:address":"2135 S 3rd St W",
    "sg:city":"Missoula",
    "sg:classifiers":[
        {
            "category":"Building & Trades",
            "subcategory":"Construction",
            "type":"Services"
        }
    ],
    "sg:phone":"+1 406 728 8112",
    "sg:postcode":"59801",
    "sg:province":"MT",
    "sg:tags":[
        "fencing",
        "siding",
        "contractor",
        "panel",
        "mfg"
    ],
    "wof:name":"Cedar Mini Storage",
    "wof:placetype":"venue"
},
  "geometry": {"coordinates":[-114.031952,46.866853],"type":"Point"}
}