{
  "type": "Feature",
  "properties": {
    "iso:country":"US",
    "sg:address":"1517 N Dodge Ave",
    "sg:city":"Helena",
    "sg:classifiers":[
        {
            "category":"Manufacturing",
            "subcategory":"Chemicals & Compounds",
            "type":"Manufacturing & Wholesale Goods"
        }
    ],
    "sg:phone":"+1 406 442 7650",
    "sg:postcode":"59601",
    "sg:province":"MT",
    "sg:tags":[
        "paint",
        "mfg"
    ],
    "wof:name":"Columbia Paint & Coatings",
    "wof:placetype":"venue"
},
  "geometry": {"coordinates":[-112.021936,46.600621],"type":"Point"}
}