{
  "type": "Feature",
  "properties": {
    "addr:full":"2615 US Hwy 2 E Kalispell MT 59901",
    "addr:housenumber":"2615",
    "addr:postcode":"59901",
    "addr:street":"Us Hwy 2 E",
    "iso:country":"US",
    "sg:address":"2615 US Hwy 2 E",
    "sg:city":"Kalispell",
    "sg:classifiers":[
        {
            "category":"Restaurant",
            "type":"Food & Drink"
        }
    ],
    "sg:phone":"+1 406 756 3234",
    "sg:postcode":"59901",
    "sg:province":"MT",
    "sg:tags":[
        "eating"
    ],
    "wof:name":"Wendys",
    "wof:placetype":"venue"
},
  "geometry": {"coordinates":[-114.276173,48.242268],"type":"Point"}
}