{
  "type": "Feature",
  "properties": {
    "iso:country":"US",
    "sg:address":"1817 Banks Ave",
    "sg:city":"Butte",
    "sg:classifiers":[
        {
            "category":"Building & Trades",
            "subcategory":"Construction",
            "type":"Services"
        }
    ],
    "sg:phone":"+1 406 723 2124",
    "sg:postcode":"59701",
    "sg:province":"MT",
    "sg:tags":[
        "house",
        "general",
        "contractor"
    ],
    "wof:name":"Stillwagon Construction LLC",
    "wof:placetype":"venue"
},
  "geometry": {"coordinates":[-112.49412599999999,45.996632],"type":"Point"}
}