{
  "type": "Feature",
  "properties": {
    "iso:country":"US",
    "sg:address":"401 N 31st St",
    "sg:city":"Billings",
    "sg:classifiers":[
        {
            "category":"Insurance",
            "subcategory":"Insurance Agent",
            "type":"Services"
        }
    ],
    "sg:phone":"+1 406 255 6300",
    "sg:postcode":"59101",
    "sg:province":"MT",
    "sg:website":"www.newyorklife.com",
    "wof:name":"New York Life Insurance Co",
    "wof:placetype":"venue"
},
  "geometry": {"coordinates":[-108.513693,45.784617],"type":"Point"}
}