{
  "type": "Feature",
  "properties": {
    "iso:country":"US",
    "sg:address":"1010 Grand Ave",
    "sg:city":"Billings",
    "sg:classifiers":[
        {
            "category":"Shopping",
            "subcategory":"Florist",
            "type":"Retail Goods"
        }
    ],
    "sg:phone":"+1 406 245 1333",
    "sg:postcode":"59102",
    "sg:province":"MT",
    "wof:name":"Flowers From The Heart",
    "wof:placetype":"venue"
},
  "geometry": {"coordinates":[-108.543222,45.78398],"type":"Point"}
}