{
  "type": "Feature",
  "properties": {
    "iso:country":"US",
    "sg:address":"834 Ridge Rd",
    "sg:city":"Stevensville",
    "sg:classifiers":[
        {
            "category":"Farming",
            "subcategory":"Livestock Farm",
            "type":"Manufacturing & Wholesale Goods"
        }
    ],
    "sg:phone":"+1 406 777 3349",
    "sg:postcode":"59870",
    "sg:province":"MT",
    "sg:tags":[
        "animal",
        "general"
    ],
    "wof:name":"El Costa Lota Ranch",
    "wof:placetype":"venue"
},
  "geometry": {"coordinates":[-113.98017,46.580869],"type":"Point"}
}