{
  "type": "Feature",
  "properties": {
    "addr:full":"1200 Westwood Dr Hamilton MT 59840",
    "addr:housenumber":"1200",
    "addr:postcode":"59840",
    "addr:street":"Westwood Dr",
    "iso:country":"US",
    "sg:address":"1200 Westwood Dr",
    "sg:city":"Hamilton",
    "sg:classifiers":[
        {
            "category":"Health Services",
            "subcategory":"Doctor",
            "type":"Services"
        }
    ],
    "sg:phone":"+1 406 375 4545",
    "sg:postcode":"59840",
    "sg:province":"MT",
    "sg:tags":[
        "physician",
        "surgeon"
    ],
    "wof:name":"Ravalli Pediatrics",
    "wof:placetype":"venue"
},
  "geometry": {"coordinates":[-114.171012,46.247251],"type":"Point"}
}