{
  "type": "Feature",
  "properties": {
    "iso:country":"US",
    "sg:address":"633 S Boulder Rd",
    "sg:city":"Cardwell",
    "sg:classifiers":[
        {
            "category":"Education",
            "subcategory":"Vocational School",
            "type":"Public Place"
        }
    ],
    "sg:phone":"+1 406 287 3323",
    "sg:postcode":"59721",
    "sg:province":"MT",
    "wof:name":"Indiana University Geological",
    "wof:placetype":"venue"
},
  "geometry": {"coordinates":[-111.978223,45.7264],"type":"Point"}
}