{
  "type": "Feature",
  "properties": {
    "iso:country":"US",
    "sg:address":"138 Jeffers Loop Rd",
    "sg:city":"Ennis",
    "sg:classifiers":[
        {
            "category":"Freight",
            "type":"Transportation"
        }
    ],
    "sg:phone":"+1 406 682 4569",
    "sg:postcode":"59729",
    "sg:province":"MT",
    "sg:tags":[
        "operator",
        "local",
        "trucking"
    ],
    "wof:name":"Reints Ranch Trucking",
    "wof:placetype":"venue"
},
  "geometry": {"coordinates":[-111.689538,45.349298],"type":"Point"}
}