{
  "type": "Feature",
  "properties": {
    "addr:full":"2300 S Central Ave Sidney MT 59270",
    "addr:housenumber":"2300",
    "addr:postcode":"59270",
    "addr:street":"S Central Ave",
    "iso:country":"US",
    "sg:address":"2300 S Central Ave",
    "sg:city":"Sidney",
    "sg:classifiers":[
        {
            "category":"Travel",
            "subcategory":"Hotels & Motels",
            "type":"Entertainment"
        }
    ],
    "sg:phone":"+1 406 482 3827",
    "sg:postcode":"59270",
    "sg:province":"MT",
    "sg:tags":[
        "operation"
    ],
    "wof:name":"Sun Rise Motel",
    "wof:placetype":"venue"
},
  "geometry": {"coordinates":[-104.172252,47.693515],"type":"Point"}
}