{
  "type": "Feature",
  "properties": {
    "iso:country":"US",
    "sg:address":"429 N 33rd St",
    "sg:city":"Billings",
    "sg:classifiers":[
        {
            "category":"Real Estate",
            "subcategory":"Real Estate Operator",
            "type":"Services"
        }
    ],
    "sg:phone":"+1 406 259 5666",
    "sg:postcode":"59101",
    "sg:province":"MT",
    "sg:tags":[
        "building",
        "apartment"
    ],
    "wof:name":"Western Towers APT",
    "wof:placetype":"venue"
},
  "geometry": {"coordinates":[-108.515216,45.78256],"type":"Point"}
}