{
  "type": "Feature",
  "properties": {
    "addr:full":"1220 Ave C Billings MT 59102",
    "addr:postcode":"59102",
    "addr:street":"1220 Ave C",
    "iso:country":"US",
    "sg:address":"1220 Ave C",
    "sg:city":"Billings",
    "sg:classifiers":[
        {
            "category":"Shopping",
            "subcategory":"Computers & Home Electronics",
            "type":"Retail Goods"
        }
    ],
    "sg:phone":"+1 406 256 1039",
    "sg:postcode":"59102",
    "sg:province":"MT",
    "wof:name":"Cornerstone Computer Services",
    "wof:placetype":"venue"
},
  "geometry": {"coordinates":[-108.54806000000001,45.785881],"type":"Point"}
}