{
  "type": "Feature",
  "properties": {
    "iso:country":"US",
    "sg:address":"2023 Stadium Dr",
    "sg:city":"Bozeman",
    "sg:classifiers":[
        {
            "category":"Banks & Credit Unions",
            "subcategory":"Investment Brokerage",
            "type":"Services"
        }
    ],
    "sg:phone":"+1 406 587 1116",
    "sg:postcode":"59715",
    "sg:province":"MT",
    "sg:tags":[
        "consultant",
        "planning",
        "financial"
    ],
    "wof:name":"Investment & Financial Svc",
    "wof:placetype":"venue"
},
  "geometry": {"coordinates":[-111.054878,45.659657],"type":"Point"}
}