{
  "type": "Feature",
  "properties": {
    "iso:country":"US",
    "sg:address":"16 Calico St",
    "sg:city":"Cut Bank",
    "sg:classifiers":[
        {
            "category":"Restaurant",
            "type":"Food & Drink"
        }
    ],
    "sg:phone":"+1 406 873 5447",
    "sg:postcode":"59427",
    "sg:province":"MT",
    "sg:tags":[
        "eating"
    ],
    "wof:name":"Froggies Bar & Grill Inc",
    "wof:placetype":"venue"
},
  "geometry": {"coordinates":[-112.321564,48.63935],"type":"Point"}
}