{
  "type": "Feature",
  "properties": {
    "addr:full":"2237 Hillside Dr Missoula MT 59803",
    "addr:housenumber":"2237",
    "addr:postcode":"59803",
    "addr:street":"Hillside Dr",
    "iso:country":"US",
    "sg:address":"2237 Hillside Dr",
    "sg:city":"Missoula",
    "sg:classifiers":[
        {
            "category":"Recreation",
            "type":"Entertainment"
        }
    ],
    "sg:phone":"+1 406 251 6611",
    "sg:postcode":"59803",
    "sg:province":"MT",
    "wof:name":"Rock Creek Cabin",
    "wof:placetype":"venue"
},
  "geometry": {"coordinates":[-114.033379,46.828281],"type":"Point"}
}