{
  "type": "Feature",
  "properties": {
    "iso:country":"US",
    "sg:address":"410 Church St",
    "sg:city":"Stevensville",
    "sg:classifiers":[
        {
            "category":"Wholesale",
            "subcategory":"Durable Goods & Equipment",
            "type":"Manufacturing & Wholesale Goods"
        }
    ],
    "sg:phone":"+1 406 777 5682",
    "sg:postcode":"59870",
    "sg:province":"MT",
    "sg:tags":[
        "tarpaulin"
    ],
    "wof:name":"Cranston Plastics Tarps & Cvrs",
    "wof:placetype":"venue"
},
  "geometry": {"coordinates":[-114.092416,46.508297],"type":"Point"}
}