{
  "type": "Feature",
  "properties": {
    "addr:full":"525 Kuhlman Dr Billings MT 59105",
    "addr:housenumber":"525",
    "addr:postcode":"59105",
    "addr:street":"Kuhlman Dr",
    "iso:country":"US",
    "sg:address":"525 Kuhlman Dr",
    "sg:city":"Billings",
    "sg:classifiers":[
        {
            "category":"Retail",
            "subcategory":"Auto Repair",
            "type":"Services"
        }
    ],
    "sg:phone":"+1 406 256 6348",
    "sg:postcode":"59105",
    "sg:province":"MT",
    "sg:tags":[
        "repairing",
        "automobile"
    ],
    "wof:name":"Profab Motorsports",
    "wof:placetype":"venue"
},
  "geometry": {"coordinates":[-108.47393099999999,45.818416],"type":"Point"}
}