{
  "type": "Feature",
  "properties": {
    "addr:full":"2023 Stadium Dr Bozeman MT 59715",
    "addr:housenumber":"2023",
    "addr:postcode":"59715",
    "addr:street":"Stadium Dr",
    "iso:country":"US",
    "sg:address":"2023 Stadium Dr",
    "sg:city":"Bozeman",
    "sg:classifiers":[
        {
            "category":"Banks & Credit Unions",
            "subcategory":"Bank",
            "type":"Services"
        }
    ],
    "sg:phone":"+1 406 585 5476",
    "sg:postcode":"59715",
    "sg:province":"MT",
    "sg:tags":[
        "mortgage"
    ],
    "wof:name":"Allied Home Mrtg Capitl Corp",
    "wof:placetype":"venue"
},
  "geometry": {"coordinates":[-111.054878,45.659657],"type":"Point"}
}