{
  "type": "Feature",
  "properties": {
    "iso:country":"US",
    "sg:address":"6042 Chicago Rd",
    "sg:city":"Shepherd",
    "sg:classifiers":[
        {
            "category":"Farming",
            "subcategory":"Livestock Farm",
            "type":"Manufacturing & Wholesale Goods"
        }
    ],
    "sg:phone":"+1 406 373 6741",
    "sg:postcode":"59079",
    "sg:province":"MT",
    "sg:tags":[
        "beef",
        "feedlot",
        "cattle"
    ],
    "wof:name":"Mark Harrington",
    "wof:placetype":"venue"
},
  "geometry": {"coordinates":[-108.331604,45.907409],"type":"Point"}
}