{
  "type": "Feature",
  "properties": {
    "addr:full":"312 Northridge Dr Kalispell MT 59901",
    "addr:housenumber":"312",
    "addr:postcode":"59901",
    "addr:street":"Northridge Dr",
    "iso:country":"US",
    "sg:address":"312 Northridge Dr",
    "sg:city":"Kalispell",
    "sg:classifiers":[
        {
            "category":"Professional",
            "subcategory":"Management & Consulting",
            "type":"Services"
        }
    ],
    "sg:phone":"+1 406 257 4122",
    "sg:postcode":"59901",
    "sg:province":"MT",
    "wof:name":"Griffin & Associates",
    "wof:placetype":"venue"
},
  "geometry": {"coordinates":[-114.33885100000001,48.219157],"type":"Point"}
}