{
  "type": "Feature",
  "properties": {
    "iso:country":"US",
    "sg:address":"116 5th Ave S",
    "sg:city":"Wolf Point",
    "sg:classifiers":[
        {
            "category":"Personal",
            "subcategory":"Beauty Salon",
            "type":"Services"
        }
    ],
    "sg:phone":"+1 406 653 1117",
    "sg:postcode":"59201",
    "sg:province":"MT",
    "sg:tags":[
        "shop"
    ],
    "wof:name":"Heads Up",
    "wof:placetype":"venue"
},
  "geometry": {"coordinates":[-105.644908,48.090513],"type":"Point"}
}