{
  "type": "Feature",
  "properties": {
    "iso:country":"US",
    "sg:address":"520 N 32nd St",
    "sg:city":"Billings",
    "sg:classifiers":[
        {
            "category":"Shopping",
            "subcategory":"Used Merchandise",
            "type":"Retail Goods"
        }
    ],
    "sg:phone":"+1 406 248 6500",
    "sg:postcode":"59101",
    "sg:province":"MT",
    "sg:tags":[
        "book",
        "rare",
        "dealer"
    ],
    "wof:name":"A Few Books More",
    "wof:placetype":"venue"
},
  "geometry": {"coordinates":[-108.513982,45.782709],"type":"Point"}
}