{
  "type": "Feature",
  "properties": {
    "iso:country":"US",
    "sg:address":"322 2nd Avenue W N",
    "sg:city":"Kalispell",
    "sg:classifiers":[
        {
            "category":"Professional",
            "subcategory":"Lawyer & Legal Services",
            "type":"Services"
        }
    ],
    "sg:phone":"+1 406 752 7300",
    "sg:postcode":"59901",
    "sg:province":"MT",
    "sg:tags":[
        "attorney"
    ],
    "wof:name":"Lane K Bennett",
    "wof:placetype":"venue"
},
  "geometry": {"coordinates":[-114.31882299999999,48.203355],"type":"Point"}
}