{
  "type": "Feature",
  "properties": {
    "iso:country":"US",
    "sg:address":"300 Moore Ln",
    "sg:city":"Billings",
    "sg:classifiers":[
        {
            "category":"Wholesale",
            "subcategory":"Machinery & Supplies",
            "type":"Manufacturing & Wholesale Goods"
        }
    ],
    "sg:phone":"+1 406 248 3546",
    "sg:postcode":"59101",
    "sg:province":"MT",
    "sg:tags":[
        "equipment",
        "mining"
    ],
    "sg:website":"www.montanasupply.com",
    "wof:name":"Montana International Supply",
    "wof:placetype":"venue"
},
  "geometry": {"coordinates":[-108.542289,45.765214],"type":"Point"}
}