{
  "type": "Feature",
  "properties": {
    "iso:country":"US",
    "sg:address":"4612 Judith Landing Rd",
    "sg:city":"Big Sandy",
    "sg:phone":"+1 406 378 2490",
    "sg:postcode":"59520",
    "sg:province":"MT",
    "sg:tags":[
        "farm",
        "wheat"
    ],
    "wof:name":"Sibra Farm Inc",
    "wof:placetype":"venue"
},
  "geometry": {"coordinates":[-110.101619,48.111277],"type":"Point"}
}