{
  "type": "Feature",
  "properties": {
    "iso:country":"US",
    "sg:address":"2521 Garland Dr",
    "sg:city":"Missoula",
    "sg:classifiers":[
        {
            "category":"Food & Beverages",
            "subcategory":"Specialty",
            "type":"Retail Goods"
        }
    ],
    "sg:phone":"+1 406 251 3859",
    "sg:postcode":"59803",
    "sg:province":"MT",
    "wof:name":"Neo-Life Distributor",
    "wof:placetype":"venue"
},
  "geometry": {"coordinates":[-114.041054,46.828241],"type":"Point"}
}