{
  "type": "Feature",
  "properties": {
    "addr:full":"715 Front St Helena MT 59601",
    "addr:housenumber":"715",
    "addr:postcode":"59601",
    "addr:street":"Front St",
    "iso:country":"US",
    "sg:address":"715 Front St",
    "sg:city":"Helena",
    "sg:classifiers":[
        {
            "category":"Social Services",
            "subcategory":"Job Training",
            "type":"Services"
        }
    ],
    "sg:phone":"+1 406 447 3217",
    "sg:postcode":"59601",
    "sg:province":"MT",
    "wof:name":"Helena Job Corps Center",
    "wof:placetype":"venue"
},
  "geometry": {"coordinates":[-112.036039,46.595779],"type":"Point"}
}