{
  "type": "Feature",
  "properties": {
    "addr:full":"650 Forest Hill Rd Kalispell MT 59901",
    "addr:housenumber":"650",
    "addr:postcode":"59901",
    "addr:street":"Forest Hill Rd",
    "iso:country":"US",
    "sg:address":"650 Forest Hill Rd",
    "sg:city":"Kalispell",
    "sg:classifiers":[
        {
            "category":"Farming",
            "subcategory":"Livestock Farm",
            "type":"Manufacturing & Wholesale Goods"
        }
    ],
    "sg:phone":"+1 406 857 3652",
    "sg:postcode":"59901",
    "sg:province":"MT",
    "sg:tags":[
        "beef",
        "feedlot",
        "cattle"
    ],
    "wof:name":"Robert Altenburg",
    "wof:placetype":"venue"
},
  "geometry": {"coordinates":[-114.244888,48.098791],"type":"Point"}
}