{
  "type": "Feature",
  "properties": {
    "iso:country":"US",
    "sg:address":"110 S Central Ave",
    "sg:city":"Sidney",
    "sg:classifiers":[
        {
            "category":"Bars & Pubs",
            "type":"Food & Drink"
        }
    ],
    "sg:phone":"+1 406 482 4566",
    "sg:postcode":"59270",
    "sg:province":"MT",
    "wof:name":"Ranger Lounge",
    "wof:placetype":"venue"
},
  "geometry": {"coordinates":[-104.15709200000001,47.71512],"type":"Point"}
}