{
  "type": "Feature",
  "properties": {
    "iso:country":"US",
    "sg:address":"808 N Wallace Ave",
    "sg:city":"Bozeman",
    "sg:classifiers":[
        {
            "category":"Shopping",
            "subcategory":"Optical Goods",
            "type":"Retail Goods"
        }
    ],
    "sg:phone":"+1 406 582 9412",
    "sg:postcode":"59715",
    "sg:province":"MT",
    "wof:name":"James Caffrey",
    "wof:placetype":"venue"
},
  "geometry": {"coordinates":[-111.028244,45.688539],"type":"Point"}
}