{
  "type": "Feature",
  "properties": {
    "addr:full":"968 Coal Pit Rd Corvallis MT 59828",
    "addr:housenumber":"968",
    "addr:postcode":"59828",
    "addr:street":"Coal Pit Rd",
    "iso:country":"US",
    "sg:address":"968 Coal Pit Rd",
    "sg:city":"Corvallis",
    "sg:classifiers":[
        {
            "category":"Manufacturing",
            "subcategory":"Textiles",
            "type":"Manufacturing & Wholesale Goods"
        }
    ],
    "sg:phone":"+1 406 961 4473",
    "sg:postcode":"59828",
    "sg:province":"MT",
    "sg:tags":[
        "spinning",
        "fiber",
        "weaving",
        "supply"
    ],
    "wof:name":"Crosspatch Creations",
    "wof:placetype":"venue"
},
  "geometry": {"coordinates":[-114.045478,46.312688],"type":"Point"}
}