{
  "type": "Feature",
  "properties": {
    "addr:full":"3620 State Hwy 200 Missoula MT 59802",
    "addr:housenumber":"3620",
    "addr:postcode":"59802",
    "addr:street":"State Hwy 200",
    "iso:country":"US",
    "sg:address":"3620 State Hwy 200",
    "sg:city":"Missoula",
    "sg:classifiers":[
        {
            "category":"Autos & Motor Vehicles",
            "subcategory":"Auto Supplies",
            "type":"Retail Goods"
        }
    ],
    "sg:phone":"+1 406 549 2814",
    "sg:postcode":"59802",
    "sg:province":"MT",
    "sg:tags":[
        "repair",
        "r",
        "general",
        "automotive"
    ],
    "wof:name":"Carls Auto Air",
    "wof:placetype":"venue"
},
  "geometry": {"coordinates":[-113.94708300000001,46.87074],"type":"Point"}
}