{
  "type": "Feature",
  "properties": {
    "addr:full":"715 Highland St Helena MT 59601",
    "addr:housenumber":"715",
    "addr:postcode":"59601",
    "addr:street":"Highland St",
    "iso:country":"US",
    "sg:address":"715 Highland St",
    "sg:city":"Helena",
    "sg:classifiers":[
        {
            "category":"Professional",
            "subcategory":"Management & Consulting",
            "type":"Services"
        }
    ],
    "sg:phone":"+1 406 444 5388",
    "sg:postcode":"59601",
    "sg:province":"MT",
    "sg:tags":[
        "computer",
        "business"
    ],
    "wof:name":"Montana Computer Consulting",
    "wof:placetype":"venue"
},
  "geometry": {"coordinates":[-112.029504,46.582934],"type":"Point"}
}