{
  "type": "Feature",
  "properties": {
    "iso:country":"US",
    "sg:address":"2419 Bluebell Ave",
    "sg:city":"Bozeman",
    "sg:classifiers":[
        {
            "category":"Building & Trades",
            "subcategory":"Construction",
            "type":"Services"
        }
    ],
    "sg:phone":"+1 406 582 7594",
    "sg:postcode":"59718",
    "sg:province":"MT",
    "sg:tags":[
        "hanging",
        "contractor"
    ],
    "wof:name":"Ken Champion Painting & W",
    "wof:placetype":"venue"
},
  "geometry": {"coordinates":[-111.10172900000001,45.750073],"type":"Point"}
}