{
  "type": "Feature",
  "properties": {
    "addr:full":"2910 Hannon Rd Billings MT 59101",
    "addr:housenumber":"2910",
    "addr:postcode":"59101",
    "addr:street":"Hannon Rd",
    "iso:country":"US",
    "sg:address":"2910 Hannon Rd",
    "sg:city":"Billings",
    "sg:classifiers":[
        {
            "category":"Wholesale",
            "subcategory":"Motor Vehicles",
            "type":"Manufacturing & Wholesale Goods"
        }
    ],
    "sg:phone":"+1 406 245 3693",
    "sg:postcode":"59101",
    "sg:province":"MT",
    "sg:tags":[
        "body",
        "equipment",
        "truck"
    ],
    "wof:name":"Custom Equipment",
    "wof:placetype":"venue"
},
  "geometry": {"coordinates":[-108.49741299999999,45.760664],"type":"Point"}
}