{
  "type": "Feature",
  "properties": {
    "iso:country":"US",
    "sg:address":"216 Mc Leod St",
    "sg:city":"Big Timber",
    "sg:classifiers":[
        {
            "category":"Shopping",
            "subcategory":"Stationery & Office Supplies",
            "type":"Retail Goods"
        }
    ],
    "sg:phone":"+1 406 932 5558",
    "sg:postcode":"59011",
    "sg:province":"MT",
    "wof:name":"Paper Creations Etc",
    "wof:placetype":"venue"
},
  "geometry": {"coordinates":[-109.954416,45.833945],"type":"Point"}
}