{
  "type": "Feature",
  "properties": {
    "iso:country":"US",
    "sg:address":"433 Mc Leod Ave",
    "sg:city":"Missoula",
    "sg:classifiers":[
        {
            "category":"Professional",
            "type":"Services"
        }
    ],
    "sg:phone":"+1 406 570 9806",
    "sg:postcode":"59801",
    "sg:province":"MT",
    "wof:name":"Birgitta A Nelson",
    "wof:placetype":"venue"
},
  "geometry": {"coordinates":[-113.991238,46.859027],"type":"Point"}
}