{
  "type": "Feature",
  "properties": {
    "iso:country":"US",
    "sg:address":"101 N Last Chance Gulch St",
    "sg:city":"Helena",
    "sg:classifiers":[
        {
            "category":"Organizations",
            "subcategory":"Professional Association",
            "type":"Services"
        }
    ],
    "sg:phone":"+1 406 443 8313",
    "sg:postcode":"59601",
    "sg:province":"MT",
    "sg:tags":[
        "profit",
        "foundation",
        "community"
    ],
    "wof:name":"Montana Community Foundation",
    "wof:placetype":"venue"
},
  "geometry": {"coordinates":[-112.03870000000001,46.588232],"type":"Point"}
}