{
  "type": "Feature",
  "properties": {
    "iso:country":"US",
    "sg:address":"1819 Whitman Ave",
    "sg:city":"Butte",
    "sg:classifiers":[
        {
            "category":"Professional",
            "subcategory":"Business Services",
            "type":"Services"
        }
    ],
    "sg:phone":"+1 406 782 5312",
    "sg:postcode":"59701",
    "sg:province":"MT",
    "sg:tags":[
        "organization",
        "membership"
    ],
    "wof:name":"Timoteo & Luisa Cachola",
    "wof:placetype":"venue"
},
  "geometry": {"coordinates":[-112.518162,45.99566],"type":"Point"}
}