{
  "type": "Feature",
  "properties": {
    "addr:full":"1715 Shadow Ln Missoula MT 59803",
    "addr:housenumber":"1715",
    "addr:postcode":"59803",
    "addr:street":"Shadow Ln",
    "iso:country":"US",
    "sg:address":"1715 Shadow Ln",
    "sg:city":"Missoula",
    "sg:classifiers":[
        {
            "category":"Organizations",
            "subcategory":"Religious Organization",
            "type":"Services"
        }
    ],
    "sg:phone":"+1 406 251 9998",
    "sg:postcode":"59803",
    "sg:province":"MT",
    "wof:name":"Mike Hagen Ministries Inc",
    "wof:placetype":"venue"
},
  "geometry": {"coordinates":[-114.02068,46.828136],"type":"Point"}
}