{
  "type": "Feature",
  "properties": {
    "iso:country":"US",
    "sg:address":"406 S Main St",
    "sg:city":"Livingston",
    "sg:classifiers":[
        {
            "category":"Insurance",
            "subcategory":"Insurance Agent",
            "type":"Services"
        }
    ],
    "sg:phone":"+1 406 222 8670",
    "sg:postcode":"59047",
    "sg:province":"MT",
    "wof:name":"Gavne Insurance Agency",
    "wof:placetype":"venue"
},
  "geometry": {"coordinates":[-110.55655299999999,45.658135],"type":"Point"}
}