{
  "type": "Feature",
  "properties": {
    "iso:country":"US",
    "sg:address":"1040 Reynolds Creek Rd",
    "sg:city":"Belgrade",
    "sg:classifiers":[
        {
            "category":"Farming",
            "subcategory":"Livestock Farm",
            "type":"Manufacturing & Wholesale Goods"
        }
    ],
    "sg:phone":"+1 406 388 2495",
    "sg:postcode":"59714",
    "sg:province":"MT",
    "sg:tags":[
        "wheat",
        "beef",
        "cash",
        "grain",
        "cattle",
        "feedlot"
    ],
    "wof:name":"Jason Camp",
    "wof:placetype":"venue"
},
  "geometry": {"coordinates":[-111.15989399999999,45.908613],"type":"Point"}
}