{
  "type": "Feature",
  "properties": {
    "addr:full":"227 Glenhaven Dr Billings MT 59105",
    "addr:housenumber":"227",
    "addr:postcode":"59105",
    "addr:street":"Glenhaven Dr",
    "iso:country":"US",
    "sg:address":"227 Glenhaven Dr",
    "sg:city":"Billings",
    "sg:classifiers":[
        {
            "category":"Freight",
            "type":"Transportation"
        }
    ],
    "sg:phone":"+1 406 256 9101",
    "sg:postcode":"59105",
    "sg:province":"MT",
    "sg:tags":[
        "hauling",
        "trucking"
    ],
    "wof:name":"Kuck Trucking Inc",
    "wof:placetype":"venue"
},
  "geometry": {"coordinates":[-108.490826,45.829512],"type":"Point"}
}