{
  "type": "Feature",
  "properties": {
    "iso:country":"US",
    "sg:address":"365 Orchard Ridge Rd",
    "sg:city":"Kalispell",
    "sg:classifiers":[
        {
            "category":"Bars & Pubs",
            "type":"Food & Drink"
        }
    ],
    "sg:phone":"+1 406 752 4326",
    "sg:postcode":"59901",
    "sg:province":"MT",
    "sg:tags":[
        "drinking"
    ],
    "wof:name":"Triple Play LLC",
    "wof:placetype":"venue"
},
  "geometry": {"coordinates":[-114.325665,48.145574],"type":"Point"}
}