{
  "type": "Feature",
  "properties": {
    "iso:country":"US",
    "sg:address":"4961 Simpson St",
    "sg:city":"Billings",
    "sg:classifiers":[
        {
            "category":"Professional",
            "subcategory":"Management & Consulting",
            "type":"Services"
        }
    ],
    "sg:phone":"+1 406 259 3175",
    "sg:postcode":"59101",
    "sg:province":"MT",
    "sg:tags":[
        "telecommunication",
        "microwave"
    ],
    "wof:name":"Wtci",
    "wof:placetype":"venue"
},
  "geometry": {"coordinates":[-108.54094000000001,45.759075],"type":"Point"}
}