{
  "type": "Feature",
  "properties": {
    "iso:country":"US",
    "sg:address":"325 N Ferndale Dr",
    "sg:city":"Bigfork",
    "sg:classifiers":[
        {
            "category":"Airport",
            "type":"Transportation"
        }
    ],
    "sg:phone":"+1 406 837 4113",
    "sg:postcode":"59911",
    "sg:province":"MT",
    "sg:tags":[
        "product",
        "petroleum"
    ],
    "wof:name":"Poorman Aviation",
    "wof:placetype":"venue"
},
  "geometry": {"coordinates":[-114.007014,48.064181],"type":"Point"}
}