{
  "type": "Feature",
  "properties": {
    "addr:full":"125 Wibaux St N Wibaux MT 59353",
    "addr:housenumber":"125",
    "addr:postcode":"59353",
    "addr:street":"Wibaux St N",
    "iso:country":"US",
    "sg:address":"125 Wibaux St N",
    "sg:city":"Wibaux",
    "sg:classifiers":[
        {
            "category":"Restaurant",
            "type":"Food & Drink"
        }
    ],
    "sg:phone":"+1 406 796 2426",
    "sg:postcode":"59353",
    "sg:province":"MT",
    "wof:name":"Palace Cafe",
    "wof:placetype":"venue"
},
  "geometry": {"coordinates":[-104.18717700000001,46.988627],"type":"Point"}
}