{
  "type": "Feature",
  "properties": {
    "iso:country":"US",
    "sg:address":"15733 Manor Blvd",
    "sg:city":"Lolo",
    "sg:classifiers":[
        {
            "category":"Retail",
            "subcategory":"Animal Services",
            "type":"Services"
        }
    ],
    "sg:phone":"+1 406 273 2165",
    "sg:postcode":"59847",
    "sg:province":"MT",
    "sg:tags":[
        "farm",
        "supply"
    ],
    "wof:name":"Treasure State Equestrian Cent",
    "wof:placetype":"venue"
},
  "geometry": {"coordinates":[-114.081492,46.723983],"type":"Point"}
}