{
  "type": "Feature",
  "properties": {
    "iso:country":"US",
    "sg:address":"1119 Maggie St",
    "sg:city":"Billings",
    "sg:classifiers":[
        {
            "category":"Wholesale",
            "subcategory":"Machinery & Supplies",
            "type":"Manufacturing & Wholesale Goods"
        }
    ],
    "sg:phone":"+1 406 256 9113",
    "sg:postcode":"59101",
    "sg:province":"MT",
    "sg:tags":[
        "chemical",
        "upholstery",
        "cleaning",
        "carpet"
    ],
    "wof:name":"Americlean Corporation",
    "wof:placetype":"venue"
},
  "geometry": {"coordinates":[-108.541614,45.748755],"type":"Point"}
}