{
  "type": "Feature",
  "properties": {
    "addr:full":"131 Central Ave Whitefish MT 59937",
    "addr:housenumber":"131",
    "addr:postcode":"59937",
    "addr:street":"Central Ave",
    "iso:country":"US",
    "sg:address":"131 Central Ave",
    "sg:city":"Whitefish",
    "sg:classifiers":[
        {
            "category":"Banks & Credit Unions",
            "subcategory":"Financial Services",
            "type":"Services"
        }
    ],
    "sg:phone":"+1 406 862 0385",
    "sg:postcode":"59937",
    "sg:province":"MT",
    "sg:tags":[
        "trust",
        "family"
    ],
    "wof:name":"McGough Family Trust",
    "wof:placetype":"venue"
},
  "geometry": {"coordinates":[-114.336686,48.411351],"type":"Point"}
}