{
  "type": "Feature",
  "properties": {
    "iso:country":"US",
    "sg:address":"8121 Altenbrand Ave",
    "sg:city":"Manhattan",
    "sg:classifiers":[
        {
            "category":"Real Estate",
            "subcategory":"Real Estate Operator",
            "type":"Services"
        }
    ],
    "sg:phone":"+1 406 284 6019",
    "sg:postcode":"59741",
    "sg:province":"MT",
    "sg:tags":[
        "mobile",
        "home",
        "site"
    ],
    "wof:name":"Rider Courts LLC",
    "wof:placetype":"venue"
},
  "geometry": {"coordinates":[-111.32608999999999,45.860889],"type":"Point"}
}