{
  "type": "Feature",
  "properties": {
    "iso:country":"US",
    "sg:address":"715 2nd Ave N",
    "sg:city":"Great Falls",
    "sg:classifiers":[
        {
            "category":"Retail",
            "subcategory":"Repair Shop",
            "type":"Services"
        }
    ],
    "sg:phone":"+1 406 453 0429",
    "sg:postcode":"59401",
    "sg:province":"MT",
    "wof:name":"Quality Piano",
    "wof:placetype":"venue"
},
  "geometry": {"coordinates":[-111.294006,47.507573],"type":"Point"}
}