{
  "type": "Feature",
  "properties": {
    "iso:country":"US",
    "sg:address":"10100 Sleeman Creek Rd",
    "sg:city":"Lolo",
    "sg:classifiers":[
        {
            "category":"Building & Trades",
            "subcategory":"Landscaping Services",
            "type":"Services"
        }
    ],
    "sg:phone":"+1 406 273 4228",
    "sg:postcode":"59847",
    "sg:province":"MT",
    "sg:tags":[
        "landscape",
        "contractor"
    ],
    "wof:name":"Innovative Landscapes",
    "wof:placetype":"venue"
},
  "geometry": {"coordinates":[-114.13261,46.764614],"type":"Point"}
}