{
  "type": "Feature",
  "properties": {
    "iso:country":"US",
    "sg:address":"3315 Lower Canal Rd",
    "sg:city":"Pompeys Pillar",
    "sg:phone":"+1 406 875 2139",
    "sg:postcode":"59064",
    "sg:province":"MT",
    "sg:tags":[
        "farm",
        "field",
        "corn",
        "beet",
        "crop"
    ],
    "wof:name":"Dave Lambrecht",
    "wof:placetype":"venue"
},
  "geometry": {"coordinates":[-107.98194700000001,45.973646],"type":"Point"}
}