{
  "type": "Feature",
  "properties": {
    "iso:country":"US",
    "sg:address":"2550 Enterprise Ave",
    "sg:city":"Billings",
    "sg:classifiers":[
        {
            "category":"Wholesale",
            "subcategory":"Hardware",
            "type":"Manufacturing & Wholesale Goods"
        }
    ],
    "sg:phone":"+1 406 656 9570",
    "sg:postcode":"59102",
    "sg:province":"MT",
    "sg:tags":[
        "steam",
        "trap"
    ],
    "sg:website":"www.kirstengineering.com",
    "wof:name":"Kirst Engineering Co",
    "wof:placetype":"venue"
},
  "geometry": {"coordinates":[-108.580586,45.750638],"type":"Point"}
}