{
  "type": "Feature",
  "properties": {
    "addr:full":"1221 Shakespeare St Missoula MT 59802",
    "addr:housenumber":"1221",
    "addr:postcode":"59802",
    "addr:street":"Shakespeare St",
    "iso:country":"US",
    "sg:address":"1221 Shakespeare St",
    "sg:city":"Missoula",
    "sg:classifiers":[
        {
            "category":"Local Transit",
            "type":"Transportation"
        }
    ],
    "sg:phone":"+1 406 721 2848",
    "sg:postcode":"59802",
    "sg:province":"MT",
    "sg:tags":[
        "city",
        "line",
        "bus"
    ],
    "wof:name":"Mountian Line",
    "wof:placetype":"venue"
},
  "geometry": {"coordinates":[-114.009354,46.883633],"type":"Point"}
}