{
  "type": "Feature",
  "properties": {
    "addr:full":"424 2nd St NW Sidney MT 59270",
    "addr:housenumber":"424",
    "addr:postcode":"59270",
    "addr:street":"2Nd St Nw",
    "iso:country":"US",
    "sg:address":"424 2nd St NW",
    "sg:city":"Sidney",
    "sg:classifiers":[
        {
            "category":"Manufacturing",
            "subcategory":"Printing",
            "type":"Manufacturing & Wholesale Goods"
        }
    ],
    "sg:phone":"+1 406 433 4375",
    "sg:postcode":"59270",
    "sg:province":"MT",
    "sg:tags":[
        "printer"
    ],
    "wof:name":"Elk River Printing Inc",
    "wof:placetype":"venue"
},
  "geometry": {"coordinates":[-104.161878,47.717717],"type":"Point"}
}