{
  "type": "Feature",
  "properties": {
    "iso:country":"US",
    "sg:address":"1330 S 4th St W",
    "sg:city":"Missoula",
    "sg:classifiers":[
        {
            "category":"Health Services",
            "subcategory":"Hospital",
            "type":"Services"
        }
    ],
    "sg:phone":"+1 406 549 8309",
    "sg:postcode":"59801",
    "sg:province":"MT",
    "sg:tags":[
        "specialty"
    ],
    "wof:name":"Western Mt Mental Health",
    "wof:placetype":"venue"
},
  "geometry": {"coordinates":[-114.01686100000001,46.866082],"type":"Point"}
}