{
  "type": "Feature",
  "properties": {
    "iso:country":"US",
    "sg:address":"255 Hoss Dr",
    "sg:city":"Hamilton",
    "sg:classifiers":[
        {
            "category":"Building & Trades",
            "subcategory":"Construction",
            "type":"Services"
        }
    ],
    "sg:phone":"+1 406 363 2038",
    "sg:postcode":"59840",
    "sg:province":"MT",
    "sg:tags":[
        "insulation",
        "heat",
        "contractor"
    ],
    "wof:name":"Hamilton Insulation",
    "wof:placetype":"venue"
},
  "geometry": {"coordinates":[-114.139339,46.192351],"type":"Point"}
}