{
  "type": "Feature",
  "properties": {
    "iso:country":"US",
    "sg:address":"196 Copper Ct",
    "sg:city":"Hamilton",
    "sg:classifiers":[
        {
            "category":"Wholesale",
            "subcategory":"Construction Materials",
            "type":"Manufacturing & Wholesale Goods"
        }
    ],
    "sg:phone":"+1 406 363 6153",
    "sg:postcode":"59840",
    "sg:province":"MT",
    "wof:name":"Bourne Lumber Sales",
    "wof:placetype":"venue"
},
  "geometry": {"coordinates":[-114.130567,46.234808],"type":"Point"}
}