{
  "type": "Feature",
  "properties": {
    "addr:full":"315 S 19th Ave Bozeman MT 59718",
    "addr:housenumber":"315",
    "addr:postcode":"59718",
    "addr:street":"S 19Th Ave",
    "iso:country":"US",
    "sg:address":"315 S 19th Ave",
    "sg:city":"Bozeman",
    "sg:classifiers":[
        {
            "category":"Organizations",
            "subcategory":"Religious Organization",
            "type":"Services"
        }
    ],
    "sg:phone":"+1 406 587 7072",
    "sg:postcode":"59718",
    "sg:province":"MT",
    "wof:name":"ABC Fundamentals",
    "wof:placetype":"venue"
},
  "geometry": {"coordinates":[-111.062743,45.676138],"type":"Point"}
}