{
  "type": "Feature",
  "properties": {
    "iso:country":"US",
    "sg:address":"3190 Stucky Rd",
    "sg:city":"Bozeman",
    "sg:classifiers":[
        {
            "category":"Professional",
            "subcategory":"Business Services",
            "type":"Services"
        }
    ],
    "sg:phone":"+1 406 586 5342",
    "sg:postcode":"59718",
    "sg:province":"MT",
    "wof:name":"Circle G LLC",
    "wof:placetype":"venue"
},
  "geometry": {"coordinates":[-111.123186,45.656467],"type":"Point"}
}