{
  "type": "Feature",
  "properties": {
    "iso:country":"US",
    "sg:address":"1111 Research Dr",
    "sg:city":"Bozeman",
    "sg:classifiers":[
        {
            "category":"Professional",
            "subcategory":"Management & Consulting",
            "type":"Services"
        }
    ],
    "sg:phone":"+1 406 556 2743",
    "sg:postcode":"59718",
    "sg:province":"MT",
    "sg:tags":[
        "consultant",
        "program",
        "incentive",
        "award"
    ],
    "wof:name":"Kmg Bozeman",
    "wof:placetype":"venue"
},
  "geometry": {"coordinates":[-111.066295,45.667488],"type":"Point"}
}