{
  "type": "Feature",
  "properties": {
    "addr:full":"3342 Stoney Ridge Rd Billings MT 59106",
    "addr:housenumber":"3342",
    "addr:street":"Stoney Ridge Rd",
    "iso:country":"US",
    "sg:address":"3342 Stoney Ridge Rd",
    "sg:city":"Billings",
    "sg:classifiers":[
        {
            "category":"Recreation",
            "subcategory":"Arcade",
            "type":"Entertainment"
        }
    ],
    "sg:phone":"+1 406 259 4707",
    "sg:postcode":"59106",
    "sg:province":"MT",
    "sg:tags":[
        "device",
        "operator",
        "amusement"
    ],
    "wof:name":"Main Street Casino Inc",
    "wof:placetype":"venue"
},
  "geometry": {"coordinates":[-108.574834,45.80246],"type":"Point"}
}