{
  "type": "Feature",
  "properties": {
    "iso:country":"US",
    "sg:address":"124 N Main St",
    "sg:city":"Livingston",
    "sg:classifiers":[
        {
            "category":"Retail",
            "subcategory":"Repair Shop",
            "type":"Services"
        }
    ],
    "sg:phone":"+1 406 222 8899",
    "sg:postcode":"59047",
    "sg:province":"MT",
    "sg:tags":[
        "timepiece",
        "clocks",
        "watch",
        "jew"
    ],
    "wof:name":"Montana Watch Co",
    "wof:placetype":"venue"
},
  "geometry": {"coordinates":[-110.560489,45.66183],"type":"Point"}
}