{
  "type": "Feature",
  "properties": {
    "addr:full":"1001 Main St Billings MT 59105",
    "addr:housenumber":"1001",
    "addr:postcode":"59105",
    "addr:street":"Main St",
    "iso:country":"US",
    "sg:address":"1001 Main St",
    "sg:city":"Billings",
    "sg:classifiers":[
        {
            "category":"Autos & Motor Vehicles",
            "subcategory":"Auto Supplies",
            "type":"Retail Goods"
        }
    ],
    "sg:phone":"+1 406 245 2868",
    "sg:postcode":"59105",
    "sg:province":"MT",
    "sg:tags":[
        "tire"
    ],
    "wof:name":"Tire Rama Svc Ctr",
    "wof:placetype":"venue"
},
  "geometry": {"coordinates":[-108.470704,45.816787],"type":"Point"}
}