{
  "type": "Feature",
  "properties": {
    "iso:country":"US",
    "sg:address":"1112 S Moorehead Ave",
    "sg:city":"Miles City",
    "sg:classifiers":[
        {
            "category":"Building & Trades",
            "subcategory":"Construction",
            "type":"Services"
        }
    ],
    "sg:phone":"+1 406 234 2219",
    "sg:postcode":"59301",
    "sg:province":"MT",
    "sg:tags":[
        "floor",
        "laying",
        "contractor"
    ],
    "wof:name":"Roland Ewalt Contractor",
    "wof:placetype":"venue"
},
  "geometry": {"coordinates":[-105.825115,46.398169],"type":"Point"}
}