{
  "type": "Feature",
  "properties": {
    "iso:country":"US",
    "sg:address":"1001 Oak St",
    "sg:city":"Bozeman",
    "sg:classifiers":[
        {
            "category":"Home & Garden",
            "subcategory":"Building Materials",
            "type":"Retail Goods"
        }
    ],
    "sg:phone":"+1 406 587 5944",
    "sg:postcode":"59715",
    "sg:province":"MT",
    "wof:name":"Pella Windows & Doors Inc",
    "wof:placetype":"venue"
},
  "geometry": {"coordinates":[-111.049954,45.693025],"type":"Point"}
}