{
  "type": "Feature",
  "properties": {
    "addr:full":"2585 US Hwy 2 E Kalispell MT 59901",
    "addr:housenumber":"2585",
    "addr:postcode":"59901",
    "addr:street":"Us Hwy 2 E",
    "iso:country":"US",
    "sg:address":"2585 US Hwy 2 E",
    "sg:city":"Kalispell",
    "sg:classifiers":[
        {
            "category":"Building & Trades",
            "subcategory":"Construction",
            "type":"Services"
        }
    ],
    "sg:phone":"+1 406 755 4804",
    "sg:postcode":"59901",
    "sg:province":"MT",
    "sg:tags":[
        "roofing",
        "siding",
        "material",
        "contractor"
    ],
    "wof:name":"All Systems Roofing Inc",
    "wof:placetype":"venue"
},
  "geometry": {"coordinates":[-114.276138,48.239479],"type":"Point"}
}