{
  "type": "Feature",
  "properties": {
    "iso:country":"US",
    "sg:address":"4022 Whitefish Stage",
    "sg:city":"Kalispell",
    "sg:classifiers":[
        {
            "category":"Shopping",
            "subcategory":"Gifts & Souvenirs",
            "type":"Retail Goods"
        }
    ],
    "sg:phone":"+1 406 862 3045",
    "sg:postcode":"59901",
    "sg:province":"MT",
    "wof:name":"Allstar Sport Cards",
    "wof:placetype":"venue"
},
  "geometry": {"coordinates":[-114.30043499999999,48.324246],"type":"Point"}
}