{
  "type": "Feature",
  "properties": {
    "iso:country":"US",
    "sg:address":"4121 Kent Spur Rd",
    "sg:city":"Bozeman",
    "sg:classifiers":[
        {
            "category":"Organizations",
            "subcategory":"Religious Organization",
            "type":"Services"
        }
    ],
    "sg:phone":"+1 406 587 2852",
    "sg:postcode":"59718",
    "sg:province":"MT",
    "wof:name":"Faith Dairy",
    "wof:placetype":"venue"
},
  "geometry": {"coordinates":[-111.111557,45.583887],"type":"Point"}
}