{
  "type": "Feature",
  "properties": {
    "addr:full":"418 Main St Eureka MT 59901",
    "addr:housenumber":"418",
    "addr:postcode":"59901",
    "addr:street":"Main St",
    "iso:country":"US",
    "sg:address":"418 Main St",
    "sg:city":"Eureka",
    "sg:classifiers":[
        {
            "category":"Government",
            "subcategory":"Office",
            "type":"Public Place"
        }
    ],
    "sg:phone":"+1 406 296 2751",
    "sg:postcode":"59901",
    "sg:province":"MT",
    "sg:tags":[
        "county",
        "resource"
    ],
    "wof:name":"Lincoln County Wic",
    "wof:placetype":"venue"
},
  "geometry": {"coordinates":[-114.312383,48.194671],"type":"Point"}
}