{
  "type": "Feature",
  "properties": {
    "iso:country":"US",
    "sg:address":"280 Blanchard Lake Rd",
    "sg:city":"Whitefish",
    "sg:classifiers":[
        {
            "category":"Building & Trades",
            "subcategory":"Construction",
            "type":"Services"
        }
    ],
    "sg:phone":"+1 406 862 0965",
    "sg:postcode":"59937",
    "sg:province":"MT",
    "sg:tags":[
        "home",
        "family"
    ],
    "wof:name":"Great Northern Homes",
    "wof:placetype":"venue"
},
  "geometry": {"coordinates":[-114.34565600000001,48.370702],"type":"Point"}
}