{
  "type": "Feature",
  "properties": {
    "iso:country":"US",
    "sg:address":"2204 Elsa Dr",
    "sg:city":"Billings",
    "sg:classifiers":[
        {
            "category":"Insurance",
            "subcategory":"Insurance Agent",
            "type":"Services"
        }
    ],
    "sg:phone":"+1 406 651 2020",
    "sg:postcode":"59106",
    "sg:province":"MT",
    "wof:name":"Allegra Insurance",
    "wof:placetype":"venue"
},
  "geometry": {"coordinates":[-108.62108600000001,45.793041],"type":"Point"}
}