{
  "type": "Feature",
  "properties": {
    "iso:country":"US",
    "sg:address":"1104 S 1st St",
    "sg:city":"Hamilton",
    "sg:classifiers":[
        {
            "category":"Building & Trades",
            "subcategory":"Construction",
            "type":"Services"
        }
    ],
    "sg:phone":"+1 406 363 1910",
    "sg:postcode":"59840",
    "sg:province":"MT",
    "sg:tags":[
        "contractor"
    ],
    "wof:name":"Valley Builders",
    "wof:placetype":"venue"
},
  "geometry": {"coordinates":[-114.155207,46.233213],"type":"Point"}
}