{
  "type": "Feature",
  "properties": {
    "addr:full":"521 SW Higgins Ave Missoula MT 59803",
    "addr:housenumber":"521",
    "addr:postcode":"59803",
    "addr:street":"Sw Higgins Ave",
    "iso:country":"US",
    "sg:address":"521 SW Higgins Ave",
    "sg:city":"Missoula",
    "sg:classifiers":[
        {
            "category":"Health Services",
            "subcategory":"Doctor",
            "type":"Services"
        }
    ],
    "sg:phone":"+1 406 728 0397",
    "sg:postcode":"59803",
    "sg:province":"MT",
    "wof:name":"Diggs D Briar DDS",
    "wof:placetype":"venue"
},
  "geometry": {"coordinates":[-114.00527599999999,46.838631],"type":"Point"}
}