{
  "type": "Feature",
  "properties": {
    "iso:country":"US",
    "sg:address":"33 Enger Cutoff Rd",
    "sg:city":"Belt",
    "sg:classifiers":[
        {
            "category":"Professional",
            "subcategory":"Computer Services",
            "type":"Services"
        }
    ],
    "sg:phone":"+1 406 453 4043",
    "sg:postcode":"59412",
    "sg:province":"MT",
    "sg:tags":[
        "aided",
        "drafting"
    ],
    "wof:name":"Cad Graphics Inc",
    "wof:placetype":"venue"
},
  "geometry": {"coordinates":[-110.98275099999999,47.430279],"type":"Point"}
}