{
  "type": "Feature",
  "properties": {
    "iso:country":"US",
    "sg:address":"139 River Butte Dr",
    "sg:city":"Columbia Falls",
    "sg:classifiers":[
        {
            "category":"Travel",
            "subcategory":"Hotels & Motels",
            "type":"Entertainment"
        }
    ],
    "sg:phone":"+1 406 892 8023",
    "sg:postcode":"59912",
    "sg:province":"MT",
    "sg:tags":[
        "operation"
    ],
    "wof:name":"Plum Creek House",
    "wof:placetype":"venue"
},
  "geometry": {"coordinates":[-114.18918499999999,48.355107],"type":"Point"}
}