{
  "type": "Feature",
  "properties": {
    "iso:country":"US",
    "sg:address":"510 Greenwood St",
    "sg:city":"Thompson Falls",
    "sg:classifiers":[
        {
            "category":"Organizations",
            "subcategory":"Religious Organization",
            "type":"Services"
        }
    ],
    "sg:phone":"+1 406 827 4974",
    "sg:postcode":"59873",
    "sg:province":"MT",
    "sg:tags":[
        "church"
    ],
    "wof:name":"Jehovah's Witnesses",
    "wof:placetype":"venue"
},
  "geometry": {"coordinates":[-115.33756700000001,47.598557],"type":"Point"}
}