{
  "type": "Feature",
  "properties": {
    "addr:full":"5400 Tumbleweed Dr Helena MT 59602",
    "addr:housenumber":"5400",
    "addr:postcode":"59602",
    "addr:street":"Tumbleweed Dr",
    "iso:country":"US",
    "sg:address":"5400 Tumbleweed Dr",
    "sg:city":"Helena",
    "sg:classifiers":[
        {
            "category":"Food & Beverages",
            "subcategory":"Groceries & Convenience Stores",
            "type":"Retail Goods"
        }
    ],
    "sg:phone":"+1 406 442 8995",
    "sg:postcode":"59602",
    "sg:province":"MT",
    "wof:name":"Moys Mrshall Cyn Delight Entps",
    "wof:placetype":"venue"
},
  "geometry": {"coordinates":[-112.07080000000001,46.653085],"type":"Point"}
}