{
  "type": "Feature",
  "properties": {
    "iso:country":"US",
    "sg:address":"424 2nd St",
    "sg:city":"Havre",
    "sg:classifiers":[
        {
            "category":"Retail",
            "subcategory":"Auto Repair",
            "type":"Services"
        }
    ],
    "sg:phone":"+1 406 265 3020",
    "sg:postcode":"59501",
    "sg:province":"MT",
    "sg:tags":[
        "shop",
        "automotive",
        "glass",
        "replacement"
    ],
    "wof:name":"Holdens Hot Wheels Inc",
    "wof:placetype":"venue"
},
  "geometry": {"coordinates":[-109.676506,48.552271],"type":"Point"}
}