{
  "type": "Feature",
  "properties": {
    "addr:full":"6330 Dawn Dr Belgrade MT 59714",
    "addr:housenumber":"6330",
    "addr:postcode":"59714",
    "addr:street":"Dawn Dr",
    "iso:country":"US",
    "sg:address":"6330 Dawn Dr",
    "sg:city":"Belgrade",
    "sg:classifiers":[
        {
            "category":"Personal",
            "type":"Services"
        }
    ],
    "sg:phone":"+1 406 388 3043",
    "sg:postcode":"59714",
    "sg:province":"MT",
    "wof:name":"High Plains Storage",
    "wof:placetype":"venue"
},
  "geometry": {"coordinates":[-111.216534,45.876029],"type":"Point"}
}