{
  "type": "Feature",
  "properties": {
    "iso:country":"US",
    "sg:address":"3419 Hannibal St",
    "sg:city":"Butte",
    "sg:classifiers":[
        {
            "category":"Shopping",
            "subcategory":"Bicycles & Sporting Goods",
            "type":"Retail Goods"
        }
    ],
    "sg:phone":"+1 406 494 3680",
    "sg:postcode":"59701",
    "sg:province":"MT",
    "wof:name":"Johns Log Cabin Guns",
    "wof:placetype":"venue"
},
  "geometry": {"coordinates":[-112.479462,45.978063],"type":"Point"}
}