{
  "type": "Feature",
  "properties": {
    "iso:country":"US",
    "sg:address":"5438 Carey Ave",
    "sg:city":"Shepherd",
    "sg:classifiers":[
        {
            "category":"Retail",
            "subcategory":"Auto Repair",
            "type":"Services"
        }
    ],
    "sg:phone":"+1 406 373 6634",
    "sg:postcode":"59079",
    "sg:province":"MT",
    "sg:tags":[
        "repairing",
        "automobile"
    ],
    "wof:name":"Galle's General Repair",
    "wof:placetype":"venue"
},
  "geometry": {"coordinates":[-108.345235,45.943687],"type":"Point"}
}