{
  "type": "Feature",
  "properties": {
    "iso:country":"US",
    "sg:address":"445 Bald Rock Rd",
    "sg:city":"Kalispell",
    "sg:classifiers":[
        {
            "category":"Professional",
            "subcategory":"Engineering",
            "type":"Services"
        }
    ],
    "sg:phone":"+1 406 755 1147",
    "sg:postcode":"59901",
    "sg:province":"MT",
    "wof:name":"A&L Engineering",
    "wof:placetype":"venue"
},
  "geometry": {"coordinates":[-114.444396,48.269852],"type":"Point"}
}