{
  "type": "Feature",
  "properties": {
    "addr:full":"8458 Back Rd Polson MT 59860",
    "addr:housenumber":"8458",
    "addr:postcode":"59860",
    "addr:street":"Back Rd",
    "iso:country":"US",
    "sg:address":"8458 Back Rd",
    "sg:city":"Polson",
    "sg:classifiers":[
        {
            "category":"Farming",
            "subcategory":"Livestock Farm",
            "type":"Manufacturing & Wholesale Goods"
        }
    ],
    "sg:phone":"+1 406 883 2041",
    "sg:postcode":"59860",
    "sg:province":"MT",
    "sg:tags":[
        "beef",
        "feedlot",
        "cattle"
    ],
    "wof:name":"Joel Clairmont",
    "wof:placetype":"venue"
},
  "geometry": {"coordinates":[-114.188367,47.652053],"type":"Point"}
}