{
  "type": "Feature",
  "properties": {
    "iso:country":"US",
    "sg:address":"1500 Lindsay Rd",
    "sg:city":"Eureka",
    "sg:classifiers":[
        {
            "category":"Freight",
            "type":"Transportation"
        }
    ],
    "sg:phone":"+1 406 889 5973",
    "sg:postcode":"59917",
    "sg:province":"MT",
    "sg:tags":[
        "arrangement"
    ],
    "wof:name":"D & D Express Inc",
    "wof:placetype":"venue"
},
  "geometry": {"coordinates":[-115.075783,48.919801],"type":"Point"}
}