{
  "type": "Feature",
  "properties": {
    "iso:country":"US",
    "sg:address":"3221 Blackwood Rd",
    "sg:city":"Bozeman",
    "sg:classifiers":[
        {
            "category":"Professional",
            "subcategory":"Management & Consulting",
            "type":"Services"
        }
    ],
    "sg:phone":"+1 406 586 7814",
    "sg:postcode":"59718",
    "sg:province":"MT",
    "wof:name":"Milestone Financial Service",
    "wof:placetype":"venue"
},
  "geometry": {"coordinates":[-111.13659199999999,45.641887],"type":"Point"}
}