{
  "type": "Feature",
  "properties": {
    "addr:full":"216 Towne Ave Terry MT 59349",
    "addr:housenumber":"216",
    "addr:postcode":"59349",
    "addr:street":"Towne Ave",
    "iso:country":"US",
    "sg:address":"216 Towne Ave",
    "sg:city":"Terry",
    "sg:classifiers":[
        {
            "category":"Government",
            "subcategory":"Post Office",
            "type":"Public Place"
        }
    ],
    "sg:phone":"+1 406 000 1111",
    "sg:postcode":"59349",
    "sg:province":"MT",
    "wof:name":"US Post Office",
    "wof:placetype":"venue"
},
  "geometry": {"coordinates":[-105.30989700000001,46.792615],"type":"Point"}
}