{
  "type": "Feature",
  "properties": {
    "iso:country":"US",
    "sg:address":"7 3rd Ave E",
    "sg:city":"Polson",
    "sg:classifiers":[
        {
            "category":"Shopping",
            "subcategory":"Catalog Store",
            "type":"Retail Goods"
        }
    ],
    "sg:phone":"+1 406 883 3667",
    "sg:postcode":"59860",
    "sg:province":"MT",
    "sg:tags":[
        "mail",
        "house"
    ],
    "wof:name":"J C Penney Catalog",
    "wof:placetype":"venue"
},
  "geometry": {"coordinates":[-114.163321,47.693453],"type":"Point"}
}