{
  "type": "Feature",
  "properties": {
    "iso:country":"US",
    "sg:address":"1900 4th St NW",
    "sg:city":"Great Falls",
    "sg:classifiers":[
        {
            "category":"Personal",
            "subcategory":"Beauty Salon",
            "type":"Services"
        }
    ],
    "sg:phone":"+1 406 454 3608",
    "sg:postcode":"59404",
    "sg:province":"MT",
    "sg:tags":[
        "shop"
    ],
    "wof:name":"Spirit of Design",
    "wof:placetype":"venue"
},
  "geometry": {"coordinates":[-111.32149,47.525928],"type":"Point"}
}