{
  "type": "Feature",
  "properties": {
    "iso:country":"US",
    "sg:address":"344 Giffen Rd",
    "sg:city":"Stockett",
    "sg:phone":"+1 406 736 5780",
    "sg:postcode":"59480",
    "sg:province":"MT",
    "sg:tags":[
        "farm",
        "wheat"
    ],
    "wof:name":"Larry Lord",
    "wof:placetype":"venue"
},
  "geometry": {"coordinates":[-111.19500499999999,47.327038],"type":"Point"}
}