{
  "type": "Feature",
  "properties": {
    "iso:country":"US",
    "sg:address":"95 Spanish Peak Dr",
    "sg:city":"Bozeman",
    "sg:classifiers":[
        {
            "category":"Health Services",
            "subcategory":"Clinic",
            "type":"Services"
        }
    ],
    "sg:phone":"+1 406 582 9496",
    "sg:postcode":"59718",
    "sg:province":"MT",
    "sg:tags":[
        "specialty",
        "outpatient"
    ],
    "wof:name":"Celebration Curves LLC",
    "wof:placetype":"venue"
},
  "geometry": {"coordinates":[-111.183384,45.673001],"type":"Point"}
}