{
  "type": "Feature",
  "properties": {
    "addr:full":"1380 Minnesota Ave Billings MT 59101",
    "addr:housenumber":"1380",
    "addr:postcode":"59101",
    "addr:street":"Minnesota Ave",
    "iso:country":"US",
    "sg:address":"1380 Minnesota Ave",
    "sg:city":"Billings",
    "sg:classifiers":[
        {
            "category":"Wholesale",
            "subcategory":"Medical Equipment & Supplies",
            "type":"Manufacturing & Wholesale Goods"
        }
    ],
    "sg:phone":"+1 406 245 9660",
    "sg:postcode":"59101",
    "sg:province":"MT",
    "wof:name":"Provet Veterinary Supply",
    "wof:placetype":"venue"
},
  "geometry": {"coordinates":[-108.491953,45.786196],"type":"Point"}
}