{
  "type": "Feature",
  "properties": {
    "addr:full":"204 Logan Ave Terry MT 59349",
    "addr:housenumber":"204",
    "addr:postcode":"59349",
    "addr:street":"Logan Ave",
    "iso:country":"US",
    "sg:address":"204 Logan Ave",
    "sg:city":"Terry",
    "sg:classifiers":[
        {
            "category":"Utilities",
            "subcategory":"Electric",
            "type":"Services"
        }
    ],
    "sg:phone":"+1 406 635 5515",
    "sg:postcode":"59349",
    "sg:province":"MT",
    "sg:tags":[
        "company"
    ],
    "wof:name":"Tongue River Electric Coop Inc",
    "wof:placetype":"venue"
},
  "geometry": {"coordinates":[-105.312899,46.791645],"type":"Point"}
}