{
  "type": "Feature",
  "properties": {
    "addr:full":"307 S 10th St Livingston MT 59047",
    "addr:housenumber":"307",
    "addr:postcode":"59047",
    "addr:street":"S 10Th St",
    "iso:country":"US",
    "sg:address":"307 S 10th St",
    "sg:city":"Livingston",
    "sg:classifiers":[
        {
            "category":"Shopping",
            "subcategory":"Bicycles & Sporting Goods",
            "type":"Retail Goods"
        }
    ],
    "sg:phone":"+1 406 222 3562",
    "sg:postcode":"59047",
    "sg:province":"MT",
    "sg:tags":[
        "outfitter"
    ],
    "wof:name":"John Greene's Fly Fishing",
    "wof:placetype":"venue"
},
  "geometry": {"coordinates":[-110.567922,45.653819],"type":"Point"}
}