{
  "type": "Feature",
  "properties": {
    "iso:country":"US",
    "sg:address":"1040 55th Ave S",
    "sg:city":"Great Falls",
    "sg:classifiers":[
        {
            "category":"Recreation",
            "type":"Entertainment"
        }
    ],
    "sg:phone":"+1 406 761 4275",
    "sg:postcode":"59405",
    "sg:province":"MT",
    "wof:name":"Smileys Gymnastics",
    "wof:placetype":"venue"
},
  "geometry": {"coordinates":[-111.291522,47.443133],"type":"Point"}
}