{
  "type": "Feature",
  "properties": {
    "iso:country":"US",
    "sg:address":"726 Karrow Ave",
    "sg:city":"Whitefish",
    "sg:classifiers":[
        {
            "category":"Manufacturing",
            "subcategory":"Lumber",
            "type":"Manufacturing & Wholesale Goods"
        }
    ],
    "sg:phone":"+1 406 862 5468",
    "sg:postcode":"59937",
    "sg:province":"MT",
    "sg:tags":[
        "forestry"
    ],
    "wof:name":"Brock Wilson Enterprises",
    "wof:placetype":"venue"
},
  "geometry": {"coordinates":[-114.35201499999999,48.405081],"type":"Point"}
}