{
  "type": "Feature",
  "properties": {
    "iso:country":"US",
    "sg:address":"618 Pemberton Ln",
    "sg:city":"Billings",
    "sg:classifiers":[
        {
            "category":"Building & Trades",
            "subcategory":"Construction",
            "type":"Services"
        }
    ],
    "sg:phone":"+1 406 245 5354",
    "sg:postcode":"59105",
    "sg:province":"MT",
    "sg:tags":[
        "house"
    ],
    "wof:name":"Andresen Homes LLC",
    "wof:placetype":"venue"
},
  "geometry": {"coordinates":[-108.475124,45.8408],"type":"Point"}
}