{
  "type": "Feature",
  "properties": {
    "iso:country":"US",
    "sg:address":"208 Pinckney St",
    "sg:city":"Hamilton",
    "sg:classifiers":[
        {
            "category":"Professional",
            "subcategory":"Computer Services",
            "type":"Services"
        }
    ],
    "sg:phone":"+1 406 363 6321",
    "sg:postcode":"59840",
    "sg:province":"MT",
    "sg:tags":[
        "consultant",
        "designer"
    ],
    "sg:website":"www.top-down.com",
    "wof:name":"Top-Down Computer Consultants",
    "wof:placetype":"venue"
},
  "geometry": {"coordinates":[-114.157346,46.248181],"type":"Point"}
}