{
  "type": "Feature",
  "properties": {
    "addr:full":"81680 Gallatin Rd Bozeman MT 59718",
    "addr:housenumber":"81680",
    "addr:postcode":"59718",
    "addr:street":"Gallatin Rd",
    "iso:country":"US",
    "sg:address":"81680 Gallatin Rd",
    "sg:city":"Bozeman",
    "sg:classifiers":[
        {
            "category":"Autos & Motor Vehicles",
            "subcategory":"Motorcycle Sales",
            "type":"Retail Goods"
        }
    ],
    "sg:phone":"+1 406 587 1473",
    "sg:postcode":"59718",
    "sg:province":"MT",
    "sg:tags":[
        "all"
    ],
    "wof:name":"Powerplay Motor Sports",
    "wof:placetype":"venue"
},
  "geometry": {"coordinates":[-111.185703,45.6682],"type":"Point"}
}