{
  "type": "Feature",
  "properties": {
    "iso:country":"US",
    "sg:address":"2021 Custer Ave",
    "sg:city":"Billings",
    "sg:classifiers":[
        {
            "category":"Retail",
            "subcategory":"Auto Repair",
            "type":"Services"
        }
    ],
    "sg:phone":"+1 406 655 0645",
    "sg:postcode":"59102",
    "sg:province":"MT",
    "sg:tags":[
        "repairing",
        "automobile"
    ],
    "wof:name":"Virg's Auto & Truck Repair",
    "wof:placetype":"venue"
},
  "geometry": {"coordinates":[-108.56810299999999,45.77625],"type":"Point"}
}