{
  "type": "Feature",
  "properties": {
    "iso:country":"US",
    "sg:address":"202 S Main St",
    "sg:city":"Kevin",
    "sg:classifiers":[
        {
            "category":"Building & Trades",
            "subcategory":"Construction",
            "type":"Services"
        }
    ],
    "sg:phone":"+1 406 337 2830",
    "sg:postcode":"59425",
    "sg:province":"MT",
    "sg:tags":[
        "roofing",
        "contractor"
    ],
    "wof:name":"Stene Spray Systems",
    "wof:placetype":"venue"
},
  "geometry": {"coordinates":[-111.945441,48.171549],"type":"Point"}
}