{
  "type": "Feature",
  "properties": {
    "addr:full":"1018 Burlington Ave Missoula MT 59801",
    "addr:housenumber":"1018",
    "addr:postcode":"59801",
    "addr:street":"Burlington Ave",
    "iso:country":"US",
    "sg:address":"1018 Burlington Ave",
    "sg:city":"Missoula",
    "sg:classifiers":[
        {
            "category":"Insurance",
            "subcategory":"Insurance Agent",
            "type":"Services"
        }
    ],
    "sg:phone":"+1 406 542 0316",
    "sg:postcode":"59801",
    "sg:province":"MT",
    "wof:name":"Mountain Agency Inc",
    "wof:placetype":"venue"
},
  "geometry": {"coordinates":[-114.01454200000001,46.855214],"type":"Point"}
}