{
  "type": "Feature",
  "properties": {
    "addr:full":"1200 S Reserve St Missoula MT 59801",
    "addr:housenumber":"1200",
    "addr:postcode":"59801",
    "addr:street":"S Reserve St",
    "iso:country":"US",
    "sg:address":"1200 S Reserve St",
    "sg:city":"Missoula",
    "sg:classifiers":[
        {
            "category":"Organizations",
            "subcategory":"Membership Organization",
            "type":"Services"
        }
    ],
    "sg:phone":"+1 406 829 5500",
    "sg:postcode":"59801",
    "sg:province":"MT",
    "wof:name":"AAA",
    "wof:placetype":"venue"
},
  "geometry": {"coordinates":[-114.039563,46.859643],"type":"Point"}
}