{
  "type": "Feature",
  "properties": {
    "iso:country":"US",
    "sg:address":"907 13th Ave NE",
    "sg:city":"Poplar",
    "sg:classifiers":[
        {
            "category":"Professional",
            "subcategory":"Secretarial Services",
            "type":"Services"
        }
    ],
    "sg:phone":"+1 406 768 3799",
    "sg:postcode":"59255",
    "sg:province":"MT",
    "sg:tags":[
        "reporting",
        "court"
    ],
    "wof:name":"AWL Desktop Svc",
    "wof:placetype":"venue"
},
  "geometry": {"coordinates":[-105.173057,48.117875],"type":"Point"}
}