{
  "type": "Feature",
  "properties": {
    "iso:country":"US",
    "sg:address":"2607 Howard Ave",
    "sg:city":"Billings",
    "sg:classifiers":[
        {
            "category":"Building & Trades",
            "subcategory":"Construction",
            "type":"Services"
        }
    ],
    "sg:phone":"+1 406 861 1272",
    "sg:postcode":"59102",
    "sg:province":"MT",
    "sg:tags":[
        "general",
        "contractor"
    ],
    "wof:name":"K & N Construction",
    "wof:placetype":"venue"
},
  "geometry": {"coordinates":[-108.583983,45.773736],"type":"Point"}
}