{
  "type": "Feature",
  "properties": {
    "iso:country":"US",
    "sg:address":"150 Sheafman Creek Rd",
    "sg:city":"Victor",
    "sg:classifiers":[
        {
            "category":"Professional",
            "subcategory":"Business Services",
            "type":"Services"
        }
    ],
    "sg:phone":"+1 406 363 4120",
    "sg:postcode":"59875",
    "sg:province":"MT",
    "sg:tags":[
        "interior",
        "consultant",
        "design",
        "decorator"
    ],
    "wof:name":"Classic Interiors",
    "wof:placetype":"venue"
},
  "geometry": {"coordinates":[-114.15942,46.341991],"type":"Point"}
}