{
  "type": "Feature",
  "properties": {
    "addr:full":"457 Daniel St Billings MT 59101",
    "addr:housenumber":"457",
    "addr:postcode":"59101",
    "addr:street":"Daniel St",
    "iso:country":"US",
    "sg:address":"457 Daniel St",
    "sg:city":"Billings",
    "sg:classifiers":[
        {
            "category":"Freight",
            "type":"Transportation"
        }
    ],
    "sg:phone":"+1 406 256 1006",
    "sg:postcode":"59101",
    "sg:province":"MT",
    "sg:tags":[
        "trucking"
    ],
    "wof:name":"Watkin & Shepard Trucking",
    "wof:placetype":"venue"
},
  "geometry": {"coordinates":[-108.554362,45.766054],"type":"Point"}
}