{
  "type": "Feature",
  "properties": {
    "addr:full":"3233 Kennedy Ave Butte MT 59701",
    "addr:housenumber":"3233",
    "addr:postcode":"mt 59701",
    "addr:street":"Kennedy Ave",
    "iso:country":"US",
    "sg:address":"3233 Kennedy Ave",
    "sg:city":"Butte",
    "sg:classifiers":[
        {
            "category":"Recreation",
            "type":"Entertainment"
        }
    ],
    "sg:phone":"+1 406 494 2754",
    "sg:postcode":"59701",
    "sg:province":"MT",
    "sg:tags":[
        "martial",
        "arts",
        "instruction"
    ],
    "wof:name":"Rocky Mountain Martial Arts",
    "wof:placetype":"venue"
},
  "geometry": {"coordinates":[-112.514231,45.978305],"type":"Point"}
}