{
  "type": "Feature",
  "properties": {
    "addr:full":"2810 Elm St Butte MT 59701",
    "addr:housenumber":"2810",
    "addr:postcode":"mt 59701",
    "addr:street":"Elm St",
    "iso:country":"US",
    "sg:address":"2810 Elm St",
    "sg:city":"Butte",
    "sg:classifiers":[
        {
            "category":"Freight",
            "type":"Transportation"
        }
    ],
    "sg:phone":"+1 406 782 3349",
    "sg:postcode":"59701",
    "sg:province":"MT",
    "sg:tags":[
        "commercial",
        "storage"
    ],
    "wof:name":"A To Z Mini Storage",
    "wof:placetype":"venue"
},
  "geometry": {"coordinates":[-112.49312999999999,46.000883],"type":"Point"}
}