{
  "type": "Feature",
  "properties": {
    "iso:country":"US",
    "sg:address":"201 S Wallace Ave",
    "sg:city":"Bozeman",
    "sg:classifiers":[
        {
            "category":"Professional",
            "subcategory":"Business Services",
            "type":"Services"
        }
    ],
    "sg:phone":"+1 406 522 9892",
    "sg:postcode":"59715",
    "sg:province":"MT",
    "sg:tags":[
        "recording",
        "studio"
    ],
    "wof:name":"Mara KATZ Gai Studio",
    "wof:placetype":"venue"
},
  "geometry": {"coordinates":[-111.02853,45.67736],"type":"Point"}
}