{
  "type": "Feature",
  "properties": {
    "addr:full":"1 2nd Ave E Polson MT 59860",
    "addr:housenumber":"1",
    "addr:postcode":"59860",
    "addr:street":"2Nd Ave E",
    "iso:country":"US",
    "sg:address":"1 2nd Ave E",
    "sg:city":"Polson",
    "sg:classifiers":[
        {
            "category":"Personal",
            "subcategory":"Beauty Salon",
            "type":"Services"
        }
    ],
    "sg:phone":"+1 406 883 0707",
    "sg:postcode":"59860",
    "sg:province":"MT",
    "sg:tags":[
        "shop"
    ],
    "wof:name":"Hair Etc",
    "wof:placetype":"venue"
},
  "geometry": {"coordinates":[-114.163372,47.694416],"type":"Point"}
}