{
  "type": "Feature",
  "properties": {
    "iso:country":"US",
    "sg:address":"2416 Quinn Haven Dr",
    "sg:city":"Billings",
    "sg:classifiers":[
        {
            "category":"Retail",
            "subcategory":"Animal Services",
            "type":"Services"
        }
    ],
    "sg:phone":"+1 406 656 5443",
    "sg:postcode":"59102",
    "sg:province":"MT",
    "wof:name":"American Black Mximizer Cattle",
    "wof:placetype":"venue"
},
  "geometry": {"coordinates":[-108.610138,45.794475],"type":"Point"}
}