{
  "type": "Feature",
  "properties": {
    "addr:full":"2416 Quinn Haven Dr Billings MT 59102",
    "addr:housenumber":"2416",
    "addr:postcode":"59102",
    "addr:street":"Quinn Haven Dr",
    "iso:country":"US",
    "sg:address":"2416 Quinn Haven Dr",
    "sg:city":"Billings",
    "sg:classifiers":[
        {
            "category":"Retail",
            "subcategory":"Animal Services",
            "type":"Services"
        }
    ],
    "sg:phone":"+1 406 656 5443",
    "sg:postcode":"59102",
    "sg:province":"MT",
    "wof:name":"American Black Mximizer Cattle",
    "wof:placetype":"venue"
},
  "geometry": {"coordinates":[-108.61013800000001,45.794475],"type":"Point"}
}