{
  "type": "Feature",
  "properties": {
    "iso:country":"US",
    "sg:address":"136 Main St",
    "sg:city":"Roundup",
    "sg:classifiers":[
        {
            "category":"Shopping",
            "subcategory":"Used Merchandise",
            "type":"Retail Goods"
        }
    ],
    "sg:phone":"+1 406 323 1333",
    "sg:postcode":"59072",
    "sg:province":"MT",
    "wof:name":"Bull Mountain Trading Co",
    "wof:placetype":"venue"
},
  "geometry": {"coordinates":[-108.541885,46.442176],"type":"Point"}
}