{
  "type": "Feature",
  "properties": {
    "addr:full":"2037 Aberdeen St Butte MT 59701",
    "addr:housenumber":"2037",
    "addr:postcode":"mt 59701",
    "addr:street":"Aberdeen St",
    "iso:country":"US",
    "sg:address":"2037 Aberdeen St",
    "sg:city":"Butte",
    "sg:classifiers":[
        {
            "category":"Professional",
            "subcategory":"Lawyer & Legal Services",
            "type":"Services"
        }
    ],
    "sg:phone":"+1 406 723 3027",
    "sg:postcode":"59701",
    "sg:province":"MT",
    "wof:name":"Keith A Christie",
    "wof:placetype":"venue"
},
  "geometry": {"coordinates":[-112.508707,45.997737],"type":"Point"}
}