{
  "type": "Feature",
  "properties": {
    "iso:country":"US",
    "sg:address":"516 S 8th Ave",
    "sg:city":"Bozeman",
    "sg:classifiers":[
        {
            "category":"Freight",
            "type":"Transportation"
        }
    ],
    "sg:phone":"+1 406 586 3147",
    "sg:postcode":"59715",
    "sg:province":"MT",
    "sg:tags":[
        "storage"
    ],
    "wof:name":"Portable Storage",
    "wof:placetype":"venue"
},
  "geometry": {"coordinates":[-111.047887,45.674139],"type":"Point"}
}