{
  "type": "Feature",
  "properties": {
    "iso:country":"US",
    "sg:address":"303 Us Highway 2 E",
    "sg:city":"Wolf Point",
    "sg:classifiers":[
        {
            "category":"Restaurant",
            "type":"Food & Drink"
        }
    ],
    "sg:menulink":"http://www.allmenus.com/mt/fort-peck-reservation/211601-mcdonalds/menu/",
    "sg:phone":"+1 406 653 1788",
    "sg:postcode":"59201",
    "sg:province":"MT",
    "sg:tags":[
        "burger",
        "american"
    ],
    "wof:name":"McDonald's",
    "wof:placetype":"venue"
},
  "geometry": {"coordinates":[-105.641138,48.094218],"type":"Point"}
}