{
  "type": "Feature",
  "properties": {
    "addr:full":"500 N Railway Ave Fallon MT 59326",
    "addr:housenumber":"500",
    "addr:postcode":"59326",
    "addr:street":"N Railway Ave",
    "iso:country":"US",
    "sg:address":"500 N Railway Ave",
    "sg:city":"Fallon",
    "sg:classifiers":[
        {
            "category":"Government",
            "subcategory":"Post Office",
            "type":"Public Place"
        }
    ],
    "sg:phone":"+1 406 486 5503",
    "sg:postcode":"59326",
    "sg:province":"MT",
    "wof:name":"US Post Office",
    "wof:placetype":"venue"
},
  "geometry": {"coordinates":[-105.120012,46.835485],"type":"Point"}
}