{
  "type": "Feature",
  "properties": {
    "addr:full":"453 Newman Ln Billings MT 59101",
    "addr:housenumber":"453",
    "addr:postcode":"59101",
    "addr:street":"Newman Ln",
    "iso:country":"US",
    "sg:address":"453 Newman Ln",
    "sg:city":"Billings",
    "sg:classifiers":[
        {
            "category":"Home & Garden",
            "subcategory":"Carpets & Floor Coverings",
            "type":"Retail Goods"
        }
    ],
    "sg:phone":"+1 406 259 5242",
    "sg:postcode":"59101",
    "sg:province":"MT",
    "sg:tags":[
        "installation"
    ],
    "wof:name":"L & R Carpet",
    "wof:placetype":"venue"
},
  "geometry": {"coordinates":[-108.53306600000001,45.759983],"type":"Point"}
}