{
  "type": "Feature",
  "properties": {
    "addr:full":"621 3rd St S Glasgow MT 59230",
    "addr:housenumber":"621",
    "addr:postcode":"59230",
    "addr:street":"3Rd St S",
    "iso:country":"US",
    "sg:address":"621 3rd St S",
    "sg:city":"Glasgow",
    "sg:classifiers":[
        {
            "category":"Shopping",
            "type":"Retail Goods"
        },
        {
            "category":"Health Services",
            "subcategory":"Hospital",
            "type":"Services"
        }
    ],
    "sg:phone":"+1 406 228 4351",
    "sg:postcode":"59230",
    "sg:province":"MT",
    "sg:tags":[
        "supply",
        "medical",
        "hearing",
        "equipment",
        "impaired",
        "general"
    ],
    "sg:website":"www.fmdh.org",
    "wof:name":"Deaconess Frances Mahon Hosp",
    "wof:placetype":"venue"
},
  "geometry": {"coordinates":[-106.63624799999999,48.189839],"type":"Point"}
}