{
  "type": "Feature",
  "properties": {
    "addr:full":"2109 1st Ave N Billings MT 59101",
    "addr:housenumber":"2109",
    "addr:postcode":"59101",
    "addr:street":"1St Ave N",
    "iso:country":"US",
    "sg:address":"2109 1st Ave N",
    "sg:city":"Billings",
    "sg:classifiers":[
        {
            "category":"Autos & Motor Vehicles",
            "subcategory":"Automobile Sales",
            "type":"Retail Goods"
        }
    ],
    "sg:phone":"+1 406 252 5933",
    "sg:postcode":"59101",
    "sg:province":"MT",
    "wof:name":"Demint Motor Co",
    "wof:placetype":"venue"
},
  "geometry": {"coordinates":[-108.498424,45.785768],"type":"Point"}
}