{
  "type": "Feature",
  "properties": {
    "addr:full":"903 Conrad Dr Kalispell MT 59901",
    "addr:housenumber":"903",
    "addr:postcode":"59901",
    "addr:street":"Conrad Dr",
    "iso:country":"US",
    "sg:address":"903 Conrad Dr",
    "sg:city":"Kalispell",
    "sg:classifiers":[
        {
            "category":"Building & Trades",
            "subcategory":"Electrical",
            "type":"Services"
        }
    ],
    "sg:phone":"+1 406 756 0444",
    "sg:postcode":"59901",
    "sg:province":"MT",
    "sg:tags":[
        "electrical",
        "contractor"
    ],
    "wof:name":"Control Electric",
    "wof:placetype":"venue"
},
  "geometry": {"coordinates":[-114.269099,48.208699],"type":"Point"}
}