{
  "type": "Feature",
  "properties": {
    "iso:country":"US",
    "sg:address":"2846 E Fork Rd",
    "sg:city":"Sula",
    "sg:classifiers":[
        {
            "category":"Building & Trades",
            "subcategory":"Construction",
            "type":"Services"
        }
    ],
    "sg:phone":"+1 406 961 4441",
    "sg:postcode":"59871",
    "sg:province":"MT",
    "sg:tags":[
        "excavating",
        "contractor"
    ],
    "wof:name":"Gasvoda Construction",
    "wof:placetype":"venue"
},
  "geometry": {"coordinates":[-113.738794,45.915365],"type":"Point"}
}