{
  "type": "Feature",
  "properties": {
    "addr:full":"2611 Minnesota Ave Billings MT 59101",
    "addr:housenumber":"2611",
    "addr:postcode":"59101",
    "addr:street":"Minnesota Ave",
    "iso:country":"US",
    "sg:address":"2611 Minnesota Ave",
    "sg:city":"Billings",
    "sg:classifiers":[
        {
            "category":"Retail",
            "subcategory":"Repair Shop",
            "type":"Services"
        }
    ],
    "sg:phone":"+1 406 256 5663",
    "sg:postcode":"59101",
    "sg:province":"MT",
    "sg:tags":[
        "scooter",
        "motorcycle",
        "motor"
    ],
    "wof:name":"Doc's Speed & Custom",
    "wof:placetype":"venue"
},
  "geometry": {"coordinates":[-108.502771,45.78116],"type":"Point"}
}