{
  "type": "Feature",
  "properties": {
    "addr:full":"505 S 24th St W Billings MT 59102",
    "addr:housenumber":"505",
    "addr:postcode":"59102",
    "addr:street":"S 24Th St W",
    "iso:country":"US",
    "sg:address":"505 S 24th St W",
    "sg:city":"Billings",
    "sg:classifiers":[
        {
            "category":"Home & Garden",
            "subcategory":"Carpets & Floor Coverings",
            "type":"Retail Goods"
        }
    ],
    "sg:phone":"+1 406 656 9300",
    "sg:postcode":"59102",
    "sg:province":"MT",
    "sg:tags":[
        "dealer",
        "rug"
    ],
    "sg:website":"www.carpetone.com",
    "wof:name":"Carpet One",
    "wof:placetype":"venue"
},
  "geometry": {"coordinates":[-108.57605100000001,45.759937],"type":"Point"}
}