{
  "type": "Feature",
  "properties": {
    "iso:country":"US",
    "sg:address":"265 Clairmont Rd",
    "sg:city":"Ronan",
    "sg:classifiers":[
        {
            "category":"Building & Trades",
            "subcategory":"Construction",
            "type":"Services"
        }
    ],
    "sg:phone":"+1 406 675 3118",
    "sg:postcode":"59864",
    "sg:province":"MT",
    "sg:tags":[
        "contractor"
    ],
    "wof:name":"Blue Ribbon Cnstr & Insul",
    "wof:placetype":"venue"
},
  "geometry": {"coordinates":[-114.106505,47.602266],"type":"Point"}
}