{
  "type": "Feature",
  "properties": {
    "iso:country":"US",
    "sg:address":"2012 Farragut Ave",
    "sg:city":"Butte",
    "sg:classifiers":[
        {
            "category":"Health Services",
            "subcategory":"Doctor",
            "type":"Services"
        }
    ],
    "sg:phone":"+1 406 723 7990",
    "sg:postcode":"59701",
    "sg:province":"MT",
    "sg:tags":[
        "medical"
    ],
    "wof:name":"Komm Brian Doctor of Pod",
    "wof:placetype":"venue"
},
  "geometry": {"coordinates":[-112.502656,45.993779],"type":"Point"}
}