{
  "type": "Feature",
  "properties": {
    "iso:country":"US",
    "sg:address":"505 W Main St",
    "sg:city":"Lewistown",
    "sg:classifiers":[
        {
            "category":"Professional",
            "subcategory":"Accounting & Tax Preparation",
            "type":"Services"
        }
    ],
    "sg:phone":"+1 406 538 8868",
    "sg:postcode":"59457",
    "sg:province":"MT",
    "sg:tags":[
        "accountant",
        "public",
        "certified"
    ],
    "wof:name":"Russel J Spika CPA",
    "wof:placetype":"venue"
},
  "geometry": {"coordinates":[-109.428994,47.063335],"type":"Point"}
}