{
  "type": "Feature",
  "properties": {
    "iso:country":"US",
    "sg:address":"1627 1st St NW",
    "sg:city":"Great Falls",
    "sg:classifiers":[
        {
            "category":"Personal",
            "subcategory":"Beauty Salon",
            "type":"Services"
        }
    ],
    "sg:phone":"+1 406 727 0491",
    "sg:postcode":"59404",
    "sg:province":"MT",
    "sg:tags":[
        "shop"
    ],
    "wof:name":"Hat Rack",
    "wof:placetype":"venue"
},
  "geometry": {"coordinates":[-111.312638,47.521731],"type":"Point"}
}