{
  "type": "Feature",
  "properties": {
    "iso:country":"US",
    "sg:address":"302 N 31st St",
    "sg:city":"Billings",
    "sg:classifiers":[
        {
            "category":"Banks & Credit Unions",
            "subcategory":"Bank",
            "type":"Services"
        }
    ],
    "sg:phone":"+1 406 255 5290",
    "sg:postcode":"59101",
    "sg:province":"MT",
    "sg:website":"www.firstinterstatebank.com",
    "wof:name":"First Interstate Bank",
    "wof:placetype":"venue"
},
  "geometry": {"coordinates":[-108.511987,45.78279],"type":"Point"}
}