{
  "type": "Feature",
  "properties": {
    "addr:full":"2096 US Hwy 93 Victor MT 59875",
    "addr:housenumber":"2096",
    "addr:postcode":"59875",
    "addr:street":"Us Hwy 93 Victor",
    "iso:country":"US",
    "sg:address":"2096 US Hwy 93",
    "sg:city":"Victor",
    "sg:classifiers":[
        {
            "category":"Manufacturing",
            "subcategory":"Building Materials",
            "type":"Manufacturing & Wholesale Goods"
        }
    ],
    "sg:phone":"+1 406 642 3701",
    "sg:postcode":"59875",
    "sg:province":"MT",
    "sg:tags":[
        "cabinet"
    ],
    "wof:name":"Linley's Cabinet Co",
    "wof:placetype":"venue"
},
  "geometry": {"coordinates":[-114.144231,46.397614],"type":"Point"}
}