{
  "type": "Feature",
  "properties": {
    "iso:country":"US",
    "sg:address":"115 N Broadway",
    "sg:city":"Billings",
    "sg:classifiers":[
        {
            "category":"Professional",
            "subcategory":"Accounting & Tax Preparation",
            "type":"Services"
        }
    ],
    "sg:phone":"+1 406 254 6399",
    "sg:postcode":"59101",
    "sg:province":"MT",
    "sg:tags":[
        "billing"
    ],
    "wof:name":"P A Accounts",
    "wof:placetype":"venue"
},
  "geometry": {"coordinates":[-108.50646399999999,45.782892],"type":"Point"}
}