{
  "type": "Feature",
  "properties": {
    "addr:full":"1194 E Idaho St Kalispell MT 59901",
    "addr:housenumber":"1194",
    "addr:postcode":"59901",
    "addr:street":"E Idaho St",
    "iso:country":"US",
    "sg:address":"1194 E Idaho St",
    "sg:city":"Kalispell",
    "sg:classifiers":[
        {
            "category":"Autos & Motor Vehicles",
            "subcategory":"Auto Supplies",
            "type":"Retail Goods"
        }
    ],
    "sg:phone":"+1 406 752 1156",
    "sg:postcode":"59901",
    "sg:province":"MT",
    "sg:tags":[
        "alternator",
        "generator"
    ],
    "wof:name":"Lasalle Automotive",
    "wof:placetype":"venue"
},
  "geometry": {"coordinates":[-114.29042699999999,48.209479],"type":"Point"}
}