{
  "type": "Feature",
  "properties": {
    "iso:country":"US",
    "sg:address":"1015 W Clark St",
    "sg:city":"Livingston",
    "sg:classifiers":[
        {
            "category":"Education",
            "subcategory":"School",
            "type":"Public Place"
        }
    ],
    "sg:phone":"+1 406 222 0192",
    "sg:postcode":"59047",
    "sg:province":"MT",
    "wof:name":"B A Winans Elementary School",
    "wof:placetype":"venue"
},
  "geometry": {"coordinates":[-110.568123,45.653696],"type":"Point"}
}