{
  "type": "Feature",
  "properties": {
    "iso:country":"US",
    "sg:address":"17 1st Ave E",
    "sg:city":"Kalispell",
    "sg:classifiers":[
        {
            "category":"Insurance",
            "subcategory":"Insurance Agent",
            "type":"Services"
        }
    ],
    "sg:phone":"+1 406 752 8693",
    "sg:postcode":"59901",
    "sg:province":"MT",
    "sg:tags":[
        "agency"
    ],
    "wof:name":"Glacier Insurance",
    "wof:placetype":"venue"
},
  "geometry": {"coordinates":[-114.31219,48.198887],"type":"Point"}
}