{
  "type": "Feature",
  "properties": {
    "iso:country":"US",
    "sg:address":"205 8th Ave NW",
    "sg:city":"Ronan",
    "sg:classifiers":[
        {
            "category":"Professional",
            "subcategory":"Business Services",
            "type":"Services"
        }
    ],
    "sg:phone":"+1 406 676 4560",
    "sg:postcode":"59864",
    "sg:province":"MT",
    "wof:name":"Montana Education Association",
    "wof:placetype":"venue"
},
  "geometry": {"coordinates":[-114.109375,47.531917],"type":"Point"}
}