{
  "type": "Feature",
  "properties": {
    "addr:full":"2919 Main St Miles City MT 59301",
    "addr:housenumber":"2919",
    "addr:postcode":"59301",
    "addr:street":"Main St",
    "iso:country":"US",
    "sg:address":"2919 Main St",
    "sg:city":"Miles City",
    "sg:classifiers":[
        {
            "category":"Home & Garden",
            "subcategory":"Building Materials",
            "type":"Retail Goods"
        }
    ],
    "sg:phone":"+1 406 232 6673",
    "sg:postcode":"59301",
    "sg:province":"MT",
    "sg:tags":[
        "wood",
        "burning",
        "st",
        "paint",
        "lumber",
        "carpeting"
    ],
    "wof:name":"Building Center Inc",
    "wof:placetype":"venue"
},
  "geometry": {"coordinates":[-105.824468,46.408431],"type":"Point"}
}