{
  "type": "Feature",
  "properties": {
    "addr:full":"9730 Derby Dr Missoula MT 59808",
    "addr:housenumber":"9730",
    "addr:postcode":"59808",
    "addr:street":"Derby Dr",
    "iso:country":"US",
    "sg:address":"9730 Derby Dr",
    "sg:city":"Missoula",
    "sg:classifiers":[
        {
            "category":"Freight",
            "type":"Transportation"
        }
    ],
    "sg:phone":"+1 406 721 5151",
    "sg:postcode":"59808",
    "sg:province":"MT",
    "sg:tags":[
        "distance",
        "long",
        "trucking"
    ],
    "sg:website":"www.jimpalmertrucking.com",
    "wof:name":"Jim Palmer Trucking",
    "wof:placetype":"venue"
},
  "geometry": {"coordinates":[-114.133039,46.944532],"type":"Point"}
}