{
  "type": "Feature",
  "properties": {
    "iso:country":"US",
    "sg:address":"45 Stockade Rd",
    "sg:city":"Absarokee",
    "sg:classifiers":[
        {
            "category":"Farming",
            "subcategory":"Livestock Farm",
            "type":"Manufacturing & Wholesale Goods"
        }
    ],
    "sg:phone":"+1 406 932 4452",
    "sg:postcode":"59001",
    "sg:province":"MT",
    "sg:tags":[
        "ranch"
    ],
    "wof:name":"Stoney Lonesome Ranch",
    "wof:placetype":"venue"
},
  "geometry": {"coordinates":[-109.629026,45.558169],"type":"Point"}
}