{
  "type": "Feature",
  "properties": {
    "addr:full":"1225 2nd Ave E Kalispell MT 59901",
    "addr:housenumber":"1225",
    "addr:postcode":"59901",
    "addr:street":"2Nd Ave E",
    "iso:country":"US",
    "sg:address":"1225 2nd Ave E",
    "sg:city":"Kalispell",
    "sg:classifiers":[
        {
            "category":"Social Services",
            "type":"Services"
        }
    ],
    "sg:phone":"+1 406 257 7571",
    "sg:postcode":"59901",
    "sg:province":"MT",
    "sg:tags":[
        "organization",
        "welfare"
    ],
    "wof:name":"Mental Health Ctr",
    "wof:placetype":"venue"
},
  "geometry": {"coordinates":[-114.306316,48.187353],"type":"Point"}
}