{
  "type": "Feature",
  "properties": {
    "iso:country":"US",
    "sg:address":"175 S 2nd St",
    "sg:city":"Hamilton",
    "sg:classifiers":[
        {
            "category":"Shopping",
            "subcategory":"Clothing, Apparel, & Fashions",
            "type":"Retail Goods"
        }
    ],
    "sg:phone":"+1 406 363 3660",
    "sg:postcode":"59840",
    "sg:province":"MT",
    "sg:tags":[
        "t"
    ],
    "wof:name":"Mystic Shirts Etc",
    "wof:placetype":"venue"
},
  "geometry": {"coordinates":[-114.15712000000001,46.24624],"type":"Point"}
}