{
  "type": "Feature",
  "properties": {
    "addr:full":"897 Bourne Loop Victor MT 59875",
    "addr:housenumber":"897",
    "addr:postcode":"59875",
    "addr:street":"Bourne Loop Victor",
    "iso:country":"US",
    "sg:address":"897 Bourne Loop",
    "sg:city":"Victor",
    "sg:classifiers":[
        {
            "category":"Home & Garden",
            "subcategory":"Home Furnishings",
            "type":"Retail Goods"
        }
    ],
    "sg:phone":"+1 406 961 2400",
    "sg:postcode":"59875",
    "sg:province":"MT",
    "sg:tags":[
        "lighting",
        "fixture"
    ],
    "wof:name":"Ragged Mountain Antler",
    "wof:placetype":"venue"
},
  "geometry": {"coordinates":[-114.228517,46.348533],"type":"Point"}
}