{
  "type": "Feature",
  "properties": {
    "iso:country":"US",
    "sg:address":"4939 Shepherd Acton Rd",
    "sg:city":"Shepherd",
    "sg:classifiers":[
        {
            "category":"Retail",
            "subcategory":"Auto Repair",
            "type":"Services"
        }
    ],
    "sg:phone":"+1 406 698 8791",
    "sg:postcode":"59079",
    "sg:province":"MT",
    "sg:tags":[
        "wrecker"
    ],
    "wof:name":"Big Sky Towing & Auto Repair",
    "wof:placetype":"venue"
},
  "geometry": {"coordinates":[-108.361542,45.943814],"type":"Point"}
}