{
  "type": "Feature",
  "properties": {
    "iso:country":"US",
    "sg:address":"105 6th Ave W",
    "sg:city":"Kalispell",
    "sg:classifiers":[
        {
            "category":"Social Services",
            "type":"Services"
        }
    ],
    "sg:phone":"+1 406 752 3663",
    "sg:postcode":"59901",
    "sg:province":"MT",
    "wof:name":"Flathead Food Bank Inc",
    "wof:placetype":"venue"
},
  "geometry": {"coordinates":[-114.322228,48.19631],"type":"Point"}
}