{
  "type": "Feature",
  "properties": {
    "iso:country":"US",
    "sg:address":"1004 18th Ave SW",
    "sg:city":"Great Falls",
    "sg:classifiers":[
        {
            "category":"Professional",
            "subcategory":"Accounting & Tax Preparation",
            "type":"Services"
        }
    ],
    "sg:phone":"+1 406 727 7703",
    "sg:postcode":"59404",
    "sg:province":"MT",
    "wof:name":"Threlkeld Accounting",
    "wof:placetype":"venue"
},
  "geometry": {"coordinates":[-111.328396,47.486672],"type":"Point"}
}