{
  "type": "Feature",
  "properties": {
    "iso:country":"US",
    "sg:address":"13 Hillcrest Rd",
    "sg:city":"Roundup",
    "sg:classifiers":[
        {
            "category":"Organizations",
            "subcategory":"Community Association",
            "type":"Services"
        }
    ],
    "sg:phone":"+1 406 323 2400",
    "sg:postcode":"59072",
    "sg:province":"MT",
    "wof:name":"Veterans of Foreign Wars",
    "wof:placetype":"venue"
},
  "geometry": {"coordinates":[-108.550048,46.397213],"type":"Point"}
}