{
  "type": "Feature",
  "properties": {
    "addr:full":"5805 US Hwy 93 Missoula MT 59804",
    "addr:housenumber":"5805",
    "addr:postcode":"59804",
    "addr:street":"Us Hwy 93",
    "iso:country":"US",
    "sg:address":"5805 US Hwy 93",
    "sg:city":"Missoula",
    "sg:classifiers":[
        {
            "category":"Professional",
            "subcategory":"Art Services",
            "type":"Services"
        }
    ],
    "sg:phone":"+1 406 251 3794",
    "sg:postcode":"59804",
    "sg:province":"MT",
    "sg:tags":[
        "photography",
        "commercial"
    ],
    "wof:name":"CJ Holding",
    "wof:placetype":"venue"
},
  "geometry": {"coordinates":[-114.092534,46.814426],"type":"Point"}
}