{
  "type": "Feature",
  "properties": {
    "iso:country":"US",
    "sg:address":"5480 US Hwy 93",
    "sg:city":"Somers",
    "sg:classifiers":[
        {
            "category":"Restaurant",
            "type":"Food & Drink"
        }
    ],
    "sg:phone":"+1 406 857 3889",
    "sg:postcode":"59932",
    "sg:province":"MT",
    "wof:name":"Mackinaw's",
    "wof:placetype":"venue"
},
  "geometry": {"coordinates":[-114.234835,48.07781],"type":"Point"}
}