{
  "type": "Feature",
  "properties": {
    "iso:country":"US",
    "sg:address":"606 N 7th Ave",
    "sg:city":"Bozeman",
    "sg:classifiers":[
        {
            "category":"Banks & Credit Unions",
            "subcategory":"Investment Brokerage",
            "type":"Services"
        }
    ],
    "sg:phone":"+1 406 587 7077",
    "sg:postcode":"59715",
    "sg:province":"MT",
    "sg:tags":[
        "advisory",
        "financial"
    ],
    "wof:name":"Marty Klotovich",
    "wof:placetype":"venue"
},
  "geometry": {"coordinates":[-111.0461,45.687473],"type":"Point"}
}