{
  "type": "Feature",
  "properties": {
    "iso:country":"US",
    "sg:address":"2631 Yellowstone Ave",
    "sg:city":"Billings",
    "sg:classifiers":[
        {
            "category":"Wholesale",
            "subcategory":"Stationery",
            "type":"Manufacturing & Wholesale Goods"
        }
    ],
    "sg:phone":"+1 406 656 7379",
    "sg:postcode":"59102",
    "sg:province":"MT",
    "sg:tags":[
        "school",
        "supply"
    ],
    "wof:name":"Great West Distributing",
    "wof:placetype":"venue"
},
  "geometry": {"coordinates":[-108.582049,45.778971],"type":"Point"}
}