{
  "type": "Feature",
  "properties": {
    "addr:full":"31908 Frontage Rd Bozeman MT 59715",
    "addr:housenumber":"31908",
    "addr:postcode":"59715",
    "addr:street":"Frontage Rd",
    "iso:country":"US",
    "sg:address":"31908 Frontage Rd",
    "sg:city":"Bozeman",
    "sg:classifiers":[
        {
            "category":"Autos & Motor Vehicles",
            "subcategory":"Motorcycle Sales",
            "type":"Retail Goods"
        }
    ],
    "sg:phone":"+1 406 586 4011",
    "sg:postcode":"59715",
    "sg:province":"MT",
    "wof:name":"Performance Fix LLC",
    "wof:placetype":"venue"
},
  "geometry": {"coordinates":[-111.00291199999999,45.673951],"type":"Point"}
}