{
  "type": "Feature",
  "properties": {
    "iso:country":"US",
    "sg:address":"2562 Nye Rd",
    "sg:city":"Nye",
    "sg:classifiers":[
        {
            "category":"Mining & Drilling",
            "type":"Manufacturing & Wholesale Goods"
        }
    ],
    "sg:phone":"+1 406 328 6400",
    "sg:postcode":"59061",
    "sg:province":"MT",
    "sg:tags":[
        "producer",
        "company",
        "metal",
        "primary",
        "nonferrous",
        "ore"
    ],
    "wof:name":"Stillwater Mining Company",
    "wof:placetype":"venue"
},
  "geometry": {"coordinates":[-109.872921,45.38201],"type":"Point"}
}