{
  "type": "Feature",
  "properties": {
    "iso:country":"US",
    "sg:address":"341 Chestnut Valley Rd",
    "sg:city":"Cascade",
    "sg:classifiers":[
        {
            "category":"Farming",
            "subcategory":"Livestock Farm",
            "type":"Manufacturing & Wholesale Goods"
        }
    ],
    "sg:phone":"+1 406 468 2474",
    "sg:postcode":"59421",
    "sg:province":"MT",
    "sg:tags":[
        "wheat",
        "beef",
        "cash",
        "grain",
        "cattle",
        "feedlot"
    ],
    "wof:name":"Von Stein Ranch",
    "wof:placetype":"venue"
},
  "geometry": {"coordinates":[-111.700595,47.218571],"type":"Point"}
}