{
  "type": "Feature",
  "properties": {
    "iso:country":"US",
    "sg:address":"2033 Main St",
    "sg:city":"Billings",
    "sg:classifiers":[
        {
            "category":"Building & Trades",
            "subcategory":"Construction",
            "type":"Services"
        }
    ],
    "sg:phone":"+1 406 855 1823",
    "sg:postcode":"59105",
    "sg:province":"MT",
    "sg:tags":[
        "residential",
        "contractor",
        "carpentry"
    ],
    "wof:name":"Keystone Construction Inc",
    "wof:placetype":"venue"
},
  "geometry": {"coordinates":[-108.470457,45.835397],"type":"Point"}
}