{
  "type": "Feature",
  "properties": {
    "addr:full":"2119 Amherst Ave Butte MT 59701",
    "addr:housenumber":"2119",
    "addr:postcode":"mt 59701",
    "addr:street":"Amherst Ave",
    "iso:country":"US",
    "sg:address":"2119 Amherst Ave",
    "sg:city":"Butte",
    "sg:classifiers":[
        {
            "category":"Restaurant",
            "type":"Food & Drink"
        }
    ],
    "sg:menulink":"http://www.allmenus.com/mt/butte/122288-quiznos-sub/menu/",
    "sg:phone":"+1 406 494 4745",
    "sg:postcode":"59701",
    "sg:province":"MT",
    "sg:tags":[
        "wrap",
        "american",
        "sandwich"
    ],
    "wof:name":"Quiznos Sub",
    "wof:placetype":"venue"
},
  "geometry": {"coordinates":[-112.507653,45.986413],"type":"Point"}
}