{
  "type": "Feature",
  "properties": {
    "iso:country":"US",
    "sg:address":"621 E 4th Ave N",
    "sg:city":"Columbus",
    "sg:classifiers":[
        {
            "category":"Health Services",
            "subcategory":"Optometrist",
            "type":"Services"
        }
    ],
    "sg:phone":"+1 406 322 5959",
    "sg:postcode":"59019",
    "sg:province":"MT",
    "wof:name":"Kent T Brown OD",
    "wof:placetype":"venue"
},
  "geometry": {"coordinates":[-109.25031,45.640772],"type":"Point"}
}