{
  "type": "Feature",
  "properties": {
    "iso:country":"US",
    "sg:address":"3516 Comstock St",
    "sg:city":"Miles City",
    "sg:classifiers":[
        {
            "category":"Insurance",
            "subcategory":"Insurance Agent",
            "type":"Services"
        }
    ],
    "sg:phone":"+1 406 698 9203",
    "sg:postcode":"59301",
    "sg:province":"MT",
    "wof:name":"Brandt & Associates Inc",
    "wof:placetype":"venue"
},
  "geometry": {"coordinates":[-105.81098,46.400954],"type":"Point"}
}