{
  "type": "Feature",
  "properties": {
    "addr:full":"1380 Douglas Dr Missoula MT 59808",
    "addr:housenumber":"1380",
    "addr:postcode":"59808",
    "addr:street":"Douglas Dr",
    "iso:country":"US",
    "sg:address":"1380 Douglas Dr",
    "sg:city":"Missoula",
    "sg:classifiers":[
        {
            "category":"Communications",
            "subcategory":"Film & Video Production",
            "type":"Services"
        }
    ],
    "sg:phone":"+1 406 543 6813",
    "sg:postcode":"59808",
    "sg:province":"MT",
    "sg:tags":[
        "motion",
        "picture"
    ],
    "wof:name":"New Creation Productions",
    "wof:placetype":"venue"
},
  "geometry": {"coordinates":[-114.099412,46.885051],"type":"Point"}
}