{
  "type": "Feature",
  "properties": {
    "addr:full":"21480 E Shore Rd Bigfork MT 59911",
    "addr:housenumber":"21480",
    "addr:postcode":"59911",
    "addr:street":"E Shore Rd",
    "iso:country":"US",
    "sg:address":"21480 E Shore Rd",
    "sg:city":"Bigfork",
    "sg:classifiers":[
        {
            "category":"Farming",
            "subcategory":"Orchard",
            "type":"Manufacturing & Wholesale Goods"
        }
    ],
    "sg:phone":"+1 406 982 3246",
    "sg:postcode":"59911",
    "sg:province":"MT",
    "sg:tags":[
        "fruit",
        "tree"
    ],
    "wof:name":"Bowman Orchards",
    "wof:placetype":"venue"
},
  "geometry": {"coordinates":[-114.029053,47.935137],"type":"Point"}
}