{
  "type": "Feature",
  "properties": {
    "iso:country":"US",
    "sg:address":"309 Garden Ave",
    "sg:city":"Billings",
    "sg:classifiers":[
        {
            "category":"Travel",
            "subcategory":"Campground",
            "type":"Entertainment"
        }
    ],
    "sg:phone":"+1 406 259 0878",
    "sg:postcode":"59101",
    "sg:province":"MT",
    "sg:tags":[
        "trailer"
    ],
    "wof:name":"Yellowstone River Campgrounds",
    "wof:placetype":"venue"
},
  "geometry": {"coordinates":[-108.484275,45.7696],"type":"Point"}
}