{
  "type": "Feature",
  "properties": {
    "iso:country":"US",
    "sg:address":"25 N Willson Ave",
    "sg:city":"Bozeman",
    "sg:classifiers":[
        {
            "category":"Personal",
            "subcategory":"Beauty Salon",
            "type":"Services"
        }
    ],
    "sg:phone":"+1 406 582 0253",
    "sg:postcode":"59715",
    "sg:province":"MT",
    "sg:tags":[
        "shop"
    ],
    "wof:name":"Artistic Images Hair Design",
    "wof:placetype":"venue"
},
  "geometry": {"coordinates":[-111.038815,45.679547],"type":"Point"}
}