{
  "type": "Feature",
  "properties": {
    "iso:country":"US",
    "sg:address":"2404 39th St",
    "sg:city":"Missoula",
    "sg:classifiers":[
        {
            "category":"Retail",
            "subcategory":"Laundry & Dry Cleaning",
            "type":"Services"
        }
    ],
    "sg:phone":"+1 406 251 5255",
    "sg:postcode":"59803",
    "sg:province":"MT",
    "wof:name":"Big Sky Chem-Dry",
    "wof:placetype":"venue"
},
  "geometry": {"coordinates":[-114.036266,46.834299],"type":"Point"}
}