{
  "type": "Feature",
  "properties": {
    "iso:country":"US",
    "sg:address":"11 S 7th St",
    "sg:city":"Miles City",
    "sg:classifiers":[
        {
            "category":"Manufacturing",
            "subcategory":"Tools & Machinery",
            "type":"Manufacturing & Wholesale Goods"
        }
    ],
    "sg:phone":"+1 406 234 1240",
    "sg:postcode":"59301",
    "sg:province":"MT",
    "sg:tags":[
        "resonance",
        "magnetic",
        "imaging",
        "apparatus"
    ],
    "wof:name":"Mondak Images Services",
    "wof:placetype":"venue"
},
  "geometry": {"coordinates":[-105.84927999999999,46.40639],"type":"Point"}
}