{
  "type": "Feature",
  "properties": {
    "iso:country":"US",
    "sg:address":"223 Main St",
    "sg:city":"Thompson Falls",
    "sg:classifiers":[
        {
            "category":"Insurance",
            "subcategory":"Insurance Agent",
            "type":"Services"
        }
    ],
    "sg:phone":"+1 406 827 3221",
    "sg:postcode":"59873",
    "sg:province":"MT",
    "wof:name":"House Of Insurance",
    "wof:placetype":"venue"
},
  "geometry": {"coordinates":[-115.343892,47.593578],"type":"Point"}
}