{
  "type": "Feature",
  "properties": {
    "iso:country":"US",
    "sg:address":"1484 Ashley Lake Rd",
    "sg:city":"Kalispell",
    "sg:classifiers":[
        {
            "category":"Manufacturing",
            "subcategory":"Lumber",
            "type":"Manufacturing & Wholesale Goods"
        }
    ],
    "sg:phone":"+1 406 755 1097",
    "sg:postcode":"59901",
    "sg:province":"MT",
    "sg:tags":[
        "company",
        "logging"
    ],
    "wof:name":"Joe Klempel Logging",
    "wof:placetype":"venue"
},
  "geometry": {"coordinates":[-114.497365,48.182952],"type":"Point"}
}