{
  "type": "Feature",
  "properties": {
    "iso:country":"US",
    "sg:address":"1200 10th Ave S",
    "sg:city":"Great Falls",
    "sg:classifiers":[
        {
            "category":"Shopping",
            "type":"Retail Goods"
        }
    ],
    "sg:phone":"+1 406 771 0863",
    "sg:postcode":"59405",
    "sg:province":"MT",
    "sg:tags":[
        "sunglasses",
        "accessory"
    ],
    "wof:name":"Sunglass Hut 2203",
    "wof:placetype":"venue"
},
  "geometry": {"coordinates":[-111.285263,47.494265],"type":"Point"}
}