{
  "type": "Feature",
  "properties": {
    "iso:country":"US",
    "sg:address":"505 W Central Ave",
    "sg:city":"Joliet",
    "sg:classifiers":[
        {
            "category":"Government",
            "subcategory":"Police Station",
            "type":"Public Place"
        }
    ],
    "sg:phone":"+1 406 962 3133",
    "sg:postcode":"59041",
    "sg:province":"MT",
    "sg:tags":[
        "department"
    ],
    "wof:name":"Joliet Police",
    "wof:placetype":"venue"
},
  "geometry": {"coordinates":[-108.976355,45.482199],"type":"Point"}
}