{
  "type": "Feature",
  "properties": {
    "addr:full":"2201 White Blvd Butte MT 59701",
    "addr:housenumber":"2201",
    "addr:postcode":"mt 59701",
    "addr:street":"White Blvd",
    "iso:country":"US",
    "sg:address":"2201 White Blvd",
    "sg:city":"Butte",
    "sg:classifiers":[
        {
            "category":"Organizations",
            "subcategory":"Labor Organization",
            "type":"Services"
        }
    ],
    "sg:phone":"+1 406 494 8303",
    "sg:postcode":"59701",
    "sg:province":"MT",
    "wof:name":"Afl-Cio Pcwa",
    "wof:placetype":"venue"
},
  "geometry": {"coordinates":[-112.504936,45.974945],"type":"Point"}
}