{
  "type": "Feature",
  "properties": {
    "iso:country":"US",
    "sg:address":"2050 Broadwater Ave",
    "sg:city":"Billings",
    "sg:classifiers":[
        {
            "category":"Real Estate",
            "subcategory":"Real Estate Agent",
            "type":"Services"
        }
    ],
    "sg:phone":"+1 406 869 2000",
    "sg:postcode":"59102",
    "sg:province":"MT",
    "sg:website":"www.mtrealestatebrokers.com",
    "wof:name":"Montana Real Estate Brokers",
    "wof:placetype":"venue"
},
  "geometry": {"coordinates":[-108.567361,45.77686],"type":"Point"}
}