{
  "type": "Feature",
  "properties": {
    "addr:full":"100 24th St W Billings MT 59102",
    "addr:housenumber":"100",
    "addr:postcode":"59102",
    "addr:street":"24Th St W",
    "iso:country":"US",
    "sg:address":"100 24th St W",
    "sg:city":"Billings",
    "sg:classifiers":[
        {
            "category":"Food & Beverages",
            "subcategory":"Liquor & Beverages",
            "type":"Retail Goods"
        }
    ],
    "sg:phone":"+1 406 656 0046",
    "sg:postcode":"59102",
    "sg:province":"MT",
    "wof:name":"Liquor Store 196",
    "wof:placetype":"venue"
},
  "geometry": {"coordinates":[-108.576238,45.77286],"type":"Point"}
}