{
  "type": "Feature",
  "properties": {
    "addr:full":"1709 Augsburg Dr Billings MT 59105",
    "addr:housenumber":"1709",
    "addr:postcode":"59105",
    "addr:street":"Augsburg Dr",
    "iso:country":"US",
    "sg:address":"1709 Augsburg Dr",
    "sg:city":"Billings",
    "sg:classifiers":[
        {
            "category":"Food & Beverages",
            "subcategory":"Specialty",
            "type":"Retail Goods"
        }
    ],
    "sg:phone":"+1 406 252 7136",
    "sg:postcode":"59105",
    "sg:province":"MT",
    "sg:tags":[
        "spice"
    ],
    "wof:name":"Watkins Quality Products",
    "wof:placetype":"venue"
},
  "geometry": {"coordinates":[-108.475037,45.828381],"type":"Point"}
}