{
  "type": "Feature",
  "properties": {
    "iso:country":"US",
    "sg:address":"1120 Maryland Ave",
    "sg:city":"Deer Lodge",
    "sg:classifiers":[
        {
            "category":"Local Transit",
            "type":"Transportation"
        }
    ],
    "sg:phone":"+1 406 846 9625",
    "sg:postcode":"59722",
    "sg:province":"MT",
    "sg:tags":[
        "ambulance"
    ],
    "wof:name":"Powell County Ambulance Servi",
    "wof:placetype":"venue"
},
  "geometry": {"coordinates":[-112.722218,46.392193],"type":"Point"}
}