{
  "type": "Feature",
  "properties": {
    "iso:country":"US",
    "sg:address":"1234 Ave C",
    "sg:city":"Billings",
    "sg:classifiers":[
        {
            "category":"Social Services",
            "type":"Services"
        }
    ],
    "sg:phone":"+1 406 657 6071",
    "sg:postcode":"59102",
    "sg:province":"MT",
    "sg:tags":[
        "counseling"
    ],
    "wof:name":"Vet Center",
    "wof:placetype":"venue"
},
  "geometry": {"coordinates":[-108.5478,45.785878],"type":"Point"}
}