{
  "type": "Feature",
  "properties": {
    "iso:country":"US",
    "sg:address":"2000 South Ave W",
    "sg:city":"Missoula",
    "sg:classifiers":[
        {
            "category":"Home & Garden",
            "subcategory":"Garden Supply",
            "type":"Retail Goods"
        }
    ],
    "sg:phone":"+1 406 721 3994",
    "sg:postcode":"59801",
    "sg:province":"MT",
    "sg:tags":[
        "supp",
        "clothing"
    ],
    "wof:name":"K & L Forest & Garden",
    "wof:placetype":"venue"
},
  "geometry": {"coordinates":[-114.03012099999999,46.848804],"type":"Point"}
}