{
  "type": "Feature",
  "properties": {
    "iso:country":"US",
    "sg:address":"5 Spruce Dr",
    "sg:city":"Havre",
    "sg:classifiers":[
        {
            "category":"Manufacturing",
            "subcategory":"Motor Vehicles & Parts",
            "type":"Manufacturing & Wholesale Goods"
        }
    ],
    "sg:phone":"+1 406 395 4041",
    "sg:postcode":"59501",
    "sg:province":"MT",
    "sg:tags":[
        "mfg",
        "trimming"
    ],
    "wof:name":"L & S Leeds Inc",
    "wof:placetype":"venue"
},
  "geometry": {"coordinates":[-109.66792,48.537776],"type":"Point"}
}