{
  "type": "Feature",
  "properties": {
    "iso:country":"US",
    "sg:address":"216 14th Ave SW",
    "sg:city":"Sidney",
    "sg:classifiers":[
        {
            "category":"Sports & Exercise",
            "subcategory":"Gym",
            "type":"Entertainment"
        }
    ],
    "sg:phone":"+1 406 488 4631",
    "sg:postcode":"59270",
    "sg:province":"MT",
    "sg:tags":[
        "club",
        "health",
        "studio",
        "gymnasium"
    ],
    "sg:website":"www.sidneyhealth.org",
    "wof:name":"Healthworks",
    "wof:placetype":"venue"
},
  "geometry": {"coordinates":[-104.174118,47.715583],"type":"Point"}
}