{
  "type": "Feature",
  "properties": {
    "addr:full":"120 W 5th St Libby MT 59923",
    "addr:housenumber":"120",
    "addr:postcode":"59923",
    "addr:street":"W 5Th St",
    "iso:country":"US",
    "sg:address":"120 W 5th St",
    "sg:city":"Libby",
    "sg:classifiers":[
        {
            "category":"Banks & Credit Unions",
            "subcategory":"Bank",
            "type":"Services"
        }
    ],
    "sg:phone":"+1 406 293 7771",
    "sg:postcode":"59923",
    "sg:province":"MT",
    "sg:website":"www.lincolncountycu.com",
    "wof:name":"Lincoln County Credit UNION",
    "wof:placetype":"venue"
},
  "geometry": {"coordinates":[-115.55253500000001,48.391478],"type":"Point"}
}