{
  "type": "Feature",
  "properties": {
    "iso:country":"US",
    "sg:address":"217 N 27th St",
    "sg:city":"Billings",
    "sg:classifiers":[
        {
            "category":"Government",
            "subcategory":"Office",
            "type":"Public Place"
        }
    ],
    "sg:phone":"+1 406 256 2828",
    "sg:postcode":"59101",
    "sg:province":"MT",
    "wof:name":"Yellowstone Extension Svc",
    "wof:placetype":"venue"
},
  "geometry": {"coordinates":[-108.50599099999999,45.784347],"type":"Point"}
}