{
  "type": "Feature",
  "properties": {
    "iso:country":"US",
    "sg:address":"9040 Horte Ln",
    "sg:city":"Ronan",
    "sg:classifiers":[
        {
            "category":"Travel",
            "subcategory":"Campground",
            "type":"Entertainment"
        }
    ],
    "sg:phone":"+1 406 676 3415",
    "sg:postcode":"59864",
    "sg:province":"MT",
    "sg:tags":[
        "operation",
        "camp"
    ],
    "wof:name":"Clearwater Guest Ranch",
    "wof:placetype":"venue"
},
  "geometry": {"coordinates":[-114.308855,47.544216],"type":"Point"}
}