{
  "type": "Feature",
  "properties": {
    "iso:country":"US",
    "sg:address":"2342 Middle Rd",
    "sg:city":"Columbia Falls",
    "sg:classifiers":[
        {
            "category":"Building & Trades",
            "subcategory":"Construction",
            "type":"Services"
        }
    ],
    "sg:phone":"+1 406 892 1558",
    "sg:postcode":"59912",
    "sg:province":"MT",
    "sg:tags":[
        "downspouts",
        "gutter"
    ],
    "wof:name":"Majestic Mountain Gutters",
    "wof:placetype":"venue"
},
  "geometry": {"coordinates":[-114.175471,48.299049],"type":"Point"}
}