{
  "type": "Feature",
  "properties": {
    "iso:country":"US",
    "sg:address":"236 Hill St",
    "sg:city":"Wolf Point",
    "sg:classifiers":[
        {
            "category":"Manufacturing",
            "subcategory":"Chemicals & Compounds",
            "type":"Manufacturing & Wholesale Goods"
        }
    ],
    "sg:phone":"+1 406 653 3106",
    "sg:postcode":"59201",
    "sg:province":"MT",
    "sg:tags":[
        "product",
        "mfg"
    ],
    "wof:name":"Sharon Parsley",
    "wof:placetype":"venue"
},
  "geometry": {"coordinates":[-105.640204,48.098434],"type":"Point"}
}