{
  "type": "Feature",
  "properties": {
    "iso:country":"US",
    "sg:address":"1510 9th St W",
    "sg:city":"Billings",
    "sg:classifiers":[
        {
            "category":"Personal",
            "subcategory":"Beauty Salon",
            "type":"Services"
        }
    ],
    "sg:phone":"+1 406 254 0940",
    "sg:postcode":"59102",
    "sg:province":"MT",
    "sg:tags":[
        "hair"
    ],
    "wof:name":"Green Door",
    "wof:placetype":"venue"
},
  "geometry": {"coordinates":[-108.53856,45.785841],"type":"Point"}
}