{
  "type": "Feature",
  "properties": {
    "iso:country":"US",
    "sg:address":"701 Avenue E",
    "sg:city":"Billings",
    "sg:classifiers":[
        {
            "category":"Personal",
            "subcategory":"Barber",
            "type":"Services"
        }
    ],
    "sg:phone":"+1 406 256 2045",
    "sg:postcode":"59102",
    "sg:province":"MT",
    "sg:tags":[
        "shop"
    ],
    "wof:name":"7th Street Barber",
    "wof:placetype":"venue"
},
  "geometry": {"coordinates":[-108.53574,45.787966],"type":"Point"}
}