{
  "type": "Feature",
  "properties": {
    "iso:country":"US",
    "sg:address":"2591 Magenta Rd",
    "sg:city":"Bozeman",
    "sg:classifiers":[
        {
            "category":"Retail",
            "subcategory":"Repair Shop",
            "type":"Services"
        }
    ],
    "sg:phone":"+1 406 586 6489",
    "sg:postcode":"59718",
    "sg:province":"MT",
    "wof:name":"Sacajawea Forge",
    "wof:placetype":"venue"
},
  "geometry": {"coordinates":[-111.194187,45.645908],"type":"Point"}
}