{
  "type": "Feature",
  "properties": {
    "iso:country":"US",
    "sg:address":"206 Siblerud Ln",
    "sg:city":"Kalispell",
    "sg:phone":"+1 406 756 6324",
    "sg:postcode":"59901",
    "sg:province":"MT",
    "sg:tags":[
        "farm",
        "field",
        "wheat",
        "crop"
    ],
    "wof:name":"Robert Borgen",
    "wof:placetype":"venue"
},
  "geometry": {"coordinates":[-114.228649,48.167928],"type":"Point"}
}