{
  "type": "Feature",
  "properties": {
    "addr:full":"2245 Amsterdam Rd Belgrade MT 59714",
    "addr:housenumber":"2245",
    "addr:postcode":"59714",
    "addr:street":"Amsterdam Rd",
    "iso:country":"US",
    "sg:address":"2245 Amsterdam Rd",
    "sg:city":"Belgrade",
    "sg:classifiers":[
        {
            "category":"Building & Trades",
            "subcategory":"Construction",
            "type":"Services"
        }
    ],
    "sg:phone":"+1 406 388 4788",
    "sg:postcode":"59714",
    "sg:province":"MT",
    "sg:tags":[
        "contractor"
    ],
    "wof:name":"Gallatin Insulation",
    "wof:placetype":"venue"
},
  "geometry": {"coordinates":[-111.227298,45.77283],"type":"Point"}
}