{
  "type": "Feature",
  "properties": {
    "iso:country":"US",
    "sg:address":"624 N Wallace Ave",
    "sg:city":"Bozeman",
    "sg:classifiers":[
        {
            "category":"Building & Trades",
            "subcategory":"Construction",
            "type":"Services"
        }
    ],
    "sg:phone":"+1 406 586 1072",
    "sg:postcode":"59715",
    "sg:province":"MT",
    "sg:tags":[
        "contractor"
    ],
    "wof:name":"Philip Howard Contractor",
    "wof:placetype":"venue"
},
  "geometry": {"coordinates":[-111.02829,45.686412],"type":"Point"}
}