{
  "type": "Feature",
  "properties": {
    "iso:country":"US",
    "sg:address":"2900 4th Ave N",
    "sg:city":"Billings",
    "sg:classifiers":[
        {
            "category":"Government",
            "subcategory":"Office",
            "type":"Public Place"
        }
    ],
    "sg:phone":"+1 406 247 7405",
    "sg:postcode":"59101",
    "sg:province":"MT",
    "sg:tags":[
        "federal",
        "govt"
    ],
    "wof:name":"US Western Area Power Adm",
    "wof:placetype":"venue"
},
  "geometry": {"coordinates":[-108.51073,45.783452],"type":"Point"}
}