{
  "type": "Feature",
  "properties": {
    "iso:country":"US",
    "sg:address":"715 W 2nd St",
    "sg:city":"Laurel",
    "sg:classifiers":[
        {
            "category":"Home & Garden",
            "subcategory":"Furniture",
            "type":"Retail Goods"
        }
    ],
    "sg:phone":"+1 406 628 6849",
    "sg:postcode":"59044",
    "sg:province":"MT",
    "wof:name":"Bobs Custom Woodworks",
    "wof:placetype":"venue"
},
  "geometry": {"coordinates":[-108.781153,45.670434],"type":"Point"}
}