{
  "type": "Feature",
  "properties": {
    "iso:country":"US",
    "sg:address":"1002 10th St W",
    "sg:city":"Billings",
    "sg:classifiers":[
        {
            "category":"Wholesale",
            "subcategory":"Medical Equipment & Supplies",
            "type":"Manufacturing & Wholesale Goods"
        },
        {
            "category":"Manufacturing",
            "subcategory":"Tools & Machinery",
            "type":"Manufacturing & Wholesale Goods"
        }
    ],
    "sg:phone":"+1 406 248 4429",
    "sg:postcode":"59102",
    "sg:province":"MT",
    "sg:tags":[
        "optical",
        "ophthalmic"
    ],
    "wof:name":"Twin City Optical",
    "wof:placetype":"venue"
},
  "geometry": {"coordinates":[-108.541065,45.779768],"type":"Point"}
}