{
  "type": "Feature",
  "properties": {
    "addr:full":"404 E 1st St Whitefish MT 59937",
    "addr:housenumber":"404",
    "addr:postcode":"59937",
    "addr:street":"E 1St St",
    "iso:country":"US",
    "sg:address":"404 E 1st St",
    "sg:city":"Whitefish",
    "sg:classifiers":[
        {
            "category":"Banks & Credit Unions",
            "subcategory":"Investment Brokerage",
            "type":"Services"
        }
    ],
    "sg:phone":"+1 406 862 4400",
    "sg:postcode":"59937",
    "sg:province":"MT",
    "sg:tags":[
        "security"
    ],
    "wof:name":"Linsco Private Ledger Fncl Svc",
    "wof:placetype":"venue"
},
  "geometry": {"coordinates":[-114.33742700000001,48.411727],"type":"Point"}
}