{
  "type": "Feature",
  "properties": {
    "addr:full":"160 Erickson Ct W Billings MT 59105",
    "addr:housenumber":"160",
    "addr:postcode":"59105",
    "addr:street":"Erickson Ct W",
    "iso:country":"US",
    "sg:address":"160 Erickson Ct W",
    "sg:city":"Billings",
    "sg:classifiers":[
        {
            "category":"Organizations",
            "subcategory":"Religious Organization",
            "type":"Services"
        }
    ],
    "sg:phone":"+1 406 256 7440",
    "sg:postcode":"59105",
    "sg:province":"MT",
    "sg:tags":[
        "church"
    ],
    "wof:name":"Church Of God Of Prophecy",
    "wof:placetype":"venue"
},
  "geometry": {"coordinates":[-108.49163900000001,45.814092],"type":"Point"}
}