{
  "type": "Feature",
  "properties": {
    "addr:full":"2101 N Main St Helena MT 59601",
    "addr:housenumber":"2101",
    "addr:postcode":"59601",
    "addr:street":"N Main St",
    "iso:country":"US",
    "sg:address":"2101 N Main St",
    "sg:city":"Helena",
    "sg:classifiers":[
        {
            "category":"Manufacturing",
            "subcategory":"Printing",
            "type":"Manufacturing & Wholesale Goods"
        }
    ],
    "sg:phone":"+1 406 443 8550",
    "sg:postcode":"59601",
    "sg:province":"MT",
    "sg:tags":[
        "commercial",
        "offset"
    ],
    "wof:name":"Neighborhood Office LLC",
    "wof:placetype":"venue"
},
  "geometry": {"coordinates":[-112.02295599999999,46.605737],"type":"Point"}
}