{
  "type": "Feature",
  "properties": {
    "iso:country":"US",
    "sg:address":"742 46th St S",
    "sg:city":"Great Falls",
    "sg:classifiers":[
        {
            "category":"Social Services",
            "subcategory":"Child Care",
            "type":"Services"
        }
    ],
    "sg:phone":"+1 406 761 6757",
    "sg:postcode":"59405",
    "sg:province":"MT",
    "sg:tags":[
        "day"
    ],
    "wof:name":"Ms Marjories Day Care",
    "wof:placetype":"venue"
},
  "geometry": {"coordinates":[-111.230485,47.496437],"type":"Point"}
}