{
  "type": "Feature",
  "properties": {
    "iso:country":"US",
    "sg:address":"442 Indian Trl",
    "sg:city":"Billings",
    "sg:classifiers":[
        {
            "category":"Building & Trades",
            "subcategory":"Construction",
            "type":"Services"
        }
    ],
    "sg:phone":"+1 406 259 1313",
    "sg:postcode":"59105",
    "sg:province":"MT",
    "sg:tags":[
        "general",
        "contractor"
    ],
    "wof:name":"Schiltz & Sheehan Constr Inc",
    "wof:placetype":"venue"
},
  "geometry": {"coordinates":[-108.502892,45.80572],"type":"Point"}
}