{
  "type": "Feature",
  "properties": {
    "iso:country":"US",
    "sg:address":"120 W Callender St",
    "sg:city":"Livingston",
    "sg:classifiers":[
        {
            "category":"Professional",
            "subcategory":"Lawyer & Legal Services",
            "type":"Services"
        }
    ],
    "sg:phone":"+1 406 222 4420",
    "sg:postcode":"59047",
    "sg:province":"MT",
    "wof:name":"Paoli & Brown PC",
    "wof:placetype":"venue"
},
  "geometry": {"coordinates":[-110.560326,45.661343],"type":"Point"}
}