{
  "type": "Feature",
  "properties": {
    "iso:country":"US",
    "sg:address":"122 S Church Ave",
    "sg:city":"Bozeman",
    "sg:classifiers":[
        {
            "category":"Professional",
            "subcategory":"Business Services",
            "type":"Services"
        }
    ],
    "sg:phone":"+1 406 587 8082",
    "sg:postcode":"59715",
    "sg:province":"MT",
    "wof:name":"Heritage Restoration",
    "wof:placetype":"venue"
},
  "geometry": {"coordinates":[-111.03021699999999,45.678114],"type":"Point"}
}