{
  "type": "Feature",
  "properties": {
    "iso:country":"US",
    "sg:address":"106 Falls Creek Rd",
    "sg:city":"Livingston",
    "sg:classifiers":[
        {
            "category":"Manufacturing",
            "subcategory":"Lumber",
            "type":"Manufacturing & Wholesale Goods"
        }
    ],
    "sg:phone":"+1 406 686 4615",
    "sg:postcode":"59047",
    "sg:province":"MT",
    "sg:tags":[
        "logging"
    ],
    "wof:name":"Timber Resource Management",
    "wof:placetype":"venue"
},
  "geometry": {"coordinates":[-110.414237,45.845799],"type":"Point"}
}