{
  "type": "Feature",
  "properties": {
    "iso:country":"US",
    "sg:address":"594 Sheridan Dr",
    "sg:city":"Hamilton",
    "sg:classifiers":[
        {
            "category":"Building & Trades",
            "subcategory":"Construction",
            "type":"Services"
        }
    ],
    "sg:phone":"+1 406 961 5415",
    "sg:postcode":"59840",
    "sg:province":"MT",
    "sg:tags":[
        "water",
        "well",
        "drilling"
    ],
    "wof:name":"Aqwa Drilling LLC",
    "wof:placetype":"venue"
},
  "geometry": {"coordinates":[-114.217145,46.322223],"type":"Point"}
}