{
  "type": "Feature",
  "properties": {
    "addr:full":"471 Pinon Dr Billings MT 59105",
    "addr:housenumber":"471",
    "addr:postcode":"59105",
    "addr:street":"Pinon Dr",
    "iso:country":"US",
    "sg:address":"471 Pinon Dr",
    "sg:city":"Billings",
    "sg:classifiers":[
        {
            "category":"Building & Trades",
            "subcategory":"Construction",
            "type":"Services"
        }
    ],
    "sg:phone":"+1 406 256 5359",
    "sg:postcode":"59105",
    "sg:province":"MT",
    "sg:tags":[
        "builder",
        "operative"
    ],
    "wof:name":"Harper Construction Inc",
    "wof:placetype":"venue"
},
  "geometry": {"coordinates":[-108.508262,45.806787],"type":"Point"}
}