{
  "type": "Feature",
  "properties": {
    "addr:full":"305 S 1st St Hamilton MT 59840",
    "addr:housenumber":"305",
    "addr:postcode":"59840",
    "addr:street":"S 1St St",
    "iso:country":"US",
    "sg:address":"305 S 1st St",
    "sg:city":"Hamilton",
    "sg:classifiers":[
        {
            "category":"Professional",
            "type":"Services"
        }
    ],
    "sg:phone":"+1 406 363 1777",
    "sg:postcode":"59840",
    "sg:province":"MT",
    "sg:tags":[
        "establishment"
    ],
    "wof:name":"Brownlee Sasha",
    "wof:placetype":"venue"
},
  "geometry": {"coordinates":[-114.155424,46.244976],"type":"Point"}
}