{
  "type": "Feature",
  "properties": {
    "iso:country":"US",
    "sg:address":"1034 Whitefish Stage",
    "sg:city":"Kalispell",
    "sg:classifiers":[
        {
            "category":"Building & Trades",
            "subcategory":"Construction",
            "type":"Services"
        }
    ],
    "sg:phone":"+1 406 752 4039",
    "sg:postcode":"59901",
    "sg:province":"MT",
    "sg:tags":[
        "hanging",
        "contractor"
    ],
    "wof:name":"Scales Sandblasting & Painting",
    "wof:placetype":"venue"
},
  "geometry": {"coordinates":[-114.307899,48.215636],"type":"Point"}
}