{
  "type": "Feature",
  "properties": {
    "iso:country":"US",
    "sg:address":"535 Grande Vista Dr",
    "sg:city":"Kalispell",
    "sg:classifiers":[
        {
            "category":"Retail",
            "subcategory":"Animal Services",
            "type":"Services"
        }
    ],
    "sg:phone":"+1 406 257 2527",
    "sg:postcode":"59901",
    "sg:province":"MT",
    "wof:name":"Crooked Tree Kennels",
    "wof:placetype":"venue"
},
  "geometry": {"coordinates":[-114.421028,48.257197],"type":"Point"}
}