{
  "type": "Feature",
  "properties": {
    "addr:full":"102 Eagle Ridge Rd Roundup MT 59072",
    "addr:housenumber":"102",
    "addr:postcode":"59072",
    "addr:street":"Eagle Ridge Rd",
    "iso:country":"US",
    "sg:address":"102 Eagle Ridge Rd",
    "sg:city":"Roundup",
    "sg:classifiers":[
        {
            "category":"Manufacturing",
            "subcategory":"Metals",
            "type":"Manufacturing & Wholesale Goods"
        }
    ],
    "sg:phone":"+1 406 323 1230",
    "sg:postcode":"59072",
    "sg:province":"MT",
    "sg:tags":[
        "mfg",
        "plate",
        "work",
        "fabricated",
        "contractor"
    ],
    "wof:name":"Big Sky Draperies",
    "wof:placetype":"venue"
},
  "geometry": {"coordinates":[-108.55460100000001,46.312019],"type":"Point"}
}