{
  "type": "Feature",
  "properties": {
    "addr:full":"7565 Minesinger Ln Polson MT 59860",
    "addr:housenumber":"7565",
    "addr:postcode":"59860",
    "addr:street":"Minesinger Ln",
    "iso:country":"US",
    "sg:address":"7565 Minesinger Ln",
    "sg:city":"Polson",
    "sg:classifiers":[
        {
            "category":"Freight",
            "type":"Transportation"
        }
    ],
    "sg:phone":"+1 406 883 1396",
    "sg:postcode":"59860",
    "sg:province":"MT",
    "sg:tags":[
        "operator",
        "trucking"
    ],
    "wof:name":"Stokes John Jay Inc",
    "wof:placetype":"venue"
},
  "geometry": {"coordinates":[-114.03729300000001,47.636952],"type":"Point"}
}