{
  "type": "Feature",
  "properties": {
    "addr:full":"2160 Central Ave Billings MT 59102",
    "addr:housenumber":"2160",
    "addr:postcode":"59102",
    "addr:street":"Central Ave",
    "iso:country":"US",
    "sg:address":"2160 Central Ave",
    "sg:city":"Billings",
    "sg:classifiers":[
        {
            "category":"Shopping",
            "subcategory":"Stationery & Office Supplies",
            "type":"Retail Goods"
        }
    ],
    "sg:phone":"+1 406 655 4773",
    "sg:postcode":"59102",
    "sg:province":"MT",
    "sg:tags":[
        "stamp"
    ],
    "wof:name":"Stampressions",
    "wof:placetype":"venue"
},
  "geometry": {"coordinates":[-108.567598,45.769687],"type":"Point"}
}