{
  "type": "Feature",
  "properties": {
    "iso:country":"US",
    "sg:address":"8750 Saddle Mountain Rd",
    "sg:city":"Bozeman",
    "sg:classifiers":[
        {
            "category":"Professional",
            "subcategory":"Engineering",
            "type":"Services"
        }
    ],
    "sg:phone":"+1 406 586 6996",
    "sg:postcode":"59715",
    "sg:province":"MT",
    "wof:name":"Hall Control",
    "wof:placetype":"venue"
},
  "geometry": {"coordinates":[-111.010049,45.764835],"type":"Point"}
}