{
  "type": "Feature",
  "properties": {
    "iso:country":"US",
    "sg:address":"105 Stoner Creek Rd",
    "sg:city":"Lakeside",
    "sg:classifiers":[
        {
            "category":"Food & Beverages",
            "subcategory":"Groceries & Convenience Stores",
            "type":"Retail Goods"
        }
    ],
    "sg:phone":"+1 406 844 2606",
    "sg:postcode":"59922",
    "sg:province":"MT",
    "wof:name":"Blacktail Grocery",
    "wof:placetype":"venue"
},
  "geometry": {"coordinates":[-114.224746,48.018184],"type":"Point"}
}