{
  "type": "Feature",
  "properties": {
    "addr:full":"1525 7th St S Great Falls MT 59405",
    "addr:housenumber":"1525",
    "addr:postcode":"59405",
    "addr:street":"7Th St S",
    "iso:country":"US",
    "sg:address":"1525 7th St S",
    "sg:city":"Great Falls",
    "sg:classifiers":[
        {
            "category":"Shopping",
            "subcategory":"Computers & Home Electronics",
            "type":"Retail Goods"
        }
    ],
    "sg:phone":"+1 406 453 6388",
    "sg:postcode":"59405",
    "sg:province":"MT",
    "wof:name":"Computer Affordable Repair",
    "wof:placetype":"venue"
},
  "geometry": {"coordinates":[-111.293933,47.48741],"type":"Point"}
}