{
  "type": "Feature",
  "properties": {
    "addr:full":"16250 Roman Creek Rd Frenchtown MT 59834",
    "addr:housenumber":"16250",
    "addr:postcode":"59834",
    "addr:street":"Roman Creek Rd",
    "iso:country":"US",
    "sg:address":"16250 Roman Creek Rd",
    "sg:city":"Frenchtown",
    "sg:classifiers":[
        {
            "category":"Building & Trades",
            "subcategory":"Plumbing",
            "type":"Services"
        }
    ],
    "sg:phone":"+1 406 626 4737",
    "sg:postcode":"59834",
    "sg:province":"MT",
    "sg:tags":[
        "contractor"
    ],
    "wof:name":"Richardson Mechanical",
    "wof:placetype":"venue"
},
  "geometry": {"coordinates":[-114.25086400000001,47.02735],"type":"Point"}
}