{
  "type": "Feature",
  "properties": {
    "addr:full":"3755 Melkat Ln Helena MT 59602",
    "addr:housenumber":"3755",
    "addr:postcode":"59602",
    "addr:street":"Melkat Ln",
    "iso:country":"US",
    "sg:address":"3755 Melkat Ln",
    "sg:city":"Helena",
    "sg:classifiers":[
        {
            "category":"Professional",
            "subcategory":"Business Services",
            "type":"Services"
        }
    ],
    "sg:phone":"+1 406 227 7227",
    "sg:postcode":"59602",
    "sg:province":"MT",
    "wof:name":"Rio Group LLC",
    "wof:placetype":"venue"
},
  "geometry": {"coordinates":[-111.89554200000001,46.661518],"type":"Point"}
}