{
  "type": "Feature",
  "properties": {
    "iso:country":"US",
    "sg:address":"710 S Atlantic St",
    "sg:city":"Dillon",
    "sg:classifiers":[
        {
            "category":"Farming",
            "subcategory":"Fish & Marine Products",
            "type":"Manufacturing & Wholesale Goods"
        }
    ],
    "sg:phone":"+1 406 683 7951",
    "sg:postcode":"59725",
    "sg:province":"MT",
    "sg:tags":[
        "wildlife",
        "management"
    ],
    "wof:name":"Brian Pilcher",
    "wof:placetype":"venue"
},
  "geometry": {"coordinates":[-112.639366,45.210594],"type":"Point"}
}