{
  "type": "Feature",
  "properties": {
    "iso:country":"US",
    "sg:address":"8 Fields Rd",
    "sg:city":"Great Falls",
    "sg:classifiers":[
        {
            "category":"Real Estate",
            "subcategory":"Real Estate Operator",
            "type":"Services"
        }
    ],
    "sg:phone":"+1 406 727 7066",
    "sg:postcode":"59405",
    "sg:province":"MT",
    "sg:tags":[
        "building",
        "commercial"
    ],
    "wof:name":"Shubat Enterprises Inc",
    "wof:placetype":"venue"
},
  "geometry": {"coordinates":[-111.284291,47.451032],"type":"Point"}
}