{
  "type": "Feature",
  "properties": {
    "iso:country":"US",
    "sg:address":"155 Waddell Ln",
    "sg:city":"Darby",
    "sg:classifiers":[
        {
            "category":"Recreation",
            "type":"Entertainment"
        },
        {
            "category":"Retail",
            "subcategory":"Animal Services",
            "type":"Services"
        }
    ],
    "sg:phone":"+1 406 821 3801",
    "sg:postcode":"59829",
    "sg:province":"MT",
    "sg:tags":[
        "stable"
    ],
    "wof:name":"Rockin C Stables LLC",
    "wof:placetype":"venue"
},
  "geometry": {"coordinates":[-114.184155,46.051469],"type":"Point"}
}