{
  "type": "Feature",
  "properties": {
    "iso:country":"US",
    "sg:address":"1050 Cote Ln",
    "sg:city":"Missoula",
    "sg:classifiers":[
        {
            "category":"Professional",
            "subcategory":"Management & Consulting",
            "type":"Services"
        }
    ],
    "sg:phone":"+1 406 542 1957",
    "sg:postcode":"59808",
    "sg:province":"MT",
    "wof:name":"Creative Benefit Designs LLC",
    "wof:placetype":"venue"
},
  "geometry": {"coordinates":[-114.111757,46.878871],"type":"Point"}
}