{
  "type": "Feature",
  "properties": {
    "iso:country":"US",
    "sg:address":"309 S Yellowstone St",
    "sg:city":"Livingston",
    "sg:classifiers":[
        {
            "category":"Real Estate",
            "subcategory":"Architect",
            "type":"Services"
        }
    ],
    "sg:phone":"+1 406 222 9357",
    "sg:postcode":"59047",
    "sg:province":"MT",
    "sg:tags":[
        "building",
        "designer"
    ],
    "wof:name":"Jerry Heist Designs Inc",
    "wof:placetype":"venue"
},
  "geometry": {"coordinates":[-110.561075,45.657489],"type":"Point"}
}