{
  "type": "Feature",
  "properties": {
    "iso:country":"US",
    "sg:address":"3035 Eastside Hwy",
    "sg:city":"Stevensville",
    "sg:classifiers":[
        {
            "category":"Shopping",
            "subcategory":"Used Merchandise",
            "type":"Retail Goods"
        }
    ],
    "sg:phone":"+1 406 777 5543",
    "sg:postcode":"59870",
    "sg:province":"MT",
    "sg:tags":[
        "antique"
    ],
    "wof:name":"Gee's House Of Antiques",
    "wof:placetype":"venue"
},
  "geometry": {"coordinates":[-114.09417500000001,46.451129],"type":"Point"}
}