{
  "type": "Feature",
  "properties": {
    "iso:country":"US",
    "sg:address":"280 Tin Cup Rd",
    "sg:city":"Darby",
    "sg:classifiers":[
        {
            "category":"Banks & Credit Unions",
            "subcategory":"Financial Services",
            "type":"Services"
        }
    ],
    "sg:phone":"+1 406 821 3199",
    "sg:postcode":"59829",
    "sg:province":"MT",
    "sg:tags":[
        "trust",
        "management"
    ],
    "wof:name":"Ritson Family Trust",
    "wof:placetype":"venue"
},
  "geometry": {"coordinates":[-114.185217,46.015338],"type":"Point"}
}