{
  "type": "Feature",
  "properties": {
    "addr:full":"1075 Foys Lake Rd Kalispell MT 59901",
    "addr:housenumber":"1075",
    "addr:postcode":"59901",
    "addr:street":"Foys Lake Rd",
    "iso:country":"US",
    "sg:address":"1075 Foys Lake Rd",
    "sg:city":"Kalispell",
    "sg:classifiers":[
        {
            "category":"Organizations",
            "subcategory":"Religious Organization",
            "type":"Services"
        }
    ],
    "sg:phone":"+1 406 257 9315",
    "sg:postcode":"59901",
    "sg:province":"MT",
    "sg:tags":[
        "church"
    ],
    "wof:name":"Kalispell Christian Church",
    "wof:placetype":"venue"
},
  "geometry": {"coordinates":[-114.348921,48.185716],"type":"Point"}
}