{
  "type": "Feature",
  "properties": {
    "iso:country":"US",
    "sg:address":"34485 US Hwy 93",
    "sg:city":"Saint Ignatius",
    "sg:classifiers":[
        {
            "category":"Building & Trades",
            "subcategory":"Construction",
            "type":"Services"
        }
    ],
    "sg:phone":"+1 406 745 4432",
    "sg:postcode":"59865",
    "sg:province":"MT",
    "sg:tags":[
        "excavation",
        "contractor"
    ],
    "wof:name":"Smyth Construction",
    "wof:placetype":"venue"
},
  "geometry": {"coordinates":[-114.096886,47.348199],"type":"Point"}
}