{
  "type": "Feature",
  "properties": {
    "iso:country":"US",
    "sg:address":"107 S Broadway",
    "sg:city":"Belgrade",
    "sg:classifiers":[
        {
            "category":"Real Estate",
            "subcategory":"Real Estate Agent",
            "type":"Services"
        }
    ],
    "sg:phone":"+1 406 388 6010",
    "sg:postcode":"59714",
    "sg:province":"MT",
    "wof:name":"Valley Realty",
    "wof:placetype":"venue"
},
  "geometry": {"coordinates":[-111.17911599999999,45.774417],"type":"Point"}
}