{
  "type": "Feature",
  "properties": {
    "iso:country":"US",
    "sg:address":"2100 Stephens Ave",
    "sg:city":"Missoula",
    "sg:classifiers":[
        {
            "category":"Home & Garden",
            "subcategory":"Furniture",
            "type":"Retail Goods"
        }
    ],
    "sg:phone":"+1 406 251 5200",
    "sg:postcode":"59801",
    "sg:province":"MT",
    "sg:tags":[
        "wall",
        "interior",
        "floor",
        "covering"
    ],
    "wof:name":"Nelson Interiors",
    "wof:placetype":"venue"
},
  "geometry": {"coordinates":[-114.01305600000001,46.850674],"type":"Point"}
}