{
  "type": "Feature",
  "properties": {
    "iso:country":"US",
    "sg:address":"110 S 36th St",
    "sg:city":"Billings",
    "sg:classifiers":[
        {
            "category":"Manufacturing",
            "subcategory":"Metals",
            "type":"Manufacturing & Wholesale Goods"
        }
    ],
    "sg:phone":"+1 406 245 4537",
    "sg:postcode":"59101",
    "sg:province":"MT",
    "sg:tags":[
        "repair",
        "cutlery",
        "mfg"
    ],
    "wof:name":"Custom Built Knives",
    "wof:placetype":"venue"
},
  "geometry": {"coordinates":[-108.51233999999999,45.77402],"type":"Point"}
}