{
  "type": "Feature",
  "properties": {
    "iso:country":"US",
    "sg:address":"612 7th St E",
    "sg:city":"Kalispell",
    "sg:classifiers":[
        {
            "category":"Health Services",
            "subcategory":"Doctor",
            "type":"Services"
        }
    ],
    "sg:phone":"+1 406 755 1112",
    "sg:postcode":"59901",
    "sg:province":"MT",
    "sg:tags":[
        "medical"
    ],
    "wof:name":"Harvey C Swanson MD",
    "wof:placetype":"venue"
},
  "geometry": {"coordinates":[-114.30110500000001,48.193559],"type":"Point"}
}