{
  "type": "Feature",
  "properties": {
    "iso:country":"US",
    "sg:address":"550 1st Ave N",
    "sg:city":"Billings",
    "sg:classifiers":[
        {
            "category":"Autos & Motor Vehicles",
            "subcategory":"Automobile Sales",
            "type":"Retail Goods"
        }
    ],
    "sg:phone":"+1 406 254 8400",
    "sg:postcode":"59101",
    "sg:province":"MT",
    "sg:tags":[
        "used"
    ],
    "wof:name":"Mountain Rovers Inc",
    "wof:placetype":"venue"
},
  "geometry": {"coordinates":[-108.480237,45.794451],"type":"Point"}
}