{
  "type": "Feature",
  "properties": {
    "iso:country":"US",
    "sg:address":"1404 Main St",
    "sg:city":"Miles City",
    "sg:classifiers":[
        {
            "category":"Autos & Motor Vehicles",
            "subcategory":"Auto Supplies",
            "type":"Retail Goods"
        }
    ],
    "sg:phone":"+1 406 234 4938",
    "sg:postcode":"59301",
    "sg:province":"MT",
    "sg:tags":[
        "tire"
    ],
    "wof:name":"Rolling Rubber LLC",
    "wof:placetype":"venue"
},
  "geometry": {"coordinates":[-105.84221700000001,46.408267],"type":"Point"}
}