{
  "type": "Feature",
  "properties": {
    "iso:country":"US",
    "sg:address":"1901 10th Ave S",
    "sg:city":"Great Falls",
    "sg:classifiers":[
        {
            "category":"Travel",
            "subcategory":"Hotels & Motels",
            "type":"Entertainment"
        }
    ],
    "sg:phone":"+1 406 727 1565",
    "sg:postcode":"59405",
    "sg:province":"MT",
    "sg:tags":[
        "operation"
    ],
    "wof:name":"Nickle Mania",
    "wof:placetype":"venue"
},
  "geometry": {"coordinates":[-111.273045,47.494209],"type":"Point"}
}