{
  "type": "Feature",
  "properties": {
    "iso:country":"US",
    "sg:address":"101 N 28th St",
    "sg:city":"Billings",
    "sg:classifiers":[
        {
            "category":"Bars & Pubs",
            "type":"Food & Drink"
        }
    ],
    "sg:phone":"+1 406 259 0010",
    "sg:postcode":"59101",
    "sg:province":"MT",
    "wof:name":"Crystal Lounge",
    "wof:placetype":"venue"
},
  "geometry": {"coordinates":[-108.506608,45.782969],"type":"Point"}
}