{
  "type": "Feature",
  "properties": {
    "addr:full":"12 N Main St Whitehall MT 59759",
    "addr:housenumber":"12",
    "addr:postcode":"59759",
    "addr:street":"N Main St",
    "iso:country":"US",
    "sg:address":"12 N Main St",
    "sg:city":"Whitehall",
    "sg:classifiers":[
        {
            "category":"Professional",
            "subcategory":"Lawyer & Legal Services",
            "type":"Services"
        }
    ],
    "sg:phone":"+1 406 287 3832",
    "sg:postcode":"59759",
    "sg:province":"MT",
    "sg:tags":[
        "attorney"
    ],
    "wof:name":"Jardine & Morris Attys",
    "wof:placetype":"venue"
},
  "geometry": {"coordinates":[-112.09909500000001,45.870734],"type":"Point"}
}