{
  "type": "Feature",
  "properties": {
    "addr:full":"121 N Last Chance Gulch St Helena MT 59601",
    "addr:housenumber":"121",
    "addr:postcode":"59601",
    "addr:street":"N Last Chance Gulch",
    "iso:country":"US",
    "sg:address":"121 N Last Chance Gulch St",
    "sg:city":"Helena",
    "sg:classifiers":[
        {
            "category":"Health Services",
            "subcategory":"Doctor",
            "type":"Services"
        }
    ],
    "sg:phone":"+1 406 442 0282",
    "sg:postcode":"59601",
    "sg:province":"MT",
    "wof:name":"Eddy A Crowley DDS",
    "wof:placetype":"venue"
},
  "geometry": {"coordinates":[-112.03874399999999,46.588092],"type":"Point"}
}