{
  "type": "Feature",
  "properties": {
    "iso:country":"US",
    "sg:address":"300 N Willson Ave",
    "sg:city":"Bozeman",
    "sg:classifiers":[
        {
            "category":"Health Services",
            "subcategory":"Doctor",
            "type":"Services"
        }
    ],
    "sg:phone":"+1 406 587 5442",
    "sg:postcode":"59715",
    "sg:province":"MT",
    "sg:tags":[
        "medical"
    ],
    "wof:name":"Bozeman Skin Clinic",
    "wof:placetype":"venue"
},
  "geometry": {"coordinates":[-111.038738,45.682978],"type":"Point"}
}