{
  "type": "Feature",
  "properties": {
    "iso:country":"US",
    "sg:address":"3567 State Hwy 287",
    "sg:city":"Sheridan",
    "sg:classifiers":[
        {
            "category":"Social Services",
            "subcategory":"Child Care",
            "type":"Services"
        }
    ],
    "sg:phone":"+1 406 842 5815",
    "sg:postcode":"59749",
    "sg:province":"MT",
    "wof:name":"Lill Dickens Daycare",
    "wof:placetype":"venue"
},
  "geometry": {"coordinates":[-112.23452,45.486279],"type":"Point"}
}