{
  "type": "Feature",
  "properties": {
    "iso:country":"US",
    "sg:address":"329 N Pacific St",
    "sg:city":"Dillon",
    "sg:classifiers":[
        {
            "category":"Social Services",
            "subcategory":"Job Training",
            "type":"Services"
        }
    ],
    "sg:phone":"+1 406 683 5773",
    "sg:postcode":"59725",
    "sg:province":"MT",
    "sg:tags":[
        "residential",
        "care"
    ],
    "wof:name":"Dillon Special Resources",
    "wof:placetype":"venue"
},
  "geometry": {"coordinates":[-112.631908,45.218353],"type":"Point"}
}