{
  "type": "Feature",
  "properties": {
    "addr:full":"831 1st Ave N Glasgow MT 59230",
    "addr:housenumber":"831",
    "addr:street":"1St Ave N",
    "iso:country":"US",
    "sg:address":"831 1st Ave N",
    "sg:city":"Glasgow",
    "sg:classifiers":[
        {
            "category":"Retail",
            "subcategory":"Car Wash",
            "type":"Services"
        }
    ],
    "sg:phone":"+1 406 228 4235",
    "sg:postcode":"59230",
    "sg:province":"MT",
    "sg:tags":[
        "operated",
        "polishing",
        "washing"
    ],
    "wof:name":"Lawrence Car Wash Systems",
    "wof:placetype":"venue"
},
  "geometry": {"coordinates":[-106.639735,48.198092],"type":"Point"}
}