{
  "type": "Feature",
  "properties": {
    "iso:country":"US",
    "sg:address":"424 N 4th St",
    "sg:city":"Hamilton",
    "sg:classifiers":[
        {
            "category":"Freight",
            "type":"Transportation"
        }
    ],
    "sg:phone":"+1 406 363 2788",
    "sg:postcode":"59840",
    "sg:province":"MT",
    "sg:tags":[
        "operator",
        "local",
        "trucking"
    ],
    "wof:name":"Rohlfs Trucking Inc",
    "wof:placetype":"venue"
},
  "geometry": {"coordinates":[-114.160556,46.250763],"type":"Point"}
}