{
  "type": "Feature",
  "properties": {
    "iso:country":"US",
    "sg:address":"1627 W Main St",
    "sg:city":"Bozeman",
    "sg:classifiers":[
        {
            "category":"Freight",
            "type":"Transportation"
        }
    ],
    "sg:phone":"+1 406 585 8000",
    "sg:postcode":"59715",
    "sg:province":"MT",
    "sg:tags":[
        "mailing"
    ],
    "wof:name":"UPS Stores 2007 The",
    "wof:placetype":"venue"
},
  "geometry": {"coordinates":[-111.058279,45.679382],"type":"Point"}
}