{
  "type": "Feature",
  "properties": {
    "iso:country":"US",
    "sg:address":"430 Main St",
    "sg:city":"Billings",
    "sg:classifiers":[
        {
            "category":"Shopping",
            "type":"Retail Goods"
        }
    ],
    "sg:phone":"+1 406 248 2882",
    "sg:postcode":"59105",
    "sg:province":"MT",
    "sg:tags":[
        "picture",
        "frame"
    ],
    "wof:name":"Country Loft Frame & Gallery",
    "wof:placetype":"venue"
},
  "geometry": {"coordinates":[-108.475151,45.805951],"type":"Point"}
}