{
  "type": "Feature",
  "properties": {
    "iso:country":"US",
    "sg:address":"1 5th St W",
    "sg:city":"Billings",
    "sg:classifiers":[
        {
            "category":"Building & Trades",
            "subcategory":"Plumbing",
            "type":"Services"
        }
    ],
    "sg:phone":"+1 406 632 4400",
    "sg:postcode":"59101",
    "sg:province":"MT",
    "sg:tags":[
        "plumbing",
        "contractor"
    ],
    "wof:name":"Wilting Plumbing & Heating",
    "wof:placetype":"venue"
},
  "geometry": {"coordinates":[-108.527874,45.771131],"type":"Point"}
}