{
  "type": "Feature",
  "properties": {
    "iso:country":"US",
    "sg:address":"33 N Broadway",
    "sg:city":"Billings",
    "sg:classifiers":[
        {
            "category":"Professional",
            "subcategory":"Lawyer & Legal Services",
            "type":"Services"
        }
    ],
    "sg:phone":"+1 406 294 5014",
    "sg:postcode":"59101",
    "sg:province":"MT",
    "sg:tags":[
        "attorney"
    ],
    "wof:name":"Steven A Kelly",
    "wof:placetype":"venue"
},
  "geometry": {"coordinates":[-108.505453,45.781872],"type":"Point"}
}