{
  "type": "Feature",
  "properties": {
    "addr:full":"656 N Ewing St Helena MT 59601",
    "addr:housenumber":"656",
    "addr:postcode":"59601",
    "addr:street":"N Ewing",
    "iso:country":"US",
    "sg:address":"656 N Ewing St",
    "sg:city":"Helena",
    "sg:classifiers":[
        {
            "category":"Professional",
            "subcategory":"Management & Consulting",
            "type":"Services"
        }
    ],
    "sg:phone":"+1 406 495 9910",
    "sg:postcode":"59601",
    "sg:province":"MT",
    "sg:tags":[
        "environmental",
        "assessment"
    ],
    "wof:name":"Kendy Hydrologic Consulting",
    "wof:placetype":"venue"
},
  "geometry": {"coordinates":[-112.030794,46.592416],"type":"Point"}
}