{
  "type": "Feature",
  "properties": {
    "addr:full":"2048 Overland Ave Billings MT 59102",
    "addr:housenumber":"2048",
    "addr:postcode":"59102",
    "addr:street":"Overland Ave",
    "iso:country":"US",
    "sg:address":"2048 Overland Ave",
    "sg:city":"Billings",
    "sg:classifiers":[
        {
            "category":"Professional",
            "subcategory":"Advertising",
            "type":"Services"
        }
    ],
    "sg:phone":"+1 406 656 0608",
    "sg:postcode":"59102",
    "sg:province":"MT",
    "sg:tags":[
        "counselor"
    ],
    "sg:website":"www.rimadvertising.com",
    "wof:name":"Rim Advertising",
    "wof:placetype":"venue"
},
  "geometry": {"coordinates":[-108.566518,45.754833],"type":"Point"}
}