{
  "type": "Feature",
  "properties": {
    "addr:full":"5360 Southgate Dr Billings MT 59101",
    "addr:housenumber":"5360",
    "addr:postcode":"59101",
    "addr:street":"Southgate Dr",
    "iso:country":"US",
    "sg:address":"5360 Southgate Dr",
    "sg:city":"Billings",
    "sg:classifiers":[
        {
            "category":"Autos & Motor Vehicles",
            "subcategory":"Auto Supplies",
            "type":"Retail Goods"
        }
    ],
    "sg:phone":"+1 406 248 1196",
    "sg:postcode":"59101",
    "sg:province":"MT",
    "sg:tags":[
        "tire"
    ],
    "sg:website":"www.wingfootct.com",
    "wof:name":"Wingfoot Commercial Tire Systs",
    "wof:placetype":"venue"
},
  "geometry": {"coordinates":[-108.54943299999999,45.75348],"type":"Point"}
}