{
  "type": "Feature",
  "properties": {
    "addr:full":"333 2nd Ave N Lewistown MT 59457",
    "addr:housenumber":"333",
    "addr:postcode":"59457",
    "addr:street":"2Nd Ave N",
    "iso:country":"US",
    "sg:address":"333 2nd Ave N",
    "sg:city":"Lewistown",
    "sg:classifiers":[
        {
            "category":"Wholesale",
            "subcategory":"Sporting Goods",
            "type":"Manufacturing & Wholesale Goods"
        }
    ],
    "sg:phone":"+1 406 538 3496",
    "sg:postcode":"59457",
    "sg:province":"MT",
    "wof:name":"Sports Incorporated",
    "wof:placetype":"venue"
},
  "geometry": {"coordinates":[-109.42669600000001,47.067475],"type":"Point"}
}