{
  "type": "Feature",
  "properties": {
    "iso:country":"US",
    "sg:address":"407 Main St",
    "sg:city":"Deer Lodge",
    "sg:classifiers":[
        {
            "category":"Personal",
            "subcategory":"Beauty Salon",
            "type":"Services"
        }
    ],
    "sg:phone":"+1 406 846 1744",
    "sg:postcode":"59722",
    "sg:province":"MT",
    "wof:name":"Todays Image",
    "wof:placetype":"venue"
},
  "geometry": {"coordinates":[-112.735141,46.398863],"type":"Point"}
}