{
  "type": "Feature",
  "properties": {
    "iso:country":"US",
    "sg:address":"1115 13th St",
    "sg:city":"Havre",
    "sg:classifiers":[
        {
            "category":"Farming",
            "subcategory":"Farm",
            "type":"Manufacturing & Wholesale Goods"
        }
    ],
    "sg:phone":"+1 406 265 1887",
    "sg:postcode":"59501",
    "sg:province":"MT",
    "sg:tags":[
        "crop",
        "general"
    ],
    "wof:name":"Robin Toner Farm",
    "wof:placetype":"venue"
},
  "geometry": {"coordinates":[-109.666459,48.540579],"type":"Point"}
}