{
  "type": "Feature",
  "properties": {
    "iso:country":"US",
    "sg:address":"4081 Hwy 312",
    "sg:city":"Billings",
    "sg:classifiers":[
        {
            "category":"Autos & Motor Vehicles",
            "subcategory":"Auto Supplies",
            "type":"Retail Goods"
        }
    ],
    "sg:phone":"+1 406 373 5625",
    "sg:postcode":"59105",
    "sg:province":"MT",
    "sg:tags":[
        "equipment",
        "racing",
        "car",
        "automobile"
    ],
    "wof:name":"DRW Performance",
    "wof:placetype":"venue"
},
  "geometry": {"coordinates":[-108.422696,45.873095],"type":"Point"}
}