{
  "type": "Feature",
  "properties": {
    "addr:full":"615 3rd Ave N Great Falls MT 59401",
    "addr:housenumber":"615",
    "addr:postcode":"59401",
    "addr:street":"3Rd Ave N",
    "iso:country":"US",
    "sg:address":"615 3rd Ave N",
    "sg:city":"Great Falls",
    "sg:classifiers":[
        {
            "category":"Professional",
            "subcategory":"Lawyer & Legal Services",
            "type":"Services"
        }
    ],
    "sg:phone":"+1 406 727 8464",
    "sg:postcode":"59401",
    "sg:province":"MT",
    "sg:tags":[
        "attorney"
    ],
    "wof:name":"Lewin Law Office",
    "wof:placetype":"venue"
},
  "geometry": {"coordinates":[-111.29571,47.508654],"type":"Point"}
}