{
  "type": "Feature",
  "properties": {
    "iso:country":"US",
    "sg:address":"1716 S 3rd St W",
    "sg:city":"Missoula",
    "sg:classifiers":[
        {
            "category":"Wholesale",
            "subcategory":"Construction Materials",
            "type":"Manufacturing & Wholesale Goods"
        }
    ],
    "sg:phone":"+1 406 721 6994",
    "sg:postcode":"59801",
    "sg:province":"MT",
    "sg:tags":[
        "fencing",
        "supply"
    ],
    "wof:name":"Alko Supply",
    "wof:placetype":"venue"
},
  "geometry": {"coordinates":[-114.024069,46.867045],"type":"Point"}
}