{
  "type": "Feature",
  "properties": {
    "iso:country":"US",
    "sg:address":"2117 S Tracy Ave",
    "sg:city":"Bozeman",
    "sg:classifiers":[
        {
            "category":"Retail",
            "subcategory":"Portrait Studio",
            "type":"Services"
        }
    ],
    "sg:phone":"+1 406 522 9700",
    "sg:postcode":"59715",
    "sg:province":"MT",
    "sg:tags":[
        "photo"
    ],
    "wof:name":"Stenzel Photography",
    "wof:placetype":"venue"
},
  "geometry": {"coordinates":[-111.04053399999999,45.658782],"type":"Point"}
}