{
  "type": "Feature",
  "properties": {
    "iso:country":"US",
    "sg:address":"622 E Main St",
    "sg:city":"Cut Bank",
    "sg:classifiers":[
        {
            "category":"Health Services",
            "subcategory":"Chiropractor",
            "type":"Services"
        }
    ],
    "sg:phone":"+1 406 873 4100",
    "sg:postcode":"59427",
    "sg:province":"MT",
    "wof:name":"Chiropractic Services",
    "wof:placetype":"venue"
},
  "geometry": {"coordinates":[-112.325243,48.63218],"type":"Point"}
}