{
  "type": "Feature",
  "properties": {
    "iso:country":"US",
    "sg:address":"3250 S Reserve St",
    "sg:city":"Missoula",
    "sg:classifiers":[
        {
            "category":"Home & Garden",
            "subcategory":"Home Furnishings",
            "type":"Retail Goods"
        }
    ],
    "sg:phone":"+1 406 543 7166",
    "sg:postcode":"59801",
    "sg:province":"MT",
    "sg:tags":[
        "light",
        "fixture"
    ],
    "wof:name":"Western Montana Lighting",
    "wof:placetype":"venue"
},
  "geometry": {"coordinates":[-114.039503,46.841043],"type":"Point"}
}