{
  "type": "Feature",
  "properties": {
    "iso:country":"US",
    "sg:address":"5 1st St",
    "sg:city":"Havre",
    "sg:classifiers":[
        {
            "category":"Wholesale",
            "subcategory":"Farm Supplies",
            "type":"Manufacturing & Wholesale Goods"
        }
    ],
    "sg:phone":"+1 406 265 2296",
    "sg:postcode":"59501",
    "sg:province":"MT",
    "sg:tags":[
        "bulk",
        "fuel",
        "hardware",
        "feed"
    ],
    "wof:name":"C H S",
    "wof:placetype":"venue"
},
  "geometry": {"coordinates":[-109.682943,48.554053],"type":"Point"}
}