{
  "type": "Feature",
  "properties": {
    "iso:country":"US",
    "sg:address":"315 Charlos St",
    "sg:city":"Stevensville",
    "sg:classifiers":[
        {
            "category":"Museum",
            "type":"Entertainment"
        }
    ],
    "sg:phone":"+1 406 777 5734",
    "sg:postcode":"59870",
    "sg:province":"MT",
    "wof:name":"St Mary's Mission-1841",
    "wof:placetype":"venue"
},
  "geometry": {"coordinates":[-114.096739,46.510191],"type":"Point"}
}