{
  "type": "Feature",
  "properties": {
    "addr:full":"210 S Lake Ave Miles City MT 59301",
    "addr:housenumber":"210",
    "addr:postcode":"59301",
    "addr:street":"S Lake Ave",
    "iso:country":"US",
    "sg:address":"210 S Lake Ave",
    "sg:city":"Miles City",
    "sg:classifiers":[
        {
            "category":"Education",
            "subcategory":"School",
            "type":"Public Place"
        }
    ],
    "sg:phone":"+1 406 234 1697",
    "sg:postcode":"59301",
    "sg:province":"MT",
    "wof:name":"Lincoln Elementary School",
    "wof:placetype":"venue"
},
  "geometry": {"coordinates":[-105.838234,46.406237],"type":"Point"}
}