{
  "type": "Feature",
  "properties": {
    "iso:country":"US",
    "sg:address":"8318 State Hwy 212",
    "sg:city":"Charlo",
    "sg:classifiers":[
        {
            "category":"Personal",
            "subcategory":"Beauty Salon",
            "type":"Services"
        }
    ],
    "sg:phone":"+1 406 644 2444",
    "sg:postcode":"59824",
    "sg:province":"MT",
    "sg:tags":[
        "shop"
    ],
    "wof:name":"Maxine's Country Cut & Curl",
    "wof:placetype":"venue"
},
  "geometry": {"coordinates":[-114.202797,47.387979],"type":"Point"}
}