{
  "type": "Feature",
  "properties": {
    "iso:country":"US",
    "sg:address":"5751 Daisy Ln",
    "sg:city":"Florence",
    "sg:classifiers":[
        {
            "category":"Home & Garden",
            "subcategory":"Furniture",
            "type":"Retail Goods"
        }
    ],
    "sg:phone":"+1 406 273 6449",
    "sg:postcode":"59833",
    "sg:province":"MT",
    "sg:tags":[
        "cabinet"
    ],
    "wof:name":"Westwood Cabinets",
    "wof:placetype":"venue"
},
  "geometry": {"coordinates":[-114.103657,46.658475],"type":"Point"}
}