{
  "type": "Feature",
  "properties": {
    "iso:country":"US",
    "sg:address":"2825 W Main St",
    "sg:city":"Bozeman",
    "sg:classifiers":[
        {
            "category":"Government",
            "subcategory":"Office",
            "type":"Public Place"
        }
    ],
    "sg:phone":"+1 406 586 8571",
    "sg:postcode":"59718",
    "sg:province":"MT",
    "sg:tags":[
        "army"
    ],
    "wof:name":"U S Army Recruiting Office",
    "wof:placetype":"venue"
},
  "geometry": {"coordinates":[-111.074416,45.672543],"type":"Point"}
}