{
  "type": "Feature",
  "properties": {
    "addr:full":"1101 7th St S Great Falls MT 59405",
    "addr:housenumber":"1101",
    "addr:postcode":"59405",
    "addr:street":"7Th St S",
    "iso:country":"US",
    "sg:address":"1101 7th St S",
    "sg:city":"Great Falls",
    "sg:classifiers":[
        {
            "category":"Freight",
            "type":"Transportation"
        }
    ],
    "sg:phone":"+1 406 454 3985",
    "sg:postcode":"59405",
    "sg:province":"MT",
    "sg:tags":[
        "rug",
        "carpet"
    ],
    "wof:name":"Inland Northwest Distributing",
    "wof:placetype":"venue"
},
  "geometry": {"coordinates":[-111.295613,47.492169],"type":"Point"}
}