{
  "type": "Feature",
  "properties": {
    "iso:country":"US",
    "sg:address":"25 Main Ave S",
    "sg:city":"Choteau",
    "sg:classifiers":[
        {
            "category":"Cinema",
            "subcategory":"Movie Theater",
            "type":"Entertainment"
        }
    ],
    "sg:phone":"+1 406 466 2413",
    "sg:postcode":"59422",
    "sg:province":"MT",
    "wof:name":"Roxy Theatre",
    "wof:placetype":"venue"
},
  "geometry": {"coordinates":[-112.182683,47.810267],"type":"Point"}
}