{
  "type": "Feature",
  "properties": {
    "iso:country":"US",
    "sg:address":"5805 Helena Dr",
    "sg:city":"Missoula",
    "sg:classifiers":[
        {
            "category":"Manufacturing",
            "subcategory":"Printing",
            "type":"Manufacturing & Wholesale Goods"
        }
    ],
    "sg:phone":"+1 406 251 5189",
    "sg:postcode":"59803",
    "sg:province":"MT",
    "sg:tags":[
        "book"
    ],
    "wof:name":"Big Sky Publishing",
    "wof:placetype":"venue"
},
  "geometry": {"coordinates":[-114.064868,46.816618],"type":"Point"}
}