{
  "type": "Feature",
  "properties": {
    "iso:country":"US",
    "sg:address":"305 W Water St",
    "sg:city":"Lewistown",
    "sg:classifiers":[
        {
            "category":"Building & Trades",
            "subcategory":"Construction",
            "type":"Services"
        }
    ],
    "sg:phone":"+1 406 538 8590",
    "sg:postcode":"59457",
    "sg:province":"MT",
    "sg:tags":[
        "roofing",
        "contractor"
    ],
    "wof:name":"Irish Construction",
    "wof:placetype":"venue"
},
  "geometry": {"coordinates":[-109.42470899999999,47.063178],"type":"Point"}
}