{
  "type": "Feature",
  "properties": {
    "addr:full":"713 N Knight St Miles City MT 59301",
    "addr:housenumber":"713",
    "addr:postcode":"59301",
    "addr:street":"N Knight St",
    "iso:country":"US",
    "sg:address":"713 N Knight St",
    "sg:city":"Miles City",
    "sg:classifiers":[
        {
            "category":"Wholesale",
            "subcategory":"Meat",
            "type":"Manufacturing & Wholesale Goods"
        }
    ],
    "sg:phone":"+1 406 232 3556",
    "sg:postcode":"59301",
    "sg:province":"MT",
    "sg:tags":[
        "plant",
        "packing"
    ],
    "wof:name":"Butcher Block Specialties",
    "wof:placetype":"venue"
},
  "geometry": {"coordinates":[-105.845029,46.413993],"type":"Point"}
}