{
  "type": "Feature",
  "properties": {
    "addr:full":"320 N Kendrick Ave Glendive MT 59330",
    "addr:housenumber":"320",
    "addr:postcode":"59330",
    "addr:street":"N Kendrick Ave",
    "iso:country":"US",
    "sg:address":"320 N Kendrick Ave",
    "sg:city":"Glendive",
    "sg:classifiers":[
        {
            "category":"Home & Garden",
            "subcategory":"Furniture",
            "type":"Retail Goods"
        }
    ],
    "sg:phone":"+1 406 365 3665",
    "sg:postcode":"59330",
    "sg:province":"MT",
    "wof:name":"Koch Furniture",
    "wof:placetype":"venue"
},
  "geometry": {"coordinates":[-104.712412,47.107395],"type":"Point"}
}