{
  "type": "Feature",
  "properties": {
    "addr:full":"559 Colony Rd Roundup MT 59072",
    "addr:housenumber":"559",
    "addr:postcode":"59072",
    "addr:street":"Colony Rd",
    "iso:country":"US",
    "sg:address":"559 Colony Rd",
    "sg:city":"Roundup",
    "sg:classifiers":[
        {
            "category":"Farming",
            "subcategory":"Livestock Farm",
            "type":"Manufacturing & Wholesale Goods"
        }
    ],
    "sg:phone":"+1 406 429 7661",
    "sg:postcode":"59072",
    "sg:province":"MT",
    "sg:tags":[
        "ranch",
        "grain"
    ],
    "wof:name":"Flatwillow Colony",
    "wof:placetype":"venue"
},
  "geometry": {"coordinates":[-108.490844,46.723442],"type":"Point"}
}