{
  "type": "Feature",
  "properties": {
    "addr:full":"1769 Conn Rd Columbia Falls MT 59912",
    "addr:housenumber":"1769",
    "addr:postcode":"59912",
    "addr:street":"Conn Rd",
    "iso:country":"US",
    "sg:address":"1769 Conn Rd",
    "sg:city":"Columbia Falls",
    "sg:classifiers":[
        {
            "category":"Professional",
            "type":"Services"
        }
    ],
    "sg:phone":"+1 406 862 2700",
    "sg:postcode":"59912",
    "sg:province":"MT",
    "wof:name":"Pampered Chef",
    "wof:placetype":"venue"
},
  "geometry": {"coordinates":[-114.276427,48.356372],"type":"Point"}
}