{
  "type": "Feature",
  "properties": {
    "iso:country":"US",
    "sg:address":"1480 Continental Dr",
    "sg:city":"Butte",
    "sg:phone":"+1 406 782 8397",
    "sg:postcode":"59701",
    "sg:province":"MT",
    "sg:tags":[
        "oil"
    ],
    "wof:name":"Mountain States Oil Co",
    "wof:placetype":"venue"
},
  "geometry": {"coordinates":[-112.48813800000001,45.998244],"type":"Point"}
}