{
  "type": "Feature",
  "properties": {
    "iso:country":"US",
    "sg:address":"421 Main St",
    "sg:city":"Polson",
    "sg:classifiers":[
        {
            "category":"Professional",
            "subcategory":"Accounting & Tax Preparation",
            "type":"Services"
        }
    ],
    "sg:phone":"+1 406 883 3592",
    "sg:postcode":"59860",
    "sg:province":"MT",
    "wof:name":"Jodi Windauer CPA",
    "wof:placetype":"venue"
},
  "geometry": {"coordinates":[-114.16331,47.692108],"type":"Point"}
}