{
  "type": "Feature",
  "properties": {
    "iso:country":"US",
    "sg:address":"2207 S 3rd St W",
    "sg:city":"Missoula",
    "sg:classifiers":[
        {
            "category":"Banks & Credit Unions",
            "subcategory":"Investment Brokerage",
            "type":"Services"
        }
    ],
    "sg:phone":"+1 406 542 1859",
    "sg:postcode":"59801",
    "sg:province":"MT",
    "sg:tags":[
        "dealer",
        "commodity"
    ],
    "wof:name":"Jackson Commodities Inc",
    "wof:placetype":"venue"
},
  "geometry": {"coordinates":[-114.033394,46.866868],"type":"Point"}
}