{
  "type": "Feature",
  "properties": {
    "addr:full":"1100 S 1st St Hamilton MT 59840",
    "addr:housenumber":"1100",
    "addr:postcode":"59840",
    "addr:street":"S 1St St",
    "iso:country":"US",
    "sg:address":"1100 S 1st St",
    "sg:city":"Hamilton",
    "sg:classifiers":[
        {
            "category":"Retail",
            "subcategory":"Auto Rental",
            "type":"Services"
        }
    ],
    "sg:phone":"+1 406 375 9393",
    "sg:postcode":"59840",
    "sg:province":"MT",
    "sg:tags":[
        "renting",
        "automobile"
    ],
    "sg:website":"www.enterprise.com",
    "wof:name":"Enterprise Rent-A-Car",
    "wof:placetype":"venue"
},
  "geometry": {"coordinates":[-114.15514899999999,46.233282],"type":"Point"}
}