{
  "type": "Feature",
  "properties": {
    "iso:country":"US",
    "sg:address":"205 N Tracy Ave",
    "sg:city":"Bozeman",
    "sg:classifiers":[
        {
            "category":"Health Services",
            "subcategory":"Clinic",
            "type":"Services"
        }
    ],
    "sg:phone":"+1 406 587 8710",
    "sg:postcode":"59715",
    "sg:province":"MT",
    "sg:tags":[
        "home",
        "care"
    ],
    "wof:name":"Welhome Health",
    "wof:placetype":"venue"
},
  "geometry": {"coordinates":[-111.03724099999999,45.681292],"type":"Point"}
}