{
  "type": "Feature",
  "properties": {
    "addr:full":"408 Bridge St Bigfork MT 59911",
    "addr:housenumber":"408",
    "addr:postcode":"59911",
    "addr:street":"Bridge St",
    "iso:country":"US",
    "sg:address":"408 Bridge St",
    "sg:city":"Bigfork",
    "sg:classifiers":[
        {
            "category":"Restaurant",
            "type":"Food & Drink"
        }
    ],
    "sg:phone":"+1 406 837 2923",
    "sg:postcode":"59911",
    "sg:province":"MT",
    "sg:tags":[
        "eating"
    ],
    "wof:name":"LA Provence Restaurant",
    "wof:placetype":"venue"
},
  "geometry": {"coordinates":[-114.07284900000001,48.060884],"type":"Point"}
}