{
  "type": "Feature",
  "properties": {
    "iso:country":"US",
    "sg:address":"900 Carolina Ave",
    "sg:city":"Butte",
    "sg:classifiers":[
        {
            "category":"Professional",
            "subcategory":"Management & Consulting",
            "type":"Services"
        }
    ],
    "sg:phone":"+1 406 723 7859",
    "sg:postcode":"59701",
    "sg:province":"MT",
    "wof:name":"Lester M Crowe",
    "wof:placetype":"venue"
},
  "geometry": {"coordinates":[-112.509277,46.002556],"type":"Point"}
}