{
  "type": "Feature",
  "properties": {
    "iso:country":"US",
    "sg:address":"7232 Frey Rd",
    "sg:city":"Shepherd",
    "sg:phone":"+1 406 373 6137",
    "sg:postcode":"59079",
    "sg:province":"MT",
    "sg:tags":[
        "farm",
        "field",
        "crop"
    ],
    "wof:name":"Wolske Farms",
    "wof:placetype":"venue"
},
  "geometry": {"coordinates":[-108.322092,45.92998],"type":"Point"}
}