{
  "type": "Feature",
  "properties": {
    "addr:full":"3703 Harrison Ave Butte MT 59701",
    "addr:housenumber":"3703",
    "addr:postcode":"mt 59701",
    "addr:street":"Harrison Ave",
    "iso:country":"US",
    "sg:address":"3703 Harrison Ave",
    "sg:city":"Butte",
    "sg:classifiers":[
        {
            "category":"Organizations",
            "subcategory":"Non-profit Organization",
            "type":"Services"
        }
    ],
    "sg:phone":"+1 406 533 0020",
    "sg:postcode":"59701",
    "sg:province":"MT",
    "sg:tags":[
        "training",
        "used",
        "relate",
        "job",
        "social",
        "merchandise"
    ],
    "wof:name":"Easter Seals Goodwill Inds Mt",
    "wof:placetype":"venue"
},
  "geometry": {"coordinates":[-112.508011,45.970106],"type":"Point"}
}