{
  "type": "Feature",
  "properties": {
    "addr:full":"2223 1st Ave N Billings MT 59101",
    "addr:housenumber":"2223",
    "addr:postcode":"59101",
    "addr:street":"1St Ave N",
    "iso:country":"US",
    "sg:address":"2223 1st Ave N",
    "sg:city":"Billings",
    "sg:classifiers":[
        {
            "category":"Retail",
            "subcategory":"Auto Rental",
            "type":"Services"
        }
    ],
    "sg:phone":"+1 406 252 8007",
    "sg:postcode":"59101",
    "sg:province":"MT",
    "sg:tags":[
        "renting",
        "automobile"
    ],
    "sg:website":"www.avis.com",
    "wof:name":"Avis Rent A Car",
    "wof:placetype":"venue"
},
  "geometry": {"coordinates":[-108.49887699999999,45.785583],"type":"Point"}
}