{
  "type": "Feature",
  "properties": {
    "iso:country":"US",
    "sg:address":"7921 Cottonwood Rd",
    "sg:city":"Bozeman",
    "sg:classifiers":[
        {
            "category":"Building & Trades",
            "subcategory":"Construction",
            "type":"Services"
        }
    ],
    "sg:phone":"+1 406 587 2414",
    "sg:postcode":"59718",
    "sg:province":"MT",
    "sg:tags":[
        "contractor"
    ],
    "wof:name":"Sickler Roofing Service",
    "wof:placetype":"venue"
},
  "geometry": {"coordinates":[-111.104311,45.628666],"type":"Point"}
}