{
  "type": "Feature",
  "properties": {
    "iso:country":"US",
    "sg:address":"3436 South Ave W",
    "sg:city":"Missoula",
    "sg:classifiers":[
        {
            "category":"Professional",
            "subcategory":"Engineering",
            "type":"Services"
        }
    ],
    "sg:phone":"+1 406 542 6294",
    "sg:postcode":"59804",
    "sg:province":"MT",
    "sg:tags":[
        "engineer"
    ],
    "wof:name":"Jones Inc",
    "wof:placetype":"venue"
},
  "geometry": {"coordinates":[-114.06518,46.848825],"type":"Point"}
}