{
  "type": "Feature",
  "properties": {
    "iso:country":"US",
    "sg:address":"116 9th St N",
    "sg:city":"Great Falls",
    "sg:classifiers":[
        {
            "category":"Ice Cream",
            "type":"Food & Drink"
        }
    ],
    "sg:menulink":"http://www.allmenus.com/mt/great-falls/167510-dairy-queen/menu/",
    "sg:phone":"+1 406 452 3521",
    "sg:postcode":"59401",
    "sg:province":"MT",
    "sg:tags":[
        "burger",
        "american"
    ],
    "wof:name":"Dairy Queen",
    "wof:placetype":"venue"
},
  "geometry": {"coordinates":[-111.292091,47.506573],"type":"Point"}
}