{
  "type": "Feature",
  "properties": {
    "iso:country":"US",
    "sg:address":"3510 Eagle Bay Dr",
    "sg:city":"Helena",
    "sg:classifiers":[
        {
            "category":"Building & Trades",
            "subcategory":"Construction",
            "type":"Services"
        }
    ],
    "sg:phone":"+1 406 475 3685",
    "sg:postcode":"59602",
    "sg:province":"MT",
    "sg:tags":[
        "hanging",
        "contractor"
    ],
    "wof:name":"Connole Painting",
    "wof:placetype":"venue"
},
  "geometry": {"coordinates":[-111.755623,46.629497],"type":"Point"}
}