{
  "type": "Feature",
  "properties": {
    "addr:full":"1801 7th Ave S Great Falls MT 59405",
    "addr:housenumber":"1801",
    "addr:postcode":"59405",
    "addr:street":"7Th Ave S Great",
    "iso:country":"US",
    "sg:address":"1801 7th Ave S",
    "sg:city":"Great Falls",
    "sg:classifiers":[
        {
            "category":"Professional",
            "subcategory":"Business Services",
            "type":"Services"
        }
    ],
    "sg:phone":"+1 406 868 1417",
    "sg:postcode":"59405",
    "sg:province":"MT",
    "wof:name":"EKH Enterprise",
    "wof:placetype":"venue"
},
  "geometry": {"coordinates":[-111.27475800000001,47.497477],"type":"Point"}
}