{
  "type": "Feature",
  "properties": {
    "iso:country":"US",
    "sg:address":"455 83rd St W",
    "sg:city":"Billings",
    "sg:classifiers":[
        {
            "category":"Building & Trades",
            "subcategory":"Construction",
            "type":"Services"
        }
    ],
    "sg:phone":"+1 406 655 0272",
    "sg:postcode":"59106",
    "sg:province":"MT",
    "sg:tags":[
        "concrete",
        "contractor"
    ],
    "wof:name":"Montana Concrete",
    "wof:placetype":"venue"
},
  "geometry": {"coordinates":[-108.728345,45.758885],"type":"Point"}
}