{
  "type": "Feature",
  "properties": {
    "iso:country":"US",
    "sg:address":"3180 US Hwy 2 W",
    "sg:city":"Havre",
    "sg:classifiers":[
        {
            "category":"Shopping",
            "subcategory":"Department Store",
            "type":"Retail Goods"
        }
    ],
    "sg:phone":"+1 406 265 2020",
    "sg:postcode":"59501",
    "sg:province":"MT",
    "sg:website":"www.kmart.com",
    "wof:name":"Kmart",
    "wof:placetype":"venue"
},
  "geometry": {"coordinates":[-109.72940699999999,48.556505],"type":"Point"}
}