{
  "type": "Feature",
  "properties": {
    "iso:country":"US",
    "sg:address":"415 2nd Ave N",
    "sg:city":"Great Falls",
    "sg:classifiers":[
        {
            "category":"Education",
            "subcategory":"Library",
            "type":"Public Place"
        }
    ],
    "sg:phone":"+1 406 454 6775",
    "sg:postcode":"59401",
    "sg:province":"MT",
    "wof:name":"Law Library",
    "wof:placetype":"venue"
},
  "geometry": {"coordinates":[-111.299309,47.507599],"type":"Point"}
}