{
  "type": "Feature",
  "properties": {
    "addr:full":"11 S Idaho St Dillon MT 59725",
    "addr:housenumber":"11",
    "addr:postcode":"59725",
    "addr:street":"S Idaho St",
    "iso:country":"US",
    "sg:address":"11 S Idaho St",
    "sg:city":"Dillon",
    "sg:classifiers":[
        {
            "category":"Organizations",
            "subcategory":"Community Association",
            "type":"Services"
        }
    ],
    "sg:phone":"+1 406 683 2701",
    "sg:postcode":"59725",
    "sg:province":"MT",
    "sg:tags":[
        "fraternal"
    ],
    "wof:name":"Masonic Lodge",
    "wof:placetype":"venue"
},
  "geometry": {"coordinates":[-112.636751,45.217002],"type":"Point"}
}