{
  "type": "Feature",
  "properties": {
    "addr:full":"700 Dewey Blvd Butte MT 59701",
    "addr:housenumber":"700",
    "addr:postcode":"mt 59701",
    "addr:street":"Dewey Blvd",
    "iso:country":"US",
    "sg:address":"700 Dewey Blvd",
    "sg:city":"Butte",
    "sg:classifiers":[
        {
            "category":"Freight",
            "type":"Transportation"
        }
    ],
    "sg:phone":"+1 406 491 2508",
    "sg:postcode":"59701",
    "sg:province":"MT",
    "sg:tags":[
        "commercial",
        "storage"
    ],
    "wof:name":"Glacier State Mini Warehouse",
    "wof:placetype":"venue"
},
  "geometry": {"coordinates":[-112.525139,45.983394],"type":"Point"}
}