{
  "type": "Feature",
  "properties": {
    "iso:country":"US",
    "sg:address":"2232 Pueblo Dr",
    "sg:city":"Billings",
    "sg:classifiers":[
        {
            "category":"Building & Trades",
            "subcategory":"Construction",
            "type":"Services"
        }
    ],
    "sg:phone":"+1 406 656 4181",
    "sg:postcode":"59102",
    "sg:province":"MT",
    "sg:tags":[
        "house"
    ],
    "wof:name":"Perma-Glaze",
    "wof:placetype":"venue"
},
  "geometry": {"coordinates":[-108.575063,45.764172],"type":"Point"}
}