{
  "type": "Feature",
  "properties": {
    "addr:full":"22 4th St SW Baker MT 59313",
    "addr:housenumber":"22",
    "addr:postcode":"59313",
    "addr:street":"4Th St Sw",
    "iso:country":"US",
    "sg:address":"22 4th St SW",
    "sg:city":"Baker",
    "sg:classifiers":[
        {
            "category":"Mining & Drilling",
            "type":"Manufacturing & Wholesale Goods"
        }
    ],
    "sg:phone":"+1 406 778 3983",
    "sg:postcode":"59313",
    "sg:province":"MT",
    "sg:tags":[
        "well"
    ],
    "wof:name":"Multi Shot",
    "wof:placetype":"venue"
},
  "geometry": {"coordinates":[-104.281632,46.36936],"type":"Point"}
}