{
  "type": "Feature",
  "properties": {
    "addr:full":"820 Division St Billings MT 59101",
    "addr:housenumber":"820",
    "addr:postcode":"59101",
    "addr:street":"Division St",
    "iso:country":"US",
    "sg:address":"820 Division St",
    "sg:city":"Billings",
    "sg:classifiers":[
        {
            "category":"Professional",
            "subcategory":"Accounting & Tax Preparation",
            "type":"Services"
        }
    ],
    "sg:phone":"+1 406 248 7704",
    "sg:postcode":"59101",
    "sg:province":"MT",
    "wof:name":"Jackson Fekety & Odle",
    "wof:placetype":"venue"
},
  "geometry": {"coordinates":[-108.515322,45.77912],"type":"Point"}
}