{
  "type": "Feature",
  "properties": {
    "iso:country":"US",
    "sg:address":"86 6th Avenue W N",
    "sg:city":"Kalispell",
    "sg:classifiers":[
        {
            "category":"Retail",
            "subcategory":"Repair Shop",
            "type":"Services"
        }
    ],
    "sg:phone":"+1 406 755 9164",
    "sg:postcode":"59901",
    "sg:province":"MT",
    "sg:tags":[
        "equipment",
        "industrial",
        "welding"
    ],
    "wof:name":"Arrow Welding Service",
    "wof:placetype":"venue"
},
  "geometry": {"coordinates":[-114.323401,48.19884],"type":"Point"}
}