{
  "type": "Feature",
  "properties": {
    "iso:country":"US",
    "sg:address":"610 E Aluminum St",
    "sg:city":"Butte",
    "sg:classifiers":[
        {
            "category":"Freight",
            "type":"Transportation"
        }
    ],
    "sg:phone":"+1 406 782 7995",
    "sg:postcode":"59701",
    "sg:province":"MT",
    "sg:tags":[
        "operator",
        "trucking"
    ],
    "wof:name":"Boka Freight Line",
    "wof:placetype":"venue"
},
  "geometry": {"coordinates":[-112.52874,46.007529],"type":"Point"}
}