{
  "type": "Feature",
  "properties": {
    "addr:full":"212 Main St Westby MT 59275",
    "addr:housenumber":"212",
    "addr:postcode":"59275",
    "addr:street":"Main St",
    "iso:country":"US",
    "sg:address":"212 Main St",
    "sg:city":"Westby",
    "sg:classifiers":[
        {
            "category":"Food & Beverages",
            "subcategory":"Groceries & Convenience Stores",
            "type":"Retail Goods"
        }
    ],
    "sg:phone":"+1 406 385 2349",
    "sg:postcode":"59275",
    "sg:province":"MT",
    "sg:tags":[
        "grocer"
    ],
    "wof:name":"Westby Meat & Groceries",
    "wof:placetype":"venue"
},
  "geometry": {"coordinates":[-104.051237,48.87132],"type":"Point"}
}