{
  "type": "Feature",
  "properties": {
    "addr:full":"101 E Mendenhall St Bozeman MT 59715",
    "addr:housenumber":"101",
    "addr:postcode":"59715",
    "addr:street":"E Mendenhall St",
    "iso:country":"US",
    "sg:address":"101 E Mendenhall St",
    "sg:city":"Bozeman",
    "sg:classifiers":[
        {
            "category":"Professional",
            "subcategory":"Business Services",
            "type":"Services"
        }
    ],
    "sg:phone":"+1 406 587 5095",
    "sg:postcode":"59715",
    "sg:province":"MT",
    "wof:name":"Global Net",
    "wof:placetype":"venue"
},
  "geometry": {"coordinates":[-111.03435,45.680386],"type":"Point"}
}