{
  "type": "Feature",
  "properties": {
    "iso:country":"US",
    "sg:address":"602 Newlan Creek Rd",
    "sg:city":"White Sulphur Springs",
    "sg:classifiers":[
        {
            "category":"Real Estate",
            "subcategory":"Architect",
            "type":"Services"
        }
    ],
    "sg:phone":"+1 406 547 2229",
    "sg:postcode":"59645",
    "sg:province":"MT",
    "sg:tags":[
        "architectural"
    ],
    "wof:name":"Richard Weitz Architect",
    "wof:placetype":"venue"
},
  "geometry": {"coordinates":[-110.936085,46.637432],"type":"Point"}
}