{
  "type": "Feature",
  "properties": {
    "iso:country":"US",
    "sg:address":"8370 Forswall Rd",
    "sg:city":"Belgrade",
    "sg:phone":"+1 406 586 6460",
    "sg:postcode":"59714",
    "sg:province":"MT",
    "sg:tags":[
        "farm",
        "wheat",
        "crop",
        "general"
    ],
    "wof:name":"Saddle Mountain Ranches",
    "wof:placetype":"venue"
},
  "geometry": {"coordinates":[-111.003619,45.834811],"type":"Point"}
}