{
  "type": "Feature",
  "properties": {
    "iso:country":"US",
    "sg:address":"2139 Broadwater Ave",
    "sg:city":"Billings",
    "sg:classifiers":[
        {
            "category":"Social Services",
            "type":"Services"
        }
    ],
    "sg:phone":"+1 406 652 7752",
    "sg:postcode":"59102",
    "sg:province":"MT",
    "sg:tags":[
        "counselor",
        "marriage",
        "family"
    ],
    "wof:name":"Inner Journeys",
    "wof:placetype":"venue"
},
  "geometry": {"coordinates":[-108.56499100000001,45.776935],"type":"Point"}
}