{
  "type": "Feature",
  "properties": {
    "addr:full":"1311 W Bell St Glendive MT 59330",
    "addr:housenumber":"1311",
    "addr:postcode":"59330",
    "addr:street":"W Bell St",
    "iso:country":"US",
    "sg:address":"1311 W Bell St",
    "sg:city":"Glendive",
    "sg:classifiers":[
        {
            "category":"Sports & Exercise",
            "subcategory":"Gym",
            "type":"Entertainment"
        }
    ],
    "sg:phone":"+1 406 377 5733",
    "sg:postcode":"59330",
    "sg:province":"MT",
    "sg:tags":[
        "fitness",
        "physical",
        "facility"
    ],
    "wof:name":"Flex Appeal Fitness & Hlth Ctr",
    "wof:placetype":"venue"
},
  "geometry": {"coordinates":[-104.731551,47.105712],"type":"Point"}
}