{
  "type": "Feature",
  "properties": {
    "iso:country":"US",
    "sg:address":"301 Main St",
    "sg:city":"Roundup",
    "sg:classifiers":[
        {
            "category":"Personal",
            "subcategory":"Beauty Salon",
            "type":"Services"
        }
    ],
    "sg:phone":"+1 406 323 1307",
    "sg:postcode":"59072",
    "sg:province":"MT",
    "sg:tags":[
        "shop"
    ],
    "wof:name":"Mary Jane's Beauty Salon",
    "wof:placetype":"venue"
},
  "geometry": {"coordinates":[-108.541932,46.443833],"type":"Point"}
}