{
  "type": "Feature",
  "properties": {
    "iso:country":"US",
    "sg:address":"2415 Rimrock Rd",
    "sg:city":"Billings",
    "sg:classifiers":[
        {
            "category":"Social Services",
            "subcategory":"Child Care",
            "type":"Services"
        }
    ],
    "sg:phone":"+1 406 656 2219",
    "sg:postcode":"59102",
    "sg:province":"MT",
    "sg:tags":[
        "day"
    ],
    "wof:name":"Strawberry Patch",
    "wof:placetype":"venue"
},
  "geometry": {"coordinates":[-108.578118,45.79875],"type":"Point"}
}