{
  "type": "Feature",
  "properties": {
    "iso:country":"US",
    "sg:address":"121 N Broadway",
    "sg:city":"Billings",
    "sg:classifiers":[
        {
            "category":"Banks & Credit Unions",
            "subcategory":"Investment Brokerage",
            "type":"Services"
        }
    ],
    "sg:phone":"+1 406 245 7250",
    "sg:postcode":"59101",
    "sg:province":"MT",
    "sg:tags":[
        "land",
        "oil",
        "lease"
    ],
    "wof:name":"R W Mc Kamy",
    "wof:placetype":"venue"
},
  "geometry": {"coordinates":[-108.506378,45.78284],"type":"Point"}
}