{
  "type": "Feature",
  "properties": {
    "addr:full":"253 Bierney Creek Rd Lakeside MT 59922",
    "addr:housenumber":"253",
    "addr:postcode":"59922",
    "addr:street":"Bierney Creek Rd",
    "iso:country":"US",
    "sg:address":"253 Bierney Creek Rd",
    "sg:city":"Lakeside",
    "sg:classifiers":[
        {
            "category":"Utilities",
            "subcategory":"Water",
            "type":"Services"
        }
    ],
    "sg:phone":"+1 406 844 3881",
    "sg:postcode":"59922",
    "sg:province":"MT",
    "sg:tags":[
        "company",
        "sewage"
    ],
    "wof:name":"Lakeside County Water & Sewer",
    "wof:placetype":"venue"
},
  "geometry": {"coordinates":[-114.23031899999999,48.023941],"type":"Point"}
}