{
  "type": "Feature",
  "properties": {
    "addr:full":"3015 Shale Rock Dr Shepherd MT 59079",
    "addr:housenumber":"3015",
    "addr:postcode":"59079",
    "addr:street":"Shale Rock Dr",
    "iso:country":"US",
    "sg:address":"3015 Shale Rock Dr",
    "sg:city":"Shepherd",
    "sg:classifiers":[
        {
            "category":"Building & Trades",
            "subcategory":"Plumbing",
            "type":"Services"
        }
    ],
    "sg:phone":"+1 406 373 9855",
    "sg:postcode":"59079",
    "sg:province":"MT",
    "sg:tags":[
        "cooling",
        "heating"
    ],
    "wof:name":"Frontier Heating and Cooling",
    "wof:placetype":"venue"
},
  "geometry": {"coordinates":[-108.40846000000001,45.97637],"type":"Point"}
}