{
  "type": "Feature",
  "properties": {
    "iso:country":"US",
    "sg:address":"304 4th Ave",
    "sg:city":"Custer",
    "sg:classifiers":[
        {
            "category":"Education",
            "subcategory":"School",
            "type":"Public Place"
        }
    ],
    "sg:phone":"+1 406 856 4117",
    "sg:postcode":"59024",
    "sg:province":"MT",
    "wof:name":"Custer Public School",
    "wof:placetype":"venue"
},
  "geometry": {"coordinates":[-107.556589,46.127144],"type":"Point"}
}