{
  "type": "Feature",
  "properties": {
    "iso:country":"US",
    "sg:address":"77 3rd Avenue W N",
    "sg:city":"Kalispell",
    "sg:classifiers":[
        {
            "category":"Shopping",
            "subcategory":"Gifts & Souvenirs",
            "type":"Retail Goods"
        }
    ],
    "sg:phone":"+1 406 755 7648",
    "sg:postcode":"59901",
    "sg:province":"MT",
    "wof:name":"Twisted Sisters",
    "wof:placetype":"venue"
},
  "geometry": {"coordinates":[-114.318909,48.199714],"type":"Point"}
}