{
  "type": "Feature",
  "properties": {
    "iso:country":"US",
    "sg:address":"81 Mission Meadow Rd",
    "sg:city":"Livingston",
    "sg:classifiers":[
        {
            "category":"Building & Trades",
            "subcategory":"Construction",
            "type":"Services"
        }
    ],
    "sg:phone":"+1 406 222 3676",
    "sg:postcode":"59047",
    "sg:province":"MT",
    "sg:tags":[
        "contractor"
    ],
    "wof:name":"Hiatt Masonry",
    "wof:placetype":"venue"
},
  "geometry": {"coordinates":[-110.361081,45.609152],"type":"Point"}
}