{
  "type": "Feature",
  "properties": {
    "addr:full":"202 Montana St Hinsdale MT 59241",
    "addr:housenumber":"202",
    "addr:postcode":"59241",
    "addr:street":"Montana St",
    "iso:country":"US",
    "sg:address":"202 Montana St",
    "sg:city":"Hinsdale",
    "sg:classifiers":[
        {
            "category":"Bars & Pubs",
            "type":"Food & Drink"
        }
    ],
    "sg:phone":"+1 406 364 2300",
    "sg:postcode":"59241",
    "sg:province":"MT",
    "wof:name":"Rainbow Room",
    "wof:placetype":"venue"
},
  "geometry": {"coordinates":[-107.084817,48.394262],"type":"Point"}
}