{
  "type": "Feature",
  "properties": {
    "addr:full":"240 E Idaho St Kalispell MT 59901",
    "addr:housenumber":"240",
    "addr:postcode":"59901",
    "addr:street":"E Idaho St",
    "iso:country":"US",
    "sg:address":"240 E Idaho St",
    "sg:city":"Kalispell",
    "sg:classifiers":[
        {
            "category":"Personal",
            "subcategory":"Beauty Salon",
            "type":"Services"
        }
    ],
    "sg:phone":"+1 406 756 1536",
    "sg:postcode":"59901",
    "sg:province":"MT",
    "wof:name":"Hot Spot Hair & Tanning Salon",
    "wof:placetype":"venue"
},
  "geometry": {"coordinates":[-114.31112400000001,48.202733],"type":"Point"}
}