{
  "type": "Feature",
  "properties": {
    "iso:country":"US",
    "sg:address":"2108 S Reserve St",
    "sg:city":"Missoula",
    "sg:classifiers":[
        {
            "category":"Building & Trades",
            "subcategory":"Electrical",
            "type":"Services"
        }
    ],
    "sg:phone":"+1 406 542 2084",
    "sg:postcode":"59801",
    "sg:province":"MT",
    "sg:tags":[
        "electrical",
        "contractor"
    ],
    "wof:name":"Madden Enterprises",
    "wof:placetype":"venue"
},
  "geometry": {"coordinates":[-114.039541,46.850644],"type":"Point"}
}