{
  "type": "Feature",
  "properties": {
    "iso:country":"US",
    "sg:address":"863 Southside Rd",
    "sg:city":"Superior",
    "sg:classifiers":[
        {
            "category":"Retail",
            "subcategory":"Animal Services",
            "type":"Services"
        }
    ],
    "sg:phone":"+1 406 822 4404",
    "sg:postcode":"59872",
    "sg:province":"MT",
    "wof:name":"Roy L Foote",
    "wof:placetype":"venue"
},
  "geometry": {"coordinates":[-115.047567,47.232185],"type":"Point"}
}