{
  "type": "Feature",
  "properties": {
    "addr:full":"801 Grayling Dr Seeley Lake MT 59868",
    "addr:housenumber":"801",
    "addr:postcode":"59868",
    "addr:street":"Grayling Dr Seeley",
    "iso:country":"US",
    "sg:address":"801 Grayling Dr",
    "sg:city":"Seeley Lake",
    "sg:classifiers":[
        {
            "category":"Building & Trades",
            "subcategory":"Construction",
            "type":"Services"
        }
    ],
    "sg:phone":"+1 406 677 3564",
    "sg:postcode":"59868",
    "sg:province":"MT",
    "sg:tags":[
        "house"
    ],
    "wof:name":"R B Construction",
    "wof:placetype":"venue"
},
  "geometry": {"coordinates":[-113.44538799999999,47.159923],"type":"Point"}
}