{
  "type": "Feature",
  "properties": {
    "iso:country":"US",
    "sg:address":"1910 North Ave W",
    "sg:city":"Missoula",
    "sg:classifiers":[
        {
            "category":"Retail",
            "subcategory":"Repair Shop",
            "type":"Services"
        }
    ],
    "sg:phone":"+1 406 542 0271",
    "sg:postcode":"59801",
    "sg:province":"MT",
    "wof:name":"North Avenue Refinishing",
    "wof:placetype":"venue"
},
  "geometry": {"coordinates":[-114.028023,46.852521],"type":"Point"}
}