{
  "type": "Feature",
  "properties": {
    "addr:full":"199 Brunner Rd Columbia Falls MT 59912",
    "addr:housenumber":"199",
    "addr:postcode":"59912",
    "addr:street":"Brunner Rd",
    "iso:country":"US",
    "sg:address":"199 Brunner Rd",
    "sg:city":"Columbia Falls",
    "sg:classifiers":[
        {
            "category":"Building & Trades",
            "subcategory":"Construction",
            "type":"Services"
        }
    ],
    "sg:phone":"+1 406 892 3578",
    "sg:postcode":"59912",
    "sg:province":"MT",
    "sg:tags":[
        "steel",
        "contractor",
        "erection",
        "fabrication",
        "structural"
    ],
    "wof:name":"North Valley St & Fabrication",
    "wof:placetype":"venue"
},
  "geometry": {"coordinates":[-114.233898,48.34177],"type":"Point"}
}