{
  "type": "Feature",
  "properties": {
    "iso:country":"US",
    "sg:address":"244 Spokane Ave",
    "sg:city":"Whitefish",
    "sg:classifiers":[
        {
            "category":"Shopping",
            "subcategory":"Books",
            "type":"Retail Goods"
        }
    ],
    "sg:phone":"+1 406 862 4980",
    "sg:postcode":"59937",
    "sg:province":"MT",
    "wof:name":"Bookworks",
    "wof:placetype":"venue"
},
  "geometry": {"coordinates":[-114.33533,48.410117],"type":"Point"}
}