{
  "type": "Feature",
  "properties": {
    "iso:country":"US",
    "sg:address":"211 N 1st St",
    "sg:city":"Hamilton",
    "sg:classifiers":[
        {
            "category":"Autos & Motor Vehicles",
            "subcategory":"Auto Supplies",
            "type":"Retail Goods"
        }
    ],
    "sg:phone":"+1 406 363 3884",
    "sg:postcode":"59840",
    "sg:province":"MT",
    "sg:tags":[
        "tire"
    ],
    "wof:name":"Les Schwab Jerry Wessel's Tire",
    "wof:placetype":"venue"
},
  "geometry": {"coordinates":[-114.155959,46.249126],"type":"Point"}
}