{
  "type": "Feature",
  "properties": {
    "iso:country":"US",
    "sg:address":"22 Woodgrain Dr",
    "sg:city":"Billings",
    "sg:classifiers":[
        {
            "category":"Shopping",
            "subcategory":"Computers & Home Electronics",
            "type":"Retail Goods"
        }
    ],
    "sg:phone":"+1 406 670 5012",
    "sg:postcode":"59102",
    "sg:province":"MT",
    "sg:tags":[
        "software"
    ],
    "sg:website":"www.fortunetechnologies.com",
    "wof:name":"Fortune Technologies",
    "wof:placetype":"venue"
},
  "geometry": {"coordinates":[-108.597841,45.751743],"type":"Point"}
}