{
  "type": "Feature",
  "properties": {
    "addr:full":"803 California Ave Libby MT 59923",
    "addr:housenumber":"803",
    "addr:postcode":"59923",
    "addr:street":"California Ave",
    "iso:country":"US",
    "sg:address":"803 California Ave",
    "sg:city":"Libby",
    "sg:classifiers":[
        {
            "category":"Social Services",
            "type":"Services"
        }
    ],
    "sg:phone":"+1 406 293 3839",
    "sg:postcode":"59923",
    "sg:province":"MT",
    "wof:name":"Poplin Clay Msw Lcsw",
    "wof:placetype":"venue"
},
  "geometry": {"coordinates":[-115.555155,48.38903],"type":"Point"}
}