{
  "type": "Feature",
  "properties": {
    "iso:country":"US",
    "sg:address":"1 Palmer St",
    "sg:city":"Miles City",
    "sg:classifiers":[
        {
            "category":"Travel",
            "subcategory":"Campground",
            "type":"Entertainment"
        }
    ],
    "sg:phone":"+1 406 232 3991",
    "sg:postcode":"59301",
    "sg:province":"MT",
    "sg:tags":[
        "trailer"
    ],
    "wof:name":"KOA Kampgrounds",
    "wof:placetype":"venue"
},
  "geometry": {"coordinates":[-105.85874699999999,46.405861],"type":"Point"}
}