{
  "type": "Feature",
  "properties": {
    "iso:country":"US",
    "sg:address":"1900 S Reserve St",
    "sg:city":"Missoula",
    "sg:classifiers":[
        {
            "category":"Health Services",
            "subcategory":"Chiropractor",
            "type":"Services"
        }
    ],
    "sg:phone":"+1 406 721 9080",
    "sg:postcode":"59801",
    "sg:province":"MT",
    "wof:name":"Affilted Bttrroot Chiropractic",
    "wof:placetype":"venue"
},
  "geometry": {"coordinates":[-114.039511,46.853668],"type":"Point"}
}