{
  "type": "Feature",
  "properties": {
    "iso:country":"US",
    "sg:address":"3801 Ten Mile Rd",
    "sg:city":"Dillon",
    "sg:classifiers":[
        {
            "category":"Government",
            "subcategory":"Office",
            "type":"Public Place"
        }
    ],
    "sg:phone":"+1 406 683 3753",
    "sg:postcode":"59725",
    "sg:province":"MT",
    "sg:tags":[
        "water",
        "solid",
        "waste",
        "management",
        "air"
    ],
    "wof:name":"Solid Waste Department",
    "wof:placetype":"venue"
},
  "geometry": {"coordinates":[-112.689576,45.223957],"type":"Point"}
}