{
  "type": "Feature",
  "properties": {
    "iso:country":"US",
    "sg:address":"10626 C A Rd",
    "sg:city":"Shepherd",
    "sg:classifiers":[
        {
            "category":"Farming",
            "subcategory":"Livestock Farm",
            "type":"Manufacturing & Wholesale Goods"
        }
    ],
    "sg:phone":"+1 406 373 5741",
    "sg:postcode":"59079",
    "sg:province":"MT",
    "sg:tags":[
        "feeding"
    ],
    "wof:name":"Weschenfelder Feedlot",
    "wof:placetype":"venue"
},
  "geometry": {"coordinates":[-108.28818200000001,45.988529],"type":"Point"}
}