{
  "type": "Feature",
  "properties": {
    "iso:country":"US",
    "sg:address":"111 N 3rd St",
    "sg:city":"Livingston",
    "sg:classifiers":[
        {
            "category":"Real Estate",
            "subcategory":"Real Estate Agent",
            "type":"Services"
        }
    ],
    "sg:phone":"+1 406 222 2209",
    "sg:postcode":"59047",
    "sg:province":"MT",
    "sg:tags":[
        "appraiser"
    ],
    "wof:name":"Kurt Holm & Assoc",
    "wof:placetype":"venue"
},
  "geometry": {"coordinates":[-110.562978,45.660669],"type":"Point"}
}