{
  "type": "Feature",
  "properties": {
    "addr:full":"710 Conrad Dr Kalispell MT 59901",
    "addr:housenumber":"710",
    "addr:postcode":"59901",
    "addr:street":"Conrad Dr",
    "iso:country":"US",
    "sg:address":"710 Conrad Dr",
    "sg:city":"Kalispell",
    "sg:classifiers":[
        {
            "category":"Retail",
            "subcategory":"Repair Shop",
            "type":"Services"
        }
    ],
    "sg:phone":"+1 406 752 4823",
    "sg:postcode":"59901",
    "sg:province":"MT",
    "wof:name":"Randalls T V",
    "wof:placetype":"venue"
},
  "geometry": {"coordinates":[-114.28677399999999,48.203342],"type":"Point"}
}