{
  "type": "Feature",
  "properties": {
    "addr:full":"2165 US Hwy 2 E Kalispell MT 59901",
    "addr:housenumber":"2165",
    "addr:postcode":"59901",
    "addr:street":"Us Hwy 2 E",
    "iso:country":"US",
    "sg:address":"2165 US Hwy 2 E",
    "sg:city":"Kalispell",
    "sg:classifiers":[
        {
            "category":"Shopping",
            "subcategory":"Crafts & Fabrics",
            "type":"Retail Goods"
        }
    ],
    "sg:phone":"+1 406 752 2987",
    "sg:postcode":"59901",
    "sg:province":"MT",
    "sg:tags":[
        "shop"
    ],
    "wof:name":"Jo-Ann Fabrics & Crafts",
    "wof:placetype":"venue"
},
  "geometry": {"coordinates":[-114.277218,48.222366],"type":"Point"}
}