{
  "type": "Feature",
  "properties": {
    "iso:country":"US",
    "sg:address":"1900 Williams St",
    "sg:city":"Helena",
    "sg:classifiers":[
        {
            "category":"Professional",
            "subcategory":"Management & Consulting",
            "type":"Services"
        }
    ],
    "sg:phone":"+1 406 443 0665",
    "sg:postcode":"59602",
    "sg:province":"MT",
    "sg:tags":[
        "food",
        "business",
        "catering"
    ],
    "wof:name":"Big Sky Catering",
    "wof:placetype":"venue"
},
  "geometry": {"coordinates":[-112.094415,46.614837],"type":"Point"}
}