{
  "type": "Feature",
  "properties": {
    "addr:full":"502 Main St Deer Lodge MT 59722",
    "addr:housenumber":"502",
    "addr:postcode":"59722",
    "addr:street":"Main St",
    "iso:country":"US",
    "sg:address":"502 Main St",
    "sg:city":"Deer Lodge",
    "sg:classifiers":[
        {
            "category":"Restaurant",
            "type":"Food & Drink"
        }
    ],
    "sg:phone":"+1 406 846 3026",
    "sg:postcode":"59722",
    "sg:province":"MT",
    "wof:name":"Spanky's Pizza & Sandwich",
    "wof:placetype":"venue"
},
  "geometry": {"coordinates":[-112.735372,46.397877],"type":"Point"}
}