{
  "type": "Feature",
  "properties": {
    "iso:country":"US",
    "sg:address":"605 Twilight Cir",
    "sg:city":"Kalispell",
    "sg:classifiers":[
        {
            "category":"Food & Beverages",
            "subcategory":"Bakery",
            "type":"Retail Goods"
        }
    ],
    "sg:phone":"+1 406 752 2978",
    "sg:postcode":"59901",
    "sg:province":"MT",
    "wof:name":"Cakes By Debi",
    "wof:placetype":"venue"
},
  "geometry": {"coordinates":[-114.280255,48.242273],"type":"Point"}
}