{
  "type": "Feature",
  "properties": {
    "iso:country":"US",
    "sg:address":"321 Main St",
    "sg:city":"Deer Lodge",
    "sg:classifiers":[
        {
            "category":"Food & Beverages",
            "subcategory":"Bakery",
            "type":"Retail Goods"
        }
    ],
    "sg:phone":"+1 406 846 7581",
    "sg:postcode":"59722",
    "sg:province":"MT",
    "wof:name":"Boomerang Bakery",
    "wof:placetype":"venue"
},
  "geometry": {"coordinates":[-112.735084,46.399756],"type":"Point"}
}