{
  "type": "Feature",
  "properties": {
    "iso:country":"US",
    "sg:address":"1717 1st Ave N",
    "sg:city":"Billings",
    "sg:classifiers":[
        {
            "category":"Autos & Motor Vehicles",
            "subcategory":"Automobile Sales",
            "type":"Retail Goods"
        }
    ],
    "sg:phone":"+1 406 252 4585",
    "sg:postcode":"59101",
    "sg:province":"MT",
    "sg:tags":[
        "truck"
    ],
    "wof:name":"Steve's Auto Sales",
    "wof:placetype":"venue"
},
  "geometry": {"coordinates":[-108.493433,45.788191],"type":"Point"}
}