{
  "type": "Feature",
  "properties": {
    "iso:country":"US",
    "sg:address":"3620 Kiowa Trl",
    "sg:city":"Billings",
    "sg:classifiers":[
        {
            "category":"Professional",
            "subcategory":"Business Services",
            "type":"Services"
        }
    ],
    "sg:phone":"+1 406 896 8293",
    "sg:postcode":"59106",
    "sg:province":"MT",
    "wof:name":"Design Studio Interiors",
    "wof:placetype":"venue"
},
  "geometry": {"coordinates":[-108.642968,45.809605],"type":"Point"}
}