{
  "type": "Feature",
  "properties": {
    "iso:country":"US",
    "sg:address":"417 Mineral Ave",
    "sg:city":"Libby",
    "sg:classifiers":[
        {
            "category":"Social Services",
            "subcategory":"Job Training",
            "type":"Services"
        }
    ],
    "sg:phone":"+1 406 293 6282",
    "sg:postcode":"59923",
    "sg:province":"MT",
    "sg:tags":[
        "rehab",
        "government"
    ],
    "wof:name":"Job Service",
    "wof:placetype":"venue"
},
  "geometry": {"coordinates":[-115.551664,48.392009],"type":"Point"}
}