{
  "type": "Feature",
  "properties": {
    "addr:full":"1827 Grand Ave Billings MT 59102",
    "addr:housenumber":"1827",
    "addr:postcode":"59102",
    "addr:street":"Grand Ave",
    "iso:country":"US",
    "sg:address":"1827 Grand Ave",
    "sg:city":"Billings",
    "sg:classifiers":[
        {
            "category":"Personal",
            "subcategory":"Beauty Salon",
            "type":"Services"
        }
    ],
    "sg:phone":"+1 406 252 3666",
    "sg:postcode":"59102",
    "sg:province":"MT",
    "sg:tags":[
        "shop"
    ],
    "wof:name":"Sophisti-Cut",
    "wof:placetype":"venue"
},
  "geometry": {"coordinates":[-108.563574,45.78413],"type":"Point"}
}