{
  "type": "Feature",
  "properties": {
    "addr:full":"3218 Viola Ln Billings MT 59102",
    "addr:housenumber":"3218",
    "addr:postcode":"59102",
    "addr:street":"Viola Ln",
    "iso:country":"US",
    "sg:address":"3218 Viola Ln",
    "sg:city":"Billings",
    "sg:classifiers":[
        {
            "category":"Insurance",
            "subcategory":"Insurance Agent",
            "type":"Services"
        }
    ],
    "sg:phone":"+1 406 655 0058",
    "sg:postcode":"59102",
    "sg:province":"MT",
    "wof:name":"Mike Sandridge Insurance AAL",
    "wof:placetype":"venue"
},
  "geometry": {"coordinates":[-108.59745700000001,45.793688],"type":"Point"}
}