{
  "type": "Feature",
  "properties": {
    "iso:country":"US",
    "sg:address":"1901 S 10th St W",
    "sg:city":"Missoula",
    "sg:classifiers":[
        {
            "category":"Education",
            "subcategory":"School",
            "type":"Public Place"
        }
    ],
    "sg:phone":"+1 406 542 4020",
    "sg:postcode":"59801",
    "sg:province":"MT",
    "wof:name":"Franklin Elementary School",
    "wof:placetype":"venue"
},
  "geometry": {"coordinates":[-114.028164,46.860498],"type":"Point"}
}