{
  "type": "Feature",
  "properties": {
    "iso:country":"US",
    "sg:address":"79 Northshore Rd",
    "sg:city":"Thompson Falls",
    "sg:classifiers":[
        {
            "category":"Professional",
            "subcategory":"Accounting & Tax Preparation",
            "type":"Services"
        }
    ],
    "sg:phone":"+1 406 827 3943",
    "sg:postcode":"59873",
    "sg:province":"MT",
    "sg:tags":[
        "billing"
    ],
    "wof:name":"Big Sky Automated Medical Svcs",
    "wof:placetype":"venue"
},
  "geometry": {"coordinates":[-115.241817,47.577599],"type":"Point"}
}