{
  "type": "Feature",
  "properties": {
    "iso:country":"US",
    "sg:address":"2205 5th Ave S",
    "sg:city":"Great Falls",
    "sg:classifiers":[
        {
            "category":"Wholesale",
            "subcategory":"Machinery & Supplies",
            "type":"Manufacturing & Wholesale Goods"
        }
    ],
    "sg:phone":"+1 406 761 3921",
    "sg:postcode":"59405",
    "sg:province":"MT",
    "sg:tags":[
        "equipment",
        "establishment"
    ],
    "wof:name":"Heiman Fire Equipment",
    "wof:placetype":"venue"
},
  "geometry": {"coordinates":[-111.267825,47.499702],"type":"Point"}
}