{
  "type": "Feature",
  "properties": {
    "iso:country":"US",
    "sg:address":"152 N 9th Ave",
    "sg:city":"Forsyth",
    "sg:classifiers":[
        {
            "category":"Professional",
            "subcategory":"Lawyer & Legal Services",
            "type":"Services"
        }
    ],
    "sg:phone":"+1 406 356 9331",
    "sg:postcode":"59327",
    "sg:province":"MT",
    "sg:tags":[
        "attorney"
    ],
    "wof:name":"John S Forsythe",
    "wof:placetype":"venue"
},
  "geometry": {"coordinates":[-106.679481,46.265875],"type":"Point"}
}