{
  "type": "Feature",
  "properties": {
    "addr:full":"7256 US Hwy 3 Billings MT 59106",
    "addr:housenumber":"7256",
    "addr:street":"Us Hwy 3",
    "iso:country":"US",
    "sg:address":"7256 US Hwy 3",
    "sg:city":"Billings",
    "sg:classifiers":[
        {
            "category":"Retail",
            "subcategory":"Animal Services",
            "type":"Services"
        }
    ],
    "sg:phone":"+1 406 245 0912",
    "sg:postcode":"59106",
    "sg:province":"MT",
    "sg:tags":[
        "breeder",
        "horse"
    ],
    "wof:name":"Intermountain Equestrian Ctr",
    "wof:placetype":"venue"
},
  "geometry": {"coordinates":[-108.667997,45.899478],"type":"Point"}
}