{
  "type": "Feature",
  "properties": {
    "iso:country":"US",
    "sg:address":"2510 Spurgin Rd",
    "sg:city":"Missoula",
    "sg:classifiers":[
        {
            "category":"Shopping",
            "type":"Retail Goods"
        }
    ],
    "sg:phone":"+1 406 549 9922",
    "sg:postcode":"59804",
    "sg:province":"MT",
    "sg:tags":[
        "pet",
        "supply"
    ],
    "wof:name":"Neptunes Palace & Pets",
    "wof:placetype":"venue"
},
  "geometry": {"coordinates":[-114.040404,46.859716],"type":"Point"}
}