{
  "type": "Feature",
  "properties": {
    "iso:country":"US",
    "sg:address":"4385 Wylie Dr",
    "sg:city":"Helena",
    "sg:classifiers":[
        {
            "category":"Farming",
            "subcategory":"Livestock Farm",
            "type":"Manufacturing & Wholesale Goods"
        }
    ],
    "sg:phone":"+1 406 227 5208",
    "sg:postcode":"59602",
    "sg:province":"MT",
    "sg:tags":[
        "feedlot",
        "grain",
        "cash",
        "beef",
        "cattle"
    ],
    "wof:name":"Craig Winterburn",
    "wof:placetype":"venue"
},
  "geometry": {"coordinates":[-111.936242,46.646366],"type":"Point"}
}