{
  "type": "Feature",
  "properties": {
    "iso:country":"US",
    "sg:address":"9981 Happy Acres W",
    "sg:city":"Bozeman",
    "sg:classifiers":[
        {
            "category":"Freight",
            "type":"Transportation"
        }
    ],
    "sg:phone":"+1 406 587 3861",
    "sg:postcode":"59718",
    "sg:province":"MT",
    "sg:tags":[
        "general"
    ],
    "wof:name":"Big Johns",
    "wof:placetype":"venue"
},
  "geometry": {"coordinates":[-111.09932,45.598706],"type":"Point"}
}