{
  "type": "Feature",
  "properties": {
    "iso:country":"US",
    "sg:address":"164 S 3rd St",
    "sg:city":"Hamilton",
    "sg:classifiers":[
        {
            "category":"Retail",
            "subcategory":"Laundry & Dry Cleaning",
            "type":"Services"
        }
    ],
    "sg:phone":"+1 406 363 2811",
    "sg:postcode":"59840",
    "sg:province":"MT",
    "sg:tags":[
        "cleaners"
    ],
    "wof:name":"Bitter Root Laundry & Cleaners",
    "wof:placetype":"venue"
},
  "geometry": {"coordinates":[-114.15847100000001,46.24627],"type":"Point"}
}