{
  "type": "Feature",
  "properties": {
    "addr:full":"139 Moore Ln Billings MT 59101",
    "addr:housenumber":"139",
    "addr:postcode":"59101",
    "addr:street":"Moore Ln",
    "iso:country":"US",
    "sg:address":"139 Moore Ln",
    "sg:city":"Billings",
    "sg:classifiers":[
        {
            "category":"Autos & Motor Vehicles",
            "subcategory":"Auto Supplies",
            "type":"Retail Goods"
        }
    ],
    "sg:phone":"+1 406 245 2100",
    "sg:postcode":"59101",
    "sg:province":"MT",
    "wof:name":"Beetle Mania",
    "wof:placetype":"venue"
},
  "geometry": {"coordinates":[-108.542168,45.768779],"type":"Point"}
}