{
  "type": "Feature",
  "properties": {
    "iso:country":"US",
    "sg:address":"1005 Marshall St",
    "sg:city":"Missoula",
    "sg:classifiers":[
        {
            "category":"Social Services",
            "subcategory":"Job Training",
            "type":"Services"
        }
    ],
    "sg:phone":"+1 406 728 5484",
    "sg:postcode":"59801",
    "sg:province":"MT",
    "sg:tags":[
        "community"
    ],
    "wof:name":"Missoula Developmental Service",
    "wof:placetype":"venue"
},
  "geometry": {"coordinates":[-114.01759699999999,46.859302],"type":"Point"}
}