{
  "type": "Feature",
  "properties": {
    "iso:country":"US",
    "sg:address":"821 N 27th St",
    "sg:city":"Billings",
    "sg:classifiers":[
        {
            "category":"Professional",
            "subcategory":"Advertising",
            "type":"Services"
        }
    ],
    "sg:phone":"+1 406 245 6461",
    "sg:postcode":"59101",
    "sg:province":"MT",
    "sg:tags":[
        "mailing",
        "shipping"
    ],
    "wof:name":"Mail Drop",
    "wof:placetype":"venue"
},
  "geometry": {"coordinates":[-108.510997,45.789458],"type":"Point"}
}