{
  "type": "Feature",
  "properties": {
    "iso:country":"US",
    "sg:address":"2900 N Roberts St",
    "sg:city":"Helena",
    "sg:classifiers":[
        {
            "category":"Building & Trades",
            "subcategory":"Construction",
            "type":"Services"
        }
    ],
    "sg:phone":"+1 406 443 4353",
    "sg:postcode":"59601",
    "sg:province":"MT",
    "sg:tags":[
        "insulation",
        "contractor"
    ],
    "wof:name":"Cover-All Shelters of Mt",
    "wof:placetype":"venue"
},
  "geometry": {"coordinates":[-112.017171,46.61378],"type":"Point"}
}