{
  "type": "Feature",
  "properties": {
    "addr:full":"720 W Main St Bozeman MT 59715",
    "addr:housenumber":"720",
    "addr:postcode":"59715",
    "addr:street":"W Main St",
    "iso:country":"US",
    "sg:address":"720 W Main St",
    "sg:city":"Bozeman",
    "sg:classifiers":[
        {
            "category":"Shopping",
            "subcategory":"Florist",
            "type":"Retail Goods"
        }
    ],
    "sg:phone":"+1 406 587 7679",
    "sg:postcode":"59715",
    "sg:province":"MT",
    "wof:name":"Country Flower 2",
    "wof:placetype":"venue"
},
  "geometry": {"coordinates":[-111.047376,45.679203],"type":"Point"}
}