{
  "type": "Feature",
  "properties": {
    "iso:country":"US",
    "sg:address":"2513 Montana Ave",
    "sg:city":"Billings",
    "sg:classifiers":[
        {
            "category":"Personal",
            "subcategory":"Beauty Salon",
            "type":"Services"
        }
    ],
    "sg:phone":"+1 406 259 4004",
    "sg:postcode":"59101",
    "sg:province":"MT",
    "wof:name":"J P's Hair Studio",
    "wof:placetype":"venue"
},
  "geometry": {"coordinates":[-108.50237799999999,45.782567],"type":"Point"}
}