{
  "type": "Feature",
  "properties": {
    "iso:country":"US",
    "sg:address":"325 S C St",
    "sg:city":"Livingston",
    "sg:classifiers":[
        {
            "category":"Shopping",
            "subcategory":"Gifts & Souvenirs",
            "type":"Retail Goods"
        }
    ],
    "sg:phone":"+1 406 222 3453",
    "sg:postcode":"59047",
    "sg:province":"MT",
    "wof:name":"Boast Card Designs",
    "wof:placetype":"venue"
},
  "geometry": {"coordinates":[-110.55476299999999,45.659896],"type":"Point"}
}