{
  "type": "Feature",
  "properties": {
    "addr:full":"123 Mountain View Blvd Cut Bank MT 59427",
    "addr:housenumber":"123",
    "addr:postcode":"59427",
    "addr:street":"Mountain View Blvd Cut",
    "iso:country":"US",
    "sg:address":"123 Mountain View Blvd",
    "sg:city":"Cut Bank",
    "sg:classifiers":[
        {
            "category":"Building & Trades",
            "subcategory":"Construction",
            "type":"Services"
        }
    ],
    "sg:phone":"+1 406 873 5358",
    "sg:postcode":"59427",
    "sg:province":"MT",
    "sg:tags":[
        "hanging",
        "contractor"
    ],
    "wof:name":"Keith Larson Painting & Cnstr",
    "wof:placetype":"venue"
},
  "geometry": {"coordinates":[-112.337267,48.630594],"type":"Point"}
}