{
  "type": "Feature",
  "properties": {
    "iso:country":"US",
    "sg:address":"2202 Avalon Rd",
    "sg:city":"Billings",
    "sg:classifiers":[
        {
            "category":"Building & Trades",
            "subcategory":"Construction",
            "type":"Services"
        }
    ],
    "sg:phone":"+1 406 656 9962",
    "sg:postcode":"59102",
    "sg:province":"MT",
    "sg:tags":[
        "concrete",
        "contractor"
    ],
    "wof:name":"Valley Construction Co",
    "wof:placetype":"venue"
},
  "geometry": {"coordinates":[-108.604253,45.794841],"type":"Point"}
}