{
  "type": "Feature",
  "properties": {
    "iso:country":"US",
    "sg:address":"412 N Front St",
    "sg:city":"Townsend",
    "sg:classifiers":[
        {
            "category":"Travel",
            "subcategory":"Hotels & Motels",
            "type":"Entertainment"
        }
    ],
    "sg:phone":"+1 406 266 3491",
    "sg:postcode":"59644",
    "sg:province":"MT",
    "sg:tags":[
        "operation"
    ],
    "wof:name":"Mustang Motel",
    "wof:placetype":"venue"
},
  "geometry": {"coordinates":[-111.523759,46.322856],"type":"Point"}
}