{
  "type": "Feature",
  "properties": {
    "addr:full":"3132 Forsythia Blvd Billings MT 59102",
    "addr:housenumber":"3132",
    "addr:postcode":"59102",
    "addr:street":"Forsythia Blvd",
    "iso:country":"US",
    "sg:address":"3132 Forsythia Blvd",
    "sg:city":"Billings",
    "sg:classifiers":[
        {
            "category":"Professional",
            "subcategory":"Management & Consulting",
            "type":"Services"
        }
    ],
    "sg:phone":"+1 406 855 6425",
    "sg:postcode":"59102",
    "sg:province":"MT",
    "sg:tags":[
        "medical",
        "consultation",
        "physics"
    ],
    "wof:name":"David Wm Switzer Ms Dabr",
    "wof:placetype":"venue"
},
  "geometry": {"coordinates":[-108.591767,45.801202],"type":"Point"}
}