{
  "type": "Feature",
  "properties": {
    "addr:full":"1521 S 5th St W Missoula MT 59801",
    "addr:housenumber":"1521",
    "addr:postcode":"59801",
    "addr:street":"S 5Th St W",
    "iso:country":"US",
    "sg:address":"1521 S 5th St W",
    "sg:city":"Missoula",
    "sg:classifiers":[
        {
            "category":"Retail",
            "subcategory":"Repair Shop",
            "type":"Services"
        }
    ],
    "sg:phone":"+1 406 542 7571",
    "sg:postcode":"59801",
    "sg:province":"MT",
    "wof:name":"Bonnie & Clyde Locksmith",
    "wof:placetype":"venue"
},
  "geometry": {"coordinates":[-114.020197,46.864968],"type":"Point"}
}