{
  "type": "Feature",
  "properties": {
    "iso:country":"US",
    "sg:address":"517 W River Rd",
    "sg:city":"Hamilton",
    "sg:classifiers":[
        {
            "category":"Wholesale",
            "subcategory":"Hardware",
            "type":"Manufacturing & Wholesale Goods"
        }
    ],
    "sg:phone":"+1 406 375 2373",
    "sg:postcode":"59840",
    "sg:province":"MT",
    "sg:tags":[
        "hearth",
        "product"
    ],
    "wof:name":"Stovesforu LLC",
    "wof:placetype":"venue"
},
  "geometry": {"coordinates":[-114.165559,46.274325],"type":"Point"}
}