{
  "type": "Feature",
  "properties": {
    "addr:full":"3200 Dexter St Butte MT 59701",
    "addr:housenumber":"3200",
    "addr:postcode":"mt 59701",
    "addr:street":"Dexter St",
    "iso:country":"US",
    "sg:address":"3200 Dexter St",
    "sg:city":"Butte",
    "sg:classifiers":[
        {
            "category":"Bars & Pubs",
            "type":"Food & Drink"
        }
    ],
    "sg:phone":"+1 406 782 7539",
    "sg:postcode":"59701",
    "sg:province":"MT",
    "wof:name":"East Side Athletic Club",
    "wof:placetype":"venue"
},
  "geometry": {"coordinates":[-112.488479,45.998016],"type":"Point"}
}