{
  "type": "Feature",
  "properties": {
    "addr:full":"18 N 29th St Billings MT 59101",
    "addr:housenumber":"18",
    "addr:postcode":"59101",
    "addr:street":"N 29Th St",
    "iso:country":"US",
    "sg:address":"18 N 29th St",
    "sg:city":"Billings",
    "sg:classifiers":[
        {
            "category":"Restaurant",
            "type":"Food & Drink"
        }
    ],
    "sg:phone":"+1 406 248 5681",
    "sg:postcode":"59101",
    "sg:province":"MT",
    "wof:name":"Athenian",
    "wof:placetype":"venue"
},
  "geometry": {"coordinates":[-108.50701100000001,45.781364],"type":"Point"}
}