{
  "type": "Feature",
  "properties": {
    "iso:country":"US",
    "sg:address":"107 Vantage Ln",
    "sg:city":"Hamilton",
    "sg:classifiers":[
        {
            "category":"Retail",
            "subcategory":"Repair Shop",
            "type":"Services"
        }
    ],
    "sg:phone":"+1 406 961 3522",
    "sg:postcode":"59840",
    "sg:province":"MT",
    "sg:tags":[
        "upholsterer"
    ],
    "wof:name":"J R Furniture Upholstery",
    "wof:placetype":"venue"
},
  "geometry": {"coordinates":[-114.185433,46.312423],"type":"Point"}
}