{
  "type": "Feature",
  "properties": {
    "addr:full":"385 Mountain Springs Rd Stevensville MT 59870",
    "addr:housenumber":"385",
    "addr:postcode":"59870",
    "addr:street":"Mountain Springs Rd",
    "iso:country":"US",
    "sg:address":"385 Mountain Springs Rd",
    "sg:city":"Stevensville",
    "sg:classifiers":[
        {
            "category":"Shopping",
            "type":"Retail Goods"
        }
    ],
    "sg:phone":"+1 406 542 4114",
    "sg:postcode":"59870",
    "sg:province":"MT",
    "sg:tags":[
        "picture"
    ],
    "wof:name":"Mountain Kid Pictures",
    "wof:placetype":"venue"
},
  "geometry": {"coordinates":[-114.057233,46.570826],"type":"Point"}
}