{
  "type": "Feature",
  "properties": {
    "addr:full":"314 Cody Cir Billings MT 59105",
    "addr:housenumber":"314",
    "addr:postcode":"59105",
    "addr:street":"Cody Cir",
    "iso:country":"US",
    "sg:address":"314 Cody Cir",
    "sg:city":"Billings",
    "sg:classifiers":[
        {
            "category":"Building & Trades",
            "subcategory":"Construction",
            "type":"Services"
        }
    ],
    "sg:phone":"+1 406 245 5911",
    "sg:postcode":"59105",
    "sg:province":"MT",
    "sg:tags":[
        "steel"
    ],
    "wof:name":"Grossman Steel Detailing",
    "wof:placetype":"venue"
},
  "geometry": {"coordinates":[-108.479342,45.833784],"type":"Point"}
}