{
  "type": "Feature",
  "properties": {
    "addr:full":"825 Mount Ave Missoula MT 59801",
    "addr:housenumber":"825",
    "addr:postcode":"59801",
    "addr:street":"Mount Ave",
    "iso:country":"US",
    "sg:address":"825 Mount Ave",
    "sg:city":"Missoula",
    "sg:classifiers":[
        {
            "category":"School Buses",
            "type":"Transportation"
        }
    ],
    "sg:phone":"+1 406 549 6121",
    "sg:postcode":"59801",
    "sg:province":"MT",
    "sg:tags":[
        "charter"
    ],
    "wof:name":"Beach Transportation Corp",
    "wof:placetype":"venue"
},
  "geometry": {"coordinates":[-114.00953199999999,46.856024],"type":"Point"}
}