{
  "type": "Feature",
  "properties": {
    "iso:country":"US",
    "sg:address":"825 Mount Ave",
    "sg:city":"Missoula",
    "sg:classifiers":[
        {
            "category":"School Buses",
            "type":"Transportation"
        }
    ],
    "sg:phone":"+1 406 549 6121",
    "sg:postcode":"59801",
    "sg:province":"MT",
    "sg:tags":[
        "charter"
    ],
    "wof:name":"Beach Transportation Corp",
    "wof:placetype":"venue"
},
  "geometry": {"coordinates":[-114.009532,46.856024],"type":"Point"}
}