{
  "type": "Feature",
  "properties": {
    "iso:country":"US",
    "sg:address":"927 Tatro St",
    "sg:city":"Miles City",
    "sg:classifiers":[
        {
            "category":"Retail",
            "subcategory":"Auto Repair",
            "type":"Services"
        }
    ],
    "sg:phone":"+1 406 232 5101",
    "sg:postcode":"59301",
    "sg:province":"MT",
    "sg:tags":[
        "general"
    ],
    "wof:name":"K M Repair",
    "wof:placetype":"venue"
},
  "geometry": {"coordinates":[-105.849184,46.416719],"type":"Point"}
}