{
  "type": "Feature",
  "properties": {
    "iso:country":"US",
    "sg:address":"1227 Cherry Dr",
    "sg:city":"Bozeman",
    "sg:classifiers":[
        {
            "category":"Professional",
            "subcategory":"Art Services",
            "type":"Services"
        }
    ],
    "sg:phone":"+1 406 586 3526",
    "sg:postcode":"59715",
    "sg:province":"MT",
    "sg:tags":[
        "commercial",
        "design"
    ],
    "wof:name":"Design Solutins LLC",
    "wof:placetype":"venue"
},
  "geometry": {"coordinates":[-111.017561,45.658089],"type":"Point"}
}