{
  "type": "Feature",
  "properties": {
    "addr:full":"2017 Harrison Ave Butte MT 59701",
    "addr:housenumber":"2017",
    "addr:postcode":"mt 59701",
    "addr:street":"Harrison Ave",
    "iso:country":"US",
    "sg:address":"2017 Harrison Ave",
    "sg:city":"Butte",
    "sg:classifiers":[
        {
            "category":"Banks & Credit Unions",
            "subcategory":"Bank",
            "type":"Services"
        }
    ],
    "sg:phone":"+1 406 723 4901",
    "sg:postcode":"59701",
    "sg:province":"MT",
    "sg:tags":[
        "personal",
        "institution"
    ],
    "wof:name":"Advance Check Loans",
    "wof:placetype":"venue"
},
  "geometry": {"coordinates":[-112.512339,45.993335],"type":"Point"}
}