{
  "type": "Feature",
  "properties": {
    "iso:country":"US",
    "sg:address":"300 W Main St",
    "sg:city":"Hamilton",
    "sg:classifiers":[
        {
            "category":"Autos & Motor Vehicles",
            "subcategory":"Automobile Sales",
            "type":"Retail Goods"
        }
    ],
    "sg:phone":"+1 406 363 2011",
    "sg:postcode":"59840",
    "sg:province":"MT",
    "sg:tags":[
        "car",
        "dealer"
    ],
    "wof:name":"Bell-Mc Call Co",
    "wof:placetype":"venue"
},
  "geometry": {"coordinates":[-114.15861099999999,46.246947],"type":"Point"}
}