{
  "type": "Feature",
  "properties": {
    "iso:country":"US",
    "sg:address":"305 W Mercury St",
    "sg:city":"Butte",
    "sg:classifiers":[
        {
            "category":"Government",
            "subcategory":"Office",
            "type":"Public Place"
        }
    ],
    "sg:phone":"+1 406 497 6215",
    "sg:postcode":"59701",
    "sg:province":"MT",
    "sg:tags":[
        "educational",
        "program",
        "administrative"
    ],
    "wof:name":"School Superintendents Office",
    "wof:placetype":"venue"
},
  "geometry": {"coordinates":[-112.540534,46.011002],"type":"Point"}
}