{
  "type": "Feature",
  "properties": {
    "iso:country":"US",
    "sg:address":"150 Larch Ln",
    "sg:city":"Columbia Falls",
    "sg:classifiers":[
        {
            "category":"Building & Trades",
            "subcategory":"Landscaping Services",
            "type":"Services"
        }
    ],
    "sg:phone":"+1 406 862 2063",
    "sg:postcode":"59912",
    "sg:province":"MT",
    "sg:tags":[
        "tree",
        "trimming"
    ],
    "wof:name":"Whitefish Tree Thinning",
    "wof:placetype":"venue"
},
  "geometry": {"coordinates":[-114.284857,48.366205],"type":"Point"}
}