{
  "type": "Feature",
  "properties": {
    "addr:full":"512 S 29th St Billings MT 59101",
    "addr:housenumber":"512",
    "addr:postcode":"59101",
    "addr:street":"S 29Th St",
    "iso:country":"US",
    "sg:address":"512 S 29th St",
    "sg:city":"Billings",
    "sg:classifiers":[
        {
            "category":"Building & Trades",
            "subcategory":"Construction",
            "type":"Services"
        }
    ],
    "sg:phone":"+1 406 698 0034",
    "sg:postcode":"59101",
    "sg:province":"MT",
    "sg:tags":[
        "painter"
    ],
    "wof:name":"Sherman's Painting",
    "wof:placetype":"venue"
},
  "geometry": {"coordinates":[-108.50038000000001,45.774743],"type":"Point"}
}