{
  "type": "Feature",
  "properties": {
    "iso:country":"US",
    "sg:address":"106 E 1st Ave",
    "sg:city":"Plentywood",
    "sg:classifiers":[
        {
            "category":"Shopping",
            "subcategory":"Used Merchandise",
            "type":"Retail Goods"
        }
    ],
    "sg:phone":"+1 406 765 2002",
    "sg:postcode":"59254",
    "sg:province":"MT",
    "wof:name":"Attic Antiques",
    "wof:placetype":"venue"
},
  "geometry": {"coordinates":[-104.55892799999999,48.774288],"type":"Point"}
}