{
  "type": "Feature",
  "properties": {
    "iso:country":"US",
    "sg:address":"129 W Park St",
    "sg:city":"Butte",
    "sg:classifiers":[
        {
            "category":"Professional",
            "subcategory":"Lawyer & Legal Services",
            "type":"Services"
        }
    ],
    "sg:phone":"+1 406 782 5800",
    "sg:postcode":"59701",
    "sg:province":"MT",
    "sg:tags":[
        "attorney"
    ],
    "wof:name":"Corette Pohlman & Kebe",
    "wof:placetype":"venue"
},
  "geometry": {"coordinates":[-112.538297,46.012752],"type":"Point"}
}