{
  "type": "Feature",
  "properties": {
    "addr:full":"2076 Walking Horse Ln Big Arm MT 59910",
    "addr:housenumber":"2076",
    "addr:postcode":"59910",
    "addr:street":"Walking Horse Ln",
    "iso:country":"US",
    "sg:address":"2076 Walking Horse Ln",
    "sg:city":"Big Arm",
    "sg:classifiers":[
        {
            "category":"Wholesale",
            "subcategory":"Home Furnishings",
            "type":"Manufacturing & Wholesale Goods"
        }
    ],
    "sg:phone":"+1 406 849 5099",
    "sg:postcode":"59910",
    "sg:province":"MT",
    "wof:name":"Valknight Studio",
    "wof:placetype":"venue"
},
  "geometry": {"coordinates":[-114.322485,47.776154],"type":"Point"}
}