{
  "type": "Feature",
  "properties": {
    "iso:country":"US",
    "sg:address":"2401 12th Ave S",
    "sg:city":"Great Falls",
    "sg:classifiers":[
        {
            "category":"Travel",
            "subcategory":"Hotels & Motels",
            "type":"Entertainment"
        }
    ],
    "sg:phone":"+1 406 452 6021",
    "sg:postcode":"59405",
    "sg:province":"MT",
    "sg:tags":[
        "operation"
    ],
    "wof:name":"Brick Casino & Lounge",
    "wof:placetype":"venue"
},
  "geometry": {"coordinates":[-111.264361,47.492318],"type":"Point"}
}