{
  "type": "Feature",
  "properties": {
    "addr:full":"3400 11th Ave S Great Falls MT 59405",
    "addr:housenumber":"3400",
    "addr:postcode":"59405",
    "addr:street":"11Th Ave S Great",
    "iso:country":"US",
    "sg:address":"3400 11th Ave S",
    "sg:city":"Great Falls",
    "sg:classifiers":[
        {
            "category":"Organizations",
            "subcategory":"Religious Organization",
            "type":"Services"
        }
    ],
    "sg:phone":"+1 406 761 0464",
    "sg:postcode":"59405",
    "sg:province":"MT",
    "wof:name":"Emmanuel Bible Church",
    "wof:placetype":"venue"
},
  "geometry": {"coordinates":[-111.242751,47.492657],"type":"Point"}
}