{
  "type": "Feature",
  "properties": {
    "iso:country":"US",
    "sg:address":"2422 8th Ave N",
    "sg:city":"Great Falls",
    "sg:classifiers":[
        {
            "category":"Professional",
            "subcategory":"Management & Consulting",
            "type":"Services"
        }
    ],
    "sg:phone":"+1 406 453 6292",
    "sg:postcode":"59401",
    "sg:province":"MT",
    "sg:tags":[
        "food",
        "retail",
        "direct",
        "sales"
    ],
    "wof:name":"Darby Edelle",
    "wof:placetype":"venue"
},
  "geometry": {"coordinates":[-111.264555,47.513826],"type":"Point"}
}