{
  "type": "Feature",
  "properties": {
    "iso:country":"US",
    "sg:address":"170 River Estates Dr",
    "sg:city":"Columbia Falls",
    "sg:classifiers":[
        {
            "category":"Building & Trades",
            "subcategory":"Construction",
            "type":"Services"
        }
    ],
    "sg:phone":"+1 406 892 1915",
    "sg:postcode":"59912",
    "sg:province":"MT",
    "sg:tags":[
        "contractor"
    ],
    "wof:name":"Big Rock Masonry Inc",
    "wof:placetype":"venue"
},
  "geometry": {"coordinates":[-114.19766799999999,48.318039],"type":"Point"}
}