{
  "type": "Feature",
  "properties": {
    "iso:country":"US",
    "sg:address":"621 W Diamond St",
    "sg:city":"Butte",
    "sg:classifiers":[
        {
            "category":"Building & Trades",
            "subcategory":"Plumbing",
            "type":"Services"
        }
    ],
    "sg:phone":"+1 406 723 1136",
    "sg:postcode":"59701",
    "sg:province":"MT",
    "sg:tags":[
        "mechanical",
        "contractor"
    ],
    "wof:name":"Tri County Mechanical Elctrcl",
    "wof:placetype":"venue"
},
  "geometry": {"coordinates":[-112.544905,46.00931],"type":"Point"}
}