{
  "type": "Feature",
  "properties": {
    "iso:country":"US",
    "sg:address":"2702 Walnut St",
    "sg:city":"Butte",
    "sg:classifiers":[
        {
            "category":"Bars & Pubs",
            "type":"Food & Drink"
        }
    ],
    "sg:phone":"+1 406 723 3141",
    "sg:postcode":"59701",
    "sg:province":"MT",
    "wof:name":"Mill Bar",
    "wof:placetype":"venue"
},
  "geometry": {"coordinates":[-112.49661399999999,46.003375],"type":"Point"}
}