{
  "type": "Feature",
  "properties": {
    "addr:full":"314 1st St W Polson MT 59860",
    "addr:housenumber":"314",
    "addr:postcode":"59860",
    "addr:street":"1St St W",
    "iso:country":"US",
    "sg:address":"314 1st St W",
    "sg:city":"Polson",
    "sg:classifiers":[
        {
            "category":"Professional",
            "subcategory":"Lawyer & Legal Services",
            "type":"Services"
        }
    ],
    "sg:phone":"+1 406 883 5444",
    "sg:postcode":"59860",
    "sg:province":"MT",
    "sg:tags":[
        "attorney"
    ],
    "wof:name":"Matthew H O'Neill",
    "wof:placetype":"venue"
},
  "geometry": {"coordinates":[-114.16499,47.693241],"type":"Point"}
}