{
  "type": "Feature",
  "properties": {
    "iso:country":"US",
    "sg:address":"850 Parkway Ln",
    "sg:city":"Billings",
    "sg:classifiers":[
        {
            "category":"Building & Trades",
            "subcategory":"Plumbing",
            "type":"Services"
        }
    ],
    "sg:phone":"+1 406 252 1319",
    "sg:postcode":"59101",
    "sg:province":"MT",
    "sg:tags":[
        "sheet",
        "work",
        "metal",
        "contractor"
    ],
    "wof:name":"Ductmasters Inc",
    "wof:placetype":"venue"
},
  "geometry": {"coordinates":[-108.551055,45.754511],"type":"Point"}
}