{
  "type": "Feature",
  "properties": {
    "iso:country":"US",
    "sg:address":"3195 US Hwy 93 N",
    "sg:city":"Kalispell",
    "sg:classifiers":[
        {
            "category":"Real Estate",
            "subcategory":"Real Estate Operator",
            "type":"Services"
        }
    ],
    "sg:phone":"+1 406 755 5588",
    "sg:postcode":"59901",
    "sg:province":"MT",
    "sg:tags":[
        "farm",
        "property",
        "lessor"
    ],
    "wof:name":"Regional Enterprises Inc",
    "wof:placetype":"venue"
},
  "geometry": {"coordinates":[-114.330263,48.266299],"type":"Point"}
}