{
  "type": "Feature",
  "properties": {
    "iso:country":"US",
    "sg:address":"2705 Gilbert Ave",
    "sg:city":"Missoula",
    "sg:classifiers":[
        {
            "category":"Building & Trades",
            "subcategory":"Construction",
            "type":"Services"
        }
    ],
    "sg:phone":"+1 406 549 1080",
    "sg:postcode":"59802",
    "sg:province":"MT",
    "sg:tags":[
        "house",
        "residential"
    ],
    "wof:name":"Russell Brooks Construction",
    "wof:placetype":"venue"
},
  "geometry": {"coordinates":[-113.96746,46.890435],"type":"Point"}
}