{
  "type": "Feature",
  "properties": {
    "iso:country":"US",
    "sg:address":"111 Sourdough Ridge Rd",
    "sg:city":"Bozeman",
    "sg:classifiers":[
        {
            "category":"Real Estate",
            "subcategory":"Real Estate Agent",
            "type":"Services"
        }
    ],
    "sg:phone":"+1 406 579 0301",
    "sg:postcode":"59715",
    "sg:province":"MT",
    "wof:name":"Vincentview LLC",
    "wof:placetype":"venue"
},
  "geometry": {"coordinates":[-111.020616,45.645816],"type":"Point"}
}