{
  "type": "Feature",
  "properties": {
    "addr:full":"17 2nd St E Kalispell MT 59901",
    "addr:housenumber":"17",
    "addr:postcode":"59901",
    "addr:street":"2Nd St E",
    "iso:country":"US",
    "sg:address":"17 2nd St E",
    "sg:city":"Kalispell",
    "sg:classifiers":[
        {
            "category":"Manufacturing",
            "subcategory":"Jewelry",
            "type":"Manufacturing & Wholesale Goods"
        }
    ],
    "sg:phone":"+1 406 257 1129",
    "sg:postcode":"59901",
    "sg:province":"MT",
    "wof:name":"L F Brown Goldwork Inc",
    "wof:placetype":"venue"
},
  "geometry": {"coordinates":[-114.311759,48.19709],"type":"Point"}
}