{
  "type": "Feature",
  "properties": {
    "iso:country":"US",
    "sg:address":"723 State Hwy 200",
    "sg:city":"Noxon",
    "sg:classifiers":[
        {
            "category":"Farming",
            "subcategory":"Orchard",
            "type":"Manufacturing & Wholesale Goods"
        }
    ],
    "sg:phone":"+1 406 847 5559",
    "sg:postcode":"59853",
    "sg:province":"MT",
    "sg:tags":[
        "fruit",
        "tree"
    ],
    "wof:name":"Malcolm Cutts",
    "wof:placetype":"venue"
},
  "geometry": {"coordinates":[-115.909836,48.064271],"type":"Point"}
}