{
  "type": "Feature",
  "properties": {
    "iso:country":"US",
    "sg:address":"1603 Grand Ave",
    "sg:city":"Billings",
    "sg:classifiers":[
        {
            "category":"Shopping",
            "subcategory":"Gifts & Souvenirs",
            "type":"Retail Goods"
        }
    ],
    "sg:phone":"+1 406 245 8778",
    "sg:postcode":"59102",
    "sg:province":"MT",
    "wof:name":"B & D Enterprises Inc",
    "wof:placetype":"venue"
},
  "geometry": {"coordinates":[-108.559038,45.784216],"type":"Point"}
}