{
  "type": "Feature",
  "properties": {
    "addr:full":"1230 W Kent Ave Missoula MT 59801",
    "addr:housenumber":"1230",
    "addr:postcode":"59801",
    "addr:street":"W Kent Ave",
    "iso:country":"US",
    "sg:address":"1230 W Kent Ave",
    "sg:city":"Missoula",
    "sg:classifiers":[
        {
            "category":"Insurance",
            "subcategory":"Insurance Agent",
            "type":"Services"
        }
    ],
    "sg:phone":"+1 406 542 2101",
    "sg:postcode":"59801",
    "sg:province":"MT",
    "wof:name":"State Farm Insurance",
    "wof:placetype":"venue"
},
  "geometry": {"coordinates":[-114.01794,46.851661],"type":"Point"}
}