{
  "type": "Feature",
  "properties": {
    "addr:full":"1201 Hilmen Rd Helena MT 59602",
    "addr:housenumber":"1201",
    "addr:postcode":"59602",
    "addr:street":"Hilmen Rd",
    "iso:country":"US",
    "sg:address":"1201 Hilmen Rd",
    "sg:city":"Helena",
    "sg:classifiers":[
        {
            "category":"Building & Trades",
            "subcategory":"Plumbing",
            "type":"Services"
        }
    ],
    "sg:phone":"+1 406 458 8155",
    "sg:postcode":"59602",
    "sg:province":"MT",
    "sg:tags":[
        "contractor"
    ],
    "wof:name":"High Country Plbg & Htg LLC",
    "wof:placetype":"venue"
},
  "geometry": {"coordinates":[-112.021119,46.665991],"type":"Point"}
}