{
  "type": "Feature",
  "properties": {
    "iso:country":"US",
    "sg:address":"1818 S 5th St W",
    "sg:city":"Missoula",
    "sg:phone":"+1 406 543 7891",
    "sg:postcode":"59801",
    "sg:province":"MT",
    "sg:tags":[
        "product",
        "petroleum"
    ],
    "wof:name":"Gosyntheticcom",
    "wof:placetype":"venue"
},
  "geometry": {"coordinates":[-114.02448200000001,46.86512],"type":"Point"}
}