{
  "type": "Feature",
  "properties": {
    "iso:country":"US",
    "sg:address":"314 Bridge St",
    "sg:city":"Belt",
    "sg:classifiers":[
        {
            "category":"Government",
            "subcategory":"Post Office",
            "type":"Public Place"
        }
    ],
    "sg:phone":"+1 406 277 3349",
    "sg:postcode":"59412",
    "sg:province":"MT",
    "sg:tags":[
        "postal",
        "us"
    ],
    "wof:name":"US Post Office",
    "wof:placetype":"venue"
},
  "geometry": {"coordinates":[-110.923524,47.386313],"type":"Point"}
}