{
  "type": "Feature",
  "properties": {
    "addr:full":"2800 10th Ave N Billings MT 59101",
    "addr:housenumber":"2800",
    "addr:postcode":"59101",
    "addr:street":"10Th Ave N",
    "iso:country":"US",
    "sg:address":"2800 10th Ave N",
    "sg:city":"Billings",
    "sg:classifiers":[
        {
            "category":"Shopping",
            "subcategory":"Gifts & Souvenirs",
            "type":"Retail Goods"
        }
    ],
    "sg:phone":"+1 406 657 4028",
    "sg:postcode":"59101",
    "sg:province":"MT",
    "wof:name":"Simply Splendid A Gift Shop",
    "wof:placetype":"venue"
},
  "geometry": {"coordinates":[-108.51461399999999,45.790223],"type":"Point"}
}