{
  "type": "Feature",
  "properties": {
    "iso:country":"US",
    "sg:address":"138 1st Ave E",
    "sg:city":"Kalispell",
    "sg:classifiers":[
        {
            "category":"Personal",
            "subcategory":"Barber",
            "type":"Services"
        }
    ],
    "sg:phone":"+1 406 756 6004",
    "sg:postcode":"59901",
    "sg:province":"MT",
    "sg:tags":[
        "shop"
    ],
    "wof:name":"Whiskers Barber Shop",
    "wof:placetype":"venue"
},
  "geometry": {"coordinates":[-114.31191099999999,48.197623],"type":"Point"}
}