{
  "type": "Feature",
  "properties": {
    "iso:country":"US",
    "sg:address":"189 Kelly Rd",
    "sg:city":"Kalispell",
    "sg:classifiers":[
        {
            "category":"Retail",
            "subcategory":"Auto Repair",
            "type":"Services"
        }
    ],
    "sg:phone":"+1 406 257 9225",
    "sg:postcode":"59901",
    "sg:province":"MT",
    "sg:tags":[
        "road"
    ],
    "wof:name":"Jack's Diesel Svc Inc",
    "wof:placetype":"venue"
},
  "geometry": {"coordinates":[-114.299167,48.177631],"type":"Point"}
}