{
  "type": "Feature",
  "properties": {
    "iso:country":"US",
    "sg:address":"811 N Park Ave",
    "sg:city":"Helena",
    "sg:classifiers":[
        {
            "category":"Wholesale",
            "subcategory":"Durable Goods & Equipment",
            "type":"Manufacturing & Wholesale Goods"
        }
    ],
    "sg:phone":"+1 406 442 1159",
    "sg:postcode":"59601",
    "sg:province":"MT",
    "wof:name":"Karma S Vintage Clothing",
    "wof:placetype":"venue"
},
  "geometry": {"coordinates":[-112.03980799999999,46.596408],"type":"Point"}
}