{
  "type": "Feature",
  "properties": {
    "addr:full":"7825 US Hwy 287 Townsend MT 59644",
    "addr:housenumber":"7825",
    "addr:postcode":"59644",
    "addr:street":"Us Hwy 287",
    "iso:country":"US",
    "sg:address":"7825 US Hwy 287",
    "sg:city":"Townsend",
    "sg:classifiers":[
        {
            "category":"Retail",
            "subcategory":"Animal Services",
            "type":"Services"
        }
    ],
    "sg:phone":"+1 406 266 4212",
    "sg:postcode":"59644",
    "sg:province":"MT",
    "sg:tags":[
        "pet",
        "grooming",
        "washing"
    ],
    "wof:name":"Kris's Doggy Detailing",
    "wof:placetype":"venue"
},
  "geometry": {"coordinates":[-111.51102899999999,46.303743],"type":"Point"}
}