{
  "type": "Feature",
  "properties": {
    "iso:country":"US",
    "sg:address":"104 4th St",
    "sg:city":"Broadus",
    "sg:classifiers":[
        {
            "category":"Retail",
            "subcategory":"Auto Repair",
            "type":"Services"
        }
    ],
    "sg:phone":"+1 406 436 2936",
    "sg:postcode":"59317",
    "sg:province":"MT",
    "sg:tags":[
        "repairing",
        "automobile"
    ],
    "wof:name":"Canon Repair Shop",
    "wof:placetype":"venue"
},
  "geometry": {"coordinates":[-105.421482,45.441471],"type":"Point"}
}