{
  "type": "Feature",
  "properties": {
    "iso:country":"US",
    "sg:address":"3988 US Hwy 93",
    "sg:city":"Stevensville",
    "sg:classifiers":[
        {
            "category":"Retail",
            "subcategory":"Animal Services",
            "type":"Services"
        }
    ],
    "sg:phone":"+1 406 777 0933",
    "sg:postcode":"59870",
    "sg:province":"MT",
    "sg:tags":[
        "pet",
        "grooming",
        "washing"
    ],
    "wof:name":"Cindy's Pet Grooming",
    "wof:placetype":"venue"
},
  "geometry": {"coordinates":[-114.112254,46.526642],"type":"Point"}
}