{
  "type": "Feature",
  "properties": {
    "addr:full":"3635 10th Ave S Great Falls MT 59405",
    "addr:housenumber":"3635",
    "addr:postcode":"59405",
    "addr:street":"10Th Ave S Great",
    "iso:country":"US",
    "sg:address":"3635 10th Ave S",
    "sg:city":"Great Falls",
    "sg:classifiers":[
        {
            "category":"Autos & Motor Vehicles",
            "subcategory":"Automobile Sales",
            "type":"Retail Goods"
        }
    ],
    "sg:phone":"+1 406 452 9999",
    "sg:postcode":"59405",
    "sg:province":"MT",
    "sg:tags":[
        "used"
    ],
    "wof:name":"Guys Good Auto",
    "wof:placetype":"venue"
},
  "geometry": {"coordinates":[-111.24327599999999,47.494123],"type":"Point"}
}