{
  "type": "Feature",
  "properties": {
    "addr:full":"105 S 2nd St Hamilton MT 59840",
    "addr:housenumber":"105",
    "addr:postcode":"59840",
    "addr:street":"S 2Nd St",
    "iso:country":"US",
    "sg:address":"105 S 2nd St",
    "sg:city":"Hamilton",
    "sg:classifiers":[
        {
            "category":"Shopping",
            "subcategory":"Beauty & Cosmetics",
            "type":"Retail Goods"
        }
    ],
    "sg:phone":"+1 406 363 1466",
    "sg:postcode":"59840",
    "sg:province":"MT",
    "wof:name":"Merle Norman Cosmetics",
    "wof:placetype":"venue"
},
  "geometry": {"coordinates":[-114.15719199999999,46.246982],"type":"Point"}
}