{
  "type": "Feature",
  "properties": {
    "iso:country":"US",
    "sg:address":"2622 Arcadia Dr",
    "sg:city":"Missoula",
    "sg:classifiers":[
        {
            "category":"Wholesale",
            "subcategory":"Drugs",
            "type":"Manufacturing & Wholesale Goods"
        }
    ],
    "sg:phone":"+1 406 251 3177",
    "sg:postcode":"59803",
    "sg:province":"MT",
    "wof:name":"P & L Sales",
    "wof:placetype":"venue"
},
  "geometry": {"coordinates":[-114.044776,46.827612],"type":"Point"}
}