{
  "type": "Feature",
  "properties": {
    "addr:full":"1111 Cedar Ave SW Sidney MT 59270",
    "addr:housenumber":"1111",
    "addr:postcode":"59270",
    "addr:street":"Cedar Ave Sw",
    "iso:country":"US",
    "sg:address":"1111 Cedar Ave SW",
    "sg:city":"Sidney",
    "sg:classifiers":[
        {
            "category":"Retail",
            "subcategory":"Repair Shop",
            "type":"Services"
        }
    ],
    "sg:phone":"+1 406 488 6499",
    "sg:postcode":"59270",
    "sg:province":"MT",
    "sg:tags":[
        "related"
    ],
    "wof:name":"Quad R Repair",
    "wof:placetype":"venue"
},
  "geometry": {"coordinates":[-104.17221499999999,47.706565],"type":"Point"}
}