{
  "type": "Feature",
  "properties": {
    "iso:country":"US",
    "sg:address":"100 N 27th St",
    "sg:city":"Billings",
    "sg:classifiers":[
        {
            "category":"Professional",
            "subcategory":"Lawyer & Legal Services",
            "type":"Services"
        }
    ],
    "sg:phone":"+1 406 294 9450",
    "sg:postcode":"59101",
    "sg:province":"MT",
    "sg:tags":[
        "attorney"
    ],
    "wof:name":"David P Legare",
    "wof:placetype":"venue"
},
  "geometry": {"coordinates":[-108.505336,45.783584],"type":"Point"}
}