{
  "type": "Feature",
  "properties": {
    "iso:country":"US",
    "sg:address":"465 Bootlegger Trl",
    "sg:city":"Great Falls",
    "sg:classifiers":[
        {
            "category":"Wholesale",
            "subcategory":"Metals & Minerals",
            "type":"Manufacturing & Wholesale Goods"
        }
    ],
    "sg:phone":"+1 406 453 7299",
    "sg:postcode":"59404",
    "sg:province":"MT",
    "sg:tags":[
        "pipe",
        "supply"
    ],
    "wof:name":"Big Sky Pipe & Supply",
    "wof:placetype":"venue"
},
  "geometry": {"coordinates":[-111.27781400000001,47.6031],"type":"Point"}
}