{
  "type": "Feature",
  "properties": {
    "iso:country":"US",
    "sg:address":"2815 N Montana Ave",
    "sg:city":"Helena",
    "sg:classifiers":[
        {
            "category":"Restaurant",
            "type":"Food & Drink"
        }
    ],
    "sg:menulink":"http://www.allmenus.com/mt/helena/205130-taco-bell/menu/",
    "sg:phone":"+1 406 442 2900",
    "sg:postcode":"59601",
    "sg:province":"MT",
    "sg:tags":[
        "american",
        "mexican"
    ],
    "wof:name":"Taco Bell",
    "wof:placetype":"venue"
},
  "geometry": {"coordinates":[-112.020839,46.612671],"type":"Point"}
}