{
  "type": "Feature",
  "properties": {
    "iso:country":"US",
    "sg:address":"15 N 26th St",
    "sg:city":"Billings",
    "sg:classifiers":[
        {
            "category":"Social Services",
            "type":"Services"
        }
    ],
    "sg:phone":"+1 406 256 5929",
    "sg:postcode":"59101",
    "sg:province":"MT",
    "sg:tags":[
        "counselor",
        "marriage",
        "family"
    ],
    "wof:name":"Second Story",
    "wof:placetype":"venue"
},
  "geometry": {"coordinates":[-108.50317800000001,45.783236],"type":"Point"}
}