{
  "type": "Feature",
  "properties": {
    "iso:country":"US",
    "sg:address":"7015 Trade Center Ave",
    "sg:city":"Billings",
    "sg:classifiers":[
        {
            "category":"Wholesale",
            "subcategory":"Construction Materials",
            "type":"Manufacturing & Wholesale Goods"
        }
    ],
    "sg:phone":"+1 406 652 2730",
    "sg:postcode":"59101",
    "sg:province":"MT",
    "sg:tags":[
        "brick"
    ],
    "wof:name":"E J Bartells Co",
    "wof:placetype":"venue"
},
  "geometry": {"coordinates":[-108.59637,45.733773],"type":"Point"}
}