{
  "type": "Feature",
  "properties": {
    "iso:country":"US",
    "sg:address":"1925 Montana Ave",
    "sg:city":"Billings",
    "sg:classifiers":[
        {
            "category":"Manufacturing",
            "subcategory":"Food",
            "type":"Manufacturing & Wholesale Goods"
        }
    ],
    "sg:phone":"+1 406 254 0664",
    "sg:postcode":"59101",
    "sg:province":"MT",
    "sg:tags":[
        "cookie",
        "mfg"
    ],
    "wof:name":"Montana Moon Cookies",
    "wof:placetype":"venue"
},
  "geometry": {"coordinates":[-108.494809,45.786218],"type":"Point"}
}