{
  "type": "Feature",
  "properties": {
    "iso:country":"US",
    "sg:address":"1600 Carter Creek Rd",
    "sg:city":"Dillon",
    "sg:classifiers":[
        {
            "category":"Professional",
            "type":"Services"
        }
    ],
    "sg:phone":"+1 406 660 0046",
    "sg:postcode":"59725",
    "sg:province":"MT",
    "sg:tags":[
        "technical",
        "writing",
        "editing",
        "research"
    ],
    "wof:name":"Montana Wordcraft",
    "wof:placetype":"venue"
},
  "geometry": {"coordinates":[-112.539339,45.240168],"type":"Point"}
}