{
  "type": "Feature",
  "properties": {
    "iso:country":"US",
    "sg:address":"102 S Main St",
    "sg:city":"Darby",
    "sg:classifiers":[
        {
            "category":"Education",
            "subcategory":"Library",
            "type":"Public Place"
        }
    ],
    "sg:phone":"+1 406 821 4771",
    "sg:postcode":"59829",
    "sg:province":"MT",
    "wof:name":"Darby Public Library",
    "wof:placetype":"venue"
},
  "geometry": {"coordinates":[-114.178089,46.020783],"type":"Point"}
}