{
  "type": "Feature",
  "properties": {
    "iso:country":"US",
    "sg:address":"201 N 28th St",
    "sg:city":"Billings",
    "sg:classifiers":[
        {
            "category":"Professional",
            "type":"Services"
        }
    ],
    "sg:phone":"+1 406 896 0432",
    "sg:postcode":"59101",
    "sg:province":"MT",
    "sg:tags":[
        "establishment"
    ],
    "wof:name":"Zoot Enterprises",
    "wof:placetype":"venue"
},
  "geometry": {"coordinates":[-108.507452,45.783822],"type":"Point"}
}