{
  "type": "Feature",
  "properties": {
    "iso:country":"US",
    "sg:address":"110 6th St S",
    "sg:city":"Glasgow",
    "sg:classifiers":[
        {
            "category":"Banks & Credit Unions",
            "subcategory":"Bank",
            "type":"Services"
        }
    ],
    "sg:phone":"+1 406 228 4364",
    "sg:postcode":"59230",
    "sg:province":"MT",
    "sg:website":"www.valleybankglasgow.com",
    "wof:name":"Valley Bank",
    "wof:placetype":"venue"
},
  "geometry": {"coordinates":[-106.63766800000001,48.195319],"type":"Point"}
}