{
  "type": "Feature",
  "properties": {
    "iso:country":"US",
    "sg:address":"45 Basin Creek Rd",
    "sg:city":"Butte",
    "sg:classifiers":[
        {
            "category":"Utilities",
            "subcategory":"Electric",
            "type":"Services"
        }
    ],
    "sg:phone":"+1 406 533 0770",
    "sg:postcode":"59701",
    "sg:province":"MT",
    "sg:tags":[
        "provider"
    ],
    "wof:name":"Ppl Montana LLC",
    "wof:placetype":"venue"
},
  "geometry": {"coordinates":[-112.50898599999999,45.921923],"type":"Point"}
}