{
  "type": "Feature",
  "properties": {
    "iso:country":"US",
    "sg:address":"538 Golf Course Rd",
    "sg:city":"Hamilton",
    "sg:classifiers":[
        {
            "category":"Utilities",
            "subcategory":"Telephone",
            "type":"Services"
        }
    ],
    "sg:phone":"+1 406 363 1625",
    "sg:postcode":"59840",
    "sg:province":"MT",
    "sg:tags":[
        "communications"
    ],
    "wof:name":"Nortel",
    "wof:placetype":"venue"
},
  "geometry": {"coordinates":[-114.12972499999999,46.23683],"type":"Point"}
}