{
  "type": "Feature",
  "properties": {
    "iso:country":"US",
    "sg:address":"2800 4th Ave N",
    "sg:city":"Billings",
    "sg:classifiers":[
        {
            "category":"Social Services",
            "subcategory":"Child Care",
            "type":"Services"
        }
    ],
    "sg:phone":"+1 406 245 1311",
    "sg:postcode":"59101",
    "sg:province":"MT",
    "sg:tags":[
        "day"
    ],
    "wof:name":"Littlseeds Early Childhood Ctr",
    "wof:placetype":"venue"
},
  "geometry": {"coordinates":[-108.509485,45.784022],"type":"Point"}
}