{
  "type": "Feature",
  "properties": {
    "iso:country":"US",
    "sg:address":"501 S Yellowstone St",
    "sg:city":"Livingston",
    "sg:classifiers":[
        {
            "category":"Real Estate",
            "subcategory":"Surveying",
            "type":"Services"
        }
    ],
    "sg:phone":"+1 406 222 1780",
    "sg:postcode":"59047",
    "sg:province":"MT",
    "wof:name":"Hallin & Associates",
    "wof:placetype":"venue"
},
  "geometry": {"coordinates":[-110.558989,45.655575],"type":"Point"}
}