{
  "type": "Feature",
  "properties": {
    "iso:country":"US",
    "sg:address":"1030 Jensen Rd",
    "sg:city":"Columbia Falls",
    "sg:classifiers":[
        {
            "category":"Retail",
            "subcategory":"Auto Repair",
            "type":"Services"
        }
    ],
    "sg:phone":"+1 406 892 5423",
    "sg:postcode":"59912",
    "sg:province":"MT",
    "sg:tags":[
        "automotive",
        "material"
    ],
    "wof:name":"Canyon Towing",
    "wof:placetype":"venue"
},
  "geometry": {"coordinates":[-114.143001,48.359072],"type":"Point"}
}