{
  "type": "Feature",
  "properties": {
    "iso:country":"US",
    "sg:address":"1 Valley View Dr",
    "sg:city":"Clancy",
    "sg:classifiers":[
        {
            "category":"Real Estate",
            "subcategory":"Real Estate Services",
            "type":"Services"
        }
    ],
    "sg:phone":"+1 406 442 9920",
    "sg:postcode":"59634",
    "sg:province":"MT",
    "sg:tags":[
        "abstract",
        "title"
    ],
    "wof:name":"Stewart Title Guaranty Company",
    "wof:placetype":"venue"
},
  "geometry": {"coordinates":[-111.94845100000001,46.537013],"type":"Point"}
}