{
  "type": "Feature",
  "properties": {
    "iso:country":"US",
    "sg:address":"1208 4th Ave NW",
    "sg:city":"Great Falls",
    "sg:classifiers":[
        {
            "category":"Building & Trades",
            "subcategory":"Electrical",
            "type":"Services"
        }
    ],
    "sg:phone":"+1 406 727 7275",
    "sg:postcode":"59404",
    "sg:province":"MT",
    "sg:tags":[
        "electric",
        "contractor"
    ],
    "wof:name":"Martins Electric",
    "wof:placetype":"venue"
},
  "geometry": {"coordinates":[-111.33411,47.51158],"type":"Point"}
}