{
  "type": "Feature",
  "properties": {
    "iso:country":"US",
    "sg:address":"700 Pine St",
    "sg:city":"Ovando",
    "sg:classifiers":[
        {
            "category":"Government",
            "subcategory":"Fire Station",
            "type":"Public Place"
        }
    ],
    "sg:phone":"+1 406 000 1111",
    "sg:postcode":"59854",
    "sg:province":"MT",
    "sg:tags":[
        "department"
    ],
    "wof:name":"Ovando Fire Dept",
    "wof:placetype":"venue"
},
  "geometry": {"coordinates":[-113.13099099999999,47.019952],"type":"Point"}
}