{
  "type": "Feature",
  "properties": {
    "iso:country":"US",
    "sg:address":"121 Weast Ave",
    "sg:city":"Absarokee",
    "sg:classifiers":[
        {
            "category":"Real Estate",
            "subcategory":"Real Estate Operator",
            "type":"Services"
        }
    ],
    "sg:phone":"+1 406 328 4615",
    "sg:postcode":"59001",
    "sg:province":"MT",
    "sg:tags":[
        "building",
        "apartment"
    ],
    "wof:name":"Homestead Lodge Apartments",
    "wof:placetype":"venue"
},
  "geometry": {"coordinates":[-109.4418,45.517547],"type":"Point"}
}