{
  "type": "Feature",
  "properties": {
    "iso:country":"US",
    "sg:address":"1520 W Beall St",
    "sg:city":"Bozeman",
    "sg:classifiers":[
        {
            "category":"Personal",
            "subcategory":"Shoe Repair & Shine",
            "type":"Services"
        }
    ],
    "sg:phone":"+1 406 587 0442",
    "sg:postcode":"59715",
    "sg:province":"MT",
    "sg:tags":[
        "boot",
        "shoes"
    ],
    "wof:name":"Ardesson Boots & Shoes",
    "wof:placetype":"venue"
},
  "geometry": {"coordinates":[-111.058118,45.682069],"type":"Point"}
}