{
  "type": "Feature",
  "properties": {
    "iso:country":"US",
    "sg:address":"1 E Beall St",
    "sg:city":"Ramsay",
    "sg:classifiers":[
        {
            "category":"Government",
            "subcategory":"Post Office",
            "type":"Public Place"
        }
    ],
    "sg:phone":"+1 406 782 1895",
    "sg:postcode":"59715",
    "sg:province":"MT",
    "sg:tags":[
        "postal",
        "us"
    ],
    "wof:name":"US Post Office",
    "wof:placetype":"venue"
},
  "geometry": {"coordinates":[-111.03724800000001,45.681993],"type":"Point"}
}