{
  "type": "Feature",
  "properties": {
    "iso:country":"US",
    "sg:address":"386 Swamp Creek Rd",
    "sg:city":"Trout Creek",
    "sg:classifiers":[
        {
            "category":"Manufacturing",
            "subcategory":"Building Materials",
            "type":"Manufacturing & Wholesale Goods"
        }
    ],
    "sg:phone":"+1 406 827 8667",
    "sg:postcode":"59874",
    "sg:province":"MT",
    "sg:tags":[
        "custom",
        "cabinet"
    ],
    "wof:name":"Cabinet Mountain Woodworks",
    "wof:placetype":"venue"
},
  "geometry": {"coordinates":[-115.63156600000001,47.875027],"type":"Point"}
}