{
  "type": "Feature",
  "properties": {
    "iso:country":"US",
    "sg:address":"109 W Main St",
    "sg:city":"Ennis",
    "sg:classifiers":[
        {
            "category":"Recreation",
            "type":"Entertainment"
        }
    ],
    "sg:phone":"+1 406 682 4293",
    "sg:postcode":"59729",
    "sg:province":"MT",
    "sg:tags":[
        "party",
        "fishing"
    ],
    "sg:website":"www.mrfc.com",
    "wof:name":"Madison River Fishing Co",
    "wof:placetype":"venue"
},
  "geometry": {"coordinates":[-111.730981,45.348677],"type":"Point"}
}