{
  "type": "Feature",
  "properties": {
    "addr:full":"367 N Juniper Bay Rd Somers MT 59932",
    "addr:housenumber":"367",
    "addr:postcode":"59932",
    "addr:street":"N Juniper Bay Rd",
    "iso:country":"US",
    "sg:address":"367 N Juniper Bay Rd",
    "sg:city":"Somers",
    "sg:classifiers":[
        {
            "category":"Shopping",
            "subcategory":"Books",
            "type":"Retail Goods"
        }
    ],
    "sg:phone":"+1 406 857 3600",
    "sg:postcode":"59932",
    "sg:province":"MT",
    "wof:name":"Kids Keepsakes",
    "wof:placetype":"venue"
},
  "geometry": {"coordinates":[-114.238828,48.064339],"type":"Point"}
}