{
  "type": "Feature",
  "properties": {
    "iso:country":"US",
    "sg:address":"6092 Moiese Valley Rd",
    "sg:city":"Charlo",
    "sg:classifiers":[
        {
            "category":"Farming",
            "subcategory":"Farm",
            "type":"Manufacturing & Wholesale Goods"
        }
    ],
    "sg:phone":"+1 406 644 2852",
    "sg:postcode":"59824",
    "sg:province":"MT",
    "sg:tags":[
        "general"
    ],
    "wof:name":"Dan Hartung",
    "wof:placetype":"venue"
},
  "geometry": {"coordinates":[-114.3096,47.43979],"type":"Point"}
}