{
  "type": "Feature",
  "properties": {
    "iso:country":"US",
    "sg:address":"4955 Arnica",
    "sg:city":"Missoula",
    "sg:classifiers":[
        {
            "category":"Retail",
            "subcategory":"Repair Shop",
            "type":"Services"
        }
    ],
    "sg:phone":"+1 406 880 0504",
    "sg:postcode":"59803",
    "sg:province":"MT",
    "wof:name":"Able Iron Works",
    "wof:placetype":"venue"
},
  "geometry": {"coordinates":[-113.970825,46.826864],"type":"Point"}
}