{
  "type": "Feature",
  "properties": {
    "iso:country":"US",
    "sg:address":"240 W 4th Ave N",
    "sg:city":"Columbus",
    "sg:classifiers":[
        {
            "category":"Organizations",
            "subcategory":"Religious Organization",
            "type":"Services"
        }
    ],
    "sg:phone":"+1 406 322 5541",
    "sg:postcode":"59019",
    "sg:province":"MT",
    "sg:tags":[
        "church"
    ],
    "wof:name":"St Mary's Catholic Church",
    "wof:placetype":"venue"
},
  "geometry": {"coordinates":[-109.262163,45.643397],"type":"Point"}
}