{
  "type": "Feature",
  "properties": {
    "iso:country":"US",
    "sg:address":"202 Main St",
    "sg:city":"Wolf Point",
    "sg:classifiers":[
        {
            "category":"Shopping",
            "subcategory":"Department Store",
            "type":"Retail Goods"
        }
    ],
    "sg:phone":"+1 406 653 1450",
    "sg:postcode":"59201",
    "sg:province":"MT",
    "wof:name":"Bryan's",
    "wof:placetype":"venue"
},
  "geometry": {"coordinates":[-105.63883,48.090719],"type":"Point"}
}