{
  "type": "Feature",
  "properties": {
    "iso:country":"US",
    "sg:address":"3906 Big Mountain Rd",
    "sg:city":"Whitefish",
    "sg:classifiers":[
        {
            "category":"Restaurant",
            "type":"Food & Drink"
        }
    ],
    "sg:phone":"+1 406 862 3777",
    "sg:postcode":"59937",
    "sg:province":"MT",
    "sg:tags":[
        "eating"
    ],
    "wof:name":"Big Drift Coffeehouse",
    "wof:placetype":"venue"
},
  "geometry": {"coordinates":[-114.355958,48.483895],"type":"Point"}
}