{
  "type": "Feature",
  "properties": {
    "addr:full":"169 Dry Gulch Rd Stevensville MT 59870",
    "addr:housenumber":"169",
    "addr:postcode":"59870",
    "addr:street":"Dry Gulch Rd",
    "iso:country":"US",
    "sg:address":"169 Dry Gulch Rd",
    "sg:city":"Stevensville",
    "sg:classifiers":[
        {
            "category":"Professional",
            "subcategory":"Advertising",
            "type":"Services"
        }
    ],
    "sg:phone":"+1 406 777 2088",
    "sg:postcode":"59870",
    "sg:province":"MT",
    "sg:tags":[
        "mail",
        "direct"
    ],
    "wof:name":"Mailing Station Inc",
    "wof:placetype":"venue"
},
  "geometry": {"coordinates":[-114.037982,46.588478],"type":"Point"}
}