{
  "type": "Feature",
  "properties": {
    "iso:country":"US",
    "sg:address":"303 N Roberts St",
    "sg:city":"Helena",
    "sg:classifiers":[
        {
            "category":"Professional",
            "subcategory":"Computer Services",
            "type":"Services"
        }
    ],
    "sg:phone":"+1 406 444 2424",
    "sg:postcode":"59601",
    "sg:province":"MT",
    "sg:tags":[
        "processing",
        "datum"
    ],
    "wof:name":"Administration Montana Dept",
    "wof:placetype":"venue"
},
  "geometry": {"coordinates":[-112.016503,46.587738],"type":"Point"}
}