{
  "type": "Feature",
  "properties": {
    "addr:full":"101 Central Ave N Dutton MT 59433",
    "addr:housenumber":"101",
    "addr:postcode":"59433",
    "addr:street":"Central Ave N",
    "iso:country":"US",
    "sg:address":"101 Central Ave N",
    "sg:city":"Dutton",
    "sg:classifiers":[
        {
            "category":"Wholesale",
            "subcategory":"Sporting Goods",
            "type":"Manufacturing & Wholesale Goods"
        }
    ],
    "sg:phone":"+1 406 476 3283",
    "sg:postcode":"59433",
    "sg:province":"MT",
    "wof:name":"Montana Survival Co",
    "wof:placetype":"venue"
},
  "geometry": {"coordinates":[-111.715377,47.84936],"type":"Point"}
}