{
  "type": "Feature",
  "properties": {
    "iso:country":"US",
    "sg:address":"38 Treasure State Dr",
    "sg:city":"Great Falls",
    "sg:classifiers":[
        {
            "category":"Professional",
            "subcategory":"Business Services",
            "type":"Services"
        }
    ],
    "sg:phone":"+1 406 452 8724",
    "sg:postcode":"59404",
    "sg:province":"MT",
    "wof:name":"Koslosky Enterprises Inc",
    "wof:placetype":"venue"
},
  "geometry": {"coordinates":[-111.330962,47.488611],"type":"Point"}
}