{
  "type": "Feature",
  "properties": {
    "addr:full":"810 Patton Ln Whitefish MT 59937",
    "addr:housenumber":"810",
    "addr:postcode":"59937",
    "addr:street":"Patton Ln",
    "iso:country":"US",
    "sg:address":"810 Patton Ln",
    "sg:city":"Whitefish",
    "sg:classifiers":[
        {
            "category":"Building & Trades",
            "subcategory":"Construction",
            "type":"Services"
        }
    ],
    "sg:phone":"+1 406 862 7288",
    "sg:postcode":"59937",
    "sg:province":"MT",
    "sg:tags":[
        "excavating",
        "contractor"
    ],
    "wof:name":"Langton Excavation",
    "wof:placetype":"venue"
},
  "geometry": {"coordinates":[-114.369799,48.416246],"type":"Point"}
}