{
  "type": "Feature",
  "properties": {
    "addr:full":"399 Jensen Rd Columbia Falls MT 59912",
    "addr:housenumber":"399",
    "addr:postcode":"59912",
    "addr:street":"Jensen Rd",
    "iso:country":"US",
    "sg:address":"399 Jensen Rd",
    "sg:city":"Columbia Falls",
    "sg:classifiers":[
        {
            "category":"Freight",
            "type":"Transportation"
        }
    ],
    "sg:phone":"+1 406 756 6969",
    "sg:postcode":"59912",
    "sg:province":"MT",
    "sg:tags":[
        "storage",
        "general"
    ],
    "wof:name":"Grizzly Mini Storage Inc",
    "wof:placetype":"venue"
},
  "geometry": {"coordinates":[-114.146505,48.334486],"type":"Point"}
}