{
  "type": "Feature",
  "properties": {
    "iso:country":"US",
    "sg:address":"3120 Drury Ln",
    "sg:city":"Billings",
    "sg:classifiers":[
        {
            "category":"Retail",
            "subcategory":"Repair Shop",
            "type":"Services"
        },
        {
            "category":"Building & Trades",
            "subcategory":"Construction",
            "type":"Services"
        }
    ],
    "sg:phone":"+1 406 373 5707",
    "sg:postcode":"59105",
    "sg:province":"MT",
    "sg:tags":[
        "well",
        "drilling"
    ],
    "wof:name":"Mayes Drilling Inc",
    "wof:placetype":"venue"
},
  "geometry": {"coordinates":[-108.406172,45.878344],"type":"Point"}
}