{
  "type": "Feature",
  "properties": {
    "iso:country":"US",
    "sg:address":"3420 15th Ave S",
    "sg:city":"Great Falls",
    "sg:classifiers":[
        {
            "category":"Education",
            "subcategory":"School",
            "type":"Public Place"
        }
    ],
    "sg:phone":"+1 406 268 7305",
    "sg:postcode":"59405",
    "sg:province":"MT",
    "sg:tags":[
        "elementary"
    ],
    "wof:name":"Mountain View Elem School",
    "wof:placetype":"venue"
},
  "geometry": {"coordinates":[-111.243526,47.487993],"type":"Point"}
}