{
  "type": "Feature",
  "properties": {
    "iso:country":"US",
    "sg:address":"6303 Hillview Way",
    "sg:city":"Missoula",
    "sg:classifiers":[
        {
            "category":"Professional",
            "subcategory":"Business Services",
            "type":"Services"
        }
    ],
    "sg:phone":"+1 406 251 3953",
    "sg:postcode":"59803",
    "sg:province":"MT",
    "wof:name":"Pas Enterprises LLC",
    "wof:placetype":"venue"
},
  "geometry": {"coordinates":[-114.026259,46.81214],"type":"Point"}
}