{
  "type": "Feature",
  "properties": {
    "iso:country":"US",
    "sg:address":"105 Rocking Bear Cir",
    "sg:city":"Bozeman",
    "sg:classifiers":[
        {
            "category":"Professional",
            "subcategory":"Accounting & Tax Preparation",
            "type":"Services"
        }
    ],
    "sg:phone":"+1 406 582 8716",
    "sg:postcode":"59715",
    "sg:province":"MT",
    "wof:name":"Ellen H Alborn CPA",
    "wof:placetype":"venue"
},
  "geometry": {"coordinates":[-111.036073,45.639579],"type":"Point"}
}