{
  "type": "Feature",
  "properties": {
    "addr:full":"1093 US Hwy 12 E Townsend MT 59644",
    "addr:housenumber":"1093",
    "addr:postcode":"59644",
    "addr:street":"Us Hwy 12 E Townsend",
    "iso:country":"US",
    "sg:address":"1093 US Hwy 12 E",
    "sg:city":"Townsend",
    "sg:classifiers":[
        {
            "category":"Manufacturing",
            "subcategory":"Toys & Sporting Goods",
            "type":"Manufacturing & Wholesale Goods"
        }
    ],
    "sg:phone":"+1 406 266 5516",
    "sg:postcode":"59644",
    "sg:province":"MT",
    "sg:tags":[
        "mfg",
        "archery",
        "accessory",
        "sights",
        "bow"
    ],
    "wof:name":"Sight Master Inc",
    "wof:placetype":"venue"
},
  "geometry": {"coordinates":[-111.293548,46.324709],"type":"Point"}
}