{
  "type": "Feature",
  "properties": {
    "iso:country":"US",
    "sg:address":"2526 Montana Ave",
    "sg:city":"Billings",
    "sg:classifiers":[
        {
            "category":"Bars & Pubs",
            "type":"Food & Drink"
        }
    ],
    "sg:phone":"+1 406 867 2337",
    "sg:postcode":"59101",
    "sg:province":"MT",
    "wof:name":"Railyard Ale House & Casino",
    "wof:placetype":"venue"
},
  "geometry": {"coordinates":[-108.502093,45.782529],"type":"Point"}
}