{
  "type": "Feature",
  "properties": {
    "addr:full":"703 W Mendenhall St Bozeman MT 59715",
    "addr:housenumber":"703",
    "addr:postcode":"59715",
    "addr:street":"W Mendenhall St",
    "iso:country":"US",
    "sg:address":"703 W Mendenhall St",
    "sg:city":"Bozeman",
    "sg:classifiers":[
        {
            "category":"Shopping",
            "subcategory":"Tobacco",
            "type":"Retail Goods"
        }
    ],
    "sg:phone":"+1 406 587 8722",
    "sg:postcode":"59715",
    "sg:province":"MT",
    "sg:tags":[
        "product"
    ],
    "wof:name":"The Cigarette Store Corp",
    "wof:placetype":"venue"
},
  "geometry": {"coordinates":[-111.046318,45.680383],"type":"Point"}
}