{
  "type": "Feature",
  "properties": {
    "iso:country":"US",
    "sg:address":"405 Main St",
    "sg:city":"Billings",
    "sg:classifiers":[
        {
            "category":"Food & Beverages",
            "subcategory":"Specialty",
            "type":"Retail Goods"
        }
    ],
    "sg:phone":"+1 406 896 8845",
    "sg:postcode":"59105",
    "sg:province":"MT",
    "sg:tags":[
        "tea",
        "coffee"
    ],
    "wof:name":"City Brew",
    "wof:placetype":"venue"
},
  "geometry": {"coordinates":[-108.474783,45.806246],"type":"Point"}
}