{
  "type": "Feature",
  "properties": {
    "addr:full":"7 S 8th St Miles City MT 59301",
    "addr:housenumber":"7",
    "addr:postcode":"59301",
    "addr:street":"S 8Th St",
    "iso:country":"US",
    "sg:address":"7 S 8th St",
    "sg:city":"Miles City",
    "sg:classifiers":[
        {
            "category":"Wholesale",
            "subcategory":"Chemicals & Plastics",
            "type":"Manufacturing & Wholesale Goods"
        }
    ],
    "sg:phone":"+1 406 232 6561",
    "sg:postcode":"59301",
    "sg:province":"MT",
    "sg:tags":[
        "oxygen"
    ],
    "wof:name":"Lincare",
    "wof:placetype":"venue"
},
  "geometry": {"coordinates":[-105.848128,46.40675],"type":"Point"}
}