{
  "type": "Feature",
  "properties": {
    "iso:country":"US",
    "sg:address":"195 Copper Ct",
    "sg:city":"Hamilton",
    "sg:classifiers":[
        {
            "category":"Building & Trades",
            "subcategory":"Construction",
            "type":"Services"
        }
    ],
    "sg:phone":"+1 406 363 3502",
    "sg:postcode":"59840",
    "sg:province":"MT",
    "sg:tags":[
        "project",
        "house"
    ],
    "wof:name":"Bauder Construction Company",
    "wof:placetype":"venue"
},
  "geometry": {"coordinates":[-114.130567,46.234808],"type":"Point"}
}