{
  "type": "Feature",
  "properties": {
    "iso:country":"US",
    "sg:address":"147 Vida East Rd",
    "sg:city":"Vida",
    "sg:phone":"+1 406 525 3243",
    "sg:postcode":"59274",
    "sg:province":"MT",
    "sg:tags":[
        "farm",
        "wheat"
    ],
    "wof:name":"Vita Farm",
    "wof:placetype":"venue"
},
  "geometry": {"coordinates":[-105.461326,47.833602],"type":"Point"}
}