{
  "type": "Feature",
  "properties": {
    "iso:country":"US",
    "sg:address":"3011 38th St W",
    "sg:city":"Billings",
    "sg:classifiers":[
        {
            "category":"Autos & Motor Vehicles",
            "subcategory":"Fuel & Gas Station",
            "type":"Retail Goods"
        }
    ],
    "sg:phone":"+1 406 656 9413",
    "sg:postcode":"59102",
    "sg:province":"MT",
    "sg:tags":[
        "station",
        "gasoline"
    ],
    "wof:name":"Canyon Creek Stn Trdg Cmpanies",
    "wof:placetype":"venue"
},
  "geometry": {"coordinates":[-108.611389,45.79932],"type":"Point"}
}