{
  "type": "Feature",
  "properties": {
    "iso:country":"US",
    "sg:address":"3716 Spotted Jack Loop S",
    "sg:city":"Billings",
    "sg:classifiers":[
        {
            "category":"Building & Trades",
            "subcategory":"Construction",
            "type":"Services"
        }
    ],
    "sg:phone":"+1 406 256 5470",
    "sg:postcode":"59101",
    "sg:province":"MT",
    "sg:tags":[
        "contractor"
    ],
    "wof:name":"Fredrickson Wall Systems Inc",
    "wof:placetype":"venue"
},
  "geometry": {"coordinates":[-108.390817,45.816152],"type":"Point"}
}