{
  "type": "Feature",
  "properties": {
    "iso:country":"US",
    "sg:address":"4632 Richlie St",
    "sg:city":"Missoula",
    "sg:classifiers":[
        {
            "category":"Professional",
            "type":"Services"
        }
    ],
    "sg:phone":"+1 406 549 0609",
    "sg:postcode":"59808",
    "sg:province":"MT",
    "wof:name":"Crazy Boy Inc",
    "wof:placetype":"venue"
},
  "geometry": {"coordinates":[-114.044697,46.909666],"type":"Point"}
}