{
  "type": "Feature",
  "properties": {
    "addr:full":"2309 9th Ave S Great Falls MT 59405",
    "addr:housenumber":"2309",
    "addr:postcode":"59405",
    "addr:street":"9Th Ave S Great",
    "iso:country":"US",
    "sg:address":"2309 9th Ave S",
    "sg:city":"Great Falls",
    "sg:classifiers":[
        {
            "category":"Social Services",
            "subcategory":"Child Care",
            "type":"Services"
        }
    ],
    "sg:phone":"+1 406 453 0859",
    "sg:postcode":"59405",
    "sg:province":"MT",
    "sg:tags":[
        "day"
    ],
    "wof:name":"Carol Suek",
    "wof:placetype":"venue"
},
  "geometry": {"coordinates":[-111.26444499999999,47.495298],"type":"Point"}
}