{
  "type": "Feature",
  "properties": {
    "iso:country":"US",
    "sg:address":"287 Lincoln Ln",
    "sg:city":"Hamilton",
    "sg:classifiers":[
        {
            "category":"Professional",
            "subcategory":"Accounting & Tax Preparation",
            "type":"Services"
        }
    ],
    "sg:phone":"+1 406 375 1769",
    "sg:postcode":"59840",
    "sg:province":"MT",
    "wof:name":"Freelance Business Solutions I",
    "wof:placetype":"venue"
},
  "geometry": {"coordinates":[-114.140546,46.225903],"type":"Point"}
}