{
  "type": "Feature",
  "properties": {
    "addr:full":"350 S Montana St Butte MT 59701",
    "addr:housenumber":"350",
    "addr:postcode":"mt 59701",
    "addr:street":"S Montana St",
    "iso:country":"US",
    "sg:address":"350 S Montana St",
    "sg:city":"Butte",
    "sg:classifiers":[
        {
            "category":"Restaurant",
            "type":"Food & Drink"
        }
    ],
    "sg:menulink":"http://www.allmenus.com/mt/butte/129733-subway/menu/",
    "sg:phone":"+1 406 723 7035",
    "sg:postcode":"59701",
    "sg:province":"MT",
    "sg:tags":[
        "american",
        "sandwich"
    ],
    "wof:name":"Subway",
    "wof:placetype":"venue"
},
  "geometry": {"coordinates":[-112.53922900000001,46.009434],"type":"Point"}
}