{
  "type": "Feature",
  "properties": {
    "iso:country":"US",
    "sg:address":"483 Airport Rd",
    "sg:city":"Stevensville",
    "sg:classifiers":[
        {
            "category":"Manufacturing",
            "subcategory":"Metals",
            "type":"Manufacturing & Wholesale Goods"
        }
    ],
    "sg:phone":"+1 406 777 7335",
    "sg:postcode":"59870",
    "sg:province":"MT",
    "sg:tags":[
        "engineering",
        "stampings",
        "mfg"
    ],
    "wof:name":"Zei",
    "wof:placetype":"venue"
},
  "geometry": {"coordinates":[-114.03642499999999,46.533628],"type":"Point"}
}