{
  "type": "Feature",
  "properties": {
    "addr:full":"1550 S Central Ave Sidney MT 59270",
    "addr:housenumber":"1550",
    "addr:postcode":"59270",
    "addr:street":"S Central Ave",
    "iso:country":"US",
    "sg:address":"1550 S Central Ave",
    "sg:city":"Sidney",
    "sg:classifiers":[
        {
            "category":"Restaurant",
            "type":"Food & Drink"
        }
    ],
    "sg:menulink":"http://www.allmenus.com/mt/sidney/211960-mcdonalds/menu/",
    "sg:phone":"+1 406 482 1983",
    "sg:postcode":"59270",
    "sg:province":"MT",
    "sg:tags":[
        "burger",
        "american"
    ],
    "wof:name":"McDonald's",
    "wof:placetype":"venue"
},
  "geometry": {"coordinates":[-104.167739,47.70037],"type":"Point"}
}