{
  "type": "Feature",
  "properties": {
    "iso:country":"US",
    "sg:address":"420 1st St W",
    "sg:city":"Melstone",
    "sg:classifiers":[
        {
            "category":"Organizations",
            "subcategory":"Religious Organization",
            "type":"Services"
        }
    ],
    "sg:phone":"+1 406 358 2429",
    "sg:postcode":"59054",
    "sg:province":"MT",
    "sg:tags":[
        "church"
    ],
    "wof:name":"Melstone Bible Church",
    "wof:placetype":"venue"
},
  "geometry": {"coordinates":[-107.869192,46.599295],"type":"Point"}
}