{
  "type": "Feature",
  "properties": {
    "addr:full":"411 N Wallace Ave Bozeman MT 59715",
    "addr:housenumber":"411",
    "addr:postcode":"59715",
    "addr:street":"N Wallace Ave",
    "iso:country":"US",
    "sg:address":"411 N Wallace Ave",
    "sg:city":"Bozeman",
    "sg:classifiers":[
        {
            "category":"Retail",
            "subcategory":"Auto Repair",
            "type":"Services"
        }
    ],
    "sg:phone":"+1 406 587 4627",
    "sg:postcode":"59715",
    "sg:province":"MT",
    "sg:tags":[
        "general"
    ],
    "wof:name":"Dels Autobody Repair",
    "wof:placetype":"venue"
},
  "geometry": {"coordinates":[-111.028477,45.68517],"type":"Point"}
}