{
  "type": "Feature",
  "properties": {
    "iso:country":"US",
    "sg:address":"521 S 12th Ave",
    "sg:city":"Bozeman",
    "sg:classifiers":[
        {
            "category":"Professional",
            "type":"Services"
        }
    ],
    "sg:phone":"+1 406 587 1881",
    "sg:postcode":"59715",
    "sg:province":"MT",
    "wof:name":"Jsp LLC",
    "wof:placetype":"venue"
},
  "geometry": {"coordinates":[-111.053348,45.674106],"type":"Point"}
}