{
  "type": "Feature",
  "properties": {
    "iso:country":"US",
    "sg:address":"203 Main St",
    "sg:city":"Three Forks",
    "sg:classifiers":[
        {
            "category":"Manufacturing",
            "subcategory":"Printing",
            "type":"Manufacturing & Wholesale Goods"
        }
    ],
    "sg:phone":"+1 406 285 3830",
    "sg:postcode":"59752",
    "sg:province":"MT",
    "sg:tags":[
        "newspaper"
    ],
    "wof:name":"Lewis & Clark Journal",
    "wof:placetype":"venue"
},
  "geometry": {"coordinates":[-111.552294,45.893049],"type":"Point"}
}