{
  "type": "Feature",
  "properties": {
    "iso:country":"US",
    "sg:address":"306 Jefferson School Rd",
    "sg:city":"Glendive",
    "sg:classifiers":[
        {
            "category":"Farming",
            "subcategory":"Livestock Farm",
            "type":"Manufacturing & Wholesale Goods"
        }
    ],
    "sg:phone":"+1 406 365 5002",
    "sg:postcode":"59330",
    "sg:province":"MT",
    "sg:tags":[
        "beef",
        "feedlot",
        "cattle"
    ],
    "wof:name":"Ty Ripley",
    "wof:placetype":"venue"
},
  "geometry": {"coordinates":[-104.746867,47.118861],"type":"Point"}
}