{
  "type": "Feature",
  "properties": {
    "addr:full":"1215 Cordova St Billings MT 59101",
    "addr:housenumber":"1215",
    "addr:postcode":"59101",
    "addr:street":"Cordova St",
    "iso:country":"US",
    "sg:address":"1215 Cordova St",
    "sg:city":"Billings",
    "sg:classifiers":[
        {
            "category":"Wholesale",
            "subcategory":"Machinery & Supplies",
            "type":"Manufacturing & Wholesale Goods"
        }
    ],
    "sg:phone":"+1 406 245 3008",
    "sg:postcode":"59101",
    "sg:province":"MT",
    "sg:tags":[
        "water",
        "irrigation",
        "well",
        "pipe",
        "equipment",
        "pump"
    ],
    "wof:name":"2 M Company Inc",
    "wof:placetype":"venue"
},
  "geometry": {"coordinates":[-108.549505,45.745239],"type":"Point"}
}