{
  "type": "Feature",
  "properties": {
    "addr:full":"502 N Main St Darby MT 59829",
    "addr:housenumber":"502",
    "addr:postcode":"59829",
    "addr:street":"N Main St",
    "iso:country":"US",
    "sg:address":"502 N Main St",
    "sg:city":"Darby",
    "sg:classifiers":[
        {
            "category":"Manufacturing",
            "subcategory":"Buildings",
            "type":"Manufacturing & Wholesale Goods"
        }
    ],
    "sg:phone":"+1 406 821 3756",
    "sg:postcode":"59829",
    "sg:province":"MT",
    "sg:tags":[
        "home",
        "log",
        "cabin"
    ],
    "wof:name":"Masterlog Homes Inc",
    "wof:placetype":"venue"
},
  "geometry": {"coordinates":[-114.177874,46.023449],"type":"Point"}
}