{
  "type": "Feature",
  "properties": {
    "iso:country":"US",
    "sg:address":"13515 Cottonwood Canyon Rd",
    "sg:city":"Bozeman",
    "sg:classifiers":[
        {
            "category":"Travel",
            "subcategory":"Travel Agent",
            "type":"Entertainment"
        }
    ],
    "sg:phone":"+1 406 763 3131",
    "sg:postcode":"59718",
    "sg:province":"MT",
    "sg:tags":[
        "agency"
    ],
    "wof:name":"Rocky Mountain Travel Co",
    "wof:placetype":"venue"
},
  "geometry": {"coordinates":[-111.10814499999999,45.553932],"type":"Point"}
}