{
  "type": "Feature",
  "properties": {
    "addr:full":"2825 Stockyard Rd Missoula MT 59808",
    "addr:housenumber":"2825",
    "addr:postcode":"59808",
    "addr:street":"Stockyard Rd",
    "iso:country":"US",
    "sg:address":"2825 Stockyard Rd",
    "sg:city":"Missoula",
    "sg:classifiers":[
        {
            "category":"Retail",
            "subcategory":"Veterinary Services",
            "type":"Services"
        }
    ],
    "sg:phone":"+1 406 541 8181",
    "sg:postcode":"59808",
    "sg:province":"MT",
    "sg:tags":[
        "clinic",
        "hospital",
        "specialty"
    ],
    "wof:name":"Grant Creek Veterinary Services",
    "wof:placetype":"venue"
},
  "geometry": {"coordinates":[-114.034205,46.900983],"type":"Point"}
}