{
  "type": "Feature",
  "properties": {
    "iso:country":"US",
    "sg:address":"3900 Jupiter Ln",
    "sg:city":"Butte",
    "sg:classifiers":[
        {
            "category":"Professional",
            "type":"Services"
        }
    ],
    "sg:phone":"+1 406 494 3974",
    "sg:postcode":"59701",
    "sg:province":"MT",
    "sg:tags":[
        "establishment"
    ],
    "wof:name":"Sisters Of Charity-Levenworth",
    "wof:placetype":"venue"
},
  "geometry": {"coordinates":[-112.490872,45.964696],"type":"Point"}
}