{
  "type": "Feature",
  "properties": {
    "iso:country":"US",
    "sg:address":"1848 Mountain Meadow Ln",
    "sg:city":"Victor",
    "sg:classifiers":[
        {
            "category":"Travel",
            "subcategory":"Hotels & Motels",
            "type":"Entertainment"
        }
    ],
    "sg:phone":"+1 406 642 9647",
    "sg:postcode":"59875",
    "sg:province":"MT",
    "sg:tags":[
        "breakfast",
        "inn",
        "bed"
    ],
    "wof:name":"Medicine Wheel Ranch",
    "wof:placetype":"venue"
},
  "geometry": {"coordinates":[-114.21854399999999,46.386137],"type":"Point"}
}