{
  "type": "Feature",
  "properties": {
    "iso:country":"US",
    "sg:address":"6334 Dawn Dr",
    "sg:city":"Belgrade",
    "sg:classifiers":[
        {
            "category":"Manufacturing",
            "subcategory":"Metals",
            "type":"Manufacturing & Wholesale Goods"
        }
    ],
    "sg:phone":"+1 406 388 1387",
    "sg:postcode":"59714",
    "sg:province":"MT",
    "sg:tags":[
        "sporting",
        "mfg",
        "forging"
    ],
    "wof:name":"Montana Hrsman Sddle Bldg Schl",
    "wof:placetype":"venue"
},
  "geometry": {"coordinates":[-111.216534,45.875979],"type":"Point"}
}