{
  "type": "Feature",
  "properties": {
    "iso:country":"US",
    "sg:address":"1150 Westwood Dr",
    "sg:city":"Hamilton",
    "sg:classifiers":[
        {
            "category":"Health Services",
            "subcategory":"Doctor",
            "type":"Services"
        }
    ],
    "sg:phone":"+1 406 363 2391",
    "sg:postcode":"59840",
    "sg:province":"MT",
    "sg:tags":[
        "physician",
        "surgeon"
    ],
    "wof:name":"James H Chandler Orthopedics",
    "wof:placetype":"venue"
},
  "geometry": {"coordinates":[-114.17003800000001,46.247241],"type":"Point"}
}