{
  "type": "Feature",
  "properties": {
    "iso:country":"US",
    "sg:address":"83 E Park St",
    "sg:city":"Butte",
    "sg:classifiers":[
        {
            "category":"Shopping",
            "subcategory":"Used Merchandise",
            "type":"Retail Goods"
        }
    ],
    "sg:phone":"+1 406 723 2176",
    "sg:postcode":"59701",
    "sg:province":"MT",
    "wof:name":"Rediscoveries Vintage Clothing",
    "wof:placetype":"venue"
},
  "geometry": {"coordinates":[-112.535203,46.012886],"type":"Point"}
}