{
  "type": "Feature",
  "properties": {
    "iso:country":"US",
    "sg:address":"2915 Country Club Ave",
    "sg:city":"Helena",
    "sg:classifiers":[
        {
            "category":"Organizations",
            "subcategory":"Membership Organization",
            "type":"Services"
        }
    ],
    "sg:phone":"+1 406 442 2521",
    "sg:postcode":"59602",
    "sg:province":"MT",
    "sg:tags":[
        "pottery",
        "mfg",
        "ceramic",
        "class",
        "clay"
    ],
    "wof:name":"Archie Bray Foundation",
    "wof:placetype":"venue"
},
  "geometry": {"coordinates":[-112.083502,46.616967],"type":"Point"}
}