{
  "type": "Feature",
  "properties": {
    "addr:city":"Helena",
    "addr:full":"2915 Country Club Avenue Helena, Mt 59602",
    "addr:house_number":"2915",
    "addr:housenumber":"2915",
    "addr:phone":"+1 406-443-3502",
    "addr:postcode":"59602",
    "addr:road":"Country Club Avenue",
    "addr:state":"MT",
    "addr:street":"Country Club Ave",
    "iso:country":"US",
    "sg:address":"2915 Country Club Ave",
    "sg:city":"Helena",
    "sg:classifiers":[
        {
            "category":"Organizations",
            "subcategory":"Membership Organization",
            "type":"Services"
        }
    ],
    "sg:phone":"+1 406 442 2521",
    "sg:postcode":"59602",
    "sg:province":"MT",
    "sg:tags":[
        "pottery",
        "mfg",
        "ceramic",
        "class",
        "clay"
    ],
    "wof:airports":[
        102532633
    ],
    "wof:name":"Archie Bray Foundation For The Ceramic Arts",
    "wof:placetype":"venue"
},
  "geometry": {"coordinates":[-112.08235999999999,46.61538],"type":"Point"}
}