{
  "type": "Feature",
  "properties": {
    "addr:full":"398 Amdahl Ln Kalispell MT 59901",
    "addr:housenumber":"398",
    "addr:postcode":"59901",
    "addr:street":"Amdahl Ln",
    "iso:country":"US",
    "sg:address":"398 Amdahl Ln",
    "sg:city":"Kalispell",
    "sg:classifiers":[
        {
            "category":"Home & Garden",
            "subcategory":"Building Materials",
            "type":"Retail Goods"
        }
    ],
    "sg:phone":"+1 406 257 2343",
    "sg:postcode":"59901",
    "sg:province":"MT",
    "wof:name":"Wagoners Sand and Gravel",
    "wof:placetype":"venue"
},
  "geometry": {"coordinates":[-114.22329999999999,48.218702],"type":"Point"}
}