{
  "type": "Feature",
  "properties": {
    "addr:full":"815 Miles Ave Billings MT 59101",
    "addr:housenumber":"815",
    "addr:postcode":"59101",
    "addr:street":"Miles Ave",
    "iso:country":"US",
    "sg:address":"815 Miles Ave",
    "sg:city":"Billings",
    "sg:classifiers":[
        {
            "category":"Building & Trades",
            "subcategory":"Construction",
            "type":"Services"
        }
    ],
    "sg:phone":"+1 406 259 5227",
    "sg:postcode":"59101",
    "sg:province":"MT",
    "sg:tags":[
        "contractor"
    ],
    "wof:name":"Heafner Construction",
    "wof:placetype":"venue"
},
  "geometry": {"coordinates":[-108.538093,45.774162],"type":"Point"}
}