{
  "type": "Feature",
  "properties": {
    "iso:country":"US",
    "sg:address":"504 3rd Ave E",
    "sg:city":"Polson",
    "sg:classifiers":[
        {
            "category":"Social Services",
            "type":"Services"
        }
    ],
    "sg:phone":"+1 406 883 4735",
    "sg:postcode":"59860",
    "sg:province":"MT",
    "wof:name":"Senior Citizens Center",
    "wof:placetype":"venue"
},
  "geometry": {"coordinates":[-114.156233,47.693272],"type":"Point"}
}