{
  "type": "Feature",
  "properties": {
    "iso:country":"US",
    "sg:address":"1501 Holmes Ave",
    "sg:city":"Butte",
    "sg:classifiers":[
        {
            "category":"Health Services",
            "subcategory":"Doctor",
            "type":"Services"
        }
    ],
    "sg:phone":"+1 406 494 5033",
    "sg:postcode":"59701",
    "sg:province":"MT",
    "wof:name":"Mike Bartoletti DDS",
    "wof:placetype":"venue"
},
  "geometry": {"coordinates":[-112.516555,45.974951],"type":"Point"}
}