{
  "type": "Feature",
  "properties": {
    "iso:country":"US",
    "sg:address":"2070 Overland Ave",
    "sg:city":"Billings",
    "sg:classifiers":[
        {
            "category":"Professional",
            "subcategory":"Accounting & Tax Preparation",
            "type":"Services"
        }
    ],
    "sg:phone":"+1 406 656 1250",
    "sg:postcode":"59102",
    "sg:province":"MT",
    "sg:tags":[
        "bookkeeping",
        "general"
    ],
    "sg:website":"www.bookends-mt.com",
    "wof:name":"Bookends Inc",
    "wof:placetype":"venue"
},
  "geometry": {"coordinates":[-108.567231,45.752814],"type":"Point"}
}