{
  "type": "Feature",
  "properties": {
    "iso:country":"US",
    "sg:address":"825 S Moorehead Ave",
    "sg:city":"Miles City",
    "sg:classifiers":[
        {
            "category":"Organizations",
            "subcategory":"Religious Organization",
            "type":"Services"
        }
    ],
    "sg:phone":"+1 406 232 0386",
    "sg:postcode":"59301",
    "sg:province":"MT",
    "wof:name":"LDS Church",
    "wof:placetype":"venue"
},
  "geometry": {"coordinates":[-105.825261,46.400768],"type":"Point"}
}