{
  "type": "Feature",
  "properties": {
    "iso:country":"US",
    "sg:address":"2825 Fort Missoula Rd",
    "sg:city":"Missoula",
    "sg:classifiers":[
        {
            "category":"Health Services",
            "subcategory":"Doctor",
            "type":"Services"
        }
    ],
    "sg:phone":"+1 406 728 4920",
    "sg:postcode":"59804",
    "sg:province":"MT",
    "sg:tags":[
        "obstetrician",
        "gynecologist"
    ],
    "wof:name":"Kristin A Rauch MD",
    "wof:placetype":"venue"
},
  "geometry": {"coordinates":[-114.045896,46.846034],"type":"Point"}
}