{
  "type": "Feature",
  "properties": {
    "iso:country":"US",
    "sg:address":"1535 Industrial Ave",
    "sg:city":"Billings",
    "sg:classifiers":[
        {
            "category":"Wholesale",
            "subcategory":"Sporting Goods",
            "type":"Manufacturing & Wholesale Goods"
        }
    ],
    "sg:phone":"+1 406 252 2109",
    "sg:postcode":"59101",
    "sg:province":"MT",
    "wof:name":"Rocky Mountain Warehouse",
    "wof:placetype":"venue"
},
  "geometry": {"coordinates":[-108.555761,45.766123],"type":"Point"}
}