{
  "type": "Feature",
  "properties": {
    "addr:full":"211 Main St Sunburst MT 59482",
    "addr:housenumber":"211",
    "addr:postcode":"59482",
    "addr:street":"Main St",
    "iso:country":"US",
    "sg:address":"211 Main St",
    "sg:city":"Sunburst",
    "sg:classifiers":[
        {
            "category":"Home & Garden",
            "subcategory":"Garden Supply",
            "type":"Retail Goods"
        }
    ],
    "sg:phone":"+1 406 937 7500",
    "sg:postcode":"59482",
    "sg:province":"MT",
    "sg:tags":[
        "engine"
    ],
    "wof:name":"HCP Enterprises",
    "wof:placetype":"venue"
},
  "geometry": {"coordinates":[-111.912756,48.883902],"type":"Point"}
}