{
  "type": "Feature",
  "properties": {
    "addr:full":"113 E Main St Laurel MT 59044",
    "addr:housenumber":"113",
    "addr:postcode":"59044",
    "addr:street":"E Main St",
    "iso:country":"US",
    "sg:address":"113 E Main St",
    "sg:city":"Laurel",
    "sg:classifiers":[
        {
            "category":"Building & Trades",
            "subcategory":"Construction",
            "type":"Services"
        }
    ],
    "sg:phone":"+1 406 628 8535",
    "sg:postcode":"59044",
    "sg:province":"MT",
    "sg:tags":[
        "home",
        "general"
    ],
    "wof:name":"Graber & Sons Construction",
    "wof:placetype":"venue"
},
  "geometry": {"coordinates":[-108.77010199999999,45.669528],"type":"Point"}
}