{
  "type": "Feature",
  "properties": {
    "addr:full":"112 Jubilee Ct Kalispell MT 59901",
    "addr:housenumber":"112",
    "addr:postcode":"59901",
    "addr:street":"Jubilee Ct",
    "iso:country":"US",
    "sg:address":"112 Jubilee Ct",
    "sg:city":"Kalispell",
    "sg:classifiers":[
        {
            "category":"Professional",
            "subcategory":"Business Services",
            "type":"Services"
        }
    ],
    "sg:phone":"+1 406 257 3076",
    "sg:postcode":"59901",
    "sg:province":"MT",
    "wof:name":"Fit By Design",
    "wof:placetype":"venue"
},
  "geometry": {"coordinates":[-114.33366700000001,48.206782],"type":"Point"}
}