{
  "type": "Feature",
  "properties": {
    "iso:country":"US",
    "sg:address":"20900 Frontage Rd",
    "sg:city":"Belgrade",
    "sg:classifiers":[
        {
            "category":"Manufacturing",
            "subcategory":"Metals",
            "type":"Manufacturing & Wholesale Goods"
        }
    ],
    "sg:phone":"+1 406 388 1185",
    "sg:postcode":"59714",
    "sg:province":"MT",
    "sg:tags":[
        "copper",
        "foundry"
    ],
    "wof:name":"Art Castings of Montana",
    "wof:placetype":"venue"
},
  "geometry": {"coordinates":[-111.16533200000001,45.769978],"type":"Point"}
}