{
  "type": "Feature",
  "properties": {
    "iso:country":"US",
    "sg:address":"13 N 23rd St",
    "sg:city":"Billings",
    "sg:classifiers":[
        {
            "category":"Professional",
            "subcategory":"Business Services",
            "type":"Services"
        }
    ],
    "sg:phone":"+1 406 896 6205",
    "sg:postcode":"59101",
    "sg:province":"MT",
    "sg:tags":[
        "interior",
        "consultant",
        "design",
        "decorator"
    ],
    "wof:name":"CTA Interior Design",
    "wof:placetype":"venue"
},
  "geometry": {"coordinates":[-108.49952,45.785014],"type":"Point"}
}