{
  "type": "Feature",
  "properties": {
    "iso:country":"US",
    "sg:address":"350 Louisiana Ave",
    "sg:city":"Libby",
    "sg:classifiers":[
        {
            "category":"Health Services",
            "subcategory":"Doctor",
            "type":"Services"
        }
    ],
    "sg:phone":"+1 406 293 8756",
    "sg:postcode":"59923",
    "sg:province":"MT",
    "sg:tags":[
        "medical"
    ],
    "wof:name":"Prompt Care",
    "wof:placetype":"venue"
},
  "geometry": {"coordinates":[-115.54872,48.391767],"type":"Point"}
}