{
  "type": "Feature",
  "properties": {
    "iso:country":"US",
    "sg:address":"2780 US Hwy 2 E",
    "sg:city":"Kalispell",
    "sg:classifiers":[
        {
            "category":"Freight",
            "type":"Transportation"
        }
    ],
    "sg:phone":"+1 406 752 3640",
    "sg:postcode":"59901",
    "sg:province":"MT",
    "sg:tags":[
        "hauling",
        "trucking"
    ],
    "wof:name":"John Jump Trucking Inc",
    "wof:placetype":"venue"
},
  "geometry": {"coordinates":[-114.27464,48.252104],"type":"Point"}
}