{
  "type": "Feature",
  "properties": {
    "iso:country":"US",
    "sg:address":"1115 4th Ave N",
    "sg:city":"Billings",
    "sg:classifiers":[
        {
            "category":"Home & Garden",
            "subcategory":"Building Materials",
            "type":"Retail Goods"
        }
    ],
    "sg:phone":"+1 406 252 5621",
    "sg:postcode":"59101",
    "sg:province":"MT",
    "sg:tags":[
        "plate",
        "window",
        "construction",
        "g",
        "glass"
    ],
    "wof:name":"Yellowstone Glass Co",
    "wof:placetype":"venue"
},
  "geometry": {"coordinates":[-108.488519,45.794262],"type":"Point"}
}