{
  "type": "Feature",
  "properties": {
    "addr:full":"1811 Harve Ave Missoula MT 59801",
    "addr:housenumber":"1811",
    "addr:postcode":"59801",
    "addr:street":"Harve Ave",
    "iso:country":"US",
    "sg:address":"1811 Harve Ave",
    "sg:city":"Missoula",
    "sg:classifiers":[
        {
            "category":"Professional",
            "subcategory":"Secretarial Services",
            "type":"Services"
        }
    ],
    "sg:phone":"+1 406 728 1765",
    "sg:postcode":"59801",
    "sg:province":"MT",
    "sg:tags":[
        "transcription"
    ],
    "wof:name":"Carousel Transcription",
    "wof:placetype":"venue"
},
  "geometry": {"coordinates":[-114.026149,46.842471],"type":"Point"}
}