{
  "type": "Feature",
  "properties": {
    "iso:country":"US",
    "sg:address":"401 Main St",
    "sg:city":"Anaconda",
    "sg:classifiers":[
        {
            "category":"Education",
            "subcategory":"Library",
            "type":"Public Place"
        }
    ],
    "sg:phone":"+1 406 563 6932",
    "sg:postcode":"59711",
    "sg:province":"MT",
    "wof:name":"Hearst Free Library",
    "wof:placetype":"venue"
},
  "geometry": {"coordinates":[-112.953687,46.127318],"type":"Point"}
}