{
  "type": "Feature",
  "properties": {
    "iso:country":"US",
    "sg:address":"2501 Harrison Ave",
    "sg:city":"Butte",
    "sg:classifiers":[
        {
            "category":"Personal",
            "subcategory":"Beauty Salon",
            "type":"Services"
        }
    ],
    "sg:phone":"+1 406 782 3918",
    "sg:postcode":"59701",
    "sg:province":"MT",
    "wof:name":"New Attitudes Salon",
    "wof:placetype":"venue"
},
  "geometry": {"coordinates":[-112.509142,45.988955],"type":"Point"}
}