{
  "type": "Feature",
  "properties": {
    "iso:country":"US",
    "sg:address":"73 Bluebird Dr",
    "sg:city":"Cascade",
    "sg:classifiers":[
        {
            "category":"Building & Trades",
            "subcategory":"Construction",
            "type":"Services"
        }
    ],
    "sg:phone":"+1 406 761 1715",
    "sg:postcode":"59421",
    "sg:province":"MT",
    "sg:tags":[
        "water",
        "well",
        "drilling",
        "pl"
    ],
    "wof:name":"Eco-Lindsay Water",
    "wof:placetype":"venue"
},
  "geometry": {"coordinates":[-111.895053,47.131498],"type":"Point"}
}