{
  "type": "Feature",
  "properties": {
    "addr:full":"2205 1st Ave N Billings MT 59101",
    "addr:housenumber":"2205",
    "addr:postcode":"59101",
    "addr:street":"1St Ave N",
    "iso:country":"US",
    "sg:address":"2205 1st Ave N",
    "sg:city":"Billings",
    "sg:classifiers":[
        {
            "category":"Manufacturing",
            "subcategory":"Apparel",
            "type":"Manufacturing & Wholesale Goods"
        }
    ],
    "sg:phone":"+1 406 248 7688",
    "sg:postcode":"59101",
    "sg:province":"MT",
    "sg:tags":[
        "hat",
        "clean",
        "mfg"
    ],
    "wof:name":"Rands",
    "wof:placetype":"venue"
},
  "geometry": {"coordinates":[-108.499037,45.785473],"type":"Point"}
}