{
  "type": "Feature",
  "properties": {
    "iso:country":"US",
    "sg:address":"2214 Amherst Ave",
    "sg:city":"Butte",
    "sg:classifiers":[
        {
            "category":"Food & Beverages",
            "subcategory":"Specialty",
            "type":"Retail Goods"
        },
        {
            "category":"Restaurant",
            "type":"Food & Drink"
        }
    ],
    "sg:phone":"+1 406 494 7924",
    "sg:postcode":"59701",
    "sg:province":"MT",
    "sg:tags":[
        "tea",
        "coffee",
        "eating"
    ],
    "wof:name":"Wetona's Coffee House & Deli",
    "wof:placetype":"venue"
},
  "geometry": {"coordinates":[-112.504441,45.98633],"type":"Point"}
}