{
  "type": "Feature",
  "properties": {
    "addr:full":"407 E Main St Laurel MT 59044",
    "addr:housenumber":"407",
    "addr:postcode":"59044",
    "addr:street":"E Main St",
    "iso:country":"US",
    "sg:address":"407 E Main St",
    "sg:city":"Laurel",
    "sg:classifiers":[
        {
            "category":"Banks & Credit Unions",
            "subcategory":"Bank",
            "type":"Services"
        }
    ],
    "sg:phone":"+1 406 628 4166",
    "sg:postcode":"59044",
    "sg:province":"MT",
    "sg:tags":[
        "loan"
    ],
    "wof:name":"Title Cash",
    "wof:placetype":"venue"
},
  "geometry": {"coordinates":[-108.76584,45.670576],"type":"Point"}
}