{
  "type": "Feature",
  "properties": {
    "iso:country":"US",
    "sg:address":"10 7th St S",
    "sg:city":"Great Falls",
    "sg:classifiers":[
        {
            "category":"Personal",
            "subcategory":"Beauty Salon",
            "type":"Services"
        }
    ],
    "sg:phone":"+1 406 453 8990",
    "sg:postcode":"59401",
    "sg:province":"MT",
    "wof:name":"Kings & Queens Beauty",
    "wof:placetype":"venue"
},
  "geometry": {"coordinates":[-111.29565599999999,47.504297],"type":"Point"}
}