{
  "type": "Feature",
  "properties": {
    "addr:full":"85 N Broadway Belgrade MT 59714",
    "addr:housenumber":"85",
    "addr:postcode":"59714",
    "addr:street":"N Broadway",
    "iso:country":"US",
    "sg:address":"85 N Broadway",
    "sg:city":"Belgrade",
    "sg:classifiers":[
        {
            "category":"Restaurant",
            "type":"Food & Drink"
        }
    ],
    "sg:phone":"+1 406 388 2875",
    "sg:postcode":"59714",
    "sg:province":"MT",
    "sg:tags":[
        "eating"
    ],
    "wof:name":"Duck-In Cafe",
    "wof:placetype":"venue"
},
  "geometry": {"coordinates":[-111.176579,45.776794],"type":"Point"}
}