{
  "type": "Feature",
  "properties": {
    "iso:country":"US",
    "sg:address":"6901 Goldenstein Ln",
    "sg:city":"Bozeman",
    "sg:classifiers":[
        {
            "category":"Social Services",
            "type":"Services"
        }
    ],
    "sg:phone":"+1 406 586 1781",
    "sg:postcode":"59715",
    "sg:province":"MT",
    "wof:name":"Eagle Mount",
    "wof:placetype":"venue"
},
  "geometry": {"coordinates":[-111.06265399999999,45.634595],"type":"Point"}
}