{
  "type": "Feature",
  "properties": {
    "iso:country":"US",
    "sg:address":"124 S Main St",
    "sg:city":"Butte",
    "sg:classifiers":[
        {
            "category":"Food & Beverages",
            "subcategory":"Specialty",
            "type":"Retail Goods"
        }
    ],
    "sg:phone":"+1 406 723 7600",
    "sg:postcode":"59701",
    "sg:province":"MT",
    "sg:tags":[
        "bars",
        "espresso"
    ],
    "wof:name":"Venus Rising Espresso House",
    "wof:placetype":"venue"
},
  "geometry": {"coordinates":[-112.535377,46.011891],"type":"Point"}
}