{
  "type": "Feature",
  "properties": {
    "iso:country":"US",
    "sg:address":"33 Pinecrest Rd",
    "sg:city":"Clancy",
    "sg:classifiers":[
        {
            "category":"Professional",
            "subcategory":"Business Services",
            "type":"Services"
        }
    ],
    "sg:phone":"+1 406 933 8641",
    "sg:postcode":"59634",
    "sg:province":"MT",
    "wof:name":"G M Enterprise",
    "wof:placetype":"venue"
},
  "geometry": {"coordinates":[-111.949463,46.495934],"type":"Point"}
}