{
  "type": "Feature",
  "properties": {
    "iso:country":"US",
    "sg:address":"651 E Broadway St",
    "sg:city":"Missoula",
    "sg:classifiers":[
        {
            "category":"Restaurant",
            "type":"Food & Drink"
        }
    ],
    "sg:menulink":"http://www.allmenus.com/mt/missoula/205134-taco-bell/menu/",
    "sg:phone":"+1 406 728 6667",
    "sg:postcode":"59802",
    "sg:province":"MT",
    "sg:tags":[
        "american",
        "mexican"
    ],
    "wof:name":"Taco Bell",
    "wof:placetype":"venue"
},
  "geometry": {"coordinates":[-113.98612900000001,46.86946],"type":"Point"}
}