{
  "type": "Feature",
  "properties": {
    "iso:country":"US",
    "sg:address":"36 Riverside Dr",
    "sg:city":"Bozeman",
    "sg:classifiers":[
        {
            "category":"Recreation",
            "type":"Entertainment"
        }
    ],
    "sg:phone":"+1 406 587 5039",
    "sg:postcode":"59715",
    "sg:province":"MT",
    "wof:name":"M B T Enterprises LLC",
    "wof:placetype":"venue"
},
  "geometry": {"coordinates":[-111.065207,45.730546],"type":"Point"}
}