{
  "type": "Feature",
  "properties": {
    "iso:country":"US",
    "sg:address":"126 Main St",
    "sg:city":"Roundup",
    "sg:classifiers":[
        {
            "category":"Shopping",
            "subcategory":"Books",
            "type":"Retail Goods"
        }
    ],
    "sg:phone":"+1 406 323 2077",
    "sg:postcode":"59072",
    "sg:province":"MT",
    "wof:name":"Book Mark",
    "wof:placetype":"venue"
},
  "geometry": {"coordinates":[-108.541887,46.442074],"type":"Point"}
}