{
  "type": "Feature",
  "properties": {
    "iso:country":"US",
    "sg:address":"620 Clark Ave",
    "sg:city":"Billings",
    "sg:classifiers":[
        {
            "category":"Farming",
            "subcategory":"Livestock Farm",
            "type":"Manufacturing & Wholesale Goods"
        }
    ],
    "sg:phone":"+1 406 652 8717",
    "sg:postcode":"59101",
    "sg:province":"MT",
    "wof:name":"Mitch Heiken Farm",
    "wof:placetype":"venue"
},
  "geometry": {"coordinates":[-108.532517,45.779985],"type":"Point"}
}