{
  "type": "Feature",
  "properties": {
    "iso:country":"US",
    "sg:address":"48 Jackson Ln",
    "sg:city":"Harrison",
    "sg:classifiers":[
        {
            "category":"Retail",
            "subcategory":"Animal Services",
            "type":"Services"
        }
    ],
    "sg:phone":"+1 406 685 3352",
    "sg:postcode":"59714",
    "sg:province":"MT",
    "sg:tags":[
        "breeder",
        "horse"
    ],
    "wof:name":"Jackson Morgan Horse Ranch",
    "wof:placetype":"venue"
},
  "geometry": {"coordinates":[-111.209999,45.773584],"type":"Point"}
}